public final class aa
  implements Runnable
{
  private final bb a;
  private final String b;
  private final bb c;
  private final String d;
  private final String e;
  
  private aa(String paramString1, String paramString2, String paramString3, bb parambb1, bb parambb2)
  {
    this.d = paramString1;
    this.b = paramString2;
    this.e = paramString3;
    this.c = parambb1;
    this.a = parambb2;
  }
  
  /* Error */
  public final void run()
  {
    // Byte code:
    //   0: aload_0
    //   1: getfield 23	aa:d	Ljava/lang/String;
    //   4: invokestatic 30	gi:e	(Ljava/lang/String;)Ljavax/microedition/io/Connection;
    //   7: checkcast 18	javax/wireless/messaging/MessageConnection
    //   10: dup
    //   11: astore_1
    //   12: ldc 4
    //   14: invokeinterface 40 2 0
    //   19: checkcast 19	javax/wireless/messaging/TextMessage
    //   22: dup
    //   23: astore_2
    //   24: aload_0
    //   25: getfield 23	aa:d	Ljava/lang/String;
    //   28: invokeinterface 39 2 0
    //   33: aload_2
    //   34: aload_0
    //   35: getfield 21	aa:b	Ljava/lang/String;
    //   38: invokeinterface 42 2 0
    //   43: aload_1
    //   44: aload_2
    //   45: invokeinterface 41 2 0
    //   50: getstatic 25	java/lang/System:out	Ljava/io/PrintStream;
    //   53: new 14	java/lang/StringBuffer
    //   56: dup
    //   57: ldc 3
    //   59: invokespecial 34	java/lang/StringBuffer:<init>	(Ljava/lang/String;)V
    //   62: aload_0
    //   63: getfield 21	aa:b	Ljava/lang/String;
    //   66: invokevirtual 35	java/lang/StringBuffer:append	(Ljava/lang/String;)Ljava/lang/StringBuffer;
    //   69: ldc 2
    //   71: invokevirtual 35	java/lang/StringBuffer:append	(Ljava/lang/String;)Ljava/lang/StringBuffer;
    //   74: aload_0
    //   75: getfield 24	aa:e	Ljava/lang/String;
    //   78: invokevirtual 35	java/lang/StringBuffer:append	(Ljava/lang/String;)Ljava/lang/StringBuffer;
    //   81: invokevirtual 36	java/lang/StringBuffer:toString	()Ljava/lang/String;
    //   84: invokevirtual 31	java/io/PrintStream:println	(Ljava/lang/String;)V
    //   87: aload_0
    //   88: getfield 22	aa:c	Lbb;
    //   91: invokevirtual 28	bb:c	()V
    //   94: return
    //   95: ldc 1
    //   97: invokevirtual 33	java/lang/String:length	()I
    //   100: pop2
    //   101: aload_0
    //   102: getfield 20	aa:a	Lbb;
    //   105: invokevirtual 28	bb:c	()V
    //   108: return
    // Local variable table:
    //   start	length	slot	name	signature
    //   0	109	0	this	aa
    //   11	33	1	localMessageConnection	javax.wireless.messaging.MessageConnection
    //   23	22	2	localTextMessage	javax.wireless.messaging.TextMessage
    //   95	1	3	localException	Exception
    // Exception table:
    //   from	to	target	type
    //   0	94	95	java/lang/Exception
  }
  
  public static void a(String paramString1, String paramString2, bb parambb1, bb parambb2)
  {
    new Thread(new aa(paramString2, paramString1, paramString2, parambb1, parambb2)).start();
  }
  
  public static void a() {}
  
  static
  {
    cs.a(171);
    a();
  }
  
  public static void b() {}
}


/* Location:              C:\Users\Admin\OneDrive\Documents\NSOv2_test.jar!\aa.class
 * Java compiler version: 1 (45.3)
 * JD-Core Version:       0.7.1
 */