import javax.microedition.lcdui.Image;

public final class aw
  extends fa
  implements ay
{
  public static int a;
  public static int b;
  public static boolean c;
  public static boolean d;
  public static boolean e;
  public static int f;
  private static Image[] az;
  private cf ba = new cf();
  private static Image[] bb;
  public static int g;
  public static cv h;
  private static int bc;
  private boolean bd;
  public static boolean[] i;
  private int[] be;
  private static Image[][] bf;
  public static boolean j;
  public static Image k;
  private static int bg;
  public static long l;
  private int[] bh;
  private static int[] bi;
  public static boolean m;
  private static int bj;
  private static int[] bk;
  public static int n;
  public static int o;
  public static int p;
  private static long bl;
  public static int q;
  public static boolean r;
  public static boolean s;
  public static aw t;
  public static fj u;
  private static int bm;
  private static long bn;
  private static int[] bo;
  public static int v;
  public static boolean w;
  public static boolean x;
  public static boolean y;
  private static Image[] bp;
  public static j z;
  private int[] bq;
  private static Image br;
  public static Image[] aa;
  private static int bs;
  private static int bt;
  public static fd ab;
  private static int[] bu;
  public static int ac;
  private static boolean[] bv;
  private static boolean bw;
  public static fq[] ad;
  public static bp ae;
  public static eu af;
  public static boolean ag;
  public static boolean ah;
  public static f ai;
  public static boolean aj;
  public static boolean[] ak;
  public static int al;
  public static Image am;
  public static boolean an;
  private static Image bx;
  public static br ao;
  public static int ap;
  private static int by;
  public static int aq;
  private static int[] bz;
  private static Image ca;
  public static ca ar;
  public static boolean as;
  public static boolean at;
  private static Image[] cb;
  public static de au;
  private static Image[][] cc;
  private static int cd;
  public static int av;
  private static int[] ce;
  private static int[] cf;
  private static int cg;
  public static int aw;
  private static int ch;
  private static int[] ci;
  private static int cj;
  private static long ck;
  public static long ax;
  public static int ay;
  
  private static boolean d(int paramInt)
  {
    return paramInt >= 0;
  }
  
  public static boolean a(int paramInt1, int paramInt2)
  {
    if (e(ag)) {
      return cf[2];
    }
    if (i(bo[cf[2]], cf[11]))
    {
      "".length();
      if (-"  ".length() < 0) {
        break label79;
      }
      return (0x8D ^ 0x9A) & (0xB8 ^ 0xAF ^ 0xFFFFFFFF);
    }
    label79:
    int i1 = cf[0];
    if (k(bo[i1], cf[11])) {
      return cf[2];
    }
    bo[i1] = cf[2];
    bi[i1] = paramInt1;
    bu[i1] = paramInt2;
    return cf[0];
  }
  
  protected final void b(int paramInt1, int paramInt2)
  {
    y = cf[2];
    j = cf[0];
    f.b = cf[11];
    f = paramInt1;
    o = paramInt2;
  }
  
  private static boolean f(int paramInt1, int paramInt2)
  {
    return paramInt1 < paramInt2;
  }
  
  /* Error */
  public final void a()
  {
    // Byte code:
    //   0: getstatic 196	aw:p	I
    //   3: invokestatic 277	aw:f	(I)Z
    //   6: ifeq +73 -> 79
    //   9: invokestatic 412	java/lang/System:currentTimeMillis	()J
    //   12: dup2
    //   13: putstatic 143	aw:ax	J
    //   16: getstatic 192	aw:l	J
    //   19: lsub
    //   20: ldc2_w 90
    //   23: invokestatic 269	aw:b	(JJ)I
    //   26: invokestatic 273	aw:d	(I)Z
    //   29: ifeq +90 -> 119
    //   32: getstatic 196	aw:p	I
    //   35: getstatic 179	aw:cf	[I
    //   38: iconst_0
    //   39: iaload
    //   40: isub
    //   41: dup
    //   42: putstatic 196	aw:p	I
    //   45: invokestatic 284	aw:i	(I)Z
    //   48: ifeq +9 -> 57
    //   51: invokestatic 258	au:a	()Lau;
    //   54: invokevirtual 260	au:e	()V
    //   57: getstatic 143	aw:ax	J
    //   60: putstatic 192	aw:l	J
    //   63: ldc 7
    //   65: invokevirtual 406	java/lang/String:length	()I
    //   68: pop
    //   69: ldc 8
    //   71: invokevirtual 406	java/lang/String:length	()I
    //   74: ineg
    //   75: iflt +44 -> 119
    //   78: return
    //   79: invokestatic 258	au:a	()Lau;
    //   82: getfield 119	au:d	Z
    //   85: invokestatic 275	aw:e	(I)Z
    //   88: ifeq +31 -> 119
    //   91: invokestatic 412	java/lang/System:currentTimeMillis	()J
    //   94: invokestatic 258	au:a	()Lau;
    //   97: getfield 120	au:m	J
    //   100: lsub
    //   101: ldc2_w 94
    //   104: invokestatic 269	aw:b	(JJ)I
    //   107: invokestatic 277	aw:f	(I)Z
    //   110: ifeq +9 -> 119
    //   113: invokestatic 258	au:a	()Lau;
    //   116: invokevirtual 260	au:e	()V
    //   119: invokestatic 412	java/lang/System:currentTimeMillis	()J
    //   122: dup2
    //   123: lstore_1
    //   124: getstatic 184	aw:ck	J
    //   127: lsub
    //   128: ldc2_w 86
    //   131: invokestatic 269	aw:b	(JJ)I
    //   134: invokestatic 273	aw:d	(I)Z
    //   137: ifeq +44 -> 181
    //   140: getstatic 203	aw:w	Z
    //   143: invokestatic 284	aw:i	(I)Z
    //   146: ifeq +35 -> 181
    //   149: lload_1
    //   150: putstatic 184	aw:ck	J
    //   153: getstatic 179	aw:cf	[I
    //   156: iconst_0
    //   157: iaload
    //   158: putstatic 203	aw:w	Z
    //   161: ldc 7
    //   163: invokevirtual 406	java/lang/String:length	()I
    //   166: pop
    //   167: ldc 10
    //   169: invokevirtual 406	java/lang/String:length	()I
    //   172: ldc 10
    //   174: invokevirtual 406	java/lang/String:length	()I
    //   177: if_icmple +12 -> 189
    //   180: return
    //   181: getstatic 179	aw:cf	[I
    //   184: iconst_2
    //   185: iaload
    //   186: putstatic 203	aw:w	Z
    //   189: lload_1
    //   190: getstatic 158	aw:bl	J
    //   193: lsub
    //   194: ldc2_w 92
    //   197: invokestatic 269	aw:b	(JJ)I
    //   200: invokestatic 273	aw:d	(I)Z
    //   203: ifeq +35 -> 238
    //   206: getstatic 198	aw:r	Z
    //   209: invokestatic 284	aw:i	(I)Z
    //   212: ifeq +26 -> 238
    //   215: lload_1
    //   216: putstatic 158	aw:bl	J
    //   219: getstatic 179	aw:cf	[I
    //   222: iconst_0
    //   223: iaload
    //   224: putstatic 198	aw:r	Z
    //   227: ldc 7
    //   229: invokevirtual 406	java/lang/String:length	()I
    //   232: pop
    //   233: aconst_null
    //   234: ifnull +12 -> 246
    //   237: return
    //   238: getstatic 179	aw:cf	[I
    //   241: iconst_2
    //   242: iaload
    //   243: putstatic 198	aw:r	Z
    //   246: getstatic 121	aw:a	I
    //   249: invokestatic 277	aw:f	(I)Z
    //   252: ifeq +15 -> 267
    //   255: getstatic 121	aw:a	I
    //   258: getstatic 179	aw:cf	[I
    //   261: iconst_0
    //   262: iaload
    //   263: isub
    //   264: putstatic 121	aw:a	I
    //   267: getstatic 136	aw:ap	I
    //   270: getstatic 179	aw:cf	[I
    //   273: iconst_0
    //   274: iaload
    //   275: iadd
    //   276: dup
    //   277: putstatic 136	aw:ap	I
    //   280: getstatic 179	aw:cf	[I
    //   283: bipush 12
    //   285: iaload
    //   286: invokestatic 282	aw:h	(II)Z
    //   289: ifeq +11 -> 300
    //   292: getstatic 179	aw:cf	[I
    //   295: iconst_2
    //   296: iaload
    //   297: putstatic 136	aw:ap	I
    //   300: getstatic 130	aw:ai	Lf;
    //   303: invokestatic 270	aw:b	(Ljava/lang/Object;)Z
    //   306: ifeq +83 -> 389
    //   309: getstatic 201	aw:u	Lfj;
    //   312: invokestatic 270	aw:b	(Ljava/lang/Object;)Z
    //   315: ifeq +29 -> 344
    //   318: getstatic 201	aw:u	Lfj;
    //   321: invokevirtual 382	fj:b	()V
    //   324: ldc 7
    //   326: invokevirtual 406	java/lang/String:length	()I
    //   329: pop
    //   330: ldc 8
    //   332: invokevirtual 406	java/lang/String:length	()I
    //   335: ldc 8
    //   337: invokevirtual 406	java/lang/String:length	()I
    //   340: if_icmple +28 -> 368
    //   343: return
    //   344: getstatic 127	aw:af	Leu;
    //   347: getfield 236	eu:c	Z
    //   350: invokestatic 275	aw:e	(I)Z
    //   353: ifeq +15 -> 368
    //   356: getstatic 127	aw:af	Leu;
    //   359: invokevirtual 372	eu:c	()V
    //   362: getstatic 127	aw:af	Leu;
    //   365: invokevirtual 369	eu:a	()V
    //   368: getstatic 204	aw:x	Z
    //   371: invokestatic 284	aw:i	(I)Z
    //   374: ifeq +9 -> 383
    //   377: getstatic 130	aw:ai	Lf;
    //   380: invokevirtual 377	f:f	()V
    //   383: getstatic 130	aw:ai	Lf;
    //   386: invokevirtual 376	f:e	()V
    //   389: invokestatic 412	java/lang/System:currentTimeMillis	()J
    //   392: lstore_3
    //   393: getstatic 222	df:k	Z
    //   396: invokestatic 275	aw:e	(I)Z
    //   399: ifeq +64 -> 463
    //   402: lload_3
    //   403: getstatic 221	df:f	J
    //   406: invokestatic 269	aw:b	(JJ)I
    //   409: invokestatic 277	aw:f	(I)Z
    //   412: ifeq +51 -> 463
    //   415: getstatic 179	aw:cf	[I
    //   418: iconst_2
    //   419: iaload
    //   420: putstatic 222	df:k	Z
    //   423: getstatic 220	df:c	I
    //   426: invokestatic 277	aw:f	(I)Z
    //   429: ifeq +13 -> 442
    //   432: invokestatic 389	fn:j	()Lfn;
    //   435: getstatic 220	df:c	I
    //   438: aconst_null
    //   439: invokevirtual 383	fn:a	(ILjava/lang/Object;)V
    //   442: ldc 7
    //   444: invokevirtual 406	java/lang/String:length	()I
    //   447: pop
    //   448: bipush 54
    //   450: bipush 51
    //   452: ixor
    //   453: ifne +10 -> 463
    //   456: return
    //   457: ldc 7
    //   459: invokevirtual 406	java/lang/String:length	()I
    //   462: pop2
    //   463: invokestatic 361	dw:c	()V
    //   466: aload_0
    //   467: getfield 150	aw:bd	Z
    //   470: invokestatic 275	aw:e	(I)Z
    //   473: ifeq +7 -> 480
    //   476: aload_0
    //   477: invokevirtual 274	aw:e	()V
    //   480: getstatic 223	dm:b	Ldm;
    //   483: invokevirtual 395	gq:repaint	()V
    //   486: getstatic 223	dm:b	Ldm;
    //   489: invokevirtual 396	gq:serviceRepaints	()V
    //   492: return
    // Local variable table:
    //   start	length	slot	name	signature
    //   0	493	0	this	aw
    //   123	93	1	l1	long
    //   392	11	3	l2	long
    //   457	1	3	localException	Exception
    // Exception table:
    //   from	to	target	type
    //   423	442	457	java/lang/Exception
  }
  
  public static boolean a(int paramInt1, int paramInt2, int paramInt3, int paramInt4)
  {
    if (((!i(y)) || (e(j))) && (j(f, paramInt1)) && (g(f, paramInt1 + paramInt3)) && (j(o, paramInt2)) && (g(o, paramInt2 + paramInt4))) {
      return cf[0];
    }
    return cf[2];
  }
  
  public static void b()
  {
    int i1 = cf[2];
    while (f(i1, cf[26]))
    {
      i[i1] = cf[2];
      i1++;
      "".length();
      if (null != null) {}
    }
  }
  
  public static void c()
  {
    au.a().a(bv.a, bv.c);
  }
  
  public static void d()
  {
    if ((i(ag)) && (b(ca)))
    {
      int i1 = cf[2];
      while (f(i1, bz.length))
      {
        if (i(ap % (i1 + cf[1] << cf[8])))
        {
          bz[i1] += cf[0];
          if (h(bz[i1], fn.au + (cf.a(ca) >> cf[0]))) {
            bz[i1] = (-(cf.a(ca) >> cf[0]));
          }
        }
        i1++;
        "".length();
        if (-(0xBD ^ 0xC5 ^ 0x2F ^ 0x53) > 0) {}
      }
    }
  }
  
  /* Error */
  public final void e()
  {
    // Byte code:
    //   0: aload_0
    //   1: getstatic 179	aw:cf	[I
    //   4: iconst_2
    //   5: iaload
    //   6: putfield 150	aw:bd	Z
    //   9: getstatic 140	aw:au	Lde;
    //   12: invokevirtual 320	de:b	()V
    //   15: invokestatic 359	dt:o	()V
    //   18: invokestatic 390	fn:n	()V
    //   21: invokestatic 385	fn:ad	()V
    //   24: invokestatic 288	aw:p	()V
    //   27: invokestatic 362	dw:e	()V
    //   30: getstatic 179	aw:cf	[I
    //   33: iconst_0
    //   34: iaload
    //   35: invokestatic 384	fn:a	(Z)V
    //   38: getstatic 179	aw:cf	[I
    //   41: bipush 13
    //   43: iaload
    //   44: putstatic 240	fn:ad	I
    //   47: getstatic 233	et:f	B
    //   50: invokestatic 262	aw:a	(I)V
    //   53: getstatic 243	fn:ax	Lci;
    //   56: invokevirtual 313	ci:removeAllElements	()V
    //   59: getstatic 241	fn:am	Lci;
    //   62: invokevirtual 313	ci:removeAllElements	()V
    //   65: getstatic 244	fn:bz	Lci;
    //   68: invokevirtual 313	ci:removeAllElements	()V
    //   71: getstatic 245	fn:ca	Lci;
    //   74: invokevirtual 313	ci:removeAllElements	()V
    //   77: aconst_null
    //   78: putstatic 229	dt:c	Lea;
    //   81: return
    //   82: ldc 7
    //   84: invokevirtual 406	java/lang/String:length	()I
    //   87: pop2
    //   88: return
    // Local variable table:
    //   start	length	slot	name	signature
    //   0	89	0	this	aw
    //   82	1	1	localException	Exception
    // Exception table:
    //   from	to	target	type
    //   15	81	82	java/lang/Exception
  }
  
  /* Error */
  protected final void a(javax.microedition.lcdui.Graphics paramGraphics)
  {
    // Byte code:
    //   0: aload_0
    //   1: getfield 147	aw:ba	Lcf;
    //   4: aload_1
    //   5: putfield 216	cf:d	Ljavax/microedition/lcdui/Graphics;
    //   8: getstatic 130	aw:ai	Lf;
    //   11: invokestatic 270	aw:b	(Ljava/lang/Object;)Z
    //   14: ifeq +45 -> 59
    //   17: getstatic 204	aw:x	Z
    //   20: invokestatic 284	aw:i	(I)Z
    //   23: ifeq +36 -> 59
    //   26: getstatic 130	aw:ai	Lf;
    //   29: aload_0
    //   30: getfield 147	aw:ba	Lcf;
    //   33: invokevirtual 374	f:a	(Lcf;)V
    //   36: aload_0
    //   37: getfield 147	aw:ba	Lcf;
    //   40: getstatic 179	aw:cf	[I
    //   43: iconst_2
    //   44: iaload
    //   45: getstatic 179	aw:cf	[I
    //   48: iconst_2
    //   49: iaload
    //   50: getstatic 146	aw:b	I
    //   53: getstatic 141	aw:av	I
    //   56: invokevirtual 309	cf:c	(IIII)V
    //   59: aload_0
    //   60: getfield 147	aw:ba	Lcf;
    //   63: aload_0
    //   64: getfield 147	aw:ba	Lcf;
    //   67: invokevirtual 305	cf:b	()I
    //   70: ineg
    //   71: aload_0
    //   72: getfield 147	aw:ba	Lcf;
    //   75: invokevirtual 308	cf:c	()I
    //   78: ineg
    //   79: invokevirtual 301	cf:a	(II)V
    //   82: aload_0
    //   83: getfield 147	aw:ba	Lcf;
    //   86: getstatic 179	aw:cf	[I
    //   89: iconst_2
    //   90: iaload
    //   91: getstatic 179	aw:cf	[I
    //   94: iconst_2
    //   95: iaload
    //   96: getstatic 146	aw:b	I
    //   99: getstatic 141	aw:av	I
    //   102: invokevirtual 309	cf:c	(IIII)V
    //   105: aload_0
    //   106: getfield 147	aw:ba	Lcf;
    //   109: invokestatic 360	dw:a	(Lcf;)V
    //   112: getstatic 201	aw:u	Lfj;
    //   115: invokestatic 270	aw:b	(Ljava/lang/Object;)Z
    //   118: ifeq +33 -> 151
    //   121: getstatic 201	aw:u	Lfj;
    //   124: aload_0
    //   125: getfield 147	aw:ba	Lcf;
    //   128: invokevirtual 381	fj:a	(Lcf;)V
    //   131: ldc 7
    //   133: invokevirtual 406	java/lang/String:length	()I
    //   136: pop
    //   137: ldc 8
    //   139: invokevirtual 406	java/lang/String:length	()I
    //   142: ldc 8
    //   144: invokevirtual 406	java/lang/String:length	()I
    //   147: if_icmpeq +26 -> 173
    //   150: return
    //   151: getstatic 127	aw:af	Leu;
    //   154: getfield 236	eu:c	Z
    //   157: invokestatic 275	aw:e	(I)Z
    //   160: ifeq +13 -> 173
    //   163: getstatic 127	aw:af	Leu;
    //   166: aload_0
    //   167: getfield 147	aw:ba	Lcf;
    //   170: invokevirtual 370	eu:a	(Lcf;)V
    //   173: aload_0
    //   174: getfield 147	aw:ba	Lcf;
    //   177: invokestatic 388	fn:b	(Lcf;)V
    //   180: getstatic 196	aw:p	I
    //   183: invokestatic 277	aw:f	(I)Z
    //   186: ifeq +113 -> 299
    //   189: getstatic 179	aw:cf	[I
    //   192: bipush 45
    //   194: iaload
    //   195: getstatic 141	aw:av	I
    //   198: getstatic 179	aw:cf	[I
    //   201: bipush 46
    //   203: iaload
    //   204: isub
    //   205: getstatic 146	aw:b	I
    //   208: getstatic 179	aw:cf	[I
    //   211: bipush 34
    //   213: iaload
    //   214: isub
    //   215: getstatic 179	aw:cf	[I
    //   218: bipush 47
    //   220: iaload
    //   221: aload_0
    //   222: getfield 147	aw:ba	Lcf;
    //   225: invokestatic 366	en:d	(IIIILcf;)V
    //   228: getstatic 137	aw:aq	I
    //   231: getstatic 141	aw:av	I
    //   234: getstatic 179	aw:cf	[I
    //   237: bipush 48
    //   239: iaload
    //   240: isub
    //   241: aload_0
    //   242: getfield 147	aw:ba	Lcf;
    //   245: invokestatic 263	aw:a	(IILcf;)V
    //   248: getstatic 207	ax:c	Lax;
    //   251: aload_0
    //   252: getfield 147	aw:ba	Lcf;
    //   255: new 82	java/lang/StringBuffer
    //   258: dup
    //   259: ldc 25
    //   261: invokespecial 408	java/lang/StringBuffer:<init>	(Ljava/lang/String;)V
    //   264: getstatic 196	aw:p	I
    //   267: invokevirtual 409	java/lang/StringBuffer:append	(I)Ljava/lang/StringBuffer;
    //   270: ldc 29
    //   272: invokevirtual 410	java/lang/StringBuffer:append	(Ljava/lang/String;)Ljava/lang/StringBuffer;
    //   275: invokevirtual 411	java/lang/StringBuffer:toString	()Ljava/lang/String;
    //   278: getstatic 137	aw:aq	I
    //   281: getstatic 141	aw:av	I
    //   284: getstatic 179	aw:cf	[I
    //   287: bipush 49
    //   289: iaload
    //   290: isub
    //   291: getstatic 179	aw:cf	[I
    //   294: iconst_1
    //   295: iaload
    //   296: invokevirtual 291	ax:a	(Lcf;Ljava/lang/String;III)V
    //   299: return
    //   300: ldc 7
    //   302: invokevirtual 406	java/lang/String:length	()I
    //   305: pop2
    //   306: return
    // Local variable table:
    //   start	length	slot	name	signature
    //   0	307	0	this	aw
    //   0	307	1	paramGraphics	javax.microedition.lcdui.Graphics
    //   300	1	2	localException	Exception
    // Exception table:
    //   from	to	target	type
    //   8	299	300	java/lang/Exception
  }
  
  private static boolean e(int paramInt)
  {
    return paramInt != 0;
  }
  
  private static boolean f(int paramInt)
  {
    return paramInt > 0;
  }
  
  public static void a(String paramString)
  {
    h.a(paramString, null, new bb(an.nd, t, cf[51], null), null);
    u = h;
  }
  
  protected final void c(int paramInt1, int paramInt2)
  {
    if ((!f(bc.a(paramInt1 - v), cf[14])) || (j(bc.a(paramInt2 - n), cf[14]))) {
      as = cf[2];
    }
    f = paramInt1;
    o = paramInt2;
    if (h(cd = cd + cf[0], cf[8])) {
      cd = cf[2];
    }
    ad[cd] = new fq(paramInt1, paramInt2);
  }
  
  private static boolean a(Object paramObject)
  {
    return paramObject == null;
  }
  
  public final void a(String paramString1, String paramString2, short paramShort, String paramString3, String paramString4)
  {
    ci localci;
    (localci = new ci()).addElement(new Short(paramShort));
    localci.addElement(paramString3);
    h.a(paramString4, new bb(paramString1, this, cf[53], localci), null, new bb(paramString2, this, cf[51], null));
    u = h;
  }
  
  public static void a(String paramString, int paramInt1, Object paramObject1, int paramInt2, Object paramObject2)
  {
    h.a(paramString, new bb(an.nt, t, paramInt1, paramObject1), new bb("", t, paramInt1, paramObject1), new bb(an.mm, t, paramInt2, paramObject2));
    u = h;
  }
  
  private static boolean g(int paramInt1, int paramInt2)
  {
    return paramInt1 <= paramInt2;
  }
  
  public static void f()
  {
    cb = null;
    ca = null;
    br = null;
  }
  
  /* Error */
  public static void a(int paramInt)
  {
    // Byte code:
    //   0: getstatic 179	aw:cf	[I
    //   3: iconst_2
    //   4: iaload
    //   5: istore_1
    //   6: getstatic 179	aw:cf	[I
    //   9: iconst_2
    //   10: iaload
    //   11: istore_2
    //   12: getstatic 179	aw:cf	[I
    //   15: iconst_2
    //   16: iaload
    //   17: istore_3
    //   18: iload_0
    //   19: putstatic 197	aw:q	I
    //   22: iload_0
    //   23: tableswitch	default:+1092->1115, 2:+73->96, 3:+146->169, 4:+224->247, 5:+260->283, 6:+331->354, 7:+360->383, 8:+443->466, 9:+520->543, 10:+556->579, 11:+685->708, 12:+758->781, 13:+836->859, 14:+906->929, 15:+988->1011, 16:+1077->1100
    //   96: getstatic 179	aw:cf	[I
    //   99: bipush 9
    //   101: iaload
    //   102: newarray <illegal type>
    //   104: dup
    //   105: getstatic 179	aw:cf	[I
    //   108: iconst_2
    //   109: iaload
    //   110: getstatic 179	aw:cf	[I
    //   113: iconst_0
    //   114: iaload
    //   115: iastore
    //   116: dup
    //   117: getstatic 179	aw:cf	[I
    //   120: iconst_0
    //   121: iaload
    //   122: getstatic 179	aw:cf	[I
    //   125: iconst_1
    //   126: iaload
    //   127: iastore
    //   128: dup
    //   129: getstatic 179	aw:cf	[I
    //   132: iconst_1
    //   133: iaload
    //   134: getstatic 179	aw:cf	[I
    //   137: bipush 8
    //   139: iaload
    //   140: iastore
    //   141: dup
    //   142: getstatic 179	aw:cf	[I
    //   145: bipush 8
    //   147: iaload
    //   148: getstatic 179	aw:cf	[I
    //   151: bipush 9
    //   153: iaload
    //   154: iastore
    //   155: putstatic 182	aw:ci	[I
    //   158: ldc 7
    //   160: invokevirtual 406	java/lang/String:length	()I
    //   163: pop
    //   164: aconst_null
    //   165: ifnull +1027 -> 1192
    //   168: return
    //   169: getstatic 179	aw:cf	[I
    //   172: bipush 9
    //   174: iaload
    //   175: newarray <illegal type>
    //   177: dup
    //   178: getstatic 179	aw:cf	[I
    //   181: iconst_2
    //   182: iaload
    //   183: getstatic 179	aw:cf	[I
    //   186: iconst_0
    //   187: iaload
    //   188: iastore
    //   189: dup
    //   190: getstatic 179	aw:cf	[I
    //   193: iconst_0
    //   194: iaload
    //   195: getstatic 179	aw:cf	[I
    //   198: iconst_1
    //   199: iaload
    //   200: iastore
    //   201: dup
    //   202: getstatic 179	aw:cf	[I
    //   205: iconst_1
    //   206: iaload
    //   207: getstatic 179	aw:cf	[I
    //   210: bipush 8
    //   212: iaload
    //   213: iastore
    //   214: dup
    //   215: getstatic 179	aw:cf	[I
    //   218: bipush 8
    //   220: iaload
    //   221: getstatic 179	aw:cf	[I
    //   224: bipush 9
    //   226: iaload
    //   227: iastore
    //   228: putstatic 182	aw:ci	[I
    //   231: ldc 7
    //   233: invokevirtual 406	java/lang/String:length	()I
    //   236: pop
    //   237: ldc 10
    //   239: invokevirtual 406	java/lang/String:length	()I
    //   242: ineg
    //   243: ifle +949 -> 1192
    //   246: return
    //   247: getstatic 179	aw:cf	[I
    //   250: bipush 33
    //   252: iaload
    //   253: istore_1
    //   254: getstatic 179	aw:cf	[I
    //   257: bipush 20
    //   259: iaload
    //   260: istore_2
    //   261: ldc 7
    //   263: invokevirtual 406	java/lang/String:length	()I
    //   266: pop
    //   267: ldc 8
    //   269: invokevirtual 406	java/lang/String:length	()I
    //   272: sipush 178
    //   275: sipush 182
    //   278: ixor
    //   279: if_icmplt +851 -> 1130
    //   282: return
    //   283: getstatic 179	aw:cf	[I
    //   286: bipush 9
    //   288: iaload
    //   289: newarray <illegal type>
    //   291: dup
    //   292: getstatic 179	aw:cf	[I
    //   295: iconst_2
    //   296: iaload
    //   297: getstatic 179	aw:cf	[I
    //   300: iconst_0
    //   301: iaload
    //   302: iastore
    //   303: dup
    //   304: getstatic 179	aw:cf	[I
    //   307: iconst_0
    //   308: iaload
    //   309: getstatic 179	aw:cf	[I
    //   312: iconst_0
    //   313: iaload
    //   314: iastore
    //   315: dup
    //   316: getstatic 179	aw:cf	[I
    //   319: iconst_1
    //   320: iaload
    //   321: getstatic 179	aw:cf	[I
    //   324: iconst_0
    //   325: iaload
    //   326: iastore
    //   327: dup
    //   328: getstatic 179	aw:cf	[I
    //   331: bipush 8
    //   333: iaload
    //   334: getstatic 179	aw:cf	[I
    //   337: iconst_0
    //   338: iaload
    //   339: iastore
    //   340: putstatic 182	aw:ci	[I
    //   343: ldc 7
    //   345: invokevirtual 406	java/lang/String:length	()I
    //   348: pop
    //   349: aconst_null
    //   350: ifnull +842 -> 1192
    //   353: return
    //   354: getstatic 179	aw:cf	[I
    //   357: bipush 24
    //   359: iaload
    //   360: istore_1
    //   361: ldc 7
    //   363: invokevirtual 406	java/lang/String:length	()I
    //   366: pop
    //   367: bipush 48
    //   369: bipush 52
    //   371: ixor
    //   372: sipush 190
    //   375: sipush 186
    //   378: ixor
    //   379: if_icmple +751 -> 1130
    //   382: return
    //   383: getstatic 179	aw:cf	[I
    //   386: bipush 9
    //   388: iaload
    //   389: newarray <illegal type>
    //   391: dup
    //   392: getstatic 179	aw:cf	[I
    //   395: iconst_2
    //   396: iaload
    //   397: getstatic 179	aw:cf	[I
    //   400: iconst_0
    //   401: iaload
    //   402: iastore
    //   403: dup
    //   404: getstatic 179	aw:cf	[I
    //   407: iconst_0
    //   408: iaload
    //   409: getstatic 179	aw:cf	[I
    //   412: iconst_1
    //   413: iaload
    //   414: iastore
    //   415: dup
    //   416: getstatic 179	aw:cf	[I
    //   419: iconst_1
    //   420: iaload
    //   421: getstatic 179	aw:cf	[I
    //   424: bipush 8
    //   426: iaload
    //   427: iastore
    //   428: dup
    //   429: getstatic 179	aw:cf	[I
    //   432: bipush 8
    //   434: iaload
    //   435: getstatic 179	aw:cf	[I
    //   438: bipush 9
    //   440: iaload
    //   441: iastore
    //   442: putstatic 182	aw:ci	[I
    //   445: ldc 7
    //   447: invokevirtual 406	java/lang/String:length	()I
    //   450: pop
    //   451: ldc 8
    //   453: invokevirtual 406	java/lang/String:length	()I
    //   456: ineg
    //   457: ldc 8
    //   459: invokevirtual 406	java/lang/String:length	()I
    //   462: if_icmplt +730 -> 1192
    //   465: return
    //   466: getstatic 179	aw:cf	[I
    //   469: bipush 9
    //   471: iaload
    //   472: newarray <illegal type>
    //   474: dup
    //   475: getstatic 179	aw:cf	[I
    //   478: iconst_2
    //   479: iaload
    //   480: getstatic 179	aw:cf	[I
    //   483: iconst_0
    //   484: iaload
    //   485: iastore
    //   486: dup
    //   487: getstatic 179	aw:cf	[I
    //   490: iconst_0
    //   491: iaload
    //   492: getstatic 179	aw:cf	[I
    //   495: iconst_1
    //   496: iaload
    //   497: iastore
    //   498: dup
    //   499: getstatic 179	aw:cf	[I
    //   502: iconst_1
    //   503: iaload
    //   504: getstatic 179	aw:cf	[I
    //   507: bipush 8
    //   509: iaload
    //   510: iastore
    //   511: dup
    //   512: getstatic 179	aw:cf	[I
    //   515: bipush 8
    //   517: iaload
    //   518: getstatic 179	aw:cf	[I
    //   521: bipush 9
    //   523: iaload
    //   524: iastore
    //   525: putstatic 182	aw:ci	[I
    //   528: ldc 7
    //   530: invokevirtual 406	java/lang/String:length	()I
    //   533: pop
    //   534: ldc 9
    //   536: invokevirtual 406	java/lang/String:length	()I
    //   539: ifne +653 -> 1192
    //   542: return
    //   543: getstatic 179	aw:cf	[I
    //   546: bipush 21
    //   548: iaload
    //   549: istore_1
    //   550: getstatic 179	aw:cf	[I
    //   553: bipush 14
    //   555: iaload
    //   556: istore_2
    //   557: getstatic 179	aw:cf	[I
    //   560: bipush 20
    //   562: iaload
    //   563: istore_3
    //   564: ldc 7
    //   566: invokevirtual 406	java/lang/String:length	()I
    //   569: pop
    //   570: bipush 14
    //   572: bipush 11
    //   574: ixor
    //   575: ifne +555 -> 1130
    //   578: return
    //   579: getstatic 179	aw:cf	[I
    //   582: bipush 9
    //   584: iaload
    //   585: newarray <illegal type>
    //   587: dup
    //   588: getstatic 179	aw:cf	[I
    //   591: iconst_2
    //   592: iaload
    //   593: getstatic 179	aw:cf	[I
    //   596: iconst_0
    //   597: iaload
    //   598: iastore
    //   599: dup
    //   600: getstatic 179	aw:cf	[I
    //   603: iconst_0
    //   604: iaload
    //   605: getstatic 179	aw:cf	[I
    //   608: iconst_0
    //   609: iaload
    //   610: iastore
    //   611: dup
    //   612: getstatic 179	aw:cf	[I
    //   615: iconst_1
    //   616: iaload
    //   617: getstatic 179	aw:cf	[I
    //   620: iconst_0
    //   621: iaload
    //   622: iastore
    //   623: dup
    //   624: getstatic 179	aw:cf	[I
    //   627: bipush 8
    //   629: iaload
    //   630: getstatic 179	aw:cf	[I
    //   633: iconst_0
    //   634: iaload
    //   635: iastore
    //   636: putstatic 182	aw:ci	[I
    //   639: ldc 7
    //   641: invokevirtual 406	java/lang/String:length	()I
    //   644: pop
    //   645: bipush 90
    //   647: bipush 52
    //   649: iadd
    //   650: bipush 97
    //   652: isub
    //   653: bipush 118
    //   655: iadd
    //   656: bipush 56
    //   658: bipush 101
    //   660: iadd
    //   661: sipush 128
    //   664: isub
    //   665: sipush 161
    //   668: iadd
    //   669: ixor
    //   670: bipush 13
    //   672: bipush 7
    //   674: iadd
    //   675: bipush -102
    //   677: isub
    //   678: bipush 53
    //   680: iadd
    //   681: sipush 162
    //   684: bipush 63
    //   686: iadd
    //   687: sipush 184
    //   690: isub
    //   691: sipush 137
    //   694: iadd
    //   695: ixor
    //   696: ldc 8
    //   698: invokevirtual 406	java/lang/String:length	()I
    //   701: ineg
    //   702: ixor
    //   703: iand
    //   704: ifeq +488 -> 1192
    //   707: return
    //   708: getstatic 179	aw:cf	[I
    //   711: bipush 9
    //   713: iaload
    //   714: newarray <illegal type>
    //   716: dup
    //   717: getstatic 179	aw:cf	[I
    //   720: iconst_2
    //   721: iaload
    //   722: getstatic 179	aw:cf	[I
    //   725: iconst_0
    //   726: iaload
    //   727: iastore
    //   728: dup
    //   729: getstatic 179	aw:cf	[I
    //   732: iconst_0
    //   733: iaload
    //   734: getstatic 179	aw:cf	[I
    //   737: iconst_1
    //   738: iaload
    //   739: iastore
    //   740: dup
    //   741: getstatic 179	aw:cf	[I
    //   744: iconst_1
    //   745: iaload
    //   746: getstatic 179	aw:cf	[I
    //   749: bipush 8
    //   751: iaload
    //   752: iastore
    //   753: dup
    //   754: getstatic 179	aw:cf	[I
    //   757: bipush 8
    //   759: iaload
    //   760: getstatic 179	aw:cf	[I
    //   763: bipush 9
    //   765: iaload
    //   766: iastore
    //   767: putstatic 182	aw:ci	[I
    //   770: ldc 7
    //   772: invokevirtual 406	java/lang/String:length	()I
    //   775: pop
    //   776: aconst_null
    //   777: ifnull +415 -> 1192
    //   780: return
    //   781: getstatic 179	aw:cf	[I
    //   784: bipush 9
    //   786: iaload
    //   787: newarray <illegal type>
    //   789: dup
    //   790: getstatic 179	aw:cf	[I
    //   793: iconst_2
    //   794: iaload
    //   795: getstatic 179	aw:cf	[I
    //   798: iconst_0
    //   799: iaload
    //   800: iastore
    //   801: dup
    //   802: getstatic 179	aw:cf	[I
    //   805: iconst_0
    //   806: iaload
    //   807: getstatic 179	aw:cf	[I
    //   810: iconst_1
    //   811: iaload
    //   812: iastore
    //   813: dup
    //   814: getstatic 179	aw:cf	[I
    //   817: iconst_1
    //   818: iaload
    //   819: getstatic 179	aw:cf	[I
    //   822: bipush 8
    //   824: iaload
    //   825: iastore
    //   826: dup
    //   827: getstatic 179	aw:cf	[I
    //   830: bipush 8
    //   832: iaload
    //   833: getstatic 179	aw:cf	[I
    //   836: bipush 9
    //   838: iaload
    //   839: iastore
    //   840: putstatic 182	aw:ci	[I
    //   843: ldc 7
    //   845: invokevirtual 406	java/lang/String:length	()I
    //   848: pop
    //   849: ldc 9
    //   851: invokevirtual 406	java/lang/String:length	()I
    //   854: ineg
    //   855: iflt +337 -> 1192
    //   858: return
    //   859: getstatic 179	aw:cf	[I
    //   862: bipush 34
    //   864: iaload
    //   865: istore_1
    //   866: ldc 7
    //   868: invokevirtual 406	java/lang/String:length	()I
    //   871: pop
    //   872: sipush 161
    //   875: sipush 151
    //   878: ixor
    //   879: bipush 109
    //   881: iconst_5
    //   882: ixor
    //   883: ixor
    //   884: sipush 164
    //   887: sipush 203
    //   890: iadd
    //   891: sipush 287
    //   894: isub
    //   895: sipush 130
    //   898: iadd
    //   899: sipush 137
    //   902: bipush 54
    //   904: iadd
    //   905: bipush 127
    //   907: isub
    //   908: bipush 76
    //   910: iadd
    //   911: ixor
    //   912: ldc 8
    //   914: invokevirtual 406	java/lang/String:length	()I
    //   917: ineg
    //   918: ixor
    //   919: iand
    //   920: ldc 9
    //   922: invokevirtual 406	java/lang/String:length	()I
    //   925: if_icmplt +205 -> 1130
    //   928: return
    //   929: getstatic 179	aw:cf	[I
    //   932: bipush 9
    //   934: iaload
    //   935: newarray <illegal type>
    //   937: dup
    //   938: getstatic 179	aw:cf	[I
    //   941: iconst_2
    //   942: iaload
    //   943: getstatic 179	aw:cf	[I
    //   946: iconst_0
    //   947: iaload
    //   948: iastore
    //   949: dup
    //   950: getstatic 179	aw:cf	[I
    //   953: iconst_0
    //   954: iaload
    //   955: getstatic 179	aw:cf	[I
    //   958: iconst_1
    //   959: iaload
    //   960: iastore
    //   961: dup
    //   962: getstatic 179	aw:cf	[I
    //   965: iconst_1
    //   966: iaload
    //   967: getstatic 179	aw:cf	[I
    //   970: bipush 8
    //   972: iaload
    //   973: iastore
    //   974: dup
    //   975: getstatic 179	aw:cf	[I
    //   978: bipush 8
    //   980: iaload
    //   981: getstatic 179	aw:cf	[I
    //   984: bipush 9
    //   986: iaload
    //   987: iastore
    //   988: putstatic 182	aw:ci	[I
    //   991: ldc 7
    //   993: invokevirtual 406	java/lang/String:length	()I
    //   996: pop
    //   997: ldc 8
    //   999: invokevirtual 406	java/lang/String:length	()I
    //   1002: ldc 10
    //   1004: invokevirtual 406	java/lang/String:length	()I
    //   1007: if_icmplt +185 -> 1192
    //   1010: return
    //   1011: getstatic 179	aw:cf	[I
    //   1014: bipush 9
    //   1016: iaload
    //   1017: newarray <illegal type>
    //   1019: dup
    //   1020: getstatic 179	aw:cf	[I
    //   1023: iconst_2
    //   1024: iaload
    //   1025: getstatic 179	aw:cf	[I
    //   1028: iconst_0
    //   1029: iaload
    //   1030: iastore
    //   1031: dup
    //   1032: getstatic 179	aw:cf	[I
    //   1035: iconst_0
    //   1036: iaload
    //   1037: getstatic 179	aw:cf	[I
    //   1040: iconst_1
    //   1041: iaload
    //   1042: iastore
    //   1043: dup
    //   1044: getstatic 179	aw:cf	[I
    //   1047: iconst_1
    //   1048: iaload
    //   1049: getstatic 179	aw:cf	[I
    //   1052: bipush 8
    //   1054: iaload
    //   1055: iastore
    //   1056: dup
    //   1057: getstatic 179	aw:cf	[I
    //   1060: bipush 8
    //   1062: iaload
    //   1063: getstatic 179	aw:cf	[I
    //   1066: bipush 9
    //   1068: iaload
    //   1069: iastore
    //   1070: putstatic 182	aw:ci	[I
    //   1073: ldc 7
    //   1075: invokevirtual 406	java/lang/String:length	()I
    //   1078: pop
    //   1079: iconst_2
    //   1080: bipush 120
    //   1082: ixor
    //   1083: sipush 252
    //   1086: sipush 130
    //   1089: ixor
    //   1090: ixor
    //   1091: ldc 8
    //   1093: invokevirtual 406	java/lang/String:length	()I
    //   1096: if_icmpne +96 -> 1192
    //   1099: return
    //   1100: ldc 7
    //   1102: invokevirtual 406	java/lang/String:length	()I
    //   1105: pop
    //   1106: bipush 77
    //   1108: bipush 72
    //   1110: ixor
    //   1111: ifgt +19 -> 1130
    //   1114: return
    //   1115: ldc 7
    //   1117: invokevirtual 406	java/lang/String:length	()I
    //   1120: pop
    //   1121: bipush 61
    //   1123: bipush 57
    //   1125: ixor
    //   1126: ifgt +66 -> 1192
    //   1129: return
    //   1130: getstatic 179	aw:cf	[I
    //   1133: bipush 9
    //   1135: iaload
    //   1136: newarray <illegal type>
    //   1138: dup
    //   1139: getstatic 179	aw:cf	[I
    //   1142: iconst_2
    //   1143: iaload
    //   1144: getstatic 179	aw:cf	[I
    //   1147: iconst_0
    //   1148: iaload
    //   1149: iastore
    //   1150: dup
    //   1151: getstatic 179	aw:cf	[I
    //   1154: iconst_0
    //   1155: iaload
    //   1156: getstatic 179	aw:cf	[I
    //   1159: iconst_1
    //   1160: iaload
    //   1161: iastore
    //   1162: dup
    //   1163: getstatic 179	aw:cf	[I
    //   1166: iconst_1
    //   1167: iaload
    //   1168: getstatic 179	aw:cf	[I
    //   1171: bipush 8
    //   1173: iaload
    //   1174: iastore
    //   1175: dup
    //   1176: getstatic 179	aw:cf	[I
    //   1179: bipush 8
    //   1181: iaload
    //   1182: getstatic 179	aw:cf	[I
    //   1185: bipush 9
    //   1187: iaload
    //   1188: iastore
    //   1189: putstatic 182	aw:ci	[I
    //   1192: getstatic 226	dr:i	[I
    //   1195: getstatic 197	aw:q	I
    //   1198: iaload
    //   1199: putstatic 180	aw:cg	I
    //   1202: getstatic 128	aw:ag	Z
    //   1205: invokestatic 284	aw:i	(I)Z
    //   1208: ifeq +653 -> 1861
    //   1211: getstatic 179	aw:cf	[I
    //   1214: bipush 9
    //   1216: iaload
    //   1217: anewarray 84	javax/microedition/lcdui/Image
    //   1220: putstatic 175	aw:cb	[Ljavax/microedition/lcdui/Image;
    //   1223: getstatic 179	aw:cf	[I
    //   1226: bipush 9
    //   1228: iaload
    //   1229: newarray <illegal type>
    //   1231: putstatic 157	aw:bk	[I
    //   1234: getstatic 179	aw:cf	[I
    //   1237: iconst_2
    //   1238: iaload
    //   1239: istore 4
    //   1241: iload 4
    //   1243: getstatic 179	aw:cf	[I
    //   1246: bipush 9
    //   1248: iaload
    //   1249: invokestatic 278	aw:f	(II)Z
    //   1252: ifeq +115 -> 1367
    //   1255: getstatic 225	dr:f	[[I
    //   1258: getstatic 197	aw:q	I
    //   1261: aaload
    //   1262: iload 4
    //   1264: iaload
    //   1265: getstatic 179	aw:cf	[I
    //   1268: bipush 11
    //   1270: iaload
    //   1271: invokestatic 287	aw:k	(II)Z
    //   1274: ifeq +26 -> 1300
    //   1277: getstatic 175	aw:cb	[Ljavax/microedition/lcdui/Image;
    //   1280: iload 4
    //   1282: getstatic 152	aw:bf	[[Ljavax/microedition/lcdui/Image;
    //   1285: iload 4
    //   1287: aaload
    //   1288: getstatic 225	dr:f	[[I
    //   1291: getstatic 197	aw:q	I
    //   1294: aaload
    //   1295: iload 4
    //   1297: iaload
    //   1298: aaload
    //   1299: aastore
    //   1300: ldc 7
    //   1302: invokevirtual 406	java/lang/String:length	()I
    //   1305: pop
    //   1306: aconst_null
    //   1307: ifnull +10 -> 1317
    //   1310: return
    //   1311: ldc 7
    //   1313: invokevirtual 406	java/lang/String:length	()I
    //   1316: pop2
    //   1317: getstatic 175	aw:cb	[Ljavax/microedition/lcdui/Image;
    //   1320: iload 4
    //   1322: aaload
    //   1323: invokestatic 270	aw:b	(Ljava/lang/Object;)Z
    //   1326: ifeq +18 -> 1344
    //   1329: getstatic 157	aw:bk	[I
    //   1332: iload 4
    //   1334: getstatic 175	aw:cb	[Ljavax/microedition/lcdui/Image;
    //   1337: iload 4
    //   1339: aaload
    //   1340: invokestatic 302	cf:a	(Ljavax/microedition/lcdui/Image;)I
    //   1343: iastore
    //   1344: iinc 4 1
    //   1347: ldc 7
    //   1349: invokevirtual 406	java/lang/String:length	()I
    //   1352: pop
    //   1353: ldc 10
    //   1355: invokevirtual 406	java/lang/String:length	()I
    //   1358: ldc 8
    //   1360: invokevirtual 406	java/lang/String:length	()I
    //   1363: if_icmpgt -122 -> 1241
    //   1366: return
    //   1367: getstatic 197	aw:q	I
    //   1370: getstatic 179	aw:cf	[I
    //   1373: bipush 14
    //   1375: iaload
    //   1376: invokestatic 285	aw:i	(II)Z
    //   1379: ifeq +95 -> 1474
    //   1382: getstatic 175	aw:cb	[Ljavax/microedition/lcdui/Image;
    //   1385: getstatic 179	aw:cf	[I
    //   1388: iconst_0
    //   1389: iaload
    //   1390: getstatic 152	aw:bf	[[Ljavax/microedition/lcdui/Image;
    //   1393: getstatic 179	aw:cf	[I
    //   1396: iconst_2
    //   1397: iaload
    //   1398: aaload
    //   1399: getstatic 179	aw:cf	[I
    //   1402: bipush 33
    //   1404: iaload
    //   1405: aaload
    //   1406: aastore
    //   1407: getstatic 175	aw:cb	[Ljavax/microedition/lcdui/Image;
    //   1410: getstatic 179	aw:cf	[I
    //   1413: iconst_1
    //   1414: iaload
    //   1415: getstatic 152	aw:bf	[[Ljavax/microedition/lcdui/Image;
    //   1418: getstatic 179	aw:cf	[I
    //   1421: iconst_2
    //   1422: iaload
    //   1423: aaload
    //   1424: getstatic 179	aw:cf	[I
    //   1427: bipush 33
    //   1429: iaload
    //   1430: aaload
    //   1431: aastore
    //   1432: getstatic 157	aw:bk	[I
    //   1435: getstatic 179	aw:cf	[I
    //   1438: iconst_0
    //   1439: iaload
    //   1440: getstatic 175	aw:cb	[Ljavax/microedition/lcdui/Image;
    //   1443: getstatic 179	aw:cf	[I
    //   1446: iconst_0
    //   1447: iaload
    //   1448: aaload
    //   1449: invokestatic 302	cf:a	(Ljavax/microedition/lcdui/Image;)I
    //   1452: iastore
    //   1453: getstatic 157	aw:bk	[I
    //   1456: getstatic 179	aw:cf	[I
    //   1459: iconst_1
    //   1460: iaload
    //   1461: getstatic 175	aw:cb	[Ljavax/microedition/lcdui/Image;
    //   1464: getstatic 179	aw:cf	[I
    //   1467: iconst_1
    //   1468: iaload
    //   1469: aaload
    //   1470: invokestatic 302	cf:a	(Ljavax/microedition/lcdui/Image;)I
    //   1473: iastore
    //   1474: getstatic 197	aw:q	I
    //   1477: getstatic 179	aw:cf	[I
    //   1480: bipush 24
    //   1482: iaload
    //   1483: invokestatic 285	aw:i	(II)Z
    //   1486: ifeq +53 -> 1539
    //   1489: getstatic 175	aw:cb	[Ljavax/microedition/lcdui/Image;
    //   1492: getstatic 179	aw:cf	[I
    //   1495: bipush 8
    //   1497: iaload
    //   1498: getstatic 152	aw:bf	[[Ljavax/microedition/lcdui/Image;
    //   1501: getstatic 179	aw:cf	[I
    //   1504: bipush 8
    //   1506: iaload
    //   1507: aaload
    //   1508: getstatic 179	aw:cf	[I
    //   1511: bipush 33
    //   1513: iaload
    //   1514: aaload
    //   1515: aastore
    //   1516: getstatic 157	aw:bk	[I
    //   1519: getstatic 179	aw:cf	[I
    //   1522: bipush 8
    //   1524: iaload
    //   1525: getstatic 175	aw:cb	[Ljavax/microedition/lcdui/Image;
    //   1528: getstatic 179	aw:cf	[I
    //   1531: bipush 8
    //   1533: iaload
    //   1534: aaload
    //   1535: invokestatic 302	cf:a	(Ljavax/microedition/lcdui/Image;)I
    //   1538: iastore
    //   1539: getstatic 197	aw:q	I
    //   1542: getstatic 179	aw:cf	[I
    //   1545: bipush 26
    //   1547: iaload
    //   1548: invokestatic 285	aw:i	(II)Z
    //   1551: ifeq +111 -> 1662
    //   1554: getstatic 199	aw:s	Z
    //   1557: invokestatic 275	aw:e	(I)Z
    //   1560: ifeq +59 -> 1619
    //   1563: getstatic 141	aw:av	I
    //   1566: getstatic 175	aw:cb	[Ljavax/microedition/lcdui/Image;
    //   1569: getstatic 179	aw:cf	[I
    //   1572: iconst_2
    //   1573: iaload
    //   1574: aaload
    //   1575: invokestatic 307	cf:b	(Ljavax/microedition/lcdui/Image;)I
    //   1578: isub
    //   1579: dup
    //   1580: putstatic 181	aw:ch	I
    //   1583: getstatic 175	aw:cb	[Ljavax/microedition/lcdui/Image;
    //   1586: getstatic 179	aw:cf	[I
    //   1589: iconst_0
    //   1590: iaload
    //   1591: aaload
    //   1592: invokestatic 307	cf:b	(Ljavax/microedition/lcdui/Image;)I
    //   1595: isub
    //   1596: putstatic 153	aw:bg	I
    //   1599: ldc 7
    //   1601: invokevirtual 406	java/lang/String:length	()I
    //   1604: pop
    //   1605: ldc 9
    //   1607: invokevirtual 406	java/lang/String:length	()I
    //   1610: ldc 8
    //   1612: invokevirtual 406	java/lang/String:length	()I
    //   1615: if_icmpge +47 -> 1662
    //   1618: return
    //   1619: getstatic 141	aw:av	I
    //   1622: getstatic 175	aw:cb	[Ljavax/microedition/lcdui/Image;
    //   1625: getstatic 179	aw:cf	[I
    //   1628: iconst_2
    //   1629: iaload
    //   1630: aaload
    //   1631: invokestatic 307	cf:b	(Ljavax/microedition/lcdui/Image;)I
    //   1634: isub
    //   1635: getstatic 179	aw:cf	[I
    //   1638: bipush 25
    //   1640: iaload
    //   1641: isub
    //   1642: dup
    //   1643: putstatic 181	aw:ch	I
    //   1646: getstatic 175	aw:cb	[Ljavax/microedition/lcdui/Image;
    //   1649: getstatic 179	aw:cf	[I
    //   1652: iconst_0
    //   1653: iaload
    //   1654: aaload
    //   1655: invokestatic 307	cf:b	(Ljavax/microedition/lcdui/Image;)I
    //   1658: isub
    //   1659: putstatic 153	aw:bg	I
    //   1662: getstatic 197	aw:q	I
    //   1665: getstatic 179	aw:cf	[I
    //   1668: bipush 6
    //   1670: iaload
    //   1671: invokestatic 285	aw:i	(II)Z
    //   1674: ifeq +55 -> 1729
    //   1677: getstatic 199	aw:s	Z
    //   1680: invokestatic 275	aw:e	(I)Z
    //   1683: ifeq +46 -> 1729
    //   1686: getstatic 141	aw:av	I
    //   1689: getstatic 175	aw:cb	[Ljavax/microedition/lcdui/Image;
    //   1692: getstatic 179	aw:cf	[I
    //   1695: iconst_2
    //   1696: iaload
    //   1697: aaload
    //   1698: invokestatic 307	cf:b	(Ljavax/microedition/lcdui/Image;)I
    //   1701: isub
    //   1702: dup
    //   1703: putstatic 181	aw:ch	I
    //   1706: getstatic 175	aw:cb	[Ljavax/microedition/lcdui/Image;
    //   1709: getstatic 179	aw:cf	[I
    //   1712: iconst_0
    //   1713: iaload
    //   1714: aaload
    //   1715: invokestatic 307	cf:b	(Ljavax/microedition/lcdui/Image;)I
    //   1718: isub
    //   1719: getstatic 179	aw:cf	[I
    //   1722: bipush 13
    //   1724: iaload
    //   1725: iadd
    //   1726: putstatic 153	aw:bg	I
    //   1729: getstatic 197	aw:q	I
    //   1732: getstatic 179	aw:cf	[I
    //   1735: bipush 21
    //   1737: iaload
    //   1738: invokestatic 285	aw:i	(II)Z
    //   1741: ifeq +120 -> 1861
    //   1744: getstatic 199	aw:s	Z
    //   1747: invokestatic 275	aw:e	(I)Z
    //   1750: ifeq +61 -> 1811
    //   1753: getstatic 141	aw:av	I
    //   1756: getstatic 175	aw:cb	[Ljavax/microedition/lcdui/Image;
    //   1759: getstatic 179	aw:cf	[I
    //   1762: iconst_2
    //   1763: iaload
    //   1764: aaload
    //   1765: invokestatic 307	cf:b	(Ljavax/microedition/lcdui/Image;)I
    //   1768: isub
    //   1769: dup
    //   1770: putstatic 181	aw:ch	I
    //   1773: getstatic 175	aw:cb	[Ljavax/microedition/lcdui/Image;
    //   1776: getstatic 179	aw:cf	[I
    //   1779: iconst_0
    //   1780: iaload
    //   1781: aaload
    //   1782: invokestatic 307	cf:b	(Ljavax/microedition/lcdui/Image;)I
    //   1785: isub
    //   1786: getstatic 179	aw:cf	[I
    //   1789: bipush 13
    //   1791: iaload
    //   1792: iadd
    //   1793: putstatic 153	aw:bg	I
    //   1796: ldc 7
    //   1798: invokevirtual 406	java/lang/String:length	()I
    //   1801: pop
    //   1802: ldc 8
    //   1804: invokevirtual 406	java/lang/String:length	()I
    //   1807: ifne +54 -> 1861
    //   1810: return
    //   1811: getstatic 141	aw:av	I
    //   1814: getstatic 175	aw:cb	[Ljavax/microedition/lcdui/Image;
    //   1817: getstatic 179	aw:cf	[I
    //   1820: iconst_2
    //   1821: iaload
    //   1822: aaload
    //   1823: invokestatic 307	cf:b	(Ljavax/microedition/lcdui/Image;)I
    //   1826: isub
    //   1827: getstatic 179	aw:cf	[I
    //   1830: bipush 35
    //   1832: iaload
    //   1833: isub
    //   1834: dup
    //   1835: putstatic 181	aw:ch	I
    //   1838: getstatic 175	aw:cb	[Ljavax/microedition/lcdui/Image;
    //   1841: getstatic 179	aw:cf	[I
    //   1844: iconst_0
    //   1845: iaload
    //   1846: aaload
    //   1847: invokestatic 307	cf:b	(Ljavax/microedition/lcdui/Image;)I
    //   1850: isub
    //   1851: getstatic 179	aw:cf	[I
    //   1854: bipush 13
    //   1856: iaload
    //   1857: iadd
    //   1858: putstatic 153	aw:bg	I
    //   1861: getstatic 197	aw:q	I
    //   1864: invokestatic 273	aw:d	(I)Z
    //   1867: ifeq +71 -> 1938
    //   1870: getstatic 197	aw:q	I
    //   1873: getstatic 179	aw:cf	[I
    //   1876: iconst_0
    //   1877: iaload
    //   1878: invokestatic 280	aw:g	(II)Z
    //   1881: ifeq +57 -> 1938
    //   1884: getstatic 162	aw:bp	[Ljavax/microedition/lcdui/Image;
    //   1887: getstatic 179	aw:cf	[I
    //   1890: iconst_2
    //   1891: iaload
    //   1892: aaload
    //   1893: putstatic 174	aw:ca	Ljavax/microedition/lcdui/Image;
    //   1896: getstatic 145	aw:az	[Ljavax/microedition/lcdui/Image;
    //   1899: getstatic 179	aw:cf	[I
    //   1902: iconst_2
    //   1903: iaload
    //   1904: aaload
    //   1905: putstatic 164	aw:br	Ljavax/microedition/lcdui/Image;
    //   1908: ldc 7
    //   1910: invokevirtual 406	java/lang/String:length	()I
    //   1913: pop
    //   1914: sipush 211
    //   1917: sipush 148
    //   1920: ixor
    //   1921: sipush 208
    //   1924: sipush 147
    //   1927: ixor
    //   1928: ixor
    //   1929: ldc 9
    //   1931: invokevirtual 406	java/lang/String:length	()I
    //   1934: if_icmpge +12 -> 1946
    //   1937: return
    //   1938: aconst_null
    //   1939: putstatic 174	aw:ca	Ljavax/microedition/lcdui/Image;
    //   1942: aconst_null
    //   1943: putstatic 164	aw:br	Ljavax/microedition/lcdui/Image;
    //   1946: getstatic 197	aw:q	I
    //   1949: getstatic 179	aw:cf	[I
    //   1952: iconst_1
    //   1953: iaload
    //   1954: invokestatic 285	aw:i	(II)Z
    //   1957: ifeq +27 -> 1984
    //   1960: getstatic 162	aw:bp	[Ljavax/microedition/lcdui/Image;
    //   1963: getstatic 179	aw:cf	[I
    //   1966: iconst_0
    //   1967: iaload
    //   1968: aaload
    //   1969: putstatic 174	aw:ca	Ljavax/microedition/lcdui/Image;
    //   1972: getstatic 145	aw:az	[Ljavax/microedition/lcdui/Image;
    //   1975: getstatic 179	aw:cf	[I
    //   1978: iconst_0
    //   1979: iaload
    //   1980: aaload
    //   1981: putstatic 164	aw:br	Ljavax/microedition/lcdui/Image;
    //   1984: getstatic 197	aw:q	I
    //   1987: getstatic 179	aw:cf	[I
    //   1990: bipush 15
    //   1992: iaload
    //   1993: invokestatic 287	aw:k	(II)Z
    //   1996: ifeq +33 -> 2029
    //   1999: getstatic 197	aw:q	I
    //   2002: getstatic 179	aw:cf	[I
    //   2005: bipush 23
    //   2007: iaload
    //   2008: invokestatic 287	aw:k	(II)Z
    //   2011: ifeq +18 -> 2029
    //   2014: getstatic 197	aw:q	I
    //   2017: getstatic 179	aw:cf	[I
    //   2020: bipush 24
    //   2022: iaload
    //   2023: invokestatic 285	aw:i	(II)Z
    //   2026: ifeq +45 -> 2071
    //   2029: getstatic 234	et:o	S
    //   2032: getstatic 179	aw:cf	[I
    //   2035: bipush 30
    //   2037: iaload
    //   2038: invokestatic 285	aw:i	(II)Z
    //   2041: ifeq +18 -> 2059
    //   2044: aconst_null
    //   2045: putstatic 174	aw:ca	Ljavax/microedition/lcdui/Image;
    //   2048: ldc 7
    //   2050: invokevirtual 406	java/lang/String:length	()I
    //   2053: pop
    //   2054: aconst_null
    //   2055: ifnull +16 -> 2071
    //   2058: return
    //   2059: getstatic 162	aw:bp	[Ljavax/microedition/lcdui/Image;
    //   2062: getstatic 179	aw:cf	[I
    //   2065: iconst_2
    //   2066: iaload
    //   2067: aaload
    //   2068: putstatic 174	aw:ca	Ljavax/microedition/lcdui/Image;
    //   2071: iload_0
    //   2072: getstatic 179	aw:cf	[I
    //   2075: bipush 31
    //   2077: iaload
    //   2078: invokestatic 287	aw:k	(II)Z
    //   2081: ifeq +16 -> 2097
    //   2084: iload_0
    //   2085: getstatic 179	aw:cf	[I
    //   2088: bipush 6
    //   2090: iaload
    //   2091: invokestatic 285	aw:i	(II)Z
    //   2094: ifeq +15 -> 2109
    //   2097: getstatic 162	aw:bp	[Ljavax/microedition/lcdui/Image;
    //   2100: getstatic 179	aw:cf	[I
    //   2103: iconst_1
    //   2104: iaload
    //   2105: aaload
    //   2106: putstatic 174	aw:ca	Ljavax/microedition/lcdui/Image;
    //   2109: ldc 7
    //   2111: invokevirtual 406	java/lang/String:length	()I
    //   2114: pop
    //   2115: sipush 147
    //   2118: sipush 165
    //   2121: ixor
    //   2122: bipush 21
    //   2124: bipush 39
    //   2126: ixor
    //   2127: ixor
    //   2128: bipush 75
    //   2130: iconst_1
    //   2131: iadd
    //   2132: bipush 56
    //   2134: isub
    //   2135: bipush 109
    //   2137: iadd
    //   2138: bipush 52
    //   2140: bipush 86
    //   2142: iadd
    //   2143: bipush 53
    //   2145: isub
    //   2146: bipush 48
    //   2148: iadd
    //   2149: ixor
    //   2150: if_icmpeq +10 -> 2160
    //   2153: return
    //   2154: ldc 7
    //   2156: invokevirtual 406	java/lang/String:length	()I
    //   2159: pop2
    //   2160: getstatic 179	aw:cf	[I
    //   2163: iconst_2
    //   2164: iaload
    //   2165: putstatic 169	aw:bw	Z
    //   2168: getstatic 128	aw:ag	Z
    //   2171: invokestatic 284	aw:i	(I)Z
    //   2174: ifeq +445 -> 2619
    //   2177: getstatic 179	aw:cf	[I
    //   2180: iconst_0
    //   2181: iaload
    //   2182: putstatic 169	aw:bw	Z
    //   2185: getstatic 175	aw:cb	[Ljavax/microedition/lcdui/Image;
    //   2188: getstatic 179	aw:cf	[I
    //   2191: iconst_2
    //   2192: iaload
    //   2193: aaload
    //   2194: invokestatic 270	aw:b	(Ljava/lang/Object;)Z
    //   2197: ifeq +85 -> 2282
    //   2200: getstatic 175	aw:cb	[Ljavax/microedition/lcdui/Image;
    //   2203: getstatic 179	aw:cf	[I
    //   2206: iconst_0
    //   2207: iaload
    //   2208: aaload
    //   2209: invokestatic 270	aw:b	(Ljava/lang/Object;)Z
    //   2212: ifeq +70 -> 2282
    //   2215: getstatic 175	aw:cb	[Ljavax/microedition/lcdui/Image;
    //   2218: getstatic 179	aw:cf	[I
    //   2221: iconst_1
    //   2222: iaload
    //   2223: aaload
    //   2224: invokestatic 270	aw:b	(Ljava/lang/Object;)Z
    //   2227: ifeq +55 -> 2282
    //   2230: getstatic 248	fn:et	I
    //   2233: getstatic 175	aw:cb	[Ljavax/microedition/lcdui/Image;
    //   2236: getstatic 179	aw:cf	[I
    //   2239: iconst_2
    //   2240: iaload
    //   2241: aaload
    //   2242: invokestatic 307	cf:b	(Ljavax/microedition/lcdui/Image;)I
    //   2245: getstatic 175	aw:cb	[Ljavax/microedition/lcdui/Image;
    //   2248: getstatic 179	aw:cf	[I
    //   2251: iconst_0
    //   2252: iaload
    //   2253: aaload
    //   2254: invokestatic 307	cf:b	(Ljavax/microedition/lcdui/Image;)I
    //   2257: iadd
    //   2258: getstatic 175	aw:cb	[Ljavax/microedition/lcdui/Image;
    //   2261: getstatic 179	aw:cf	[I
    //   2264: iconst_1
    //   2265: iaload
    //   2266: aaload
    //   2267: invokestatic 307	cf:b	(Ljavax/microedition/lcdui/Image;)I
    //   2270: iadd
    //   2271: isub
    //   2272: getstatic 179	aw:cf	[I
    //   2275: bipush 23
    //   2277: iaload
    //   2278: iadd
    //   2279: putstatic 171	aw:by	I
    //   2282: getstatic 175	aw:cb	[Ljavax/microedition/lcdui/Image;
    //   2285: getstatic 179	aw:cf	[I
    //   2288: iconst_2
    //   2289: iaload
    //   2290: aaload
    //   2291: invokestatic 270	aw:b	(Ljava/lang/Object;)Z
    //   2294: ifeq +22 -> 2316
    //   2297: getstatic 248	fn:et	I
    //   2300: getstatic 175	aw:cb	[Ljavax/microedition/lcdui/Image;
    //   2303: getstatic 179	aw:cf	[I
    //   2306: iconst_2
    //   2307: iaload
    //   2308: aaload
    //   2309: invokestatic 307	cf:b	(Ljavax/microedition/lcdui/Image;)I
    //   2312: isub
    //   2313: putstatic 183	aw:cj	I
    //   2316: getstatic 175	aw:cb	[Ljavax/microedition/lcdui/Image;
    //   2319: getstatic 179	aw:cf	[I
    //   2322: iconst_0
    //   2323: iaload
    //   2324: aaload
    //   2325: invokestatic 270	aw:b	(Ljava/lang/Object;)Z
    //   2328: ifeq +22 -> 2350
    //   2331: getstatic 183	aw:cj	I
    //   2334: getstatic 175	aw:cb	[Ljavax/microedition/lcdui/Image;
    //   2337: getstatic 179	aw:cf	[I
    //   2340: iconst_0
    //   2341: iaload
    //   2342: aaload
    //   2343: invokestatic 307	cf:b	(Ljavax/microedition/lcdui/Image;)I
    //   2346: isub
    //   2347: putstatic 156	aw:bj	I
    //   2350: getstatic 175	aw:cb	[Ljavax/microedition/lcdui/Image;
    //   2353: getstatic 179	aw:cf	[I
    //   2356: iconst_1
    //   2357: iaload
    //   2358: aaload
    //   2359: invokestatic 270	aw:b	(Ljava/lang/Object;)Z
    //   2362: ifeq +22 -> 2384
    //   2365: getstatic 156	aw:bj	I
    //   2368: getstatic 175	aw:cb	[Ljavax/microedition/lcdui/Image;
    //   2371: getstatic 179	aw:cf	[I
    //   2374: iconst_1
    //   2375: iaload
    //   2376: aaload
    //   2377: invokestatic 307	cf:b	(Ljavax/microedition/lcdui/Image;)I
    //   2380: isub
    //   2381: putstatic 165	aw:bs	I
    //   2384: getstatic 175	aw:cb	[Ljavax/microedition/lcdui/Image;
    //   2387: getstatic 179	aw:cf	[I
    //   2390: bipush 8
    //   2392: iaload
    //   2393: aaload
    //   2394: invokestatic 270	aw:b	(Ljava/lang/Object;)Z
    //   2397: ifeq +30 -> 2427
    //   2400: getstatic 156	aw:bj	I
    //   2403: getstatic 175	aw:cb	[Ljavax/microedition/lcdui/Image;
    //   2406: getstatic 179	aw:cf	[I
    //   2409: bipush 8
    //   2411: iaload
    //   2412: aaload
    //   2413: invokestatic 307	cf:b	(Ljavax/microedition/lcdui/Image;)I
    //   2416: isub
    //   2417: getstatic 179	aw:cf	[I
    //   2420: bipush 14
    //   2422: iaload
    //   2423: isub
    //   2424: putstatic 149	aw:bc	I
    //   2427: getstatic 197	aw:q	I
    //   2430: getstatic 179	aw:cf	[I
    //   2433: iconst_1
    //   2434: iaload
    //   2435: invokestatic 286	aw:j	(II)Z
    //   2438: ifeq +181 -> 2619
    //   2441: getstatic 197	aw:q	I
    //   2444: getstatic 179	aw:cf	[I
    //   2447: bipush 31
    //   2449: iaload
    //   2450: invokestatic 280	aw:g	(II)Z
    //   2453: ifeq +166 -> 2619
    //   2456: getstatic 248	fn:et	I
    //   2459: getstatic 175	aw:cb	[Ljavax/microedition/lcdui/Image;
    //   2462: getstatic 179	aw:cf	[I
    //   2465: iconst_2
    //   2466: iaload
    //   2467: aaload
    //   2468: invokestatic 307	cf:b	(Ljavax/microedition/lcdui/Image;)I
    //   2471: isub
    //   2472: dup
    //   2473: istore 4
    //   2475: putstatic 181	aw:ch	I
    //   2478: getstatic 175	aw:cb	[Ljavax/microedition/lcdui/Image;
    //   2481: getstatic 179	aw:cf	[I
    //   2484: iconst_0
    //   2485: iaload
    //   2486: aaload
    //   2487: invokestatic 270	aw:b	(Ljava/lang/Object;)Z
    //   2490: ifeq +22 -> 2512
    //   2493: iload 4
    //   2495: getstatic 175	aw:cb	[Ljavax/microedition/lcdui/Image;
    //   2498: getstatic 179	aw:cf	[I
    //   2501: iconst_0
    //   2502: iaload
    //   2503: aaload
    //   2504: invokestatic 307	cf:b	(Ljavax/microedition/lcdui/Image;)I
    //   2507: isub
    //   2508: iload_1
    //   2509: iadd
    //   2510: istore 4
    //   2512: iload 4
    //   2514: putstatic 153	aw:bg	I
    //   2517: getstatic 175	aw:cb	[Ljavax/microedition/lcdui/Image;
    //   2520: getstatic 179	aw:cf	[I
    //   2523: bipush 8
    //   2525: iaload
    //   2526: aaload
    //   2527: invokestatic 270	aw:b	(Ljava/lang/Object;)Z
    //   2530: ifeq +23 -> 2553
    //   2533: iload 4
    //   2535: getstatic 175	aw:cb	[Ljavax/microedition/lcdui/Image;
    //   2538: getstatic 179	aw:cf	[I
    //   2541: bipush 8
    //   2543: iaload
    //   2544: aaload
    //   2545: invokestatic 307	cf:b	(Ljavax/microedition/lcdui/Image;)I
    //   2548: isub
    //   2549: iload_3
    //   2550: iadd
    //   2551: istore 4
    //   2553: iload 4
    //   2555: putstatic 149	aw:bc	I
    //   2558: iload 4
    //   2560: putstatic 171	aw:by	I
    //   2563: getstatic 175	aw:cb	[Ljavax/microedition/lcdui/Image;
    //   2566: getstatic 179	aw:cf	[I
    //   2569: iconst_1
    //   2570: iaload
    //   2571: aaload
    //   2572: invokestatic 270	aw:b	(Ljava/lang/Object;)Z
    //   2575: ifeq +24 -> 2599
    //   2578: getstatic 153	aw:bg	I
    //   2581: getstatic 175	aw:cb	[Ljavax/microedition/lcdui/Image;
    //   2584: getstatic 179	aw:cf	[I
    //   2587: iconst_1
    //   2588: iaload
    //   2589: aaload
    //   2590: invokestatic 307	cf:b	(Ljavax/microedition/lcdui/Image;)I
    //   2593: isub
    //   2594: iload_2
    //   2595: iadd
    //   2596: putstatic 165	aw:bs	I
    //   2599: getstatic 197	aw:q	I
    //   2602: getstatic 179	aw:cf	[I
    //   2605: iconst_1
    //   2606: iaload
    //   2607: invokestatic 285	aw:i	(II)Z
    //   2610: ifeq +9 -> 2619
    //   2613: getstatic 141	aw:av	I
    //   2616: putstatic 171	aw:by	I
    //   2619: getstatic 197	aw:q	I
    //   2622: getstatic 179	aw:cf	[I
    //   2625: iconst_1
    //   2626: iaload
    //   2627: invokestatic 286	aw:j	(II)Z
    //   2630: ifeq +55 -> 2685
    //   2633: getstatic 197	aw:q	I
    //   2636: getstatic 179	aw:cf	[I
    //   2639: bipush 24
    //   2641: iaload
    //   2642: invokestatic 280	aw:g	(II)Z
    //   2645: ifeq +40 -> 2685
    //   2648: getstatic 179	aw:cf	[I
    //   2651: iconst_1
    //   2652: iaload
    //   2653: getstatic 248	fn:et	I
    //   2656: imul
    //   2657: getstatic 179	aw:cf	[I
    //   2660: bipush 8
    //   2662: iaload
    //   2663: idiv
    //   2664: getstatic 153	aw:bg	I
    //   2667: isub
    //   2668: istore 4
    //   2670: ldc 7
    //   2672: invokevirtual 406	java/lang/String:length	()I
    //   2675: pop
    //   2676: ldc 8
    //   2678: invokevirtual 406	java/lang/String:length	()I
    //   2681: ifne +26 -> 2707
    //   2684: return
    //   2685: getstatic 179	aw:cf	[I
    //   2688: iconst_1
    //   2689: iaload
    //   2690: getstatic 248	fn:et	I
    //   2693: imul
    //   2694: getstatic 179	aw:cf	[I
    //   2697: bipush 8
    //   2699: iaload
    //   2700: idiv
    //   2701: getstatic 156	aw:bj	I
    //   2704: isub
    //   2705: istore 4
    //   2707: iload 4
    //   2709: invokestatic 281	aw:h	(I)Z
    //   2712: ifeq +10 -> 2722
    //   2715: getstatic 179	aw:cf	[I
    //   2718: iconst_2
    //   2719: iaload
    //   2720: istore 4
    //   2722: getstatic 234	et:o	S
    //   2725: getstatic 179	aw:cf	[I
    //   2728: bipush 36
    //   2730: iaload
    //   2731: invokestatic 285	aw:i	(II)Z
    //   2734: ifeq +27 -> 2761
    //   2737: getstatic 234	et:o	S
    //   2740: getstatic 179	aw:cf	[I
    //   2743: bipush 37
    //   2745: iaload
    //   2746: invokestatic 285	aw:i	(II)Z
    //   2749: ifeq +12 -> 2761
    //   2752: getstatic 181	aw:ch	I
    //   2755: iload 4
    //   2757: iadd
    //   2758: putstatic 181	aw:ch	I
    //   2761: getstatic 197	aw:q	I
    //   2764: getstatic 179	aw:cf	[I
    //   2767: iconst_1
    //   2768: iaload
    //   2769: invokestatic 286	aw:j	(II)Z
    //   2772: ifeq +27 -> 2799
    //   2775: getstatic 197	aw:q	I
    //   2778: getstatic 179	aw:cf	[I
    //   2781: bipush 20
    //   2783: iaload
    //   2784: invokestatic 280	aw:g	(II)Z
    //   2787: ifeq +12 -> 2799
    //   2790: getstatic 153	aw:bg	I
    //   2793: iload 4
    //   2795: iadd
    //   2796: putstatic 153	aw:bg	I
    //   2799: getstatic 171	aw:by	I
    //   2802: iload 4
    //   2804: iadd
    //   2805: putstatic 171	aw:by	I
    //   2808: getstatic 183	aw:cj	I
    //   2811: iload 4
    //   2813: iadd
    //   2814: putstatic 183	aw:cj	I
    //   2817: getstatic 156	aw:bj	I
    //   2820: iload 4
    //   2822: iadd
    //   2823: putstatic 156	aw:bj	I
    //   2826: getstatic 165	aw:bs	I
    //   2829: iload 4
    //   2831: iadd
    //   2832: putstatic 165	aw:bs	I
    //   2835: getstatic 149	aw:bc	I
    //   2838: iload 4
    //   2840: iadd
    //   2841: putstatic 149	aw:bc	I
    //   2844: getstatic 179	aw:cf	[I
    //   2847: bipush 8
    //   2849: iaload
    //   2850: getstatic 242	fn:au	I
    //   2853: imul
    //   2854: getstatic 179	aw:cf	[I
    //   2857: bipush 9
    //   2859: iaload
    //   2860: idiv
    //   2861: putstatic 166	aw:bt	I
    //   2864: getstatic 171	aw:by	I
    //   2867: getstatic 179	aw:cf	[I
    //   2870: bipush 8
    //   2872: iaload
    //   2873: idiv
    //   2874: putstatic 159	aw:bm	I
    //   2877: getstatic 179	aw:cf	[I
    //   2880: iconst_1
    //   2881: iaload
    //   2882: newarray <illegal type>
    //   2884: putstatic 172	aw:bz	[I
    //   2887: getstatic 179	aw:cf	[I
    //   2890: iconst_1
    //   2891: iaload
    //   2892: newarray <illegal type>
    //   2894: putstatic 178	aw:ce	[I
    //   2897: getstatic 172	aw:bz	[I
    //   2900: getstatic 179	aw:cf	[I
    //   2903: iconst_2
    //   2904: iaload
    //   2905: getstatic 242	fn:au	I
    //   2908: getstatic 179	aw:cf	[I
    //   2911: bipush 8
    //   2913: iaload
    //   2914: idiv
    //   2915: iastore
    //   2916: getstatic 178	aw:ce	[I
    //   2919: getstatic 179	aw:cf	[I
    //   2922: iconst_2
    //   2923: iaload
    //   2924: getstatic 171	aw:by	I
    //   2927: getstatic 179	aw:cf	[I
    //   2930: iconst_1
    //   2931: iaload
    //   2932: idiv
    //   2933: getstatic 179	aw:cf	[I
    //   2936: bipush 22
    //   2938: iaload
    //   2939: isub
    //   2940: iastore
    //   2941: getstatic 172	aw:bz	[I
    //   2944: getstatic 179	aw:cf	[I
    //   2947: iconst_0
    //   2948: iaload
    //   2949: getstatic 179	aw:cf	[I
    //   2952: iconst_1
    //   2953: iaload
    //   2954: getstatic 242	fn:au	I
    //   2957: imul
    //   2958: getstatic 179	aw:cf	[I
    //   2961: bipush 8
    //   2963: iaload
    //   2964: idiv
    //   2965: iastore
    //   2966: getstatic 178	aw:ce	[I
    //   2969: getstatic 179	aw:cf	[I
    //   2972: iconst_0
    //   2973: iaload
    //   2974: getstatic 171	aw:by	I
    //   2977: getstatic 179	aw:cf	[I
    //   2980: iconst_1
    //   2981: iaload
    //   2982: idiv
    //   2983: getstatic 179	aw:cf	[I
    //   2986: bipush 22
    //   2988: iaload
    //   2989: iadd
    //   2990: iastore
    //   2991: getstatic 197	aw:q	I
    //   2994: getstatic 179	aw:cf	[I
    //   2997: iconst_1
    //   2998: iaload
    //   2999: invokestatic 285	aw:i	(II)Z
    //   3002: ifeq +293 -> 3295
    //   3005: getstatic 171	aw:by	I
    //   3008: getstatic 179	aw:cf	[I
    //   3011: bipush 10
    //   3013: iaload
    //   3014: idiv
    //   3015: putstatic 159	aw:bm	I
    //   3018: getstatic 179	aw:cf	[I
    //   3021: bipush 10
    //   3023: iaload
    //   3024: newarray <illegal type>
    //   3026: putstatic 172	aw:bz	[I
    //   3029: getstatic 179	aw:cf	[I
    //   3032: bipush 10
    //   3034: iaload
    //   3035: newarray <illegal type>
    //   3037: putstatic 178	aw:ce	[I
    //   3040: getstatic 172	aw:bz	[I
    //   3043: getstatic 179	aw:cf	[I
    //   3046: iconst_2
    //   3047: iaload
    //   3048: getstatic 242	fn:au	I
    //   3051: getstatic 179	aw:cf	[I
    //   3054: bipush 8
    //   3056: iaload
    //   3057: idiv
    //   3058: iastore
    //   3059: getstatic 178	aw:ce	[I
    //   3062: getstatic 179	aw:cf	[I
    //   3065: iconst_2
    //   3066: iaload
    //   3067: getstatic 171	aw:by	I
    //   3070: getstatic 179	aw:cf	[I
    //   3073: bipush 8
    //   3075: iaload
    //   3076: idiv
    //   3077: getstatic 179	aw:cf	[I
    //   3080: bipush 38
    //   3082: iaload
    //   3083: isub
    //   3084: iastore
    //   3085: getstatic 172	aw:bz	[I
    //   3088: getstatic 179	aw:cf	[I
    //   3091: iconst_0
    //   3092: iaload
    //   3093: getstatic 179	aw:cf	[I
    //   3096: bipush 8
    //   3098: iaload
    //   3099: getstatic 242	fn:au	I
    //   3102: imul
    //   3103: getstatic 179	aw:cf	[I
    //   3106: bipush 9
    //   3108: iaload
    //   3109: idiv
    //   3110: iastore
    //   3111: getstatic 178	aw:ce	[I
    //   3114: getstatic 179	aw:cf	[I
    //   3117: iconst_0
    //   3118: iaload
    //   3119: getstatic 171	aw:by	I
    //   3122: getstatic 179	aw:cf	[I
    //   3125: bipush 8
    //   3127: iaload
    //   3128: idiv
    //   3129: getstatic 179	aw:cf	[I
    //   3132: bipush 24
    //   3134: iaload
    //   3135: iadd
    //   3136: iastore
    //   3137: getstatic 172	aw:bz	[I
    //   3140: getstatic 179	aw:cf	[I
    //   3143: iconst_1
    //   3144: iaload
    //   3145: getstatic 242	fn:au	I
    //   3148: getstatic 179	aw:cf	[I
    //   3151: bipush 8
    //   3153: iaload
    //   3154: idiv
    //   3155: getstatic 179	aw:cf	[I
    //   3158: bipush 6
    //   3160: iaload
    //   3161: isub
    //   3162: iastore
    //   3163: getstatic 178	aw:ce	[I
    //   3166: getstatic 179	aw:cf	[I
    //   3169: iconst_1
    //   3170: iaload
    //   3171: getstatic 171	aw:by	I
    //   3174: getstatic 179	aw:cf	[I
    //   3177: bipush 8
    //   3179: iaload
    //   3180: idiv
    //   3181: getstatic 179	aw:cf	[I
    //   3184: bipush 24
    //   3186: iaload
    //   3187: iadd
    //   3188: iastore
    //   3189: getstatic 172	aw:bz	[I
    //   3192: getstatic 179	aw:cf	[I
    //   3195: bipush 8
    //   3197: iaload
    //   3198: getstatic 242	fn:au	I
    //   3201: getstatic 179	aw:cf	[I
    //   3204: bipush 6
    //   3206: iaload
    //   3207: idiv
    //   3208: iastore
    //   3209: getstatic 178	aw:ce	[I
    //   3212: getstatic 179	aw:cf	[I
    //   3215: bipush 8
    //   3217: iaload
    //   3218: getstatic 171	aw:by	I
    //   3221: getstatic 179	aw:cf	[I
    //   3224: iconst_1
    //   3225: iaload
    //   3226: idiv
    //   3227: getstatic 179	aw:cf	[I
    //   3230: bipush 24
    //   3232: iaload
    //   3233: iadd
    //   3234: iastore
    //   3235: getstatic 172	aw:bz	[I
    //   3238: getstatic 179	aw:cf	[I
    //   3241: bipush 9
    //   3243: iaload
    //   3244: getstatic 179	aw:cf	[I
    //   3247: iconst_1
    //   3248: iaload
    //   3249: getstatic 242	fn:au	I
    //   3252: imul
    //   3253: getstatic 179	aw:cf	[I
    //   3256: bipush 8
    //   3258: iaload
    //   3259: idiv
    //   3260: getstatic 179	aw:cf	[I
    //   3263: bipush 39
    //   3265: iaload
    //   3266: iadd
    //   3267: iastore
    //   3268: getstatic 178	aw:ce	[I
    //   3271: getstatic 179	aw:cf	[I
    //   3274: bipush 9
    //   3276: iaload
    //   3277: getstatic 171	aw:by	I
    //   3280: getstatic 179	aw:cf	[I
    //   3283: bipush 8
    //   3285: iaload
    //   3286: idiv
    //   3287: getstatic 179	aw:cf	[I
    //   3290: bipush 24
    //   3292: iaload
    //   3293: iadd
    //   3294: iastore
    //   3295: getstatic 128	aw:ag	Z
    //   3298: invokestatic 284	aw:i	(I)Z
    //   3301: ifeq +124 -> 3425
    //   3304: getstatic 197	aw:q	I
    //   3307: getstatic 179	aw:cf	[I
    //   3310: bipush 22
    //   3312: iaload
    //   3313: invokestatic 285	aw:i	(II)Z
    //   3316: ifeq +20 -> 3336
    //   3319: getstatic 251	fn:k	I
    //   3322: getstatic 179	aw:cf	[I
    //   3325: bipush 40
    //   3327: iaload
    //   3328: isub
    //   3329: dup
    //   3330: putstatic 153	aw:bg	I
    //   3333: putstatic 181	aw:ch	I
    //   3336: getstatic 197	aw:q	I
    //   3339: getstatic 179	aw:cf	[I
    //   3342: bipush 14
    //   3344: iaload
    //   3345: invokestatic 285	aw:i	(II)Z
    //   3348: ifeq +39 -> 3387
    //   3351: getstatic 175	aw:cb	[Ljavax/microedition/lcdui/Image;
    //   3354: getstatic 179	aw:cf	[I
    //   3357: bipush 8
    //   3359: iaload
    //   3360: aaload
    //   3361: invokestatic 270	aw:b	(Ljava/lang/Object;)Z
    //   3364: ifeq +23 -> 3387
    //   3367: getstatic 165	aw:bs	I
    //   3370: getstatic 175	aw:cb	[Ljavax/microedition/lcdui/Image;
    //   3373: getstatic 179	aw:cf	[I
    //   3376: bipush 8
    //   3378: iaload
    //   3379: aaload
    //   3380: invokestatic 307	cf:b	(Ljavax/microedition/lcdui/Image;)I
    //   3383: isub
    //   3384: putstatic 149	aw:bc	I
    //   3387: getstatic 197	aw:q	I
    //   3390: getstatic 179	aw:cf	[I
    //   3393: bipush 23
    //   3395: iaload
    //   3396: invokestatic 287	aw:k	(II)Z
    //   3399: ifeq +18 -> 3417
    //   3402: getstatic 197	aw:q	I
    //   3405: getstatic 179	aw:cf	[I
    //   3408: bipush 24
    //   3410: iaload
    //   3411: invokestatic 285	aw:i	(II)Z
    //   3414: ifeq +11 -> 3425
    //   3417: getstatic 179	aw:cf	[I
    //   3420: iconst_2
    //   3421: iaload
    //   3422: putstatic 149	aw:bc	I
    //   3425: return
    // Local variable table:
    //   start	length	slot	name	signature
    //   0	3426	0	paramInt	int
    //   5	2505	1	i1	int
    //   11	2585	2	i2	int
    //   17	2534	3	i3	int
    //   1239	1602	4	i4	int
    //   1311	1	5	localException1	Exception
    //   2154	1	6	localException2	Exception
    // Exception table:
    //   from	to	target	type
    //   1255	1300	1311	java/lang/Exception
    //   1202	2109	2154	java/lang/Exception
  }
  
  private static void u()
  {
    if (i(ag))
    {
      bb = new Image[cf[8]];
      int i1 = cf[2];
      while (f(i1, cf[8]))
      {
        bb[i1] = c("/e/w" + i1 + ".png");
        i1++;
        "".length();
        if ("   ".length() <= ((1 + 120 - 100 + 133 ^ 65 + '' - 63 + 4) & (25 + 15 - -22 + 65 ^ 0xCE ^ 0xBA ^ -" ".length()))) {
          return;
        }
      }
      bi = new int[cf[1]];
      bu = new int[cf[1]];
      (bo = new int[cf[1]])[cf[2]] = (bo[cf[0]] = cf[11]);
    }
  }
  
  protected final void b(int paramInt)
  {
    ac = cf[2];
    switch (paramInt)
    {
    case -39: 
    case -2: 
      i[cf[22]] = cf[2];
      return;
    case -38: 
    case -1: 
      i[cf[1]] = cf[2];
      return;
    case -37: 
    case -36: 
    case -35: 
    case -34: 
    case -33: 
    case -32: 
    case -31: 
    case -30: 
    case -29: 
    case -28: 
    case -27: 
    case -26: 
    case -25: 
    case -24: 
    case -23: 
    case -20: 
    case -19: 
    case -18: 
    case -17: 
    case -16: 
    case -15: 
    case -14: 
    case -13: 
    case -12: 
    case -11: 
    case -10: 
    case -9: 
    case -8: 
    case 0: 
    case 1: 
    case 2: 
    case 3: 
    case 4: 
    case 5: 
    case 6: 
    case 7: 
    case 8: 
    case 9: 
    case 11: 
    case 12: 
    case 13: 
    case 14: 
    case 15: 
    case 16: 
    case 17: 
    case 18: 
    case 19: 
    case 20: 
    case 21: 
    case 22: 
    case 23: 
    case 24: 
    case 25: 
    case 26: 
    case 27: 
    case 28: 
    case 29: 
    case 30: 
    case 31: 
    case 32: 
    case 33: 
    case 34: 
    case 36: 
    case 37: 
    case 38: 
    case 39: 
    case 40: 
    case 41: 
    case 43: 
    case 44: 
    case 45: 
    case 46: 
    case 47: 
    default: 
      return;
    case -22: 
    case -7: 
      i[cf[31]] = cf[2];
      bv[cf[31]] = cf[0];
      return;
    case -21: 
    case -6: 
      i[cf[24]] = cf[2];
      bv[cf[24]] = cf[0];
      return;
    case -5: 
    case 10: 
      i[cf[10]] = cf[2];
      bv[cf[10]] = cf[0];
      return;
    case -4: 
      i[cf[20]] = cf[2];
      return;
    case -3: 
      i[cf[9]] = cf[2];
      return;
    case 35: 
      i[cf[23]] = cf[2];
      bv[cf[23]] = cf[0];
      return;
    case 42: 
      i[cf[14]] = cf[2];
      bv[cf[14]] = cf[0];
      return;
    case 48: 
      i[cf[2]] = cf[2];
      bv[cf[2]] = cf[0];
      return;
    case 49: 
      if ((a(ai, fn.eq)) && (e(an)) && (i(k.b().e)))
      {
        i[cf[0]] = cf[2];
        bv[cf[0]] = cf[0];
      }
      return;
    case 50: 
      if ((a(ai, fn.eq)) && (e(an)) && (i(k.b().e)))
      {
        i[cf[1]] = cf[2];
        bv[cf[1]] = cf[0];
      }
      return;
    case 51: 
      if ((a(ai, fn.eq)) && (e(an)) && (i(k.b().e)))
      {
        i[cf[8]] = cf[2];
        bv[cf[8]] = cf[0];
      }
      return;
    case 52: 
      if ((a(ai, fn.eq)) && (e(an)) && (i(k.b().e)))
      {
        i[cf[9]] = cf[2];
        bv[cf[9]] = cf[0];
      }
      return;
    case 53: 
      if ((a(ai, fn.eq)) && (e(an)) && (i(k.b().e)))
      {
        i[cf[10]] = cf[2];
        bv[cf[10]] = cf[0];
      }
      return;
    case 54: 
      if ((a(ai, fn.eq)) && (e(an)) && (i(k.b().e)))
      {
        i[cf[20]] = cf[2];
        bv[cf[20]] = cf[0];
      }
      return;
    case 55: 
      i[cf[15]] = cf[2];
      bv[cf[15]] = cf[0];
      return;
    case 56: 
      if ((a(ai, fn.eq)) && (e(an)) && (i(k.b().e)))
      {
        i[cf[22]] = cf[2];
        bv[cf[22]] = cf[0];
      }
      return;
    }
    i[cf[33]] = cf[2];
    bv[cf[33]] = cf[0];
  }
  
  public static void b(String paramString)
  {
    h.a(paramString, null, new bb(an.gk, t, cf[51], null), null);
    u = h;
    h.b = cf[0];
  }
  
  private static void v()
  {
    cf = new int[58];
    cf[0] = " ".length();
    cf[1] = "  ".length();
    cf[2] = ((0x3C ^ 0x16) & (0x4C ^ 0x66 ^ 0xFFFFFFFF));
    cf[3] = ((0x42 ^ 0x51) + (0x6 ^ 0x2A) - -(0x69 ^ 0x15) + (0x20 ^ 0x15));
    cf[4] = (0x915B & 0x6FE4);
    cf[5] = (2 + 76 - 56 + 138);
    cf[6] = (0x5C ^ 0x49 ^ 0x68 ^ 0x72);
    cf[7] = (0x1A ^ 0xB);
    cf[8] = "   ".length();
    cf[9] = (0x69 ^ 0x6D);
    cf[10] = (100 + 113 - 120 + 76 ^ '¥' + 116 - 133 + 24);
    cf[11] = (-" ".length());
    cf[12] = (-(0xC6F6 & 0x796F) & 0xFF7D & 0x67F7);
    cf[13] = (0xF6 ^ 0xBB ^ 0xBB ^ 0x92);
    cf[14] = (59 + 11 - 56 + 129 ^ 106 + 23 - 86 + 90);
    cf[15] = (0x43 ^ 0x44);
    cf[16] = (-" ".length() & 0xFFFFFFFF & 0xFFFFFF);
    cf[17] = (66 + 117 - 103 + 56 ^ 104 + 84 - 122 + 78);
    cf[18] = (0xED ^ 0xAD);
    cf[19] = (36 + 105 - 131 + 182);
    cf[20] = (0xAF ^ 0xA9);
    cf[21] = (0x1 ^ 0x11);
    cf[22] = (0xA6 ^ 0xAE);
    cf[23] = (0x72 ^ 0x69 ^ 0xAB ^ 0xBB);
    cf[24] = (0x8E ^ 0x95 ^ 0xD4 ^ 0xC3);
    cf[25] = (0x48 ^ 0x65);
    cf[26] = (0x84 ^ 0x8A);
    cf[27] = (0x51 ^ 0x18 ^ 0x21 ^ 0x5C);
    cf[28] = (0x90 ^ 0xC7 ^ 0x54 ^ 0x34);
    cf[29] = (0xBE7B & 0x114184);
    cf[30] = (0x1 ^ 0x15);
    cf[31] = (0x76 ^ 0x7B);
    cf[32] = (9 + 80 - 83 + 124);
    cf[33] = (0xB2 ^ 0xBB);
    cf[34] = (0x31 ^ 0xD);
    cf[35] = (0x43 ^ 0x6B);
    cf[36] = (0x4E ^ 0x7E);
    cf[37] = (0x15 ^ 0x26);
    cf[38] = (0x8D ^ 0xAE);
    cf[39] = (0x37 ^ 0x2E);
    cf[40] = (0x54 ^ 0x26 ^ 0xED ^ 0xAD);
    cf[41] = (0xBD ^ 0xA4 ^ 0x3A ^ 0x1A);
    cf[42] = (0x7 ^ 0x46);
    cf[43] = (0x7C ^ 0x6);
    cf[44] = (0x8D ^ 0xAD);
    cf[45] = ('' + 11 - 6 + 30 ^ 41 + 31 - -109 + 1);
    cf[46] = (0x3A ^ 0x4C);
    cf[47] = (0x1 ^ 0x51);
    cf[48] = (0x7B ^ 0x19);
    cf[49] = (0x1 ^ 0x4F);
    cf[50] = (0xE1F7 & 0x1FFC);
    cf[51] = (-(0xD459 & 0x7FEF) & 0xFEFA & 0x77FF);
    cf[52] = (-(0xF74B & 0xDFF) & 0xFFFFFFFF & 0x27FB);
    cf[53] = (0xB7B7 & 0x6AFB);
    cf[54] = (0xDFFD & 0x17AF7);
    cf[55] = (0x8FE9 & 0xDFE3F);
    cf[56] = (0x96BF & 0x1EFDF);
    cf[57] = (0xAFF7 & 0xDDE4F);
  }
  
  private static int a(long paramLong1, long paramLong2)
  {
    return paramLong1 < paramLong2;
  }
  
  public static void g()
  {
    int i1 = cf[2];
    while (f(i1, cf[26]))
    {
      ak[i1] = cf[2];
      i1++;
      "".length();
      if (-" ".length() > 0) {
        return;
      }
    }
    j = cf[2];
  }
  
  public static void a(int paramInt1, int paramInt2, cf paramcf)
  {
    int i1 = ap % cf[8];
    paramcf.a(bx, cf[2], i1 << cf[9], cf[21], cf[21], cf[2], paramInt1, paramInt2, cf[8]);
  }
  
  public static void a(String paramString, int paramInt)
  {
    h.a(paramString, null, new bb(an.nd, t, paramInt, b / cf[1] - cf[38], av - cf[40]), null);
    u = h;
  }
  
  protected final void c(int paramInt)
  {
    bn = System.currentTimeMillis();
    if (((j(paramInt, cf[36])) && (!h(paramInt, cf[41]))) || ((j(paramInt, cf[42])) && (!h(paramInt, cf[43]))) || (!k(paramInt, cf[14])) || (!k(paramInt, cf[22])) || (!k(paramInt, cf[31])) || (i(paramInt, cf[44]))) {
      ac = paramInt;
    }
    if (b(u))
    {
      u.a(paramInt);
      ac = cf[2];
      return;
    }
    ai.a(paramInt);
    switch (paramInt)
    {
    case -39: 
    case -2: 
      i[cf[22]] = cf[0];
      ak[cf[22]] = cf[0];
      return;
    case -38: 
    case -1: 
      i[cf[1]] = cf[0];
      ak[cf[1]] = cf[0];
      return;
    case -37: 
    case -36: 
    case -35: 
    case -34: 
    case -33: 
    case -32: 
    case -31: 
    case -30: 
    case -29: 
    case -28: 
    case -27: 
    case -26: 
    case -25: 
    case -24: 
    case -23: 
    case -20: 
    case -19: 
    case -18: 
    case -17: 
    case -16: 
    case -15: 
    case -14: 
    case -13: 
    case -12: 
    case -11: 
    case -10: 
    case -9: 
    case -8: 
    case 0: 
    case 1: 
    case 2: 
    case 3: 
    case 4: 
    case 5: 
    case 6: 
    case 7: 
    case 8: 
    case 9: 
    case 11: 
    case 12: 
    case 13: 
    case 14: 
    case 15: 
    case 16: 
    case 17: 
    case 18: 
    case 19: 
    case 20: 
    case 21: 
    case 22: 
    case 23: 
    case 24: 
    case 25: 
    case 26: 
    case 27: 
    case 28: 
    case 29: 
    case 30: 
    case 31: 
    case 32: 
    case 33: 
    case 34: 
    case 36: 
    case 37: 
    case 38: 
    case 39: 
    case 40: 
    case 41: 
    case 43: 
    case 44: 
    case 45: 
    case 46: 
    case 47: 
    default: 
      return;
    case -22: 
    case -7: 
      i[cf[31]] = cf[0];
      ak[cf[31]] = cf[0];
      return;
    case -21: 
    case -6: 
      i[cf[24]] = cf[0];
      ak[cf[24]] = cf[0];
      return;
    case -5: 
    case 10: 
      i[cf[10]] = cf[0];
      ak[cf[10]] = cf[0];
      return;
    case -4: 
      i[cf[20]] = cf[0];
      ak[cf[20]] = cf[0];
      return;
    case -3: 
      i[cf[9]] = cf[0];
      ak[cf[9]] = cf[0];
      return;
    case 35: 
      i[cf[23]] = cf[0];
      ak[cf[23]] = cf[0];
      return;
    case 42: 
      i[cf[14]] = cf[0];
      ak[cf[14]] = cf[0];
      return;
    case 48: 
      i[cf[2]] = cf[0];
      ak[cf[2]] = cf[0];
      return;
    case 49: 
      if ((a(ai, fn.eq)) && (e(an)) && (i(k.b().e)))
      {
        i[cf[0]] = cf[0];
        ak[cf[0]] = cf[0];
      }
      return;
    case 50: 
      if ((a(ai, fn.eq)) && (e(an)) && (i(k.b().e)) && (i(fn.fb)))
      {
        i[cf[1]] = cf[0];
        ak[cf[1]] = cf[0];
      }
      return;
    case 51: 
      if ((a(ai, fn.eq)) && (e(an)) && (i(k.b().e)))
      {
        i[cf[8]] = cf[0];
        ak[cf[8]] = cf[0];
      }
      return;
    case 52: 
      if ((a(ai, fn.eq)) && (e(an)) && (i(k.b().e)) && (i(fn.fb)))
      {
        i[cf[9]] = cf[0];
        ak[cf[9]] = cf[0];
      }
      return;
    case 53: 
      if ((a(ai, fn.eq)) && (e(an)) && (i(k.b().e)) && (i(fn.fb)))
      {
        i[cf[10]] = cf[0];
        ak[cf[10]] = cf[0];
      }
      return;
    case 54: 
      if ((a(ai, fn.eq)) && (e(an)) && (i(k.b().e)) && (i(fn.fb)))
      {
        i[cf[20]] = cf[0];
        ak[cf[20]] = cf[0];
      }
      return;
    case 55: 
      i[cf[15]] = cf[0];
      ak[cf[15]] = cf[0];
      return;
    case 56: 
      if ((a(ai, fn.eq)) && (e(an)) && (i(k.b().e)) && (i(fn.fb)))
      {
        i[cf[22]] = cf[0];
        ak[cf[22]] = cf[0];
      }
      return;
    }
    i[cf[33]] = cf[0];
    ak[cf[33]] = cf[0];
  }
  
  private static boolean h(int paramInt1, int paramInt2)
  {
    return paramInt1 > paramInt2;
  }
  
  public static void h()
  {
    b(an.ki);
  }
  
  public static void i()
  {
    v();
    ag = cf[2];
    an = cf[0];
    ah = cf[0];
    d = cf[2];
    s = cf[2];
    ak = new boolean[cf[26]];
    bv = new boolean[cf[26]];
    i = new boolean[cf[26]];
    ad = new fq[cf[9]];
    af = new eu();
    cd = cf[2];
    aa = new Image[cf[1]];
    q = cf[11];
    bn = 0L;
    bf = new Image[cf[9]][];
    bp = new Image[cf[9]];
    az = new Image[cf[1]];
  }
  
  static
  {
    cs.a(11);
    i();
  }
  
  public static void j()
  {
    b = dm.b.c();
    av = dm.b.b();
    aq = b / cf[1];
    al = av / cf[1];
    ae = new bp();
    au = new de();
    new ag();
    ao = new br();
    z = new j();
  }
  
  private static boolean g(int paramInt)
  {
    return paramInt <= 0;
  }
  
  private static int b(long paramLong1, long paramLong2)
  {
    return paramLong1 < paramLong2;
  }
  
  public final void a(cf paramcf)
  {
    if (i(ag))
    {
      int i1 = cf[2];
      while (f(i1, cf[1]))
      {
        if ((k(this.bq[i1], cf[11])) && (e(e(this.bh[i1], this.be[i1])))) {
          paramcf.a(cc[i1][this.bq[i1]], this.bh[i1], this.be[i1], cf[8]);
        }
        i1++;
        "".length();
        if (((71 + 112 - 158 + 151 ^ '¡' + 40 - 152 + 118) & (0xB4 ^ 0x82 ^ 0x19 ^ 0x38 ^ -" ".length())) != 0) {}
      }
    }
  }
  
  private static boolean i(int paramInt1, int paramInt2)
  {
    return paramInt1 == paramInt2;
  }
  
  public static boolean b(int paramInt1, int paramInt2, int paramInt3, int paramInt4)
  {
    if (((!i(y)) || (e(j))) && (j(f, paramInt1)) && (g(f, paramInt1 + paramInt3)) && (j(o, paramInt2)) && (g(o, paramInt2 + paramInt4))) {
      return cf[0];
    }
    return cf[2];
  }
  
  /* Error */
  public static Image c(String paramString)
  {
    // Byte code:
    //   0: new 82	java/lang/StringBuffer
    //   3: dup
    //   4: ldc 23
    //   6: invokespecial 408	java/lang/StringBuffer:<init>	(Ljava/lang/String;)V
    //   9: getstatic 215	cf:c	I
    //   12: invokevirtual 409	java/lang/StringBuffer:append	(I)Ljava/lang/StringBuffer;
    //   15: aload_0
    //   16: invokevirtual 410	java/lang/StringBuffer:append	(Ljava/lang/String;)Ljava/lang/StringBuffer;
    //   19: invokevirtual 411	java/lang/StringBuffer:toString	()Ljava/lang/String;
    //   22: astore_0
    //   23: aload_0
    //   24: invokestatic 415	javax/microedition/lcdui/Image:createImage	(Ljava/lang/String;)Ljavax/microedition/lcdui/Image;
    //   27: areturn
    //   28: ldc 7
    //   30: invokevirtual 406	java/lang/String:length	()I
    //   33: pop2
    //   34: aconst_null
    //   35: areturn
    // Local variable table:
    //   start	length	slot	name	signature
    //   0	36	0	paramString	String
    //   28	1	1	localException	Exception
    // Exception table:
    //   from	to	target	type
    //   23	27	28	java/lang/Exception
  }
  
  private static boolean a(Object paramObject1, Object paramObject2)
  {
    return paramObject1 == paramObject2;
  }
  
  public static aw k()
  {
    if (a(t)) {
      t = new aw();
    }
    return t;
  }
  
  public final void l()
  {
    if (i(ag))
    {
      int i1 = cf[2];
      while (f(i1, cf[1]))
      {
        if (k(this.bq[i1], cf[11]))
        {
          this.bq[i1] += cf[0];
          if (j(this.bq[i1], cf[10])) {
            this.bq[i1] = cf[11];
          }
          if (i(i1))
          {
            this.bh[i1] -= cf[0];
            "".length();
            if (((0xFD ^ 0xC4) & (0xFA ^ 0xC3 ^ 0xFFFFFFFF)) < "   ".length()) {}
          }
          else
          {
            this.bh[i1] += cf[0];
          }
          this.be[i1] -= cf[0];
        }
        i1++;
        "".length();
        if ("  ".length() >= "   ".length()) {}
      }
    }
  }
  
  public static void a(String paramString, bb parambb1, bb parambb2)
  {
    h.a(paramString, parambb1, null, parambb2);
    u = h;
  }
  
  public static void m()
  {
    h.a = cf[50];
    h.a(an.ki, null, null, null);
    u = h;
    h.b = cf[0];
  }
  
  public static void n()
  {
    if ((e(d)) && (h(g = g - cf[0]))) {
      d = cf[2];
    }
  }
  
  private static boolean j(int paramInt1, int paramInt2)
  {
    return paramInt1 >= paramInt2;
  }
  
  /* Error */
  public final void a(int paramInt, Object paramObject)
  {
    // Byte code:
    //   0: iload_1
    //   1: lookupswitch	default:+2009->2010, 1608:+403->404, 1700:+436->437, 8881:+464->465, 8882:+476->477, 8883:+481->482, 8884:+524->525, 8885:+534->535, 8887:+541->542, 8888:+560->561, 8889:+579->580, 8890:+595->596, 16081:+612->613, 88810:+645->646, 88811:+664->665, 88812:+674->675, 88813:+693->694, 88814:+709->710, 88815:+725->726, 88816:+738->739, 88817:+766->767, 88818:+831->832, 88819:+859->860, 88820:+881->882, 88821:+1060->1061, 88822:+1116->1117, 88823:+1168->1169, 88824:+1175->1176, 88825:+1182->1183, 88826:+1189->1190, 88827:+1196->1197, 88828:+1203->1204, 88829:+1210->1211, 88830:+1254->1255, 88831:+1273->1274, 88832:+1292->1293, 88833:+1325->1326, 88834:+1406->1407, 88835:+1459->1460, 88836:+1525->1526, 88837:+1575->1576, 88838:+1609->1610, 88839:+1742->1743, 88840:+1798->1799, 88841:+1817->1818, 88842:+1836->1837, 88843:+1843->1844, 888181:+1883->1884, 888361:+1911->1912, 888391:+1983->1984
    //   404: invokestatic 329	dl:ae	()Ldl;
    //   407: getstatic 206	aw:z	Lj;
    //   410: getfield 253	j:b	Lek;
    //   413: invokevirtual 363	ek:a	()Ljava/lang/String;
    //   416: getstatic 206	aw:z	Lj;
    //   419: getfield 252	j:a	Lek;
    //   422: invokevirtual 363	ek:a	()Ljava/lang/String;
    //   425: getstatic 179	aw:cf	[I
    //   428: iconst_2
    //   429: iaload
    //   430: invokevirtual 323	dl:a	(Ljava/lang/String;Ljava/lang/String;B)V
    //   433: invokestatic 288	aw:p	()V
    //   436: return
    //   437: invokestatic 329	dl:ae	()Ldl;
    //   440: getstatic 179	aw:cf	[I
    //   443: bipush 13
    //   445: iaload
    //   446: getstatic 135	aw:ao	Lbr;
    //   449: getfield 209	br:a	Lek;
    //   452: invokevirtual 363	ek:a	()Ljava/lang/String;
    //   455: getstatic 249	fn:ex	B
    //   458: invokevirtual 325	dl:a	(SLjava/lang/String;B)V
    //   461: invokestatic 288	aw:p	()V
    //   464: return
    //   465: aload_2
    //   466: checkcast 81	java/lang/String
    //   469: invokestatic 315	cl:b	(Ljava/lang/String;)V
    //   472: aconst_null
    //   473: putstatic 201	aw:u	Lfj;
    //   476: return
    //   477: aconst_null
    //   478: putstatic 201	aw:u	Lfj;
    //   481: return
    //   482: aload_2
    //   483: checkcast 51	ci
    //   486: getstatic 179	aw:cf	[I
    //   489: iconst_2
    //   490: iaload
    //   491: invokevirtual 312	ci:elementAt	(I)Ljava/lang/Object;
    //   494: checkcast 80	java/lang/Short
    //   497: invokevirtual 403	java/lang/Short:shortValue	()S
    //   500: istore_1
    //   501: aload_2
    //   502: checkcast 51	ci
    //   505: getstatic 179	aw:cf	[I
    //   508: iconst_2
    //   509: iaload
    //   510: invokevirtual 312	ci:elementAt	(I)Ljava/lang/Object;
    //   513: checkcast 81	java/lang/String
    //   516: iload_1
    //   517: invokestatic 314	cl:a	(Ljava/lang/String;S)V
    //   520: aconst_null
    //   521: putstatic 201	aw:u	Lfj;
    //   524: return
    //   525: invokestatic 288	aw:p	()V
    //   528: getstatic 140	aw:au	Lde;
    //   531: invokevirtual 320	de:b	()V
    //   534: return
    //   535: getstatic 212	bv:d	Lbv;
    //   538: invokevirtual 393	gl:g	()V
    //   541: return
    //   542: invokestatic 288	aw:p	()V
    //   545: aload_2
    //   546: checkcast 79	java/lang/Integer
    //   549: invokevirtual 400	java/lang/Integer:intValue	()I
    //   552: istore_1
    //   553: invokestatic 329	dl:ae	()Ldl;
    //   556: iload_1
    //   557: invokevirtual 328	dl:ac	(I)V
    //   560: return
    //   561: aload_2
    //   562: checkcast 79	java/lang/Integer
    //   565: invokevirtual 400	java/lang/Integer:intValue	()I
    //   568: istore_1
    //   569: invokestatic 329	dl:ae	()Ldl;
    //   572: iload_1
    //   573: invokevirtual 331	dl:ai	(I)V
    //   576: invokestatic 288	aw:p	()V
    //   579: return
    //   580: aload_2
    //   581: checkcast 81	java/lang/String
    //   584: astore_1
    //   585: invokestatic 288	aw:p	()V
    //   588: invokestatic 329	dl:ae	()Ldl;
    //   591: aload_1
    //   592: invokevirtual 340	dl:e	(Ljava/lang/String;)V
    //   595: return
    //   596: invokestatic 288	aw:p	()V
    //   599: invokestatic 329	dl:ae	()Ldl;
    //   602: aload_2
    //   603: checkcast 79	java/lang/Integer
    //   606: invokevirtual 400	java/lang/Integer:intValue	()I
    //   609: invokevirtual 350	dl:q	(I)V
    //   612: return
    //   613: invokestatic 329	dl:ae	()Ldl;
    //   616: getstatic 206	aw:z	Lj;
    //   619: getfield 253	j:b	Lek;
    //   622: invokevirtual 363	ek:a	()Ljava/lang/String;
    //   625: getstatic 206	aw:z	Lj;
    //   628: getfield 252	j:a	Lek;
    //   631: invokevirtual 363	ek:a	()Ljava/lang/String;
    //   634: getstatic 179	aw:cf	[I
    //   637: iconst_0
    //   638: iaload
    //   639: invokevirtual 323	dl:a	(Ljava/lang/String;Ljava/lang/String;B)V
    //   642: invokestatic 288	aw:p	()V
    //   645: return
    //   646: aload_2
    //   647: checkcast 79	java/lang/Integer
    //   650: invokevirtual 400	java/lang/Integer:intValue	()I
    //   653: istore_1
    //   654: invokestatic 288	aw:p	()V
    //   657: invokestatic 329	dl:ae	()Ldl;
    //   660: iload_1
    //   661: invokevirtual 332	dl:al	(I)V
    //   664: return
    //   665: invokestatic 288	aw:p	()V
    //   668: invokestatic 329	dl:ae	()Ldl;
    //   671: invokevirtual 348	dl:p	()V
    //   674: return
    //   675: aload_2
    //   676: checkcast 61	dt
    //   679: astore_1
    //   680: invokestatic 288	aw:p	()V
    //   683: invokestatic 329	dl:ae	()Ldl;
    //   686: aload_1
    //   687: getfield 230	dt:fy	I
    //   690: invokevirtual 341	dl:f	(I)V
    //   693: return
    //   694: invokestatic 288	aw:p	()V
    //   697: aload_2
    //   698: checkcast 30	[Lao;
    //   701: astore_1
    //   702: invokestatic 329	dl:ae	()Ldl;
    //   705: aload_1
    //   706: invokevirtual 326	dl:a	([Lao;)V
    //   709: return
    //   710: aload_2
    //   711: checkcast 30	[Lao;
    //   714: astore_1
    //   715: invokestatic 288	aw:p	()V
    //   718: invokestatic 329	dl:ae	()Ldl;
    //   721: aload_1
    //   722: invokevirtual 337	dl:b	([Lao;)V
    //   725: return
    //   726: invokestatic 389	fn:j	()Lfn;
    //   729: ldc 7
    //   731: invokevirtual 406	java/lang/String:length	()I
    //   734: pop2
    //   735: invokestatic 386	fn:ae	()V
    //   738: return
    //   739: invokestatic 329	dl:ae	()Ldl;
    //   742: getstatic 206	aw:z	Lj;
    //   745: getfield 253	j:b	Lek;
    //   748: invokevirtual 363	ek:a	()Ljava/lang/String;
    //   751: getstatic 206	aw:z	Lj;
    //   754: getfield 252	j:a	Lek;
    //   757: invokevirtual 363	ek:a	()Ljava/lang/String;
    //   760: invokevirtual 322	dl:a	(Ljava/lang/String;Ljava/lang/String;)V
    //   763: invokestatic 288	aw:p	()V
    //   766: return
    //   767: invokestatic 358	dt:g	()Ldt;
    //   770: getfield 228	dt:bw	Lfc;
    //   773: invokestatic 270	aw:b	(Ljava/lang/Object;)Z
    //   776: ifeq +33 -> 809
    //   779: invokestatic 329	dl:ae	()Ldl;
    //   782: invokestatic 358	dt:g	()Ldt;
    //   785: getfield 228	dt:bw	Lfc;
    //   788: getfield 239	fc:go	Lch;
    //   791: getfield 217	ch:a	I
    //   794: getstatic 127	aw:af	Leu;
    //   797: getfield 235	eu:a	I
    //   800: getstatic 179	aw:cf	[I
    //   803: iconst_2
    //   804: iaload
    //   805: invokevirtual 338	dl:c	(III)V
    //   808: return
    //   809: invokestatic 329	dl:ae	()Ldl;
    //   812: getstatic 179	aw:cf	[I
    //   815: iconst_2
    //   816: iaload
    //   817: getstatic 127	aw:af	Leu;
    //   820: getfield 235	eu:a	I
    //   823: getstatic 179	aw:cf	[I
    //   826: iconst_2
    //   827: iaload
    //   828: invokevirtual 338	dl:c	(III)V
    //   831: return
    //   832: aload_2
    //   833: checkcast 80	java/lang/Short
    //   836: invokevirtual 403	java/lang/Short:shortValue	()S
    //   839: istore_1
    //   840: invokestatic 329	dl:ae	()Ldl;
    //   843: iload_1
    //   844: getstatic 135	aw:ao	Lbr;
    //   847: getfield 209	br:a	Lek;
    //   850: invokevirtual 363	ek:a	()Ljava/lang/String;
    //   853: invokevirtual 324	dl:a	(SLjava/lang/String;)V
    //   856: invokestatic 288	aw:p	()V
    //   859: return
    //   860: aload_2
    //   861: checkcast 80	java/lang/Short
    //   864: invokevirtual 403	java/lang/Short:shortValue	()S
    //   867: istore_1
    //   868: invokestatic 329	dl:ae	()Ldl;
    //   871: iload_1
    //   872: invokevirtual 339	dl:c	(S)V
    //   875: invokestatic 389	fn:j	()Lfn;
    //   878: invokevirtual 387	fn:ai	()V
    //   881: return
    //   882: aload_2
    //   883: checkcast 31	[Ljava/lang/String;
    //   886: astore_2
    //   887: invokestatic 358	dt:g	()Ldt;
    //   890: getfield 228	dt:bw	Lfc;
    //   893: invokestatic 265	aw:a	(Ljava/lang/Object;)Z
    //   896: ifeq +4 -> 900
    //   899: return
    //   900: new 79	java/lang/Integer
    //   903: dup
    //   904: getstatic 127	aw:af	Leu;
    //   907: getfield 235	eu:a	I
    //   910: invokespecial 399	java/lang/Integer:<init>	(I)V
    //   913: astore_3
    //   914: aload_2
    //   915: arraylength
    //   916: getstatic 179	aw:cf	[I
    //   919: iconst_0
    //   920: iaload
    //   921: invokestatic 280	aw:g	(II)Z
    //   924: ifeq +53 -> 977
    //   927: ldc 7
    //   929: getstatic 179	aw:cf	[I
    //   932: iconst_0
    //   933: iaload
    //   934: invokestatic 358	dt:g	()Ldt;
    //   937: getfield 228	dt:bw	Lfc;
    //   940: invokestatic 392	g:a	(Ljava/lang/String;ILdt;)Lg;
    //   943: ldc 7
    //   945: invokevirtual 406	java/lang/String:length	()I
    //   948: pop2
    //   949: invokestatic 329	dl:ae	()Ldl;
    //   952: invokestatic 358	dt:g	()Ldt;
    //   955: getfield 228	dt:bw	Lfc;
    //   958: getfield 239	fc:go	Lch;
    //   961: getfield 217	ch:a	I
    //   964: aload_3
    //   965: invokevirtual 400	java/lang/Integer:intValue	()I
    //   968: getstatic 179	aw:cf	[I
    //   971: iconst_2
    //   972: iaload
    //   973: invokevirtual 338	dl:c	(III)V
    //   976: return
    //   977: new 51	ci
    //   980: dup
    //   981: invokespecial 310	ci:<init>	()V
    //   984: astore 4
    //   986: getstatic 179	aw:cf	[I
    //   989: iconst_2
    //   990: iaload
    //   991: istore_1
    //   992: iload_1
    //   993: aload_2
    //   994: arraylength
    //   995: getstatic 179	aw:cf	[I
    //   998: iconst_0
    //   999: iaload
    //   1000: isub
    //   1001: invokestatic 278	aw:f	(II)Z
    //   1004: ifeq +48 -> 1052
    //   1007: aload 4
    //   1009: new 42	bb
    //   1012: dup
    //   1013: aload_2
    //   1014: iload_1
    //   1015: getstatic 179	aw:cf	[I
    //   1018: iconst_0
    //   1019: iaload
    //   1020: iadd
    //   1021: aaload
    //   1022: getstatic 200	aw:t	Law;
    //   1025: getstatic 179	aw:cf	[I
    //   1028: bipush 54
    //   1030: iaload
    //   1031: aload_3
    //   1032: invokespecial 293	bb:<init>	(Ljava/lang/String;Lay;ILjava/lang/Object;)V
    //   1035: invokevirtual 311	ci:addElement	(Ljava/lang/Object;)V
    //   1038: iinc 1 1
    //   1041: ldc 7
    //   1043: invokevirtual 406	java/lang/String:length	()I
    //   1046: pop
    //   1047: aconst_null
    //   1048: ifnull -56 -> 992
    //   1051: return
    //   1052: getstatic 127	aw:af	Leu;
    //   1055: aload 4
    //   1057: invokevirtual 371	eu:a	(Lci;)V
    //   1060: return
    //   1061: aload_2
    //   1062: checkcast 79	java/lang/Integer
    //   1065: invokevirtual 400	java/lang/Integer:intValue	()I
    //   1068: istore_1
    //   1069: ldc 7
    //   1071: getstatic 179	aw:cf	[I
    //   1074: iconst_0
    //   1075: iaload
    //   1076: invokestatic 358	dt:g	()Ldt;
    //   1079: getfield 228	dt:bw	Lfc;
    //   1082: invokestatic 392	g:a	(Ljava/lang/String;ILdt;)Lg;
    //   1085: ldc 7
    //   1087: invokevirtual 406	java/lang/String:length	()I
    //   1090: pop2
    //   1091: invokestatic 329	dl:ae	()Ldl;
    //   1094: invokestatic 358	dt:g	()Ldt;
    //   1097: getfield 228	dt:bw	Lfc;
    //   1100: getfield 239	fc:go	Lch;
    //   1103: getfield 217	ch:a	I
    //   1106: iload_1
    //   1107: getstatic 127	aw:af	Leu;
    //   1110: getfield 235	eu:a	I
    //   1113: invokevirtual 338	dl:c	(III)V
    //   1116: return
    //   1117: ldc 7
    //   1119: getstatic 179	aw:cf	[I
    //   1122: iconst_0
    //   1123: iaload
    //   1124: invokestatic 358	dt:g	()Ldt;
    //   1127: getfield 228	dt:bw	Lfc;
    //   1130: invokestatic 392	g:a	(Ljava/lang/String;ILdt;)Lg;
    //   1133: ldc 7
    //   1135: invokevirtual 406	java/lang/String:length	()I
    //   1138: pop2
    //   1139: invokestatic 329	dl:ae	()Ldl;
    //   1142: invokestatic 358	dt:g	()Ldt;
    //   1145: getfield 228	dt:bw	Lfc;
    //   1148: getfield 239	fc:go	Lch;
    //   1151: getfield 217	ch:a	I
    //   1154: getstatic 127	aw:af	Leu;
    //   1157: getfield 235	eu:a	I
    //   1160: getstatic 179	aw:cf	[I
    //   1163: iconst_2
    //   1164: iaload
    //   1165: invokevirtual 338	dl:c	(III)V
    //   1168: return
    //   1169: getstatic 109	an:mh	Ljava/lang/String;
    //   1172: invokestatic 267	aw:a	(Ljava/lang/String;)V
    //   1175: return
    //   1176: getstatic 103	an:ho	Ljava/lang/String;
    //   1179: invokestatic 267	aw:a	(Ljava/lang/String;)V
    //   1182: return
    //   1183: getstatic 100	an:gg	Ljava/lang/String;
    //   1186: invokestatic 267	aw:a	(Ljava/lang/String;)V
    //   1189: return
    //   1190: getstatic 98	an:es	Ljava/lang/String;
    //   1193: invokestatic 267	aw:a	(Ljava/lang/String;)V
    //   1196: return
    //   1197: getstatic 107	an:kc	Ljava/lang/String;
    //   1200: invokestatic 267	aw:a	(Ljava/lang/String;)V
    //   1203: return
    //   1204: getstatic 96	an:be	Ljava/lang/String;
    //   1207: invokestatic 267	aw:a	(Ljava/lang/String;)V
    //   1210: return
    //   1211: getstatic 135	aw:ao	Lbr;
    //   1214: getfield 209	br:a	Lek;
    //   1217: invokevirtual 363	ek:a	()Ljava/lang/String;
    //   1220: dup
    //   1221: astore_1
    //   1222: ldc 7
    //   1224: invokevirtual 404	java/lang/String:equals	(Ljava/lang/Object;)Z
    //   1227: invokestatic 275	aw:e	(I)Z
    //   1230: ifeq +4 -> 1234
    //   1233: return
    //   1234: invokestatic 329	dl:ae	()Ldl;
    //   1237: aload_1
    //   1238: aload_2
    //   1239: checkcast 79	java/lang/Integer
    //   1242: invokevirtual 400	java/lang/Integer:intValue	()I
    //   1245: invokevirtual 335	dl:b	(Ljava/lang/String;I)V
    //   1248: getstatic 108	an:ki	Ljava/lang/String;
    //   1251: invokestatic 271	aw:b	(Ljava/lang/String;)V
    //   1254: return
    //   1255: aload_2
    //   1256: checkcast 79	java/lang/Integer
    //   1259: invokevirtual 400	java/lang/Integer:intValue	()I
    //   1262: istore_1
    //   1263: invokestatic 288	aw:p	()V
    //   1266: invokestatic 329	dl:ae	()Ldl;
    //   1269: iload_1
    //   1270: invokevirtual 349	dl:p	(I)V
    //   1273: return
    //   1274: aload_2
    //   1275: checkcast 79	java/lang/Integer
    //   1278: invokevirtual 400	java/lang/Integer:intValue	()I
    //   1281: istore_1
    //   1282: invokestatic 288	aw:p	()V
    //   1285: invokestatic 329	dl:ae	()Ldl;
    //   1288: iload_1
    //   1289: invokevirtual 327	dl:aa	(I)V
    //   1292: return
    //   1293: getstatic 135	aw:ao	Lbr;
    //   1296: getfield 209	br:a	Lek;
    //   1299: invokevirtual 363	ek:a	()Ljava/lang/String;
    //   1302: astore_1
    //   1303: invokestatic 288	aw:p	()V
    //   1306: aload_1
    //   1307: ldc 7
    //   1309: invokevirtual 404	java/lang/String:equals	(Ljava/lang/Object;)Z
    //   1312: invokestatic 284	aw:i	(I)Z
    //   1315: ifeq +695 -> 2010
    //   1318: invokestatic 329	dl:ae	()Ldl;
    //   1321: aload_1
    //   1322: invokevirtual 334	dl:b	(Ljava/lang/String;)V
    //   1325: return
    //   1326: getstatic 135	aw:ao	Lbr;
    //   1329: getfield 209	br:a	Lek;
    //   1332: invokevirtual 363	ek:a	()Ljava/lang/String;
    //   1335: astore_1
    //   1336: invokestatic 288	aw:p	()V
    //   1339: aload_1
    //   1340: ldc 7
    //   1342: invokevirtual 404	java/lang/String:equals	(Ljava/lang/Object;)Z
    //   1345: invokestatic 284	aw:i	(I)Z
    //   1348: ifeq +662 -> 2010
    //   1351: aload_1
    //   1352: invokestatic 401	java/lang/Integer:parseInt	(Ljava/lang/String;)I
    //   1355: istore_1
    //   1356: invokestatic 358	dt:g	()Ldt;
    //   1359: getfield 227	dt:a	I
    //   1362: iload_1
    //   1363: invokestatic 286	aw:j	(II)Z
    //   1366: ifeq +18 -> 1384
    //   1369: iload_1
    //   1370: invokestatic 273	aw:d	(I)Z
    //   1373: ifeq +11 -> 1384
    //   1376: invokestatic 329	dl:ae	()Ldl;
    //   1379: iload_1
    //   1380: invokevirtual 352	dl:y	(I)V
    //   1383: return
    //   1384: getstatic 115	an:pg	Ljava/lang/String;
    //   1387: getstatic 179	aw:cf	[I
    //   1390: bipush 30
    //   1392: iaload
    //   1393: getstatic 208	ax:l	Lax;
    //   1396: invokestatic 255	ae:a	(Ljava/lang/String;ILax;)V
    //   1399: return
    //   1400: ldc 7
    //   1402: invokevirtual 406	java/lang/String:length	()I
    //   1405: pop2
    //   1406: return
    //   1407: getstatic 135	aw:ao	Lbr;
    //   1410: getfield 209	br:a	Lek;
    //   1413: invokevirtual 363	ek:a	()Ljava/lang/String;
    //   1416: astore_1
    //   1417: invokestatic 288	aw:p	()V
    //   1420: aload_1
    //   1421: ldc 7
    //   1423: invokevirtual 404	java/lang/String:equals	(Ljava/lang/Object;)Z
    //   1426: invokestatic 284	aw:i	(I)Z
    //   1429: ifeq +581 -> 2010
    //   1432: aload_1
    //   1433: invokestatic 401	java/lang/Integer:parseInt	(Ljava/lang/String;)I
    //   1436: dup
    //   1437: istore_1
    //   1438: invokestatic 279	aw:g	(I)Z
    //   1441: ifeq +4 -> 1445
    //   1444: return
    //   1445: invokestatic 329	dl:ae	()Ldl;
    //   1448: iload_1
    //   1449: invokevirtual 353	dl:z	(I)V
    //   1452: return
    //   1453: ldc 7
    //   1455: invokevirtual 406	java/lang/String:length	()I
    //   1458: pop2
    //   1459: return
    //   1460: aload_2
    //   1461: checkcast 81	java/lang/String
    //   1464: invokestatic 401	java/lang/Integer:parseInt	(Ljava/lang/String;)I
    //   1467: istore_1
    //   1468: getstatic 135	aw:ao	Lbr;
    //   1471: getfield 209	br:a	Lek;
    //   1474: invokevirtual 363	ek:a	()Ljava/lang/String;
    //   1477: invokestatic 401	java/lang/Integer:parseInt	(Ljava/lang/String;)I
    //   1480: istore_2
    //   1481: aconst_null
    //   1482: putstatic 201	aw:u	Lfj;
    //   1485: iload_2
    //   1486: invokestatic 277	aw:f	(I)Z
    //   1489: ifeq +30 -> 1519
    //   1492: iload_2
    //   1493: invokestatic 358	dt:g	()Ldt;
    //   1496: getfield 231	dt:w	[Lao;
    //   1499: iload_1
    //   1500: aaload
    //   1501: getfield 118	ao:u	I
    //   1504: invokestatic 278	aw:f	(II)Z
    //   1507: ifeq +12 -> 1519
    //   1510: invokestatic 329	dl:ae	()Ldl;
    //   1513: iload_1
    //   1514: iload_2
    //   1515: invokevirtual 345	dl:j	(II)V
    //   1518: return
    //   1519: getstatic 102	an:hd	Ljava/lang/String;
    //   1522: invokestatic 267	aw:a	(Ljava/lang/String;)V
    //   1525: return
    //   1526: getstatic 135	aw:ao	Lbr;
    //   1529: getfield 209	br:a	Lek;
    //   1532: getstatic 179	aw:cf	[I
    //   1535: bipush 20
    //   1537: iaload
    //   1538: invokevirtual 364	ek:a	(I)V
    //   1541: getstatic 135	aw:ao	Lbr;
    //   1544: getstatic 117	an:rt	Ljava/lang/String;
    //   1547: new 42	bb
    //   1550: dup
    //   1551: getstatic 114	an:o	Ljava/lang/String;
    //   1554: getstatic 200	aw:t	Law;
    //   1557: getstatic 179	aw:cf	[I
    //   1560: bipush 55
    //   1562: iaload
    //   1563: aconst_null
    //   1564: invokespecial 293	bb:<init>	(Ljava/lang/String;Lay;ILjava/lang/Object;)V
    //   1567: getstatic 179	aw:cf	[I
    //   1570: iconst_0
    //   1571: iaload
    //   1572: invokevirtual 297	br:a	(Ljava/lang/String;Lbb;I)V
    //   1575: return
    //   1576: getstatic 135	aw:ao	Lbr;
    //   1579: getfield 209	br:a	Lek;
    //   1582: invokevirtual 363	ek:a	()Ljava/lang/String;
    //   1585: astore_1
    //   1586: invokestatic 288	aw:p	()V
    //   1589: invokestatic 329	dl:ae	()Ldl;
    //   1592: aload_1
    //   1593: invokevirtual 407	java/lang/String:trim	()Ljava/lang/String;
    //   1596: invokestatic 401	java/lang/Integer:parseInt	(Ljava/lang/String;)I
    //   1599: invokevirtual 347	dl:o	(I)V
    //   1602: return
    //   1603: ldc 7
    //   1605: invokevirtual 406	java/lang/String:length	()I
    //   1608: pop2
    //   1609: return
    //   1610: getstatic 206	aw:z	Lj;
    //   1613: getfield 253	j:b	Lek;
    //   1616: invokevirtual 363	ek:a	()Ljava/lang/String;
    //   1619: invokevirtual 407	java/lang/String:trim	()Ljava/lang/String;
    //   1622: astore_1
    //   1623: getstatic 206	aw:z	Lj;
    //   1626: getfield 252	j:a	Lek;
    //   1629: invokevirtual 363	ek:a	()Ljava/lang/String;
    //   1632: invokevirtual 407	java/lang/String:trim	()Ljava/lang/String;
    //   1635: astore_2
    //   1636: invokestatic 288	aw:p	()V
    //   1639: aload_1
    //   1640: invokevirtual 406	java/lang/String:length	()I
    //   1643: getstatic 179	aw:cf	[I
    //   1646: bipush 20
    //   1648: iaload
    //   1649: invokestatic 286	aw:j	(II)Z
    //   1652: ifeq +84 -> 1736
    //   1655: aload_2
    //   1656: invokevirtual 406	java/lang/String:length	()I
    //   1659: getstatic 179	aw:cf	[I
    //   1662: bipush 20
    //   1664: iaload
    //   1665: invokestatic 286	aw:j	(II)Z
    //   1668: ifeq +68 -> 1736
    //   1671: aload_1
    //   1672: invokestatic 401	java/lang/Integer:parseInt	(Ljava/lang/String;)I
    //   1675: istore_1
    //   1676: aload_2
    //   1677: invokestatic 401	java/lang/Integer:parseInt	(Ljava/lang/String;)I
    //   1680: istore_2
    //   1681: iload_1
    //   1682: getstatic 179	aw:cf	[I
    //   1685: bipush 56
    //   1687: iaload
    //   1688: invokestatic 286	aw:j	(II)Z
    //   1691: ifeq +25 -> 1716
    //   1694: iload_2
    //   1695: getstatic 179	aw:cf	[I
    //   1698: bipush 56
    //   1700: iaload
    //   1701: invokestatic 286	aw:j	(II)Z
    //   1704: ifeq +12 -> 1716
    //   1707: invokestatic 329	dl:ae	()Ldl;
    //   1710: iload_1
    //   1711: iload_2
    //   1712: invokevirtual 342	dl:f	(II)V
    //   1715: return
    //   1716: getstatic 106	an:k	Ljava/lang/String;
    //   1719: invokestatic 267	aw:a	(Ljava/lang/String;)V
    //   1722: return
    //   1723: ldc 7
    //   1725: invokevirtual 406	java/lang/String:length	()I
    //   1728: pop2
    //   1729: getstatic 110	an:mj	Ljava/lang/String;
    //   1732: invokestatic 267	aw:a	(Ljava/lang/String;)V
    //   1735: return
    //   1736: getstatic 104	an:hw	Ljava/lang/String;
    //   1739: invokestatic 267	aw:a	(Ljava/lang/String;)V
    //   1742: return
    //   1743: getstatic 135	aw:ao	Lbr;
    //   1746: getfield 209	br:a	Lek;
    //   1749: invokevirtual 363	ek:a	()Ljava/lang/String;
    //   1752: astore_1
    //   1753: invokestatic 288	aw:p	()V
    //   1756: getstatic 116	an:qw	Ljava/lang/String;
    //   1759: getstatic 179	aw:cf	[I
    //   1762: bipush 57
    //   1764: iaload
    //   1765: aload_1
    //   1766: getstatic 179	aw:cf	[I
    //   1769: bipush 51
    //   1771: iaload
    //   1772: aconst_null
    //   1773: invokestatic 268	aw:a	(Ljava/lang/String;ILjava/lang/Object;ILjava/lang/Object;)V
    //   1776: return
    //   1777: ldc 7
    //   1779: invokevirtual 406	java/lang/String:length	()I
    //   1782: pop2
    //   1783: getstatic 105	an:jr	Ljava/lang/String;
    //   1786: getstatic 179	aw:cf	[I
    //   1789: bipush 30
    //   1791: iaload
    //   1792: getstatic 208	ax:l	Lax;
    //   1795: invokestatic 255	ae:a	(Ljava/lang/String;ILax;)V
    //   1798: return
    //   1799: aload_2
    //   1800: checkcast 61	dt
    //   1803: astore_1
    //   1804: invokestatic 288	aw:p	()V
    //   1807: invokestatic 329	dl:ae	()Ldl;
    //   1810: aload_1
    //   1811: getfield 230	dt:fy	I
    //   1814: invokevirtual 351	dl:w	(I)V
    //   1817: return
    //   1818: aload_2
    //   1819: checkcast 61	dt
    //   1822: astore_1
    //   1823: invokestatic 288	aw:p	()V
    //   1826: invokestatic 329	dl:ae	()Ldl;
    //   1829: aload_1
    //   1830: getfield 230	dt:fy	I
    //   1833: invokevirtual 344	dl:j	(I)V
    //   1836: return
    //   1837: invokestatic 329	dl:ae	()Ldl;
    //   1840: invokevirtual 330	dl:ai	()V
    //   1843: return
    //   1844: getstatic 135	aw:ao	Lbr;
    //   1847: getfield 209	br:a	Lek;
    //   1850: invokevirtual 363	ek:a	()Ljava/lang/String;
    //   1853: astore_2
    //   1854: invokestatic 288	aw:p	()V
    //   1857: aload_2
    //   1858: ldc 7
    //   1860: invokevirtual 404	java/lang/String:equals	(Ljava/lang/Object;)Z
    //   1863: invokestatic 275	aw:e	(I)Z
    //   1866: ifeq +10 -> 1876
    //   1869: getstatic 99	an:fa	Ljava/lang/String;
    //   1872: invokestatic 267	aw:a	(Ljava/lang/String;)V
    //   1875: return
    //   1876: invokestatic 329	dl:ae	()Ldl;
    //   1879: aload_2
    //   1880: invokevirtual 343	dl:f	(Ljava/lang/String;)V
    //   1883: return
    //   1884: aload_2
    //   1885: checkcast 80	java/lang/Short
    //   1888: invokevirtual 403	java/lang/Short:shortValue	()S
    //   1891: istore_1
    //   1892: invokestatic 329	dl:ae	()Ldl;
    //   1895: iload_1
    //   1896: getstatic 135	aw:ao	Lbr;
    //   1899: getfield 209	br:a	Lek;
    //   1902: invokevirtual 363	ek:a	()Ljava/lang/String;
    //   1905: invokevirtual 336	dl:b	(SLjava/lang/String;)V
    //   1908: invokestatic 288	aw:p	()V
    //   1911: return
    //   1912: getstatic 135	aw:ao	Lbr;
    //   1915: getfield 209	br:a	Lek;
    //   1918: invokevirtual 363	ek:a	()Ljava/lang/String;
    //   1921: astore_1
    //   1922: invokestatic 288	aw:p	()V
    //   1925: aload_1
    //   1926: invokevirtual 406	java/lang/String:length	()I
    //   1929: getstatic 179	aw:cf	[I
    //   1932: bipush 20
    //   1934: iaload
    //   1935: invokestatic 286	aw:j	(II)Z
    //   1938: ifeq +39 -> 1977
    //   1941: aload_1
    //   1942: ldc 7
    //   1944: invokevirtual 404	java/lang/String:equals	(Ljava/lang/Object;)Z
    //   1947: invokestatic 284	aw:i	(I)Z
    //   1950: ifeq +27 -> 1977
    //   1953: invokestatic 329	dl:ae	()Ldl;
    //   1956: aload_1
    //   1957: invokestatic 401	java/lang/Integer:parseInt	(Ljava/lang/String;)I
    //   1960: invokevirtual 333	dl:ap	(I)V
    //   1963: return
    //   1964: ldc 7
    //   1966: invokevirtual 406	java/lang/String:length	()I
    //   1969: pop2
    //   1970: getstatic 110	an:mj	Ljava/lang/String;
    //   1973: invokestatic 267	aw:a	(Ljava/lang/String;)V
    //   1976: return
    //   1977: getstatic 104	an:hw	Ljava/lang/String;
    //   1980: invokestatic 267	aw:a	(Ljava/lang/String;)V
    //   1983: return
    //   1984: invokestatic 288	aw:p	()V
    //   1987: aload_2
    //   1988: checkcast 81	java/lang/String
    //   1991: invokestatic 401	java/lang/Integer:parseInt	(Ljava/lang/String;)I
    //   1994: istore_2
    //   1995: invokestatic 329	dl:ae	()Ldl;
    //   1998: iload_2
    //   1999: invokevirtual 346	dl:m	(I)V
    //   2002: return
    //   2003: ldc 7
    //   2005: invokevirtual 406	java/lang/String:length	()I
    //   2008: pop2
    //   2009: return
    //   2010: return
    // Local variable table:
    //   start	length	slot	name	signature
    //   0	2011	0	this	aw
    //   0	2011	1	paramInt	int
    //   0	2011	2	paramObject	Object
    //   913	119	3	localInteger	Integer
    //   984	72	4	localci	ci
    //   1400	1	5	localException1	Exception
    //   1453	1	6	localException2	Exception
    //   1603	1	7	localException3	Exception
    //   1723	1	8	localException4	Exception
    //   1777	1	9	localException5	Exception
    //   1964	1	10	localException6	Exception
    //   2003	1	11	localException7	Exception
    // Exception table:
    //   from	to	target	type
    //   1351	1383	1400	java/lang/Exception
    //   1384	1399	1400	java/lang/Exception
    //   1432	1444	1453	java/lang/Exception
    //   1445	1452	1453	java/lang/Exception
    //   1589	1602	1603	java/lang/Exception
    //   1671	1715	1723	java/lang/Exception
    //   1716	1722	1723	java/lang/Exception
    //   1756	1776	1777	java/lang/Exception
    //   1953	1963	1964	java/lang/Exception
    //   1984	2002	2003	java/lang/Exception
  }
  
  public final void o()
  {
    x = cf[2];
    this.bd = cf[0];
  }
  
  public aw()
  {
    dm localdm;
    (localdm = dm.d()).setFullScreenMode(cf[0]);
    localdm.c = this;
    b = localdm.c();
    av = localdm.b();
    aq = b / cf[1];
    al = av / cf[1];
    if (i(System.getProperty("microedition.platform").indexOf("RIM")))
    {
      "".length();
      if (null == null) {
        break label109;
      }
      throw null;
    }
    label109:
    aj = cf[2];
    if (e(dm.b.hasPointerEvents()))
    {
      s = cf[0];
      if (j(b, cf[3])) {
        m = cf[0];
      }
      if (f(b, cf[4])) {
        c = cf[0];
      }
      if (j(b, cf[4])) {
        e = cf[0];
      }
    }
    ab = new fd();
    if (h(i1 = df.c("indLanguage")))
    {
      an.dc = cf[2];
      "".length();
      if (null != null) {
        throw null;
      }
    }
    else
    {
      an.dc = i1;
    }
    an.b();
    h = new cv();
    if (g(av, cf[5]))
    {
      en.c = cf[6];
      f.g = cf[7];
    }
    t = this;
    System.gc();
    new en();
    bf[cf[2]] = new Image[cf[7]];
    int i1 = cf[2];
    while (f(i1, cf[7]))
    {
      bf[cf[2]][i1] = c("/bg/bg0" + i1 + ".png");
      "".length();
      if ("   ".length() >= (0x10 ^ 0x14)) {
        throw null;
      }
    }
    bf[cf[0]] = new Image[cf[7]];
    i1 = cf[2];
    while (f(i1, cf[7]))
    {
      bf[cf[0]][i1] = c("/bg/bg1" + i1 + ".png");
      "".length();
      if ((74 + 111 - 160 + 105 ^ 127 + 10 - 71 + 68) == 0) {
        throw null;
      }
    }
    bf[cf[1]] = new Image[cf[7]];
    i1 = cf[2];
    while (f(i1, cf[7]))
    {
      bf[cf[1]][i1] = c("/bg/bg2" + i1 + ".png");
      "".length();
      if ("  ".length() < -" ".length()) {
        throw null;
      }
    }
    bf[cf[8]] = new Image[cf[6]];
    i1 = cf[2];
    while (f(i1, cf[6]))
    {
      bf[cf[8]][i1] = c("/bg/bg3" + i1 + ".png");
      "".length();
      if ((0x77 ^ 0x6B ^ 0x79 ^ 0x61) == ((79 + 118 - 160 + 182 ^ 93 + 73 - 162 + 134) & (0xF2 ^ 0x81 ^ 0x5D ^ 0x7F ^ -" ".length()))) {
        throw null;
      }
    }
    i1 = cf[2];
    while (f(i1, cf[9]))
    {
      bp[i1] = c("/bg/cl" + i1 + ".png");
      "".length();
      if ("  ".length() == " ".length()) {
        throw null;
      }
    }
    az[cf[2]] = c("/bg/sun0.png");
    az[cf[0]] = c("/bg/sun1.png");
    et.g();
    if (i(ag))
    {
      if (a(cc))
      {
        cc = new Image[cf[1]][cf[10]];
        i1 = cf[2];
        while (f(i1, cf[1]))
        {
          int i2 = cf[2];
          while (f(i2, cf[10]))
          {
            cc[i1][i2] = c("/e/d" + i1 + i2 + ".png");
            "".length();
            if (null != null) {
              throw null;
            }
          }
          i1++;
          "".length();
          if (((0x2F ^ 0x64 ^ 0x4C ^ 0x27) & (0x88 ^ 0x99 ^ 0x9A ^ 0xAB ^ -" ".length())) != 0) {
            throw null;
          }
        }
      }
      this.bh = new int[cf[1]];
      this.be = new int[cf[1]];
      this.bq = new int[cf[1]];
      this.bq[cf[2]] = (this.bq[cf[0]] = cf[11]);
    }
    u();
    bx = c("/u/f.png");
    if (e(s))
    {
      i1 = cf[2];
      while (f(i1, cf[1]))
      {
        aa[i1] = c("/hd/bd" + i1 + ".png");
        "".length();
        if ("  ".length() <= 0) {
          throw null;
        }
      }
      aw = cf.a(aa[cf[2]]);
      ay = cf.b(aa[cf[2]]);
      "".length();
      "".length();
      "".length();
      if (-(0x6D ^ 0x69) >= 0) {
        throw null;
      }
    }
    else if (i(df.c("lowGraphic"), cf[0]))
    {
      ag = cf[0];
    }
    dq.d();
    f.c();
    ar = new ca();
  }
  
  private static boolean b(Object paramObject)
  {
    return paramObject != null;
  }
  
  public static boolean a(int paramInt1, int paramInt2, int paramInt3, int paramInt4, ce paramce)
  {
    int i1 = f + paramce.b;
    paramce = paramce.c + o;
    if (((!i(y)) || (e(j))) && (j(i1, paramInt1)) && (g(i1, paramInt1 + paramInt3)) && (j(paramce, paramInt2)) && (g(paramce, paramInt2 + paramInt4))) {
      return cf[0];
    }
    return cf[2];
  }
  
  protected final void d(int paramInt1, int paramInt2)
  {
    y = cf[0];
    as = cf[0];
    bn = System.currentTimeMillis();
    v = paramInt1;
    n = paramInt2;
    f = paramInt1;
    o = paramInt2;
  }
  
  public final boolean a(int paramInt1, int paramInt2, int paramInt3)
  {
    if (e(ag)) {
      return cf[2];
    }
    if (i(paramInt1, cf[0]))
    {
      "".length();
      if (" ".length() != 0) {
        break label95;
      }
      return (0x22 ^ 0x8 ^ 0x4D ^ 0x33) & (66 + 77 - 14 + 19 ^ 10 + 20 - -2 + 160 ^ -" ".length());
    }
    label95:
    paramInt1 = cf[0];
    if (k(this.bq[paramInt1], cf[11])) {
      return cf[2];
    }
    this.bq[paramInt1] = cf[2];
    this.bh[paramInt1] = paramInt2;
    this.be[paramInt1] = paramInt3;
    return cf[0];
  }
  
  public static boolean c(int paramInt1, int paramInt2, int paramInt3, int paramInt4)
  {
    int i1 = f + fn.ad;
    int i2 = fn.dz + o;
    if (((!i(y)) || (e(j))) && (j(i1, paramInt1)) && (g(i1, paramInt1 + paramInt3)) && (j(i2, paramInt2)) && (g(i2, paramInt2 + paramInt4))) {
      return cf[0];
    }
    return cf[2];
  }
  
  public static void b(cf paramcf)
  {
    if (e(d))
    {
      if (h(ap % cf[14], cf[15]))
      {
        paramcf.a(cf[16]);
        "".length();
        if (-"  ".length() < 0) {}
      }
      else
      {
        paramcf.a(cf[2]);
      }
      paramcf.b(cf[2], cf[2], fn.au, fn.et);
      return;
    }
    if ((e(bw)) && (i(ag)) && (b(cb)))
    {
      paramcf.a(cg);
      paramcf.b(cf[2], cf[2], fn.au, by);
      int i1;
      if ((d(q)) && (g(q, cf[0])))
      {
        if (b(cb[cf[2]]))
        {
          i1 = -((fn.ad >> cf[0]) % cf[17]);
          while (f(i1, fn.au))
          {
            paramcf.a(cb[cf[2]], i1, cj, cf[2]);
            i1 += 24;
            "".length();
            if (-(0x50 ^ 0x55) >= 0) {
              return;
            }
          }
        }
        if (b(cb[cf[0]]))
        {
          i1 = -((fn.ad >> cf[1]) % cf[17]);
          while (f(i1, fn.au))
          {
            paramcf.a(cb[cf[0]], i1, bj, cf[2]);
            i1 += 24;
            "".length();
            if (-(0xA7 ^ 0xA3) > 0) {
              return;
            }
          }
        }
        if (b(cb[cf[8]]))
        {
          i1 = -((fn.ad >> cf[9]) % cf[18]);
          while (f(i1, fn.au))
          {
            paramcf.a(cb[cf[8]], i1, bc, cf[2]);
            i1 += 64;
            "".length();
            if ("  ".length() > (0x16 ^ 0x12)) {
              return;
            }
          }
        }
        if (b(br)) {
          paramcf.a(br, bt, bm, cf[8]);
        }
        if (b(ca))
        {
          i1 = cf[2];
          while (f(i1, cf[1]))
          {
            paramcf.a(ca, bz[i1], ce[i1], cf[8]);
            i1++;
            "".length();
            if (-" ".length() == ("   ".length() & ("   ".length() ^ 0xFFFFFFFF))) {
              return;
            }
          }
        }
        if (b(cb[cf[1]]))
        {
          i1 = -((fn.ad >> cf[8]) % cf[19]);
          while (f(i1, fn.au))
          {
            paramcf.a(cb[cf[1]], i1, bs, cf[2]);
            i1 += 192;
            "".length();
            if ((0xAE ^ 0x8D ^ 0x92 ^ 0xB5) <= " ".length()) {
              return;
            }
          }
        }
      }
      else if ((j(q, cf[1])) && (g(q, cf[20])))
      {
        if (b(br)) {
          paramcf.a(br, bt, bm, cf[8]);
        }
        if (b(ca))
        {
          i1 = cf[2];
          while (f(i1, bz.length))
          {
            paramcf.a(ca, bz[i1], ce[i1], cf[8]);
            i1++;
            "".length();
            if ((113 + 75 - 21 + 32 ^ 95 + 50 - 95 + 145) <= " ".length()) {
              return;
            }
          }
        }
        if (k(q, cf[1]))
        {
          if (b(cb[cf[8]]))
          {
            i1 = -((fn.ad >> ci[cf[8]]) % bk[cf[8]]);
            while (f(i1, fn.au))
            {
              paramcf.a(cb[cf[8]], i1, bc, cf[2]);
              i1 += bk[cf[8]];
              "".length();
              if (null != null) {
                return;
              }
            }
          }
          if (b(cb[cf[1]]))
          {
            i1 = -((fn.ad >> ci[cf[1]]) % bk[cf[1]]);
            while (f(i1, fn.au))
            {
              paramcf.a(cb[cf[1]], i1, bs, cf[2]);
              i1 += bk[cf[1]];
              "".length();
              if ((('' + '' - 262 + 185 ^ 82 + 35 - 38 + 76) & ('²' + 58 - 233 + 214 ^ 93 + 31 - -9 + 8 ^ -" ".length())) <= -" ".length()) {
                return;
              }
            }
          }
          if (b(cb[cf[0]]))
          {
            i1 = -((fn.ad >> ci[cf[0]]) % bk[cf[0]]);
            while (f(i1, fn.au))
            {
              paramcf.a(cb[cf[0]], i1, bg, cf[2]);
              i1 += bk[cf[0]];
              "".length();
              if (null != null) {
                return;
              }
            }
          }
          if (b(cb[cf[2]]))
          {
            i1 = -((fn.ad >> ci[cf[2]]) % bk[cf[2]]);
            while (f(i1, fn.au))
            {
              paramcf.a(cb[cf[2]], i1, ch, cf[2]);
              i1 += bk[cf[2]];
              "".length();
              if (-" ".length() > 0) {
                return;
              }
            }
          }
        }
      }
      else if ((j(q, cf[15])) && (g(q, cf[21])))
      {
        paramcf.a(cg);
        paramcf.b(cf[2], cf[2], fn.au, fn.et);
        if ((k(q, cf[22])) && (b(cb[cf[8]])))
        {
          i1 = -((fn.ad >> ci[cf[8]]) % bk[cf[8]]);
          while (f(i1, fn.au))
          {
            if ((k(q, cf[23])) && (k(q, cf[24])))
            {
              paramcf.a(cb[cf[8]], i1, bc, cf[2]);
              "".length();
              if (" ".length() > 0) {}
            }
            else
            {
              paramcf.a(cb[cf[8]], i1, fn.et - cf.b(cb[cf[8]]), cf[2]);
            }
            i1 += bk[cf[8]];
            "".length();
            if (-" ".length() >= 0) {
              return;
            }
          }
        }
        if ((k(q, cf[22])) && (k(q, cf[23])) && (k(q, cf[24])) && (b(cb[cf[1]]))) {
          if (i(et.o, cf[25]))
          {
            paramcf.a(cb[cf[1]], fn.au, bs, cf[2]);
            "".length();
            if (((0x1 ^ 0x5D) & (0x64 ^ 0x38 ^ 0xFFFFFFFF)) == 0) {}
          }
          else
          {
            i1 = -((fn.ad >> ci[cf[1]]) % bk[cf[1]]);
            while (f(i1, fn.au))
            {
              if (i(q, cf[26]))
              {
                paramcf.a(cb[cf[1]], i1, bs + cf[24], cf[2]);
                "".length();
                if ((0x94 ^ 0x90) >= (0x4D ^ 0x49)) {}
              }
              else
              {
                paramcf.a(cb[cf[1]], i1, bs, cf[2]);
              }
              i1 += bk[cf[1]];
              "".length();
              if (-" ".length() != -" ".length()) {
                return;
              }
            }
          }
        }
        if ((k(q, cf[23])) && (k(q, cf[24])) && (b(cb[cf[0]])) && (k(et.o, cf[27])))
        {
          i1 = -((fn.ad >> ci[cf[0]]) % bk[cf[0]]);
          while (f(i1, fn.au))
          {
            paramcf.a(cb[cf[0]], i1, bg, cf[2]);
            i1 += bk[cf[0]];
            "".length();
            if (" ".length() == -" ".length()) {
              return;
            }
          }
        }
        if ((!k(et.o, cf[25])) || (i(et.o, cf[28])))
        {
          paramcf.a(cf[29]);
          paramcf.b(cf[2], ch + cf[30], fn.au, fn.et);
        }
        if (b(cb[cf[2]]))
        {
          i1 = -((fn.ad >> ci[cf[2]]) % bk[cf[2]]);
          while (f(i1, fn.au))
          {
            paramcf.a(cb[cf[2]], i1, ch, cf[2]);
            i1 += bk[cf[2]];
            "".length();
            if (null != null) {
              return;
            }
          }
        }
        if (b(ca))
        {
          if ((k(q, cf[31])) && (k(q, cf[6])))
          {
            i1 = cf[2];
            while (f(i1, cf[1]))
            {
              paramcf.a(ca, bz[i1], ce[i1], cf[8]);
              i1++;
              "".length();
              if (" ".length() == 0) {
                return;
              }
            }
            return;
          }
          i1 = cf[2];
          while (f(i1, cf[1]))
          {
            paramcf.a(ca, bz[i1], ce[i1] - cf[32], cf[8]);
            i1++;
            "".length();
            if ("  ".length() != "  ".length()) {
              return;
            }
          }
          return;
        }
      }
      return;
    }
    paramcf.a(cg);
    paramcf.b(cf[2], cf[2], fn.au, fn.et);
  }
  
  public final void a(String paramString1, String paramString2, String paramString3, String paramString4)
  {
    h.a(paramString4, new bb(paramString1, this, cf[52], paramString3), null, new bb(paramString2, this, cf[51], null));
    u = h;
  }
  
  public static boolean e(int paramInt1, int paramInt2)
  {
    if ((j(paramInt1, fn.ad)) && (g(paramInt1, fn.ad + fn.au)) && (j(paramInt2, fn.dz)) && (g(paramInt2, fn.dz + fn.et + cf[45]))) {
      return cf[0];
    }
    return cf[2];
  }
  
  private static boolean h(int paramInt)
  {
    return paramInt < 0;
  }
  
  public static void p()
  {
    ao.a.a(cf[50]);
    z.b.a(cf[50]);
    z.a.a(cf[50]);
    u = null;
  }
  
  public static boolean q()
  {
    if (d(a(System.currentTimeMillis() - bn, 800L))) {
      return cf[0];
    }
    return cf[2];
  }
  
  private static boolean i(int paramInt)
  {
    return paramInt == 0;
  }
  
  private static boolean k(int paramInt1, int paramInt2)
  {
    return paramInt1 != paramInt2;
  }
  
  public static void r() {}
}


/* Location:              C:\Users\Admin\OneDrive\Documents\NSOv2_test.jar!\aw.class
 * Java compiler version: 1 (45.3)
 * JD-Core Version:       0.7.1
 */