public final class bi
  extends r
{
  private long w = 0L;
  private static int[] x;
  private static long y;
  private boolean z = x[0];
  public static r v;
  
  private static boolean c(int paramInt1, int paramInt2)
  {
    return paramInt1 <= paramInt2;
  }
  
  private static boolean d(int paramInt1, int paramInt2)
  {
    return paramInt1 != paramInt2;
  }
  
  private static void q()
  {
    x = new int[11];
    x[0] = ((0x6B ^ 0x32) & (0xD7 ^ 0x8E ^ 0xFFFFFFFF));
    x[1] = (-" ".length());
    x[2] = (0x4F ^ 0x16 ^ 0xB9 ^ 0xA6);
    x[3] = (-(0xBE27 & 0x5BDB) & 0xDFFE & 0x3FDF);
    x[4] = (0xC697 & 0x3B78);
    x[5] = (0x5C ^ 0x45 ^ 0x87 ^ 0x94);
    x[6] = " ".length();
    x[7] = (34 + '³' - 72 + 39 ^ 121 + 81 - 194 + 126);
    x[8] = "  ".length();
    x[9] = "   ".length();
    x[10] = (0xB ^ 0xD);
  }
  
  private static boolean d(int paramInt)
  {
    return paramInt > 0;
  }
  
  private static boolean e(int paramInt)
  {
    return paramInt <= 0;
  }
  
  public static void c()
  {
    q();
    y = 0L;
  }
  
  static
  {
    cs.a(160);
    c();
  }
  
  /* Error */
  public final void b()
  {
    // Byte code:
    //   0: invokestatic 92	dt:g	()Ldt;
    //   3: getfield 50	dt:ba	J
    //   6: lconst_0
    //   7: invokestatic 65	bi:a	(JJ)I
    //   10: invokestatic 69	bi:d	(I)Z
    //   13: ifeq +29 -> 42
    //   16: invokestatic 92	dt:g	()Ldt;
    //   19: getfield 50	dt:ba	J
    //   22: ldc 1
    //   24: invokevirtual 97	java/lang/String:length	()I
    //   27: pop
    //   28: ldc 2
    //   30: invokevirtual 97	java/lang/String:length	()I
    //   33: ldc 2
    //   35: invokevirtual 97	java/lang/String:length	()I
    //   38: if_icmpeq +10 -> 48
    //   41: return
    //   42: invokestatic 92	dt:g	()Ldt;
    //   45: getfield 51	dt:by	J
    //   48: ldc2_w 27
    //   51: lmul
    //   52: getstatic 59	fn:y	[J
    //   55: invokestatic 92	dt:g	()Ldt;
    //   58: getfield 49	dt:ap	I
    //   61: laload
    //   62: ldiv
    //   63: lstore_1
    //   64: invokestatic 92	dt:g	()Ldt;
    //   67: getfield 50	dt:ba	J
    //   70: lconst_0
    //   71: invokestatic 65	bi:a	(JJ)I
    //   74: invokestatic 69	bi:d	(I)Z
    //   77: ifeq +19 -> 96
    //   80: lload_1
    //   81: invokestatic 96	java/lang/Math:abs	(J)J
    //   84: ldc2_w 25
    //   87: invokestatic 65	bi:a	(JJ)I
    //   90: invokestatic 69	bi:d	(I)Z
    //   93: ifeq +76 -> 169
    //   96: invokestatic 92	dt:g	()Ldt;
    //   99: getfield 50	dt:ba	J
    //   102: lconst_0
    //   103: invokestatic 65	bi:a	(JJ)I
    //   106: invokestatic 71	bi:e	(I)Z
    //   109: ifeq +17 -> 126
    //   112: lload_1
    //   113: invokestatic 96	java/lang/Math:abs	(J)J
    //   116: lconst_0
    //   117: invokestatic 65	bi:a	(JJ)I
    //   120: invokestatic 75	bi:g	(I)Z
    //   123: ifeq +46 -> 169
    //   126: invokestatic 86	dl:ae	()Ldl;
    //   129: getstatic 39	bi:x	[I
    //   132: iconst_0
    //   133: iaload
    //   134: invokevirtual 87	dl:x	(I)V
    //   137: ldc 7
    //   139: invokestatic 94	fn:a	(Ljava/lang/String;)V
    //   142: getstatic 37	bi:v	Lr;
    //   145: invokestatic 66	bi:a	(Ljava/lang/Object;)Z
    //   148: ifeq +17 -> 165
    //   151: invokestatic 83	cn:z	()V
    //   154: getstatic 37	bi:v	Lr;
    //   157: putstatic 43	dn:ac	Lr;
    //   160: aconst_null
    //   161: putstatic 37	bi:v	Lr;
    //   164: return
    //   165: invokestatic 90	dn:o	()V
    //   168: return
    //   169: invokestatic 92	dt:g	()Ldt;
    //   172: getfield 55	dt:g	B
    //   175: getstatic 39	bi:x	[I
    //   178: iconst_5
    //   179: iaload
    //   180: invokestatic 68	bi:c	(II)Z
    //   183: ifeq +482 -> 665
    //   186: aload_0
    //   187: getfield 41	bi:z	Z
    //   190: invokestatic 77	bi:h	(I)Z
    //   193: ifeq +472 -> 665
    //   196: invokestatic 105	r:k	()Z
    //   199: invokestatic 73	bi:f	(I)Z
    //   202: ifeq +26 -> 228
    //   205: getstatic 39	bi:x	[I
    //   208: bipush 6
    //   210: iaload
    //   211: invokestatic 104	r:a	(Z)V
    //   214: ldc2_w 33
    //   217: invokestatic 99	java/lang/Thread:sleep	(J)V
    //   220: return
    //   221: ldc 1
    //   223: invokevirtual 97	java/lang/String:length	()I
    //   226: pop2
    //   227: return
    //   228: getstatic 57	et:o	S
    //   231: getstatic 48	dn:v	I
    //   234: invokestatic 76	bi:g	(II)Z
    //   237: ifeq +407 -> 644
    //   240: getstatic 56	et:b	B
    //   243: getstatic 45	dn:at	I
    //   246: invokestatic 76	bi:g	(II)Z
    //   249: ifeq +395 -> 644
    //   252: invokestatic 92	dt:g	()Ldt;
    //   255: getfield 53	dt:eg	I
    //   258: getstatic 42	dn:a	I
    //   261: invokestatic 76	bi:g	(II)Z
    //   264: ifeq +278 -> 542
    //   267: invokestatic 92	dt:g	()Ldt;
    //   270: getfield 54	dt:ey	I
    //   273: getstatic 47	dn:u	I
    //   276: invokestatic 76	bi:g	(II)Z
    //   279: ifeq +263 -> 542
    //   282: invokestatic 98	java/lang/System:currentTimeMillis	()J
    //   285: getstatic 40	bi:y	J
    //   288: lsub
    //   289: ldc2_w 29
    //   292: invokestatic 65	bi:a	(JJ)I
    //   295: invokestatic 78	bi:i	(I)Z
    //   298: ifeq +230 -> 528
    //   301: new 9	ci
    //   304: dup
    //   305: invokespecial 80	ci:<init>	()V
    //   308: astore_1
    //   309: getstatic 39	bi:x	[I
    //   312: iconst_0
    //   313: iaload
    //   314: istore_2
    //   315: iload_2
    //   316: getstatic 58	fn:ep	Lci;
    //   319: invokevirtual 100	java/util/Vector:size	()I
    //   322: invokestatic 74	bi:f	(II)Z
    //   325: ifeq +203 -> 528
    //   328: getstatic 58	fn:ep	Lci;
    //   331: iload_2
    //   332: invokevirtual 82	ci:elementAt	(I)Ljava/lang/Object;
    //   335: checkcast 14	dt
    //   338: dup
    //   339: astore_3
    //   340: getfield 52	dt:ef	I
    //   343: invokestatic 69	bi:d	(I)Z
    //   346: ifeq +164 -> 510
    //   349: invokestatic 92	dt:g	()Ldt;
    //   352: getfield 53	dt:eg	I
    //   355: aload_3
    //   356: getfield 53	dt:eg	I
    //   359: isub
    //   360: invokestatic 95	java/lang/Math:abs	(I)I
    //   363: getstatic 39	bi:x	[I
    //   366: bipush 7
    //   368: iaload
    //   369: invokestatic 68	bi:c	(II)Z
    //   372: ifeq +138 -> 510
    //   375: invokestatic 92	dt:g	()Ldt;
    //   378: getfield 54	dt:ey	I
    //   381: aload_3
    //   382: getfield 54	dt:ey	I
    //   385: isub
    //   386: invokestatic 95	java/lang/Math:abs	(I)I
    //   389: getstatic 39	bi:x	[I
    //   392: bipush 7
    //   394: iaload
    //   395: invokestatic 68	bi:c	(II)Z
    //   398: ifeq +112 -> 510
    //   401: aload_1
    //   402: invokevirtual 100	java/util/Vector:size	()I
    //   405: getstatic 64	r:m	Lfy;
    //   408: getfield 60	fy:i	I
    //   411: invokestatic 68	bi:c	(II)Z
    //   414: ifeq +96 -> 510
    //   417: aload_1
    //   418: aload_3
    //   419: invokevirtual 81	ci:addElement	(Ljava/lang/Object;)V
    //   422: aload_3
    //   423: getfield 52	dt:ef	I
    //   426: invokestatic 69	bi:d	(I)Z
    //   429: ifeq +81 -> 510
    //   432: invokestatic 92	dt:g	()Ldt;
    //   435: getfield 53	dt:eg	I
    //   438: aload_3
    //   439: getfield 53	dt:eg	I
    //   442: isub
    //   443: invokestatic 95	java/lang/Math:abs	(I)I
    //   446: getstatic 39	bi:x	[I
    //   449: bipush 7
    //   451: iaload
    //   452: invokestatic 68	bi:c	(II)Z
    //   455: ifeq +55 -> 510
    //   458: invokestatic 92	dt:g	()Ldt;
    //   461: getfield 54	dt:ey	I
    //   464: aload_3
    //   465: getfield 54	dt:ey	I
    //   468: isub
    //   469: invokestatic 95	java/lang/Math:abs	(I)I
    //   472: getstatic 39	bi:x	[I
    //   475: bipush 7
    //   477: iaload
    //   478: invokestatic 68	bi:c	(II)Z
    //   481: ifeq +29 -> 510
    //   484: invokestatic 86	dl:ae	()Ldl;
    //   487: new 9	ci
    //   490: dup
    //   491: invokespecial 80	ci:<init>	()V
    //   494: aload_1
    //   495: getstatic 39	bi:x	[I
    //   498: bipush 8
    //   500: iaload
    //   501: invokevirtual 85	dl:a	(Lci;Lci;I)V
    //   504: invokestatic 98	java/lang/System:currentTimeMillis	()J
    //   507: putstatic 40	bi:y	J
    //   510: iinc 2 1
    //   513: ldc 1
    //   515: invokevirtual 97	java/lang/String:length	()I
    //   518: pop
    //   519: ldc 3
    //   521: invokevirtual 97	java/lang/String:length	()I
    //   524: ifgt -209 -> 315
    //   527: return
    //   528: ldc2_w 27
    //   531: invokestatic 99	java/lang/Thread:sleep	(J)V
    //   534: return
    //   535: ldc 1
    //   537: invokevirtual 97	java/lang/String:length	()I
    //   540: pop2
    //   541: return
    //   542: invokestatic 86	dl:ae	()Ldl;
    //   545: getstatic 39	bi:x	[I
    //   548: bipush 9
    //   550: iaload
    //   551: invokevirtual 87	dl:x	(I)V
    //   554: getstatic 42	dn:a	I
    //   557: getstatic 39	bi:x	[I
    //   560: iconst_1
    //   561: iaload
    //   562: invokestatic 70	bi:d	(II)Z
    //   565: ifeq +47 -> 612
    //   568: getstatic 47	dn:u	I
    //   571: getstatic 39	bi:x	[I
    //   574: iconst_1
    //   575: iaload
    //   576: invokestatic 70	bi:d	(II)Z
    //   579: ifeq +33 -> 612
    //   582: getstatic 42	dn:a	I
    //   585: getstatic 47	dn:u	I
    //   588: invokestatic 91	dt:b	(II)Z
    //   591: ldc 1
    //   593: invokevirtual 97	java/lang/String:length	()I
    //   596: pop2
    //   597: ldc 1
    //   599: invokevirtual 97	java/lang/String:length	()I
    //   602: pop
    //   603: ldc 2
    //   605: invokevirtual 97	java/lang/String:length	()I
    //   608: ifne +22 -> 630
    //   611: return
    //   612: invokestatic 92	dt:g	()Ldt;
    //   615: getfield 53	dt:eg	I
    //   618: putstatic 42	dn:a	I
    //   621: invokestatic 92	dt:g	()Ldt;
    //   624: getfield 54	dt:ey	I
    //   627: putstatic 47	dn:u	I
    //   630: ldc2_w 31
    //   633: invokestatic 99	java/lang/Thread:sleep	(J)V
    //   636: return
    //   637: ldc 1
    //   639: invokevirtual 97	java/lang/String:length	()I
    //   642: pop2
    //   643: return
    //   644: aload_0
    //   645: getstatic 48	dn:v	I
    //   648: getstatic 45	dn:at	I
    //   651: getstatic 39	bi:x	[I
    //   654: iconst_1
    //   655: iaload
    //   656: getstatic 39	bi:x	[I
    //   659: iconst_1
    //   660: iaload
    //   661: invokevirtual 103	r:a	(IIII)V
    //   664: return
    //   665: aload_0
    //   666: invokestatic 92	dt:g	()Ldt;
    //   669: getfield 55	dt:g	B
    //   672: getstatic 39	bi:x	[I
    //   675: bipush 10
    //   677: iaload
    //   678: invokestatic 72	bi:e	(II)Z
    //   681: ifeq +30 -> 711
    //   684: getstatic 39	bi:x	[I
    //   687: bipush 6
    //   689: iaload
    //   690: ldc 1
    //   692: invokevirtual 97	java/lang/String:length	()I
    //   695: pop
    //   696: ldc 2
    //   698: invokevirtual 97	java/lang/String:length	()I
    //   701: ineg
    //   702: ldc 3
    //   704: invokevirtual 97	java/lang/String:length	()I
    //   707: if_icmplt +9 -> 716
    //   710: return
    //   711: getstatic 39	bi:x	[I
    //   714: iconst_0
    //   715: iaload
    //   716: putfield 41	bi:z	Z
    //   719: invokestatic 105	r:k	()Z
    //   722: invokestatic 73	bi:f	(I)Z
    //   725: ifeq +13 -> 738
    //   728: getstatic 39	bi:x	[I
    //   731: bipush 6
    //   733: iaload
    //   734: invokestatic 104	r:a	(Z)V
    //   737: return
    //   738: getstatic 57	et:o	S
    //   741: getstatic 48	dn:v	I
    //   744: invokestatic 76	bi:g	(II)Z
    //   747: ifeq +199 -> 946
    //   750: getstatic 56	et:b	B
    //   753: getstatic 44	dn:an	I
    //   756: invokestatic 76	bi:g	(II)Z
    //   759: ifeq +187 -> 946
    //   762: invokestatic 92	dt:g	()Ldt;
    //   765: getfield 53	dt:eg	I
    //   768: getstatic 42	dn:a	I
    //   771: invokestatic 76	bi:g	(II)Z
    //   774: ifeq +63 -> 837
    //   777: invokestatic 92	dt:g	()Ldt;
    //   780: getfield 54	dt:ey	I
    //   783: getstatic 47	dn:u	I
    //   786: invokestatic 76	bi:g	(II)Z
    //   789: ifeq +48 -> 837
    //   792: invokestatic 89	dn:l	()V
    //   795: invokestatic 98	java/lang/System:currentTimeMillis	()J
    //   798: aload_0
    //   799: getfield 38	bi:w	J
    //   802: lsub
    //   803: ldc2_w 35
    //   806: invokestatic 65	bi:a	(JJ)I
    //   809: invokestatic 78	bi:i	(I)Z
    //   812: ifeq +154 -> 966
    //   815: getstatic 46	dn:e	Ldn;
    //   818: ldc 1
    //   820: invokevirtual 97	java/lang/String:length	()I
    //   823: pop2
    //   824: ldc 6
    //   826: invokestatic 88	dn:d	(Ljava/lang/String;)V
    //   829: aload_0
    //   830: invokestatic 98	java/lang/System:currentTimeMillis	()J
    //   833: putfield 38	bi:w	J
    //   836: return
    //   837: invokestatic 86	dl:ae	()Ldl;
    //   840: getstatic 39	bi:x	[I
    //   843: bipush 9
    //   845: iaload
    //   846: invokevirtual 87	dl:x	(I)V
    //   849: getstatic 42	dn:a	I
    //   852: getstatic 39	bi:x	[I
    //   855: iconst_1
    //   856: iaload
    //   857: invokestatic 70	bi:d	(II)Z
    //   860: ifeq +54 -> 914
    //   863: getstatic 47	dn:u	I
    //   866: getstatic 39	bi:x	[I
    //   869: iconst_1
    //   870: iaload
    //   871: invokestatic 70	bi:d	(II)Z
    //   874: ifeq +40 -> 914
    //   877: getstatic 42	dn:a	I
    //   880: getstatic 47	dn:u	I
    //   883: invokestatic 91	dt:b	(II)Z
    //   886: ldc 1
    //   888: invokevirtual 97	java/lang/String:length	()I
    //   891: pop2
    //   892: ldc 1
    //   894: invokevirtual 97	java/lang/String:length	()I
    //   897: pop
    //   898: ldc 2
    //   900: invokevirtual 97	java/lang/String:length	()I
    //   903: ineg
    //   904: ldc 2
    //   906: invokevirtual 97	java/lang/String:length	()I
    //   909: ineg
    //   910: if_icmpeq +22 -> 932
    //   913: return
    //   914: invokestatic 92	dt:g	()Ldt;
    //   917: getfield 53	dt:eg	I
    //   920: putstatic 42	dn:a	I
    //   923: invokestatic 92	dt:g	()Ldt;
    //   926: getfield 54	dt:ey	I
    //   929: putstatic 47	dn:u	I
    //   932: ldc2_w 31
    //   935: invokestatic 99	java/lang/Thread:sleep	(J)V
    //   938: return
    //   939: ldc 1
    //   941: invokevirtual 97	java/lang/String:length	()I
    //   944: pop2
    //   945: return
    //   946: aload_0
    //   947: getstatic 48	dn:v	I
    //   950: getstatic 44	dn:an	I
    //   953: getstatic 39	bi:x	[I
    //   956: iconst_1
    //   957: iaload
    //   958: getstatic 39	bi:x	[I
    //   961: iconst_1
    //   962: iaload
    //   963: invokevirtual 103	r:a	(IIII)V
    //   966: return
    // Local variable table:
    //   start	length	slot	name	signature
    //   0	967	0	this	bi
    //   63	50	1	l	long
    //   308	187	1	localci	ci
    //   314	197	2	i	int
    //   339	126	3	localdt	dt
    //   221	1	5	localInterruptedException1	InterruptedException
    //   535	1	6	localInterruptedException2	InterruptedException
    //   637	1	7	localInterruptedException3	InterruptedException
    //   939	1	8	localInterruptedException4	InterruptedException
    // Exception table:
    //   from	to	target	type
    //   214	220	221	java/lang/InterruptedException
    //   528	534	535	java/lang/InterruptedException
    //   630	636	637	java/lang/InterruptedException
    //   932	938	939	java/lang/InterruptedException
  }
  
  private static boolean e(int paramInt1, int paramInt2)
  {
    return paramInt1 > paramInt2;
  }
  
  private static int a(long paramLong1, long paramLong2)
  {
    return paramLong1 < paramLong2;
  }
  
  private static boolean f(int paramInt)
  {
    return paramInt != 0;
  }
  
  private static boolean f(int paramInt1, int paramInt2)
  {
    return paramInt1 < paramInt2;
  }
  
  public final String toString()
  {
    return "Auto pk âm";
  }
  
  private static boolean g(int paramInt1, int paramInt2)
  {
    return paramInt1 == paramInt2;
  }
  
  public final void d()
  {
    super.a();
    if ((!d(dn.v, x[1])) || (!d(dn.a, x[1])) || (g(dn.u, x[1])))
    {
      dn.v = x[2];
      dn.a = x[3];
      dn.u = x[4];
    }
    this.d = dn.v;
    this.f = dn.an;
    this.h = et.f(dn.v);
  }
  
  private static boolean g(int paramInt)
  {
    return paramInt < 0;
  }
  
  private static boolean h(int paramInt)
  {
    return paramInt == 0;
  }
  
  private static boolean i(int paramInt)
  {
    return paramInt >= 0;
  }
  
  private static boolean a(Object paramObject)
  {
    return paramObject != null;
  }
  
  public static void p() {}
}


/* Location:              C:\Users\Admin\OneDrive\Documents\NSOv2_test.jar!\bi.class
 * Java compiler version: 1 (45.3)
 * JD-Core Version:       0.7.1
 */