public final class cm
  implements Runnable
{
  private db a;
  
  public static void a() {}
  
  static
  {
    cs.a(126);
    a();
  }
  
  public cm(au paramau, db paramdb)
  {
    this.a = paramdb;
  }
  
  private static boolean a(int paramInt)
  {
    return paramInt != 0;
  }
  
  /* Error */
  public final void run()
  {
    // Byte code:
    //   0: ldc2_w 13
    //   3: invokestatic 25	java/lang/Thread:sleep	(J)V
    //   6: ldc 1
    //   8: invokevirtual 23	java/lang/String:length	()I
    //   11: pop
    //   12: ldc 2
    //   14: invokevirtual 23	java/lang/String:length	()I
    //   17: ifne +10 -> 27
    //   20: return
    //   21: ldc 1
    //   23: invokevirtual 23	java/lang/String:length	()I
    //   26: pop2
    //   27: aload_0
    //   28: getfield 16	cm:a	Ldb;
    //   31: getfield 17	db:a	Lau;
    //   34: getfield 15	au:f	Z
    //   37: invokestatic 20	cm:a	(I)Z
    //   40: ifeq +16 -> 56
    //   43: aload_0
    //   44: getfield 16	cm:a	Ldb;
    //   47: getfield 17	db:a	Lau;
    //   50: invokestatic 18	au:a	(Lau;)Ljava/lang/Thread;
    //   53: invokevirtual 24	java/lang/Thread:interrupt	()V
    //   56: return
    //   57: ldc 1
    //   59: invokevirtual 23	java/lang/String:length	()I
    //   62: pop2
    //   63: return
    // Local variable table:
    //   start	length	slot	name	signature
    //   0	64	0	this	cm
    //   21	1	1	localInterruptedException	InterruptedException
    //   57	1	2	localException	Exception
    // Exception table:
    //   from	to	target	type
    //   0	6	21	java/lang/InterruptedException
    //   27	56	57	java/lang/Exception
  }
  
  public static void b() {}
}


/* Location:              C:\Users\Admin\OneDrive\Documents\NSOv2_test.jar!\cm.class
 * Java compiler version: 1 (45.3)
 * JD-Core Version:       0.7.1
 */