import java.io.PrintStream;
import java.util.Vector;

public final class cn
{
  private static boolean c;
  private static boolean d;
  private static boolean e;
  private static int f;
  private static boolean g;
  private static boolean h;
  private static boolean i;
  private static boolean j;
  private static boolean k;
  private static boolean l;
  private static boolean m;
  private static boolean n;
  private static boolean o;
  private static boolean p;
  public static boolean a;
  private static boolean q;
  private static boolean r;
  private static Object s;
  private static int[] t;
  public static boolean b;
  
  /* Error */
  public static void a()
  {
    // Byte code:
    //   0: getstatic 66	cn:t	[I
    //   3: iconst_0
    //   4: iaload
    //   5: putstatic 61	cn:o	Z
    //   8: getstatic 65	cn:s	Ljava/lang/Object;
    //   11: ldc 1
    //   13: invokevirtual 110	java/lang/String:length	()I
    //   16: pop2
    //   17: getstatic 65	cn:s	Ljava/lang/Object;
    //   20: dup
    //   21: astore_0
    //   22: monitorenter
    //   23: getstatic 65	cn:s	Ljava/lang/Object;
    //   26: ldc2_w 29
    //   29: invokevirtual 108	java/lang/Object:wait	(J)V
    //   32: ldc 1
    //   34: invokevirtual 110	java/lang/String:length	()I
    //   37: pop
    //   38: aconst_null
    //   39: ifnull +10 -> 49
    //   42: return
    //   43: ldc 1
    //   45: invokevirtual 110	java/lang/String:length	()I
    //   48: pop2
    //   49: aload_0
    //   50: monitorexit
    //   51: return
    //   52: astore_1
    //   53: aload_0
    //   54: monitorexit
    //   55: aload_1
    //   56: athrow
    // Local variable table:
    //   start	length	slot	name	signature
    //   21	33	0	Ljava/lang/Object;	Object
    //   52	4	1	localObject1	Object
    //   43	1	2	localInterruptedException	InterruptedException
    // Exception table:
    //   from	to	target	type
    //   23	32	43	java/lang/InterruptedException
    //   23	51	52	finally
  }
  
  /* Error */
  public static void b()
  {
    // Byte code:
    //   0: getstatic 66	cn:t	[I
    //   3: iconst_0
    //   4: iaload
    //   5: putstatic 53	cn:g	Z
    //   8: getstatic 65	cn:s	Ljava/lang/Object;
    //   11: ldc 1
    //   13: invokevirtual 110	java/lang/String:length	()I
    //   16: pop2
    //   17: getstatic 65	cn:s	Ljava/lang/Object;
    //   20: dup
    //   21: astore_0
    //   22: monitorenter
    //   23: getstatic 65	cn:s	Ljava/lang/Object;
    //   26: ldc2_w 31
    //   29: invokevirtual 108	java/lang/Object:wait	(J)V
    //   32: ldc 1
    //   34: invokevirtual 110	java/lang/String:length	()I
    //   37: pop
    //   38: bipush 107
    //   40: bipush 26
    //   42: ixor
    //   43: bipush 112
    //   45: iconst_4
    //   46: ixor
    //   47: ixor
    //   48: ifgt +10 -> 58
    //   51: return
    //   52: ldc 1
    //   54: invokevirtual 110	java/lang/String:length	()I
    //   57: pop2
    //   58: aload_0
    //   59: monitorexit
    //   60: return
    //   61: astore_1
    //   62: aload_0
    //   63: monitorexit
    //   64: aload_1
    //   65: athrow
    // Local variable table:
    //   start	length	slot	name	signature
    //   21	42	0	Ljava/lang/Object;	Object
    //   61	4	1	localObject1	Object
    //   52	1	2	localInterruptedException	InterruptedException
    // Exception table:
    //   from	to	target	type
    //   23	32	52	java/lang/InterruptedException
    //   23	60	61	finally
  }
  
  /* Error */
  public static void c()
  {
    // Byte code:
    //   0: getstatic 66	cn:t	[I
    //   3: iconst_0
    //   4: iaload
    //   5: putstatic 54	cn:h	Z
    //   8: getstatic 65	cn:s	Ljava/lang/Object;
    //   11: ldc 1
    //   13: invokevirtual 110	java/lang/String:length	()I
    //   16: pop2
    //   17: getstatic 65	cn:s	Ljava/lang/Object;
    //   20: dup
    //   21: astore_0
    //   22: monitorenter
    //   23: getstatic 65	cn:s	Ljava/lang/Object;
    //   26: ldc2_w 29
    //   29: invokevirtual 108	java/lang/Object:wait	(J)V
    //   32: ldc 1
    //   34: invokevirtual 110	java/lang/String:length	()I
    //   37: pop
    //   38: aconst_null
    //   39: ifnull +10 -> 49
    //   42: return
    //   43: ldc 1
    //   45: invokevirtual 110	java/lang/String:length	()I
    //   48: pop2
    //   49: aload_0
    //   50: monitorexit
    //   51: return
    //   52: astore_1
    //   53: aload_0
    //   54: monitorexit
    //   55: aload_1
    //   56: athrow
    // Local variable table:
    //   start	length	slot	name	signature
    //   21	33	0	Ljava/lang/Object;	Object
    //   52	4	1	localObject1	Object
    //   43	1	2	localInterruptedException	InterruptedException
    // Exception table:
    //   from	to	target	type
    //   23	32	43	java/lang/InterruptedException
    //   23	51	52	finally
  }
  
  private static boolean a(int paramInt)
  {
    return paramInt < 0;
  }
  
  private static int a(long paramLong1, long paramLong2)
  {
    return paramLong1 < paramLong2;
  }
  
  public static void d()
  {
    if (b(n))
    {
      "".length();
      synchronized (s)
      {
        s.notifyAll();
        "".length();
        if (" ".length() != " ".length()) {
          return;
        }
      }
      n = t[1];
    }
  }
  
  private static boolean b(int paramInt)
  {
    return paramInt != 0;
  }
  
  /* Error */
  public static boolean a(long paramLong)
  {
    // Byte code:
    //   0: getstatic 66	cn:t	[I
    //   3: iconst_0
    //   4: iaload
    //   5: putstatic 57	cn:k	Z
    //   8: lload_0
    //   9: lconst_0
    //   10: invokestatic 98	cn:j	(JJ)I
    //   13: invokestatic 79	cn:a	(I)Z
    //   16: ifeq +158 -> 174
    //   19: getstatic 65	cn:s	Ljava/lang/Object;
    //   22: dup
    //   23: astore_2
    //   24: dup
    //   25: astore_3
    //   26: monitorenter
    //   27: getstatic 65	cn:s	Ljava/lang/Object;
    //   30: invokevirtual 107	java/lang/Object:wait	()V
    //   33: ldc 1
    //   35: invokevirtual 110	java/lang/String:length	()I
    //   38: pop
    //   39: ldc 3
    //   41: invokevirtual 110	java/lang/String:length	()I
    //   44: ldc 2
    //   46: invokevirtual 110	java/lang/String:length	()I
    //   49: if_icmpge +24 -> 73
    //   52: sipush 230
    //   55: sipush 167
    //   58: ixor
    //   59: iconst_5
    //   60: bipush 68
    //   62: ixor
    //   63: iconst_m1
    //   64: ixor
    //   65: iand
    //   66: ireturn
    //   67: ldc 1
    //   69: invokevirtual 110	java/lang/String:length	()I
    //   72: pop2
    //   73: aload_3
    //   74: monitorexit
    //   75: ldc 1
    //   77: invokevirtual 110	java/lang/String:length	()I
    //   80: pop
    //   81: ldc 4
    //   83: invokevirtual 110	java/lang/String:length	()I
    //   86: ineg
    //   87: ifle +58 -> 145
    //   90: bipush 9
    //   92: bipush 113
    //   94: iadd
    //   95: bipush 86
    //   97: isub
    //   98: bipush 122
    //   100: iadd
    //   101: sipush 146
    //   104: bipush 76
    //   106: iadd
    //   107: sipush 151
    //   110: isub
    //   111: sipush 128
    //   114: iadd
    //   115: ixor
    //   116: bipush 81
    //   118: bipush 126
    //   120: ixor
    //   121: sipush 195
    //   124: sipush 181
    //   127: ixor
    //   128: ixor
    //   129: ldc 2
    //   131: invokevirtual 110	java/lang/String:length	()I
    //   134: ineg
    //   135: ixor
    //   136: iand
    //   137: ireturn
    //   138: astore 4
    //   140: aload_3
    //   141: monitorexit
    //   142: aload 4
    //   144: athrow
    //   145: getstatic 76	x:v	Z
    //   148: invokestatic 85	cn:b	(I)Z
    //   151: ifeq +17 -> 168
    //   154: getstatic 66	cn:t	[I
    //   157: iconst_1
    //   158: iaload
    //   159: putstatic 76	x:v	Z
    //   162: getstatic 66	cn:t	[I
    //   165: iconst_1
    //   166: iaload
    //   167: ireturn
    //   168: getstatic 66	cn:t	[I
    //   171: iconst_0
    //   172: iaload
    //   173: ireturn
    //   174: invokestatic 111	java/lang/System:currentTimeMillis	()J
    //   177: lstore_2
    //   178: getstatic 65	cn:s	Ljava/lang/Object;
    //   181: dup
    //   182: astore 4
    //   184: dup
    //   185: astore 4
    //   187: monitorenter
    //   188: getstatic 65	cn:s	Ljava/lang/Object;
    //   191: lload_0
    //   192: invokevirtual 108	java/lang/Object:wait	(J)V
    //   195: ldc 1
    //   197: invokevirtual 110	java/lang/String:length	()I
    //   200: pop
    //   201: sipush 173
    //   204: sipush 141
    //   207: ixor
    //   208: bipush 99
    //   210: bipush 67
    //   212: ixor
    //   213: iconst_m1
    //   214: ixor
    //   215: iand
    //   216: ifle +25 -> 241
    //   219: sipush 197
    //   222: sipush 140
    //   225: ixor
    //   226: bipush 66
    //   228: bipush 11
    //   230: ixor
    //   231: iconst_m1
    //   232: ixor
    //   233: iand
    //   234: ireturn
    //   235: ldc 1
    //   237: invokevirtual 110	java/lang/String:length	()I
    //   240: pop2
    //   241: aload 4
    //   243: monitorexit
    //   244: ldc 1
    //   246: invokevirtual 110	java/lang/String:length	()I
    //   249: pop
    //   250: ldc 2
    //   252: invokevirtual 110	java/lang/String:length	()I
    //   255: ifge +44 -> 299
    //   258: sipush 194
    //   261: sipush 184
    //   264: ixor
    //   265: bipush 76
    //   267: bipush 46
    //   269: ixor
    //   270: ixor
    //   271: bipush 52
    //   273: bipush 14
    //   275: ixor
    //   276: sipush 136
    //   279: sipush 170
    //   282: ixor
    //   283: ixor
    //   284: ldc 2
    //   286: invokevirtual 110	java/lang/String:length	()I
    //   289: ineg
    //   290: ixor
    //   291: iand
    //   292: ireturn
    //   293: astore_0
    //   294: aload 4
    //   296: monitorexit
    //   297: aload_0
    //   298: athrow
    //   299: getstatic 76	x:v	Z
    //   302: invokestatic 85	cn:b	(I)Z
    //   305: ifeq +17 -> 322
    //   308: getstatic 66	cn:t	[I
    //   311: iconst_1
    //   312: iaload
    //   313: putstatic 76	x:v	Z
    //   316: getstatic 66	cn:t	[I
    //   319: iconst_1
    //   320: iaload
    //   321: ireturn
    //   322: invokestatic 111	java/lang/System:currentTimeMillis	()J
    //   325: lload_2
    //   326: lsub
    //   327: lload_0
    //   328: invokestatic 98	cn:j	(JJ)I
    //   331: invokestatic 79	cn:a	(I)Z
    //   334: ifeq +9 -> 343
    //   337: getstatic 66	cn:t	[I
    //   340: iconst_0
    //   341: iaload
    //   342: ireturn
    //   343: getstatic 66	cn:t	[I
    //   346: iconst_1
    //   347: iaload
    //   348: ireturn
    // Local variable table:
    //   start	length	slot	name	signature
    //   0	349	0	paramLong	long
    //   23	1	2	localObject1	Object
    //   177	149	2	l1	long
    //   25	116	3	Ljava/lang/Object;	Object
    //   138	5	4	localObject2	Object
    //   182	1	4	localObject3	Object
    //   185	110	4	Ljava/lang/Object;	Object
    //   67	1	7	localInterruptedException1	InterruptedException
    //   235	1	8	localInterruptedException2	InterruptedException
    // Exception table:
    //   from	to	target	type
    //   27	33	67	java/lang/InterruptedException
    //   27	75	138	finally
    //   188	195	235	java/lang/InterruptedException
    //   188	244	293	finally
  }
  
  public static void e()
  {
    System.out.println("NotifyDV");
    if (b(l))
    {
      "".length();
      synchronized (s)
      {
        s.notifyAll();
        "".length();
        if (((0x4E ^ 0x49 ^ 0xA0 ^ 0x8D) & ('' + 33 - 75 + 83 ^ 107 + 9 - -23 + 18 ^ -" ".length())) != 0) {
          return;
        }
      }
      l = t[1];
    }
  }
  
  /* Error */
  public static boolean f()
  {
    // Byte code:
    //   0: getstatic 66	cn:t	[I
    //   3: iconst_0
    //   4: iaload
    //   5: putstatic 64	cn:r	Z
    //   8: invokestatic 111	java/lang/System:currentTimeMillis	()J
    //   11: lstore_0
    //   12: getstatic 65	cn:s	Ljava/lang/Object;
    //   15: ldc 1
    //   17: invokevirtual 110	java/lang/String:length	()I
    //   20: pop2
    //   21: getstatic 65	cn:s	Ljava/lang/Object;
    //   24: dup
    //   25: astore_2
    //   26: monitorenter
    //   27: getstatic 65	cn:s	Ljava/lang/Object;
    //   30: ldc2_w 35
    //   33: invokevirtual 108	java/lang/Object:wait	(J)V
    //   36: ldc 1
    //   38: invokevirtual 110	java/lang/String:length	()I
    //   41: pop
    //   42: bipush 95
    //   44: bipush 77
    //   46: iadd
    //   47: bipush 99
    //   49: isub
    //   50: bipush 59
    //   52: iadd
    //   53: bipush 123
    //   55: bipush 17
    //   57: iadd
    //   58: bipush 110
    //   60: isub
    //   61: bipush 98
    //   63: iadd
    //   64: ixor
    //   65: ldc 2
    //   67: invokevirtual 110	java/lang/String:length	()I
    //   70: ineg
    //   71: if_icmpge +69 -> 140
    //   74: bipush 80
    //   76: bipush 124
    //   78: iadd
    //   79: sipush 203
    //   82: isub
    //   83: sipush 187
    //   86: iadd
    //   87: bipush 109
    //   89: bipush 6
    //   91: iadd
    //   92: bipush 100
    //   94: isub
    //   95: bipush 117
    //   97: iadd
    //   98: ixor
    //   99: bipush 65
    //   101: bipush 98
    //   103: iadd
    //   104: sipush 157
    //   107: isub
    //   108: sipush 152
    //   111: iadd
    //   112: bipush 119
    //   114: bipush 109
    //   116: iadd
    //   117: sipush 170
    //   120: isub
    //   121: bipush 108
    //   123: iadd
    //   124: ixor
    //   125: ldc 2
    //   127: invokevirtual 110	java/lang/String:length	()I
    //   130: ineg
    //   131: ixor
    //   132: iand
    //   133: ireturn
    //   134: ldc 1
    //   136: invokevirtual 110	java/lang/String:length	()I
    //   139: pop2
    //   140: aload_2
    //   141: monitorexit
    //   142: ldc 1
    //   144: invokevirtual 110	java/lang/String:length	()I
    //   147: pop
    //   148: bipush 118
    //   150: bipush 37
    //   152: ixor
    //   153: sipush 151
    //   156: sipush 196
    //   159: ixor
    //   160: iconst_m1
    //   161: ixor
    //   162: iand
    //   163: ifeq +24 -> 187
    //   166: sipush 156
    //   169: sipush 173
    //   172: ixor
    //   173: bipush 71
    //   175: bipush 118
    //   177: ixor
    //   178: iconst_m1
    //   179: ixor
    //   180: iand
    //   181: ireturn
    //   182: astore_0
    //   183: aload_2
    //   184: monitorexit
    //   185: aload_0
    //   186: athrow
    //   187: invokestatic 111	java/lang/System:currentTimeMillis	()J
    //   190: lload_0
    //   191: lsub
    //   192: ldc2_w 35
    //   195: invokestatic 81	cn:a	(JJ)I
    //   198: invokestatic 79	cn:a	(I)Z
    //   201: ifeq +9 -> 210
    //   204: getstatic 66	cn:t	[I
    //   207: iconst_0
    //   208: iaload
    //   209: ireturn
    //   210: getstatic 66	cn:t	[I
    //   213: iconst_1
    //   214: iaload
    //   215: ireturn
    // Local variable table:
    //   start	length	slot	name	signature
    //   11	1	0	l1	long
    //   182	9	0	localObject1	Object
    //   25	159	2	Ljava/lang/Object;	Object
    //   134	1	3	localInterruptedException	InterruptedException
    // Exception table:
    //   from	to	target	type
    //   27	36	134	java/lang/InterruptedException
    //   27	142	182	finally
  }
  
  /* Error */
  public static boolean g()
  {
    // Byte code:
    //   0: getstatic 66	cn:t	[I
    //   3: iconst_0
    //   4: iaload
    //   5: putstatic 57	cn:k	Z
    //   8: invokestatic 111	java/lang/System:currentTimeMillis	()J
    //   11: lstore_0
    //   12: getstatic 65	cn:s	Ljava/lang/Object;
    //   15: ldc 1
    //   17: invokevirtual 110	java/lang/String:length	()I
    //   20: pop2
    //   21: getstatic 65	cn:s	Ljava/lang/Object;
    //   24: dup
    //   25: astore_2
    //   26: monitorenter
    //   27: getstatic 65	cn:s	Ljava/lang/Object;
    //   30: ldc2_w 39
    //   33: invokevirtual 108	java/lang/Object:wait	(J)V
    //   36: ldc 1
    //   38: invokevirtual 110	java/lang/String:length	()I
    //   41: pop
    //   42: ldc 2
    //   44: invokevirtual 110	java/lang/String:length	()I
    //   47: ifgt +44 -> 91
    //   50: sipush 191
    //   53: sipush 193
    //   56: ixor
    //   57: sipush 224
    //   60: sipush 133
    //   63: ixor
    //   64: ixor
    //   65: bipush 107
    //   67: bipush 119
    //   69: ixor
    //   70: bipush 67
    //   72: bipush 68
    //   74: ixor
    //   75: ixor
    //   76: ldc 2
    //   78: invokevirtual 110	java/lang/String:length	()I
    //   81: ineg
    //   82: ixor
    //   83: iand
    //   84: ireturn
    //   85: ldc 1
    //   87: invokevirtual 110	java/lang/String:length	()I
    //   90: pop2
    //   91: aload_2
    //   92: monitorexit
    //   93: ldc 1
    //   95: invokevirtual 110	java/lang/String:length	()I
    //   98: pop
    //   99: ldc 3
    //   101: invokevirtual 110	java/lang/String:length	()I
    //   104: ifge +24 -> 128
    //   107: sipush 183
    //   110: sipush 145
    //   113: ixor
    //   114: bipush 53
    //   116: bipush 19
    //   118: ixor
    //   119: iconst_m1
    //   120: ixor
    //   121: iand
    //   122: ireturn
    //   123: astore_0
    //   124: aload_2
    //   125: monitorexit
    //   126: aload_0
    //   127: athrow
    //   128: getstatic 76	x:v	Z
    //   131: invokestatic 85	cn:b	(I)Z
    //   134: ifeq +17 -> 151
    //   137: getstatic 66	cn:t	[I
    //   140: iconst_1
    //   141: iaload
    //   142: putstatic 76	x:v	Z
    //   145: getstatic 66	cn:t	[I
    //   148: iconst_1
    //   149: iaload
    //   150: ireturn
    //   151: invokestatic 111	java/lang/System:currentTimeMillis	()J
    //   154: lload_0
    //   155: lsub
    //   156: ldc2_w 39
    //   159: invokestatic 90	cn:c	(JJ)I
    //   162: invokestatic 79	cn:a	(I)Z
    //   165: ifeq +9 -> 174
    //   168: getstatic 66	cn:t	[I
    //   171: iconst_0
    //   172: iaload
    //   173: ireturn
    //   174: getstatic 66	cn:t	[I
    //   177: iconst_1
    //   178: iaload
    //   179: ireturn
    // Local variable table:
    //   start	length	slot	name	signature
    //   11	1	0	l1	long
    //   123	32	0	localObject1	Object
    //   25	100	2	Ljava/lang/Object;	Object
    //   85	1	3	localInterruptedException	InterruptedException
    // Exception table:
    //   from	to	target	type
    //   27	36	85	java/lang/InterruptedException
    //   27	93	123	finally
  }
  
  private static int b(long paramLong1, long paramLong2)
  {
    return paramLong1 < paramLong2;
  }
  
  /* Error */
  public static void h()
  {
    // Byte code:
    //   0: getstatic 66	cn:t	[I
    //   3: iconst_0
    //   4: iaload
    //   5: putstatic 51	cn:e	Z
    //   8: getstatic 65	cn:s	Ljava/lang/Object;
    //   11: ldc 1
    //   13: invokevirtual 110	java/lang/String:length	()I
    //   16: pop2
    //   17: getstatic 65	cn:s	Ljava/lang/Object;
    //   20: dup
    //   21: astore_0
    //   22: monitorenter
    //   23: getstatic 65	cn:s	Ljava/lang/Object;
    //   26: ldc2_w 27
    //   29: invokevirtual 108	java/lang/Object:wait	(J)V
    //   32: ldc 1
    //   34: invokevirtual 110	java/lang/String:length	()I
    //   37: pop
    //   38: sipush 254
    //   41: sipush 174
    //   44: ixor
    //   45: bipush 96
    //   47: iconst_3
    //   48: ixor
    //   49: ixor
    //   50: bipush 41
    //   52: bipush 45
    //   54: ixor
    //   55: sipush 144
    //   58: sipush 167
    //   61: ixor
    //   62: ixor
    //   63: ldc 2
    //   65: invokevirtual 110	java/lang/String:length	()I
    //   68: ineg
    //   69: ixor
    //   70: iand
    //   71: ifeq +10 -> 81
    //   74: return
    //   75: ldc 1
    //   77: invokevirtual 110	java/lang/String:length	()I
    //   80: pop2
    //   81: aload_0
    //   82: monitorexit
    //   83: return
    //   84: astore_1
    //   85: aload_0
    //   86: monitorexit
    //   87: aload_1
    //   88: athrow
    // Local variable table:
    //   start	length	slot	name	signature
    //   21	65	0	Ljava/lang/Object;	Object
    //   84	4	1	localObject1	Object
    //   75	1	2	localInterruptedException	InterruptedException
    // Exception table:
    //   from	to	target	type
    //   23	32	75	java/lang/InterruptedException
    //   23	83	84	finally
  }
  
  public static void i()
  {
    if (b(k))
    {
      "".length();
      synchronized (s)
      {
        s.notifyAll();
        "".length();
        if (-" ".length() >= 0) {
          return;
        }
      }
      k = t[1];
    }
  }
  
  private static boolean a(int paramInt1, int paramInt2)
  {
    return paramInt1 >= paramInt2;
  }
  
  public static void j()
  {
    if (a(dn.as))
    {
      long l1 = System.currentTimeMillis();
      label185:
      do
      {
        try
        {
          do
          {
            int i1 = t[1];
            if (a(i1, dn.p.size()))
            {
              i1 = t[0];
              "".length();
              if (" ".length() < "   ".length()) {}
            }
            else
            {
              String str = (String)dn.p.elementAt(i1);
              int i2 = t[1];
              for (;;)
              {
                if (c(i2, fn.ax.size()))
                {
                  bk localbk;
                  if (b((localbk = (bk)fn.ax.elementAt(i2)).a.equals(str)))
                  {
                    if (!a(localbk.f)) {
                      break label185;
                    }
                    i1++;
                    "".length();
                    if (null == null) {
                      break;
                    }
                    return;
                  }
                  i2++;
                  "".length();
                  if ("  ".length() >= (82 + 35 - 92 + 159 ^ 21 + '' - 57 + 72)) {
                    return;
                  }
                }
              }
              i1 = t[1];
            }
            if ((!c(i1)) || (d(d(System.currentTimeMillis() - l1, 300000L)))) {
              return;
            }
            Thread.sleep(2000L);
            "".length();
          } while (((0x7F ^ 0x70) & (0x96 ^ 0x99 ^ 0xFFFFFFFF)) == 0);
          return;
        }
        catch (InterruptedException localInterruptedException2)
        {
          InterruptedException localInterruptedException1;
          (localInterruptedException1 = localInterruptedException2).printStackTrace();
          "".length();
        }
      } while (((0x6F ^ 0x16 ^ 0x7E ^ 0xE) & (44 + '' - 7 + 22 ^ '' + 78 - 217 + 188 ^ -" ".length())) <= 0);
      return;
    }
  }
  
  private static void an()
  {
    t = new int[3];
    t[0] = " ".length();
    t[1] = ((13 + 107 - -9 + 31 ^ 96 + '¢' - 116 + 32) & (0x32 ^ 0x66 ^ 0xDD ^ 0x87 ^ -" ".length()));
    t[2] = (0xDE ^ 0xBA);
  }
  
  private static int c(long paramLong1, long paramLong2)
  {
    return paramLong1 < paramLong2;
  }
  
  /* Error */
  public static void k()
  {
    // Byte code:
    //   0: getstatic 66	cn:t	[I
    //   3: iconst_0
    //   4: iaload
    //   5: putstatic 55	cn:i	Z
    //   8: getstatic 65	cn:s	Ljava/lang/Object;
    //   11: ldc 1
    //   13: invokevirtual 110	java/lang/String:length	()I
    //   16: pop2
    //   17: getstatic 65	cn:s	Ljava/lang/Object;
    //   20: dup
    //   21: astore_0
    //   22: monitorenter
    //   23: getstatic 65	cn:s	Ljava/lang/Object;
    //   26: ldc2_w 29
    //   29: invokevirtual 108	java/lang/Object:wait	(J)V
    //   32: ldc 1
    //   34: invokevirtual 110	java/lang/String:length	()I
    //   37: pop
    //   38: ldc 2
    //   40: invokevirtual 110	java/lang/String:length	()I
    //   43: ldc 4
    //   45: invokevirtual 110	java/lang/String:length	()I
    //   48: if_icmplt +10 -> 58
    //   51: return
    //   52: ldc 1
    //   54: invokevirtual 110	java/lang/String:length	()I
    //   57: pop2
    //   58: aload_0
    //   59: monitorexit
    //   60: return
    //   61: astore_1
    //   62: aload_0
    //   63: monitorexit
    //   64: aload_1
    //   65: athrow
    // Local variable table:
    //   start	length	slot	name	signature
    //   21	42	0	Ljava/lang/Object;	Object
    //   61	4	1	localObject1	Object
    //   52	1	2	localInterruptedException	InterruptedException
    // Exception table:
    //   from	to	target	type
    //   23	32	52	java/lang/InterruptedException
    //   23	60	61	finally
  }
  
  private static int d(long paramLong1, long paramLong2)
  {
    return paramLong1 < paramLong2;
  }
  
  public static boolean l()
  {
    int i1 = t[1];
    while (c(i1, dn.p.size()))
    {
      String str = (String)dn.p.elementAt(i1);
      int i2 = t[1];
      while (c(i2, fn.ax.size()))
      {
        if (!c(((bk)fn.ax.elementAt(i2)).a.equals(str))) {
          break label151;
        }
        i2++;
        "".length();
        if (null != null) {
          return (62 + 97 - 148 + 179 ^ 113 + 48 - 97 + 68) & ('' + 75 - 154 + 83 ^ 27 + 47 - 73 + 177 ^ -" ".length());
        }
      }
      return t[1];
      label151:
      i1++;
      "".length();
      if (null != null) {
        return (0x6B ^ 0x71 ^ 0x22 ^ 0x15) & (0x66 ^ 0x1C ^ 0x6A ^ 0x3D ^ -" ".length());
      }
    }
    return t[0];
  }
  
  public static void m()
  {
    if (b(c))
    {
      "".length();
      synchronized (s)
      {
        s.notifyAll();
        "".length();
        if ((('¢' + 33 - 126 + 110 ^ 13 + 106 - 13 + 24) & (0x1E ^ 0x18 ^ 0x30 ^ 0x7 ^ -" ".length())) <= -" ".length()) {
          return;
        }
      }
      c = t[1];
    }
  }
  
  private static boolean a(Object paramObject)
  {
    return paramObject != null;
  }
  
  /* Error */
  public static boolean n()
  {
    // Byte code:
    //   0: getstatic 74	java/lang/System:out	Ljava/io/PrintStream;
    //   3: ldc 6
    //   5: invokevirtual 104	java/io/PrintStream:println	(Ljava/lang/String;)V
    //   8: getstatic 66	cn:t	[I
    //   11: iconst_0
    //   12: iaload
    //   13: putstatic 58	cn:l	Z
    //   16: invokestatic 111	java/lang/System:currentTimeMillis	()J
    //   19: lstore_0
    //   20: getstatic 65	cn:s	Ljava/lang/Object;
    //   23: ldc 1
    //   25: invokevirtual 110	java/lang/String:length	()I
    //   28: pop2
    //   29: getstatic 65	cn:s	Ljava/lang/Object;
    //   32: dup
    //   33: astore_2
    //   34: monitorenter
    //   35: getstatic 65	cn:s	Ljava/lang/Object;
    //   38: ldc2_w 37
    //   41: invokevirtual 108	java/lang/Object:wait	(J)V
    //   44: ldc 1
    //   46: invokevirtual 110	java/lang/String:length	()I
    //   49: pop
    //   50: ldc 2
    //   52: invokevirtual 110	java/lang/String:length	()I
    //   55: ifne +23 -> 78
    //   58: bipush 64
    //   60: bipush 127
    //   62: ixor
    //   63: bipush 124
    //   65: bipush 67
    //   67: ixor
    //   68: iconst_m1
    //   69: ixor
    //   70: iand
    //   71: ireturn
    //   72: ldc 1
    //   74: invokevirtual 110	java/lang/String:length	()I
    //   77: pop2
    //   78: aload_2
    //   79: monitorexit
    //   80: ldc 1
    //   82: invokevirtual 110	java/lang/String:length	()I
    //   85: pop
    //   86: bipush 14
    //   88: bipush 94
    //   90: ixor
    //   91: sipush 148
    //   94: sipush 138
    //   97: ixor
    //   98: ixor
    //   99: sipush 213
    //   102: sipush 159
    //   105: ixor
    //   106: sipush 150
    //   109: sipush 146
    //   112: ixor
    //   113: ixor
    //   114: ldc 2
    //   116: invokevirtual 110	java/lang/String:length	()I
    //   119: ineg
    //   120: ixor
    //   121: iand
    //   122: bipush 43
    //   124: bipush 116
    //   126: iadd
    //   127: bipush 99
    //   129: isub
    //   130: bipush 101
    //   132: iadd
    //   133: bipush 67
    //   135: bipush 46
    //   137: iadd
    //   138: bipush -51
    //   140: isub
    //   141: iconst_1
    //   142: iadd
    //   143: ixor
    //   144: if_icmpne +40 -> 184
    //   147: bipush 78
    //   149: bipush 73
    //   151: ixor
    //   152: bipush 70
    //   154: bipush 10
    //   156: ixor
    //   157: ixor
    //   158: sipush 247
    //   161: sipush 179
    //   164: ixor
    //   165: iconst_5
    //   166: bipush 10
    //   168: ixor
    //   169: ixor
    //   170: ldc 2
    //   172: invokevirtual 110	java/lang/String:length	()I
    //   175: ineg
    //   176: ixor
    //   177: iand
    //   178: ireturn
    //   179: astore_0
    //   180: aload_2
    //   181: monitorexit
    //   182: aload_0
    //   183: athrow
    //   184: invokestatic 111	java/lang/System:currentTimeMillis	()J
    //   187: lload_0
    //   188: lsub
    //   189: ldc2_w 37
    //   192: invokestatic 96	cn:h	(JJ)I
    //   195: invokestatic 79	cn:a	(I)Z
    //   198: ifeq +9 -> 207
    //   201: getstatic 66	cn:t	[I
    //   204: iconst_0
    //   205: iaload
    //   206: ireturn
    //   207: getstatic 66	cn:t	[I
    //   210: iconst_1
    //   211: iaload
    //   212: ireturn
    // Local variable table:
    //   start	length	slot	name	signature
    //   19	1	0	l1	long
    //   179	9	0	localObject1	Object
    //   33	148	2	Ljava/lang/Object;	Object
    //   72	1	3	localInterruptedException	InterruptedException
    // Exception table:
    //   from	to	target	type
    //   35	44	72	java/lang/InterruptedException
    //   35	80	179	finally
  }
  
  private static int e(long paramLong1, long paramLong2)
  {
    return paramLong1 < paramLong2;
  }
  
  /* Error */
  public static boolean o()
  {
    // Byte code:
    //   0: getstatic 66	cn:t	[I
    //   3: iconst_0
    //   4: iaload
    //   5: putstatic 56	cn:j	Z
    //   8: invokestatic 111	java/lang/System:currentTimeMillis	()J
    //   11: lstore_0
    //   12: getstatic 65	cn:s	Ljava/lang/Object;
    //   15: ldc 1
    //   17: invokevirtual 110	java/lang/String:length	()I
    //   20: pop2
    //   21: getstatic 65	cn:s	Ljava/lang/Object;
    //   24: dup
    //   25: astore_2
    //   26: monitorenter
    //   27: getstatic 65	cn:s	Ljava/lang/Object;
    //   30: ldc2_w 33
    //   33: invokevirtual 108	java/lang/Object:wait	(J)V
    //   36: ldc 1
    //   38: invokevirtual 110	java/lang/String:length	()I
    //   41: pop
    //   42: ldc 4
    //   44: invokevirtual 110	java/lang/String:length	()I
    //   47: ineg
    //   48: iflt +24 -> 72
    //   51: iconst_0
    //   52: bipush 82
    //   54: ixor
    //   55: sipush 255
    //   58: sipush 173
    //   61: ixor
    //   62: iconst_m1
    //   63: ixor
    //   64: iand
    //   65: ireturn
    //   66: ldc 1
    //   68: invokevirtual 110	java/lang/String:length	()I
    //   71: pop2
    //   72: aload_2
    //   73: monitorexit
    //   74: ldc 1
    //   76: invokevirtual 110	java/lang/String:length	()I
    //   79: pop
    //   80: ldc 2
    //   82: invokevirtual 110	java/lang/String:length	()I
    //   85: ldc 2
    //   87: invokevirtual 110	java/lang/String:length	()I
    //   90: if_icmpeq +51 -> 141
    //   93: bipush 66
    //   95: sipush 130
    //   98: iadd
    //   99: bipush 96
    //   101: isub
    //   102: bipush 37
    //   104: iadd
    //   105: bipush 55
    //   107: bipush 121
    //   109: iadd
    //   110: bipush 101
    //   112: isub
    //   113: bipush 106
    //   115: iadd
    //   116: ixor
    //   117: bipush 56
    //   119: bipush 21
    //   121: ixor
    //   122: bipush 18
    //   124: iconst_3
    //   125: ixor
    //   126: ixor
    //   127: ldc 2
    //   129: invokevirtual 110	java/lang/String:length	()I
    //   132: ineg
    //   133: ixor
    //   134: iand
    //   135: ireturn
    //   136: astore_0
    //   137: aload_2
    //   138: monitorexit
    //   139: aload_0
    //   140: athrow
    //   141: invokestatic 111	java/lang/System:currentTimeMillis	()J
    //   144: lload_0
    //   145: lsub
    //   146: ldc2_w 33
    //   149: invokestatic 93	cn:e	(JJ)I
    //   152: invokestatic 79	cn:a	(I)Z
    //   155: ifeq +9 -> 164
    //   158: getstatic 66	cn:t	[I
    //   161: iconst_0
    //   162: iaload
    //   163: ireturn
    //   164: getstatic 66	cn:t	[I
    //   167: iconst_1
    //   168: iaload
    //   169: ireturn
    // Local variable table:
    //   start	length	slot	name	signature
    //   11	1	0	l1	long
    //   136	9	0	localObject1	Object
    //   25	113	2	Ljava/lang/Object;	Object
    //   66	1	3	localInterruptedException	InterruptedException
    // Exception table:
    //   from	to	target	type
    //   27	36	66	java/lang/InterruptedException
    //   27	74	136	finally
  }
  
  private static int f(long paramLong1, long paramLong2)
  {
    return paramLong1 < paramLong2;
  }
  
  private static boolean c(int paramInt)
  {
    return paramInt == 0;
  }
  
  /* Error */
  public static boolean p()
  {
    // Byte code:
    //   0: getstatic 75	r:m	Lfy;
    //   3: invokestatic 82	cn:a	(Ljava/lang/Object;)Z
    //   6: ifeq +44 -> 50
    //   9: getstatic 75	r:m	Lfy;
    //   12: getfield 73	fy:j	I
    //   15: ldc 1
    //   17: invokevirtual 110	java/lang/String:length	()I
    //   20: pop
    //   21: ldc 3
    //   23: invokevirtual 110	java/lang/String:length	()I
    //   26: ldc 3
    //   28: invokevirtual 110	java/lang/String:length	()I
    //   31: if_icmpge +24 -> 55
    //   34: sipush 218
    //   37: sipush 131
    //   40: ixor
    //   41: bipush 47
    //   43: bipush 118
    //   45: ixor
    //   46: iconst_m1
    //   47: ixor
    //   48: iand
    //   49: ireturn
    //   50: getstatic 66	cn:t	[I
    //   53: iconst_1
    //   54: iaload
    //   55: putstatic 52	cn:f	I
    //   58: getstatic 66	cn:t	[I
    //   61: iconst_0
    //   62: iaload
    //   63: putstatic 62	cn:p	Z
    //   66: getstatic 65	cn:s	Ljava/lang/Object;
    //   69: ldc 1
    //   71: invokevirtual 110	java/lang/String:length	()I
    //   74: pop2
    //   75: getstatic 65	cn:s	Ljava/lang/Object;
    //   78: dup
    //   79: astore_0
    //   80: monitorenter
    //   81: getstatic 65	cn:s	Ljava/lang/Object;
    //   84: ldc2_w 31
    //   87: invokevirtual 108	java/lang/Object:wait	(J)V
    //   90: ldc 1
    //   92: invokevirtual 110	java/lang/String:length	()I
    //   95: pop
    //   96: ldc 3
    //   98: invokevirtual 110	java/lang/String:length	()I
    //   101: ldc 3
    //   103: invokevirtual 110	java/lang/String:length	()I
    //   106: if_icmpeq +23 -> 129
    //   109: bipush 23
    //   111: bipush 13
    //   113: ixor
    //   114: bipush 45
    //   116: bipush 55
    //   118: ixor
    //   119: iconst_m1
    //   120: ixor
    //   121: iand
    //   122: ireturn
    //   123: ldc 1
    //   125: invokevirtual 110	java/lang/String:length	()I
    //   128: pop2
    //   129: aload_0
    //   130: monitorexit
    //   131: ldc 1
    //   133: invokevirtual 110	java/lang/String:length	()I
    //   136: pop
    //   137: ldc 2
    //   139: invokevirtual 110	java/lang/String:length	()I
    //   142: ifge +24 -> 166
    //   145: bipush 63
    //   147: bipush 99
    //   149: ixor
    //   150: sipush 242
    //   153: sipush 174
    //   156: ixor
    //   157: iconst_m1
    //   158: ixor
    //   159: iand
    //   160: ireturn
    //   161: astore_1
    //   162: aload_0
    //   163: monitorexit
    //   164: aload_1
    //   165: athrow
    //   166: getstatic 75	r:m	Lfy;
    //   169: invokestatic 82	cn:a	(Ljava/lang/Object;)Z
    //   172: ifeq +18 -> 190
    //   175: getstatic 75	r:m	Lfy;
    //   178: getfield 73	fy:j	I
    //   181: getstatic 52	cn:f	I
    //   184: invokestatic 86	cn:b	(II)Z
    //   187: ifeq +9 -> 196
    //   190: getstatic 66	cn:t	[I
    //   193: iconst_0
    //   194: iaload
    //   195: ireturn
    //   196: getstatic 66	cn:t	[I
    //   199: iconst_1
    //   200: iaload
    //   201: ireturn
    // Local variable table:
    //   start	length	slot	name	signature
    //   79	84	0	Ljava/lang/Object;	Object
    //   161	4	1	localObject1	Object
    //   123	1	2	localInterruptedException	InterruptedException
    // Exception table:
    //   from	to	target	type
    //   81	90	123	java/lang/InterruptedException
    //   81	131	161	finally
  }
  
  public static void q()
  {
    if (b(p))
    {
      "".length();
      synchronized (s)
      {
        s.notifyAll();
        "".length();
        if (((0x6E ^ 0x73 ^ 0x5B ^ 0x64) & (0x12 ^ 0x2C ^ 0x64 ^ 0x78 ^ -" ".length())) >= "  ".length()) {
          return;
        }
      }
      p = t[1];
    }
  }
  
  /* Error */
  public static void r()
  {
    // Byte code:
    //   0: getstatic 66	cn:t	[I
    //   3: iconst_0
    //   4: iaload
    //   5: putstatic 49	cn:c	Z
    //   8: getstatic 65	cn:s	Ljava/lang/Object;
    //   11: ldc 1
    //   13: invokevirtual 110	java/lang/String:length	()I
    //   16: pop2
    //   17: getstatic 65	cn:s	Ljava/lang/Object;
    //   20: dup
    //   21: astore_0
    //   22: monitorenter
    //   23: getstatic 65	cn:s	Ljava/lang/Object;
    //   26: ldc2_w 29
    //   29: invokevirtual 108	java/lang/Object:wait	(J)V
    //   32: ldc 1
    //   34: invokevirtual 110	java/lang/String:length	()I
    //   37: pop
    //   38: ldc 4
    //   40: invokevirtual 110	java/lang/String:length	()I
    //   43: ldc 4
    //   45: invokevirtual 110	java/lang/String:length	()I
    //   48: if_icmpeq +10 -> 58
    //   51: return
    //   52: ldc 1
    //   54: invokevirtual 110	java/lang/String:length	()I
    //   57: pop2
    //   58: aload_0
    //   59: monitorexit
    //   60: return
    //   61: astore_1
    //   62: aload_0
    //   63: monitorexit
    //   64: aload_1
    //   65: athrow
    // Local variable table:
    //   start	length	slot	name	signature
    //   21	42	0	Ljava/lang/Object;	Object
    //   61	4	1	localObject1	Object
    //   52	1	2	localInterruptedException	InterruptedException
    // Exception table:
    //   from	to	target	type
    //   23	32	52	java/lang/InterruptedException
    //   23	60	61	finally
  }
  
  /* Error */
  public static void s()
  {
    // Byte code:
    //   0: getstatic 66	cn:t	[I
    //   3: iconst_0
    //   4: iaload
    //   5: putstatic 50	cn:d	Z
    //   8: getstatic 65	cn:s	Ljava/lang/Object;
    //   11: ldc 1
    //   13: invokevirtual 110	java/lang/String:length	()I
    //   16: pop2
    //   17: getstatic 65	cn:s	Ljava/lang/Object;
    //   20: dup
    //   21: astore_0
    //   22: monitorenter
    //   23: getstatic 65	cn:s	Ljava/lang/Object;
    //   26: ldc2_w 29
    //   29: invokevirtual 108	java/lang/Object:wait	(J)V
    //   32: ldc 1
    //   34: invokevirtual 110	java/lang/String:length	()I
    //   37: pop
    //   38: aconst_null
    //   39: ifnull +10 -> 49
    //   42: return
    //   43: ldc 1
    //   45: invokevirtual 110	java/lang/String:length	()I
    //   48: pop2
    //   49: aload_0
    //   50: monitorexit
    //   51: return
    //   52: astore_1
    //   53: aload_0
    //   54: monitorexit
    //   55: aload_1
    //   56: athrow
    // Local variable table:
    //   start	length	slot	name	signature
    //   21	33	0	Ljava/lang/Object;	Object
    //   52	4	1	localObject1	Object
    //   43	1	2	localInterruptedException	InterruptedException
    // Exception table:
    //   from	to	target	type
    //   23	32	43	java/lang/InterruptedException
    //   23	51	52	finally
  }
  
  private static boolean d(int paramInt)
  {
    return paramInt >= 0;
  }
  
  public static void t()
  {
    if (b(r))
    {
      "".length();
      synchronized (s)
      {
        s.notifyAll();
        "".length();
        if (((0x33 ^ 0x18) & (0x1C ^ 0x37 ^ 0xFFFFFFFF)) < -" ".length()) {
          return;
        }
      }
      r = t[1];
    }
  }
  
  public static void u()
  {
    if (b(d))
    {
      "".length();
      synchronized (s)
      {
        s.notifyAll();
        "".length();
        if (null != null) {
          return;
        }
      }
      d = t[1];
    }
  }
  
  public static void v()
  {
    if (b(g))
    {
      "".length();
      synchronized (s)
      {
        s.notifyAll();
        "".length();
        if ("  ".length() < 0) {
          return;
        }
      }
      g = t[1];
    }
  }
  
  public static void w()
  {
    an();
    d = t[1];
    a = t[1];
    b = t[1];
    i = t[1];
    o = t[1];
    c = t[1];
    h = t[1];
    n = t[1];
    m = t[1];
    q = t[1];
    r = t[1];
    p = t[1];
    g = t[1];
    j = t[1];
    k = t[1];
    e = t[1];
    l = t[1];
    s = new Object();
  }
  
  static
  {
    cs.a(161);
    w();
  }
  
  /* Error */
  public static void x()
  {
    // Byte code:
    //   0: getstatic 66	cn:t	[I
    //   3: iconst_0
    //   4: iaload
    //   5: putstatic 63	cn:q	Z
    //   8: getstatic 65	cn:s	Ljava/lang/Object;
    //   11: ldc 1
    //   13: invokevirtual 110	java/lang/String:length	()I
    //   16: pop2
    //   17: getstatic 65	cn:s	Ljava/lang/Object;
    //   20: dup
    //   21: astore_0
    //   22: monitorenter
    //   23: getstatic 65	cn:s	Ljava/lang/Object;
    //   26: invokevirtual 107	java/lang/Object:wait	()V
    //   29: ldc 1
    //   31: invokevirtual 110	java/lang/String:length	()I
    //   34: pop
    //   35: aconst_null
    //   36: ifnull +10 -> 46
    //   39: return
    //   40: ldc 1
    //   42: invokevirtual 110	java/lang/String:length	()I
    //   45: pop2
    //   46: aload_0
    //   47: monitorexit
    //   48: return
    //   49: astore_1
    //   50: aload_0
    //   51: monitorexit
    //   52: aload_1
    //   53: athrow
    // Local variable table:
    //   start	length	slot	name	signature
    //   21	30	0	Ljava/lang/Object;	Object
    //   49	4	1	localObject1	Object
    //   40	1	2	localInterruptedException	InterruptedException
    // Exception table:
    //   from	to	target	type
    //   23	29	40	java/lang/InterruptedException
    //   23	48	49	finally
  }
  
  private static int g(long paramLong1, long paramLong2)
  {
    return paramLong1 < paramLong2;
  }
  
  public static void y()
  {
    if (b(j))
    {
      "".length();
      synchronized (s)
      {
        s.notifyAll();
        "".length();
        if (-"   ".length() >= 0) {
          return;
        }
      }
      j = t[1];
    }
  }
  
  public static void z()
  {
    "".length();
    synchronized (s)
    {
      s.notifyAll();
      "".length();
      if ((('£' + 29 - 68 + 66 ^ '¡' + 76 - 89 + 25) & (75 + 1 - 40 + 108 ^ 47 + 40 - 1 + 45 ^ -" ".length())) == " ".length()) {
        return;
      }
    }
    b = t[1];
    i = t[1];
    o = t[1];
    c = t[1];
    h = t[1];
    n = t[1];
    q = t[1];
    d = t[1];
    m = t[1];
    a = t[1];
    r = t[1];
    p = t[1];
    g = t[1];
    j = t[1];
    k = t[1];
    e = t[1];
    et.w = t[1];
    et.k();
  }
  
  /* Error */
  public static boolean aa()
  {
    // Byte code:
    //   0: getstatic 66	cn:t	[I
    //   3: iconst_0
    //   4: iaload
    //   5: putstatic 48	cn:b	Z
    //   8: invokestatic 111	java/lang/System:currentTimeMillis	()J
    //   11: lstore_0
    //   12: getstatic 65	cn:s	Ljava/lang/Object;
    //   15: ldc 1
    //   17: invokevirtual 110	java/lang/String:length	()I
    //   20: pop2
    //   21: getstatic 65	cn:s	Ljava/lang/Object;
    //   24: dup
    //   25: astore_2
    //   26: monitorenter
    //   27: getstatic 65	cn:s	Ljava/lang/Object;
    //   30: lconst_1
    //   31: invokevirtual 108	java/lang/Object:wait	(J)V
    //   34: ldc 1
    //   36: invokevirtual 110	java/lang/String:length	()I
    //   39: pop
    //   40: ldc 4
    //   42: invokevirtual 110	java/lang/String:length	()I
    //   45: bipush 31
    //   47: bipush 19
    //   49: iadd
    //   50: bipush -63
    //   52: isub
    //   53: bipush 45
    //   55: iadd
    //   56: sipush 137
    //   59: bipush 28
    //   61: iadd
    //   62: bipush 69
    //   64: isub
    //   65: bipush 58
    //   67: iadd
    //   68: ixor
    //   69: if_icmplt +42 -> 111
    //   72: bipush 101
    //   74: bipush 75
    //   76: ixor
    //   77: sipush 138
    //   80: sipush 163
    //   83: ixor
    //   84: ixor
    //   85: bipush 23
    //   87: bipush 46
    //   89: ixor
    //   90: bipush 96
    //   92: bipush 94
    //   94: ixor
    //   95: ixor
    //   96: ldc 2
    //   98: invokevirtual 110	java/lang/String:length	()I
    //   101: ineg
    //   102: ixor
    //   103: iand
    //   104: ireturn
    //   105: ldc 1
    //   107: invokevirtual 110	java/lang/String:length	()I
    //   110: pop2
    //   111: aload_2
    //   112: monitorexit
    //   113: ldc 1
    //   115: invokevirtual 110	java/lang/String:length	()I
    //   118: pop
    //   119: aconst_null
    //   120: ifnull +56 -> 176
    //   123: bipush 46
    //   125: sipush 132
    //   128: iadd
    //   129: bipush 46
    //   131: isub
    //   132: bipush 19
    //   134: iadd
    //   135: bipush 117
    //   137: sipush 171
    //   140: iadd
    //   141: sipush 152
    //   144: isub
    //   145: bipush 41
    //   147: iadd
    //   148: ixor
    //   149: sipush 213
    //   152: sipush 189
    //   155: ixor
    //   156: bipush 33
    //   158: bipush 111
    //   160: ixor
    //   161: ixor
    //   162: ldc 2
    //   164: invokevirtual 110	java/lang/String:length	()I
    //   167: ineg
    //   168: ixor
    //   169: iand
    //   170: ireturn
    //   171: astore_0
    //   172: aload_2
    //   173: monitorexit
    //   174: aload_0
    //   175: athrow
    //   176: invokestatic 111	java/lang/System:currentTimeMillis	()J
    //   179: lload_0
    //   180: lsub
    //   181: lconst_1
    //   182: invokestatic 94	cn:f	(JJ)I
    //   185: invokestatic 79	cn:a	(I)Z
    //   188: ifeq +9 -> 197
    //   191: getstatic 66	cn:t	[I
    //   194: iconst_0
    //   195: iaload
    //   196: ireturn
    //   197: getstatic 66	cn:t	[I
    //   200: iconst_1
    //   201: iaload
    //   202: ireturn
    // Local variable table:
    //   start	length	slot	name	signature
    //   11	1	0	l1	long
    //   171	9	0	localObject1	Object
    //   25	148	2	Ljava/lang/Object;	Object
    //   105	1	3	localInterruptedException	InterruptedException
    // Exception table:
    //   from	to	target	type
    //   27	34	105	java/lang/InterruptedException
    //   27	113	171	finally
  }
  
  private static boolean b(int paramInt1, int paramInt2)
  {
    return paramInt1 > paramInt2;
  }
  
  public static void b(long paramLong)
  {
    if (a(dn.as))
    {
      long l1 = System.currentTimeMillis();
      while ((c(ai())) && (a(b(System.currentTimeMillis() - l1, paramLong))))
      {
        try
        {
          Thread.sleep(2000L);
          "".length();
          if (-" ".length() <= 0) {
            continue;
          }
          return;
        }
        catch (InterruptedException localInterruptedException1)
        {
          InterruptedException localInterruptedException2;
          (localInterruptedException2 = localInterruptedException1).printStackTrace();
          "".length();
        }
        if (-" ".length() < -" ".length()) {}
      }
    }
  }
  
  public static void ab()
  {
    if (b(b))
    {
      "".length();
      synchronized (s)
      {
        s.notifyAll();
        "".length();
        if (-" ".length() > ((0xFB ^ 0xA4 ^ 0x20 ^ 0x49) & (109 + '' - 174 + 102 ^ 2 + 44 - 11 + 97 ^ -" ".length()))) {
          return;
        }
      }
      b = t[1];
    }
  }
  
  private static int h(long paramLong1, long paramLong2)
  {
    return paramLong1 < paramLong2;
  }
  
  /* Error */
  public static void ac()
  {
    // Byte code:
    //   0: getstatic 66	cn:t	[I
    //   3: iconst_0
    //   4: iaload
    //   5: putstatic 60	cn:n	Z
    //   8: getstatic 65	cn:s	Ljava/lang/Object;
    //   11: ldc 1
    //   13: invokevirtual 110	java/lang/String:length	()I
    //   16: pop2
    //   17: getstatic 65	cn:s	Ljava/lang/Object;
    //   20: dup
    //   21: astore_0
    //   22: monitorenter
    //   23: getstatic 65	cn:s	Ljava/lang/Object;
    //   26: ldc2_w 29
    //   29: invokevirtual 108	java/lang/Object:wait	(J)V
    //   32: ldc 1
    //   34: invokevirtual 110	java/lang/String:length	()I
    //   37: pop
    //   38: bipush 72
    //   40: bipush 78
    //   42: iadd
    //   43: bipush 15
    //   45: isub
    //   46: bipush 28
    //   48: iadd
    //   49: iconst_2
    //   50: sipush 136
    //   53: iadd
    //   54: bipush -5
    //   56: isub
    //   57: bipush 24
    //   59: iadd
    //   60: ixor
    //   61: ldc 4
    //   63: invokevirtual 110	java/lang/String:length	()I
    //   66: if_icmpge +10 -> 76
    //   69: return
    //   70: ldc 1
    //   72: invokevirtual 110	java/lang/String:length	()I
    //   75: pop2
    //   76: aload_0
    //   77: monitorexit
    //   78: return
    //   79: astore_1
    //   80: aload_0
    //   81: monitorexit
    //   82: aload_1
    //   83: athrow
    // Local variable table:
    //   start	length	slot	name	signature
    //   21	60	0	Ljava/lang/Object;	Object
    //   79	4	1	localObject1	Object
    //   70	1	2	localInterruptedException	InterruptedException
    // Exception table:
    //   from	to	target	type
    //   23	32	70	java/lang/InterruptedException
    //   23	78	79	finally
  }
  
  public static void ad()
  {
    if (a(dn.as))
    {
      long l1 = System.currentTimeMillis();
      while ((c(l())) && (a(i(System.currentTimeMillis() - l1, 60000L))))
      {
        try
        {
          Thread.sleep(2000L);
          "".length();
          if ((0x30 ^ 0x5F ^ 0x78 ^ 0x13) == (0xA3 ^ 0xC3 ^ 0x29 ^ 0x4D)) {
            continue;
          }
          return;
        }
        catch (InterruptedException localInterruptedException1)
        {
          InterruptedException localInterruptedException2;
          (localInterruptedException2 = localInterruptedException1).printStackTrace();
          "".length();
        }
        if (((0x4B ^ 0x53 ^ 0xF2 ^ 0xC4) & (0x50 ^ 0x3 ^ 0x67 ^ 0x1A ^ -" ".length())) != 0) {}
      }
    }
  }
  
  /* Error */
  public static boolean ae()
  {
    // Byte code:
    //   0: getstatic 66	cn:t	[I
    //   3: iconst_0
    //   4: iaload
    //   5: putstatic 59	cn:m	Z
    //   8: invokestatic 111	java/lang/System:currentTimeMillis	()J
    //   11: lstore_0
    //   12: getstatic 65	cn:s	Ljava/lang/Object;
    //   15: ldc 1
    //   17: invokevirtual 110	java/lang/String:length	()I
    //   20: pop2
    //   21: getstatic 65	cn:s	Ljava/lang/Object;
    //   24: dup
    //   25: astore_2
    //   26: monitorenter
    //   27: getstatic 65	cn:s	Ljava/lang/Object;
    //   30: ldc2_w 29
    //   33: invokevirtual 108	java/lang/Object:wait	(J)V
    //   36: ldc 1
    //   38: invokevirtual 110	java/lang/String:length	()I
    //   41: pop
    //   42: ldc 4
    //   44: invokevirtual 110	java/lang/String:length	()I
    //   47: ifne +25 -> 72
    //   50: sipush 161
    //   53: sipush 167
    //   56: ixor
    //   57: bipush 88
    //   59: bipush 94
    //   61: ixor
    //   62: iconst_m1
    //   63: ixor
    //   64: iand
    //   65: ireturn
    //   66: ldc 1
    //   68: invokevirtual 110	java/lang/String:length	()I
    //   71: pop2
    //   72: aload_2
    //   73: monitorexit
    //   74: ldc 1
    //   76: invokevirtual 110	java/lang/String:length	()I
    //   79: pop
    //   80: aconst_null
    //   81: ifnull +22 -> 103
    //   84: bipush 83
    //   86: bipush 17
    //   88: ixor
    //   89: bipush 13
    //   91: bipush 79
    //   93: ixor
    //   94: iconst_m1
    //   95: ixor
    //   96: iand
    //   97: ireturn
    //   98: astore_0
    //   99: aload_2
    //   100: monitorexit
    //   101: aload_0
    //   102: athrow
    //   103: invokestatic 111	java/lang/System:currentTimeMillis	()J
    //   106: lload_0
    //   107: lsub
    //   108: ldc2_w 29
    //   111: invokestatic 95	cn:g	(JJ)I
    //   114: invokestatic 79	cn:a	(I)Z
    //   117: ifeq +9 -> 126
    //   120: getstatic 66	cn:t	[I
    //   123: iconst_0
    //   124: iaload
    //   125: ireturn
    //   126: getstatic 66	cn:t	[I
    //   129: iconst_1
    //   130: iaload
    //   131: ireturn
    // Local variable table:
    //   start	length	slot	name	signature
    //   11	1	0	l1	long
    //   98	9	0	localObject1	Object
    //   25	75	2	Ljava/lang/Object;	Object
    //   66	1	3	localInterruptedException	InterruptedException
    // Exception table:
    //   from	to	target	type
    //   27	36	66	java/lang/InterruptedException
    //   27	74	98	finally
  }
  
  public static void af()
  {
    if (b(q))
    {
      "".length();
      synchronized (s)
      {
        s.notifyAll();
        "".length();
        if ((69 + '©' - 200 + 139 ^ '' + 9 - 17 + 44) != (0x18 ^ 0x3E ^ 0x97 ^ 0xB5)) {
          return;
        }
      }
      q = t[1];
    }
  }
  
  private static boolean c(int paramInt1, int paramInt2)
  {
    return paramInt1 < paramInt2;
  }
  
  public static void ag()
  {
    if (b(m))
    {
      "".length();
      synchronized (s)
      {
        s.notifyAll();
        "".length();
        if (((0x3C ^ 0x6) & (0x1E ^ 0x24 ^ 0xFFFFFFFF)) > " ".length()) {
          return;
        }
      }
      m = t[1];
    }
  }
  
  private static int i(long paramLong1, long paramLong2)
  {
    return paramLong1 < paramLong2;
  }
  
  public static void ah()
  {
    if (b(e))
    {
      "".length();
      synchronized (s)
      {
        s.notifyAll();
        "".length();
        if (((0x37 ^ 0x2F) & (0x31 ^ 0x29 ^ 0xFFFFFFFF)) <= -" ".length()) {
          return;
        }
      }
      e = t[1];
    }
  }
  
  public static boolean ai()
  {
    int i1 = t[1];
    if (c(i1, dn.p.size()))
    {
      String str = (String)dn.p.elementAt(i1);
      int i2 = t[1];
      for (;;)
      {
        if (c(i2, fn.ax.size()))
        {
          bk localbk;
          if (b((localbk = (bk)fn.ax.elementAt(i2)).a.equals(str)))
          {
            if ((!a(localbk.f)) || (b(bc.a(dt.g().eg, dt.g().ey, localbk.f.eg, localbk.f.ey), t[2]))) {
              return t[1];
            }
            i1++;
            "".length();
            if ("  ".length() >= 0) {
              break;
            }
            return "   ".length() & ("   ".length() ^ 0xFFFFFFFF);
          }
          i2++;
          "".length();
          if (null != null) {
            return (0x63 ^ 0x36) & (0x3B ^ 0x6E ^ 0xFFFFFFFF);
          }
        }
      }
      return t[1];
    }
    return t[0];
  }
  
  public static void aj()
  {
    if (b(o))
    {
      "".length();
      synchronized (s)
      {
        s.notifyAll();
        "".length();
        if (null != null) {
          return;
        }
      }
      o = t[1];
    }
  }
  
  private static int j(long paramLong1, long paramLong2)
  {
    return paramLong1 < paramLong2;
  }
  
  public static void ak()
  {
    if (b(i))
    {
      "".length();
      synchronized (s)
      {
        s.notifyAll();
        "".length();
        if (-" ".length() == ('¥' + 72 - 129 + 69 ^ 31 + 36 - -28 + 86)) {
          return;
        }
      }
      i = t[1];
    }
  }
  
  public static void al()
  {
    if (b(h))
    {
      "".length();
      synchronized (s)
      {
        s.notifyAll();
        "".length();
        if (((0xA0 ^ 0x8F) & (0x3E ^ 0x11 ^ 0xFFFFFFFF)) != 0) {
          return;
        }
      }
      h = t[1];
    }
  }
  
  public static void am() {}
}


/* Location:              C:\Users\Admin\OneDrive\Documents\NSOv2_test.jar!\cn.class
 * Java compiler version: 1 (45.3)
 * JD-Core Version:       0.7.1
 */