import java.io.ByteArrayInputStream;
import java.io.ByteArrayOutputStream;
import java.io.DataInputStream;
import java.io.DataOutputStream;
import javax.microedition.lcdui.ChoiceGroup;
import javax.microedition.lcdui.Command;
import javax.microedition.lcdui.CommandListener;
import javax.microedition.lcdui.Displayable;
import javax.microedition.lcdui.TextField;
import javax.microedition.rms.RecordStore;

public final class cz
  implements CommandListener
{
  public static int a;
  public static int b;
  public static boolean c;
  public static String d;
  private static ByteArrayOutputStream p;
  private TextField q = new TextField("Map Đánh Quái (Kiếm Yên + Nhặt Đá)", a, r[2], r[1]);
  private static int[] r;
  public static int e;
  private TextField s = new TextField("Tên Đối Thủ + ',': <Cách nhau bằng dấu phảy ','> ;", d, r[3], r[4]);
  private static RecordStore t;
  private TextField u = new TextField("Map Cừu Sát", b, r[2], r[2]);
  private TextField v = new TextField("Map Cừu Sát", e, r[2], r[2]);
  private TextField w = new TextField("Khu lôi đài", f, r[2], r[5]);
  public static int f;
  private final ChoiceGroup x = new ChoiceGroup("Hủy NVDV!!", r[5], new String[] { "Đánh Tinh Anh", "Đánh Thủ Lĩnh", "Nâng Cấp Trang Bị", "Lôi Đài", "Kiếm Yên", "Cừu Sát" }, null);
  public static boolean g;
  private final ChoiceGroup y = new ChoiceGroup("Cài Dùng Bảo Hiểm NVDV Nâng Cấp!!", r[5], new String[] { "Dùng Bào Hiểm Nâng Lên 7", "Dùng Bào Hiểm Nâng Lên 8" }, null);
  public static boolean h;
  private static DataOutputStream z;
  private final Command aa = new Command("Lưu", r[0], r[1]);
  private final gn ab = new gn("menu dv");
  private final Command ac = new Command("Hủy", r[2], r[1]);
  public static boolean i;
  public static int j;
  public static boolean k;
  private TextField ad = new TextField("Khu Đánh Quái (Kiếm Yên + Nhặt Đá)", j, r[2], r[1]);
  public static int l;
  public static boolean m;
  private static DataInputStream ae;
  private TextField af = new TextField("Map lôi đài", l, r[2], r[5]);
  private static ByteArrayInputStream ag;
  public static boolean n;
  public static boolean o;
  
  private static boolean a(int paramInt)
  {
    return paramInt != 0;
  }
  
  private static boolean b(int paramInt)
  {
    return paramInt == 0;
  }
  
  private static void a(Displayable paramDisplayable)
  {
    gb.a(bv.d).a(paramDisplayable);
  }
  
  /* Error */
  public final void commandAction(Command paramCommand, Displayable paramDisplayable)
  {
    // Byte code:
    //   0: aload_1
    //   1: aload_0
    //   2: getfield 54	cz:aa	Ljavax/microedition/lcdui/Command;
    //   5: invokestatic 90	cz:a	(Ljava/lang/Object;Ljava/lang/Object;)Z
    //   8: ifeq +570 -> 578
    //   11: aload_0
    //   12: getfield 78	cz:s	Ljavax/microedition/lcdui/TextField;
    //   15: invokevirtual 128	javax/microedition/lcdui/TextField:getString	()Ljava/lang/String;
    //   18: putstatic 63	cz:d	Ljava/lang/String;
    //   21: aload_0
    //   22: getfield 59	cz:af	Ljavax/microedition/lcdui/TextField;
    //   25: invokevirtual 128	javax/microedition/lcdui/TextField:getString	()Ljava/lang/String;
    //   28: invokestatic 115	java/lang/Integer:parseInt	(Ljava/lang/String;)I
    //   31: putstatic 71	cz:l	I
    //   34: aload_0
    //   35: getfield 82	cz:w	Ljavax/microedition/lcdui/TextField;
    //   38: invokevirtual 128	javax/microedition/lcdui/TextField:getString	()Ljava/lang/String;
    //   41: invokestatic 115	java/lang/Integer:parseInt	(Ljava/lang/String;)I
    //   44: putstatic 65	cz:f	I
    //   47: aload_0
    //   48: getfield 76	cz:q	Ljavax/microedition/lcdui/TextField;
    //   51: invokevirtual 128	javax/microedition/lcdui/TextField:getString	()Ljava/lang/String;
    //   54: invokestatic 115	java/lang/Integer:parseInt	(Ljava/lang/String;)I
    //   57: putstatic 53	cz:a	I
    //   60: aload_0
    //   61: getfield 57	cz:ad	Ljavax/microedition/lcdui/TextField;
    //   64: invokevirtual 128	javax/microedition/lcdui/TextField:getString	()Ljava/lang/String;
    //   67: invokestatic 115	java/lang/Integer:parseInt	(Ljava/lang/String;)I
    //   70: putstatic 69	cz:j	I
    //   73: aload_0
    //   74: getfield 80	cz:u	Ljavax/microedition/lcdui/TextField;
    //   77: invokevirtual 128	javax/microedition/lcdui/TextField:getString	()Ljava/lang/String;
    //   80: invokestatic 115	java/lang/Integer:parseInt	(Ljava/lang/String;)I
    //   83: putstatic 61	cz:b	I
    //   86: aload_0
    //   87: getfield 81	cz:v	Ljavax/microedition/lcdui/TextField;
    //   90: invokevirtual 128	javax/microedition/lcdui/TextField:getString	()Ljava/lang/String;
    //   93: invokestatic 115	java/lang/Integer:parseInt	(Ljava/lang/String;)I
    //   96: putstatic 64	cz:e	I
    //   99: aload_0
    //   100: getfield 83	cz:x	Ljavax/microedition/lcdui/ChoiceGroup;
    //   103: getstatic 77	cz:r	[I
    //   106: iconst_4
    //   107: iaload
    //   108: invokevirtual 122	javax/microedition/lcdui/ChoiceGroup:isSelected	(I)Z
    //   111: putstatic 70	cz:k	Z
    //   114: aload_0
    //   115: getfield 83	cz:x	Ljavax/microedition/lcdui/ChoiceGroup;
    //   118: getstatic 77	cz:r	[I
    //   121: iconst_1
    //   122: iaload
    //   123: invokevirtual 122	javax/microedition/lcdui/ChoiceGroup:isSelected	(I)Z
    //   126: putstatic 74	cz:o	Z
    //   129: aload_0
    //   130: getfield 83	cz:x	Ljavax/microedition/lcdui/ChoiceGroup;
    //   133: getstatic 77	cz:r	[I
    //   136: iconst_5
    //   137: iaload
    //   138: invokevirtual 122	javax/microedition/lcdui/ChoiceGroup:isSelected	(I)Z
    //   141: putstatic 73	cz:n	Z
    //   144: aload_0
    //   145: getfield 83	cz:x	Ljavax/microedition/lcdui/ChoiceGroup;
    //   148: getstatic 77	cz:r	[I
    //   151: iconst_2
    //   152: iaload
    //   153: invokevirtual 122	javax/microedition/lcdui/ChoiceGroup:isSelected	(I)Z
    //   156: putstatic 68	cz:i	Z
    //   159: aload_0
    //   160: getfield 83	cz:x	Ljavax/microedition/lcdui/ChoiceGroup;
    //   163: getstatic 77	cz:r	[I
    //   166: iconst_0
    //   167: iaload
    //   168: invokevirtual 122	javax/microedition/lcdui/ChoiceGroup:isSelected	(I)Z
    //   171: putstatic 66	cz:g	Z
    //   174: aload_0
    //   175: getfield 83	cz:x	Ljavax/microedition/lcdui/ChoiceGroup;
    //   178: getstatic 77	cz:r	[I
    //   181: bipush 7
    //   183: iaload
    //   184: invokevirtual 122	javax/microedition/lcdui/ChoiceGroup:isSelected	(I)Z
    //   187: putstatic 67	cz:h	Z
    //   190: aload_0
    //   191: getfield 84	cz:y	Ljavax/microedition/lcdui/ChoiceGroup;
    //   194: getstatic 77	cz:r	[I
    //   197: iconst_4
    //   198: iaload
    //   199: invokevirtual 122	javax/microedition/lcdui/ChoiceGroup:isSelected	(I)Z
    //   202: putstatic 62	cz:c	Z
    //   205: aload_0
    //   206: getfield 84	cz:y	Ljavax/microedition/lcdui/ChoiceGroup;
    //   209: getstatic 77	cz:r	[I
    //   212: iconst_1
    //   213: iaload
    //   214: invokevirtual 122	javax/microedition/lcdui/ChoiceGroup:isSelected	(I)Z
    //   217: putstatic 72	cz:m	Z
    //   220: new 36	java/io/ByteArrayOutputStream
    //   223: dup
    //   224: invokespecial 101	java/io/ByteArrayOutputStream:<init>	()V
    //   227: putstatic 75	cz:p	Ljava/io/ByteArrayOutputStream;
    //   230: new 38	java/io/DataOutputStream
    //   233: dup
    //   234: getstatic 75	cz:p	Ljava/io/ByteArrayOutputStream;
    //   237: invokespecial 108	java/io/DataOutputStream:<init>	(Ljava/io/OutputStream;)V
    //   240: putstatic 85	cz:z	Ljava/io/DataOutputStream;
    //   243: getstatic 85	cz:z	Ljava/io/DataOutputStream;
    //   246: getstatic 63	cz:d	Ljava/lang/String;
    //   249: invokevirtual 113	java/io/DataOutputStream:writeUTF	(Ljava/lang/String;)V
    //   252: getstatic 85	cz:z	Ljava/io/DataOutputStream;
    //   255: getstatic 71	cz:l	I
    //   258: invokevirtual 112	java/io/DataOutputStream:writeInt	(I)V
    //   261: getstatic 85	cz:z	Ljava/io/DataOutputStream;
    //   264: getstatic 65	cz:f	I
    //   267: invokevirtual 112	java/io/DataOutputStream:writeInt	(I)V
    //   270: getstatic 85	cz:z	Ljava/io/DataOutputStream;
    //   273: getstatic 53	cz:a	I
    //   276: invokevirtual 112	java/io/DataOutputStream:writeInt	(I)V
    //   279: getstatic 85	cz:z	Ljava/io/DataOutputStream;
    //   282: getstatic 69	cz:j	I
    //   285: invokevirtual 112	java/io/DataOutputStream:writeInt	(I)V
    //   288: getstatic 85	cz:z	Ljava/io/DataOutputStream;
    //   291: getstatic 61	cz:b	I
    //   294: invokevirtual 112	java/io/DataOutputStream:writeInt	(I)V
    //   297: getstatic 85	cz:z	Ljava/io/DataOutputStream;
    //   300: getstatic 64	cz:e	I
    //   303: invokevirtual 112	java/io/DataOutputStream:writeInt	(I)V
    //   306: getstatic 85	cz:z	Ljava/io/DataOutputStream;
    //   309: getstatic 70	cz:k	Z
    //   312: invokevirtual 111	java/io/DataOutputStream:writeBoolean	(Z)V
    //   315: getstatic 85	cz:z	Ljava/io/DataOutputStream;
    //   318: getstatic 74	cz:o	Z
    //   321: invokevirtual 111	java/io/DataOutputStream:writeBoolean	(Z)V
    //   324: getstatic 85	cz:z	Ljava/io/DataOutputStream;
    //   327: getstatic 73	cz:n	Z
    //   330: invokevirtual 111	java/io/DataOutputStream:writeBoolean	(Z)V
    //   333: getstatic 85	cz:z	Ljava/io/DataOutputStream;
    //   336: getstatic 68	cz:i	Z
    //   339: invokevirtual 111	java/io/DataOutputStream:writeBoolean	(Z)V
    //   342: getstatic 85	cz:z	Ljava/io/DataOutputStream;
    //   345: getstatic 66	cz:g	Z
    //   348: invokevirtual 111	java/io/DataOutputStream:writeBoolean	(Z)V
    //   351: getstatic 85	cz:z	Ljava/io/DataOutputStream;
    //   354: getstatic 67	cz:h	Z
    //   357: invokevirtual 111	java/io/DataOutputStream:writeBoolean	(Z)V
    //   360: getstatic 85	cz:z	Ljava/io/DataOutputStream;
    //   363: getstatic 62	cz:c	Z
    //   366: invokevirtual 111	java/io/DataOutputStream:writeBoolean	(Z)V
    //   369: getstatic 85	cz:z	Ljava/io/DataOutputStream;
    //   372: getstatic 72	cz:m	Z
    //   375: invokevirtual 111	java/io/DataOutputStream:writeBoolean	(Z)V
    //   378: getstatic 85	cz:z	Ljava/io/DataOutputStream;
    //   381: invokevirtual 110	java/io/DataOutputStream:flush	()V
    //   384: getstatic 85	cz:z	Ljava/io/DataOutputStream;
    //   387: invokevirtual 109	java/io/DataOutputStream:close	()V
    //   390: getstatic 75	cz:p	Ljava/io/ByteArrayOutputStream;
    //   393: invokevirtual 114	java/io/OutputStream:flush	()V
    //   396: ldc 20
    //   398: getstatic 77	cz:r	[I
    //   401: iconst_1
    //   402: iaload
    //   403: invokestatic 97	gk:b	(Ljava/lang/String;Z)Ljavax/microedition/rms/RecordStore;
    //   406: putstatic 79	cz:t	Ljavax/microedition/rms/RecordStore;
    //   409: getstatic 75	cz:p	Ljava/io/ByteArrayOutputStream;
    //   412: invokevirtual 103	java/io/ByteArrayOutputStream:toByteArray	()[B
    //   415: astore_1
    //   416: getstatic 75	cz:p	Ljava/io/ByteArrayOutputStream;
    //   419: invokevirtual 102	java/io/ByteArrayOutputStream:close	()V
    //   422: getstatic 79	cz:t	Ljavax/microedition/rms/RecordStore;
    //   425: invokevirtual 131	javax/microedition/rms/RecordStore:getNumRecords	()I
    //   428: invokestatic 92	cz:b	(I)Z
    //   431: ifeq +45 -> 476
    //   434: getstatic 79	cz:t	Ljavax/microedition/rms/RecordStore;
    //   437: aload_1
    //   438: getstatic 77	cz:r	[I
    //   441: iconst_4
    //   442: iaload
    //   443: aload_1
    //   444: arraylength
    //   445: invokevirtual 129	javax/microedition/rms/RecordStore:addRecord	([BII)I
    //   448: ldc 1
    //   450: invokevirtual 117	java/lang/String:length	()I
    //   453: pop2
    //   454: ldc 1
    //   456: invokevirtual 117	java/lang/String:length	()I
    //   459: pop
    //   460: ldc 4
    //   462: invokevirtual 117	java/lang/String:length	()I
    //   465: sipush 163
    //   468: sipush 167
    //   471: ixor
    //   472: if_icmplt +23 -> 495
    //   475: return
    //   476: getstatic 79	cz:t	Ljavax/microedition/rms/RecordStore;
    //   479: getstatic 77	cz:r	[I
    //   482: iconst_1
    //   483: iaload
    //   484: aload_1
    //   485: getstatic 77	cz:r	[I
    //   488: iconst_4
    //   489: iaload
    //   490: aload_1
    //   491: arraylength
    //   492: invokevirtual 133	javax/microedition/rms/RecordStore:setRecord	(I[BII)V
    //   495: getstatic 79	cz:t	Ljavax/microedition/rms/RecordStore;
    //   498: invokevirtual 130	javax/microedition/rms/RecordStore:closeRecordStore	()V
    //   501: ldc 1
    //   503: invokevirtual 117	java/lang/String:length	()I
    //   506: pop
    //   507: iconst_5
    //   508: bipush 21
    //   510: ixor
    //   511: sipush 133
    //   514: sipush 149
    //   517: ixor
    //   518: iconst_m1
    //   519: ixor
    //   520: iand
    //   521: ldc 2
    //   523: invokevirtual 117	java/lang/String:length	()I
    //   526: if_icmplt +10 -> 536
    //   529: return
    //   530: ldc 1
    //   532: invokevirtual 117	java/lang/String:length	()I
    //   535: pop2
    //   536: ldc 16
    //   538: invokestatic 86	aw:a	(Ljava/lang/String;)V
    //   541: ldc 1
    //   543: invokevirtual 117	java/lang/String:length	()I
    //   546: pop
    //   547: ldc 2
    //   549: invokevirtual 117	java/lang/String:length	()I
    //   552: ineg
    //   553: sipush 196
    //   556: sipush 139
    //   559: ixor
    //   560: bipush 104
    //   562: bipush 39
    //   564: ixor
    //   565: iconst_m1
    //   566: ixor
    //   567: iand
    //   568: if_icmplt +10 -> 578
    //   571: return
    //   572: ldc 1
    //   574: invokevirtual 117	java/lang/String:length	()I
    //   577: pop2
    //   578: invokestatic 94	dm:d	()Ldm;
    //   581: invokestatic 91	cz:a	(Ljavax/microedition/lcdui/Displayable;)V
    //   584: return
    // Local variable table:
    //   start	length	slot	name	signature
    //   0	585	0	this	cz
    //   0	585	1	paramCommand	Command
    //   0	585	2	paramDisplayable	Displayable
    //   530	1	3	localException	Exception
    //   572	1	4	localNumberFormatException	NumberFormatException
    // Exception table:
    //   from	to	target	type
    //   243	501	530	java/lang/Exception
    //   11	541	572	java/lang/NumberFormatException
  }
  
  private static void d()
  {
    r = new int[10];
    r[0] = (0xEA ^ 0x85 ^ 0x6B ^ 0x0);
    r[1] = " ".length();
    r[2] = "   ".length();
    r[3] = (-(0xF4F6 & 0x3B5F) & 0xFF5F & 0x34F5);
    r[4] = ((0x78 ^ 0x52) & (0xBB ^ 0x91 ^ 0xFFFFFFFF));
    r[5] = "  ".length();
    r[6] = (0x8A ^ 0x8C);
    r[7] = (0x2B ^ 0x2E);
    r[8] = (33 + 46 - 52 + 163 ^ 112 + 107 - 164 + 115);
    r[9] = (-" ".length());
  }
  
  /* Error */
  public static void a()
  {
    // Byte code:
    //   0: invokestatic 93	cz:d	()V
    //   3: ldc 24
    //   5: putstatic 63	cz:d	Ljava/lang/String;
    //   8: getstatic 77	cz:r	[I
    //   11: iconst_4
    //   12: iaload
    //   13: putstatic 70	cz:k	Z
    //   16: getstatic 77	cz:r	[I
    //   19: iconst_4
    //   20: iaload
    //   21: putstatic 74	cz:o	Z
    //   24: getstatic 77	cz:r	[I
    //   27: iconst_4
    //   28: iaload
    //   29: putstatic 73	cz:n	Z
    //   32: getstatic 77	cz:r	[I
    //   35: iconst_4
    //   36: iaload
    //   37: putstatic 68	cz:i	Z
    //   40: getstatic 77	cz:r	[I
    //   43: iconst_4
    //   44: iaload
    //   45: putstatic 66	cz:g	Z
    //   48: getstatic 77	cz:r	[I
    //   51: iconst_4
    //   52: iaload
    //   53: putstatic 67	cz:h	Z
    //   56: getstatic 77	cz:r	[I
    //   59: iconst_4
    //   60: iaload
    //   61: putstatic 62	cz:c	Z
    //   64: getstatic 77	cz:r	[I
    //   67: iconst_4
    //   68: iaload
    //   69: putstatic 72	cz:m	Z
    //   72: getstatic 77	cz:r	[I
    //   75: iconst_1
    //   76: iaload
    //   77: putstatic 71	cz:l	I
    //   80: getstatic 77	cz:r	[I
    //   83: bipush 8
    //   85: iaload
    //   86: putstatic 65	cz:f	I
    //   89: getstatic 77	cz:r	[I
    //   92: bipush 9
    //   94: iaload
    //   95: putstatic 53	cz:a	I
    //   98: getstatic 77	cz:r	[I
    //   101: bipush 9
    //   103: iaload
    //   104: putstatic 69	cz:j	I
    //   107: getstatic 77	cz:r	[I
    //   110: iconst_5
    //   111: iaload
    //   112: putstatic 61	cz:b	I
    //   115: getstatic 77	cz:r	[I
    //   118: iconst_4
    //   119: iaload
    //   120: putstatic 64	cz:e	I
    //   123: ldc 20
    //   125: getstatic 77	cz:r	[I
    //   128: iconst_1
    //   129: iaload
    //   130: invokestatic 97	gk:b	(Ljava/lang/String;Z)Ljavax/microedition/rms/RecordStore;
    //   133: dup
    //   134: putstatic 79	cz:t	Ljavax/microedition/rms/RecordStore;
    //   137: invokevirtual 131	javax/microedition/rms/RecordStore:getNumRecords	()I
    //   140: invokestatic 89	cz:a	(I)Z
    //   143: ifeq +170 -> 313
    //   146: new 35	java/io/ByteArrayInputStream
    //   149: dup
    //   150: getstatic 79	cz:t	Ljavax/microedition/rms/RecordStore;
    //   153: getstatic 77	cz:r	[I
    //   156: iconst_1
    //   157: iaload
    //   158: invokevirtual 132	javax/microedition/rms/RecordStore:getRecord	(I)[B
    //   161: invokespecial 100	java/io/ByteArrayInputStream:<init>	([B)V
    //   164: putstatic 60	cz:ag	Ljava/io/ByteArrayInputStream;
    //   167: new 37	java/io/DataInputStream
    //   170: dup
    //   171: getstatic 60	cz:ag	Ljava/io/ByteArrayInputStream;
    //   174: invokespecial 104	java/io/DataInputStream:<init>	(Ljava/io/InputStream;)V
    //   177: dup
    //   178: putstatic 58	cz:ae	Ljava/io/DataInputStream;
    //   181: invokevirtual 107	java/io/DataInputStream:readUTF	()Ljava/lang/String;
    //   184: putstatic 63	cz:d	Ljava/lang/String;
    //   187: getstatic 58	cz:ae	Ljava/io/DataInputStream;
    //   190: invokevirtual 106	java/io/DataInputStream:readInt	()I
    //   193: putstatic 71	cz:l	I
    //   196: getstatic 58	cz:ae	Ljava/io/DataInputStream;
    //   199: invokevirtual 106	java/io/DataInputStream:readInt	()I
    //   202: putstatic 65	cz:f	I
    //   205: getstatic 58	cz:ae	Ljava/io/DataInputStream;
    //   208: invokevirtual 106	java/io/DataInputStream:readInt	()I
    //   211: putstatic 53	cz:a	I
    //   214: getstatic 58	cz:ae	Ljava/io/DataInputStream;
    //   217: invokevirtual 106	java/io/DataInputStream:readInt	()I
    //   220: putstatic 69	cz:j	I
    //   223: getstatic 58	cz:ae	Ljava/io/DataInputStream;
    //   226: invokevirtual 106	java/io/DataInputStream:readInt	()I
    //   229: putstatic 61	cz:b	I
    //   232: getstatic 58	cz:ae	Ljava/io/DataInputStream;
    //   235: invokevirtual 106	java/io/DataInputStream:readInt	()I
    //   238: putstatic 64	cz:e	I
    //   241: getstatic 58	cz:ae	Ljava/io/DataInputStream;
    //   244: invokevirtual 105	java/io/DataInputStream:readBoolean	()Z
    //   247: putstatic 70	cz:k	Z
    //   250: getstatic 58	cz:ae	Ljava/io/DataInputStream;
    //   253: invokevirtual 105	java/io/DataInputStream:readBoolean	()Z
    //   256: putstatic 74	cz:o	Z
    //   259: getstatic 58	cz:ae	Ljava/io/DataInputStream;
    //   262: invokevirtual 105	java/io/DataInputStream:readBoolean	()Z
    //   265: putstatic 73	cz:n	Z
    //   268: getstatic 58	cz:ae	Ljava/io/DataInputStream;
    //   271: invokevirtual 105	java/io/DataInputStream:readBoolean	()Z
    //   274: putstatic 68	cz:i	Z
    //   277: getstatic 58	cz:ae	Ljava/io/DataInputStream;
    //   280: invokevirtual 105	java/io/DataInputStream:readBoolean	()Z
    //   283: putstatic 66	cz:g	Z
    //   286: getstatic 58	cz:ae	Ljava/io/DataInputStream;
    //   289: invokevirtual 105	java/io/DataInputStream:readBoolean	()Z
    //   292: putstatic 67	cz:h	Z
    //   295: getstatic 58	cz:ae	Ljava/io/DataInputStream;
    //   298: invokevirtual 105	java/io/DataInputStream:readBoolean	()Z
    //   301: putstatic 62	cz:c	Z
    //   304: getstatic 58	cz:ae	Ljava/io/DataInputStream;
    //   307: invokevirtual 105	java/io/DataInputStream:readBoolean	()Z
    //   310: putstatic 72	cz:m	Z
    //   313: getstatic 79	cz:t	Ljavax/microedition/rms/RecordStore;
    //   316: invokevirtual 130	javax/microedition/rms/RecordStore:closeRecordStore	()V
    //   319: return
    //   320: ldc 1
    //   322: invokevirtual 117	java/lang/String:length	()I
    //   325: pop2
    //   326: return
    // Local variable table:
    //   start	length	slot	name	signature
    //   320	1	0	localException	Exception
    // Exception table:
    //   from	to	target	type
    //   123	319	320	java/lang/Exception
  }
  
  static
  {
    cs.a(162);
    a();
  }
  
  public final void b()
  {
    "".length();
    "".length();
    "".length();
    "".length();
    "".length();
    "".length();
    "".length();
    "".length();
    "".length();
    this.ab.addCommand(this.aa);
    this.ab.addCommand(this.ac);
    this.ab.setCommandListener(this);
    this.x.setSelectedIndex(r[4], k);
    this.x.setSelectedIndex(r[1], o);
    this.x.setSelectedIndex(r[5], n);
    this.x.setSelectedIndex(r[2], i);
    this.x.setSelectedIndex(r[0], g);
    this.x.setSelectedIndex(r[7], h);
    this.y.setSelectedIndex(r[4], c);
    this.y.setSelectedIndex(r[1], m);
    a(this.ab);
  }
  
  private static boolean a(Object paramObject1, Object paramObject2)
  {
    return paramObject1 == paramObject2;
  }
  
  public static void c() {}
}


/* Location:              C:\Users\Admin\OneDrive\Documents\NSOv2_test.jar!\cz.class
 * Java compiler version: 1 (45.3)
 * JD-Core Version:       0.7.1
 */