public final class db
  implements Runnable
{
  private static int[] b;
  private final au c;
  private String d;
  public final au a;
  
  public db(au paramau1, au paramau2)
  {
    this.c = paramau1;
    this.d = new String(new char[] { b[2], b[4], b[6], b[8], b[10], b[12], b[14], b[16], b[16], b[2], b[20], b[22], b[24], b[12], b[27], b[29], b[4], b[32], b[34], b[36], b[4], b[6], b[32], b[41], b[32], b[44], b[46], b[24], b[6], b[4], b[51], b[14], b[22], b[55], b[55], b[55], b[55] });
    this.a = paramau2;
  }
  
  private static void c()
  {
    b = new int[60];
    b[0] = (0x26 ^ 0x3);
    b[1] = ((0x2D ^ 0x27) & (0x80 ^ 0x8A ^ 0xFFFFFFFF));
    b[2] = (47 + '' - -20 + 38 ^ 81 + 64 - 14 + 28);
    b[3] = " ".length();
    b[4] = (0x1A ^ 0x75);
    b[5] = "  ".length();
    b[6] = (0x50 ^ 0x7A ^ 0xE4 ^ 0xAD);
    b[7] = "   ".length();
    b[8] = (0x37 ^ 0x54 ^ 0x9B ^ 0x93);
    b[9] = (0x1B ^ 0x9 ^ 0x92 ^ 0x84);
    b[10] = (0x69 ^ 0xC);
    b[11] = (0x6A ^ 0x6F);
    b[12] = (0x18 ^ 0x6C);
    b[13] = (0x88 ^ 0x93 ^ 0x2D ^ 0x30);
    b[14] = (0x62 ^ 0x58);
    b[15] = (52 + 14 - -39 + 59 ^ 74 + 97 - 83 + 75);
    b[16] = (0xF4 ^ 0xBF ^ 0x52 ^ 0x36);
    b[17] = (0x10 ^ 0x49 ^ 0xFE ^ 0xAF);
    b[18] = (0x51 ^ 0xB ^ 0x2 ^ 0x51);
    b[19] = (0x99 ^ 0x93);
    b[20] = (0xEE ^ 0x98);
    b[21] = (0x27 ^ 0x2C);
    b[22] = (0xE ^ 0x77 ^ 0xF9 ^ 0xB1);
    b[23] = (0xBF ^ 0xAF ^ 0x8A ^ 0x96);
    b[24] = (0xAF ^ 0x81);
    b[25] = (0x1E ^ 0x13);
    b[26] = (0xEF ^ 0x8B ^ 0xE1 ^ 0x8B);
    b[27] = (0xF ^ 0x7D);
    b[28] = (0x17 ^ 0x7B ^ 0x11 ^ 0x72);
    b[29] = (0x1A ^ 0x6A ^ 0x59 ^ 0x5C);
    b[30] = (0x34 ^ 0x24);
    b[31] = (0x1 ^ 0x10);
    b[32] = (0xDE ^ 0xB2 ^ "  ".length());
    b[33] = (0xC ^ 0x1E);
    b[34] = (0x56 ^ 0x1F ^ 0xEB ^ 0xC5);
    b[35] = (0x7F ^ 0x6C);
    b[36] = (0x7A ^ 0xF ^ 0x4B ^ 0x56);
    b[37] = (0x91 ^ 0x85);
    b[38] = (0x77 ^ 0x62);
    b[39] = (0x3 ^ 0x15);
    b[40] = (40 + 105 - -55 + 11 ^ 16 + 62 - -5 + 113);
    b[41] = (0x1 ^ 0x5C ^ 0x8F ^ 0xBB);
    b[42] = (0xA0 ^ 0xB9 ^ " ".length());
    b[43] = (0x2B ^ 0x73 ^ 0x69 ^ 0x28);
    b[44] = (0x42 ^ 0x28);
    b[45] = (0xD2 ^ 0x87 ^ 0x7C ^ 0x33);
    b[46] = (0xC3 ^ 0xA2);
    b[47] = (0x44 ^ 0x5F);
    b[48] = (0xB8 ^ 0xAF ^ 0x18 ^ 0x13);
    b[49] = ('' + 119 - 149 + 87 ^ 48 + '' - 101 + 89);
    b[50] = (33 + 59 - -1 + 84 ^ 51 + 7 - -16 + 101);
    b[51] = (0x2C ^ 0x41);
    b[52] = (0x19 ^ 0x6);
    b[53] = (0x0 ^ 0x21 ^ " ".length());
    b[54] = (0x74 ^ 0x7 ^ 0x37 ^ 0x65);
    b[55] = (0x3A ^ 0x34 ^ 0x4C ^ 0x76);
    b[56] = (0x97 ^ 0xB5);
    b[57] = (0x86 ^ 0xA5);
    b[58] = (0xBA ^ 0x9E);
    b[59] = (-(0x8C ^ 0x9D ^ 0x82 ^ 0x88));
  }
  
  private static boolean a(Object paramObject)
  {
    return paramObject != null;
  }
  
  /* Error */
  public final void run()
  {
    // Byte code:
    //   0: aload_0
    //   1: getfield 28	db:a	Lau;
    //   4: new 17	java/lang/Thread
    //   7: dup
    //   8: new 8	cm
    //   11: dup
    //   12: aload_0
    //   13: getfield 30	db:c	Lau;
    //   16: aload_0
    //   17: invokespecial 44	cm:<init>	(Lau;Ldb;)V
    //   20: invokespecial 54	java/lang/Thread:<init>	(Ljava/lang/Runnable;)V
    //   23: invokestatic 35	au:b	(Lau;Ljava/lang/Thread;)V
    //   26: aload_0
    //   27: getfield 28	db:a	Lau;
    //   30: invokestatic 39	au:f	(Lau;)Ljava/lang/Thread;
    //   33: invokevirtual 55	java/lang/Thread:start	()V
    //   36: aload_0
    //   37: getfield 28	db:a	Lau;
    //   40: invokestatic 53	java/lang/System:currentTimeMillis	()J
    //   43: putfield 27	au:m	J
    //   46: aload_0
    //   47: getfield 28	db:a	Lau;
    //   50: getstatic 29	db:b	[I
    //   53: iconst_3
    //   54: iaload
    //   55: putfield 23	au:f	Z
    //   58: aload_0
    //   59: getfield 28	db:a	Lau;
    //   62: getstatic 29	db:b	[I
    //   65: iconst_3
    //   66: iaload
    //   67: putfield 22	au:d	Z
    //   70: aload_0
    //   71: getfield 28	db:a	Lau;
    //   74: aload_0
    //   75: getfield 31	db:d	Ljava/lang/String;
    //   78: invokestatic 49	gi:e	(Ljava/lang/String;)Ljavax/microedition/io/Connection;
    //   81: checkcast 20	javax/microedition/io/SocketConnection
    //   84: putfield 25	au:k	Ljavax/microedition/io/SocketConnection;
    //   87: aload_0
    //   88: getfield 28	db:a	Lau;
    //   91: aload_0
    //   92: getfield 28	db:a	Lau;
    //   95: getfield 25	au:k	Ljavax/microedition/io/SocketConnection;
    //   98: invokeinterface 59 1 0
    //   103: putfield 21	au:a	Ljava/io/DataOutputStream;
    //   106: aload_0
    //   107: getfield 28	db:a	Lau;
    //   110: aload_0
    //   111: getfield 28	db:a	Lau;
    //   114: getfield 25	au:k	Ljavax/microedition/io/SocketConnection;
    //   117: invokeinterface 58 1 0
    //   122: putfield 26	au:l	Ljava/io/DataInputStream;
    //   125: aload_0
    //   126: getfield 28	db:a	Lau;
    //   129: new 17	java/lang/Thread
    //   132: dup
    //   133: aload_0
    //   134: getfield 28	db:a	Lau;
    //   137: invokestatic 42	au:i	(Lau;)Lai;
    //   140: invokespecial 54	java/lang/Thread:<init>	(Ljava/lang/Runnable;)V
    //   143: invokestatic 37	au:c	(Lau;Ljava/lang/Thread;)V
    //   146: aload_0
    //   147: getfield 28	db:a	Lau;
    //   150: new 17	java/lang/Thread
    //   153: dup
    //   154: aload_0
    //   155: getfield 28	db:a	Lau;
    //   158: invokestatic 40	au:g	(Lau;)Lw;
    //   161: invokespecial 54	java/lang/Thread:<init>	(Ljava/lang/Runnable;)V
    //   164: invokestatic 34	au:a	(Lau;Ljava/lang/Thread;)V
    //   167: aload_0
    //   168: getfield 28	db:a	Lau;
    //   171: invokestatic 41	au:h	(Lau;)Ljava/lang/Thread;
    //   174: invokevirtual 55	java/lang/Thread:start	()V
    //   177: aload_0
    //   178: getfield 28	db:a	Lau;
    //   181: invokestatic 38	au:e	(Lau;)Ljava/lang/Thread;
    //   184: invokevirtual 55	java/lang/Thread:start	()V
    //   187: aload_0
    //   188: getfield 28	db:a	Lau;
    //   191: invokestatic 53	java/lang/System:currentTimeMillis	()J
    //   194: invokestatic 32	au:a	(Lau;J)V
    //   197: aload_0
    //   198: getfield 28	db:a	Lau;
    //   201: new 7	bj
    //   204: dup
    //   205: getstatic 29	db:b	[I
    //   208: bipush 59
    //   210: iaload
    //   211: invokespecial 43	bj:<init>	(B)V
    //   214: invokestatic 33	au:a	(Lau;Lbj;)V
    //   217: aload_0
    //   218: getfield 28	db:a	Lau;
    //   221: getstatic 29	db:b	[I
    //   224: iconst_1
    //   225: iaload
    //   226: putfield 23	au:f	Z
    //   229: aload_0
    //   230: getfield 28	db:a	Lau;
    //   233: getfield 24	au:i	Lac;
    //   236: invokeinterface 57 1 0
    //   241: return
    //   242: ldc 1
    //   244: invokevirtual 52	java/lang/String:length	()I
    //   247: pop2
    //   248: aload_0
    //   249: getfield 28	db:a	Lau;
    //   252: invokevirtual 36	au:c	()V
    //   255: aload_0
    //   256: getfield 28	db:a	Lau;
    //   259: getfield 24	au:i	Lac;
    //   262: invokestatic 47	db:a	(Ljava/lang/Object;)Z
    //   265: ifeq +15 -> 280
    //   268: aload_0
    //   269: getfield 28	db:a	Lau;
    //   272: getfield 24	au:i	Lac;
    //   275: invokeinterface 56 1 0
    //   280: return
    // Local variable table:
    //   start	length	slot	name	signature
    //   0	281	0	this	db
    //   242	1	1	localException	Exception
    // Exception table:
    //   from	to	target	type
    //   0	241	242	java/lang/Exception
  }
  
  public static void a() {}
  
  static
  {
    cs.a(72);
    a();
  }
  
  public static void b() {}
}


/* Location:              C:\Users\Admin\OneDrive\Documents\NSOv2_test.jar!\db.class
 * Java compiler version: 1 (45.3)
 * JD-Core Version:       0.7.1
 */