public final class dd
{
  public static ex a;
  public static ex b;
  private static int[] c;
  
  private static boolean a(int paramInt)
  {
    return paramInt != 0;
  }
  
  /* Error */
  public static void a(short paramShort, byte[] paramArrayOfByte)
  {
    // Byte code:
    //   0: getstatic 28	dd:b	Lex;
    //   3: iload_0
    //   4: invokestatic 55	java/lang/String:valueOf	(I)Ljava/lang/String;
    //   7: invokevirtual 51	ex:get	(Ljava/lang/Object;)Ljava/lang/Object;
    //   10: checkcast 21	p
    //   13: dup
    //   14: astore_2
    //   15: invokestatic 39	dd:a	(Ljava/lang/Object;)Z
    //   18: ifeq +11 -> 29
    //   21: new 21	p
    //   24: dup
    //   25: invokespecial 62	p:<init>	()V
    //   28: astore_2
    //   29: getstatic 28	dd:b	Lex;
    //   32: iload_0
    //   33: invokestatic 55	java/lang/String:valueOf	(I)Ljava/lang/String;
    //   36: aload_2
    //   37: invokevirtual 52	ex:put	(Ljava/lang/Object;Ljava/lang/Object;)Ljava/lang/Object;
    //   40: ldc 1
    //   42: invokevirtual 54	java/lang/String:length	()I
    //   45: pop2
    //   46: aload_1
    //   47: arraylength
    //   48: invokestatic 43	dd:c	(I)Z
    //   51: ifeq +17 -> 68
    //   54: aload_2
    //   55: invokestatic 60	java/lang/System:currentTimeMillis	()J
    //   58: ldc2_w 24
    //   61: ldiv
    //   62: l2i
    //   63: i2l
    //   64: putfield 30	p:a	J
    //   67: return
    //   68: aload_2
    //   69: aload_1
    //   70: getstatic 29	dd:c	[I
    //   73: iconst_0
    //   74: iaload
    //   75: aload_1
    //   76: arraylength
    //   77: invokestatic 61	javax/microedition/lcdui/Image:createImage	([BII)Ljavax/microedition/lcdui/Image;
    //   80: putfield 31	p:b	Ljavax/microedition/lcdui/Image;
    //   83: return
    //   84: ldc 1
    //   86: invokevirtual 54	java/lang/String:length	()I
    //   89: pop2
    //   90: return
    // Local variable table:
    //   start	length	slot	name	signature
    //   0	91	0	paramShort	short
    //   0	91	1	paramArrayOfByte	byte[]
    //   14	55	2	localp	p
    //   84	1	3	localException	Exception
    // Exception table:
    //   from	to	target	type
    //   0	67	84	java/lang/Exception
    //   68	83	84	java/lang/Exception
  }
  
  private static void c()
  {
    c = new int[1];
    c[0] = ((0x8 ^ 0x30 ^ 0xD7 ^ 0xC5) & (99 + 79 - 43 + 45 ^ 0 + '' - 46 + 69 ^ -" ".length()));
  }
  
  private static boolean b(int paramInt)
  {
    return paramInt >= 0;
  }
  
  private static boolean c(int paramInt)
  {
    return paramInt <= 0;
  }
  
  /* Error */
  public static p a(short paramShort)
  {
    // Byte code:
    //   0: getstatic 28	dd:b	Lex;
    //   3: iload_0
    //   4: invokestatic 55	java/lang/String:valueOf	(I)Ljava/lang/String;
    //   7: invokevirtual 51	ex:get	(Ljava/lang/Object;)Ljava/lang/Object;
    //   10: checkcast 21	p
    //   13: dup
    //   14: astore_1
    //   15: invokestatic 41	dd:b	(Ljava/lang/Object;)Z
    //   18: ifeq +20 -> 38
    //   21: aload_1
    //   22: invokestatic 41	dd:b	(Ljava/lang/Object;)Z
    //   25: ifeq +188 -> 213
    //   28: aload_1
    //   29: getfield 31	p:b	Ljavax/microedition/lcdui/Image;
    //   32: invokestatic 39	dd:a	(Ljava/lang/Object;)Z
    //   35: ifeq +178 -> 213
    //   38: aload_1
    //   39: invokestatic 39	dd:a	(Ljava/lang/Object;)Z
    //   42: ifeq +28 -> 70
    //   45: new 21	p
    //   48: dup
    //   49: invokespecial 62	p:<init>	()V
    //   52: astore_1
    //   53: getstatic 28	dd:b	Lex;
    //   56: iload_0
    //   57: invokestatic 55	java/lang/String:valueOf	(I)Ljava/lang/String;
    //   60: aload_1
    //   61: invokevirtual 52	ex:put	(Ljava/lang/Object;Ljava/lang/Object;)Ljava/lang/Object;
    //   64: ldc 1
    //   66: invokevirtual 54	java/lang/String:length	()I
    //   69: pop2
    //   70: aload_1
    //   71: ldc 5
    //   73: iload_0
    //   74: invokestatic 55	java/lang/String:valueOf	(I)Ljava/lang/String;
    //   77: invokevirtual 53	java/lang/String:concat	(Ljava/lang/String;)Ljava/lang/String;
    //   80: invokestatic 45	df:b	(Ljava/lang/String;)[B
    //   83: invokestatic 35	cu:a	([B)Ljavax/microedition/lcdui/Image;
    //   86: putfield 31	p:b	Ljavax/microedition/lcdui/Image;
    //   89: aload_1
    //   90: getfield 31	p:b	Ljavax/microedition/lcdui/Image;
    //   93: invokestatic 39	dd:a	(Ljava/lang/Object;)Z
    //   96: ifeq +117 -> 213
    //   99: invokestatic 60	java/lang/System:currentTimeMillis	()J
    //   102: ldc2_w 24
    //   105: ldiv
    //   106: aload_1
    //   107: getfield 30	p:a	J
    //   110: lsub
    //   111: ldc2_w 22
    //   114: invokestatic 38	dd:a	(JJ)I
    //   117: invokestatic 44	dd:d	(I)Z
    //   120: ifeq +93 -> 213
    //   123: aload_1
    //   124: invokestatic 60	java/lang/System:currentTimeMillis	()J
    //   127: ldc2_w 24
    //   130: ldiv
    //   131: l2i
    //   132: i2l
    //   133: putfield 30	p:a	J
    //   136: iload_0
    //   137: invokestatic 40	dd:b	(I)Z
    //   140: ifeq +31 -> 171
    //   143: aload_1
    //   144: new 18	java/lang/StringBuffer
    //   147: dup
    //   148: ldc 4
    //   150: invokespecial 56	java/lang/StringBuffer:<init>	(Ljava/lang/String;)V
    //   153: iload_0
    //   154: invokevirtual 57	java/lang/StringBuffer:append	(I)Ljava/lang/StringBuffer;
    //   157: ldc 3
    //   159: invokevirtual 58	java/lang/StringBuffer:append	(Ljava/lang/String;)Ljava/lang/StringBuffer;
    //   162: invokevirtual 59	java/lang/StringBuffer:toString	()Ljava/lang/String;
    //   165: invokestatic 33	aw:c	(Ljava/lang/String;)Ljavax/microedition/lcdui/Image;
    //   168: putfield 31	p:b	Ljavax/microedition/lcdui/Image;
    //   171: aload_1
    //   172: getfield 31	p:b	Ljavax/microedition/lcdui/Image;
    //   175: invokestatic 39	dd:a	(Ljava/lang/Object;)Z
    //   178: ifeq +35 -> 213
    //   181: invokestatic 32	au:a	()Lau;
    //   184: getfield 26	au:d	Z
    //   187: invokestatic 37	dd:a	(I)Z
    //   190: ifeq +23 -> 213
    //   193: invokestatic 46	dl:ae	()Ldl;
    //   196: iload_0
    //   197: invokevirtual 48	dl:b	(S)V
    //   200: aload_1
    //   201: invokestatic 60	java/lang/System:currentTimeMillis	()J
    //   204: ldc2_w 24
    //   207: ldiv
    //   208: l2i
    //   209: i2l
    //   210: putfield 30	p:a	J
    //   213: aload_1
    //   214: areturn
    //   215: ldc 1
    //   217: invokevirtual 54	java/lang/String:length	()I
    //   220: pop2
    //   221: aconst_null
    //   222: areturn
    // Local variable table:
    //   start	length	slot	name	signature
    //   0	223	0	paramShort	short
    //   14	200	1	localp	p
    //   215	1	2	localException	Exception
    // Exception table:
    //   from	to	target	type
    //   0	214	215	java/lang/Exception
  }
  
  private static int a(long paramLong1, long paramLong2)
  {
    return paramLong1 < paramLong2;
  }
  
  private static boolean d(int paramInt)
  {
    return paramInt > 0;
  }
  
  public static void a()
  {
    c();
    b = new ex();
    a = new ex();
  }
  
  static
  {
    cs.a(147);
    a();
  }
  
  private static boolean a(Object paramObject)
  {
    return paramObject == null;
  }
  
  private static boolean b(Object paramObject)
  {
    return paramObject != null;
  }
  
  public static eg b(short paramShort)
  {
    eg localeg;
    if (a(localeg = (eg)a.get(String.valueOf(paramShort))))
    {
      localeg = new eg();
      "".length();
      dl.ae().ak(paramShort);
    }
    return localeg;
  }
  
  public static void b() {}
}


/* Location:              C:\Users\Admin\OneDrive\Documents\NSOv2_test.jar!\dd.class
 * Java compiler version: 1 (45.3)
 * JD-Core Version:       0.7.1
 */