import java.io.DataOutputStream;
import java.io.IOException;
import java.io.OutputStream;
import java.io.PrintStream;
import java.util.Vector;

public final class dl
{
  private static dl a;
  private int b;
  private c c = au.a();
  private int d;
  private static int[] e;
  
  public final void a(int paramInt)
  {
    bj localbj1 = null;
    try
    {
      bj localbj2;
      (localbj2 = localbj1 = new bj(e[17])).c.writeByte(paramInt);
      this.c.a(localbj1);
      return;
    }
    catch (Exception localException) {}finally
    {
      localbj1.c();
    }
  }
  
  public final void a(ao paramao, int paramInt)
  {
    bj localbj1 = null;
    try
    {
      bj localbj2;
      (localbj2 = localbj1 = new bj(e[116])).c.writeByte(paramao.n);
      (localbj2 = localbj1).c.writeInt(paramInt);
      this.c.a(localbj1);
      return;
    }
    catch (Exception localException) {}finally
    {
      localbj1.c();
    }
  }
  
  public final void b(int paramInt)
  {
    bj localbj1 = null;
    try
    {
      bj localbj2;
      (localbj2 = localbj1 = d(e[96])).c.writeInt(paramInt);
      this.c.a(localbj1);
      return;
    }
    catch (Exception localException) {}finally
    {
      localbj1.c();
    }
  }
  
  public final void a(int paramInt1, int paramInt2, int paramInt3)
  {
    bj localbj1 = null;
    try
    {
      bj localbj2;
      (localbj2 = localbj1 = d(e[78])).c.writeByte(paramInt1);
      (localbj2 = localbj1).c.writeByte(paramInt2);
      (localbj2 = localbj1).c.writeByte(paramInt3);
      this.c.a(localbj1);
      return;
    }
    catch (Exception localException) {}finally
    {
      localbj1.c();
    }
  }
  
  public final void a(byte paramByte)
  {
    bj localbj1 = null;
    try
    {
      bj localbj2;
      (localbj2 = localbj1 = d(e[''])).c.writeByte(e[50]);
      (localbj2 = localbj1).c.writeByte(paramByte);
      this.c.a(localbj1);
      return;
    }
    catch (Exception localException) {}finally
    {
      localbj1.c();
    }
  }
  
  public final void a(String paramString)
  {
    bj localbj1 = null;
    try
    {
      bj localbj2;
      (localbj2 = localbj1 = new bj(e[89])).c.writeUTF(paramString);
      this.c.a(localbj1);
      return;
    }
    catch (Exception localException) {}finally
    {
      localbj1.c();
    }
  }
  
  public final void a()
  {
    bj localbj = null;
    try
    {
      localbj = new bj(e[26]);
      this.c.a(localbj);
      return;
    }
    catch (Exception localException2)
    {
      Exception localException1;
      return;
    }
    finally
    {
      localbj.c();
    }
  }
  
  public final void a(short paramShort, String paramString)
  {
    bj localbj1 = null;
    try
    {
      bj localbj2;
      (localbj2 = localbj1 = new bj(e[31])).c.writeShort(paramShort);
      (localbj2 = localbj1).c.writeUTF(paramString);
      this.c.a(localbj1);
      return;
    }
    catch (Exception localException) {}finally
    {
      localbj1.c();
    }
  }
  
  public static void b() {}
  
  static
  {
    cs.a(115);
    b();
  }
  
  public final void c(int paramInt)
  {
    bj localbj1 = null;
    try
    {
      bj localbj2;
      (localbj2 = localbj1 = c(e[102])).c.writeInt(paramInt);
      this.c.a(localbj1);
      return;
    }
    catch (Exception localException) {}finally
    {
      localbj1.c();
    }
  }
  
  public final void a(int paramInt1, int paramInt2)
  {
    bj localbj1 = null;
    try
    {
      bj localbj2;
      (localbj2 = localbj1 = new bj(e[14])).c.writeInt(paramInt1);
      (localbj2 = localbj1).c.writeByte(paramInt2);
      this.c.a(localbj1);
      return;
    }
    catch (Exception localException) {}finally
    {
      localbj1.c();
    }
  }
  
  public final void d(int paramInt)
  {
    bj localbj1 = null;
    try
    {
      bj localbj2;
      (localbj2 = localbj1 = c(e[75])).c.writeByte(paramInt);
      this.c.a(localbj1);
      return;
    }
    catch (Exception localException) {}finally
    {
      localbj1.c();
    }
  }
  
  private static boolean ar(int paramInt)
  {
    return paramInt == 0;
  }
  
  public final void a(String paramString1, String paramString2, String paramString3)
  {
    try
    {
      Object localObject2;
      (localObject2 = localObject1 = b(e[''])).c.writeUTF(paramString1);
      (localObject2 = localObject1).c.writeUTF(paramString2);
      (localObject2 = localObject1).c.writeUTF(paramString3);
      this.c.a((bj)localObject1);
      ((bj)localObject1).c();
      return;
    }
    catch (IOException localIOException)
    {
      Object localObject1;
      (localObject1 = localIOException).printStackTrace();
    }
  }
  
  public final void e(int paramInt)
  {
    bj localbj1 = null;
    try
    {
      bj localbj2;
      (localbj2 = localbj1 = c(e[36])).c.writeInt(paramInt);
      this.c.a(localbj1);
      return;
    }
    catch (Exception localException) {}finally
    {
      localbj1.c();
    }
  }
  
  public final void b(String paramString)
  {
    bj localbj1 = null;
    try
    {
      bj localbj2;
      (localbj2 = localbj1 = d(e[105])).c.writeUTF(paramString);
      this.c.a(localbj1);
      return;
    }
    catch (Exception localException) {}finally
    {
      localbj1.c();
    }
  }
  
  public final void c(String paramString)
  {
    bj localbj1 = null;
    try
    {
      bj localbj2;
      (localbj2 = localbj1 = d(e[61])).c.writeUTF(paramString);
      this.c.a(localbj1);
      return;
    }
    catch (Exception localException) {}finally
    {
      localbj1.c();
    }
  }
  
  public final void c()
  {
    bj localbj = null;
    try
    {
      localbj = d(e[103]);
      this.c.a(localbj);
      return;
    }
    catch (Exception localException2)
    {
      Exception localException1;
      return;
    }
    finally
    {
      localbj.c();
    }
  }
  
  public final void d(String paramString)
  {
    bj localbj1 = new bj(e[1]);
    try
    {
      bj localbj2;
      (localbj2 = localbj1).c.writeByte(e[11]);
      (localbj2 = localbj1).c.writeUTF(paramString);
      "".length();
      if (" ".length() >= "   ".length()) {
        return;
      }
    }
    catch (Exception localException)
    {
      (paramString = localException).printStackTrace();
      this.c.a(localbj1);
    }
  }
  
  public final void f(int paramInt)
  {
    bj localbj1 = null;
    try
    {
      bj localbj2;
      (localbj2 = localbj1 = new bj(e[45])).c.writeInt(paramInt);
      this.c.a(localbj1);
      return;
    }
    catch (Exception localException) {}finally
    {
      localbj1.c();
    }
  }
  
  public final void g(int paramInt)
  {
    bj localbj1 = null;
    try
    {
      bj localbj2;
      (localbj2 = localbj1 = new bj(e[55])).c.writeShort(paramInt);
      this.c.a(localbj1);
      return;
    }
    catch (Exception localException) {}finally
    {
      localbj1.c();
    }
  }
  
  public final void h(int paramInt)
  {
    bj localbj1 = null;
    try
    {
      bj localbj2;
      (localbj2 = localbj1 = c(e[101])).c.writeInt(paramInt);
      this.c.a(localbj1);
      return;
    }
    catch (Exception localException) {}finally
    {
      localbj1.c();
    }
  }
  
  public final void a(ao paramao)
  {
    aw.h.a();
    bj localbj1 = null;
    try
    {
      bj localbj2;
      (localbj2 = localbj1 = new bj(e[40])).c.writeByte(paramao.n);
      this.c.a(localbj1);
      return;
    }
    catch (Exception localException) {}finally
    {
      localbj1.c();
    }
  }
  
  public final void d()
  {
    bj localbj = null;
    try
    {
      localbj = d(e[99]);
      this.c.a(localbj);
      return;
    }
    catch (Exception localException2)
    {
      Exception localException1;
      return;
    }
    finally
    {
      localbj.c();
    }
  }
  
  public final void e(String paramString)
  {
    bj localbj1 = null;
    try
    {
      bj localbj2;
      (localbj2 = localbj1 = new bj(e[21])).c.writeUTF(paramString);
      this.c.a(localbj1);
      return;
    }
    catch (Exception localException) {}finally
    {
      localbj1.c();
    }
  }
  
  public final void b(int paramInt1, int paramInt2, int paramInt3)
  {
    bj localbj1 = null;
    try
    {
      bj localbj2;
      (localbj2 = localbj1 = new bj(e[23])).c.writeByte(paramInt1);
      (localbj2 = localbj1).c.writeByte(paramInt2);
      if (m(paramInt3, e[10])) {
        (localbj2 = localbj1).c.writeShort(paramInt3);
      }
      this.c.a(localbj1);
      return;
    }
    catch (Exception localException) {}finally
    {
      localbj1.c();
    }
  }
  
  public final void a(byte paramByte, ao paramao1, ao paramao2, ao[] paramArrayOfao)
  {
    aw.h.a();
    bj localbj1 = null;
    try
    {
      bj localbj2;
      (localbj2 = localbj1 = new bj(e[''])).c.writeByte(paramByte);
      if (ar(paramByte))
      {
        (localbj2 = localbj1).c.writeByte(paramao1.n);
        (localbj2 = localbj1).c.writeByte(paramao2.n);
        paramByte = e[4];
        do
        {
          if (!p(paramByte, paramArrayOfao.length)) {
            break;
          }
          if (a(paramArrayOfao[paramByte])) {
            (localbj2 = localbj1).c.writeByte(paramArrayOfao[paramByte].n);
          }
          paramByte++;
          "".length();
        } while (null == null);
        return;
      }
      if (n(paramByte, e[10]))
      {
        (localbj2 = localbj1).c.writeByte(paramao2.n);
        paramByte = e[4];
        do
        {
          if (!p(paramByte, paramArrayOfao.length)) {
            break;
          }
          if (a(paramArrayOfao[paramByte])) {
            (localbj2 = localbj1).c.writeByte(paramArrayOfao[paramByte].n);
          }
          paramByte++;
          "".length();
        } while (-"   ".length() < 0);
        return;
      }
      if ((!o(paramByte, e[''])) || (n(paramByte, e['']))) {
        (localbj2 = localbj1).c.writeByte(paramao2.n);
      }
      this.c.a(localbj1);
      return;
    }
    catch (Exception localException) {}finally
    {
      localbj1.c();
    }
  }
  
  public final void a(String paramString, int paramInt)
  {
    bj localbj1 = null;
    try
    {
      bj localbj2;
      (localbj2 = localbj1 = d(e[106])).c.writeUTF(paramString);
      (localbj2 = localbj1).c.writeByte(paramInt);
      this.c.a(localbj1);
      return;
    }
    catch (Exception localException) {}finally
    {
      localbj1.c();
    }
  }
  
  public final void e()
  {
    bj localbj = null;
    try
    {
      localbj = d(e[113]);
      this.c.a(localbj);
      return;
    }
    catch (Exception localException2)
    {
      Exception localException1;
      return;
    }
    finally
    {
      localbj.c();
    }
  }
  
  public final void a(ao[] paramArrayOfao)
  {
    aw.h.a();
    bj localbj1 = null;
    try
    {
      localbj1 = new bj(e[37]);
      int i = e[4];
      while (p(i, paramArrayOfao.length))
      {
        if (a(paramArrayOfao[i]))
        {
          bj localbj2;
          (localbj2 = localbj1).c.writeByte(paramArrayOfao[i].n);
        }
        i++;
        "".length();
        if (-(120 + 55 - 108 + 69 ^ 22 + 69 - 49 + 98) >= 0) {
          return;
        }
      }
      this.c.a(localbj1);
      return;
    }
    catch (Exception localException2)
    {
      Exception localException1;
      return;
    }
    finally
    {
      localbj1.c();
    }
  }
  
  public final void b(ao[] paramArrayOfao)
  {
    aw.h.a();
    bj localbj1 = null;
    try
    {
      localbj1 = new bj(e[39]);
      int i = e[4];
      while (p(i, paramArrayOfao.length))
      {
        if (a(paramArrayOfao[i]))
        {
          bj localbj2;
          (localbj2 = localbj1).c.writeByte(paramArrayOfao[i].n);
        }
        i++;
        "".length();
        if ((44 + 69 - 42 + 116 ^ 119 + 11 - 54 + 115) <= 0) {
          return;
        }
      }
      this.c.a(localbj1);
      return;
    }
    catch (Exception localException2)
    {
      Exception localException1;
      return;
    }
    finally
    {
      localbj1.c();
    }
  }
  
  public final void f()
  {
    bj localbj = null;
    try
    {
      localbj = new bj(e[57]);
      this.c.a(localbj);
      return;
    }
    catch (Exception localException2)
    {
      Exception localException1;
      return;
    }
    finally
    {
      localbj.c();
    }
  }
  
  public final void g()
  {
    bj localbj = null;
    try
    {
      localbj = d(e[97]);
      this.c.a(localbj);
      return;
    }
    catch (Exception localException2)
    {
      Exception localException1;
      return;
    }
    finally
    {
      localbj.c();
    }
  }
  
  public final void h()
  {
    bj localbj = null;
    try
    {
      localbj = d(e[62]);
      this.c.a(localbj);
      return;
    }
    catch (Exception localException2)
    {
      Exception localException1;
      return;
    }
    finally
    {
      localbj.c();
    }
  }
  
  public final void f(String paramString)
  {
    bj localbj1 = null;
    try
    {
      bj localbj2;
      (localbj2 = localbj1 = d(e[102])).c.writeByte(fn.du);
      (localbj2 = localbj1).c.writeUTF(paramString);
      this.c.a(localbj1);
      return;
    }
    catch (Exception localException) {}finally
    {
      localbj1.c();
    }
  }
  
  public final void g(String paramString)
  {
    bj localbj1 = null;
    try
    {
      bj localbj2;
      (localbj2 = localbj1 = d(e[74])).c.writeUTF(paramString);
      this.c.a(localbj1);
      return;
    }
    catch (Exception localException) {}finally
    {
      localbj1.c();
    }
  }
  
  public final void i(int paramInt)
  {
    bj localbj1 = null;
    try
    {
      bj localbj2;
      (localbj2 = localbj1 = new bj(e[56])).c.writeByte(paramInt);
      this.c.a(localbj1);
      return;
    }
    catch (Exception localException) {}finally
    {
      localbj1.c();
    }
  }
  
  public final void a(ci paramci)
  {
    bj localbj1 = null;
    try
    {
      bj localbj2;
      (localbj2 = localbj1 = new bj(e[83])).c.writeByte(paramci.size());
      int i = e[4];
      while (p(i, paramci.size()))
      {
        dt localdt = (dt)paramci.elementAt(i);
        (localbj2 = localbj1).c.writeInt(localdt.fy);
        i++;
        "".length();
        if ((" ".length() & (" ".length() ^ 0xFFFFFFFF)) != 0) {
          return;
        }
      }
      this.c.a(localbj1);
      return;
    }
    catch (Exception localException2)
    {
      Exception localException1;
      return;
    }
    finally
    {
      localbj1.c();
    }
  }
  
  private static boolean m(int paramInt1, int paramInt2)
  {
    return paramInt1 > paramInt2;
  }
  
  public final void a(String paramString1, String paramString2)
  {
    bj localbj1 = null;
    try
    {
      bj localbj2;
      (localbj2 = localbj1 = d(e[92])).c.writeUTF(paramString1);
      (localbj2 = localbj1).c.writeUTF(paramString2);
      this.c.a(localbj1);
      return;
    }
    catch (Exception localException) {}finally
    {
      localbj1.c();
    }
  }
  
  public final void i()
  {
    bj localbj = null;
    try
    {
      localbj = new bj(e[80]);
      this.c.a(localbj);
      return;
    }
    catch (Exception localException2)
    {
      Exception localException1;
      return;
    }
    finally
    {
      localbj.c();
    }
  }
  
  public final void h(String paramString)
  {
    bj localbj1 = null;
    try
    {
      bj localbj2;
      (localbj2 = localbj1 = new bj(e[91])).c.writeUTF(paramString);
      this.c.a(localbj1);
      return;
    }
    catch (Exception localException) {}finally
    {
      localbj1.c();
    }
  }
  
  private static bj b(byte paramByte)
  {
    try
    {
      bj localbj;
      (localbj = localObject = new bj(e[0])).c.writeByte(paramByte);
      return (bj)localObject;
    }
    catch (IOException localIOException)
    {
      Object localObject;
      (localObject = localIOException).printStackTrace();
    }
    return null;
  }
  
  public final void j(int paramInt)
  {
    bj localbj1 = null;
    try
    {
      bj localbj2;
      (localbj2 = localbj1 = new bj(e[43])).c.writeInt(paramInt);
      this.c.a(localbj1);
      return;
    }
    catch (Exception localException) {}finally
    {
      localbj1.c();
    }
  }
  
  public final void a(byte paramByte, short paramShort)
  {
    bj localbj1 = null;
    try
    {
      bj localbj2;
      (localbj2 = localbj1 = d(e[''])).c.writeByte(paramByte);
      (localbj2 = localbj1).c.writeByte(paramShort);
      this.c.a(localbj1);
      return;
    }
    catch (Exception localException) {}finally
    {
      localbj1.c();
    }
  }
  
  public final void c(ao[] paramArrayOfao)
  {
    aw.h.a();
    bj localbj1 = null;
    try
    {
      localbj1 = new bj(e[120]);
      int i = e[4];
      bj localbj2;
      while (p(i, paramArrayOfao.length)) {
        if ((a(paramArrayOfao[i])) && ((!o(paramArrayOfao[i].j.f, e[121])) || (n(paramArrayOfao[i].j.f, e[20]))))
        {
          (localbj2 = localbj1).c.writeByte(paramArrayOfao[i].n);
          "".length();
          if ((0x8 ^ 0xC) >= "  ".length()) {
            break;
          }
        }
        else
        {
          i++;
          "".length();
          if (null != null) {
            return;
          }
        }
      }
      i = e[4];
      while (p(i, paramArrayOfao.length))
      {
        if ((a(paramArrayOfao[i])) && ((!o(paramArrayOfao[i].j.f, e[122])) || (n(paramArrayOfao[i].j.f, e[123])))) {
          (localbj2 = localbj1).c.writeByte(paramArrayOfao[i].n);
        }
        i++;
        "".length();
        if (" ".length() < -" ".length()) {
          return;
        }
      }
      this.c.a(localbj1);
      return;
    }
    catch (Exception localException2)
    {
      Exception localException1;
      return;
    }
    finally
    {
      localbj1.c();
    }
  }
  
  public final void k(int paramInt)
  {
    bj localbj1 = null;
    try
    {
      bj localbj2;
      (localbj2 = localbj1 = new bj(e[118])).c.writeInt(paramInt);
      this.c.a(localbj1);
      return;
    }
    catch (Exception localException) {}finally
    {
      localbj1.c();
    }
  }
  
  /* Error */
  public final void a(String paramString1, String paramString2, byte paramByte)
  {
    // Byte code:
    //   0: aconst_null
    //   1: astore 4
    //   3: new 34	java/lang/StringBuffer
    //   6: dup
    //   7: invokespecial 105	java/lang/StringBuffer:<init>	()V
    //   10: aload_1
    //   11: invokevirtual 107	java/lang/StringBuffer:append	(Ljava/lang/String;)Ljava/lang/StringBuffer;
    //   14: ldc 2
    //   16: invokevirtual 107	java/lang/StringBuffer:append	(Ljava/lang/String;)Ljava/lang/StringBuffer;
    //   19: aload_2
    //   20: invokevirtual 107	java/lang/StringBuffer:append	(Ljava/lang/String;)Ljava/lang/StringBuffer;
    //   23: invokevirtual 108	java/lang/StringBuffer:toString	()Ljava/lang/String;
    //   26: astore_1
    //   27: new 13	bj
    //   30: dup
    //   31: getstatic 59	dl:e	[I
    //   34: bipush 89
    //   36: iaload
    //   37: invokespecial 69	bj:<init>	(B)V
    //   40: dup
    //   41: astore 4
    //   43: dup
    //   44: astore_2
    //   45: getfield 49	bj:c	Ljava/io/DataOutputStream;
    //   48: aload_1
    //   49: invokevirtual 100	java/io/DataOutputStream:writeUTF	(Ljava/lang/String;)V
    //   52: aload 4
    //   54: dup
    //   55: astore_2
    //   56: getfield 49	bj:c	Ljava/io/DataOutputStream;
    //   59: iload_3
    //   60: invokevirtual 97	java/io/DataOutputStream:writeByte	(I)V
    //   63: aload_0
    //   64: getfield 57	dl:c	Lc;
    //   67: aload 4
    //   69: invokeinterface 113 2 0
    //   74: aload 4
    //   76: invokevirtual 70	bj:c	()V
    //   79: return
    //   80: ldc 1
    //   82: invokevirtual 104	java/lang/String:length	()I
    //   85: pop2
    //   86: aload 4
    //   88: invokevirtual 70	bj:c	()V
    //   91: return
    //   92: astore_1
    //   93: aload 4
    //   95: invokevirtual 70	bj:c	()V
    //   98: aload_1
    //   99: athrow
    // Local variable table:
    //   start	length	slot	name	signature
    //   0	100	0	this	dl
    //   0	100	1	paramString1	String
    //   0	100	2	paramString2	String
    //   0	100	3	paramByte	byte
    //   1	93	4	localbj	bj
    //   80	1	5	localException	Exception
    // Exception table:
    //   from	to	target	type
    //   27	74	80	java/lang/Exception
    //   27	74	92	finally
  }
  
  public final void a(int paramInt, ao[] paramArrayOfao)
  {
    bj localbj1 = null;
    try
    {
      bj localbj2;
      (localbj2 = localbj1 = new bj(e[49])).c.writeInt(paramInt);
      paramInt = e[4];
      int i = e[4];
      while (p(i, paramArrayOfao.length))
      {
        if (a(paramArrayOfao[i])) {
          paramInt++;
        }
        i++;
        "".length();
        if ("   ".length() > "   ".length()) {
          return;
        }
      }
      (localbj2 = localbj1).c.writeByte(paramInt);
      i = e[4];
      while (p(i, paramArrayOfao.length))
      {
        if (a(paramArrayOfao[i])) {
          (localbj2 = localbj1).c.writeByte(paramArrayOfao[i].n);
        }
        i++;
        "".length();
        if ((0xC1 ^ 0xC4) <= 0) {
          return;
        }
      }
      this.c.a(localbj1);
      return;
    }
    catch (Exception localException2)
    {
      Exception localException1;
      return;
    }
    finally
    {
      localbj1.c();
    }
  }
  
  public final void l(int paramInt)
  {
    bj localbj1 = null;
    try
    {
      bj localbj2;
      (localbj2 = localbj1 = new bj(e[24])).c.writeShort(paramInt);
      this.c.a(localbj1);
      return;
    }
    catch (Exception localException) {}finally
    {
      localbj1.c();
    }
  }
  
  private static void al()
  {
    e = new int[''];
    e[0] = (-(0x57 ^ 0x11 ^ 0x22 ^ 0x79));
    e[1] = (-(0xDF ^ 0x93 ^ 0xC7 ^ 0x97));
    e[2] = (-(0xA9 ^ 0x84 ^ 0x94 ^ 0xA7));
    e[3] = (-(0x44 ^ 0x39));
    e[4] = ((0xF0 ^ 0x93) & (0x6F ^ 0xC ^ 0xFFFFFFFF));
    e[5] = (-((0x5D ^ 0x66) + (0x65 ^ 0x35) - (0x4D ^ 0x6A) + (0x7E ^ 0x65)));
    e[6] = (0xB5 ^ 0xC3);
    e[7] = (-('¡' + 'Û' - 266 + 110 ^ 38 + '' - 30 + 1));
    e[8] = (-(0x8F ^ 0x9E));
    e[9] = (44 + 72 - -38 + 19 ^ 88 + 79 - 21 + 31);
    e[10] = " ".length();
    e[11] = (-(0xC7 ^ 0x97 ^ 0x57 ^ 0x79));
    e[12] = (-(0xCB ^ 0xA7));
    e[13] = (0xAC ^ 0x86);
    e[14] = (93 + 64 - 45 + 135 ^ 75 + 42 - 77 + 129);
    e[15] = (-(0x45 ^ 0x28));
    e[16] = (0xC ^ 0x3);
    e[17] = (0x8B ^ 0x87 ^ 0x18 ^ 0x78);
    e[18] = (0x1E ^ 0xE);
    e[19] = (0x72 ^ 0x63);
    e[20] = (54 + '' - 155 + 166 ^ 40 + '' - 16 + 12);
    e[21] = (0x66 ^ 0x75 ^ 0x95 ^ 0x9E);
    e[22] = (0x2 ^ 0x5D ^ 0x65 ^ 0x34);
    e[23] = (0x55 ^ 0x19 ^ 0x50 ^ 0x11);
    e[24] = (0x1F ^ 0x27 ^ 0x72 ^ 0x63);
    e[25] = (-(0x4C ^ 0x6 ^ 0x9D ^ 0x9A));
    e[26] = (0xB3 ^ 0x97);
    e[27] = (0x5D ^ 0x9 ^ 0x1A ^ 0x42);
    e[28] = (0x50 ^ 0x2B ^ 0x37 ^ 0x64);
    e[29] = (0xA0 ^ 0xBD);
    e[30] = ('Ä' + 21 - 117 + 125 ^ '¶' + '' - 139 + 11);
    e[31] = (0x96 ^ 0xB0 ^ 0x42 ^ 0x38);
    e[32] = (-(0x9C ^ 0xAE ^ 0x74 ^ 0x21));
    e[33] = (-(0x68 ^ 0x27 ^ 0xAE ^ 0x8A));
    e[34] = (-(0x7D ^ 0x17));
    e[35] = (-(0x38 ^ 0x51));
    e[36] = (-(0x16 ^ 0x7E));
    e[37] = (0x79 ^ 0x6A);
    e[38] = (0x70 ^ 0x14 ^ 0x4B ^ 0x3A);
    e[39] = (122 + 19 - 51 + 43 ^ 116 + 36 - 138 + 131);
    e[40] = (34 + 39 - -47 + 8 ^ 77 + 83 - 44 + 34);
    e[41] = (0xED ^ 0xC1);
    e[42] = (0xC7 ^ 0xA4);
    e[43] = (0x72 ^ 0x1B ^ "   ".length());
    e[44] = (0x22 ^ 0x49);
    e[45] = (0x4D ^ 0xF);
    e[46] = (122 + 117 - 167 + 92 ^ 67 + 11 - 77 + 155);
    e[47] = (20 + 93 - 1 + 40 ^ 2 + '' - 37 + 63);
    e[48] = (18 + 123 - 82 + 132 ^ 60 + 45 - 5 + 45);
    e[49] = (0x71 ^ 0x5C);
    e[50] = (0x25 ^ 0x3E ^ 0x1C ^ 0x3);
    e[51] = (0x61 ^ 0xF ^ 0x2A ^ 0xD);
    e[52] = (-" ".length());
    e[53] = (0x4D ^ 0x71);
    e[54] = ("   ".length() ^ 0x34 ^ 0xA);
    e[55] = (-(0xCF ^ 0xA7 ^ 0x19 ^ 0x7F));
    e[56] = (-(0x7C ^ 0x70));
    e[57] = (-(0x10 ^ 0x66 ^ 90 + 76 - 97 + 58));
    e[58] = (-(0x42 ^ 0x5B ^ 0x8E ^ 0x9D));
    e[59] = (2 + 21 - 11 + 157 ^ 71 + 18 - 8 + 53);
    e[60] = (-(57 + 15 - -29 + 53 ^ 45 + 71 - 52 + 77));
    e[61] = (-(0x6A ^ 0x24));
    e[62] = (-(0xB8 ^ 0xC1));
    e[63] = (-(0xA2 ^ 0x97 ^ 0xF0 ^ 0xBD));
    e[64] = (-(0x1F ^ 0x68));
    e[65] = (-('Ö' + '' - 257 + 144 ^ 120 + 7 - 0 + 12));
    e[66] = (0x90 ^ 0xBB);
    e[67] = (0xFF ^ 0xC4);
    e[68] = (0xDC ^ 0x8C);
    e[69] = (0x14 ^ 0x45);
    e[70] = (0x36 ^ 0x60 ^ 0x83 ^ 0x94);
    e[71] = (0x3B ^ 0x7F);
    e[72] = (-(0x88 ^ 0xC7));
    e[73] = (0x9A ^ 0x95 ^ 0x7C ^ 0x3C);
    e[74] = (-(0xC5 ^ 0x98));
    e[75] = (-(114 + 'ã' - 210 + 101 ^ '' + 71 - 132 + 107));
    e[76] = (-(0x3C ^ 0xD ^ 0x9 ^ 0x6E));
    e[77] = (0x21 ^ 0x6B);
    e[78] = (-(0xF9 ^ 0x90 ^ 0xB1 ^ 0x80));
    e[79] = (-(0x5B ^ 0x17));
    e[80] = (0x21 ^ 0x72);
    e[81] = (-(22 + 34 - 65372 + 3 ^ '' + 84 - 114 + 34));
    e[82] = (0x74 ^ 0x10);
    e[83] = (0x9D ^ 0x84);
    e[84] = (-(121 + 'Ó' - 247 + 152 ^ 118 + 55 - 77 + 89));
    e[85] = (-(0x48 ^ 0x1B));
    e[86] = (0x9A ^ 0x8D);
    e[87] = (0x16 ^ 0x4B);
    e[88] = (-(0x69 ^ 0x7D));
    e[89] = (-(0x5A ^ 0x4F));
    e[90] = (-('' + 3 - 63 + 94 ^ 29 + 17 - -114 + 0));
    e[91] = (-(0x1C ^ 0x4B ^ 0x1C ^ 0x58));
    e[92] = (-(0xB6 ^ 0xC0 ^ 0xD ^ 0x18));
    e[93] = (-(0xF0 ^ 0xB3));
    e[94] = (-(0xB4 ^ 0xAB ^ 0x7E ^ 0x20));
    e[95] = (-(0x4F ^ 0x2E));
    e[96] = (-(0x3E ^ 0x4D));
    e[97] = (-(0x3C ^ 0x4D));
    e[98] = (-(0xCE ^ 0xBE));
    e[99] = (-(0x4D ^ 0x22));
    e[100] = (-(0xCB ^ 0xB9));
    e[101] = (-(0x5D ^ 0x2B ^ 0x38 ^ 0x71));
    e[102] = (-(0x3D ^ 0x75 ^ 0x26 ^ 0x53));
    e[103] = (-(0xFC ^ 0xC2));
    e[104] = (-(0x48 ^ 0x74));
    e[105] = (-(0x2D ^ 0x37 ^ 0x30 ^ 0x75));
    e[106] = (-(0x3 ^ 0x2C ^ 0x3B ^ 0x4A));
    e[107] = (-(0x21 ^ 0x34 ^ 0x4A ^ 0x3));
    e[108] = (-(126 + 14 - 105 + 160 ^ 105 + 4 - -30 + 14));
    e[109] = (-(0xD8 ^ 0xC0 ^ 0x36 ^ 0x77));
    e[110] = (-(0x19 ^ 0x5A ^ 0x38 ^ 0x20));
    e[111] = (-(0x5E ^ 0x19 ^ " ".length()));
    e[112] = (-(0xFC ^ 0xB8));
    e[113] = (-(0xE9 ^ 0xAC));
    e[114] = (-(58 + '»' - 167 + 168 ^ 33 + 90 - 7 + 28));
    e[115] = (-(0x1A ^ 0x48));
    e[116] = (0xCC ^ 0xAA);
    e[117] = (0xA8 ^ 0xBD ^ 0xE2 ^ 0x9F);
    e[118] = (0x2D ^ 0x1A ^ 0x9C ^ 0xC2);
    e[119] = (-(0xE2 ^ 0xAA));
    e[120] = (0xE0 ^ 0x8E);
    e[121] = (0x75 ^ 0x7F);
    e[122] = (-(0xDE6F & 0x7FB9) & 0xFFFFFFFF & 0x5FEF);
    e[123] = (-(0xDF3E & 0x64D5) & 0xD5FB & 0x6FDF);
    e[124] = (0x18 ^ 0x22 ^ 0x59 ^ 0xC);
    e[125] = (-(0xFD7F & 0x7297) & 0xF7FF & 0x79DF);
    e[126] = (115 + 'ò' - 289 + 186 ^ 125 + 5 - 84 + 96);
    e[127] = (0xE5F7 & 0x1BCE);
    e[''] = (0xB3 ^ 0xC2);
    e[''] = (0x27 ^ 0x50);
    e[''] = (-(105 + 59 - 59 + 94 ^ 20 + '·' - 170 + 155));
    e[''] = ('ì' + 'ñ' - 439 + 211 ^ 49 + 108 - 66 + 37);
    e[''] = (0x4F ^ 0x35);
    e[''] = (0x40 ^ 0x1D ^ 0x99 ^ 0xBF);
    e[''] = (0x30 ^ 0x4C);
    e[''] = "  ".length();
    e[''] = "   ".length();
    e[''] = (0xDD ^ 0xB4 ^ 0xAC ^ 0xBB);
    e[''] = (7 + 56 - -126 + 4 ^ 28 + 86 - 45 + 119);
  }
  
  public final void m(int paramInt)
  {
    bj localbj1 = null;
    try
    {
      bj localbj2;
      (localbj2 = localbj1 = d(e[114])).c.writeInt(paramInt);
      this.c.a(localbj1);
      return;
    }
    catch (Exception localException) {}finally
    {
      localbj1.c();
    }
  }
  
  public final void j()
  {
    bj localbj = null;
    try
    {
      localbj = c(e[81]);
      this.c.a(localbj);
      return;
    }
    catch (Exception localException2)
    {
      Exception localException1;
      return;
    }
    finally
    {
      localbj.c();
    }
  }
  
  private static bj c(byte paramByte)
  {
    try
    {
      bj localbj;
      (localbj = localObject = new bj(e[2])).c.writeByte(paramByte);
      return (bj)localObject;
    }
    catch (IOException localIOException)
    {
      Object localObject;
      (localObject = localIOException).printStackTrace();
    }
    return null;
  }
  
  public final void i(String paramString)
  {
    bj localbj1 = null;
    try
    {
      bj localbj2;
      (localbj2 = localbj1 = new bj(e[73])).c.writeUTF(paramString);
      this.c.a(localbj1);
      return;
    }
    catch (Exception localException) {}finally
    {
      localbj1.c();
    }
  }
  
  public final void n(int paramInt)
  {
    bj localbj1 = null;
    try
    {
      bj localbj2;
      (localbj2 = localbj1 = new bj(e[16])).c.writeByte(paramInt);
      this.c.a(localbj1);
      return;
    }
    catch (Exception localException) {}finally
    {
      localbj1.c();
    }
  }
  
  public final void o(int paramInt)
  {
    bj localbj1 = null;
    try
    {
      bj localbj2;
      (localbj2 = localbj1 = d(e[32])).c.writeInt(paramInt);
      this.c.a(localbj1);
      return;
    }
    catch (Exception localException) {}finally
    {
      localbj1.c();
    }
  }
  
  public final void p(int paramInt)
  {
    bj localbj1 = null;
    try
    {
      bj localbj2;
      (localbj2 = localbj1 = c(e[103])).c.writeInt(paramInt);
      this.c.a(localbj1);
      return;
    }
    catch (Exception localException) {}finally
    {
      localbj1.c();
    }
  }
  
  private static boolean a(Object paramObject)
  {
    return paramObject != null;
  }
  
  public final void k()
  {
    bj localbj = null;
    try
    {
      (localObject1 = localbj = d(e[104])).c.writeByte(fn.du);
      this.c.a(localbj);
      return;
    }
    catch (Exception localException)
    {
      Object localObject1;
      return;
    }
    finally
    {
      localbj.c();
    }
  }
  
  public final void l()
  {
    bj localbj = null;
    try
    {
      localbj = d(e[100]);
      this.c.a(localbj);
      return;
    }
    catch (Exception localException2)
    {
      Exception localException1;
      return;
    }
    finally
    {
      localbj.c();
    }
  }
  
  /* Error */
  public final void b(int paramInt1, int paramInt2)
  {
    // Byte code:
    //   0: new 13	bj
    //   3: dup
    //   4: getstatic 59	dl:e	[I
    //   7: bipush 9
    //   9: iaload
    //   10: invokespecial 69	bj:<init>	(B)V
    //   13: astore_3
    //   14: aload_3
    //   15: dup
    //   16: astore 4
    //   18: getfield 49	bj:c	Ljava/io/DataOutputStream;
    //   21: iload_1
    //   22: invokevirtual 97	java/io/DataOutputStream:writeByte	(I)V
    //   25: aload_3
    //   26: dup
    //   27: astore 4
    //   29: getfield 49	bj:c	Ljava/io/DataOutputStream;
    //   32: iload_2
    //   33: invokevirtual 97	java/io/DataOutputStream:writeByte	(I)V
    //   36: aload_0
    //   37: getfield 57	dl:c	Lc;
    //   40: aload_3
    //   41: invokeinterface 113 2 0
    //   46: aload_3
    //   47: invokevirtual 70	bj:c	()V
    //   50: return
    //   51: ldc 1
    //   53: invokevirtual 104	java/lang/String:length	()I
    //   56: pop2
    //   57: return
    // Local variable table:
    //   start	length	slot	name	signature
    //   0	58	0	this	dl
    //   0	58	1	paramInt1	int
    //   0	58	2	paramInt2	int
    //   13	34	3	localbj1	bj
    //   16	12	4	localbj2	bj
    //   51	1	5	localException	Exception
    // Exception table:
    //   from	to	target	type
    //   14	50	51	java/lang/Exception
  }
  
  public final void c(int paramInt1, int paramInt2, int paramInt3)
  {
    bj localbj1 = null;
    try
    {
      bj localbj2;
      (localbj2 = localbj1 = new bj(e[29])).c.writeByte(paramInt1);
      (localbj2 = localbj1).c.writeByte(paramInt2);
      (localbj2 = localbj1).c.writeByte(paramInt3);
      this.c.a(localbj1);
      return;
    }
    catch (Exception localException) {}finally
    {
      localbj1.c();
    }
  }
  
  public final void m()
  {
    bj localbj = null;
    try
    {
      localbj = d(e[7]);
      this.c.a(localbj);
      return;
    }
    catch (Exception localException2)
    {
      Exception localException1;
      return;
    }
    finally
    {
      localbj.c();
    }
  }
  
  public final void q(int paramInt)
  {
    bj localbj1 = null;
    try
    {
      bj localbj2;
      (localbj2 = localbj1 = new bj(e[44])).c.writeByte(paramInt);
      this.c.a(localbj1);
      return;
    }
    catch (Exception localException) {}finally
    {
      localbj1.c();
    }
  }
  
  public final void r(int paramInt)
  {
    bj localbj1 = null;
    try
    {
      bj localbj2;
      (localbj2 = localbj1 = c(e[32])).c.writeByte(paramInt);
      this.c.a(localbj1);
      return;
    }
    catch (Exception localException) {}finally
    {
      localbj1.c();
    }
  }
  
  public final void d(ao[] paramArrayOfao)
  {
    bj localbj1 = null;
    try
    {
      localbj1 = new bj(e[120]);
      int i = e[4];
      bj localbj2;
      while (p(i, e[21])) {
        if ((a(paramArrayOfao[i])) && ((!o(paramArrayOfao[i].j.f, e[121])) || (n(paramArrayOfao[i].j.f, e[20]))))
        {
          (localbj2 = localbj1).c.writeByte(paramArrayOfao[i].n);
          "".length();
          if ("   ".length() == "   ".length()) {
            break;
          }
        }
        else
        {
          i++;
          "".length();
          if (" ".length() >= "  ".length()) {
            return;
          }
        }
      }
      i = e[4];
      while (p(i, e[21]))
      {
        if ((a(paramArrayOfao[i])) && ((!o(paramArrayOfao[i].j.f, e[122])) || (n(paramArrayOfao[i].j.f, e[123])))) {
          (localbj2 = localbj1).c.writeByte(paramArrayOfao[i].n);
        }
        i++;
        "".length();
        if ((0x92 ^ 0x97) == 0) {
          return;
        }
      }
      this.c.a(localbj1);
      return;
    }
    catch (Exception localException2)
    {
      Exception localException1;
      return;
    }
    finally
    {
      localbj1.c();
    }
  }
  
  public final void n()
  {
    bj localbj = null;
    try
    {
      (localObject1 = localbj = d(e[119])).c.writeByte(fn.du);
      this.c.a(localbj);
      return;
    }
    catch (Exception localException)
    {
      Object localObject1;
      return;
    }
    finally
    {
      localbj.c();
    }
  }
  
  public final void c(int paramInt1, int paramInt2)
  {
    bj localbj1 = null;
    try
    {
      bj localbj2;
      (localbj2 = localbj1 = c(e[15])).c.writeByte(paramInt1);
      (localbj2 = localbj1).c.writeShort(paramInt2);
      this.c.a(localbj1);
      return;
    }
    catch (Exception localException) {}finally
    {
      localbj1.c();
    }
  }
  
  public final void d(int paramInt1, int paramInt2)
  {
    bj localbj1 = null;
    try
    {
      bj localbj2;
      (localbj2 = localbj1 = new bj(e[13])).c.writeByte(paramInt1);
      (localbj2 = localbj1).c.writeByte(paramInt2);
      this.c.a(localbj1);
      return;
    }
    catch (Exception localException) {}finally
    {
      localbj1.c();
    }
  }
  
  public final void b(String paramString, int paramInt)
  {
    bj localbj1 = null;
    try
    {
      bj localbj2;
      (localbj2 = localbj1 = d(e[95])).c.writeInt(paramInt);
      (localbj2 = localbj1).c.writeUTF(paramString);
      this.c.a(localbj1);
      return;
    }
    catch (Exception localException) {}finally
    {
      localbj1.c();
    }
  }
  
  public final void e(int paramInt1, int paramInt2)
  {
    bj localbj1 = null;
    try
    {
      bj localbj2;
      (localbj2 = localbj1 = new bj(e[27])).c.writeByte(paramInt1);
      (localbj2 = localbj1).c.writeByte(paramInt2);
      this.c.a(localbj1);
      return;
    }
    catch (Exception localException) {}finally
    {
      localbj1.c();
    }
  }
  
  public final void f(int paramInt1, int paramInt2)
  {
    bj localbj1 = null;
    try
    {
      bj localbj2;
      (localbj2 = localbj1 = d(e[36])).c.writeInt(paramInt1);
      (localbj2 = localbj1).c.writeInt(paramInt2);
      this.c.a(localbj1);
      return;
    }
    catch (Exception localException) {}finally
    {
      localbj1.c();
    }
  }
  
  public final void s(int paramInt)
  {
    bj localbj1 = null;
    try
    {
      bj localbj2;
      (localbj2 = localbj1 = new bj(e[28])).c.writeShort(paramInt);
      this.c.a(localbj1);
      return;
    }
    catch (Exception localException) {}finally
    {
      localbj1.c();
    }
  }
  
  public final void t(int paramInt)
  {
    bj localbj1 = null;
    try
    {
      bj localbj2;
      (localbj2 = localbj1 = c(e[76])).c.writeByte(paramInt);
      this.c.a(localbj1);
      return;
    }
    catch (Exception localException) {}finally
    {
      localbj1.c();
    }
  }
  
  public final void a(short paramShort)
  {
    bj localbj1 = null;
    try
    {
      bj localbj2;
      (localbj2 = localbj1 = new bj(e[''])).c.writeByte(paramShort);
      this.c.a(localbj1);
      return;
    }
    catch (Exception localException) {}finally
    {
      localbj1.c();
    }
  }
  
  private static boolean n(int paramInt1, int paramInt2)
  {
    return paramInt1 == paramInt2;
  }
  
  public final void u(int paramInt)
  {
    bj localbj1 = null;
    try
    {
      bj localbj2;
      (localbj2 = localbj1 = c(e[35])).c.writeInt(paramInt);
      this.c.a(localbj1);
      return;
    }
    catch (Exception localException) {}finally
    {
      localbj1.c();
    }
  }
  
  public final void v(int paramInt)
  {
    bj localbj1 = null;
    try
    {
      bj localbj2;
      (localbj2 = localbj1 = new bj(e[70])).c.writeInt(paramInt);
      this.c.a(localbj1);
      return;
    }
    catch (Exception localException) {}finally
    {
      localbj1.c();
    }
  }
  
  private static boolean as(int paramInt)
  {
    return paramInt > 0;
  }
  
  public final void o()
  {
    bj localbj = null;
    try
    {
      localbj = new bj(e[48]);
      this.c.a(localbj);
      return;
    }
    catch (Exception localException2)
    {
      Exception localException1;
      return;
    }
    finally
    {
      localbj.c();
    }
  }
  
  public final void w(int paramInt)
  {
    bj localbj1 = null;
    try
    {
      bj localbj2;
      (localbj2 = localbj1 = new bj(e[42])).c.writeInt(paramInt);
      this.c.a(localbj1);
      return;
    }
    catch (Exception localException) {}finally
    {
      localbj1.c();
    }
  }
  
  public final void b(short paramShort)
  {
    bj localbj1 = null;
    try
    {
      bj localbj2;
      (localbj2 = localbj1 = new bj(e[''])).c.writeByte(e[10]);
      (localbj2 = localbj1).c.writeShort(paramShort);
      this.c.a(localbj1);
      return;
    }
    catch (Exception localException) {}finally
    {
      localbj1.c();
    }
  }
  
  public final void p()
  {
    bj localbj = null;
    try
    {
      localbj = new bj(e[46]);
      this.c.a(localbj);
      return;
    }
    catch (Exception localException2)
    {
      Exception localException1;
      return;
    }
    finally
    {
      localbj.c();
    }
  }
  
  public final void j(String paramString)
  {
    bj localbj1 = null;
    try
    {
      bj localbj2;
      (localbj2 = localbj1 = new bj(e[67])).c.writeUTF(paramString);
      this.c.a(localbj1);
      return;
    }
    catch (Exception localException) {}finally
    {
      localbj1.c();
    }
  }
  
  public final void q()
  {
    bj localbj = null;
    try
    {
      localbj = d(e[115]);
      this.c.a(localbj);
      return;
    }
    catch (Exception localException2)
    {
      Exception localException1;
      return;
    }
    finally
    {
      localbj.c();
    }
  }
  
  public final void r()
  {
    bj localbj = null;
    try
    {
      localbj = d(e[107]);
      this.c.a(localbj);
      return;
    }
    catch (Exception localException2)
    {
      Exception localException1;
      return;
    }
    finally
    {
      localbj.c();
    }
  }
  
  public final void x(int paramInt)
  {
    bj localbj1 = null;
    try
    {
      bj localbj2;
      (localbj2 = localbj1 = c(e[74])).c.writeByte(paramInt);
      this.c.a(localbj1);
      return;
    }
    catch (Exception localException) {}finally
    {
      localbj1.c();
    }
  }
  
  public final void y(int paramInt)
  {
    bj localbj1 = null;
    try
    {
      bj localbj2;
      (localbj2 = localbj1 = d(e[108])).c.writeInt(paramInt);
      this.c.a(localbj1);
      return;
    }
    catch (Exception localException) {}finally
    {
      localbj1.c();
    }
  }
  
  public final void k(String paramString)
  {
    bj localbj1 = null;
    try
    {
      bj localbj2;
      (localbj2 = localbj1 = c(e[85])).c.writeUTF(paramString);
      this.c.a(localbj1);
      return;
    }
    catch (Exception localException) {}finally
    {
      localbj1.c();
    }
  }
  
  public final void s()
  {
    try
    {
      Object localObject2;
      (localObject2 = localObject1 = b(e[3])).c.writeByte(bv.j);
      (localObject2 = localObject1).c.writeByte(cf.c);
      (localObject2 = localObject1).c.writeBoolean(aw.ah);
      (localObject2 = localObject1).c.writeInt(aw.b);
      (localObject2 = localObject1).c.writeInt(aw.av);
      (localObject2 = localObject1).c.writeBoolean(ek.g);
      (localObject2 = localObject1).c.writeBoolean(aw.s);
      (localObject2 = localObject1).c.writeUTF(System.getProperty("microedition.platform"));
      (localObject2 = localObject1).c.writeByte(e[4]);
      (localObject2 = localObject1).c.writeInt(e[4]);
      (localObject2 = localObject1).c.writeByte(an.dc);
      (localObject2 = localObject1).c.writeInt(bv.f);
      (localObject2 = localObject1).c.writeUTF(bv.i);
      this.c.a((bj)localObject1);
      ((bj)localObject1).c();
      return;
    }
    catch (IOException localIOException)
    {
      Object localObject1;
      (localObject1 = localIOException).printStackTrace();
    }
  }
  
  public final void l(String paramString)
  {
    bj localbj1 = null;
    try
    {
      bj localbj2;
      (localbj2 = localbj1 = new bj(e[86])).c.writeUTF(paramString);
      this.c.a(localbj1);
      return;
    }
    catch (Exception localException) {}finally
    {
      localbj1.c();
    }
  }
  
  public final void b(String paramString1, String paramString2, String paramString3)
  {
    s();
    try
    {
      Object localObject2;
      (localObject2 = localObject1 = b(e[5])).c.writeUTF(paramString1);
      (localObject2 = localObject1).c.writeUTF(paramString2);
      (localObject2 = localObject1).c.writeUTF(paramString3);
      (localObject2 = localObject1).c.writeUTF("");
      (localObject2 = localObject1).c.writeUTF("");
      (localObject2 = localObject1).c.writeUTF(df.d("random"));
      (localObject2 = localObject1).c.writeByte(bv.e);
      this.c.a((bj)localObject1);
      ((bj)localObject1).c();
      return;
    }
    catch (IOException localIOException)
    {
      Object localObject1;
      (localObject1 = localIOException).printStackTrace();
    }
  }
  
  public final void t()
  {
    bj localbj = null;
    try
    {
      localbj = d(e[110]);
      this.c.a(localbj);
      return;
    }
    catch (Exception localException2)
    {
      Exception localException1;
      return;
    }
    finally
    {
      localbj.c();
    }
  }
  
  public final void u()
  {
    bj localbj = null;
    try
    {
      localbj = d(e[98]);
      this.c.a(localbj);
      return;
    }
    catch (Exception localException2)
    {
      Exception localException1;
      return;
    }
    finally
    {
      localbj.c();
    }
  }
  
  private static boolean o(int paramInt1, int paramInt2)
  {
    return paramInt1 != paramInt2;
  }
  
  public final void z(int paramInt)
  {
    bj localbj1 = null;
    try
    {
      bj localbj2;
      (localbj2 = localbj1 = d(e[109])).c.writeInt(paramInt);
      this.c.a(localbj1);
      return;
    }
    catch (Exception localException) {}finally
    {
      localbj1.c();
    }
  }
  
  public final void m(String paramString)
  {
    bj localbj1 = null;
    try
    {
      bj localbj2;
      (localbj2 = localbj1 = c(e[94])).c.writeUTF(paramString);
      this.c.a(localbj1);
      return;
    }
    catch (Exception localException) {}finally
    {
      localbj1.c();
    }
  }
  
  public final void g(int paramInt1, int paramInt2)
  {
    bj localbj1 = null;
    try
    {
      bj localbj2;
      (localbj2 = localbj1 = new bj(e[22])).c.writeByte(paramInt1);
      if (m(paramInt2, e[10])) {
        (localbj2 = localbj1).c.writeInt(paramInt2);
      }
      this.c.a(localbj1);
      return;
    }
    catch (Exception localException) {}finally
    {
      localbj1.c();
    }
  }
  
  public final void n(String paramString)
  {
    bj localbj1 = null;
    try
    {
      bj localbj2;
      (localbj2 = localbj1 = new bj(e[88])).c.writeUTF(paramString);
      this.c.a(localbj1);
      return;
    }
    catch (Exception localException) {}finally
    {
      localbj1.c();
    }
  }
  
  public final void v()
  {
    bj localbj = null;
    try
    {
      (localObject1 = localbj = new bj(e[77])).c.writeByte(dt.g().dm);
      this.c.a(localbj);
      return;
    }
    catch (Exception localException)
    {
      Object localObject1;
      return;
    }
    finally
    {
      localbj.c();
    }
  }
  
  public final void w()
  {
    bj localbj = null;
    try
    {
      localbj = d(e[65]);
      this.c.a(localbj);
      return;
    }
    catch (Exception localException2)
    {
      Exception localException1;
      return;
    }
    finally
    {
      localbj.c();
    }
  }
  
  public final void b(String paramString1, String paramString2)
  {
    bj localbj1 = null;
    try
    {
      bj localbj2;
      (localbj2 = localbj1 = new bj(e[90])).c.writeUTF(paramString1);
      (localbj2 = localbj1).c.writeUTF(paramString2);
      this.c.a(localbj1);
      return;
    }
    catch (Exception localException) {}finally
    {
      localbj1.c();
    }
  }
  
  public final void e(ao[] paramArrayOfao)
  {
    aw.h.a();
    bj localbj1 = null;
    try
    {
      localbj1 = new bj(e['']);
      int i = e[4];
      while (p(i, paramArrayOfao.length))
      {
        if (a(paramArrayOfao[i]))
        {
          bj localbj2;
          (localbj2 = localbj1).c.writeByte(paramArrayOfao[i].n);
        }
        i++;
        "".length();
        if (" ".length() == 0) {
          return;
        }
      }
      this.c.a(localbj1);
      return;
    }
    catch (Exception localException2)
    {
      Exception localException1;
      return;
    }
    finally
    {
      localbj1.c();
    }
  }
  
  public final void a(short paramShort, String paramString, byte paramByte)
  {
    bj localbj1 = null;
    try
    {
      bj localbj2;
      (localbj2 = localbj1 = new bj(e[31])).c.writeShort(paramShort);
      (localbj2 = localbj1).c.writeUTF(paramString);
      (localbj2 = localbj1).c.writeByte(paramByte);
      this.c.a(localbj1);
      return;
    }
    catch (Exception localException) {}finally
    {
      localbj1.c();
    }
  }
  
  public final void aa(int paramInt)
  {
    bj localbj1 = null;
    try
    {
      bj localbj2;
      (localbj2 = localbj1 = c(e[104])).c.writeInt(paramInt);
      this.c.a(localbj1);
      return;
    }
    catch (Exception localException) {}finally
    {
      localbj1.c();
    }
  }
  
  public final void a(ao paramao, ao[] paramArrayOfao)
  {
    bj localbj1 = null;
    try
    {
      bj localbj2;
      (localbj2 = localbj1 = new bj(e[38])).c.writeBoolean(e[4]);
      (localbj2 = localbj1).c.writeByte(paramao.n);
      paramao = e[4];
      while (p(paramao, paramArrayOfao.length))
      {
        if (a(paramArrayOfao[paramao])) {
          (localbj2 = localbj1).c.writeByte(paramArrayOfao[paramao].n);
        }
        paramao++;
        "".length();
        if (-" ".length() > "  ".length()) {
          return;
        }
      }
      this.c.a(localbj1);
      return;
    }
    catch (Exception localException) {}finally
    {
      localbj1.c();
    }
  }
  
  public final void ab(int paramInt)
  {
    bj localbj1 = null;
    try
    {
      bj localbj2;
      (localbj2 = localbj1 = d(e[15])).c.writeByte(paramInt);
      this.c.a(localbj1);
      return;
    }
    catch (Exception localException) {}finally
    {
      localbj1.c();
    }
  }
  
  public final void ac(int paramInt)
  {
    bj localbj1 = null;
    try
    {
      bj localbj2;
      (localbj2 = localbj1 = new bj(e[68])).c.writeInt(paramInt);
      this.c.a(localbj1);
      return;
    }
    catch (Exception localException) {}finally
    {
      localbj1.c();
    }
  }
  
  private static bj d(byte paramByte)
  {
    try
    {
      bj localbj;
      (localbj = localObject = new bj(e[1])).c.writeByte(paramByte);
      return (bj)localObject;
    }
    catch (IOException localIOException)
    {
      Object localObject;
      (localObject = localIOException).printStackTrace();
    }
    return null;
  }
  
  public final void ad(int paramInt)
  {
    bj localbj = null;
    try
    {
      (localObject = localbj = new bj(e[20])).c.writeByte(paramInt);
      this.c.a(localbj);
      localbj.c();
      "".length();
      if ((0x41 ^ 0x37 ^ 0x2B ^ 0x58) <= 0) {
        return;
      }
    }
    catch (Exception localException)
    {
      Object localObject;
      localbj.c();
      "".length();
      if (" ".length() > "  ".length()) {
        return;
      }
    }
    finally
    {
      localbj.c();
    }
    if ((a(dt.g().w[paramInt])) && (n(dt.g().w[paramInt].j.b, e[21])))
    {
      fn.j().af();
      dw.a("");
    }
  }
  
  public final void ae(int paramInt)
  {
    bj localbj1 = null;
    try
    {
      bj localbj2;
      (localbj2 = localbj1 = new bj(e[19])).c.writeByte(paramInt);
      this.c.a(localbj1);
      return;
    }
    catch (Exception localException) {}finally
    {
      localbj1.c();
    }
  }
  
  public final void h(int paramInt1, int paramInt2)
  {
    bj localbj1 = null;
    try
    {
      bj localbj2;
      (localbj2 = localbj1 = c(e[12])).c.writeShort(paramInt1);
      (localbj2 = localbj1).c.writeByte(paramInt2);
      this.c.a(localbj1);
      return;
    }
    catch (Exception localException) {}finally
    {
      localbj1.c();
    }
  }
  
  public final void a(boolean paramBoolean)
  {
    bj localbj1 = null;
    try
    {
      bj localbj2;
      (localbj2 = localbj1 = c(e[79])).c.writeBoolean(paramBoolean);
      this.c.a(localbj1);
      return;
    }
    catch (Exception localException) {}finally
    {
      localbj1.c();
    }
  }
  
  private static boolean at(int paramInt)
  {
    return paramInt != 0;
  }
  
  public final void a(String paramString1, String paramString2, String paramString3, String paramString4, String paramString5, String paramString6, String paramString7)
  {
    try
    {
      Object localObject2;
      (localObject2 = localObject1 = new bj(e[''])).c.writeUTF(paramString1);
      (localObject2 = localObject1).c.writeUTF(paramString2);
      (localObject2 = localObject1).c.writeUTF(paramString3);
      (localObject2 = localObject1).c.writeUTF(paramString4);
      (localObject2 = localObject1).c.writeUTF(paramString5);
      (localObject2 = localObject1).c.writeUTF(paramString6);
      (localObject2 = localObject1).c.writeUTF(paramString7);
      this.c.a((bj)localObject1);
      ((bj)localObject1).c();
      return;
    }
    catch (Exception localException)
    {
      Object localObject1;
      (localObject1 = localException).printStackTrace();
    }
  }
  
  public final void af(int paramInt)
  {
    bj localbj1 = null;
    try
    {
      bj localbj2;
      (localbj2 = localbj1 = new bj(e[''])).c.writeShort(paramInt);
      this.c.a(localbj1);
      return;
    }
    catch (Exception localException) {}finally
    {
      localbj1.c();
    }
  }
  
  public final void o(String paramString)
  {
    bj localbj1 = null;
    try
    {
      bj localbj2;
      (localbj2 = localbj1 = d(e[111])).c.writeUTF(paramString);
      this.c.a(localbj1);
      return;
    }
    catch (Exception localException) {}finally
    {
      localbj1.c();
    }
  }
  
  private static boolean b(Object paramObject)
  {
    return paramObject == null;
  }
  
  public final void ag(int paramInt)
  {
    bj localbj1 = null;
    try
    {
      bj localbj2;
      (localbj2 = localbj1 = new bj(e[71])).c.writeInt(paramInt);
      this.c.a(localbj1);
      return;
    }
    catch (Exception localException) {}finally
    {
      localbj1.c();
    }
  }
  
  public final void d(int paramInt1, int paramInt2, int paramInt3)
  {
    aw.h.a();
    bj localbj1 = null;
    try
    {
      bj localbj2;
      (localbj2 = localbj1 = new bj(e[23])).c.writeByte(paramInt1);
      (localbj2 = localbj1).c.writeByte(paramInt2);
      if (m(paramInt3, e[10])) {
        (localbj2 = localbj1).c.writeShort(paramInt3);
      }
      this.c.a(localbj1);
      return;
    }
    catch (Exception localException) {}finally
    {
      localbj1.c();
    }
  }
  
  public final void ah(int paramInt)
  {
    bj localbj1 = null;
    try
    {
      bj localbj2;
      (localbj2 = localbj1 = d(e[12])).c.writeByte(paramInt);
      this.c.a(localbj1);
      return;
    }
    catch (Exception localException) {}finally
    {
      localbj1.c();
    }
  }
  
  public final void ai(int paramInt)
  {
    bj localbj1 = null;
    try
    {
      bj localbj2;
      (localbj2 = localbj1 = new bj(e[69])).c.writeInt(paramInt);
      this.c.a(localbj1);
      return;
    }
    catch (Exception localException) {}finally
    {
      localbj1.c();
    }
  }
  
  public final void p(String paramString)
  {
    bj localbj1 = null;
    try
    {
      bj localbj2;
      (localbj2 = localbj1 = d(e[75])).c.writeUTF(paramString);
      this.c.a(localbj1);
      return;
    }
    catch (Exception localException) {}finally
    {
      localbj1.c();
    }
  }
  
  public final void c(String paramString1, String paramString2, String paramString3)
  {
    try
    {
      Object localObject2;
      (localObject2 = localObject1 = new bj(e[6])).c.writeUTF(paramString1);
      (localObject2 = localObject1).c.writeUTF(paramString2);
      (localObject2 = localObject1).c.writeUTF(paramString3);
      this.c.a((bj)localObject1);
      ((bj)localObject1).c();
      return;
    }
    catch (Exception localException)
    {
      Object localObject1;
      (localObject1 = localException).printStackTrace();
    }
  }
  
  public final void x()
  {
    bj localbj = new bj(e[8]);
    this.c.a(localbj);
    localbj.c();
  }
  
  public final void aj(int paramInt)
  {
    bj localbj1 = null;
    try
    {
      bj localbj2;
      (localbj2 = localbj1 = new bj(e[18])).c.writeByte(paramInt);
      this.c.a(localbj1);
      return;
    }
    catch (Exception localException) {}finally
    {
      localbj1.c();
    }
  }
  
  public final void y()
  {
    bj localbj = null;
    try
    {
      localbj = c(e[33]);
      this.c.a(localbj);
      return;
    }
    catch (Exception localException2)
    {
      Exception localException1;
      return;
    }
    finally
    {
      localbj.c();
    }
  }
  
  public final void z()
  {
    bj localbj = null;
    try
    {
      localbj = c(e[34]);
      this.c.a(localbj);
      return;
    }
    catch (Exception localException2)
    {
      Exception localException1;
      return;
    }
    finally
    {
      localbj.c();
    }
  }
  
  private static boolean p(int paramInt1, int paramInt2)
  {
    return paramInt1 < paramInt2;
  }
  
  public final void aa()
  {
    bj localbj = null;
    try
    {
      localbj = new bj(e[47]);
      this.c.a(localbj);
      return;
    }
    catch (Exception localException2)
    {
      Exception localException1;
      return;
    }
    finally
    {
      localbj.c();
    }
  }
  
  public final void ak(int paramInt)
  {
    bj localbj1 = null;
    try
    {
      bj localbj2;
      (localbj2 = localbj1 = new bj(e[''])).c.writeByte(e['']);
      (localbj2 = localbj1).c.writeShort(paramInt);
      this.c.a(localbj1);
      return;
    }
    catch (Exception localException) {}finally
    {
      localbj1.c();
    }
  }
  
  public final void ab()
  {
    bj localbj = null;
    try
    {
      localbj = new bj(e[58]);
      this.c.a(localbj);
      return;
    }
    catch (Exception localException2)
    {
      Exception localException1;
      return;
    }
    finally
    {
      localbj.c();
    }
  }
  
  public final void q(String paramString)
  {
    bj localbj1 = null;
    try
    {
      bj localbj2;
      (localbj2 = localbj1 = new bj(e[60])).c.writeUTF(paramString);
      this.c.a(localbj1);
      return;
    }
    catch (Exception localException) {}finally
    {
      localbj1.c();
    }
  }
  
  public final void i(int paramInt1, int paramInt2)
  {
    try
    {
      if ((!ar(paramInt1 - this.b)) || (at(paramInt2 - this.d)))
      {
        Object localObject2;
        (localObject2 = localObject1 = new bj(e[10])).c.writeShort(paramInt1);
        (localObject2 = localObject1).c.writeShort(paramInt2);
        this.b = paramInt1;
        this.d = paramInt2;
        this.c.a((bj)localObject1);
        ((bj)localObject1).c();
      }
      return;
    }
    catch (Exception localException)
    {
      Object localObject1;
      (localObject1 = localException).printStackTrace();
    }
  }
  
  public final void al(int paramInt)
  {
    bj localbj1 = null;
    try
    {
      bj localbj2;
      (localbj2 = localbj1 = new bj(e[41])).c.writeInt(paramInt);
      this.c.a(localbj1);
      return;
    }
    catch (Exception localException) {}finally
    {
      localbj1.c();
    }
  }
  
  public final void am(int paramInt)
  {
    bj localbj1 = null;
    try
    {
      bj localbj2;
      (localbj2 = localbj1 = new bj(e[117])).c.writeInt(paramInt);
      this.c.a(localbj1);
      return;
    }
    catch (Exception localException) {}finally
    {
      localbj1.c();
    }
  }
  
  public final void ac()
  {
    bj localbj = null;
    try
    {
      localbj = c(e[25]);
      this.c.a(localbj);
      return;
    }
    catch (Exception localException2)
    {
      Exception localException1;
      return;
    }
    finally
    {
      localbj.c();
    }
  }
  
  public final void ad()
  {
    bj localbj = null;
    try
    {
      localbj = d(e[64]);
      this.c.a(localbj);
      return;
    }
    catch (Exception localException2)
    {
      Exception localException1;
      return;
    }
    finally
    {
      localbj.c();
    }
  }
  
  public static dl ae()
  {
    if (b(a)) {
      a = new dl();
    }
    return a;
  }
  
  public final void r(String paramString)
  {
    bj localbj1 = null;
    try
    {
      bj localbj2;
      (localbj2 = localbj1 = new bj(e[87])).c.writeUTF(paramString);
      (localbj2 = localbj1).c.writeByte(e[4]);
      this.c.a(localbj1);
      return;
    }
    catch (Exception localException) {}finally
    {
      localbj1.c();
    }
  }
  
  public final void c(short paramShort)
  {
    bj localbj1 = null;
    try
    {
      bj localbj2;
      (localbj2 = localbj1 = new bj(e[30])).c.writeShort(paramShort);
      this.c.a(localbj1);
      return;
    }
    catch (Exception localException) {}finally
    {
      localbj1.c();
    }
  }
  
  public final void a(String paramString, byte[] paramArrayOfByte, byte paramByte)
  {
    bj localbj1 = null;
    try
    {
      bj localbj2;
      (localbj2 = localbj1 = c(e[93])).c.writeUTF(paramString);
      (localbj2 = localbj1).c.writeInt(paramArrayOfByte.length);
      (localbj2 = localbj1).c.write(paramArrayOfByte);
      (localbj2 = localbj1).c.writeByte(paramByte);
      this.c.a(localbj1);
      return;
    }
    catch (Exception localException) {}finally
    {
      localbj1.c();
    }
  }
  
  public final void b(ao paramao, ao[] paramArrayOfao)
  {
    bj localbj1 = null;
    try
    {
      bj localbj2;
      (localbj2 = localbj1 = new bj(e[124])).c.writeByte(paramao.n);
      paramao = e[4];
      while (p(paramao, e[21]))
      {
        if ((a(paramArrayOfao[paramao])) && ((!o(paramArrayOfao[paramao].j.f, e[122])) || (!o(paramArrayOfao[paramao].j.f, e[123])) || (n(paramArrayOfao[paramao].j.f, e[125])))) {
          (localbj2 = localbj1).c.writeByte(paramArrayOfao[paramao].n);
        }
        paramao++;
        "".length();
        if (null != null) {
          return;
        }
      }
      this.c.a(localbj1);
      return;
    }
    catch (Exception localException) {}finally
    {
      localbj1.c();
    }
  }
  
  public final void an(int paramInt)
  {
    bj localbj1 = null;
    try
    {
      bj localbj2;
      (localbj2 = localbj1 = new bj(e[82])).c.writeByte(paramInt);
      this.c.a(localbj1);
      return;
    }
    catch (Exception localException) {}finally
    {
      localbj1.c();
    }
  }
  
  public final void a(ao paramao, ao[] paramArrayOfao, boolean paramBoolean)
  {
    aw.h.a();
    bj localbj1 = null;
    try
    {
      bj localbj2;
      (localbj2 = localbj1 = new bj(e[38])).c.writeBoolean(paramBoolean);
      (localbj2 = localbj1).c.writeByte(paramao.n);
      paramao = e[4];
      while (p(paramao, paramArrayOfao.length))
      {
        if (a(paramArrayOfao[paramao])) {
          (localbj2 = localbj1).c.writeByte(paramArrayOfao[paramao].n);
        }
        paramao++;
        "".length();
        if ((111 + 34 - 13 + 8 ^ 104 + 103 - 146 + 76) <= 0) {
          return;
        }
      }
      this.c.a(localbj1);
      return;
    }
    catch (Exception localException) {}finally
    {
      localbj1.c();
    }
  }
  
  public final void c(ao paramao, ao[] paramArrayOfao)
  {
    aw.h.a();
    bj localbj1 = null;
    try
    {
      bj localbj2;
      (localbj2 = localbj1 = new bj(e[126])).c.writeByte(paramao.n);
      paramao = e[4];
      int i = e[4];
      while (p(i, paramArrayOfao.length))
      {
        if ((a(paramArrayOfao[i])) && (n(paramArrayOfao[i].j.f, e[127])))
        {
          (localbj2 = localbj1).c.writeByte(paramArrayOfao[i].n);
          paramao++;
        }
        i++;
        "".length();
        if (-"   ".length() >= 0) {
          return;
        }
      }
      if (q(paramao, e[39]))
      {
        this.c.a(localbj1);
        return;
      }
      aw.a(an.bw);
      return;
    }
    catch (Exception localException) {}finally
    {
      localbj1.c();
    }
  }
  
  public final void af()
  {
    bj localbj = null;
    try
    {
      localbj = d(e[72]);
      this.c.a(localbj);
      return;
    }
    catch (Exception localException2)
    {
      Exception localException1;
      return;
    }
    finally
    {
      localbj.c();
    }
  }
  
  public final void j(int paramInt1, int paramInt2)
  {
    bj localbj1 = null;
    try
    {
      bj localbj2;
      (localbj2 = localbj1 = d(e[81])).c.writeByte(paramInt1);
      (localbj2 = localbj1).c.writeInt(paramInt2);
      this.c.a(localbj1);
      return;
    }
    catch (Exception localException) {}finally
    {
      localbj1.c();
    }
  }
  
  public final void f(ao[] paramArrayOfao)
  {
    bj localbj1 = null;
    try
    {
      localbj1 = new bj(e[39]);
      int i = e[4];
      while (p(i, paramArrayOfao.length))
      {
        if (a(paramArrayOfao[i]))
        {
          bj localbj2;
          (localbj2 = localbj1).c.writeByte(paramArrayOfao[i].n);
        }
        i++;
        "".length();
        if (((0x42 ^ 0x70) & (0x1D ^ 0x2F ^ 0xFFFFFFFF)) != 0) {
          return;
        }
      }
      this.c.a(localbj1);
      return;
    }
    catch (Exception localException2)
    {
      Exception localException1;
      return;
    }
    finally
    {
      localbj1.c();
    }
  }
  
  public final void e(int paramInt1, int paramInt2, int paramInt3)
  {
    bj localbj1 = null;
    try
    {
      bj localbj2;
      (localbj2 = localbj1 = c(e[124])).c.writeByte(paramInt1);
      (localbj2 = localbj1).c.writeInt(paramInt2);
      (localbj2 = localbj1).c.writeInt(paramInt3);
      this.c.a(localbj1);
      return;
    }
    catch (Exception localException) {}finally
    {
      localbj1.c();
    }
  }
  
  public final void ao(int paramInt)
  {
    bj localbj1 = null;
    try
    {
      bj localbj2;
      (localbj2 = localbj1 = c(e[72])).c.writeInt(paramInt);
      this.c.a(localbj1);
      return;
    }
    catch (Exception localException) {}finally
    {
      localbj1.c();
    }
  }
  
  public final void ap(int paramInt)
  {
    bj localbj1 = null;
    try
    {
      bj localbj2;
      (localbj2 = localbj1 = d(e[35])).c.writeInt(paramInt);
      this.c.a(localbj1);
      return;
    }
    catch (Exception localException) {}finally
    {
      localbj1.c();
    }
  }
  
  public final void aq(int paramInt)
  {
    bj localbj1 = null;
    try
    {
      bj localbj2;
      (localbj2 = localbj1 = new bj(e[66])).c.writeInt(paramInt);
      this.c.a(localbj1);
      return;
    }
    catch (Exception localException) {}finally
    {
      localbj1.c();
    }
  }
  
  public final void a(String paramString, int paramInt1, int paramInt2)
  {
    bj localbj1 = new bj(e[1]);
    try
    {
      bj localbj2;
      (localbj2 = localbj1).c.writeByte(e[3]);
      (localbj2 = localbj1).c.writeUTF(paramString);
      (localbj2 = localbj1).c.writeByte(paramInt1);
      (localbj2 = localbj1).c.writeByte(paramInt2);
      "".length();
      if (-" ".length() == "   ".length()) {
        return;
      }
    }
    catch (Exception localException)
    {
      (paramString = localException).printStackTrace();
      this.c.a(localbj1);
    }
  }
  
  public final void b(short paramShort, String paramString)
  {
    bj localbj1 = null;
    try
    {
      bj localbj2;
      (localbj2 = localbj1 = new bj(e[6])).c.writeUTF(paramString);
      (localbj2 = localbj1).c.writeShort(paramShort);
      this.c.a(localbj1);
      return;
    }
    catch (Exception localException) {}finally
    {
      localbj1.c();
    }
  }
  
  public final void d(ao paramao, ao[] paramArrayOfao)
  {
    aw.h.a();
    bj localbj1 = null;
    try
    {
      bj localbj2;
      (localbj2 = localbj1 = new bj(e[124])).c.writeByte(paramao.n);
      paramao = e[4];
      while (p(paramao, paramArrayOfao.length))
      {
        if ((a(paramArrayOfao[paramao])) && ((!o(paramArrayOfao[paramao].j.f, e[122])) || (!o(paramArrayOfao[paramao].j.f, e[123])) || (n(paramArrayOfao[paramao].j.f, e[125])))) {
          (localbj2 = localbj1).c.writeByte(paramArrayOfao[paramao].n);
        }
        paramao++;
        "".length();
        if (((0xF0 ^ 0xBF) & (0x1E ^ 0x51 ^ 0xFFFFFFFF)) != 0) {
          return;
        }
      }
      this.c.a(localbj1);
      return;
    }
    catch (Exception localException) {}finally
    {
      localbj1.c();
    }
  }
  
  public final void s(String paramString)
  {
    try
    {
      bj localbj;
      (localbj = localObject = b(e[7])).c.writeUTF(paramString);
      this.c.a((bj)localObject);
      ((bj)localObject).c();
      return;
    }
    catch (IOException localIOException)
    {
      Object localObject;
      (localObject = localIOException).printStackTrace();
    }
  }
  
  public final void ag()
  {
    bj localbj = null;
    try
    {
      localbj = c(e[84]);
      this.c.a(localbj);
      return;
    }
    catch (Exception localException2)
    {
      Exception localException1;
      return;
    }
    finally
    {
      localbj.c();
    }
  }
  
  public final void ah()
  {
    bj localbj = null;
    try
    {
      localbj = c(e[78]);
      this.c.a(localbj);
      return;
    }
    catch (Exception localException2)
    {
      Exception localException1;
      return;
    }
    finally
    {
      localbj.c();
    }
  }
  
  private static boolean q(int paramInt1, int paramInt2)
  {
    return paramInt1 >= paramInt2;
  }
  
  public final void k(int paramInt1, int paramInt2)
  {
    aw.h.a();
    bj localbj1 = null;
    try
    {
      bj localbj2;
      (localbj2 = localbj1 = new bj(e[22])).c.writeByte(paramInt1);
      if (m(paramInt2, e[10])) {
        (localbj2 = localbj1).c.writeInt(paramInt2);
      }
      this.c.a(localbj1);
      return;
    }
    catch (Exception localException) {}finally
    {
      localbj1.c();
    }
  }
  
  public final void l(int paramInt1, int paramInt2)
  {
    bj localbj1 = null;
    try
    {
      bj localbj2;
      (localbj2 = localbj1 = new bj(e[59])).c.writeByte(paramInt1);
      (localbj2 = localbj1).c.writeByte(paramInt2);
      this.c.a(localbj1);
      return;
    }
    catch (Exception localException) {}finally
    {
      localbj1.c();
    }
  }
  
  public final void ai()
  {
    bj localbj = null;
    try
    {
      localbj = d(e[112]);
      this.c.a(localbj);
      return;
    }
    catch (Exception localException2)
    {
      Exception localException1;
      return;
    }
    finally
    {
      localbj.c();
    }
  }
  
  public final void aj()
  {
    bj localbj = null;
    try
    {
      localbj = d(e[63]);
      this.c.a(localbj);
      return;
    }
    catch (Exception localException2)
    {
      Exception localException1;
      return;
    }
    finally
    {
      localbj.c();
    }
  }
  
  public final void a(byte paramByte, String paramString)
  {
    bj localbj1 = null;
    try
    {
      bj localbj2;
      (localbj2 = localbj1 = new bj(e[''])).c.writeByte(paramByte);
      (localbj2 = localbj1).c.writeUTF(paramString);
      this.c.a(localbj1);
      return;
    }
    catch (Exception localException) {}finally
    {
      localbj1.c();
    }
  }
  
  public final void a(ci paramci1, ci paramci2, int paramInt)
  {
    bj localbj1 = null;
    if (at(paramInt)) {
      try
      {
        bj localbj2;
        e locale;
        if ((as(paramci1.size())) && (as(paramci2.size())))
        {
          switch (paramInt)
          {
          case 1: 
            localbj1 = new bj(e[50]);
            "".length();
            if (-" ".length() >= "  ".length()) {
              return;
            }
            break;
          case 2: 
            localbj1 = new bj(e[51]);
          }
          (localbj2 = localbj1).c.writeByte(paramci1.size());
          paramInt = e[4];
          while (p(paramInt, paramci1.size()))
          {
            locale = (e)paramci1.elementAt(paramInt);
            (localbj2 = localbj1).c.writeByte(locale.y);
            paramInt++;
            "".length();
            if ("  ".length() <= " ".length()) {
              return;
            }
          }
          paramInt = e[4];
        }
        while (p(paramInt, paramci2.size()))
        {
          if (a(paramci1 = (dt)paramci2.elementAt(paramInt)))
          {
            (localbj2 = localbj1).c.writeInt(paramci1.fy);
            "".length();
            if (-"   ".length() < 0) {}
          }
          else
          {
            (localbj2 = localbj1).c.writeInt(e[52]);
          }
          paramInt++;
          "".length();
          if (" ".length() <= 0)
          {
            return;
            if (as(paramci1.size()))
            {
              localbj1 = new bj(e[53]);
              paramInt = e[4];
              do
              {
                if (!p(paramInt, paramci1.size())) {
                  break;
                }
                locale = (e)paramci1.elementAt(paramInt);
                (localbj2 = localbj1).c.writeByte(locale.y);
                paramInt++;
                "".length();
              } while (-" ".length() != ((0x61 ^ 0x36 ^ 0x9 ^ 0x61) & (5 + 89 - 71 + 129 ^ 6 + 11 - -40 + 110 ^ -" ".length())));
              return;
            }
            if (as(paramci2.size()))
            {
              localbj1 = new bj(e[54]);
              paramInt = e[4];
              while (p(paramInt, paramci2.size()))
              {
                paramci1 = (dt)paramci2.elementAt(paramInt);
                (localbj2 = localbj1).c.writeInt(paramci1.fy);
                paramInt++;
                "".length();
                if ("  ".length() <= -" ".length()) {
                  return;
                }
              }
            }
          }
        }
        if (a(localbj1)) {
          this.c.a(localbj1);
        }
        return;
      }
      catch (Exception localException)
      {
        System.out.println("loi send attt " + localException.getMessage());
        localException.printStackTrace();
      }
    }
  }
  
  public static void ak() {}
}


/* Location:              C:\Users\Admin\OneDrive\Documents\NSOv2_test.jar!\dl.class
 * Java compiler version: 1 (45.3)
 * JD-Core Version:       0.7.1
 */