public final class ea
{
  public String a = "";
  public int b;
  public int c;
  public int d;
  public int e;
  public int f;
  public String g = "";
  public ao[] h;
  public String i = "";
  public String j = "";
  public String k = "";
  private static int[] q;
  public int l;
  public int m;
  public int n;
  public int o;
  public int p;
  
  public static void a() {}
  
  static
  {
    cs.a(148);
    a();
  }
  
  private static boolean a(int paramInt1, int paramInt2)
  {
    return paramInt1 == paramInt2;
  }
  
  private static boolean b(int paramInt1, int paramInt2)
  {
    return paramInt1 < paramInt2;
  }
  
  /* Error */
  public final void a(String paramString)
  {
    // Byte code:
    //   0: aload_1
    //   1: ldc 2
    //   3: invokestatic 29	cl:a	(Ljava/lang/String;Ljava/lang/String;)[Ljava/lang/String;
    //   6: astore_1
    //   7: aload_0
    //   8: ldc 1
    //   10: putfield 22	ea:g	Ljava/lang/String;
    //   13: getstatic 26	ea:q	[I
    //   16: iconst_0
    //   17: iaload
    //   18: istore_2
    //   19: iload_2
    //   20: aload_1
    //   21: arraylength
    //   22: invokestatic 34	ea:b	(II)Z
    //   25: ifeq +873 -> 898
    //   28: aload_1
    //   29: iload_2
    //   30: aaload
    //   31: invokevirtual 41	java/lang/String:trim	()Ljava/lang/String;
    //   34: dup
    //   35: astore_3
    //   36: ldc 1
    //   38: invokevirtual 39	java/lang/String:equals	(Ljava/lang/Object;)Z
    //   41: invokestatic 32	ea:a	(I)Z
    //   44: ifeq +829 -> 873
    //   47: aload_3
    //   48: ldc 6
    //   50: invokestatic 29	cl:a	(Ljava/lang/String;Ljava/lang/String;)[Ljava/lang/String;
    //   53: dup
    //   54: astore_3
    //   55: getstatic 26	ea:q	[I
    //   58: iconst_0
    //   59: iaload
    //   60: aaload
    //   61: astore 4
    //   63: aload_3
    //   64: getstatic 26	ea:q	[I
    //   67: iconst_1
    //   68: iaload
    //   69: aaload
    //   70: invokestatic 36	java/lang/Integer:parseInt	(Ljava/lang/String;)I
    //   73: dup
    //   74: istore 5
    //   76: invokestatic 32	ea:a	(I)Z
    //   79: ifeq +114 -> 193
    //   82: ldc 7
    //   84: aload 4
    //   86: invokestatic 42	java/lang/String:valueOf	(Ljava/lang/Object;)Ljava/lang/String;
    //   89: invokevirtual 38	java/lang/String:concat	(Ljava/lang/String;)Ljava/lang/String;
    //   92: astore 4
    //   94: new 19	java/lang/StringBuffer
    //   97: dup
    //   98: invokespecial 43	java/lang/StringBuffer:<init>	()V
    //   101: aload 4
    //   103: invokevirtual 44	java/lang/StringBuffer:append	(Ljava/lang/String;)Ljava/lang/StringBuffer;
    //   106: getstatic 20	an:oz	[Ljava/lang/String;
    //   109: getstatic 26	ea:q	[I
    //   112: iconst_1
    //   113: iaload
    //   114: aaload
    //   115: invokevirtual 44	java/lang/StringBuffer:append	(Ljava/lang/String;)Ljava/lang/StringBuffer;
    //   118: ldc 3
    //   120: invokevirtual 44	java/lang/StringBuffer:append	(Ljava/lang/String;)Ljava/lang/StringBuffer;
    //   123: aload_3
    //   124: getstatic 26	ea:q	[I
    //   127: iconst_2
    //   128: iaload
    //   129: aaload
    //   130: invokestatic 28	cl:a	(Ljava/lang/String;)Ljava/lang/String;
    //   133: invokevirtual 44	java/lang/StringBuffer:append	(Ljava/lang/String;)Ljava/lang/StringBuffer;
    //   136: ldc 3
    //   138: invokevirtual 44	java/lang/StringBuffer:append	(Ljava/lang/String;)Ljava/lang/StringBuffer;
    //   141: getstatic 20	an:oz	[Ljava/lang/String;
    //   144: getstatic 26	ea:q	[I
    //   147: iconst_0
    //   148: iaload
    //   149: aaload
    //   150: invokevirtual 44	java/lang/StringBuffer:append	(Ljava/lang/String;)Ljava/lang/StringBuffer;
    //   153: ldc 3
    //   155: invokevirtual 44	java/lang/StringBuffer:append	(Ljava/lang/String;)Ljava/lang/StringBuffer;
    //   158: aload_3
    //   159: getstatic 26	ea:q	[I
    //   162: iconst_3
    //   163: iaload
    //   164: aaload
    //   165: invokevirtual 44	java/lang/StringBuffer:append	(Ljava/lang/String;)Ljava/lang/StringBuffer;
    //   168: invokevirtual 45	java/lang/StringBuffer:toString	()Ljava/lang/String;
    //   171: astore 4
    //   173: ldc 1
    //   175: invokevirtual 40	java/lang/String:length	()I
    //   178: pop
    //   179: ldc 5
    //   181: invokevirtual 40	java/lang/String:length	()I
    //   184: ldc 3
    //   186: invokevirtual 40	java/lang/String:length	()I
    //   189: if_icmpge +632 -> 821
    //   192: return
    //   193: iload 5
    //   195: getstatic 26	ea:q	[I
    //   198: iconst_1
    //   199: iaload
    //   200: invokestatic 33	ea:a	(II)Z
    //   203: ifeq +110 -> 313
    //   206: ldc 8
    //   208: aload 4
    //   210: invokestatic 42	java/lang/String:valueOf	(Ljava/lang/Object;)Ljava/lang/String;
    //   213: invokevirtual 38	java/lang/String:concat	(Ljava/lang/String;)Ljava/lang/String;
    //   216: astore 4
    //   218: new 19	java/lang/StringBuffer
    //   221: dup
    //   222: invokespecial 43	java/lang/StringBuffer:<init>	()V
    //   225: aload 4
    //   227: invokevirtual 44	java/lang/StringBuffer:append	(Ljava/lang/String;)Ljava/lang/StringBuffer;
    //   230: ldc 3
    //   232: invokevirtual 44	java/lang/StringBuffer:append	(Ljava/lang/String;)Ljava/lang/StringBuffer;
    //   235: getstatic 20	an:oz	[Ljava/lang/String;
    //   238: getstatic 26	ea:q	[I
    //   241: iconst_2
    //   242: iaload
    //   243: aaload
    //   244: invokevirtual 44	java/lang/StringBuffer:append	(Ljava/lang/String;)Ljava/lang/StringBuffer;
    //   247: ldc 3
    //   249: invokevirtual 44	java/lang/StringBuffer:append	(Ljava/lang/String;)Ljava/lang/StringBuffer;
    //   252: aload_3
    //   253: getstatic 26	ea:q	[I
    //   256: iconst_2
    //   257: iaload
    //   258: aaload
    //   259: invokestatic 28	cl:a	(Ljava/lang/String;)Ljava/lang/String;
    //   262: invokevirtual 44	java/lang/StringBuffer:append	(Ljava/lang/String;)Ljava/lang/StringBuffer;
    //   265: ldc 3
    //   267: invokevirtual 44	java/lang/StringBuffer:append	(Ljava/lang/String;)Ljava/lang/StringBuffer;
    //   270: getstatic 20	an:oz	[Ljava/lang/String;
    //   273: getstatic 26	ea:q	[I
    //   276: iconst_0
    //   277: iaload
    //   278: aaload
    //   279: invokevirtual 44	java/lang/StringBuffer:append	(Ljava/lang/String;)Ljava/lang/StringBuffer;
    //   282: ldc 3
    //   284: invokevirtual 44	java/lang/StringBuffer:append	(Ljava/lang/String;)Ljava/lang/StringBuffer;
    //   287: aload_3
    //   288: getstatic 26	ea:q	[I
    //   291: iconst_3
    //   292: iaload
    //   293: aaload
    //   294: invokevirtual 44	java/lang/StringBuffer:append	(Ljava/lang/String;)Ljava/lang/StringBuffer;
    //   297: invokevirtual 45	java/lang/StringBuffer:toString	()Ljava/lang/String;
    //   300: astore 4
    //   302: ldc 1
    //   304: invokevirtual 40	java/lang/String:length	()I
    //   307: pop
    //   308: aconst_null
    //   309: ifnull +512 -> 821
    //   312: return
    //   313: iload 5
    //   315: getstatic 26	ea:q	[I
    //   318: iconst_2
    //   319: iaload
    //   320: invokestatic 33	ea:a	(II)Z
    //   323: ifeq +114 -> 437
    //   326: ldc 9
    //   328: aload 4
    //   330: invokestatic 42	java/lang/String:valueOf	(Ljava/lang/Object;)Ljava/lang/String;
    //   333: invokevirtual 38	java/lang/String:concat	(Ljava/lang/String;)Ljava/lang/String;
    //   336: astore 4
    //   338: new 19	java/lang/StringBuffer
    //   341: dup
    //   342: invokespecial 43	java/lang/StringBuffer:<init>	()V
    //   345: aload 4
    //   347: invokevirtual 44	java/lang/StringBuffer:append	(Ljava/lang/String;)Ljava/lang/StringBuffer;
    //   350: ldc 3
    //   352: invokevirtual 44	java/lang/StringBuffer:append	(Ljava/lang/String;)Ljava/lang/StringBuffer;
    //   355: getstatic 20	an:oz	[Ljava/lang/String;
    //   358: getstatic 26	ea:q	[I
    //   361: iconst_3
    //   362: iaload
    //   363: aaload
    //   364: invokevirtual 44	java/lang/StringBuffer:append	(Ljava/lang/String;)Ljava/lang/StringBuffer;
    //   367: ldc 3
    //   369: invokevirtual 44	java/lang/StringBuffer:append	(Ljava/lang/String;)Ljava/lang/StringBuffer;
    //   372: aload_3
    //   373: getstatic 26	ea:q	[I
    //   376: iconst_2
    //   377: iaload
    //   378: aaload
    //   379: invokestatic 28	cl:a	(Ljava/lang/String;)Ljava/lang/String;
    //   382: invokevirtual 44	java/lang/StringBuffer:append	(Ljava/lang/String;)Ljava/lang/StringBuffer;
    //   385: ldc 3
    //   387: invokevirtual 44	java/lang/StringBuffer:append	(Ljava/lang/String;)Ljava/lang/StringBuffer;
    //   390: getstatic 20	an:oz	[Ljava/lang/String;
    //   393: getstatic 26	ea:q	[I
    //   396: iconst_0
    //   397: iaload
    //   398: aaload
    //   399: invokevirtual 44	java/lang/StringBuffer:append	(Ljava/lang/String;)Ljava/lang/StringBuffer;
    //   402: ldc 3
    //   404: invokevirtual 44	java/lang/StringBuffer:append	(Ljava/lang/String;)Ljava/lang/StringBuffer;
    //   407: aload_3
    //   408: getstatic 26	ea:q	[I
    //   411: iconst_3
    //   412: iaload
    //   413: aaload
    //   414: invokevirtual 44	java/lang/StringBuffer:append	(Ljava/lang/String;)Ljava/lang/StringBuffer;
    //   417: invokevirtual 45	java/lang/StringBuffer:toString	()Ljava/lang/String;
    //   420: astore 4
    //   422: ldc 1
    //   424: invokevirtual 40	java/lang/String:length	()I
    //   427: pop
    //   428: ldc 3
    //   430: invokevirtual 40	java/lang/String:length	()I
    //   433: ifgt +388 -> 821
    //   436: return
    //   437: iload 5
    //   439: getstatic 26	ea:q	[I
    //   442: iconst_3
    //   443: iaload
    //   444: invokestatic 33	ea:a	(II)Z
    //   447: ifeq +127 -> 574
    //   450: ldc 8
    //   452: aload 4
    //   454: invokestatic 42	java/lang/String:valueOf	(Ljava/lang/Object;)Ljava/lang/String;
    //   457: invokevirtual 38	java/lang/String:concat	(Ljava/lang/String;)Ljava/lang/String;
    //   460: astore 4
    //   462: new 19	java/lang/StringBuffer
    //   465: dup
    //   466: invokespecial 43	java/lang/StringBuffer:<init>	()V
    //   469: aload 4
    //   471: invokevirtual 44	java/lang/StringBuffer:append	(Ljava/lang/String;)Ljava/lang/StringBuffer;
    //   474: ldc 3
    //   476: invokevirtual 44	java/lang/StringBuffer:append	(Ljava/lang/String;)Ljava/lang/StringBuffer;
    //   479: getstatic 20	an:oz	[Ljava/lang/String;
    //   482: getstatic 26	ea:q	[I
    //   485: iconst_4
    //   486: iaload
    //   487: aaload
    //   488: invokevirtual 44	java/lang/StringBuffer:append	(Ljava/lang/String;)Ljava/lang/StringBuffer;
    //   491: ldc 3
    //   493: invokevirtual 44	java/lang/StringBuffer:append	(Ljava/lang/String;)Ljava/lang/StringBuffer;
    //   496: aload_3
    //   497: getstatic 26	ea:q	[I
    //   500: iconst_2
    //   501: iaload
    //   502: aaload
    //   503: invokestatic 28	cl:a	(Ljava/lang/String;)Ljava/lang/String;
    //   506: invokevirtual 44	java/lang/StringBuffer:append	(Ljava/lang/String;)Ljava/lang/StringBuffer;
    //   509: ldc 3
    //   511: invokevirtual 44	java/lang/StringBuffer:append	(Ljava/lang/String;)Ljava/lang/StringBuffer;
    //   514: getstatic 20	an:oz	[Ljava/lang/String;
    //   517: getstatic 26	ea:q	[I
    //   520: iconst_0
    //   521: iaload
    //   522: aaload
    //   523: invokevirtual 44	java/lang/StringBuffer:append	(Ljava/lang/String;)Ljava/lang/StringBuffer;
    //   526: ldc 3
    //   528: invokevirtual 44	java/lang/StringBuffer:append	(Ljava/lang/String;)Ljava/lang/StringBuffer;
    //   531: aload_3
    //   532: getstatic 26	ea:q	[I
    //   535: iconst_3
    //   536: iaload
    //   537: aaload
    //   538: invokevirtual 44	java/lang/StringBuffer:append	(Ljava/lang/String;)Ljava/lang/StringBuffer;
    //   541: invokevirtual 45	java/lang/StringBuffer:toString	()Ljava/lang/String;
    //   544: astore 4
    //   546: ldc 1
    //   548: invokevirtual 40	java/lang/String:length	()I
    //   551: pop
    //   552: ldc 3
    //   554: invokevirtual 40	java/lang/String:length	()I
    //   557: bipush 99
    //   559: bipush 73
    //   561: ixor
    //   562: sipush 137
    //   565: sipush 167
    //   568: ixor
    //   569: ixor
    //   570: if_icmple +251 -> 821
    //   573: return
    //   574: iload 5
    //   576: getstatic 26	ea:q	[I
    //   579: iconst_4
    //   580: iaload
    //   581: invokestatic 33	ea:a	(II)Z
    //   584: ifeq +127 -> 711
    //   587: ldc 8
    //   589: aload 4
    //   591: invokestatic 42	java/lang/String:valueOf	(Ljava/lang/Object;)Ljava/lang/String;
    //   594: invokevirtual 38	java/lang/String:concat	(Ljava/lang/String;)Ljava/lang/String;
    //   597: astore 4
    //   599: new 19	java/lang/StringBuffer
    //   602: dup
    //   603: invokespecial 43	java/lang/StringBuffer:<init>	()V
    //   606: aload 4
    //   608: invokevirtual 44	java/lang/StringBuffer:append	(Ljava/lang/String;)Ljava/lang/StringBuffer;
    //   611: getstatic 20	an:oz	[Ljava/lang/String;
    //   614: getstatic 26	ea:q	[I
    //   617: iconst_5
    //   618: iaload
    //   619: aaload
    //   620: invokevirtual 44	java/lang/StringBuffer:append	(Ljava/lang/String;)Ljava/lang/StringBuffer;
    //   623: ldc 3
    //   625: invokevirtual 44	java/lang/StringBuffer:append	(Ljava/lang/String;)Ljava/lang/StringBuffer;
    //   628: aload_3
    //   629: getstatic 26	ea:q	[I
    //   632: iconst_2
    //   633: iaload
    //   634: aaload
    //   635: invokestatic 28	cl:a	(Ljava/lang/String;)Ljava/lang/String;
    //   638: invokevirtual 44	java/lang/StringBuffer:append	(Ljava/lang/String;)Ljava/lang/StringBuffer;
    //   641: ldc 3
    //   643: invokevirtual 44	java/lang/StringBuffer:append	(Ljava/lang/String;)Ljava/lang/StringBuffer;
    //   646: getstatic 20	an:oz	[Ljava/lang/String;
    //   649: getstatic 26	ea:q	[I
    //   652: iconst_0
    //   653: iaload
    //   654: aaload
    //   655: invokevirtual 44	java/lang/StringBuffer:append	(Ljava/lang/String;)Ljava/lang/StringBuffer;
    //   658: ldc 3
    //   660: invokevirtual 44	java/lang/StringBuffer:append	(Ljava/lang/String;)Ljava/lang/StringBuffer;
    //   663: aload_3
    //   664: getstatic 26	ea:q	[I
    //   667: iconst_3
    //   668: iaload
    //   669: aaload
    //   670: invokevirtual 44	java/lang/StringBuffer:append	(Ljava/lang/String;)Ljava/lang/StringBuffer;
    //   673: invokevirtual 45	java/lang/StringBuffer:toString	()Ljava/lang/String;
    //   676: astore 4
    //   678: ldc 1
    //   680: invokevirtual 40	java/lang/String:length	()I
    //   683: pop
    //   684: ldc 4
    //   686: invokevirtual 40	java/lang/String:length	()I
    //   689: ldc 5
    //   691: invokevirtual 40	java/lang/String:length	()I
    //   694: ldc 5
    //   696: invokevirtual 40	java/lang/String:length	()I
    //   699: ldc 3
    //   701: invokevirtual 40	java/lang/String:length	()I
    //   704: ineg
    //   705: ixor
    //   706: iand
    //   707: if_icmpgt +114 -> 821
    //   710: return
    //   711: iload 5
    //   713: getstatic 26	ea:q	[I
    //   716: iconst_5
    //   717: iaload
    //   718: invokestatic 33	ea:a	(II)Z
    //   721: ifeq +100 -> 821
    //   724: ldc 9
    //   726: aload 4
    //   728: invokestatic 42	java/lang/String:valueOf	(Ljava/lang/Object;)Ljava/lang/String;
    //   731: invokevirtual 38	java/lang/String:concat	(Ljava/lang/String;)Ljava/lang/String;
    //   734: astore 4
    //   736: new 19	java/lang/StringBuffer
    //   739: dup
    //   740: invokespecial 43	java/lang/StringBuffer:<init>	()V
    //   743: aload 4
    //   745: invokevirtual 44	java/lang/StringBuffer:append	(Ljava/lang/String;)Ljava/lang/StringBuffer;
    //   748: ldc 3
    //   750: invokevirtual 44	java/lang/StringBuffer:append	(Ljava/lang/String;)Ljava/lang/StringBuffer;
    //   753: getstatic 20	an:oz	[Ljava/lang/String;
    //   756: getstatic 26	ea:q	[I
    //   759: bipush 6
    //   761: iaload
    //   762: aaload
    //   763: invokevirtual 44	java/lang/StringBuffer:append	(Ljava/lang/String;)Ljava/lang/StringBuffer;
    //   766: ldc 3
    //   768: invokevirtual 44	java/lang/StringBuffer:append	(Ljava/lang/String;)Ljava/lang/StringBuffer;
    //   771: aload_3
    //   772: getstatic 26	ea:q	[I
    //   775: iconst_2
    //   776: iaload
    //   777: aaload
    //   778: invokestatic 28	cl:a	(Ljava/lang/String;)Ljava/lang/String;
    //   781: invokevirtual 44	java/lang/StringBuffer:append	(Ljava/lang/String;)Ljava/lang/StringBuffer;
    //   784: ldc 3
    //   786: invokevirtual 44	java/lang/StringBuffer:append	(Ljava/lang/String;)Ljava/lang/StringBuffer;
    //   789: getstatic 20	an:oz	[Ljava/lang/String;
    //   792: getstatic 26	ea:q	[I
    //   795: iconst_0
    //   796: iaload
    //   797: aaload
    //   798: invokevirtual 44	java/lang/StringBuffer:append	(Ljava/lang/String;)Ljava/lang/StringBuffer;
    //   801: ldc 3
    //   803: invokevirtual 44	java/lang/StringBuffer:append	(Ljava/lang/String;)Ljava/lang/StringBuffer;
    //   806: aload_3
    //   807: getstatic 26	ea:q	[I
    //   810: iconst_3
    //   811: iaload
    //   812: aaload
    //   813: invokevirtual 44	java/lang/StringBuffer:append	(Ljava/lang/String;)Ljava/lang/StringBuffer;
    //   816: invokevirtual 45	java/lang/StringBuffer:toString	()Ljava/lang/String;
    //   819: astore 4
    //   821: aload_0
    //   822: new 19	java/lang/StringBuffer
    //   825: dup
    //   826: invokespecial 43	java/lang/StringBuffer:<init>	()V
    //   829: aload_0
    //   830: getfield 22	ea:g	Ljava/lang/String;
    //   833: invokevirtual 44	java/lang/StringBuffer:append	(Ljava/lang/String;)Ljava/lang/StringBuffer;
    //   836: aload 4
    //   838: invokevirtual 44	java/lang/StringBuffer:append	(Ljava/lang/String;)Ljava/lang/StringBuffer;
    //   841: ldc 2
    //   843: invokevirtual 44	java/lang/StringBuffer:append	(Ljava/lang/String;)Ljava/lang/StringBuffer;
    //   846: invokevirtual 45	java/lang/StringBuffer:toString	()Ljava/lang/String;
    //   849: putfield 22	ea:g	Ljava/lang/String;
    //   852: ldc 1
    //   854: invokevirtual 40	java/lang/String:length	()I
    //   857: pop
    //   858: ldc 5
    //   860: invokevirtual 40	java/lang/String:length	()I
    //   863: ifge +10 -> 873
    //   866: return
    //   867: ldc 1
    //   869: invokevirtual 40	java/lang/String:length	()I
    //   872: pop2
    //   873: iinc 2 1
    //   876: ldc 1
    //   878: invokevirtual 40	java/lang/String:length	()I
    //   881: pop
    //   882: ldc 3
    //   884: invokevirtual 40	java/lang/String:length	()I
    //   887: sipush 135
    //   890: sipush 131
    //   893: ixor
    //   894: if_icmpne -875 -> 19
    //   897: return
    //   898: return
    //   899: ldc 1
    //   901: invokevirtual 40	java/lang/String:length	()I
    //   904: pop2
    //   905: return
    // Local variable table:
    //   start	length	slot	name	signature
    //   0	906	0	this	ea
    //   0	906	1	paramString	String
    //   18	856	2	i1	int
    //   35	772	3	localObject	Object
    //   61	776	4	str	String
    //   74	638	5	i2	int
    //   867	1	6	localException1	Exception
    //   899	1	7	localException2	Exception
    // Exception table:
    //   from	to	target	type
    //   47	852	867	java/lang/Exception
    //   13	898	899	java/lang/Exception
  }
  
  private static boolean a(int paramInt)
  {
    return paramInt == 0;
  }
  
  public ea()
  {
    new ci();
  }
  
  private static void c()
  {
    q = new int[7];
    q[0] = ((0x8A ^ 0xA4) & (0x84 ^ 0xAA ^ 0xFFFFFFFF));
    q[1] = " ".length();
    q[2] = "  ".length();
    q[3] = "   ".length();
    q[4] = (0x4A ^ 0x6B ^ 0x35 ^ 0x10);
    q[5] = (31 + 63 - 72 + 121 ^ 114 + 121 - 148 + 51);
    q[6] = (0x7D ^ 0x7B);
  }
  
  public static void b() {}
}


/* Location:              C:\Users\Admin\OneDrive\Documents\NSOv2_test.jar!\ea.class
 * Java compiler version: 1 (45.3)
 * JD-Core Version:       0.7.1
 */