public final class ec
{
  public int a;
  private static int[] d;
  private int e;
  private static int[] f;
  public int b;
  private static int[] g;
  private an h = null;
  private int i;
  private int j;
  public int c = f[0];
  private int k;
  private int l;
  private int m;
  private static byte[] n;
  private dt o;
  
  private static boolean a(int paramInt1, int paramInt2)
  {
    return paramInt1 <= paramInt2;
  }
  
  private static boolean a(int paramInt)
  {
    return paramInt != 0;
  }
  
  private static boolean b(int paramInt1, int paramInt2)
  {
    return paramInt1 < paramInt2;
  }
  
  private static boolean c(int paramInt1, int paramInt2)
  {
    return paramInt1 != paramInt2;
  }
  
  private static boolean b(int paramInt)
  {
    return paramInt > 0;
  }
  
  private static boolean a(Object paramObject)
  {
    return paramObject != null;
  }
  
  private static boolean d(int paramInt1, int paramInt2)
  {
    return paramInt1 >= paramInt2;
  }
  
  private static void d()
  {
    f = new int[45];
    f[0] = ((0x14 ^ 0x2 ^ 0x8C ^ 0xA1) & (0xDF ^ 0xAE ^ 0xD0 ^ 0x9A ^ -" ".length()));
    f[1] = (79 + 77 - 65 + 42 ^ 110 + 57 - 138 + 100);
    f[2] = (0x31 ^ 0x64 ^ 0x6 ^ 0x6F);
    f[3] = "   ".length();
    f[4] = (0x4B ^ 0x55);
    f[5] = "  ".length();
    f[6] = (36 + 116 - -25 + 18 ^ 13 + '' - 27 + 64);
    f[7] = (-(0x5C ^ 0x59));
    f[8] = (0xA4 ^ 0xAB);
    f[9] = " ".length();
    f[10] = (0x3 ^ 0x13);
    f[11] = (0x38 ^ 0x5B ^ 0xC9 ^ 0xB3);
    f[12] = ("  ".length() ^ 0x2F ^ 0x2B);
    f[13] = (0xDB ^ 0xBC ^ 0xA6 ^ 0xC6);
    f[14] = (0x66 ^ 0x6E);
    f[15] = (87 + 91 - 89 + 94 ^ 51 + 93 - -24 + 22);
    f[16] = (0x31 ^ 0x3B);
    f[17] = (0x15 ^ 0x1E);
    f[18] = (68 + 'ª' - 122 + 61 ^ 73 + 20 - 59 + 155);
    f[19] = (0x1F ^ 0x12);
    f[20] = (0x59 ^ 0x57);
    f[21] = (0x5A ^ 0x6 ^ 0x6E ^ 0x23);
    f[22] = (0x24 ^ 0xB ^ 0x64 ^ 0x59);
    f[23] = (0xAE ^ 0x9D ^ 0xAC ^ 0x8C);
    f[24] = (0xFC ^ 0xA9 ^ 0x4C ^ 0xD);
    f[25] = (0x5F ^ 0x4A);
    f[26] = ('' + 57 - 69 + 14 ^ 90 + 57 - 118 + 130);
    f[27] = (0x53 ^ 0x44);
    f[28] = (86 + 41 - 51 + 53 ^ 10 + 89 - 39 + 93);
    f[29] = (0xBC ^ 0x99);
    f[30] = (0x42 ^ 0xE ^ 0x6 ^ 0x7E);
    f[31] = (0xE7 ^ 0xAC);
    f[32] = (0x3D ^ 0x54);
    f[33] = (93 + 33 - 35 + 36);
    f[34] = (102 + 19 - 44 + 65);
    f[35] = ("   ".length() + (0x87 ^ 0x9A) - (0x1 ^ 0xB) + (33 + 97 - -10 + 3));
    f[36] = ((0xF1 ^ 0x87) + ('' + 75 - 182 + 117) - ('°' + 8 - -3 + 19) + (82 + 60 - 89 + 85));
    f[37] = (82 + 71 - -20 + 44);
    f[38] = ((0xB4 ^ 0xAF) + ('Å' + 'À' - 202 + 26) - ('' + '' - 221 + 113) + (118 + 79 - 140 + 101));
    f[39] = ("   ".length() + (97 + 'Ç' - 228 + 136) - ('' + 30 - 105 + 98) + (99 + 78 - 154 + 200));
    f[40] = (0xB91D & 0x47FF);
    f[41] = (-(0xBEEB & 0x7D1D) & 0xBF3F & 0x7DFB);
    f[42] = (-(0xDEFA & 0x29AF) & 0xABEF & 0x5DFB);
    f[43] = (-(0xFAAD & 0x57F7) & 0xD7FD & 0x7BFF);
    f[44] = (-(0xFFFFFFEE & 0x769F) & 0xF7FF & 0x7FFF);
  }
  
  private static boolean c(int paramInt)
  {
    return paramInt < 0;
  }
  
  /* Error */
  public final void a(cf paramcf)
  {
    // Byte code:
    //   0: aload_0
    //   1: getfield 39	ec:l	I
    //   4: aload_0
    //   5: getfield 29	ec:b	I
    //   8: isub
    //   9: istore_2
    //   10: aload_0
    //   11: getfield 38	ec:k	I
    //   14: aload_0
    //   15: getfield 28	ec:a	I
    //   18: isub
    //   19: istore_3
    //   20: iload_2
    //   21: iload_3
    //   22: ineg
    //   23: invokestatic 43	bc:a	(II)I
    //   26: istore_2
    //   27: getstatic 33	ec:f	[I
    //   30: iconst_0
    //   31: iaload
    //   32: istore_3
    //   33: iload_3
    //   34: getstatic 34	ec:g	[I
    //   37: arraylength
    //   38: getstatic 33	ec:f	[I
    //   41: bipush 9
    //   43: iaload
    //   44: isub
    //   45: invokestatic 58	ec:d	(II)Z
    //   48: ifeq +24 -> 72
    //   51: getstatic 33	ec:f	[I
    //   54: iconst_0
    //   55: iaload
    //   56: istore_2
    //   57: ldc 1
    //   59: invokevirtual 61	java/lang/String:length	()I
    //   62: pop
    //   63: ldc 3
    //   65: invokevirtual 61	java/lang/String:length	()I
    //   68: ifge +111 -> 179
    //   71: return
    //   72: iload_2
    //   73: getstatic 34	ec:g	[I
    //   76: iload_3
    //   77: iaload
    //   78: invokestatic 58	ec:d	(II)Z
    //   81: ifeq +79 -> 160
    //   84: iload_2
    //   85: getstatic 34	ec:g	[I
    //   88: iload_3
    //   89: getstatic 33	ec:f	[I
    //   92: bipush 9
    //   94: iaload
    //   95: iadd
    //   96: iaload
    //   97: invokestatic 50	ec:a	(II)Z
    //   100: ifeq +60 -> 160
    //   103: iload_3
    //   104: getstatic 33	ec:f	[I
    //   107: bipush 10
    //   109: iaload
    //   110: invokestatic 58	ec:d	(II)Z
    //   113: ifeq +24 -> 137
    //   116: getstatic 33	ec:f	[I
    //   119: iconst_0
    //   120: iaload
    //   121: ldc 1
    //   123: invokevirtual 61	java/lang/String:length	()I
    //   126: pop
    //   127: ldc 4
    //   129: invokevirtual 61	java/lang/String:length	()I
    //   132: ineg
    //   133: iflt +5 -> 138
    //   136: return
    //   137: iload_3
    //   138: istore_2
    //   139: ldc 1
    //   141: invokevirtual 61	java/lang/String:length	()I
    //   144: pop
    //   145: ldc 3
    //   147: invokevirtual 61	java/lang/String:length	()I
    //   150: ldc 2
    //   152: invokevirtual 61	java/lang/String:length	()I
    //   155: ineg
    //   156: if_icmpgt +23 -> 179
    //   159: return
    //   160: iinc 3 1
    //   163: ldc 1
    //   165: invokevirtual 61	java/lang/String:length	()I
    //   168: pop
    //   169: ldc 2
    //   171: invokevirtual 61	java/lang/String:length	()I
    //   174: ineg
    //   175: iflt -142 -> 33
    //   178: return
    //   179: aload_1
    //   180: aload_0
    //   181: getfield 35	ec:h	Lan;
    //   184: getfield 15	an:la	[I
    //   187: getstatic 41	ec:n	[B
    //   190: iload_2
    //   191: baload
    //   192: iaload
    //   193: aload_0
    //   194: getfield 29	ec:b	I
    //   197: aload_0
    //   198: getfield 28	ec:a	I
    //   201: getstatic 31	ec:d	[I
    //   204: iload_2
    //   205: iaload
    //   206: getstatic 33	ec:f	[I
    //   209: iconst_3
    //   210: iaload
    //   211: invokestatic 45	dq:a	(Lcf;IIIII)V
    //   214: return
    //   215: ldc 1
    //   217: invokevirtual 61	java/lang/String:length	()I
    //   220: pop2
    //   221: return
    // Local variable table:
    //   start	length	slot	name	signature
    //   0	222	0	this	ec
    //   0	222	1	paramcf	cf
    //   9	196	2	i1	int
    //   19	142	3	i2	int
    //   215	1	4	localException	Exception
    // Exception table:
    //   from	to	target	type
    //   179	214	215	java/lang/Exception
  }
  
  public static void a()
  {
    d();
    n = new byte[] { f[0], f[9], f[5], f[9], f[0], f[9], f[5], f[9], f[0], f[9], f[5], f[9], f[0], f[9], f[5], f[9], f[0], f[9], f[5], f[9], f[0], f[9], f[5], f[9], f[0] };
    g = new int[] { f[0], f[8], f[29], f[30], f[31], f[32], f[33], f[34], f[35], f[36], f[37], f[38], f[39], f[40], f[41], f[42], f[43], f[44] };
    d = new int[] { f[0], f[0], f[0], f[13], f[12], f[12], f[12], f[5], f[5], f[3], f[3], f[1], f[6], f[6], f[6], f[9] };
  }
  
  static
  {
    cs.a(0);
    a();
  }
  
  private static boolean b(Object paramObject)
  {
    return paramObject == null;
  }
  
  public ec(dt paramdt, an paraman)
  {
    this.o = paramdt;
    this.h = paraman;
  }
  
  private static boolean e(int paramInt1, int paramInt2)
  {
    return paramInt1 > paramInt2;
  }
  
  public final void b()
  {
    if ((!b(this.o.ab)) || (a(this.o.cs)))
    {
      if (a(this.o.ab))
      {
        this.l = this.o.ab.u;
        this.k = (this.o.ab.l - this.o.ab.k / f[1]);
        "".length();
        if (((0xEA ^ 0xBF) & (0x5E ^ 0xB ^ 0xFFFFFFFF)) == 0) {}
      }
      else if (a(this.o.cs))
      {
        this.l = this.o.cs.eg;
        this.k = (this.o.cs.ey - this.o.cs.fp / f[1]);
      }
      int i1 = this.l - this.b;
      int i2 = this.k - this.a;
      int i3 = f[1];
      if (b(i1 + i2, f[2]))
      {
        i3 = f[3];
        "".length();
        if (((0xE7 ^ 0xAE) & (0x8 ^ 0x41 ^ 0xFFFFFFFF)) <= (0x9B ^ 0x9F)) {}
      }
      else if (b(i1 + i2, f[4]))
      {
        i3 = f[5];
      }
      if (c(this.b, this.l)) {
        if ((b(i1)) && (b(i1, f[6])))
        {
          this.b = this.l;
          "".length();
          if (((0x2B ^ 0x68) & (0x49 ^ 0xA ^ 0xFFFFFFFF)) <= 0) {}
        }
        else if ((c(i1)) && (e(i1, f[7])))
        {
          this.b = this.l;
          "".length();
          if ((0xA1 ^ 0xA5) > ((0x6B ^ 0x23) & (0xF7 ^ 0xBF ^ 0xFFFFFFFF))) {}
        }
        else
        {
          this.j = (this.l - this.b << f[5]);
          this.i += this.j;
          this.b += (this.i >> i3);
          this.i &= f[8];
        }
      }
      if (c(this.a, this.k)) {
        if ((b(i2)) && (b(i2, f[6])))
        {
          this.a = this.k;
          "".length();
          if (-" ".length() != ((0x37 ^ 0x31) & (0x6A ^ 0x6C ^ 0xFFFFFFFF))) {}
        }
        else if ((c(i2)) && (e(i2, f[7])))
        {
          this.a = this.k;
          "".length();
          if (((0x48 ^ 0x61) & (0xAD ^ 0x84 ^ 0xFFFFFFFF)) <= 0) {}
        }
        else
        {
          this.m = (this.k - this.a << f[5]);
          this.e += this.m;
          this.a += (this.e >> i3);
          this.e &= f[8];
        }
      }
      i1 = f[0];
      i2 = f[0];
      i3 = f[0];
      int i4 = f[0];
      if (a(this.o.ab))
      {
        i1 = this.l - this.o.ab.ac / f[1];
        i3 = this.l + this.o.ab.ac / f[1];
        i2 = this.k - this.o.ab.k / f[1];
        i4 = this.k + this.o.ab.k / f[1];
        "".length();
        if (-" ".length() != " ".length()) {}
      }
      else if (a(this.o.cs))
      {
        i1 = this.l - this.o.cs.bj / f[1];
        i3 = this.l + this.o.cs.bj / f[1];
        i2 = this.k - this.o.cs.fp / f[1];
        i4 = this.k + this.o.cs.fp / f[1];
      }
      if (b(this.c)) {
        this.c -= f[9];
      }
      if ((a(this.c)) && ((!d(this.b, i1)) || (!a(this.b, i3)) || (!d(this.a, i2)) || (e(this.a, i4)))) {
        return;
      }
    }
    this.o.bl = null;
    this.b = (this.a = this.l = this.k = this.j = this.m = this.i = this.e = f[0]);
    this.o.c();
    if (a(this.o.ez)) {
      this.o.w();
    }
  }
  
  public static void c() {}
}


/* Location:              C:\Users\Admin\OneDrive\Documents\NSOv2_test.jar!\ec.class
 * Java compiler version: 1 (45.3)
 * JD-Core Version:       0.7.1
 */