import java.io.ByteArrayInputStream;
import java.io.DataInputStream;
import java.io.IOException;
import java.io.InputStream;
import java.io.PrintStream;
import java.util.Vector;
import javax.microedition.lcdui.Image;

public final class et
{
  public static boolean a;
  public static byte b;
  private static int ah;
  public static String c;
  private static Image ai;
  public static int d;
  public static byte e;
  private static Image[] aj;
  private static short[] ak;
  private static byte[][] al;
  private static int[] am;
  public static byte f;
  private static int an;
  private static int ao;
  private static int ap;
  private static Image aq;
  public static ex g;
  public static int h;
  public static int i;
  public static int j;
  private static Image ar;
  public static int k;
  private static Image as;
  private static boolean[] at;
  private static int au;
  private static int av;
  public static int l;
  public static short[][] m;
  private static int[] aw;
  private static Image ax;
  public static int n;
  public static short o;
  private static int ay;
  public static int[] p;
  public static int q;
  public static ex r;
  public static int s;
  public static ci t;
  public static byte u;
  public static int v;
  private static Image[] az;
  public static boolean w;
  public static int x;
  private static Object ba;
  private static int bb;
  public static String y;
  public static Image z;
  private static int bc;
  public static short aa;
  public static int ab;
  private static int[] bd;
  public static int ac;
  private static int be;
  private static int bf;
  private static Image bg;
  public static int ad;
  public static int ae;
  public static char[] af;
  private static Image bh;
  public static String[] ag;
  
  private static boolean f(int paramInt1, int paramInt2)
  {
    return paramInt1 == paramInt2;
  }
  
  public static void a()
  {
    bg = null;
    System.gc();
  }
  
  public static final void a(cf paramcf)
  {
    if (t(aw.ag))
    {
      int i1 = fn.ec;
      int i2;
      while (h(i1, fn.ea))
      {
        i2 = fn.o;
        while (h(i2, fn.dr))
        {
          Image localImage;
          if (f(d, am[3]))
          {
            localImage = ar;
            "".length();
            if (" ".length() <= (0xAE ^ 0xAA)) {}
          }
          else
          {
            localImage = aq;
          }
          if (f(j(i1, i2) & am[58], am[58])) {
            paramcf.a(bh, i1, i2, am[2]);
          }
          if (f(j(i1, i2) & am[24], am[24])) {
            paramcf.a(localImage, am[2], (aw.ap % am[20] >> am[1]) * am[108], am[108], am[108], am[2], i1 * u, i2 * u, am[2]);
          }
          if (f(j(i1, i2) & am[61], am[61])) {
            paramcf.a(bg, am[2], (af[(i2 * ae + i1)] - am[5]) * u, am[108], am[108], am[2], i1 * u, i2 * u, am[2]);
          }
          i2++;
          "".length();
          if (((0xE6 ^ 0xB0) & (0x1B ^ 0x4D ^ 0xFFFFFFFF)) != 0) {
            return;
          }
        }
        i1++;
        "".length();
        if (" ".length() < 0) {
          return;
        }
      }
      if ((l(d, am[3])) && (q(aw.s)) && (q(aw.m)) && (k(fn.dr, ad - am[1])))
      {
        i1 = fn.ec;
        while (h(i1, fn.ea))
        {
          i2 = ad - am[1];
          int i3 = af[(i2 * ae + i1)] - am[5];
          int i4;
          if (f(j(i1, i2) & am[53], am[53]))
          {
            i4 = am[5];
            do
            {
              if (!g(i4, am[3])) {
                break;
              }
              paramcf.a(as, am[2], am[108] * (aw.ap % am[3]), am[108], am[108], am[2], i1 * u, (i2 + i4) * u, am[2]);
              i4++;
              "".length();
            } while (null == null);
            return;
          }
          if (f(o, am[24])) {
            av = am[81];
          }
          if ((!l(j(i1, i2) & am[1], am[1])) || (f(j(i1, i2) & am[24], am[24]))) {
            i3 = av;
          }
          if (s(i3))
          {
            i4 = am[5];
            while (g(i4, am[3]))
            {
              paramcf.a(bg, am[2], i3 * u, am[108], am[108], am[2], i1 * u, (i2 + i4) * u, am[2]);
              i4++;
              "".length();
              if ("  ".length() < " ".length()) {
                return;
              }
            }
          }
          i1++;
          "".length();
          if (-(0xBC ^ 0xB8) >= 0) {}
        }
      }
    }
  }
  
  /* Error */
  public static final boolean a(int paramInt1, int paramInt2, int paramInt3)
  {
    // Byte code:
    //   0: getstatic 186	et:p	[I
    //   3: iload_1
    //   4: getstatic 190	et:u	B
    //   7: idiv
    //   8: getstatic 148	et:ae	I
    //   11: imul
    //   12: iload_0
    //   13: getstatic 190	et:u	B
    //   16: idiv
    //   17: iadd
    //   18: iaload
    //   19: iload_2
    //   20: iand
    //   21: iload_2
    //   22: invokestatic 254	et:f	(II)Z
    //   25: ifeq +9 -> 34
    //   28: getstatic 155	et:am	[I
    //   31: iconst_5
    //   32: iaload
    //   33: ireturn
    //   34: getstatic 155	et:am	[I
    //   37: iconst_2
    //   38: iaload
    //   39: ireturn
    //   40: ldc 24
    //   42: invokevirtual 291	java/lang/String:length	()I
    //   45: pop2
    //   46: getstatic 155	et:am	[I
    //   49: iconst_2
    //   50: iaload
    //   51: ireturn
    // Local variable table:
    //   start	length	slot	name	signature
    //   0	52	0	paramInt1	int
    //   0	52	1	paramInt2	int
    //   0	52	2	paramInt3	int
    //   40	1	3	localException	Exception
    // Exception table:
    //   from	to	target	type
    //   0	39	40	java/lang/Exception
  }
  
  public static int a(int paramInt1, int paramInt2)
  {
    paramInt2 = k(paramInt2);
    if (t(a(paramInt1, paramInt2, am[1])))
    {
      int i1 = am[2];
      while (h(i1, am[28]))
      {
        int i2;
        if ((r(i2 = paramInt2 - am[''] + i1 * am[108])) && (h(i2, h)) && (q(a(paramInt1, i2, am[1])))) {
          return i2;
        }
        i1++;
        "".length();
        if (null != null) {
          return (0x23 ^ 0x4 ^ 0xA2 ^ 0x90) & (0xD5 ^ 0xA1 ^ 0xD6 ^ 0xB7 ^ -" ".length());
        }
      }
    }
    return paramInt2;
  }
  
  private static boolean p(int paramInt)
  {
    return paramInt < 0;
  }
  
  public static int a(int paramInt)
  {
    if (q(f(paramInt))) {
      switch (paramInt)
      {
      case 92: 
        return am[32];
      case 93: 
        return am[33];
      case 94: 
      case 98: 
      case 99: 
      case 100: 
      case 101: 
      case 102: 
      case 103: 
      case 104: 
      case 105: 
      case 110: 
      case 111: 
      case 112: 
      case 113: 
      case 114: 
      case 117: 
      case 118: 
      case 119: 
      case 120: 
      case 121: 
      case 122: 
      case 123: 
      case 124: 
      case 125: 
      case 129: 
      case 130: 
      case 131: 
      case 132: 
      case 133: 
      case 134: 
      case 135: 
      case 136: 
      case 137: 
      case 138: 
      case 139: 
      case 140: 
      case 141: 
      case 142: 
      case 143: 
      case 144: 
      case 145: 
      case 146: 
      case 147: 
      case 148: 
      case 149: 
      case 150: 
      case 151: 
      case 152: 
      case 153: 
      case 154: 
      case 155: 
      case 156: 
      case 157: 
      default: 
        "".length();
        if (" ".length() == "   ".length()) {
          return (0xE1 ^ 0xBF ^ 0xA8 ^ 0xBB) & (1 + 84 - -31 + 102 ^ 26 + 78 - 39 + 86 ^ -" ".length());
        }
        break;
      case 95: 
        return am[35];
      case 96: 
        return am[109];
      case 97: 
        return am[111];
      case 106: 
        return am[115];
      case 107: 
        return am[98];
      case 108: 
        return am[99];
      case 109: 
        return am[69];
      case 115: 
        return am[80];
      case 116: 
        return am[81];
      case 126: 
        return am[74];
      case 127: 
        return am[75];
      case 128: 
        return am[76];
      case 158: 
        return am[''];
      case 159: 
        return am[''];
      }
    }
    return am[126];
  }
  
  public static void b()
  {
    an = dt.g().eg / am[0];
    be = dt.g().ey / am[0];
    if (i(an, ae * v - l / am[1]))
    {
      an = ae * v - l;
      "".length();
      if ((0xA7 ^ 0x9F ^ 0x14 ^ 0x28) >= 0) {}
    }
    else if (h(an, l / am[1]))
    {
      an = am[2];
      "".length();
      if ((0x3E ^ 0x35 ^ 0x7E ^ 0x71) == (70 + '' - 62 + 24 ^ '' + 4 - 122 + 152)) {}
    }
    else
    {
      an -= l / am[1];
    }
    if (h(be, q / am[1]))
    {
      be = am[2];
      "".length();
      if (((83 + '½' - 253 + 222 ^ 79 + 2 - -87 + 12) & (0xC ^ 0x2E ^ 0xF ^ 0x68 ^ -" ".length())) < " ".length()) {}
    }
    else
    {
      be -= q / am[1];
    }
    if (i(be, ad * v - q)) {
      be = ad * v - q;
    }
  }
  
  public static void b(int paramInt)
  {
    try
    {
      int i1 = (paramInt = (bh)t.elementAt(paramInt)).b;
      int i2 = paramInt.c;
      if ((q(paramInt.c)) && (h(paramInt.d, h - am[108])))
      {
        if (g(paramInt.a, ab / am[1]))
        {
          i1 = paramInt.a + am[0];
          i2 = paramInt.d;
          "".length();
          if (null == null) {}
        }
        else if (k(paramInt.b, ab / am[1]))
        {
          i1 = paramInt.b - am[0];
          i2 = paramInt.d;
          "".length();
          if ("  ".length() < (0x4 ^ 0x0)) {}
        }
      }
      else if (g(paramInt.d, h / am[1]))
      {
        i1 = (paramInt.a + paramInt.b) / am[1];
        i2 = paramInt.d + am[108];
        "".length();
        if (((0xD0 ^ 0x99) & (0x34 ^ 0x7D ^ 0xFFFFFFFF)) == 0) {}
      }
      else if (k(paramInt.c, h / am[1]))
      {
        i1 = (paramInt.a + paramInt.b) / am[1] + am[108];
        i2 = paramInt.d - am[''];
      }
      if ((l(o, am[80])) && (l(o, am[81])) && (l(o, am[40])))
      {
        "".length();
        "".length();
        if (((0x29 ^ 0x2D ^ 0x4A ^ 0x5B) & (0xC8 ^ 0xC4 ^ 0x6 ^ 0x1F ^ -" ".length())) <= 0) {}
      }
      else
      {
        dt.c(i1, i2);
      }
      Thread.sleep(10L);
      dl.ae().x();
      return;
    }
    catch (InterruptedException localInterruptedException)
    {
      (paramInt = localInterruptedException).printStackTrace();
    }
  }
  
  private static boolean g(int paramInt1, int paramInt2)
  {
    return paramInt1 <= paramInt2;
  }
  
  public static final void b(int paramInt1, int paramInt2)
  {
    int[] arrayOfInt = p;
    paramInt1 = paramInt2 / u * ae + paramInt1 / u;
    arrayOfInt[paramInt1] &= am[''];
  }
  
  static final void c()
  {
    if (a(bh)) {
      bh = aw.c("/t/uwt.png");
    }
    if (a(as)) {
      as = aw.c("/t/wtf.png");
    }
    if (a(ax)) {
      ax = aw.c("/t/twtf.png");
    }
    if (a(aq)) {
      aq = aw.c("/t/wts.png");
    }
    if (a(ar)) {
      ar = aw.c("/t/wts1.png");
    }
    System.gc();
  }
  
  /* Error */
  public static void d()
  {
    // Byte code:
    //   0: getstatic 155	et:am	[I
    //   3: iconst_5
    //   4: iaload
    //   5: putstatic 144	et:a	Z
    //   8: getstatic 170	et:ba	Ljava/lang/Object;
    //   11: ldc 24
    //   13: invokevirtual 291	java/lang/String:length	()I
    //   16: pop2
    //   17: getstatic 170	et:ba	Ljava/lang/Object;
    //   20: dup
    //   21: astore_0
    //   22: monitorenter
    //   23: getstatic 170	et:ba	Ljava/lang/Object;
    //   26: ldc2_w 101
    //   29: invokevirtual 289	java/lang/Object:wait	(J)V
    //   32: ldc 24
    //   34: invokevirtual 291	java/lang/String:length	()I
    //   37: pop
    //   38: aconst_null
    //   39: ifnull +10 -> 49
    //   42: return
    //   43: ldc 24
    //   45: invokevirtual 291	java/lang/String:length	()I
    //   48: pop2
    //   49: aload_0
    //   50: monitorexit
    //   51: return
    //   52: astore_1
    //   53: aload_0
    //   54: monitorexit
    //   55: aload_1
    //   56: athrow
    // Local variable table:
    //   start	length	slot	name	signature
    //   21	33	0	Ljava/lang/Object;	Object
    //   52	4	1	localObject1	Object
    //   43	1	2	localInterruptedException	InterruptedException
    // Exception table:
    //   from	to	target	type
    //   23	32	43	java/lang/InterruptedException
    //   23	51	52	finally
  }
  
  public static void e()
  {
    try
    {
      localObject = new ByteArrayInputStream(al[o]);
      ae = (char)(localObject = new DataInputStream((InputStream)localObject)).readUnsignedByte();
      ad = (char)((DataInputStream)localObject).readUnsignedByte();
      af = new char[((DataInputStream)localObject).available()];
      int i1 = am[2];
      while (h(i1, ae * ad))
      {
        af[i1] = ((char)((DataInputStream)localObject).readUnsignedByte());
        i1++;
        "".length();
        if (-(0x5 ^ 0x59 ^ 0x64 ^ 0x3D) >= 0) {
          return;
        }
      }
      p = new int[af.length];
      return;
    }
    catch (IOException localIOException)
    {
      Object localObject;
      (localObject = localIOException).printStackTrace();
    }
  }
  
  public static final int c(int paramInt)
  {
    return paramInt / u * u;
  }
  
  public static boolean d(int paramInt)
  {
    if ((k(paramInt, am[''])) && (g(paramInt, am['']))) {
      return am[5];
    }
    return am[2];
  }
  
  public static void a(int paramInt1, int paramInt2, int paramInt3, int paramInt4)
  {
    l = paramInt3;
    q = paramInt4;
    ac = paramInt1;
    i = paramInt2;
  }
  
  private static boolean h(int paramInt1, int paramInt2)
  {
    return paramInt1 < paramInt2;
  }
  
  private static void m()
  {
    am = new int['Ð'];
    am[0] = (27 + 119 - 63 + 48 ^ 116 + 90 - 133 + 70);
    am[1] = "  ".length();
    am[2] = ((0xEE ^ 0xC1) & (0x51 ^ 0x7E ^ 0xFFFFFFFF));
    am[3] = (0x23 ^ 0x27);
    am[4] = (0xB6 ^ 0xB9);
    am[5] = " ".length();
    am[6] = "   ".length();
    am[7] = (0x99 ^ 0xB4 ^ 0x4A ^ 0x62);
    am[8] = (46 + '' - 118 + 110 ^ '' + 97 - 96 + 40);
    am[9] = (0xAC ^ 0x9E ^ 0x13 ^ 0x28);
    am[10] = (49 + 66 - 111 + 152 ^ 53 + 59 - 45 + 83);
    am[11] = (24 + 111 - -77 + 5 ^ 116 + 103 - 131 + 62);
    am[12] = ('' + '´' - 152 + 74 ^ '' + 70 - 192 + 156);
    am[13] = (0x37 ^ 0x57 ^ 0xFD ^ 0x90);
    am[14] = (0x42 ^ 0x4C);
    am[15] = (0x9 ^ 0x5 ^ 0x63 ^ 0x44);
    am[16] = ('¦' + 55 - 121 + 84 ^ 23 + 104 - 61 + 82);
    am[17] = (0x23 ^ 0xE);
    am[18] = (44 + 119 - 71 + 62 ^ 49 + '' - 140 + 124);
    am[19] = (0x1C ^ 0x17);
    am[20] = (0x29 ^ 0x21);
    am[21] = (-(0xFFFFFFBB & 0x1F7) & 0xAFF2 & 0x55BF);
    am[22] = (0xF8 ^ 0xB4);
    am[23] = (0xC6 ^ 0x8B);
    am[24] = (0xDA ^ 0xB6 ^ 0x5 ^ 0x29);
    am[25] = (0x64 ^ 0x9 ^ 0x71 ^ 0x52);
    am[26] = (-(0xFFFFFFAF & 0x7FB) & 0xDFEF & 0x37BA);
    am[27] = (115 + '©' - 175 + 68 ^ 25 + '' - 66 + 65);
    am[28] = (0x53 ^ 0x54);
    am[29] = (0x3 ^ 0x27);
    am[30] = (0x4F ^ 0x3B ^ 0xE6 ^ 0xB7);
    am[31] = (0x17 ^ 0x21);
    am[32] = (0x62 ^ 0x39);
    am[33] = (0x1 ^ 0x5D);
    am[34] = (0xCF ^ 0x92);
    am[35] = (0xFF ^ 0x8A ^ 0x24 ^ 0xF);
    am[36] = (0x3F ^ 0x76);
    am[37] = (0x8D ^ 0xA3 ^ 0xE3 ^ 0x87);
    am[38] = (0xFA ^ 0x9B);
    am[39] = ('¯' + '»' - 276 + 150 ^ 21 + '' - 70 + 57);
    am[40] = (0x29 ^ 0x5D);
    am[41] = ('¶' + 106 - 159 + 106 ^ 21 + '' - 99 + 108);
    am[42] = (0xFB ^ 0x8D);
    am[43] = (0xD9 ^ 0xA1);
    am[44] = (0x8 ^ 0x4D ^ 0xE2 ^ 0x9A);
    am[45] = (0x71 ^ 0x65);
    am[46] = (127 + 22 - 70 + 78 ^ 37 + '' - 126 + 93);
    am[47] = (0x24 ^ 0x33);
    am[48] = (0x73 ^ 0x55);
    am[49] = (80 + 96 - 126 + 105 ^ 101 + 14 - 37 + 110);
    am[50] = (0xDA ^ 0xC4);
    am[51] = (46 + 39 - 56 + 122 ^ 17 + 15 - -56 + 47);
    am[52] = (0x44 ^ 0x55);
    am[53] = (0x62 ^ 0x42);
    am[54] = (0x49 ^ 0x5B);
    am[55] = ((0x1A ^ 0x1C) + (0xDC ^ 0xBB) - (0xAA ^ 0xC6) + (48 + 20 - 46 + 105));
    am[56] = (0xC6 ^ 0x9A ^ 0xEA ^ 0xA5);
    am[57] = (20 + 46 - 26 + 87 ^ 0xD0 ^ 0x8C);
    am[58] = (-(20 + 121 - 3 + 1) & 0xEBCF & 0x1CBA);
    am[59] = (0x90 ^ 0xB1);
    am[60] = (0xA3 ^ 0x88 ^ 0x8 ^ 0x1);
    am[61] = (-(0xEC1F & 0x17FD) & 0xDF5E & 0x25BD);
    am[62] = (0xA ^ 0x74 ^ 0x2F ^ 0x36);
    am[63] = (0xDF ^ 0xB0);
    am[64] = (0x91 ^ 0xC3);
    am[65] = (0x6F ^ 0x3C);
    am[66] = (0x3F ^ 0x5C);
    am[67] = (0x2C ^ 0x48);
    am[68] = (0xCB ^ 0x9A ^ 0xBA ^ 0x8D);
    am[69] = (48 + 110 - 5 + 19 ^ '' + 88 - 215 + 170);
    am[70] = (0x11 ^ 0x7C);
    am[71] = (0x48 ^ 0x45 ^ 0xFF ^ 0x9C);
    am[72] = (0x22 ^ 0x52);
    am[73] = (0x89 ^ 0x90 ^ 0x53 ^ 0x3B);
    am[74] = (0xF ^ 0x6A ^ 0x7E ^ 0x66);
    am[75] = (60 + 110 - 1 + 35 ^ '' + 100 - 124 + 68);
    am[76] = ((0xE7 ^ 0xB7) + (0xC5 ^ 0x84) - (0x2A ^ 0x5E) + (0x75 ^ 0x17));
    am[77] = (124 + 78 - 124 + 51);
    am[78] = ((0x26 ^ 0x7B) + (0x59 ^ 0x5C) - -(0x81 ^ 0x97) + (0xA7 ^ 0xAD));
    am[79] = (0x2D ^ 0x39 ^ 0x93 ^ 0xB0);
    am[80] = (0x55 ^ 0x7D ^ 0x29 ^ 0x73);
    am[81] = (0xB9 ^ 0x99 ^ 0x59 ^ 0xA);
    am[82] = (11 + 17 - 22 + 129);
    am[83] = (116 + 124 - 185 + 76);
    am[84] = ("  ".length() + (0x3 ^ 0x5E) - -(0x38 ^ 0x37) + (0x63 ^ 0x75));
    am[85] = ((0xBC ^ 0xBA) + (0x2A ^ 0x3) - -(0x5F ^ 0x18) + (0x43 ^ 0x53));
    am[86] = (0xE0AF & 0x3F50);
    am[87] = (0x10 ^ 0x2C ^ 0x73 ^ 0x7C);
    am[88] = (0x60 ^ 0x55 ^ 0x28 ^ 0x45);
    am[89] = (0x2F ^ 0x62 ^ 0x0 ^ 0x72);
    am[90] = (0x5 ^ 0x19 ^ 0x6D ^ 0x30);
    am[91] = (43 + 54 - -2 + 28 ^ 0x9C ^ 0xA0);
    am[92] = (0x13 ^ 0x57);
    am[93] = (0x14 ^ 0x2D ^ 0x53 ^ 0x2D);
    am[94] = (0xC2 ^ 0xB0 ^ 0xBE ^ 0x84);
    am[95] = (93 + 'ñ' - 173 + 93 ^ 36 + '¢' - 180 + 152);
    am[96] = (0xC6 ^ 0xAE ^ 0x65 ^ 0x58);
    am[97] = ('' + 'Õ' - 259 + 121 ^ 67 + '»' - 135 + 72);
    am[98] = ("  ".length() ^ 0x5F ^ 0x37);
    am[99] = (0xFD ^ 0x96);
    am[100] = (0xDD ^ 0xAA);
    am[101] = ('' + 41 - 170 + 131);
    am[102] = (122 + 121 - 227 + 120);
    am[103] = ((0x78 ^ 0x3B) + (0x9 ^ 0x31) - (0x69 ^ 0x59) + (0x81 ^ 0xBE));
    am[104] = (10 + 72 - 38 + 95);
    am[105] = ((0x26 ^ 0x37) + (0x93 ^ 0x8A) - -(0xA3 ^ 0xC2) + "   ".length());
    am[106] = (0xFA ^ 0x87 ^ " ".length());
    am[107] = (84 + 2 - 49 + 216 ^ 7 + 109 - 53 + 71);
    am[108] = (0xC9 ^ 0x95 ^ 0x3F ^ 0x7B);
    am[109] = ('½' + '¥' - 323 + 162 ^ 29 + 0 - -110 + 19);
    am[110] = ((0x2E ^ 0x3B) + (0xC5 ^ 0x90) - -(0x87 ^ 0x9A) + (0x2A ^ 0x2F));
    am[111] = (0x74 ^ 0x29 ^ 0x68 ^ 0x55);
    am[112] = (74 + '' - 113 + 51);
    am[113] = (0x9D ^ 0x84);
    am[114] = (0xEB ^ 0x83);
    am[115] = (0x32 ^ 0x15 ^ 0xE ^ 0x40);
    am[116] = (0x54 ^ 0x4E);
    am[117] = (21 + 122 - 96 + 96);
    am[118] = (0xC0D5 & 0x7F2A);
    am[119] = (0xC1DA & 0x13E25);
    am[120] = (0xCA03 & 0xB5FC);
    am[121] = (0xD1 ^ 0xB8 ^ 0x45 ^ 0x4);
    am[122] = (0x6D ^ 0x44);
    am[123] = (0x9689 & 0x26976);
    am[124] = (-(0xE3EE & 0x5E11) & 0xD3FF & 0x46DFF);
    am[125] = (0xE243 & 0x81DBC);
    am[126] = (-" ".length());
    am[127] = (0x14 ^ 0xF);
    am[''] = (109 + 16 - 72 + 92 ^ 121 + 67 - 135 + 115);
    am[''] = (125 + 79 - 66 + 113 ^ 26 + 101 - 81 + 147);
    am[''] = (36 + 95 - 43 + 41 ^ 81 + '' - 180 + 153);
    am[''] = (0x0 ^ 0x6E ^ 0x69 ^ 0x41);
    am[''] = (40 + 92 - -40 + 67 ^ 31 + 50 - -44 + 39);
    am[''] = (0xE8 ^ 0xA5 ^ 0x83 ^ 0x9F);
    am[''] = (0x6E ^ 0x40);
    am[''] = (0x69 ^ 0x59);
    am[''] = (91 + 94 - 154 + 111 ^ 83 + 49 - -33 + 17);
    am[''] = (0x25 ^ 0x28 ^ 0x30 ^ 0x3);
    am[''] = ((0x36 ^ 0x31) + (0x76 ^ 0x6) - (0xA2 ^ 0x9D) + (0x52 ^ 0xC));
    am[''] = (2 + 89 - -22 + 87);
    am[''] = ('' + 20 - 3 + 31 ^ '' + 101 - 153 + 53);
    am[''] = (0x99FA & 0x67FD);
    am[''] = (0xA6C4 & 0x5B3B);
    am[''] = ((0x44 ^ 0x52) + "   ".length() - -(0xCA ^ 0x96) + (0x22 ^ 0x19));
    am[''] = (-"  ".length());
    am[''] = (0xFFFFFFFF & 0xFFFFFF);
    am[''] = (4 + 22 - -41 + 88 + (0xC2 ^ 0xBF) - ('' + 6 - 79 + 109) + ('' + '' - 158 + 49));
    am[''] = (0x9DFF & 0xFF62FF);
    am[''] = (-" ".length() & 0xFFFFFFFF & 0xFFFF);
    am[''] = (-(0xEFEF & 0x1FF5) & 0xEFEE & 0xFF1FF5);
    am[''] = (-(0x71 ^ 0x32) & 0xFF63 & 0xFFDE);
    am[''] = (-(0xFDB7 & 0x7E59) & 0xFFFFFFFA & 0x7FFD);
    am[''] = (-(-(0xFFFFFFF9 & 0x54FF) & 0xDFF9 & 0x76FF));
    am[''] = (0x8BFD & 0x76BE);
    am[''] = (0x4E ^ 0x53);
    am[''] = ((0x6A ^ 0x4F) + (0xFD ^ 0xB0) - -(0xA7 ^ 0x85) + (0x4 ^ 0xA));
    am[''] = (66 + '' - 136 + 92);
    am[''] = ((0xB4 ^ 0x84) + (0x47 ^ 0x42) - -(0xEC ^ 0x8D) + (0x7 ^ 0x0));
    am[''] = ((0x57 ^ 0x4F) + (23 + 125 - 89 + 75) - (0x5C ^ 0xA) + (0x50 ^ 0x6));
    am[''] = (9 + 60 - -26 + 64);
    am[' '] = (0xD454 & 0x7002BAB);
    am['¡'] = (-(0xD9BE & 0x7E4D) & 0xFDBB & 0xF05A4F);
    am['¢'] = (-(0xBF65 & 0x70BF) & 0xBCBC & 0x5007367);
    am['£'] = (-(0xFCC7 & 0x3BF9) & 0xFBFE & 0x203CC1);
    am['¤'] = (0xFE57 & 0x80001A8);
    am['¥'] = (0xB335 & 0x19004CCA);
    am['¦'] = (-(0xF6D3 & 0x59FD) & 0xD0F0 & 0x37FDF);
    am['§'] = (-(0xB0BF & 0x7FF9) & 0xBFBB & 0x1070FC);
    am['¨'] = (0x8714 & 0x578EB);
    am['©'] = (-(0xED73 & 0x3FFD) & 0xBD7A & 0x66FF5);
    am['ª'] = (0xB9 ^ 0xA0 ^ 0xC4 ^ 0xC1);
    am['«'] = (0xE3EA & 0x1DFF);
    am['¬'] = ((0xE ^ 0x30) + (0x31 ^ 0x74) - (0x1B ^ 0x26) + (0x5C ^ 0x3C));
    am['­'] = ((0x4D ^ 0x37) + (0x46 ^ 0xD) - (127 + 1 - 103 + 115) + (0x65 ^ 0xD));
    am['®'] = (0xBBE9 & 0x4757);
    am['¯'] = (-(0xD95A & 0x3FF7) & 0xDD7B & 0x7BD7);
    am['°'] = (97 + 12 - -30 + 101);
    am['±'] = (0xFFFFFF8B & 0x503A7E);
    am['²'] = (-(0xBDEE & 0x5E33) & 0xFF3F & 0x867FF9);
    am['³'] = (0xC0 ^ 0x85);
    am['´'] = (0xAD ^ 0x8C ^ 0x1E ^ 0x4);
    am['µ'] = (109 + '' - 86 + 8 ^ 123 + 115 - 196 + 86);
    am['¶'] = (113 + 118 - 166 + 70 ^ 32 + '' - 64 + 98);
    am['·'] = (0x6A ^ 0xC ^ 0xD ^ 0x41);
    am['¸'] = (0x98 ^ 0xAD);
    am['¹'] = (0x5A ^ 0x75);
    am['º'] = (0x82 ^ 0xB3);
    am['»'] = (0x4B ^ 0x1 ^ 0x4E ^ 0x52);
    am['¼'] = (0x4C ^ 0x15);
    am['½'] = (0x53 ^ 0x9);
    am['¾'] = (0x37 ^ 0x39 ^ 0x68 ^ 0x3);
    am['¿'] = (0xDF ^ 0x80 ^ 0xE ^ 0x28);
    am['À'] = (0x1E ^ 0x64);
    am['Á'] = (23 + 101 - 73 + 86);
    am['Â'] = (59 + '' - 83 + 36);
    am['Ã'] = (23 + 13 - -12 + 97);
    am['Ä'] = ((0x46 ^ 0x4A) + (0xD6 ^ 0xC0) - " ".length() + (0x69 ^ 0x18));
    am['Å'] = (72 + 18 - -27 + 30);
    am['Æ'] = ((0x98 ^ 0x9E) + (0x6B ^ 0x4A) - -(0x8C ^ 0xB1) + (0x58 ^ 0x68));
    am['Ç'] = ((0x1A ^ 0x6F) + (0x32 ^ 0x5C) - ('' + 100 - 191 + 121) + (0x29 ^ 0x4E));
    am['È'] = ((0x6C ^ 0x4F) + (0x6E ^ 0x78) - (0x9E ^ 0xAF) + (11 + 49 - 2 + 85));
    am['É'] = (103 + 14 - 39 + 60 + (0x29 ^ 0x9) - (0x8 ^ 0x57) + (0xB ^ 0x46));
    am['Ê'] = (1 + 101 - -24 + 27);
    am['Ë'] = ('' + 18 - 55 + 53 + (101 + 33 - 123 + 126) - (0x9B37 & 0x65DD) + (82 + 12 - 36 + 89));
    am['Ì'] = ((0xF9 ^ 0x8D) + (0x7A ^ 0x7F) - -(0xB0 ^ 0xA7) + (0x85 ^ 0x8E));
    am['Í'] = (14 + 18 - -86 + 38);
    am['Î'] = (54 + 110 - 107 + 88 + (0x1E ^ 0x7D) - (107 + 10 - 83 + 93) + (0xA9 ^ 0x87));
    am['Ï'] = (18 + '£' - 137 + 120);
  }
  
  /* Error */
  public static void f()
  {
    // Byte code:
    //   0: invokestatic 264	et:m	()V
    //   3: getstatic 155	et:am	[I
    //   6: bipush 108
    //   8: iaload
    //   9: putstatic 190	et:u	B
    //   12: aconst_null
    //   13: putstatic 178	et:c	Ljava/lang/String;
    //   16: ldc 24
    //   18: putstatic 194	et:y	Ljava/lang/String;
    //   21: new 61	ci
    //   24: dup
    //   25: invokespecial 227	ci:<init>	()V
    //   28: putstatic 189	et:t	Lci;
    //   31: new 72	ex
    //   34: dup
    //   35: invokespecial 271	ex:<init>	()V
    //   38: putstatic 188	et:r	Lex;
    //   41: new 72	ex
    //   44: dup
    //   45: invokespecial 271	ex:<init>	()V
    //   48: putstatic 180	et:g	Lex;
    //   51: getstatic 155	et:am	[I
    //   54: iconst_1
    //   55: iaload
    //   56: putstatic 191	et:v	I
    //   59: getstatic 155	et:am	[I
    //   62: iconst_1
    //   63: iaload
    //   64: newarray <illegal type>
    //   66: dup
    //   67: getstatic 155	et:am	[I
    //   70: iconst_2
    //   71: iaload
    //   72: getstatic 155	et:am	[I
    //   75: sipush 177
    //   78: iaload
    //   79: iastore
    //   80: dup
    //   81: getstatic 155	et:am	[I
    //   84: iconst_5
    //   85: iaload
    //   86: getstatic 155	et:am	[I
    //   89: sipush 178
    //   92: iaload
    //   93: iastore
    //   94: putstatic 165	et:aw	[I
    //   97: getstatic 155	et:am	[I
    //   100: sipush 172
    //   103: iaload
    //   104: anewarray 47	[S
    //   107: putstatic 184	et:m	[[S
    //   110: getstatic 155	et:am	[I
    //   113: sipush 172
    //   116: iaload
    //   117: newarray <illegal type>
    //   119: putstatic 162	et:at	[Z
    //   122: getstatic 155	et:am	[I
    //   125: sipush 172
    //   128: iaload
    //   129: newarray <illegal type>
    //   131: putstatic 173	et:bd	[I
    //   134: getstatic 155	et:am	[I
    //   137: sipush 172
    //   140: iaload
    //   141: newarray <illegal type>
    //   143: putstatic 153	et:ak	[S
    //   146: getstatic 184	et:m	[[S
    //   149: getstatic 155	et:am	[I
    //   152: iconst_2
    //   153: iaload
    //   154: getstatic 155	et:am	[I
    //   157: iconst_5
    //   158: iaload
    //   159: newarray <illegal type>
    //   161: dup
    //   162: getstatic 155	et:am	[I
    //   165: iconst_2
    //   166: iaload
    //   167: getstatic 155	et:am	[I
    //   170: bipush 127
    //   172: iaload
    //   173: sastore
    //   174: aastore
    //   175: getstatic 184	et:m	[[S
    //   178: getstatic 155	et:am	[I
    //   181: iconst_5
    //   182: iaload
    //   183: getstatic 155	et:am	[I
    //   186: bipush 13
    //   188: iaload
    //   189: newarray <illegal type>
    //   191: dup
    //   192: getstatic 155	et:am	[I
    //   195: iconst_2
    //   196: iaload
    //   197: getstatic 155	et:am	[I
    //   200: iconst_1
    //   201: iaload
    //   202: sastore
    //   203: dup
    //   204: getstatic 155	et:am	[I
    //   207: iconst_5
    //   208: iaload
    //   209: getstatic 155	et:am	[I
    //   212: bipush 6
    //   214: iaload
    //   215: sastore
    //   216: dup
    //   217: getstatic 155	et:am	[I
    //   220: iconst_1
    //   221: iaload
    //   222: getstatic 155	et:am	[I
    //   225: bipush 127
    //   227: iaload
    //   228: sastore
    //   229: dup
    //   230: getstatic 155	et:am	[I
    //   233: bipush 6
    //   235: iaload
    //   236: getstatic 155	et:am	[I
    //   239: bipush 94
    //   241: iaload
    //   242: sastore
    //   243: dup
    //   244: getstatic 155	et:am	[I
    //   247: iconst_3
    //   248: iaload
    //   249: getstatic 155	et:am	[I
    //   252: bipush 32
    //   254: iaload
    //   255: sastore
    //   256: dup
    //   257: getstatic 155	et:am	[I
    //   260: bipush 7
    //   262: iaload
    //   263: getstatic 155	et:am	[I
    //   266: bipush 35
    //   268: iaload
    //   269: sastore
    //   270: dup
    //   271: getstatic 155	et:am	[I
    //   274: bipush 8
    //   276: iaload
    //   277: getstatic 155	et:am	[I
    //   280: bipush 115
    //   282: iaload
    //   283: sastore
    //   284: dup
    //   285: getstatic 155	et:am	[I
    //   288: bipush 28
    //   290: iaload
    //   291: getstatic 155	et:am	[I
    //   294: bipush 80
    //   296: iaload
    //   297: sastore
    //   298: dup
    //   299: getstatic 155	et:am	[I
    //   302: bipush 20
    //   304: iaload
    //   305: getstatic 155	et:am	[I
    //   308: bipush 74
    //   310: iaload
    //   311: sastore
    //   312: dup
    //   313: getstatic 155	et:am	[I
    //   316: bipush 9
    //   318: iaload
    //   319: getstatic 155	et:am	[I
    //   322: sipush 157
    //   325: iaload
    //   326: sastore
    //   327: dup
    //   328: getstatic 155	et:am	[I
    //   331: bipush 10
    //   333: iaload
    //   334: getstatic 155	et:am	[I
    //   337: bipush 104
    //   339: iaload
    //   340: sastore
    //   341: dup
    //   342: getstatic 155	et:am	[I
    //   345: bipush 19
    //   347: iaload
    //   348: getstatic 155	et:am	[I
    //   351: bipush 73
    //   353: iaload
    //   354: sastore
    //   355: dup
    //   356: getstatic 155	et:am	[I
    //   359: iconst_0
    //   360: iaload
    //   361: getstatic 155	et:am	[I
    //   364: bipush 12
    //   366: iaload
    //   367: sastore
    //   368: aastore
    //   369: getstatic 184	et:m	[[S
    //   372: getstatic 155	et:am	[I
    //   375: iconst_1
    //   376: iaload
    //   377: getstatic 155	et:am	[I
    //   380: iconst_1
    //   381: iaload
    //   382: newarray <illegal type>
    //   384: dup
    //   385: getstatic 155	et:am	[I
    //   388: iconst_2
    //   389: iaload
    //   390: getstatic 155	et:am	[I
    //   393: bipush 8
    //   395: iaload
    //   396: sastore
    //   397: dup
    //   398: getstatic 155	et:am	[I
    //   401: iconst_5
    //   402: iaload
    //   403: getstatic 155	et:am	[I
    //   406: iconst_5
    //   407: iaload
    //   408: sastore
    //   409: aastore
    //   410: getstatic 184	et:m	[[S
    //   413: getstatic 155	et:am	[I
    //   416: bipush 6
    //   418: iaload
    //   419: getstatic 155	et:am	[I
    //   422: iconst_1
    //   423: iaload
    //   424: newarray <illegal type>
    //   426: dup
    //   427: getstatic 155	et:am	[I
    //   430: iconst_2
    //   431: iaload
    //   432: getstatic 155	et:am	[I
    //   435: iconst_5
    //   436: iaload
    //   437: sastore
    //   438: dup
    //   439: getstatic 155	et:am	[I
    //   442: iconst_5
    //   443: iaload
    //   444: getstatic 155	et:am	[I
    //   447: iconst_3
    //   448: iaload
    //   449: sastore
    //   450: aastore
    //   451: getstatic 184	et:m	[[S
    //   454: getstatic 155	et:am	[I
    //   457: iconst_3
    //   458: iaload
    //   459: getstatic 155	et:am	[I
    //   462: iconst_1
    //   463: iaload
    //   464: newarray <illegal type>
    //   466: dup
    //   467: getstatic 155	et:am	[I
    //   470: iconst_2
    //   471: iaload
    //   472: getstatic 155	et:am	[I
    //   475: bipush 6
    //   477: iaload
    //   478: sastore
    //   479: dup
    //   480: getstatic 155	et:am	[I
    //   483: iconst_5
    //   484: iaload
    //   485: getstatic 155	et:am	[I
    //   488: bipush 7
    //   490: iaload
    //   491: sastore
    //   492: aastore
    //   493: getstatic 184	et:m	[[S
    //   496: getstatic 155	et:am	[I
    //   499: bipush 7
    //   501: iaload
    //   502: getstatic 155	et:am	[I
    //   505: iconst_1
    //   506: iaload
    //   507: newarray <illegal type>
    //   509: dup
    //   510: getstatic 155	et:am	[I
    //   513: iconst_2
    //   514: iaload
    //   515: getstatic 155	et:am	[I
    //   518: bipush 28
    //   520: iaload
    //   521: sastore
    //   522: dup
    //   523: getstatic 155	et:am	[I
    //   526: iconst_5
    //   527: iaload
    //   528: getstatic 155	et:am	[I
    //   531: iconst_3
    //   532: iaload
    //   533: sastore
    //   534: aastore
    //   535: getstatic 184	et:m	[[S
    //   538: getstatic 155	et:am	[I
    //   541: bipush 8
    //   543: iaload
    //   544: getstatic 155	et:am	[I
    //   547: iconst_3
    //   548: iaload
    //   549: newarray <illegal type>
    //   551: dup
    //   552: getstatic 155	et:am	[I
    //   555: iconst_2
    //   556: iaload
    //   557: getstatic 155	et:am	[I
    //   560: bipush 28
    //   562: iaload
    //   563: sastore
    //   564: dup
    //   565: getstatic 155	et:am	[I
    //   568: iconst_5
    //   569: iaload
    //   570: getstatic 155	et:am	[I
    //   573: iconst_1
    //   574: iaload
    //   575: sastore
    //   576: dup
    //   577: getstatic 155	et:am	[I
    //   580: iconst_1
    //   581: iaload
    //   582: getstatic 155	et:am	[I
    //   585: bipush 45
    //   587: iaload
    //   588: sastore
    //   589: dup
    //   590: getstatic 155	et:am	[I
    //   593: bipush 6
    //   595: iaload
    //   596: getstatic 155	et:am	[I
    //   599: bipush 46
    //   601: iaload
    //   602: sastore
    //   603: aastore
    //   604: getstatic 184	et:m	[[S
    //   607: getstatic 155	et:am	[I
    //   610: bipush 28
    //   612: iaload
    //   613: getstatic 155	et:am	[I
    //   616: bipush 6
    //   618: iaload
    //   619: newarray <illegal type>
    //   621: dup
    //   622: getstatic 155	et:am	[I
    //   625: iconst_2
    //   626: iaload
    //   627: getstatic 155	et:am	[I
    //   630: bipush 8
    //   632: iaload
    //   633: sastore
    //   634: dup
    //   635: getstatic 155	et:am	[I
    //   638: iconst_5
    //   639: iaload
    //   640: getstatic 155	et:am	[I
    //   643: bipush 7
    //   645: iaload
    //   646: sastore
    //   647: dup
    //   648: getstatic 155	et:am	[I
    //   651: iconst_1
    //   652: iaload
    //   653: getstatic 155	et:am	[I
    //   656: bipush 20
    //   658: iaload
    //   659: sastore
    //   660: aastore
    //   661: getstatic 184	et:m	[[S
    //   664: getstatic 155	et:am	[I
    //   667: bipush 20
    //   669: iaload
    //   670: getstatic 155	et:am	[I
    //   673: iconst_1
    //   674: iaload
    //   675: newarray <illegal type>
    //   677: dup
    //   678: getstatic 155	et:am	[I
    //   681: iconst_2
    //   682: iaload
    //   683: getstatic 155	et:am	[I
    //   686: bipush 28
    //   688: iaload
    //   689: sastore
    //   690: dup
    //   691: getstatic 155	et:am	[I
    //   694: iconst_5
    //   695: iaload
    //   696: getstatic 155	et:am	[I
    //   699: bipush 9
    //   701: iaload
    //   702: sastore
    //   703: aastore
    //   704: getstatic 184	et:m	[[S
    //   707: getstatic 155	et:am	[I
    //   710: bipush 9
    //   712: iaload
    //   713: getstatic 155	et:am	[I
    //   716: iconst_1
    //   717: iaload
    //   718: newarray <illegal type>
    //   720: dup
    //   721: getstatic 155	et:am	[I
    //   724: iconst_2
    //   725: iaload
    //   726: getstatic 155	et:am	[I
    //   729: bipush 20
    //   731: iaload
    //   732: sastore
    //   733: dup
    //   734: getstatic 155	et:am	[I
    //   737: iconst_5
    //   738: iaload
    //   739: getstatic 155	et:am	[I
    //   742: bipush 10
    //   744: iaload
    //   745: sastore
    //   746: aastore
    //   747: getstatic 184	et:m	[[S
    //   750: getstatic 155	et:am	[I
    //   753: bipush 10
    //   755: iaload
    //   756: getstatic 155	et:am	[I
    //   759: bipush 9
    //   761: iaload
    //   762: newarray <illegal type>
    //   764: dup
    //   765: getstatic 155	et:am	[I
    //   768: iconst_2
    //   769: iaload
    //   770: getstatic 155	et:am	[I
    //   773: bipush 9
    //   775: iaload
    //   776: sastore
    //   777: dup
    //   778: getstatic 155	et:am	[I
    //   781: iconst_5
    //   782: iaload
    //   783: getstatic 155	et:am	[I
    //   786: bipush 19
    //   788: iaload
    //   789: sastore
    //   790: dup
    //   791: getstatic 155	et:am	[I
    //   794: iconst_1
    //   795: iaload
    //   796: getstatic 155	et:am	[I
    //   799: bipush 52
    //   801: iaload
    //   802: sastore
    //   803: dup
    //   804: getstatic 155	et:am	[I
    //   807: bipush 6
    //   809: iaload
    //   810: getstatic 155	et:am	[I
    //   813: bipush 27
    //   815: iaload
    //   816: sastore
    //   817: dup
    //   818: getstatic 155	et:am	[I
    //   821: iconst_3
    //   822: iaload
    //   823: getstatic 155	et:am	[I
    //   826: bipush 53
    //   828: iaload
    //   829: sastore
    //   830: dup
    //   831: getstatic 155	et:am	[I
    //   834: bipush 7
    //   836: iaload
    //   837: getstatic 155	et:am	[I
    //   840: bipush 48
    //   842: iaload
    //   843: sastore
    //   844: dup
    //   845: getstatic 155	et:am	[I
    //   848: bipush 8
    //   850: iaload
    //   851: getstatic 155	et:am	[I
    //   854: bipush 15
    //   856: iaload
    //   857: sastore
    //   858: dup
    //   859: getstatic 155	et:am	[I
    //   862: bipush 28
    //   864: iaload
    //   865: getstatic 155	et:am	[I
    //   868: sipush 135
    //   871: iaload
    //   872: sastore
    //   873: dup
    //   874: getstatic 155	et:am	[I
    //   877: bipush 20
    //   879: iaload
    //   880: getstatic 155	et:am	[I
    //   883: bipush 104
    //   885: iaload
    //   886: sastore
    //   887: aastore
    //   888: getstatic 184	et:m	[[S
    //   891: getstatic 155	et:am	[I
    //   894: bipush 19
    //   896: iaload
    //   897: getstatic 155	et:am	[I
    //   900: iconst_1
    //   901: iaload
    //   902: newarray <illegal type>
    //   904: dup
    //   905: getstatic 155	et:am	[I
    //   908: iconst_2
    //   909: iaload
    //   910: getstatic 155	et:am	[I
    //   913: iconst_0
    //   914: iaload
    //   915: sastore
    //   916: dup
    //   917: getstatic 155	et:am	[I
    //   920: iconst_5
    //   921: iaload
    //   922: getstatic 155	et:am	[I
    //   925: bipush 10
    //   927: iaload
    //   928: sastore
    //   929: aastore
    //   930: getstatic 184	et:m	[[S
    //   933: getstatic 155	et:am	[I
    //   936: iconst_0
    //   937: iaload
    //   938: getstatic 155	et:am	[I
    //   941: iconst_1
    //   942: iaload
    //   943: newarray <illegal type>
    //   945: dup
    //   946: getstatic 155	et:am	[I
    //   949: iconst_2
    //   950: iaload
    //   951: getstatic 155	et:am	[I
    //   954: bipush 19
    //   956: iaload
    //   957: sastore
    //   958: dup
    //   959: getstatic 155	et:am	[I
    //   962: iconst_5
    //   963: iaload
    //   964: getstatic 155	et:am	[I
    //   967: sipush 128
    //   970: iaload
    //   971: sastore
    //   972: aastore
    //   973: getstatic 184	et:m	[[S
    //   976: getstatic 155	et:am	[I
    //   979: bipush 13
    //   981: iaload
    //   982: getstatic 155	et:am	[I
    //   985: iconst_1
    //   986: iaload
    //   987: newarray <illegal type>
    //   989: dup
    //   990: getstatic 155	et:am	[I
    //   993: iconst_2
    //   994: iaload
    //   995: getstatic 155	et:am	[I
    //   998: sipush 128
    //   1001: iaload
    //   1002: sastore
    //   1003: dup
    //   1004: getstatic 155	et:am	[I
    //   1007: iconst_5
    //   1008: iaload
    //   1009: getstatic 155	et:am	[I
    //   1012: bipush 14
    //   1014: iaload
    //   1015: sastore
    //   1016: aastore
    //   1017: getstatic 184	et:m	[[S
    //   1020: getstatic 155	et:am	[I
    //   1023: bipush 14
    //   1025: iaload
    //   1026: getstatic 155	et:am	[I
    //   1029: iconst_1
    //   1030: iaload
    //   1031: newarray <illegal type>
    //   1033: dup
    //   1034: getstatic 155	et:am	[I
    //   1037: iconst_2
    //   1038: iaload
    //   1039: getstatic 155	et:am	[I
    //   1042: bipush 13
    //   1044: iaload
    //   1045: sastore
    //   1046: dup
    //   1047: getstatic 155	et:am	[I
    //   1050: iconst_5
    //   1051: iaload
    //   1052: getstatic 155	et:am	[I
    //   1055: iconst_4
    //   1056: iaload
    //   1057: sastore
    //   1058: aastore
    //   1059: getstatic 184	et:m	[[S
    //   1062: getstatic 155	et:am	[I
    //   1065: iconst_4
    //   1066: iaload
    //   1067: getstatic 155	et:am	[I
    //   1070: iconst_1
    //   1071: iaload
    //   1072: newarray <illegal type>
    //   1074: dup
    //   1075: getstatic 155	et:am	[I
    //   1078: iconst_2
    //   1079: iaload
    //   1080: getstatic 155	et:am	[I
    //   1083: bipush 14
    //   1085: iaload
    //   1086: sastore
    //   1087: dup
    //   1088: getstatic 155	et:am	[I
    //   1091: iconst_5
    //   1092: iaload
    //   1093: getstatic 155	et:am	[I
    //   1096: bipush 51
    //   1098: iaload
    //   1099: sastore
    //   1100: aastore
    //   1101: getstatic 184	et:m	[[S
    //   1104: getstatic 155	et:am	[I
    //   1107: bipush 51
    //   1109: iaload
    //   1110: getstatic 155	et:am	[I
    //   1113: iconst_1
    //   1114: iaload
    //   1115: newarray <illegal type>
    //   1117: dup
    //   1118: getstatic 155	et:am	[I
    //   1121: iconst_2
    //   1122: iaload
    //   1123: getstatic 155	et:am	[I
    //   1126: iconst_4
    //   1127: iaload
    //   1128: sastore
    //   1129: dup
    //   1130: getstatic 155	et:am	[I
    //   1133: iconst_5
    //   1134: iaload
    //   1135: getstatic 155	et:am	[I
    //   1138: bipush 52
    //   1140: iaload
    //   1141: sastore
    //   1142: aastore
    //   1143: getstatic 184	et:m	[[S
    //   1146: getstatic 155	et:am	[I
    //   1149: bipush 52
    //   1151: iaload
    //   1152: getstatic 155	et:am	[I
    //   1155: bipush 9
    //   1157: iaload
    //   1158: newarray <illegal type>
    //   1160: dup
    //   1161: getstatic 155	et:am	[I
    //   1164: iconst_2
    //   1165: iaload
    //   1166: getstatic 155	et:am	[I
    //   1169: bipush 51
    //   1171: iaload
    //   1172: sastore
    //   1173: dup
    //   1174: getstatic 155	et:am	[I
    //   1177: iconst_5
    //   1178: iaload
    //   1179: getstatic 155	et:am	[I
    //   1182: bipush 54
    //   1184: iaload
    //   1185: sastore
    //   1186: dup
    //   1187: getstatic 155	et:am	[I
    //   1190: iconst_1
    //   1191: iaload
    //   1192: getstatic 155	et:am	[I
    //   1195: bipush 10
    //   1197: iaload
    //   1198: sastore
    //   1199: dup
    //   1200: getstatic 155	et:am	[I
    //   1203: bipush 6
    //   1205: iaload
    //   1206: getstatic 155	et:am	[I
    //   1209: bipush 27
    //   1211: iaload
    //   1212: sastore
    //   1213: dup
    //   1214: getstatic 155	et:am	[I
    //   1217: iconst_3
    //   1218: iaload
    //   1219: getstatic 155	et:am	[I
    //   1222: bipush 53
    //   1224: iaload
    //   1225: sastore
    //   1226: dup
    //   1227: getstatic 155	et:am	[I
    //   1230: bipush 7
    //   1232: iaload
    //   1233: getstatic 155	et:am	[I
    //   1236: bipush 48
    //   1238: iaload
    //   1239: sastore
    //   1240: dup
    //   1241: getstatic 155	et:am	[I
    //   1244: bipush 8
    //   1246: iaload
    //   1247: getstatic 155	et:am	[I
    //   1250: bipush 15
    //   1252: iaload
    //   1253: sastore
    //   1254: dup
    //   1255: getstatic 155	et:am	[I
    //   1258: bipush 28
    //   1260: iaload
    //   1261: getstatic 155	et:am	[I
    //   1264: sipush 135
    //   1267: iaload
    //   1268: sastore
    //   1269: dup
    //   1270: getstatic 155	et:am	[I
    //   1273: bipush 20
    //   1275: iaload
    //   1276: getstatic 155	et:am	[I
    //   1279: bipush 104
    //   1281: iaload
    //   1282: sastore
    //   1283: aastore
    //   1284: getstatic 184	et:m	[[S
    //   1287: getstatic 155	et:am	[I
    //   1290: bipush 54
    //   1292: iaload
    //   1293: getstatic 155	et:am	[I
    //   1296: iconst_1
    //   1297: iaload
    //   1298: newarray <illegal type>
    //   1300: dup
    //   1301: getstatic 155	et:am	[I
    //   1304: iconst_2
    //   1305: iaload
    //   1306: getstatic 155	et:am	[I
    //   1309: bipush 52
    //   1311: iaload
    //   1312: sastore
    //   1313: dup
    //   1314: getstatic 155	et:am	[I
    //   1317: iconst_5
    //   1318: iaload
    //   1319: getstatic 155	et:am	[I
    //   1322: bipush 56
    //   1324: iaload
    //   1325: sastore
    //   1326: aastore
    //   1327: getstatic 184	et:m	[[S
    //   1330: getstatic 155	et:am	[I
    //   1333: bipush 56
    //   1335: iaload
    //   1336: getstatic 155	et:am	[I
    //   1339: iconst_1
    //   1340: iaload
    //   1341: newarray <illegal type>
    //   1343: dup
    //   1344: getstatic 155	et:am	[I
    //   1347: iconst_2
    //   1348: iaload
    //   1349: getstatic 155	et:am	[I
    //   1352: bipush 54
    //   1354: iaload
    //   1355: sastore
    //   1356: dup
    //   1357: getstatic 155	et:am	[I
    //   1360: iconst_5
    //   1361: iaload
    //   1362: getstatic 155	et:am	[I
    //   1365: sipush 129
    //   1368: iaload
    //   1369: sastore
    //   1370: aastore
    //   1371: getstatic 184	et:m	[[S
    //   1374: getstatic 155	et:am	[I
    //   1377: bipush 45
    //   1379: iaload
    //   1380: getstatic 155	et:am	[I
    //   1383: iconst_5
    //   1384: iaload
    //   1385: newarray <illegal type>
    //   1387: dup
    //   1388: getstatic 155	et:am	[I
    //   1391: iconst_2
    //   1392: iaload
    //   1393: getstatic 155	et:am	[I
    //   1396: bipush 8
    //   1398: iaload
    //   1399: sastore
    //   1400: aastore
    //   1401: getstatic 184	et:m	[[S
    //   1404: getstatic 155	et:am	[I
    //   1407: bipush 46
    //   1409: iaload
    //   1410: getstatic 155	et:am	[I
    //   1413: iconst_1
    //   1414: iaload
    //   1415: newarray <illegal type>
    //   1417: dup
    //   1418: getstatic 155	et:am	[I
    //   1421: iconst_2
    //   1422: iaload
    //   1423: getstatic 155	et:am	[I
    //   1426: bipush 27
    //   1428: iaload
    //   1429: sastore
    //   1430: dup
    //   1431: getstatic 155	et:am	[I
    //   1434: iconst_5
    //   1435: iaload
    //   1436: getstatic 155	et:am	[I
    //   1439: bipush 8
    //   1441: iaload
    //   1442: sastore
    //   1443: aastore
    //   1444: getstatic 184	et:m	[[S
    //   1447: getstatic 155	et:am	[I
    //   1450: bipush 27
    //   1452: iaload
    //   1453: getstatic 155	et:am	[I
    //   1456: bipush 9
    //   1458: iaload
    //   1459: newarray <illegal type>
    //   1461: dup
    //   1462: getstatic 155	et:am	[I
    //   1465: iconst_2
    //   1466: iaload
    //   1467: getstatic 155	et:am	[I
    //   1470: bipush 47
    //   1472: iaload
    //   1473: sastore
    //   1474: dup
    //   1475: getstatic 155	et:am	[I
    //   1478: iconst_5
    //   1479: iaload
    //   1480: getstatic 155	et:am	[I
    //   1483: bipush 46
    //   1485: iaload
    //   1486: sastore
    //   1487: dup
    //   1488: getstatic 155	et:am	[I
    //   1491: iconst_1
    //   1492: iaload
    //   1493: getstatic 155	et:am	[I
    //   1496: bipush 10
    //   1498: iaload
    //   1499: sastore
    //   1500: dup
    //   1501: getstatic 155	et:am	[I
    //   1504: bipush 6
    //   1506: iaload
    //   1507: getstatic 155	et:am	[I
    //   1510: bipush 52
    //   1512: iaload
    //   1513: sastore
    //   1514: dup
    //   1515: getstatic 155	et:am	[I
    //   1518: iconst_3
    //   1519: iaload
    //   1520: getstatic 155	et:am	[I
    //   1523: bipush 53
    //   1525: iaload
    //   1526: sastore
    //   1527: dup
    //   1528: getstatic 155	et:am	[I
    //   1531: bipush 7
    //   1533: iaload
    //   1534: getstatic 155	et:am	[I
    //   1537: bipush 48
    //   1539: iaload
    //   1540: sastore
    //   1541: dup
    //   1542: getstatic 155	et:am	[I
    //   1545: bipush 8
    //   1547: iaload
    //   1548: getstatic 155	et:am	[I
    //   1551: bipush 15
    //   1553: iaload
    //   1554: sastore
    //   1555: dup
    //   1556: getstatic 155	et:am	[I
    //   1559: bipush 28
    //   1561: iaload
    //   1562: getstatic 155	et:am	[I
    //   1565: sipush 135
    //   1568: iaload
    //   1569: sastore
    //   1570: dup
    //   1571: getstatic 155	et:am	[I
    //   1574: bipush 20
    //   1576: iaload
    //   1577: getstatic 155	et:am	[I
    //   1580: bipush 104
    //   1582: iaload
    //   1583: sastore
    //   1584: aastore
    //   1585: getstatic 184	et:m	[[S
    //   1588: getstatic 155	et:am	[I
    //   1591: bipush 47
    //   1593: iaload
    //   1594: getstatic 155	et:am	[I
    //   1597: bipush 6
    //   1599: iaload
    //   1600: newarray <illegal type>
    //   1602: dup
    //   1603: getstatic 155	et:am	[I
    //   1606: iconst_2
    //   1607: iaload
    //   1608: getstatic 155	et:am	[I
    //   1611: bipush 27
    //   1613: iaload
    //   1614: sastore
    //   1615: dup
    //   1616: getstatic 155	et:am	[I
    //   1619: iconst_5
    //   1620: iaload
    //   1621: getstatic 155	et:am	[I
    //   1624: sipush 179
    //   1627: iaload
    //   1628: sastore
    //   1629: dup
    //   1630: getstatic 155	et:am	[I
    //   1633: iconst_1
    //   1634: iaload
    //   1635: getstatic 155	et:am	[I
    //   1638: bipush 113
    //   1640: iaload
    //   1641: sastore
    //   1642: aastore
    //   1643: getstatic 184	et:m	[[S
    //   1646: getstatic 155	et:am	[I
    //   1649: bipush 108
    //   1651: iaload
    //   1652: getstatic 155	et:am	[I
    //   1655: iconst_1
    //   1656: iaload
    //   1657: newarray <illegal type>
    //   1659: dup
    //   1660: getstatic 155	et:am	[I
    //   1663: iconst_2
    //   1664: iaload
    //   1665: getstatic 155	et:am	[I
    //   1668: sipush 180
    //   1671: iaload
    //   1672: sastore
    //   1673: dup
    //   1674: getstatic 155	et:am	[I
    //   1677: iconst_5
    //   1678: iaload
    //   1679: getstatic 155	et:am	[I
    //   1682: bipush 29
    //   1684: iaload
    //   1685: sastore
    //   1686: aastore
    //   1687: getstatic 184	et:m	[[S
    //   1690: getstatic 155	et:am	[I
    //   1693: bipush 113
    //   1695: iaload
    //   1696: getstatic 155	et:am	[I
    //   1699: iconst_1
    //   1700: iaload
    //   1701: newarray <illegal type>
    //   1703: dup
    //   1704: getstatic 155	et:am	[I
    //   1707: iconst_2
    //   1708: iaload
    //   1709: getstatic 155	et:am	[I
    //   1712: bipush 47
    //   1714: iaload
    //   1715: sastore
    //   1716: dup
    //   1717: getstatic 155	et:am	[I
    //   1720: iconst_5
    //   1721: iaload
    //   1722: getstatic 155	et:am	[I
    //   1725: bipush 116
    //   1727: iaload
    //   1728: sastore
    //   1729: aastore
    //   1730: getstatic 184	et:m	[[S
    //   1733: getstatic 155	et:am	[I
    //   1736: bipush 116
    //   1738: iaload
    //   1739: getstatic 155	et:am	[I
    //   1742: iconst_1
    //   1743: iaload
    //   1744: newarray <illegal type>
    //   1746: dup
    //   1747: getstatic 155	et:am	[I
    //   1750: iconst_2
    //   1751: iaload
    //   1752: getstatic 155	et:am	[I
    //   1755: bipush 127
    //   1757: iaload
    //   1758: sastore
    //   1759: dup
    //   1760: getstatic 155	et:am	[I
    //   1763: iconst_5
    //   1764: iaload
    //   1765: getstatic 155	et:am	[I
    //   1768: bipush 113
    //   1770: iaload
    //   1771: sastore
    //   1772: aastore
    //   1773: getstatic 184	et:m	[[S
    //   1776: getstatic 155	et:am	[I
    //   1779: bipush 127
    //   1781: iaload
    //   1782: getstatic 155	et:am	[I
    //   1785: bipush 13
    //   1787: iaload
    //   1788: newarray <illegal type>
    //   1790: dup
    //   1791: getstatic 155	et:am	[I
    //   1794: iconst_2
    //   1795: iaload
    //   1796: getstatic 155	et:am	[I
    //   1799: bipush 116
    //   1801: iaload
    //   1802: sastore
    //   1803: dup
    //   1804: getstatic 155	et:am	[I
    //   1807: iconst_5
    //   1808: iaload
    //   1809: getstatic 155	et:am	[I
    //   1812: sipush 170
    //   1815: iaload
    //   1816: sastore
    //   1817: dup
    //   1818: getstatic 155	et:am	[I
    //   1821: iconst_1
    //   1822: iaload
    //   1823: getstatic 155	et:am	[I
    //   1826: iconst_5
    //   1827: iaload
    //   1828: sastore
    //   1829: dup
    //   1830: getstatic 155	et:am	[I
    //   1833: bipush 6
    //   1835: iaload
    //   1836: getstatic 155	et:am	[I
    //   1839: bipush 94
    //   1841: iaload
    //   1842: sastore
    //   1843: dup
    //   1844: getstatic 155	et:am	[I
    //   1847: iconst_3
    //   1848: iaload
    //   1849: getstatic 155	et:am	[I
    //   1852: bipush 32
    //   1854: iaload
    //   1855: sastore
    //   1856: dup
    //   1857: getstatic 155	et:am	[I
    //   1860: bipush 7
    //   1862: iaload
    //   1863: getstatic 155	et:am	[I
    //   1866: bipush 35
    //   1868: iaload
    //   1869: sastore
    //   1870: dup
    //   1871: getstatic 155	et:am	[I
    //   1874: bipush 8
    //   1876: iaload
    //   1877: getstatic 155	et:am	[I
    //   1880: bipush 115
    //   1882: iaload
    //   1883: sastore
    //   1884: dup
    //   1885: getstatic 155	et:am	[I
    //   1888: bipush 28
    //   1890: iaload
    //   1891: getstatic 155	et:am	[I
    //   1894: bipush 80
    //   1896: iaload
    //   1897: sastore
    //   1898: dup
    //   1899: getstatic 155	et:am	[I
    //   1902: bipush 20
    //   1904: iaload
    //   1905: getstatic 155	et:am	[I
    //   1908: bipush 74
    //   1910: iaload
    //   1911: sastore
    //   1912: dup
    //   1913: getstatic 155	et:am	[I
    //   1916: bipush 9
    //   1918: iaload
    //   1919: getstatic 155	et:am	[I
    //   1922: sipush 157
    //   1925: iaload
    //   1926: sastore
    //   1927: dup
    //   1928: getstatic 155	et:am	[I
    //   1931: bipush 10
    //   1933: iaload
    //   1934: getstatic 155	et:am	[I
    //   1937: bipush 104
    //   1939: iaload
    //   1940: sastore
    //   1941: dup
    //   1942: getstatic 155	et:am	[I
    //   1945: bipush 19
    //   1947: iaload
    //   1948: getstatic 155	et:am	[I
    //   1951: bipush 73
    //   1953: iaload
    //   1954: sastore
    //   1955: dup
    //   1956: getstatic 155	et:am	[I
    //   1959: iconst_0
    //   1960: iaload
    //   1961: getstatic 155	et:am	[I
    //   1964: bipush 12
    //   1966: iaload
    //   1967: sastore
    //   1968: aastore
    //   1969: getstatic 184	et:m	[[S
    //   1972: getstatic 155	et:am	[I
    //   1975: sipush 170
    //   1978: iaload
    //   1979: getstatic 155	et:am	[I
    //   1982: iconst_1
    //   1983: iaload
    //   1984: newarray <illegal type>
    //   1986: dup
    //   1987: getstatic 155	et:am	[I
    //   1990: iconst_2
    //   1991: iaload
    //   1992: getstatic 155	et:am	[I
    //   1995: bipush 127
    //   1997: iaload
    //   1998: sastore
    //   1999: dup
    //   2000: getstatic 155	et:am	[I
    //   2003: iconst_5
    //   2004: iaload
    //   2005: getstatic 155	et:am	[I
    //   2008: sipush 130
    //   2011: iaload
    //   2012: sastore
    //   2013: aastore
    //   2014: getstatic 184	et:m	[[S
    //   2017: getstatic 155	et:am	[I
    //   2020: sipush 154
    //   2023: iaload
    //   2024: getstatic 155	et:am	[I
    //   2027: iconst_1
    //   2028: iaload
    //   2029: newarray <illegal type>
    //   2031: dup
    //   2032: getstatic 155	et:am	[I
    //   2035: iconst_2
    //   2036: iaload
    //   2037: getstatic 155	et:am	[I
    //   2040: sipush 130
    //   2043: iaload
    //   2044: sastore
    //   2045: dup
    //   2046: getstatic 155	et:am	[I
    //   2049: iconst_5
    //   2050: iaload
    //   2051: getstatic 155	et:am	[I
    //   2054: bipush 50
    //   2056: iaload
    //   2057: sastore
    //   2058: aastore
    //   2059: getstatic 184	et:m	[[S
    //   2062: getstatic 155	et:am	[I
    //   2065: bipush 50
    //   2067: iaload
    //   2068: getstatic 155	et:am	[I
    //   2071: iconst_1
    //   2072: iaload
    //   2073: newarray <illegal type>
    //   2075: dup
    //   2076: getstatic 155	et:am	[I
    //   2079: iconst_2
    //   2080: iaload
    //   2081: getstatic 155	et:am	[I
    //   2084: sipush 154
    //   2087: iaload
    //   2088: sastore
    //   2089: dup
    //   2090: getstatic 155	et:am	[I
    //   2093: iconst_5
    //   2094: iaload
    //   2095: getstatic 155	et:am	[I
    //   2098: sipush 181
    //   2101: iaload
    //   2102: sastore
    //   2103: aastore
    //   2104: getstatic 184	et:m	[[S
    //   2107: getstatic 155	et:am	[I
    //   2110: sipush 181
    //   2113: iaload
    //   2114: getstatic 155	et:am	[I
    //   2117: iconst_1
    //   2118: iaload
    //   2119: newarray <illegal type>
    //   2121: dup
    //   2122: getstatic 155	et:am	[I
    //   2125: iconst_2
    //   2126: iaload
    //   2127: getstatic 155	et:am	[I
    //   2130: bipush 53
    //   2132: iaload
    //   2133: sastore
    //   2134: dup
    //   2135: getstatic 155	et:am	[I
    //   2138: iconst_5
    //   2139: iaload
    //   2140: getstatic 155	et:am	[I
    //   2143: bipush 50
    //   2145: iaload
    //   2146: sastore
    //   2147: aastore
    //   2148: getstatic 184	et:m	[[S
    //   2151: getstatic 155	et:am	[I
    //   2154: bipush 53
    //   2156: iaload
    //   2157: getstatic 155	et:am	[I
    //   2160: bipush 9
    //   2162: iaload
    //   2163: newarray <illegal type>
    //   2165: dup
    //   2166: getstatic 155	et:am	[I
    //   2169: iconst_2
    //   2170: iaload
    //   2171: getstatic 155	et:am	[I
    //   2174: sipush 181
    //   2177: iaload
    //   2178: sastore
    //   2179: dup
    //   2180: getstatic 155	et:am	[I
    //   2183: iconst_5
    //   2184: iaload
    //   2185: getstatic 155	et:am	[I
    //   2188: bipush 44
    //   2190: iaload
    //   2191: sastore
    //   2192: dup
    //   2193: getstatic 155	et:am	[I
    //   2196: iconst_1
    //   2197: iaload
    //   2198: getstatic 155	et:am	[I
    //   2201: bipush 10
    //   2203: iaload
    //   2204: sastore
    //   2205: dup
    //   2206: getstatic 155	et:am	[I
    //   2209: bipush 6
    //   2211: iaload
    //   2212: getstatic 155	et:am	[I
    //   2215: bipush 52
    //   2217: iaload
    //   2218: sastore
    //   2219: dup
    //   2220: getstatic 155	et:am	[I
    //   2223: iconst_3
    //   2224: iaload
    //   2225: getstatic 155	et:am	[I
    //   2228: bipush 27
    //   2230: iaload
    //   2231: sastore
    //   2232: dup
    //   2233: getstatic 155	et:am	[I
    //   2236: bipush 7
    //   2238: iaload
    //   2239: getstatic 155	et:am	[I
    //   2242: bipush 48
    //   2244: iaload
    //   2245: sastore
    //   2246: dup
    //   2247: getstatic 155	et:am	[I
    //   2250: bipush 8
    //   2252: iaload
    //   2253: getstatic 155	et:am	[I
    //   2256: bipush 15
    //   2258: iaload
    //   2259: sastore
    //   2260: dup
    //   2261: getstatic 155	et:am	[I
    //   2264: bipush 28
    //   2266: iaload
    //   2267: getstatic 155	et:am	[I
    //   2270: sipush 135
    //   2273: iaload
    //   2274: sastore
    //   2275: dup
    //   2276: getstatic 155	et:am	[I
    //   2279: bipush 20
    //   2281: iaload
    //   2282: getstatic 155	et:am	[I
    //   2285: bipush 104
    //   2287: iaload
    //   2288: sastore
    //   2289: aastore
    //   2290: getstatic 184	et:m	[[S
    //   2293: getstatic 155	et:am	[I
    //   2296: bipush 59
    //   2298: iaload
    //   2299: getstatic 155	et:am	[I
    //   2302: iconst_1
    //   2303: iaload
    //   2304: newarray <illegal type>
    //   2306: dup
    //   2307: getstatic 155	et:am	[I
    //   2310: iconst_2
    //   2311: iaload
    //   2312: getstatic 155	et:am	[I
    //   2315: bipush 44
    //   2317: iaload
    //   2318: sastore
    //   2319: dup
    //   2320: getstatic 155	et:am	[I
    //   2323: iconst_5
    //   2324: iaload
    //   2325: getstatic 155	et:am	[I
    //   2328: bipush 60
    //   2330: iaload
    //   2331: sastore
    //   2332: aastore
    //   2333: getstatic 184	et:m	[[S
    //   2336: getstatic 155	et:am	[I
    //   2339: bipush 60
    //   2341: iaload
    //   2342: getstatic 155	et:am	[I
    //   2345: iconst_1
    //   2346: iaload
    //   2347: newarray <illegal type>
    //   2349: dup
    //   2350: getstatic 155	et:am	[I
    //   2353: iconst_2
    //   2354: iaload
    //   2355: getstatic 155	et:am	[I
    //   2358: bipush 57
    //   2360: iaload
    //   2361: sastore
    //   2362: dup
    //   2363: getstatic 155	et:am	[I
    //   2366: iconst_5
    //   2367: iaload
    //   2368: getstatic 155	et:am	[I
    //   2371: bipush 59
    //   2373: iaload
    //   2374: sastore
    //   2375: aastore
    //   2376: getstatic 184	et:m	[[S
    //   2379: getstatic 155	et:am	[I
    //   2382: bipush 57
    //   2384: iaload
    //   2385: getstatic 155	et:am	[I
    //   2388: iconst_1
    //   2389: iaload
    //   2390: newarray <illegal type>
    //   2392: dup
    //   2393: getstatic 155	et:am	[I
    //   2396: iconst_2
    //   2397: iaload
    //   2398: getstatic 155	et:am	[I
    //   2401: bipush 60
    //   2403: iaload
    //   2404: sastore
    //   2405: dup
    //   2406: getstatic 155	et:am	[I
    //   2409: iconst_5
    //   2410: iaload
    //   2411: getstatic 155	et:am	[I
    //   2414: sipush 182
    //   2417: iaload
    //   2418: sastore
    //   2419: aastore
    //   2420: getstatic 184	et:m	[[S
    //   2423: getstatic 155	et:am	[I
    //   2426: bipush 29
    //   2428: iaload
    //   2429: getstatic 155	et:am	[I
    //   2432: iconst_1
    //   2433: iaload
    //   2434: newarray <illegal type>
    //   2436: dup
    //   2437: getstatic 155	et:am	[I
    //   2440: iconst_2
    //   2441: iaload
    //   2442: getstatic 155	et:am	[I
    //   2445: bipush 30
    //   2447: iaload
    //   2448: sastore
    //   2449: dup
    //   2450: getstatic 155	et:am	[I
    //   2453: iconst_5
    //   2454: iaload
    //   2455: getstatic 155	et:am	[I
    //   2458: bipush 108
    //   2460: iaload
    //   2461: sastore
    //   2462: aastore
    //   2463: getstatic 184	et:m	[[S
    //   2466: getstatic 155	et:am	[I
    //   2469: bipush 30
    //   2471: iaload
    //   2472: getstatic 155	et:am	[I
    //   2475: iconst_5
    //   2476: iaload
    //   2477: newarray <illegal type>
    //   2479: dup
    //   2480: getstatic 155	et:am	[I
    //   2483: iconst_2
    //   2484: iaload
    //   2485: getstatic 155	et:am	[I
    //   2488: bipush 29
    //   2490: iaload
    //   2491: sastore
    //   2492: aastore
    //   2493: getstatic 184	et:m	[[S
    //   2496: getstatic 155	et:am	[I
    //   2499: bipush 48
    //   2501: iaload
    //   2502: getstatic 155	et:am	[I
    //   2505: bipush 9
    //   2507: iaload
    //   2508: newarray <illegal type>
    //   2510: dup
    //   2511: getstatic 155	et:am	[I
    //   2514: iconst_2
    //   2515: iaload
    //   2516: getstatic 155	et:am	[I
    //   2519: bipush 91
    //   2521: iaload
    //   2522: sastore
    //   2523: dup
    //   2524: getstatic 155	et:am	[I
    //   2527: iconst_5
    //   2528: iaload
    //   2529: getstatic 155	et:am	[I
    //   2532: bipush 92
    //   2534: iaload
    //   2535: sastore
    //   2536: dup
    //   2537: getstatic 155	et:am	[I
    //   2540: iconst_1
    //   2541: iaload
    //   2542: getstatic 155	et:am	[I
    //   2545: bipush 10
    //   2547: iaload
    //   2548: sastore
    //   2549: dup
    //   2550: getstatic 155	et:am	[I
    //   2553: bipush 6
    //   2555: iaload
    //   2556: getstatic 155	et:am	[I
    //   2559: bipush 52
    //   2561: iaload
    //   2562: sastore
    //   2563: dup
    //   2564: getstatic 155	et:am	[I
    //   2567: iconst_3
    //   2568: iaload
    //   2569: getstatic 155	et:am	[I
    //   2572: bipush 27
    //   2574: iaload
    //   2575: sastore
    //   2576: dup
    //   2577: getstatic 155	et:am	[I
    //   2580: bipush 7
    //   2582: iaload
    //   2583: getstatic 155	et:am	[I
    //   2586: bipush 53
    //   2588: iaload
    //   2589: sastore
    //   2590: dup
    //   2591: getstatic 155	et:am	[I
    //   2594: bipush 8
    //   2596: iaload
    //   2597: getstatic 155	et:am	[I
    //   2600: bipush 15
    //   2602: iaload
    //   2603: sastore
    //   2604: dup
    //   2605: getstatic 155	et:am	[I
    //   2608: bipush 28
    //   2610: iaload
    //   2611: getstatic 155	et:am	[I
    //   2614: sipush 135
    //   2617: iaload
    //   2618: sastore
    //   2619: dup
    //   2620: getstatic 155	et:am	[I
    //   2623: bipush 20
    //   2625: iaload
    //   2626: getstatic 155	et:am	[I
    //   2629: bipush 104
    //   2631: iaload
    //   2632: sastore
    //   2633: aastore
    //   2634: getstatic 184	et:m	[[S
    //   2637: getstatic 155	et:am	[I
    //   2640: bipush 49
    //   2642: iaload
    //   2643: getstatic 155	et:am	[I
    //   2646: bipush 6
    //   2648: iaload
    //   2649: newarray <illegal type>
    //   2651: dup
    //   2652: getstatic 155	et:am	[I
    //   2655: iconst_2
    //   2656: iaload
    //   2657: getstatic 155	et:am	[I
    //   2660: bipush 94
    //   2662: iaload
    //   2663: sastore
    //   2664: dup
    //   2665: getstatic 155	et:am	[I
    //   2668: iconst_5
    //   2669: iaload
    //   2670: getstatic 155	et:am	[I
    //   2673: sipush 134
    //   2676: iaload
    //   2677: sastore
    //   2678: dup
    //   2679: getstatic 155	et:am	[I
    //   2682: iconst_1
    //   2683: iaload
    //   2684: getstatic 155	et:am	[I
    //   2687: bipush 121
    //   2689: iaload
    //   2690: sastore
    //   2691: aastore
    //   2692: getstatic 184	et:m	[[S
    //   2695: getstatic 155	et:am	[I
    //   2698: bipush 121
    //   2700: iaload
    //   2701: getstatic 155	et:am	[I
    //   2704: bipush 6
    //   2706: iaload
    //   2707: newarray <illegal type>
    //   2709: dup
    //   2710: getstatic 155	et:am	[I
    //   2713: iconst_2
    //   2714: iaload
    //   2715: getstatic 155	et:am	[I
    //   2718: bipush 49
    //   2720: iaload
    //   2721: sastore
    //   2722: dup
    //   2723: getstatic 155	et:am	[I
    //   2726: iconst_5
    //   2727: iaload
    //   2728: getstatic 155	et:am	[I
    //   2731: bipush 90
    //   2733: iaload
    //   2734: sastore
    //   2735: dup
    //   2736: getstatic 155	et:am	[I
    //   2739: iconst_1
    //   2740: iaload
    //   2741: getstatic 155	et:am	[I
    //   2744: bipush 122
    //   2746: iaload
    //   2747: sastore
    //   2748: aastore
    //   2749: getstatic 184	et:m	[[S
    //   2752: getstatic 155	et:am	[I
    //   2755: bipush 122
    //   2757: iaload
    //   2758: getstatic 155	et:am	[I
    //   2761: bipush 6
    //   2763: iaload
    //   2764: newarray <illegal type>
    //   2766: dup
    //   2767: getstatic 155	et:am	[I
    //   2770: iconst_2
    //   2771: iaload
    //   2772: getstatic 155	et:am	[I
    //   2775: sipush 183
    //   2778: iaload
    //   2779: sastore
    //   2780: dup
    //   2781: getstatic 155	et:am	[I
    //   2784: iconst_5
    //   2785: iaload
    //   2786: getstatic 155	et:am	[I
    //   2789: bipush 121
    //   2791: iaload
    //   2792: sastore
    //   2793: dup
    //   2794: getstatic 155	et:am	[I
    //   2797: iconst_1
    //   2798: iaload
    //   2799: getstatic 155	et:am	[I
    //   2802: bipush 15
    //   2804: iaload
    //   2805: sastore
    //   2806: aastore
    //   2807: getstatic 184	et:m	[[S
    //   2810: getstatic 155	et:am	[I
    //   2813: sipush 183
    //   2816: iaload
    //   2817: getstatic 155	et:am	[I
    //   2820: iconst_1
    //   2821: iaload
    //   2822: newarray <illegal type>
    //   2824: dup
    //   2825: getstatic 155	et:am	[I
    //   2828: iconst_2
    //   2829: iaload
    //   2830: getstatic 155	et:am	[I
    //   2833: sipush 137
    //   2836: iaload
    //   2837: sastore
    //   2838: dup
    //   2839: getstatic 155	et:am	[I
    //   2842: iconst_5
    //   2843: iaload
    //   2844: getstatic 155	et:am	[I
    //   2847: bipush 122
    //   2849: iaload
    //   2850: sastore
    //   2851: aastore
    //   2852: getstatic 184	et:m	[[S
    //   2855: getstatic 155	et:am	[I
    //   2858: bipush 15
    //   2860: iaload
    //   2861: getstatic 155	et:am	[I
    //   2864: bipush 9
    //   2866: iaload
    //   2867: newarray <illegal type>
    //   2869: dup
    //   2870: getstatic 155	et:am	[I
    //   2873: iconst_2
    //   2874: iaload
    //   2875: getstatic 155	et:am	[I
    //   2878: bipush 122
    //   2880: iaload
    //   2881: sastore
    //   2882: dup
    //   2883: getstatic 155	et:am	[I
    //   2886: iconst_5
    //   2887: iaload
    //   2888: getstatic 155	et:am	[I
    //   2891: bipush 16
    //   2893: iaload
    //   2894: sastore
    //   2895: dup
    //   2896: getstatic 155	et:am	[I
    //   2899: iconst_1
    //   2900: iaload
    //   2901: getstatic 155	et:am	[I
    //   2904: bipush 10
    //   2906: iaload
    //   2907: sastore
    //   2908: dup
    //   2909: getstatic 155	et:am	[I
    //   2912: bipush 6
    //   2914: iaload
    //   2915: getstatic 155	et:am	[I
    //   2918: bipush 52
    //   2920: iaload
    //   2921: sastore
    //   2922: dup
    //   2923: getstatic 155	et:am	[I
    //   2926: iconst_3
    //   2927: iaload
    //   2928: getstatic 155	et:am	[I
    //   2931: bipush 27
    //   2933: iaload
    //   2934: sastore
    //   2935: dup
    //   2936: getstatic 155	et:am	[I
    //   2939: bipush 7
    //   2941: iaload
    //   2942: getstatic 155	et:am	[I
    //   2945: bipush 53
    //   2947: iaload
    //   2948: sastore
    //   2949: dup
    //   2950: getstatic 155	et:am	[I
    //   2953: bipush 8
    //   2955: iaload
    //   2956: getstatic 155	et:am	[I
    //   2959: bipush 48
    //   2961: iaload
    //   2962: sastore
    //   2963: dup
    //   2964: getstatic 155	et:am	[I
    //   2967: bipush 28
    //   2969: iaload
    //   2970: getstatic 155	et:am	[I
    //   2973: sipush 135
    //   2976: iaload
    //   2977: sastore
    //   2978: dup
    //   2979: getstatic 155	et:am	[I
    //   2982: bipush 20
    //   2984: iaload
    //   2985: getstatic 155	et:am	[I
    //   2988: bipush 104
    //   2990: iaload
    //   2991: sastore
    //   2992: aastore
    //   2993: getstatic 184	et:m	[[S
    //   2996: getstatic 155	et:am	[I
    //   2999: bipush 16
    //   3001: iaload
    //   3002: getstatic 155	et:am	[I
    //   3005: iconst_1
    //   3006: iaload
    //   3007: newarray <illegal type>
    //   3009: dup
    //   3010: getstatic 155	et:am	[I
    //   3013: iconst_2
    //   3014: iaload
    //   3015: getstatic 155	et:am	[I
    //   3018: bipush 15
    //   3020: iaload
    //   3021: sastore
    //   3022: dup
    //   3023: getstatic 155	et:am	[I
    //   3026: iconst_5
    //   3027: iaload
    //   3028: getstatic 155	et:am	[I
    //   3031: bipush 17
    //   3033: iaload
    //   3034: sastore
    //   3035: aastore
    //   3036: getstatic 184	et:m	[[S
    //   3039: getstatic 155	et:am	[I
    //   3042: bipush 17
    //   3044: iaload
    //   3045: getstatic 155	et:am	[I
    //   3048: iconst_1
    //   3049: iaload
    //   3050: newarray <illegal type>
    //   3052: dup
    //   3053: getstatic 155	et:am	[I
    //   3056: iconst_2
    //   3057: iaload
    //   3058: getstatic 155	et:am	[I
    //   3061: bipush 16
    //   3063: iaload
    //   3064: sastore
    //   3065: dup
    //   3066: getstatic 155	et:am	[I
    //   3069: iconst_5
    //   3070: iaload
    //   3071: getstatic 155	et:am	[I
    //   3074: sipush 184
    //   3077: iaload
    //   3078: sastore
    //   3079: aastore
    //   3080: getstatic 184	et:m	[[S
    //   3083: getstatic 155	et:am	[I
    //   3086: sipush 134
    //   3089: iaload
    //   3090: getstatic 155	et:am	[I
    //   3093: bipush 6
    //   3095: iaload
    //   3096: newarray <illegal type>
    //   3098: dup
    //   3099: getstatic 155	et:am	[I
    //   3102: iconst_2
    //   3103: iaload
    //   3104: getstatic 155	et:am	[I
    //   3107: bipush 89
    //   3109: iaload
    //   3110: sastore
    //   3111: dup
    //   3112: getstatic 155	et:am	[I
    //   3115: iconst_5
    //   3116: iaload
    //   3117: getstatic 155	et:am	[I
    //   3120: bipush 49
    //   3122: iaload
    //   3123: sastore
    //   3124: dup
    //   3125: getstatic 155	et:am	[I
    //   3128: iconst_1
    //   3129: iaload
    //   3130: getstatic 155	et:am	[I
    //   3133: sipush 185
    //   3136: iaload
    //   3137: sastore
    //   3138: aastore
    //   3139: getstatic 184	et:m	[[S
    //   3142: getstatic 155	et:am	[I
    //   3145: sipush 185
    //   3148: iaload
    //   3149: getstatic 155	et:am	[I
    //   3152: iconst_1
    //   3153: iaload
    //   3154: newarray <illegal type>
    //   3156: dup
    //   3157: getstatic 155	et:am	[I
    //   3160: iconst_2
    //   3161: iaload
    //   3162: getstatic 155	et:am	[I
    //   3165: sipush 134
    //   3168: iaload
    //   3169: sastore
    //   3170: dup
    //   3171: getstatic 155	et:am	[I
    //   3174: iconst_5
    //   3175: iaload
    //   3176: getstatic 155	et:am	[I
    //   3179: sipush 135
    //   3182: iaload
    //   3183: sastore
    //   3184: aastore
    //   3185: getstatic 184	et:m	[[S
    //   3188: getstatic 155	et:am	[I
    //   3191: sipush 135
    //   3194: iaload
    //   3195: getstatic 155	et:am	[I
    //   3198: bipush 9
    //   3200: iaload
    //   3201: newarray <illegal type>
    //   3203: dup
    //   3204: getstatic 155	et:am	[I
    //   3207: iconst_2
    //   3208: iaload
    //   3209: getstatic 155	et:am	[I
    //   3212: sipush 185
    //   3215: iaload
    //   3216: sastore
    //   3217: dup
    //   3218: getstatic 155	et:am	[I
    //   3221: iconst_5
    //   3222: iaload
    //   3223: getstatic 155	et:am	[I
    //   3226: bipush 18
    //   3228: iaload
    //   3229: sastore
    //   3230: dup
    //   3231: getstatic 155	et:am	[I
    //   3234: iconst_1
    //   3235: iaload
    //   3236: getstatic 155	et:am	[I
    //   3239: bipush 10
    //   3241: iaload
    //   3242: sastore
    //   3243: dup
    //   3244: getstatic 155	et:am	[I
    //   3247: bipush 6
    //   3249: iaload
    //   3250: getstatic 155	et:am	[I
    //   3253: bipush 52
    //   3255: iaload
    //   3256: sastore
    //   3257: dup
    //   3258: getstatic 155	et:am	[I
    //   3261: iconst_3
    //   3262: iaload
    //   3263: getstatic 155	et:am	[I
    //   3266: bipush 27
    //   3268: iaload
    //   3269: sastore
    //   3270: dup
    //   3271: getstatic 155	et:am	[I
    //   3274: bipush 7
    //   3276: iaload
    //   3277: getstatic 155	et:am	[I
    //   3280: bipush 53
    //   3282: iaload
    //   3283: sastore
    //   3284: dup
    //   3285: getstatic 155	et:am	[I
    //   3288: bipush 8
    //   3290: iaload
    //   3291: getstatic 155	et:am	[I
    //   3294: bipush 48
    //   3296: iaload
    //   3297: sastore
    //   3298: dup
    //   3299: getstatic 155	et:am	[I
    //   3302: bipush 28
    //   3304: iaload
    //   3305: getstatic 155	et:am	[I
    //   3308: bipush 15
    //   3310: iaload
    //   3311: sastore
    //   3312: dup
    //   3313: getstatic 155	et:am	[I
    //   3316: bipush 20
    //   3318: iaload
    //   3319: getstatic 155	et:am	[I
    //   3322: bipush 104
    //   3324: iaload
    //   3325: sastore
    //   3326: aastore
    //   3327: getstatic 184	et:m	[[S
    //   3330: getstatic 155	et:am	[I
    //   3333: sipush 186
    //   3336: iaload
    //   3337: getstatic 155	et:am	[I
    //   3340: iconst_1
    //   3341: iaload
    //   3342: newarray <illegal type>
    //   3344: dup
    //   3345: getstatic 155	et:am	[I
    //   3348: iconst_2
    //   3349: iaload
    //   3350: getstatic 155	et:am	[I
    //   3353: bipush 18
    //   3355: iaload
    //   3356: sastore
    //   3357: dup
    //   3358: getstatic 155	et:am	[I
    //   3361: iconst_5
    //   3362: iaload
    //   3363: getstatic 155	et:am	[I
    //   3366: bipush 87
    //   3368: iaload
    //   3369: sastore
    //   3370: aastore
    //   3371: getstatic 184	et:m	[[S
    //   3374: getstatic 155	et:am	[I
    //   3377: bipush 18
    //   3379: iaload
    //   3380: getstatic 155	et:am	[I
    //   3383: iconst_1
    //   3384: iaload
    //   3385: newarray <illegal type>
    //   3387: dup
    //   3388: getstatic 155	et:am	[I
    //   3391: iconst_2
    //   3392: iaload
    //   3393: getstatic 155	et:am	[I
    //   3396: sipush 135
    //   3399: iaload
    //   3400: sastore
    //   3401: dup
    //   3402: getstatic 155	et:am	[I
    //   3405: iconst_5
    //   3406: iaload
    //   3407: getstatic 155	et:am	[I
    //   3410: sipush 186
    //   3413: iaload
    //   3414: sastore
    //   3415: aastore
    //   3416: getstatic 184	et:m	[[S
    //   3419: getstatic 155	et:am	[I
    //   3422: bipush 87
    //   3424: iaload
    //   3425: getstatic 155	et:am	[I
    //   3428: iconst_1
    //   3429: iaload
    //   3430: newarray <illegal type>
    //   3432: dup
    //   3433: getstatic 155	et:am	[I
    //   3436: iconst_2
    //   3437: iaload
    //   3438: getstatic 155	et:am	[I
    //   3441: sipush 140
    //   3444: iaload
    //   3445: sastore
    //   3446: dup
    //   3447: getstatic 155	et:am	[I
    //   3450: iconst_5
    //   3451: iaload
    //   3452: getstatic 155	et:am	[I
    //   3455: sipush 186
    //   3458: iaload
    //   3459: sastore
    //   3460: aastore
    //   3461: getstatic 184	et:m	[[S
    //   3464: getstatic 155	et:am	[I
    //   3467: sipush 140
    //   3470: iaload
    //   3471: getstatic 155	et:am	[I
    //   3474: iconst_1
    //   3475: iaload
    //   3476: newarray <illegal type>
    //   3478: dup
    //   3479: getstatic 155	et:am	[I
    //   3482: iconst_2
    //   3483: iaload
    //   3484: getstatic 155	et:am	[I
    //   3487: bipush 87
    //   3489: iaload
    //   3490: sastore
    //   3491: dup
    //   3492: getstatic 155	et:am	[I
    //   3495: iconst_5
    //   3496: iaload
    //   3497: getstatic 155	et:am	[I
    //   3500: bipush 24
    //   3502: iaload
    //   3503: sastore
    //   3504: aastore
    //   3505: getstatic 184	et:m	[[S
    //   3508: getstatic 155	et:am	[I
    //   3511: sipush 184
    //   3514: iaload
    //   3515: getstatic 155	et:am	[I
    //   3518: iconst_1
    //   3519: iaload
    //   3520: newarray <illegal type>
    //   3522: dup
    //   3523: getstatic 155	et:am	[I
    //   3526: iconst_2
    //   3527: iaload
    //   3528: getstatic 155	et:am	[I
    //   3531: bipush 31
    //   3533: iaload
    //   3534: sastore
    //   3535: dup
    //   3536: getstatic 155	et:am	[I
    //   3539: iconst_5
    //   3540: iaload
    //   3541: getstatic 155	et:am	[I
    //   3544: bipush 17
    //   3546: iaload
    //   3547: sastore
    //   3548: aastore
    //   3549: getstatic 184	et:m	[[S
    //   3552: getstatic 155	et:am	[I
    //   3555: bipush 31
    //   3557: iaload
    //   3558: getstatic 155	et:am	[I
    //   3561: iconst_1
    //   3562: iaload
    //   3563: newarray <illegal type>
    //   3565: dup
    //   3566: getstatic 155	et:am	[I
    //   3569: iconst_2
    //   3570: iaload
    //   3571: getstatic 155	et:am	[I
    //   3574: bipush 79
    //   3576: iaload
    //   3577: sastore
    //   3578: dup
    //   3579: getstatic 155	et:am	[I
    //   3582: iconst_5
    //   3583: iaload
    //   3584: getstatic 155	et:am	[I
    //   3587: sipush 184
    //   3590: iaload
    //   3591: sastore
    //   3592: aastore
    //   3593: getstatic 184	et:m	[[S
    //   3596: getstatic 155	et:am	[I
    //   3599: bipush 79
    //   3601: iaload
    //   3602: getstatic 155	et:am	[I
    //   3605: iconst_5
    //   3606: iaload
    //   3607: newarray <illegal type>
    //   3609: dup
    //   3610: getstatic 155	et:am	[I
    //   3613: iconst_2
    //   3614: iaload
    //   3615: getstatic 155	et:am	[I
    //   3618: bipush 31
    //   3620: iaload
    //   3621: sastore
    //   3622: aastore
    //   3623: getstatic 184	et:m	[[S
    //   3626: getstatic 155	et:am	[I
    //   3629: sipush 136
    //   3632: iaload
    //   3633: getstatic 155	et:am	[I
    //   3636: iconst_5
    //   3637: iaload
    //   3638: newarray <illegal type>
    //   3640: dup
    //   3641: getstatic 155	et:am	[I
    //   3644: iconst_2
    //   3645: iaload
    //   3646: getstatic 155	et:am	[I
    //   3649: bipush 94
    //   3651: iaload
    //   3652: sastore
    //   3653: aastore
    //   3654: getstatic 184	et:m	[[S
    //   3657: getstatic 155	et:am	[I
    //   3660: sipush 128
    //   3663: iaload
    //   3664: getstatic 155	et:am	[I
    //   3667: iconst_1
    //   3668: iaload
    //   3669: newarray <illegal type>
    //   3671: dup
    //   3672: getstatic 155	et:am	[I
    //   3675: iconst_2
    //   3676: iaload
    //   3677: getstatic 155	et:am	[I
    //   3680: iconst_0
    //   3681: iaload
    //   3682: sastore
    //   3683: dup
    //   3684: getstatic 155	et:am	[I
    //   3687: iconst_5
    //   3688: iaload
    //   3689: getstatic 155	et:am	[I
    //   3692: bipush 13
    //   3694: iaload
    //   3695: sastore
    //   3696: aastore
    //   3697: getstatic 184	et:m	[[S
    //   3700: getstatic 155	et:am	[I
    //   3703: sipush 129
    //   3706: iaload
    //   3707: getstatic 155	et:am	[I
    //   3710: iconst_5
    //   3711: iaload
    //   3712: newarray <illegal type>
    //   3714: dup
    //   3715: getstatic 155	et:am	[I
    //   3718: iconst_2
    //   3719: iaload
    //   3720: getstatic 155	et:am	[I
    //   3723: bipush 56
    //   3725: iaload
    //   3726: sastore
    //   3727: aastore
    //   3728: getstatic 184	et:m	[[S
    //   3731: getstatic 155	et:am	[I
    //   3734: sipush 180
    //   3737: iaload
    //   3738: getstatic 155	et:am	[I
    //   3741: iconst_1
    //   3742: iaload
    //   3743: newarray <illegal type>
    //   3745: dup
    //   3746: getstatic 155	et:am	[I
    //   3749: iconst_2
    //   3750: iaload
    //   3751: getstatic 155	et:am	[I
    //   3754: bipush 92
    //   3756: iaload
    //   3757: sastore
    //   3758: dup
    //   3759: getstatic 155	et:am	[I
    //   3762: iconst_5
    //   3763: iaload
    //   3764: getstatic 155	et:am	[I
    //   3767: bipush 108
    //   3769: iaload
    //   3770: sastore
    //   3771: aastore
    //   3772: getstatic 184	et:m	[[S
    //   3775: getstatic 155	et:am	[I
    //   3778: sipush 130
    //   3781: iaload
    //   3782: getstatic 155	et:am	[I
    //   3785: iconst_1
    //   3786: iaload
    //   3787: newarray <illegal type>
    //   3789: dup
    //   3790: getstatic 155	et:am	[I
    //   3793: iconst_2
    //   3794: iaload
    //   3795: getstatic 155	et:am	[I
    //   3798: sipush 170
    //   3801: iaload
    //   3802: sastore
    //   3803: dup
    //   3804: getstatic 155	et:am	[I
    //   3807: iconst_5
    //   3808: iaload
    //   3809: getstatic 155	et:am	[I
    //   3812: sipush 154
    //   3815: iaload
    //   3816: sastore
    //   3817: aastore
    //   3818: getstatic 184	et:m	[[S
    //   3821: getstatic 155	et:am	[I
    //   3824: bipush 44
    //   3826: iaload
    //   3827: getstatic 155	et:am	[I
    //   3830: iconst_1
    //   3831: iaload
    //   3832: newarray <illegal type>
    //   3834: dup
    //   3835: getstatic 155	et:am	[I
    //   3838: iconst_2
    //   3839: iaload
    //   3840: getstatic 155	et:am	[I
    //   3843: bipush 59
    //   3845: iaload
    //   3846: sastore
    //   3847: dup
    //   3848: getstatic 155	et:am	[I
    //   3851: iconst_5
    //   3852: iaload
    //   3853: getstatic 155	et:am	[I
    //   3856: bipush 53
    //   3858: iaload
    //   3859: sastore
    //   3860: aastore
    //   3861: getstatic 184	et:m	[[S
    //   3864: getstatic 155	et:am	[I
    //   3867: sipush 137
    //   3870: iaload
    //   3871: getstatic 155	et:am	[I
    //   3874: iconst_5
    //   3875: iaload
    //   3876: newarray <illegal type>
    //   3878: dup
    //   3879: getstatic 155	et:am	[I
    //   3882: iconst_2
    //   3883: iaload
    //   3884: getstatic 155	et:am	[I
    //   3887: sipush 183
    //   3890: iaload
    //   3891: sastore
    //   3892: aastore
    //   3893: getstatic 184	et:m	[[S
    //   3896: getstatic 155	et:am	[I
    //   3899: bipush 89
    //   3901: iaload
    //   3902: getstatic 155	et:am	[I
    //   3905: iconst_5
    //   3906: iaload
    //   3907: newarray <illegal type>
    //   3909: dup
    //   3910: getstatic 155	et:am	[I
    //   3913: iconst_2
    //   3914: iaload
    //   3915: getstatic 155	et:am	[I
    //   3918: sipush 134
    //   3921: iaload
    //   3922: sastore
    //   3923: aastore
    //   3924: getstatic 184	et:m	[[S
    //   3927: getstatic 155	et:am	[I
    //   3930: bipush 24
    //   3932: iaload
    //   3933: getstatic 155	et:am	[I
    //   3936: iconst_5
    //   3937: iaload
    //   3938: newarray <illegal type>
    //   3940: dup
    //   3941: getstatic 155	et:am	[I
    //   3944: iconst_2
    //   3945: iaload
    //   3946: getstatic 155	et:am	[I
    //   3949: sipush 140
    //   3952: iaload
    //   3953: sastore
    //   3954: aastore
    //   3955: getstatic 184	et:m	[[S
    //   3958: getstatic 155	et:am	[I
    //   3961: bipush 90
    //   3963: iaload
    //   3964: getstatic 155	et:am	[I
    //   3967: iconst_5
    //   3968: iaload
    //   3969: newarray <illegal type>
    //   3971: dup
    //   3972: getstatic 155	et:am	[I
    //   3975: iconst_2
    //   3976: iaload
    //   3977: getstatic 155	et:am	[I
    //   3980: bipush 121
    //   3982: iaload
    //   3983: sastore
    //   3984: aastore
    //   3985: getstatic 184	et:m	[[S
    //   3988: getstatic 155	et:am	[I
    //   3991: sipush 182
    //   3994: iaload
    //   3995: getstatic 155	et:am	[I
    //   3998: iconst_1
    //   3999: iaload
    //   4000: newarray <illegal type>
    //   4002: dup
    //   4003: getstatic 155	et:am	[I
    //   4006: iconst_2
    //   4007: iaload
    //   4008: getstatic 155	et:am	[I
    //   4011: bipush 91
    //   4013: iaload
    //   4014: sastore
    //   4015: dup
    //   4016: getstatic 155	et:am	[I
    //   4019: iconst_5
    //   4020: iaload
    //   4021: getstatic 155	et:am	[I
    //   4024: bipush 57
    //   4026: iaload
    //   4027: sastore
    //   4028: aastore
    //   4029: getstatic 184	et:m	[[S
    //   4032: getstatic 155	et:am	[I
    //   4035: bipush 91
    //   4037: iaload
    //   4038: getstatic 155	et:am	[I
    //   4041: iconst_1
    //   4042: iaload
    //   4043: newarray <illegal type>
    //   4045: dup
    //   4046: getstatic 155	et:am	[I
    //   4049: iconst_2
    //   4050: iaload
    //   4051: getstatic 155	et:am	[I
    //   4054: sipush 182
    //   4057: iaload
    //   4058: sastore
    //   4059: dup
    //   4060: getstatic 155	et:am	[I
    //   4063: iconst_5
    //   4064: iaload
    //   4065: getstatic 155	et:am	[I
    //   4068: bipush 48
    //   4070: iaload
    //   4071: sastore
    //   4072: aastore
    //   4073: getstatic 184	et:m	[[S
    //   4076: getstatic 155	et:am	[I
    //   4079: bipush 92
    //   4081: iaload
    //   4082: getstatic 155	et:am	[I
    //   4085: iconst_1
    //   4086: iaload
    //   4087: newarray <illegal type>
    //   4089: dup
    //   4090: getstatic 155	et:am	[I
    //   4093: iconst_2
    //   4094: iaload
    //   4095: getstatic 155	et:am	[I
    //   4098: sipush 180
    //   4101: iaload
    //   4102: sastore
    //   4103: dup
    //   4104: getstatic 155	et:am	[I
    //   4107: iconst_5
    //   4108: iaload
    //   4109: getstatic 155	et:am	[I
    //   4112: bipush 48
    //   4114: iaload
    //   4115: sastore
    //   4116: aastore
    //   4117: getstatic 184	et:m	[[S
    //   4120: getstatic 155	et:am	[I
    //   4123: sipush 179
    //   4126: iaload
    //   4127: getstatic 155	et:am	[I
    //   4130: iconst_1
    //   4131: iaload
    //   4132: newarray <illegal type>
    //   4134: dup
    //   4135: getstatic 155	et:am	[I
    //   4138: iconst_2
    //   4139: iaload
    //   4140: getstatic 155	et:am	[I
    //   4143: sipush 131
    //   4146: iaload
    //   4147: sastore
    //   4148: dup
    //   4149: getstatic 155	et:am	[I
    //   4152: iconst_5
    //   4153: iaload
    //   4154: getstatic 155	et:am	[I
    //   4157: bipush 47
    //   4159: iaload
    //   4160: sastore
    //   4161: aastore
    //   4162: getstatic 184	et:m	[[S
    //   4165: getstatic 155	et:am	[I
    //   4168: sipush 131
    //   4171: iaload
    //   4172: getstatic 155	et:am	[I
    //   4175: iconst_1
    //   4176: iaload
    //   4177: newarray <illegal type>
    //   4179: dup
    //   4180: getstatic 155	et:am	[I
    //   4183: iconst_2
    //   4184: iaload
    //   4185: getstatic 155	et:am	[I
    //   4188: sipush 179
    //   4191: iaload
    //   4192: sastore
    //   4193: dup
    //   4194: getstatic 155	et:am	[I
    //   4197: iconst_5
    //   4198: iaload
    //   4199: getstatic 155	et:am	[I
    //   4202: bipush 93
    //   4204: iaload
    //   4205: sastore
    //   4206: aastore
    //   4207: getstatic 184	et:m	[[S
    //   4210: getstatic 155	et:am	[I
    //   4213: bipush 93
    //   4215: iaload
    //   4216: getstatic 155	et:am	[I
    //   4219: iconst_1
    //   4220: iaload
    //   4221: newarray <illegal type>
    //   4223: dup
    //   4224: getstatic 155	et:am	[I
    //   4227: iconst_2
    //   4228: iaload
    //   4229: getstatic 155	et:am	[I
    //   4232: bipush 94
    //   4234: iaload
    //   4235: sastore
    //   4236: dup
    //   4237: getstatic 155	et:am	[I
    //   4240: iconst_5
    //   4241: iaload
    //   4242: getstatic 155	et:am	[I
    //   4245: sipush 131
    //   4248: iaload
    //   4249: sastore
    //   4250: aastore
    //   4251: getstatic 184	et:m	[[S
    //   4254: getstatic 155	et:am	[I
    //   4257: bipush 94
    //   4259: iaload
    //   4260: getstatic 155	et:am	[I
    //   4263: bipush 13
    //   4265: iaload
    //   4266: newarray <illegal type>
    //   4268: dup
    //   4269: getstatic 155	et:am	[I
    //   4272: iconst_2
    //   4273: iaload
    //   4274: getstatic 155	et:am	[I
    //   4277: bipush 93
    //   4279: iaload
    //   4280: sastore
    //   4281: dup
    //   4282: getstatic 155	et:am	[I
    //   4285: iconst_5
    //   4286: iaload
    //   4287: getstatic 155	et:am	[I
    //   4290: bipush 49
    //   4292: iaload
    //   4293: sastore
    //   4294: dup
    //   4295: getstatic 155	et:am	[I
    //   4298: iconst_1
    //   4299: iaload
    //   4300: getstatic 155	et:am	[I
    //   4303: iconst_5
    //   4304: iaload
    //   4305: sastore
    //   4306: dup
    //   4307: getstatic 155	et:am	[I
    //   4310: bipush 6
    //   4312: iaload
    //   4313: getstatic 155	et:am	[I
    //   4316: bipush 127
    //   4318: iaload
    //   4319: sastore
    //   4320: dup
    //   4321: getstatic 155	et:am	[I
    //   4324: iconst_3
    //   4325: iaload
    //   4326: getstatic 155	et:am	[I
    //   4329: bipush 32
    //   4331: iaload
    //   4332: sastore
    //   4333: dup
    //   4334: getstatic 155	et:am	[I
    //   4337: bipush 7
    //   4339: iaload
    //   4340: getstatic 155	et:am	[I
    //   4343: bipush 35
    //   4345: iaload
    //   4346: sastore
    //   4347: dup
    //   4348: getstatic 155	et:am	[I
    //   4351: bipush 8
    //   4353: iaload
    //   4354: getstatic 155	et:am	[I
    //   4357: bipush 115
    //   4359: iaload
    //   4360: sastore
    //   4361: dup
    //   4362: getstatic 155	et:am	[I
    //   4365: bipush 28
    //   4367: iaload
    //   4368: getstatic 155	et:am	[I
    //   4371: bipush 80
    //   4373: iaload
    //   4374: sastore
    //   4375: dup
    //   4376: getstatic 155	et:am	[I
    //   4379: bipush 20
    //   4381: iaload
    //   4382: getstatic 155	et:am	[I
    //   4385: bipush 74
    //   4387: iaload
    //   4388: sastore
    //   4389: dup
    //   4390: getstatic 155	et:am	[I
    //   4393: bipush 9
    //   4395: iaload
    //   4396: getstatic 155	et:am	[I
    //   4399: sipush 157
    //   4402: iaload
    //   4403: sastore
    //   4404: dup
    //   4405: getstatic 155	et:am	[I
    //   4408: bipush 10
    //   4410: iaload
    //   4411: getstatic 155	et:am	[I
    //   4414: bipush 104
    //   4416: iaload
    //   4417: sastore
    //   4418: dup
    //   4419: getstatic 155	et:am	[I
    //   4422: bipush 19
    //   4424: iaload
    //   4425: getstatic 155	et:am	[I
    //   4428: bipush 73
    //   4430: iaload
    //   4431: sastore
    //   4432: dup
    //   4433: getstatic 155	et:am	[I
    //   4436: iconst_0
    //   4437: iaload
    //   4438: getstatic 155	et:am	[I
    //   4441: bipush 12
    //   4443: iaload
    //   4444: sastore
    //   4445: aastore
    //   4446: getstatic 184	et:m	[[S
    //   4449: getstatic 155	et:am	[I
    //   4452: bipush 36
    //   4454: iaload
    //   4455: getstatic 155	et:am	[I
    //   4458: iconst_5
    //   4459: iaload
    //   4460: newarray <illegal type>
    //   4462: dup
    //   4463: getstatic 155	et:am	[I
    //   4466: iconst_2
    //   4467: iaload
    //   4468: getstatic 155	et:am	[I
    //   4471: iconst_5
    //   4472: iaload
    //   4473: sastore
    //   4474: aastore
    //   4475: getstatic 184	et:m	[[S
    //   4478: getstatic 155	et:am	[I
    //   4481: bipush 37
    //   4483: iaload
    //   4484: getstatic 155	et:am	[I
    //   4487: iconst_2
    //   4488: iaload
    //   4489: newarray <illegal type>
    //   4491: aastore
    //   4492: getstatic 184	et:m	[[S
    //   4495: getstatic 155	et:am	[I
    //   4498: sipush 132
    //   4501: iaload
    //   4502: getstatic 155	et:am	[I
    //   4505: iconst_2
    //   4506: iaload
    //   4507: newarray <illegal type>
    //   4509: aastore
    //   4510: getstatic 184	et:m	[[S
    //   4513: getstatic 155	et:am	[I
    //   4516: bipush 22
    //   4518: iaload
    //   4519: getstatic 155	et:am	[I
    //   4522: iconst_2
    //   4523: iaload
    //   4524: newarray <illegal type>
    //   4526: aastore
    //   4527: getstatic 184	et:m	[[S
    //   4530: getstatic 155	et:am	[I
    //   4533: bipush 23
    //   4535: iaload
    //   4536: getstatic 155	et:am	[I
    //   4539: iconst_2
    //   4540: iaload
    //   4541: newarray <illegal type>
    //   4543: aastore
    //   4544: getstatic 184	et:m	[[S
    //   4547: getstatic 155	et:am	[I
    //   4550: bipush 25
    //   4552: iaload
    //   4553: getstatic 155	et:am	[I
    //   4556: iconst_2
    //   4557: iaload
    //   4558: newarray <illegal type>
    //   4560: aastore
    //   4561: getstatic 184	et:m	[[S
    //   4564: getstatic 155	et:am	[I
    //   4567: bipush 11
    //   4569: iaload
    //   4570: getstatic 155	et:am	[I
    //   4573: iconst_2
    //   4574: iaload
    //   4575: newarray <illegal type>
    //   4577: aastore
    //   4578: getstatic 184	et:m	[[S
    //   4581: getstatic 155	et:am	[I
    //   4584: bipush 12
    //   4586: iaload
    //   4587: getstatic 155	et:am	[I
    //   4590: bipush 6
    //   4592: iaload
    //   4593: newarray <illegal type>
    //   4595: dup
    //   4596: getstatic 155	et:am	[I
    //   4599: iconst_2
    //   4600: iaload
    //   4601: getstatic 155	et:am	[I
    //   4604: sipush 133
    //   4607: iaload
    //   4608: sastore
    //   4609: dup
    //   4610: getstatic 155	et:am	[I
    //   4613: iconst_5
    //   4614: iaload
    //   4615: getstatic 155	et:am	[I
    //   4618: bipush 64
    //   4620: iaload
    //   4621: sastore
    //   4622: dup
    //   4623: getstatic 155	et:am	[I
    //   4626: iconst_1
    //   4627: iaload
    //   4628: getstatic 155	et:am	[I
    //   4631: bipush 65
    //   4633: iaload
    //   4634: sastore
    //   4635: aastore
    //   4636: getstatic 184	et:m	[[S
    //   4639: getstatic 155	et:am	[I
    //   4642: sipush 133
    //   4645: iaload
    //   4646: getstatic 155	et:am	[I
    //   4649: iconst_1
    //   4650: iaload
    //   4651: newarray <illegal type>
    //   4653: dup
    //   4654: getstatic 155	et:am	[I
    //   4657: iconst_2
    //   4658: iaload
    //   4659: getstatic 155	et:am	[I
    //   4662: bipush 12
    //   4664: iaload
    //   4665: sastore
    //   4666: dup
    //   4667: getstatic 155	et:am	[I
    //   4670: iconst_5
    //   4671: iaload
    //   4672: getstatic 155	et:am	[I
    //   4675: bipush 95
    //   4677: iaload
    //   4678: sastore
    //   4679: aastore
    //   4680: getstatic 184	et:m	[[S
    //   4683: getstatic 155	et:am	[I
    //   4686: bipush 64
    //   4688: iaload
    //   4689: getstatic 155	et:am	[I
    //   4692: iconst_1
    //   4693: iaload
    //   4694: newarray <illegal type>
    //   4696: dup
    //   4697: getstatic 155	et:am	[I
    //   4700: iconst_2
    //   4701: iaload
    //   4702: getstatic 155	et:am	[I
    //   4705: bipush 12
    //   4707: iaload
    //   4708: sastore
    //   4709: dup
    //   4710: getstatic 155	et:am	[I
    //   4713: iconst_5
    //   4714: iaload
    //   4715: getstatic 155	et:am	[I
    //   4718: bipush 96
    //   4720: iaload
    //   4721: sastore
    //   4722: aastore
    //   4723: getstatic 184	et:m	[[S
    //   4726: getstatic 155	et:am	[I
    //   4729: bipush 65
    //   4731: iaload
    //   4732: getstatic 155	et:am	[I
    //   4735: iconst_1
    //   4736: iaload
    //   4737: newarray <illegal type>
    //   4739: dup
    //   4740: getstatic 155	et:am	[I
    //   4743: iconst_2
    //   4744: iaload
    //   4745: getstatic 155	et:am	[I
    //   4748: bipush 12
    //   4750: iaload
    //   4751: sastore
    //   4752: dup
    //   4753: getstatic 155	et:am	[I
    //   4756: iconst_5
    //   4757: iaload
    //   4758: getstatic 155	et:am	[I
    //   4761: sipush 187
    //   4764: iaload
    //   4765: sastore
    //   4766: aastore
    //   4767: getstatic 184	et:m	[[S
    //   4770: getstatic 155	et:am	[I
    //   4773: bipush 95
    //   4775: iaload
    //   4776: getstatic 155	et:am	[I
    //   4779: iconst_1
    //   4780: iaload
    //   4781: newarray <illegal type>
    //   4783: dup
    //   4784: getstatic 155	et:am	[I
    //   4787: iconst_2
    //   4788: iaload
    //   4789: getstatic 155	et:am	[I
    //   4792: sipush 133
    //   4795: iaload
    //   4796: sastore
    //   4797: dup
    //   4798: getstatic 155	et:am	[I
    //   4801: iconst_5
    //   4802: iaload
    //   4803: getstatic 155	et:am	[I
    //   4806: bipush 97
    //   4808: iaload
    //   4809: sastore
    //   4810: aastore
    //   4811: getstatic 184	et:m	[[S
    //   4814: getstatic 155	et:am	[I
    //   4817: bipush 96
    //   4819: iaload
    //   4820: getstatic 155	et:am	[I
    //   4823: iconst_1
    //   4824: iaload
    //   4825: newarray <illegal type>
    //   4827: dup
    //   4828: getstatic 155	et:am	[I
    //   4831: iconst_2
    //   4832: iaload
    //   4833: getstatic 155	et:am	[I
    //   4836: bipush 64
    //   4838: iaload
    //   4839: sastore
    //   4840: dup
    //   4841: getstatic 155	et:am	[I
    //   4844: iconst_5
    //   4845: iaload
    //   4846: getstatic 155	et:am	[I
    //   4849: bipush 88
    //   4851: iaload
    //   4852: sastore
    //   4853: aastore
    //   4854: getstatic 184	et:m	[[S
    //   4857: getstatic 155	et:am	[I
    //   4860: sipush 187
    //   4863: iaload
    //   4864: getstatic 155	et:am	[I
    //   4867: iconst_1
    //   4868: iaload
    //   4869: newarray <illegal type>
    //   4871: dup
    //   4872: getstatic 155	et:am	[I
    //   4875: iconst_2
    //   4876: iaload
    //   4877: getstatic 155	et:am	[I
    //   4880: bipush 65
    //   4882: iaload
    //   4883: sastore
    //   4884: dup
    //   4885: getstatic 155	et:am	[I
    //   4888: iconst_5
    //   4889: iaload
    //   4890: getstatic 155	et:am	[I
    //   4893: sipush 188
    //   4896: iaload
    //   4897: sastore
    //   4898: aastore
    //   4899: getstatic 184	et:m	[[S
    //   4902: getstatic 155	et:am	[I
    //   4905: bipush 97
    //   4907: iaload
    //   4908: getstatic 155	et:am	[I
    //   4911: iconst_1
    //   4912: iaload
    //   4913: newarray <illegal type>
    //   4915: dup
    //   4916: getstatic 155	et:am	[I
    //   4919: iconst_2
    //   4920: iaload
    //   4921: getstatic 155	et:am	[I
    //   4924: bipush 95
    //   4926: iaload
    //   4927: sastore
    //   4928: dup
    //   4929: getstatic 155	et:am	[I
    //   4932: iconst_5
    //   4933: iaload
    //   4934: getstatic 155	et:am	[I
    //   4937: sipush 189
    //   4940: iaload
    //   4941: sastore
    //   4942: aastore
    //   4943: getstatic 184	et:m	[[S
    //   4946: getstatic 155	et:am	[I
    //   4949: bipush 88
    //   4951: iaload
    //   4952: getstatic 155	et:am	[I
    //   4955: iconst_1
    //   4956: iaload
    //   4957: newarray <illegal type>
    //   4959: dup
    //   4960: getstatic 155	et:am	[I
    //   4963: iconst_2
    //   4964: iaload
    //   4965: getstatic 155	et:am	[I
    //   4968: bipush 96
    //   4970: iaload
    //   4971: sastore
    //   4972: dup
    //   4973: getstatic 155	et:am	[I
    //   4976: iconst_5
    //   4977: iaload
    //   4978: getstatic 155	et:am	[I
    //   4981: sipush 189
    //   4984: iaload
    //   4985: sastore
    //   4986: aastore
    //   4987: getstatic 184	et:m	[[S
    //   4990: getstatic 155	et:am	[I
    //   4993: sipush 188
    //   4996: iaload
    //   4997: getstatic 155	et:am	[I
    //   5000: iconst_1
    //   5001: iaload
    //   5002: newarray <illegal type>
    //   5004: dup
    //   5005: getstatic 155	et:am	[I
    //   5008: iconst_2
    //   5009: iaload
    //   5010: getstatic 155	et:am	[I
    //   5013: sipush 187
    //   5016: iaload
    //   5017: sastore
    //   5018: dup
    //   5019: getstatic 155	et:am	[I
    //   5022: iconst_5
    //   5023: iaload
    //   5024: getstatic 155	et:am	[I
    //   5027: sipush 189
    //   5030: iaload
    //   5031: sastore
    //   5032: aastore
    //   5033: getstatic 184	et:m	[[S
    //   5036: getstatic 155	et:am	[I
    //   5039: sipush 189
    //   5042: iaload
    //   5043: getstatic 155	et:am	[I
    //   5046: iconst_2
    //   5047: iaload
    //   5048: newarray <illegal type>
    //   5050: aastore
    //   5051: getstatic 184	et:m	[[S
    //   5054: getstatic 155	et:am	[I
    //   5057: bipush 32
    //   5059: iaload
    //   5060: getstatic 155	et:am	[I
    //   5063: iconst_5
    //   5064: iaload
    //   5065: newarray <illegal type>
    //   5067: dup
    //   5068: getstatic 155	et:am	[I
    //   5071: iconst_2
    //   5072: iaload
    //   5073: getstatic 155	et:am	[I
    //   5076: bipush 33
    //   5078: iaload
    //   5079: sastore
    //   5080: aastore
    //   5081: getstatic 184	et:m	[[S
    //   5084: getstatic 155	et:am	[I
    //   5087: bipush 33
    //   5089: iaload
    //   5090: getstatic 155	et:am	[I
    //   5093: iconst_1
    //   5094: iaload
    //   5095: newarray <illegal type>
    //   5097: dup
    //   5098: getstatic 155	et:am	[I
    //   5101: iconst_2
    //   5102: iaload
    //   5103: getstatic 155	et:am	[I
    //   5106: bipush 32
    //   5108: iaload
    //   5109: sastore
    //   5110: dup
    //   5111: getstatic 155	et:am	[I
    //   5114: iconst_5
    //   5115: iaload
    //   5116: getstatic 155	et:am	[I
    //   5119: bipush 34
    //   5121: iaload
    //   5122: sastore
    //   5123: aastore
    //   5124: getstatic 184	et:m	[[S
    //   5127: getstatic 155	et:am	[I
    //   5130: bipush 34
    //   5132: iaload
    //   5133: getstatic 155	et:am	[I
    //   5136: iconst_5
    //   5137: iaload
    //   5138: newarray <illegal type>
    //   5140: dup
    //   5141: getstatic 155	et:am	[I
    //   5144: iconst_2
    //   5145: iaload
    //   5146: getstatic 155	et:am	[I
    //   5149: bipush 33
    //   5151: iaload
    //   5152: sastore
    //   5153: aastore
    //   5154: getstatic 184	et:m	[[S
    //   5157: getstatic 155	et:am	[I
    //   5160: bipush 35
    //   5162: iaload
    //   5163: getstatic 155	et:am	[I
    //   5166: iconst_5
    //   5167: iaload
    //   5168: newarray <illegal type>
    //   5170: dup
    //   5171: getstatic 155	et:am	[I
    //   5174: iconst_2
    //   5175: iaload
    //   5176: getstatic 155	et:am	[I
    //   5179: bipush 109
    //   5181: iaload
    //   5182: sastore
    //   5183: aastore
    //   5184: getstatic 184	et:m	[[S
    //   5187: getstatic 155	et:am	[I
    //   5190: bipush 109
    //   5192: iaload
    //   5193: getstatic 155	et:am	[I
    //   5196: iconst_1
    //   5197: iaload
    //   5198: newarray <illegal type>
    //   5200: dup
    //   5201: getstatic 155	et:am	[I
    //   5204: iconst_2
    //   5205: iaload
    //   5206: getstatic 155	et:am	[I
    //   5209: bipush 35
    //   5211: iaload
    //   5212: sastore
    //   5213: dup
    //   5214: getstatic 155	et:am	[I
    //   5217: iconst_5
    //   5218: iaload
    //   5219: getstatic 155	et:am	[I
    //   5222: bipush 111
    //   5224: iaload
    //   5225: sastore
    //   5226: aastore
    //   5227: getstatic 184	et:m	[[S
    //   5230: getstatic 155	et:am	[I
    //   5233: bipush 111
    //   5235: iaload
    //   5236: getstatic 155	et:am	[I
    //   5239: iconst_1
    //   5240: iaload
    //   5241: newarray <illegal type>
    //   5243: dup
    //   5244: getstatic 155	et:am	[I
    //   5247: iconst_2
    //   5248: iaload
    //   5249: getstatic 155	et:am	[I
    //   5252: bipush 109
    //   5254: iaload
    //   5255: sastore
    //   5256: dup
    //   5257: getstatic 155	et:am	[I
    //   5260: iconst_5
    //   5261: iaload
    //   5262: getstatic 155	et:am	[I
    //   5265: bipush 38
    //   5267: iaload
    //   5268: sastore
    //   5269: aastore
    //   5270: getstatic 184	et:m	[[S
    //   5273: getstatic 155	et:am	[I
    //   5276: bipush 38
    //   5278: iaload
    //   5279: getstatic 155	et:am	[I
    //   5282: iconst_5
    //   5283: iaload
    //   5284: newarray <illegal type>
    //   5286: dup
    //   5287: getstatic 155	et:am	[I
    //   5290: iconst_2
    //   5291: iaload
    //   5292: getstatic 155	et:am	[I
    //   5295: bipush 111
    //   5297: iaload
    //   5298: sastore
    //   5299: aastore
    //   5300: getstatic 184	et:m	[[S
    //   5303: getstatic 155	et:am	[I
    //   5306: bipush 39
    //   5308: iaload
    //   5309: getstatic 155	et:am	[I
    //   5312: iconst_5
    //   5313: iaload
    //   5314: newarray <illegal type>
    //   5316: dup
    //   5317: getstatic 155	et:am	[I
    //   5320: iconst_2
    //   5321: iaload
    //   5322: getstatic 155	et:am	[I
    //   5325: bipush 66
    //   5327: iaload
    //   5328: sastore
    //   5329: aastore
    //   5330: getstatic 184	et:m	[[S
    //   5333: getstatic 155	et:am	[I
    //   5336: bipush 66
    //   5338: iaload
    //   5339: getstatic 155	et:am	[I
    //   5342: iconst_3
    //   5343: iaload
    //   5344: newarray <illegal type>
    //   5346: dup
    //   5347: getstatic 155	et:am	[I
    //   5350: iconst_2
    //   5351: iaload
    //   5352: getstatic 155	et:am	[I
    //   5355: bipush 39
    //   5357: iaload
    //   5358: sastore
    //   5359: dup
    //   5360: getstatic 155	et:am	[I
    //   5363: iconst_5
    //   5364: iaload
    //   5365: getstatic 155	et:am	[I
    //   5368: sipush 190
    //   5371: iaload
    //   5372: sastore
    //   5373: dup
    //   5374: getstatic 155	et:am	[I
    //   5377: iconst_1
    //   5378: iaload
    //   5379: getstatic 155	et:am	[I
    //   5382: bipush 67
    //   5384: iaload
    //   5385: sastore
    //   5386: dup
    //   5387: getstatic 155	et:am	[I
    //   5390: bipush 6
    //   5392: iaload
    //   5393: getstatic 155	et:am	[I
    //   5396: bipush 68
    //   5398: iaload
    //   5399: sastore
    //   5400: aastore
    //   5401: getstatic 184	et:m	[[S
    //   5404: getstatic 155	et:am	[I
    //   5407: bipush 67
    //   5409: iaload
    //   5410: getstatic 155	et:am	[I
    //   5413: iconst_1
    //   5414: iaload
    //   5415: newarray <illegal type>
    //   5417: dup
    //   5418: getstatic 155	et:am	[I
    //   5421: iconst_2
    //   5422: iaload
    //   5423: getstatic 155	et:am	[I
    //   5426: bipush 66
    //   5428: iaload
    //   5429: sastore
    //   5430: dup
    //   5431: getstatic 155	et:am	[I
    //   5434: iconst_5
    //   5435: iaload
    //   5436: getstatic 155	et:am	[I
    //   5439: bipush 62
    //   5441: iaload
    //   5442: sastore
    //   5443: aastore
    //   5444: getstatic 184	et:m	[[S
    //   5447: getstatic 155	et:am	[I
    //   5450: sipush 190
    //   5453: iaload
    //   5454: getstatic 155	et:am	[I
    //   5457: iconst_1
    //   5458: iaload
    //   5459: newarray <illegal type>
    //   5461: dup
    //   5462: getstatic 155	et:am	[I
    //   5465: iconst_2
    //   5466: iaload
    //   5467: getstatic 155	et:am	[I
    //   5470: bipush 66
    //   5472: iaload
    //   5473: sastore
    //   5474: dup
    //   5475: getstatic 155	et:am	[I
    //   5478: iconst_5
    //   5479: iaload
    //   5480: getstatic 155	et:am	[I
    //   5483: bipush 62
    //   5485: iaload
    //   5486: sastore
    //   5487: aastore
    //   5488: getstatic 184	et:m	[[S
    //   5491: getstatic 155	et:am	[I
    //   5494: bipush 68
    //   5496: iaload
    //   5497: getstatic 155	et:am	[I
    //   5500: iconst_1
    //   5501: iaload
    //   5502: newarray <illegal type>
    //   5504: dup
    //   5505: getstatic 155	et:am	[I
    //   5508: iconst_2
    //   5509: iaload
    //   5510: getstatic 155	et:am	[I
    //   5513: bipush 66
    //   5515: iaload
    //   5516: sastore
    //   5517: dup
    //   5518: getstatic 155	et:am	[I
    //   5521: iconst_5
    //   5522: iaload
    //   5523: getstatic 155	et:am	[I
    //   5526: bipush 62
    //   5528: iaload
    //   5529: sastore
    //   5530: aastore
    //   5531: getstatic 184	et:m	[[S
    //   5534: getstatic 155	et:am	[I
    //   5537: bipush 62
    //   5539: iaload
    //   5540: getstatic 155	et:am	[I
    //   5543: iconst_3
    //   5544: iaload
    //   5545: newarray <illegal type>
    //   5547: dup
    //   5548: getstatic 155	et:am	[I
    //   5551: iconst_2
    //   5552: iaload
    //   5553: getstatic 155	et:am	[I
    //   5556: sipush 190
    //   5559: iaload
    //   5560: sastore
    //   5561: dup
    //   5562: getstatic 155	et:am	[I
    //   5565: iconst_5
    //   5566: iaload
    //   5567: getstatic 155	et:am	[I
    //   5570: bipush 68
    //   5572: iaload
    //   5573: sastore
    //   5574: dup
    //   5575: getstatic 155	et:am	[I
    //   5578: iconst_1
    //   5579: iaload
    //   5580: getstatic 155	et:am	[I
    //   5583: bipush 114
    //   5585: iaload
    //   5586: sastore
    //   5587: dup
    //   5588: getstatic 155	et:am	[I
    //   5591: bipush 6
    //   5593: iaload
    //   5594: getstatic 155	et:am	[I
    //   5597: bipush 67
    //   5599: iaload
    //   5600: sastore
    //   5601: aastore
    //   5602: getstatic 184	et:m	[[S
    //   5605: getstatic 155	et:am	[I
    //   5608: bipush 114
    //   5610: iaload
    //   5611: getstatic 155	et:am	[I
    //   5614: iconst_5
    //   5615: iaload
    //   5616: newarray <illegal type>
    //   5618: dup
    //   5619: getstatic 155	et:am	[I
    //   5622: iconst_2
    //   5623: iaload
    //   5624: getstatic 155	et:am	[I
    //   5627: bipush 62
    //   5629: iaload
    //   5630: sastore
    //   5631: aastore
    //   5632: getstatic 184	et:m	[[S
    //   5635: getstatic 155	et:am	[I
    //   5638: bipush 115
    //   5640: iaload
    //   5641: getstatic 155	et:am	[I
    //   5644: bipush 6
    //   5646: iaload
    //   5647: newarray <illegal type>
    //   5649: dup
    //   5650: getstatic 155	et:am	[I
    //   5653: iconst_2
    //   5654: iaload
    //   5655: getstatic 155	et:am	[I
    //   5658: bipush 99
    //   5660: iaload
    //   5661: sastore
    //   5662: dup
    //   5663: getstatic 155	et:am	[I
    //   5666: iconst_5
    //   5667: iaload
    //   5668: getstatic 155	et:am	[I
    //   5671: bipush 98
    //   5673: iaload
    //   5674: sastore
    //   5675: dup
    //   5676: getstatic 155	et:am	[I
    //   5679: iconst_1
    //   5680: iaload
    //   5681: getstatic 155	et:am	[I
    //   5684: bipush 69
    //   5686: iaload
    //   5687: sastore
    //   5688: aastore
    //   5689: getstatic 184	et:m	[[S
    //   5692: getstatic 155	et:am	[I
    //   5695: bipush 98
    //   5697: iaload
    //   5698: getstatic 155	et:am	[I
    //   5701: iconst_1
    //   5702: iaload
    //   5703: newarray <illegal type>
    //   5705: dup
    //   5706: getstatic 155	et:am	[I
    //   5709: iconst_2
    //   5710: iaload
    //   5711: getstatic 155	et:am	[I
    //   5714: bipush 115
    //   5716: iaload
    //   5717: sastore
    //   5718: dup
    //   5719: getstatic 155	et:am	[I
    //   5722: iconst_5
    //   5723: iaload
    //   5724: getstatic 155	et:am	[I
    //   5727: bipush 70
    //   5729: iaload
    //   5730: sastore
    //   5731: aastore
    //   5732: getstatic 184	et:m	[[S
    //   5735: getstatic 155	et:am	[I
    //   5738: bipush 99
    //   5740: iaload
    //   5741: getstatic 155	et:am	[I
    //   5744: iconst_1
    //   5745: iaload
    //   5746: newarray <illegal type>
    //   5748: dup
    //   5749: getstatic 155	et:am	[I
    //   5752: iconst_2
    //   5753: iaload
    //   5754: getstatic 155	et:am	[I
    //   5757: bipush 115
    //   5759: iaload
    //   5760: sastore
    //   5761: dup
    //   5762: getstatic 155	et:am	[I
    //   5765: iconst_5
    //   5766: iaload
    //   5767: getstatic 155	et:am	[I
    //   5770: bipush 70
    //   5772: iaload
    //   5773: sastore
    //   5774: aastore
    //   5775: getstatic 184	et:m	[[S
    //   5778: getstatic 155	et:am	[I
    //   5781: bipush 69
    //   5783: iaload
    //   5784: getstatic 155	et:am	[I
    //   5787: iconst_1
    //   5788: iaload
    //   5789: newarray <illegal type>
    //   5791: dup
    //   5792: getstatic 155	et:am	[I
    //   5795: iconst_2
    //   5796: iaload
    //   5797: getstatic 155	et:am	[I
    //   5800: bipush 115
    //   5802: iaload
    //   5803: sastore
    //   5804: dup
    //   5805: getstatic 155	et:am	[I
    //   5808: iconst_5
    //   5809: iaload
    //   5810: getstatic 155	et:am	[I
    //   5813: bipush 70
    //   5815: iaload
    //   5816: sastore
    //   5817: aastore
    //   5818: getstatic 184	et:m	[[S
    //   5821: getstatic 155	et:am	[I
    //   5824: bipush 70
    //   5826: iaload
    //   5827: getstatic 155	et:am	[I
    //   5830: bipush 6
    //   5832: iaload
    //   5833: newarray <illegal type>
    //   5835: dup
    //   5836: getstatic 155	et:am	[I
    //   5839: iconst_2
    //   5840: iaload
    //   5841: getstatic 155	et:am	[I
    //   5844: bipush 98
    //   5846: iaload
    //   5847: sastore
    //   5848: dup
    //   5849: getstatic 155	et:am	[I
    //   5852: iconst_5
    //   5853: iaload
    //   5854: getstatic 155	et:am	[I
    //   5857: bipush 99
    //   5859: iaload
    //   5860: sastore
    //   5861: dup
    //   5862: getstatic 155	et:am	[I
    //   5865: iconst_1
    //   5866: iaload
    //   5867: getstatic 155	et:am	[I
    //   5870: bipush 69
    //   5872: iaload
    //   5873: sastore
    //   5874: aastore
    //   5875: getstatic 184	et:m	[[S
    //   5878: getstatic 155	et:am	[I
    //   5881: bipush 71
    //   5883: iaload
    //   5884: getstatic 155	et:am	[I
    //   5887: iconst_2
    //   5888: iaload
    //   5889: newarray <illegal type>
    //   5891: aastore
    //   5892: getstatic 184	et:m	[[S
    //   5895: getstatic 155	et:am	[I
    //   5898: bipush 63
    //   5900: iaload
    //   5901: getstatic 155	et:am	[I
    //   5904: iconst_2
    //   5905: iaload
    //   5906: newarray <illegal type>
    //   5908: aastore
    //   5909: getstatic 184	et:m	[[S
    //   5912: getstatic 155	et:am	[I
    //   5915: bipush 72
    //   5917: iaload
    //   5918: getstatic 155	et:am	[I
    //   5921: iconst_5
    //   5922: iaload
    //   5923: newarray <illegal type>
    //   5925: dup
    //   5926: getstatic 155	et:am	[I
    //   5929: iconst_2
    //   5930: iaload
    //   5931: getstatic 155	et:am	[I
    //   5934: bipush 73
    //   5936: iaload
    //   5937: sastore
    //   5938: aastore
    //   5939: getstatic 184	et:m	[[S
    //   5942: getstatic 155	et:am	[I
    //   5945: bipush 73
    //   5947: iaload
    //   5948: getstatic 155	et:am	[I
    //   5951: iconst_5
    //   5952: iaload
    //   5953: newarray <illegal type>
    //   5955: dup
    //   5956: getstatic 155	et:am	[I
    //   5959: iconst_2
    //   5960: iaload
    //   5961: getstatic 155	et:am	[I
    //   5964: bipush 72
    //   5966: iaload
    //   5967: sastore
    //   5968: aastore
    //   5969: getstatic 184	et:m	[[S
    //   5972: getstatic 155	et:am	[I
    //   5975: bipush 80
    //   5977: iaload
    //   5978: getstatic 155	et:am	[I
    //   5981: iconst_5
    //   5982: iaload
    //   5983: newarray <illegal type>
    //   5985: dup
    //   5986: getstatic 155	et:am	[I
    //   5989: iconst_2
    //   5990: iaload
    //   5991: getstatic 155	et:am	[I
    //   5994: bipush 81
    //   5996: iaload
    //   5997: sastore
    //   5998: aastore
    //   5999: getstatic 184	et:m	[[S
    //   6002: getstatic 155	et:am	[I
    //   6005: bipush 81
    //   6007: iaload
    //   6008: getstatic 155	et:am	[I
    //   6011: iconst_1
    //   6012: iaload
    //   6013: newarray <illegal type>
    //   6015: dup
    //   6016: getstatic 155	et:am	[I
    //   6019: iconst_2
    //   6020: iaload
    //   6021: getstatic 155	et:am	[I
    //   6024: bipush 80
    //   6026: iaload
    //   6027: sastore
    //   6028: dup
    //   6029: getstatic 155	et:am	[I
    //   6032: iconst_5
    //   6033: iaload
    //   6034: getstatic 155	et:am	[I
    //   6037: bipush 40
    //   6039: iaload
    //   6040: sastore
    //   6041: aastore
    //   6042: getstatic 184	et:m	[[S
    //   6045: getstatic 155	et:am	[I
    //   6048: bipush 40
    //   6050: iaload
    //   6051: getstatic 155	et:am	[I
    //   6054: iconst_5
    //   6055: iaload
    //   6056: newarray <illegal type>
    //   6058: dup
    //   6059: getstatic 155	et:am	[I
    //   6062: iconst_2
    //   6063: iaload
    //   6064: getstatic 155	et:am	[I
    //   6067: bipush 81
    //   6069: iaload
    //   6070: sastore
    //   6071: aastore
    //   6072: getstatic 184	et:m	[[S
    //   6075: getstatic 155	et:am	[I
    //   6078: bipush 41
    //   6080: iaload
    //   6081: getstatic 155	et:am	[I
    //   6084: iconst_2
    //   6085: iaload
    //   6086: newarray <illegal type>
    //   6088: aastore
    //   6089: getstatic 184	et:m	[[S
    //   6092: getstatic 155	et:am	[I
    //   6095: bipush 42
    //   6097: iaload
    //   6098: getstatic 155	et:am	[I
    //   6101: iconst_2
    //   6102: iaload
    //   6103: newarray <illegal type>
    //   6105: aastore
    //   6106: getstatic 184	et:m	[[S
    //   6109: getstatic 155	et:am	[I
    //   6112: bipush 100
    //   6114: iaload
    //   6115: getstatic 155	et:am	[I
    //   6118: iconst_2
    //   6119: iaload
    //   6120: newarray <illegal type>
    //   6122: aastore
    //   6123: getstatic 184	et:m	[[S
    //   6126: getstatic 155	et:am	[I
    //   6129: bipush 43
    //   6131: iaload
    //   6132: getstatic 155	et:am	[I
    //   6135: iconst_2
    //   6136: iaload
    //   6137: newarray <illegal type>
    //   6139: aastore
    //   6140: getstatic 184	et:m	[[S
    //   6143: getstatic 155	et:am	[I
    //   6146: sipush 191
    //   6149: iaload
    //   6150: getstatic 155	et:am	[I
    //   6153: iconst_2
    //   6154: iaload
    //   6155: newarray <illegal type>
    //   6157: aastore
    //   6158: getstatic 184	et:m	[[S
    //   6161: getstatic 155	et:am	[I
    //   6164: sipush 192
    //   6167: iaload
    //   6168: getstatic 155	et:am	[I
    //   6171: iconst_2
    //   6172: iaload
    //   6173: newarray <illegal type>
    //   6175: aastore
    //   6176: getstatic 184	et:m	[[S
    //   6179: getstatic 155	et:am	[I
    //   6182: bipush 107
    //   6184: iaload
    //   6185: getstatic 155	et:am	[I
    //   6188: iconst_2
    //   6189: iaload
    //   6190: newarray <illegal type>
    //   6192: aastore
    //   6193: getstatic 184	et:m	[[S
    //   6196: getstatic 155	et:am	[I
    //   6199: bipush 106
    //   6201: iaload
    //   6202: getstatic 155	et:am	[I
    //   6205: iconst_2
    //   6206: iaload
    //   6207: newarray <illegal type>
    //   6209: aastore
    //   6210: getstatic 184	et:m	[[S
    //   6213: getstatic 155	et:am	[I
    //   6216: bipush 74
    //   6218: iaload
    //   6219: getstatic 155	et:am	[I
    //   6222: iconst_5
    //   6223: iaload
    //   6224: newarray <illegal type>
    //   6226: dup
    //   6227: getstatic 155	et:am	[I
    //   6230: iconst_2
    //   6231: iaload
    //   6232: getstatic 155	et:am	[I
    //   6235: bipush 75
    //   6237: iaload
    //   6238: sastore
    //   6239: aastore
    //   6240: getstatic 184	et:m	[[S
    //   6243: getstatic 155	et:am	[I
    //   6246: bipush 75
    //   6248: iaload
    //   6249: getstatic 155	et:am	[I
    //   6252: iconst_1
    //   6253: iaload
    //   6254: newarray <illegal type>
    //   6256: dup
    //   6257: getstatic 155	et:am	[I
    //   6260: iconst_2
    //   6261: iaload
    //   6262: getstatic 155	et:am	[I
    //   6265: bipush 74
    //   6267: iaload
    //   6268: sastore
    //   6269: dup
    //   6270: getstatic 155	et:am	[I
    //   6273: iconst_5
    //   6274: iaload
    //   6275: getstatic 155	et:am	[I
    //   6278: bipush 76
    //   6280: iaload
    //   6281: sastore
    //   6282: aastore
    //   6283: getstatic 184	et:m	[[S
    //   6286: getstatic 155	et:am	[I
    //   6289: bipush 76
    //   6291: iaload
    //   6292: getstatic 155	et:am	[I
    //   6295: iconst_1
    //   6296: iaload
    //   6297: newarray <illegal type>
    //   6299: dup
    //   6300: getstatic 155	et:am	[I
    //   6303: iconst_2
    //   6304: iaload
    //   6305: getstatic 155	et:am	[I
    //   6308: bipush 75
    //   6310: iaload
    //   6311: sastore
    //   6312: dup
    //   6313: getstatic 155	et:am	[I
    //   6316: iconst_5
    //   6317: iaload
    //   6318: getstatic 155	et:am	[I
    //   6321: bipush 55
    //   6323: iaload
    //   6324: sastore
    //   6325: aastore
    //   6326: getstatic 184	et:m	[[S
    //   6329: getstatic 155	et:am	[I
    //   6332: bipush 55
    //   6334: iaload
    //   6335: getstatic 155	et:am	[I
    //   6338: iconst_5
    //   6339: iaload
    //   6340: newarray <illegal type>
    //   6342: dup
    //   6343: getstatic 155	et:am	[I
    //   6346: iconst_2
    //   6347: iaload
    //   6348: getstatic 155	et:am	[I
    //   6351: bipush 76
    //   6353: iaload
    //   6354: sastore
    //   6355: aastore
    //   6356: getstatic 184	et:m	[[S
    //   6359: getstatic 155	et:am	[I
    //   6362: bipush 77
    //   6364: iaload
    //   6365: getstatic 155	et:am	[I
    //   6368: iconst_2
    //   6369: iaload
    //   6370: newarray <illegal type>
    //   6372: aastore
    //   6373: getstatic 184	et:m	[[S
    //   6376: getstatic 155	et:am	[I
    //   6379: bipush 78
    //   6381: iaload
    //   6382: getstatic 155	et:am	[I
    //   6385: iconst_2
    //   6386: iaload
    //   6387: newarray <illegal type>
    //   6389: aastore
    //   6390: getstatic 184	et:m	[[S
    //   6393: getstatic 155	et:am	[I
    //   6396: bipush 83
    //   6398: iaload
    //   6399: getstatic 155	et:am	[I
    //   6402: iconst_2
    //   6403: iaload
    //   6404: newarray <illegal type>
    //   6406: aastore
    //   6407: getstatic 184	et:m	[[S
    //   6410: getstatic 155	et:am	[I
    //   6413: bipush 84
    //   6415: iaload
    //   6416: getstatic 155	et:am	[I
    //   6419: iconst_2
    //   6420: iaload
    //   6421: newarray <illegal type>
    //   6423: aastore
    //   6424: getstatic 184	et:m	[[S
    //   6427: getstatic 155	et:am	[I
    //   6430: bipush 101
    //   6432: iaload
    //   6433: getstatic 155	et:am	[I
    //   6436: iconst_2
    //   6437: iaload
    //   6438: newarray <illegal type>
    //   6440: aastore
    //   6441: getstatic 184	et:m	[[S
    //   6444: getstatic 155	et:am	[I
    //   6447: bipush 85
    //   6449: iaload
    //   6450: getstatic 155	et:am	[I
    //   6453: iconst_5
    //   6454: iaload
    //   6455: newarray <illegal type>
    //   6457: dup
    //   6458: getstatic 155	et:am	[I
    //   6461: iconst_2
    //   6462: iaload
    //   6463: getstatic 155	et:am	[I
    //   6466: bipush 103
    //   6468: iaload
    //   6469: sastore
    //   6470: aastore
    //   6471: getstatic 184	et:m	[[S
    //   6474: getstatic 155	et:am	[I
    //   6477: bipush 82
    //   6479: iaload
    //   6480: getstatic 155	et:am	[I
    //   6483: iconst_5
    //   6484: iaload
    //   6485: newarray <illegal type>
    //   6487: dup
    //   6488: getstatic 155	et:am	[I
    //   6491: iconst_2
    //   6492: iaload
    //   6493: getstatic 155	et:am	[I
    //   6496: bipush 103
    //   6498: iaload
    //   6499: sastore
    //   6500: aastore
    //   6501: getstatic 184	et:m	[[S
    //   6504: getstatic 155	et:am	[I
    //   6507: bipush 102
    //   6509: iaload
    //   6510: getstatic 155	et:am	[I
    //   6513: iconst_5
    //   6514: iaload
    //   6515: newarray <illegal type>
    //   6517: dup
    //   6518: getstatic 155	et:am	[I
    //   6521: iconst_2
    //   6522: iaload
    //   6523: getstatic 155	et:am	[I
    //   6526: bipush 103
    //   6528: iaload
    //   6529: sastore
    //   6530: aastore
    //   6531: getstatic 184	et:m	[[S
    //   6534: getstatic 155	et:am	[I
    //   6537: sipush 193
    //   6540: iaload
    //   6541: getstatic 155	et:am	[I
    //   6544: iconst_5
    //   6545: iaload
    //   6546: newarray <illegal type>
    //   6548: dup
    //   6549: getstatic 155	et:am	[I
    //   6552: iconst_2
    //   6553: iaload
    //   6554: getstatic 155	et:am	[I
    //   6557: bipush 103
    //   6559: iaload
    //   6560: sastore
    //   6561: aastore
    //   6562: getstatic 184	et:m	[[S
    //   6565: getstatic 155	et:am	[I
    //   6568: bipush 103
    //   6570: iaload
    //   6571: getstatic 155	et:am	[I
    //   6574: iconst_3
    //   6575: iaload
    //   6576: newarray <illegal type>
    //   6578: dup
    //   6579: getstatic 155	et:am	[I
    //   6582: iconst_2
    //   6583: iaload
    //   6584: getstatic 155	et:am	[I
    //   6587: bipush 85
    //   6589: iaload
    //   6590: sastore
    //   6591: dup
    //   6592: getstatic 155	et:am	[I
    //   6595: iconst_5
    //   6596: iaload
    //   6597: getstatic 155	et:am	[I
    //   6600: bipush 82
    //   6602: iaload
    //   6603: sastore
    //   6604: dup
    //   6605: getstatic 155	et:am	[I
    //   6608: iconst_1
    //   6609: iaload
    //   6610: getstatic 155	et:am	[I
    //   6613: bipush 102
    //   6615: iaload
    //   6616: sastore
    //   6617: dup
    //   6618: getstatic 155	et:am	[I
    //   6621: bipush 6
    //   6623: iaload
    //   6624: getstatic 155	et:am	[I
    //   6627: sipush 193
    //   6630: iaload
    //   6631: sastore
    //   6632: aastore
    //   6633: getstatic 184	et:m	[[S
    //   6636: getstatic 155	et:am	[I
    //   6639: bipush 104
    //   6641: iaload
    //   6642: getstatic 155	et:am	[I
    //   6645: iconst_5
    //   6646: iaload
    //   6647: newarray <illegal type>
    //   6649: dup
    //   6650: getstatic 155	et:am	[I
    //   6653: iconst_2
    //   6654: iaload
    //   6655: getstatic 155	et:am	[I
    //   6658: bipush 110
    //   6660: iaload
    //   6661: sastore
    //   6662: aastore
    //   6663: getstatic 184	et:m	[[S
    //   6666: getstatic 155	et:am	[I
    //   6669: bipush 110
    //   6671: iaload
    //   6672: getstatic 155	et:am	[I
    //   6675: iconst_1
    //   6676: iaload
    //   6677: newarray <illegal type>
    //   6679: dup
    //   6680: getstatic 155	et:am	[I
    //   6683: iconst_2
    //   6684: iaload
    //   6685: getstatic 155	et:am	[I
    //   6688: bipush 104
    //   6690: iaload
    //   6691: sastore
    //   6692: dup
    //   6693: getstatic 155	et:am	[I
    //   6696: iconst_5
    //   6697: iaload
    //   6698: getstatic 155	et:am	[I
    //   6701: bipush 112
    //   6703: iaload
    //   6704: sastore
    //   6705: aastore
    //   6706: getstatic 184	et:m	[[S
    //   6709: getstatic 155	et:am	[I
    //   6712: bipush 112
    //   6714: iaload
    //   6715: getstatic 155	et:am	[I
    //   6718: iconst_1
    //   6719: iaload
    //   6720: newarray <illegal type>
    //   6722: dup
    //   6723: getstatic 155	et:am	[I
    //   6726: iconst_2
    //   6727: iaload
    //   6728: getstatic 155	et:am	[I
    //   6731: bipush 110
    //   6733: iaload
    //   6734: sastore
    //   6735: dup
    //   6736: getstatic 155	et:am	[I
    //   6739: iconst_5
    //   6740: iaload
    //   6741: getstatic 155	et:am	[I
    //   6744: bipush 105
    //   6746: iaload
    //   6747: sastore
    //   6748: aastore
    //   6749: getstatic 184	et:m	[[S
    //   6752: getstatic 155	et:am	[I
    //   6755: bipush 105
    //   6757: iaload
    //   6758: getstatic 155	et:am	[I
    //   6761: iconst_1
    //   6762: iaload
    //   6763: newarray <illegal type>
    //   6765: dup
    //   6766: getstatic 155	et:am	[I
    //   6769: iconst_2
    //   6770: iaload
    //   6771: getstatic 155	et:am	[I
    //   6774: bipush 112
    //   6776: iaload
    //   6777: sastore
    //   6778: dup
    //   6779: getstatic 155	et:am	[I
    //   6782: iconst_5
    //   6783: iaload
    //   6784: getstatic 155	et:am	[I
    //   6787: bipush 117
    //   6789: iaload
    //   6790: sastore
    //   6791: aastore
    //   6792: getstatic 184	et:m	[[S
    //   6795: getstatic 155	et:am	[I
    //   6798: bipush 117
    //   6800: iaload
    //   6801: getstatic 155	et:am	[I
    //   6804: iconst_1
    //   6805: iaload
    //   6806: newarray <illegal type>
    //   6808: dup
    //   6809: getstatic 155	et:am	[I
    //   6812: iconst_2
    //   6813: iaload
    //   6814: getstatic 155	et:am	[I
    //   6817: bipush 105
    //   6819: iaload
    //   6820: sastore
    //   6821: dup
    //   6822: getstatic 155	et:am	[I
    //   6825: iconst_5
    //   6826: iaload
    //   6827: getstatic 155	et:am	[I
    //   6830: sipush 194
    //   6833: iaload
    //   6834: sastore
    //   6835: aastore
    //   6836: getstatic 184	et:m	[[S
    //   6839: getstatic 155	et:am	[I
    //   6842: sipush 194
    //   6845: iaload
    //   6846: getstatic 155	et:am	[I
    //   6849: iconst_1
    //   6850: iaload
    //   6851: newarray <illegal type>
    //   6853: dup
    //   6854: getstatic 155	et:am	[I
    //   6857: iconst_2
    //   6858: iaload
    //   6859: getstatic 155	et:am	[I
    //   6862: bipush 117
    //   6864: iaload
    //   6865: sastore
    //   6866: dup
    //   6867: getstatic 155	et:am	[I
    //   6870: iconst_5
    //   6871: iaload
    //   6872: getstatic 155	et:am	[I
    //   6875: sipush 195
    //   6878: iaload
    //   6879: sastore
    //   6880: aastore
    //   6881: getstatic 184	et:m	[[S
    //   6884: getstatic 155	et:am	[I
    //   6887: sipush 195
    //   6890: iaload
    //   6891: getstatic 155	et:am	[I
    //   6894: iconst_1
    //   6895: iaload
    //   6896: newarray <illegal type>
    //   6898: dup
    //   6899: getstatic 155	et:am	[I
    //   6902: iconst_2
    //   6903: iaload
    //   6904: getstatic 155	et:am	[I
    //   6907: sipush 194
    //   6910: iaload
    //   6911: sastore
    //   6912: dup
    //   6913: getstatic 155	et:am	[I
    //   6916: iconst_5
    //   6917: iaload
    //   6918: getstatic 155	et:am	[I
    //   6921: sipush 196
    //   6924: iaload
    //   6925: sastore
    //   6926: aastore
    //   6927: getstatic 184	et:m	[[S
    //   6930: getstatic 155	et:am	[I
    //   6933: sipush 196
    //   6936: iaload
    //   6937: getstatic 155	et:am	[I
    //   6940: iconst_1
    //   6941: iaload
    //   6942: newarray <illegal type>
    //   6944: dup
    //   6945: getstatic 155	et:am	[I
    //   6948: iconst_2
    //   6949: iaload
    //   6950: getstatic 155	et:am	[I
    //   6953: sipush 195
    //   6956: iaload
    //   6957: sastore
    //   6958: dup
    //   6959: getstatic 155	et:am	[I
    //   6962: iconst_5
    //   6963: iaload
    //   6964: getstatic 155	et:am	[I
    //   6967: sipush 197
    //   6970: iaload
    //   6971: sastore
    //   6972: aastore
    //   6973: getstatic 184	et:m	[[S
    //   6976: getstatic 155	et:am	[I
    //   6979: sipush 197
    //   6982: iaload
    //   6983: getstatic 155	et:am	[I
    //   6986: iconst_1
    //   6987: iaload
    //   6988: newarray <illegal type>
    //   6990: dup
    //   6991: getstatic 155	et:am	[I
    //   6994: iconst_2
    //   6995: iaload
    //   6996: getstatic 155	et:am	[I
    //   6999: sipush 196
    //   7002: iaload
    //   7003: sastore
    //   7004: dup
    //   7005: getstatic 155	et:am	[I
    //   7008: iconst_5
    //   7009: iaload
    //   7010: getstatic 155	et:am	[I
    //   7013: sipush 198
    //   7016: iaload
    //   7017: sastore
    //   7018: aastore
    //   7019: getstatic 184	et:m	[[S
    //   7022: getstatic 155	et:am	[I
    //   7025: sipush 198
    //   7028: iaload
    //   7029: getstatic 155	et:am	[I
    //   7032: iconst_5
    //   7033: iaload
    //   7034: newarray <illegal type>
    //   7036: dup
    //   7037: getstatic 155	et:am	[I
    //   7040: iconst_2
    //   7041: iaload
    //   7042: getstatic 155	et:am	[I
    //   7045: sipush 197
    //   7048: iaload
    //   7049: sastore
    //   7050: aastore
    //   7051: getstatic 184	et:m	[[S
    //   7054: getstatic 155	et:am	[I
    //   7057: sipush 199
    //   7060: iaload
    //   7061: getstatic 155	et:am	[I
    //   7064: iconst_2
    //   7065: iaload
    //   7066: newarray <illegal type>
    //   7068: aastore
    //   7069: getstatic 184	et:m	[[S
    //   7072: getstatic 155	et:am	[I
    //   7075: sipush 138
    //   7078: iaload
    //   7079: getstatic 155	et:am	[I
    //   7082: iconst_2
    //   7083: iaload
    //   7084: newarray <illegal type>
    //   7086: aastore
    //   7087: getstatic 184	et:m	[[S
    //   7090: getstatic 155	et:am	[I
    //   7093: sipush 200
    //   7096: iaload
    //   7097: getstatic 155	et:am	[I
    //   7100: iconst_2
    //   7101: iaload
    //   7102: newarray <illegal type>
    //   7104: aastore
    //   7105: getstatic 184	et:m	[[S
    //   7108: getstatic 155	et:am	[I
    //   7111: sipush 201
    //   7114: iaload
    //   7115: getstatic 155	et:am	[I
    //   7118: iconst_2
    //   7119: iaload
    //   7120: newarray <illegal type>
    //   7122: aastore
    //   7123: getstatic 184	et:m	[[S
    //   7126: getstatic 155	et:am	[I
    //   7129: sipush 202
    //   7132: iaload
    //   7133: getstatic 155	et:am	[I
    //   7136: iconst_2
    //   7137: iaload
    //   7138: newarray <illegal type>
    //   7140: aastore
    //   7141: getstatic 184	et:m	[[S
    //   7144: getstatic 155	et:am	[I
    //   7147: sipush 203
    //   7150: iaload
    //   7151: getstatic 155	et:am	[I
    //   7154: iconst_2
    //   7155: iaload
    //   7156: newarray <illegal type>
    //   7158: aastore
    //   7159: getstatic 184	et:m	[[S
    //   7162: getstatic 155	et:am	[I
    //   7165: sipush 204
    //   7168: iaload
    //   7169: getstatic 155	et:am	[I
    //   7172: iconst_2
    //   7173: iaload
    //   7174: newarray <illegal type>
    //   7176: aastore
    //   7177: getstatic 184	et:m	[[S
    //   7180: getstatic 155	et:am	[I
    //   7183: sipush 205
    //   7186: iaload
    //   7187: getstatic 155	et:am	[I
    //   7190: iconst_2
    //   7191: iaload
    //   7192: newarray <illegal type>
    //   7194: aastore
    //   7195: getstatic 184	et:m	[[S
    //   7198: getstatic 155	et:am	[I
    //   7201: sipush 157
    //   7204: iaload
    //   7205: getstatic 155	et:am	[I
    //   7208: iconst_1
    //   7209: iaload
    //   7210: newarray <illegal type>
    //   7212: dup
    //   7213: getstatic 155	et:am	[I
    //   7216: iconst_2
    //   7217: iaload
    //   7218: getstatic 155	et:am	[I
    //   7221: sipush 158
    //   7224: iaload
    //   7225: sastore
    //   7226: dup
    //   7227: getstatic 155	et:am	[I
    //   7230: iconst_5
    //   7231: iaload
    //   7232: getstatic 155	et:am	[I
    //   7235: sipush 159
    //   7238: iaload
    //   7239: sastore
    //   7240: aastore
    //   7241: getstatic 184	et:m	[[S
    //   7244: getstatic 155	et:am	[I
    //   7247: sipush 158
    //   7250: iaload
    //   7251: getstatic 155	et:am	[I
    //   7254: iconst_1
    //   7255: iaload
    //   7256: newarray <illegal type>
    //   7258: dup
    //   7259: getstatic 155	et:am	[I
    //   7262: iconst_2
    //   7263: iaload
    //   7264: getstatic 155	et:am	[I
    //   7267: sipush 159
    //   7270: iaload
    //   7271: sastore
    //   7272: dup
    //   7273: getstatic 155	et:am	[I
    //   7276: iconst_5
    //   7277: iaload
    //   7278: getstatic 155	et:am	[I
    //   7281: sipush 157
    //   7284: iaload
    //   7285: sastore
    //   7286: aastore
    //   7287: getstatic 184	et:m	[[S
    //   7290: getstatic 155	et:am	[I
    //   7293: sipush 159
    //   7296: iaload
    //   7297: getstatic 155	et:am	[I
    //   7300: iconst_1
    //   7301: iaload
    //   7302: newarray <illegal type>
    //   7304: dup
    //   7305: getstatic 155	et:am	[I
    //   7308: iconst_2
    //   7309: iaload
    //   7310: getstatic 155	et:am	[I
    //   7313: sipush 157
    //   7316: iaload
    //   7317: sastore
    //   7318: dup
    //   7319: getstatic 155	et:am	[I
    //   7322: iconst_5
    //   7323: iaload
    //   7324: getstatic 155	et:am	[I
    //   7327: sipush 158
    //   7330: iaload
    //   7331: sastore
    //   7332: aastore
    //   7333: getstatic 184	et:m	[[S
    //   7336: getstatic 155	et:am	[I
    //   7339: sipush 155
    //   7342: iaload
    //   7343: getstatic 155	et:am	[I
    //   7346: bipush 6
    //   7348: iaload
    //   7349: newarray <illegal type>
    //   7351: dup
    //   7352: getstatic 155	et:am	[I
    //   7355: iconst_2
    //   7356: iaload
    //   7357: getstatic 155	et:am	[I
    //   7360: sipush 156
    //   7363: iaload
    //   7364: sastore
    //   7365: dup
    //   7366: getstatic 155	et:am	[I
    //   7369: iconst_5
    //   7370: iaload
    //   7371: getstatic 155	et:am	[I
    //   7374: sipush 206
    //   7377: iaload
    //   7378: sastore
    //   7379: dup
    //   7380: getstatic 155	et:am	[I
    //   7383: iconst_1
    //   7384: iaload
    //   7385: getstatic 155	et:am	[I
    //   7388: sipush 207
    //   7391: iaload
    //   7392: sastore
    //   7393: aastore
    //   7394: getstatic 184	et:m	[[S
    //   7397: getstatic 155	et:am	[I
    //   7400: sipush 206
    //   7403: iaload
    //   7404: getstatic 155	et:am	[I
    //   7407: iconst_5
    //   7408: iaload
    //   7409: newarray <illegal type>
    //   7411: dup
    //   7412: getstatic 155	et:am	[I
    //   7415: iconst_2
    //   7416: iaload
    //   7417: getstatic 155	et:am	[I
    //   7420: sipush 155
    //   7423: iaload
    //   7424: sastore
    //   7425: aastore
    //   7426: getstatic 184	et:m	[[S
    //   7429: getstatic 155	et:am	[I
    //   7432: sipush 156
    //   7435: iaload
    //   7436: getstatic 155	et:am	[I
    //   7439: iconst_5
    //   7440: iaload
    //   7441: newarray <illegal type>
    //   7443: dup
    //   7444: getstatic 155	et:am	[I
    //   7447: iconst_2
    //   7448: iaload
    //   7449: getstatic 155	et:am	[I
    //   7452: sipush 155
    //   7455: iaload
    //   7456: sastore
    //   7457: aastore
    //   7458: getstatic 184	et:m	[[S
    //   7461: getstatic 155	et:am	[I
    //   7464: sipush 207
    //   7467: iaload
    //   7468: getstatic 155	et:am	[I
    //   7471: iconst_5
    //   7472: iaload
    //   7473: newarray <illegal type>
    //   7475: dup
    //   7476: getstatic 155	et:am	[I
    //   7479: iconst_2
    //   7480: iaload
    //   7481: getstatic 155	et:am	[I
    //   7484: sipush 155
    //   7487: iaload
    //   7488: sastore
    //   7489: aastore
    //   7490: getstatic 155	et:am	[I
    //   7493: bipush 126
    //   7495: iaload
    //   7496: putstatic 193	et:x	I
    //   7499: getstatic 155	et:am	[I
    //   7502: iconst_2
    //   7503: iaload
    //   7504: putstatic 192	et:w	Z
    //   7507: getstatic 155	et:am	[I
    //   7510: iconst_2
    //   7511: iaload
    //   7512: putstatic 144	et:a	Z
    //   7515: new 86	java/lang/Object
    //   7518: dup
    //   7519: invokespecial 286	java/lang/Object:<init>	()V
    //   7522: putstatic 170	et:ba	Ljava/lang/Object;
    //   7525: getstatic 155	et:am	[I
    //   7528: sipush 172
    //   7531: iaload
    //   7532: anewarray 46	[B
    //   7535: putstatic 154	et:al	[[B
    //   7538: getstatic 155	et:am	[I
    //   7541: iconst_2
    //   7542: iaload
    //   7543: istore_0
    //   7544: iload_0
    //   7545: getstatic 155	et:am	[I
    //   7548: sipush 172
    //   7551: iaload
    //   7552: invokestatic 256	et:h	(II)Z
    //   7555: ifeq +246 -> 7801
    //   7558: iload_0
    //   7559: istore_1
    //   7560: aconst_null
    //   7561: astore_2
    //   7562: ldc 24
    //   7564: invokevirtual 287	java/lang/Object:getClass	()Ljava/lang/Class;
    //   7567: ldc 30
    //   7569: iload_1
    //   7570: invokestatic 292	java/lang/String:valueOf	(I)Ljava/lang/String;
    //   7573: invokevirtual 290	java/lang/String:concat	(Ljava/lang/String;)Ljava/lang/String;
    //   7576: invokevirtual 283	java/lang/Class:getResourceAsStream	(Ljava/lang/String;)Ljava/io/InputStream;
    //   7579: astore_2
    //   7580: getstatic 154	et:al	[[B
    //   7583: iload_1
    //   7584: aload_2
    //   7585: invokevirtual 279	java/io/InputStream:available	()I
    //   7588: newarray <illegal type>
    //   7590: aastore
    //   7591: aload_2
    //   7592: getstatic 154	et:al	[[B
    //   7595: iload_1
    //   7596: aaload
    //   7597: invokevirtual 281	java/io/InputStream:read	([B)I
    //   7600: ldc 24
    //   7602: invokevirtual 291	java/lang/String:length	()I
    //   7605: pop2
    //   7606: aload_2
    //   7607: invokevirtual 280	java/io/InputStream:close	()V
    //   7610: aload_2
    //   7611: invokevirtual 280	java/io/InputStream:close	()V
    //   7614: ldc 24
    //   7616: invokevirtual 291	java/lang/String:length	()I
    //   7619: pop
    //   7620: aconst_null
    //   7621: ifnull +155 -> 7776
    //   7624: return
    //   7625: ldc 24
    //   7627: invokevirtual 291	java/lang/String:length	()I
    //   7630: pop2
    //   7631: ldc 24
    //   7633: invokevirtual 291	java/lang/String:length	()I
    //   7636: pop
    //   7637: bipush 92
    //   7639: bipush 109
    //   7641: iadd
    //   7642: bipush 108
    //   7644: isub
    //   7645: bipush 68
    //   7647: iadd
    //   7648: sipush 152
    //   7651: sipush 143
    //   7654: iadd
    //   7655: sipush 143
    //   7658: isub
    //   7659: bipush 25
    //   7661: iadd
    //   7662: ixor
    //   7663: bipush 69
    //   7665: bipush 93
    //   7667: iadd
    //   7668: bipush 108
    //   7670: isub
    //   7671: bipush 84
    //   7673: iadd
    //   7674: bipush 41
    //   7676: bipush 68
    //   7678: iadd
    //   7679: iconst_1
    //   7680: isub
    //   7681: bipush 46
    //   7683: iadd
    //   7684: ixor
    //   7685: ldc 25
    //   7687: invokevirtual 291	java/lang/String:length	()I
    //   7690: ineg
    //   7691: ixor
    //   7692: iand
    //   7693: ifeq +83 -> 7776
    //   7696: return
    //   7697: dup
    //   7698: astore_1
    //   7699: invokevirtual 302	java/lang/Throwable:printStackTrace	()V
    //   7702: aload_2
    //   7703: invokevirtual 280	java/io/InputStream:close	()V
    //   7706: ldc 24
    //   7708: invokevirtual 291	java/lang/String:length	()I
    //   7711: pop
    //   7712: ldc 27
    //   7714: invokevirtual 291	java/lang/String:length	()I
    //   7717: ifne +59 -> 7776
    //   7720: return
    //   7721: ldc 24
    //   7723: invokevirtual 291	java/lang/String:length	()I
    //   7726: pop2
    //   7727: ldc 24
    //   7729: invokevirtual 291	java/lang/String:length	()I
    //   7732: pop
    //   7733: ldc 26
    //   7735: invokevirtual 291	java/lang/String:length	()I
    //   7738: ifge +38 -> 7776
    //   7741: return
    //   7742: astore_0
    //   7743: aload_2
    //   7744: invokevirtual 280	java/io/InputStream:close	()V
    //   7747: ldc 24
    //   7749: invokevirtual 291	java/lang/String:length	()I
    //   7752: pop
    //   7753: ldc 25
    //   7755: invokevirtual 291	java/lang/String:length	()I
    //   7758: ldc 25
    //   7760: invokevirtual 291	java/lang/String:length	()I
    //   7763: ineg
    //   7764: if_icmpgt +10 -> 7774
    //   7767: return
    //   7768: ldc 24
    //   7770: invokevirtual 291	java/lang/String:length	()I
    //   7773: pop2
    //   7774: aload_0
    //   7775: athrow
    //   7776: iinc 0 1
    //   7779: ldc 24
    //   7781: invokevirtual 291	java/lang/String:length	()I
    //   7784: pop
    //   7785: ldc 25
    //   7787: invokevirtual 291	java/lang/String:length	()I
    //   7790: ineg
    //   7791: ldc 25
    //   7793: invokevirtual 291	java/lang/String:length	()I
    //   7796: ineg
    //   7797: if_icmpeq -253 -> 7544
    //   7800: return
    //   7801: getstatic 155	et:am	[I
    //   7804: bipush 7
    //   7806: iaload
    //   7807: anewarray 93	javax/microedition/lcdui/Image
    //   7810: putstatic 152	et:aj	[Ljavax/microedition/lcdui/Image;
    //   7813: getstatic 155	et:am	[I
    //   7816: bipush 7
    //   7818: iaload
    //   7819: anewarray 93	javax/microedition/lcdui/Image
    //   7822: putstatic 168	et:az	[Ljavax/microedition/lcdui/Image;
    //   7825: return
    // Local variable table:
    //   start	length	slot	name	signature
    //   7543	16	0	i1	int
    //   7742	35	0	localObject	Object
    //   7559	37	1	i2	int
    //   7698	1	1	localException1	Exception
    //   7561	183	2	localInputStream	InputStream
    //   7625	1	5	localException2	Exception
    //   7697	1	6	localException3	Exception
    //   7721	1	7	localException4	Exception
    //   7768	1	8	localException5	Exception
    // Exception table:
    //   from	to	target	type
    //   7610	7614	7625	java/lang/Exception
    //   7562	7610	7697	java/lang/Exception
    //   7702	7706	7721	java/lang/Exception
    //   7562	7610	7742	finally
    //   7697	7702	7742	finally
    //   7743	7747	7768	java/lang/Exception
  }
  
  static
  {
    cs.a(174);
    f();
  }
  
  private static boolean i(int paramInt1, int paramInt2)
  {
    return paramInt1 > paramInt2;
  }
  
  private static boolean a(Object paramObject1, Object paramObject2)
  {
    return paramObject1 != paramObject2;
  }
  
  /* Error */
  private static int j(int paramInt1, int paramInt2)
  {
    // Byte code:
    //   0: getstatic 186	et:p	[I
    //   3: iload_1
    //   4: getstatic 148	et:ae	I
    //   7: imul
    //   8: iload_0
    //   9: iadd
    //   10: iaload
    //   11: ireturn
    //   12: ldc 24
    //   14: invokevirtual 291	java/lang/String:length	()I
    //   17: pop2
    //   18: getstatic 155	et:am	[I
    //   21: sipush 151
    //   24: iaload
    //   25: ireturn
    // Local variable table:
    //   start	length	slot	name	signature
    //   0	26	0	paramInt1	int
    //   0	26	1	paramInt2	int
    //   12	1	2	localException	Exception
    // Exception table:
    //   from	to	target	type
    //   0	11	12	java/lang/Exception
  }
  
  public static boolean e(int paramInt)
  {
    int i1 = o;
    x = paramInt;
    int i2;
    int i6;
    int i9;
    if ((s(i1)) && (h(i1, m.length)) && (s(paramInt)) && (h(paramInt, m.length)) && (r(m[i1].length)))
    {
      localObject4 = dt.k(am[2]);
      i2 = am[2];
      while (h(i2, at.length))
      {
        at[i2] = am[5];
        bd[i2] = am[126];
        ak[i2] = am[126];
        i2++;
        "".length();
        if ((0x5D ^ 0x3D ^ 0x61 ^ 0x5) == "   ".length()) {
          return (25 + 125 - 4 + 35 ^ 96 + '¢' - 191 + 106) & (0x70 ^ 0x41 ^ 0x67 ^ 0x4E ^ -" ".length());
        }
      }
      bd[i1] = am[2];
      label3312:
      label3762:
      do
      {
        do
        {
          int i10;
          if (t(at[paramInt]))
          {
            ci localci;
            (localci = new ci()).addElement(new Integer(paramInt));
            i6 = paramInt;
            while (l(i6, i1))
            {
              int i7;
              if (q(j(i10 = ak[i6])))
              {
                if ((q(j(i6))) && (l(i6, am[103])) && (l(i6, am[''])))
                {
                  i7 = am[5];
                  if (f(i6, am[10]))
                  {
                    i7 = am[5];
                    "".length();
                    if (null != null) {
                      return (0xCD ^ 0x87) & (0x50 ^ 0x1A ^ 0xFFFFFFFF);
                    }
                  }
                  else if (f(i6, am[52]))
                  {
                    i7 = am[1];
                    "".length();
                    if (-" ".length() < -" ".length()) {
                      return (0xCC ^ 0x8D) & (0xF5 ^ 0xB4 ^ 0xFFFFFFFF);
                    }
                  }
                  else if (f(i6, am[27]))
                  {
                    i7 = am[6];
                    "".length();
                    if (((0xD5 ^ 0xAF ^ 0x37 ^ 0x5F) & (0x8E ^ 0x8B ^ 0xA9 ^ 0xBE ^ -" ".length())) != 0) {
                      return (66 + 87 - -39 + 34 ^ 12 + 96 - 28 + 101) & ('»' + 16 - 34 + 30 ^ 47 + 66 - -6 + 25 ^ -" ".length());
                    }
                  }
                  else if (f(i6, am[53]))
                  {
                    i7 = am[3];
                    "".length();
                    if (('¨' + 107 - 137 + 39 ^ 72 + '' - 77 + 49) <= "   ".length()) {
                      return (0xEB ^ 0xB3 ^ " ".length()) & (73 + 32 - -121 + 4 ^ 127 + 87 - 25 + 2 ^ -" ".length());
                    }
                  }
                  else if (f(i6, am[48]))
                  {
                    i7 = am[7];
                    "".length();
                    if (-" ".length() != -" ".length()) {
                      return (0x91 ^ 0x89) & (0x5E ^ 0x46 ^ 0xFFFFFFFF);
                    }
                  }
                  else if (f(i6, am[15]))
                  {
                    i7 = am[8];
                    "".length();
                    if ("  ".length() != "  ".length()) {
                      return "  ".length() & ("  ".length() ^ -" ".length());
                    }
                  }
                  else if (f(i6, am['']))
                  {
                    i7 = am[28];
                  }
                  i10 = i10 | 0x80000000 | am[' '] | i7 << am[45] & am['¡'];
                  "".length();
                  if ((38 + 107 - 53 + 58 ^ 43 + 8 - -68 + 27) <= ((113 + 88 - 88 + 34 ^ '' + 30 - 163 + 196) & (0x5B ^ 0x46 ^ 0x49 ^ 0x2 ^ -" ".length()))) {
                    return (0x30 ^ 0x16 ^ 0xA1 ^ 0xC5) & (98 + 2 - 28 + 126 ^ 1 + 117 - 86 + 100 ^ -" ".length());
                  }
                }
                else if (f(i6, am[104]))
                {
                  i10 = i10 | 0x80000000 | am['¢'] | am['£'];
                  "".length();
                  if ("  ".length() == 0) {
                    return (122 + 1 - 116 + 149 ^ 16 + 103 - 16 + 70) & ('£' + 54 - 39 + 62 ^ 124 + 93 - 140 + 116 ^ -" ".length());
                  }
                }
              }
              else if (q(i(i10))) {
                if (q(i(i6)))
                {
                  i7 = am[2];
                  if (f(i6, am[5]))
                  {
                    i7 = am[2];
                    "".length();
                    if (" ".length() >= "  ".length()) {
                      return (0x2A ^ 0x7) & (0xA2 ^ 0x8F ^ 0xFFFFFFFF);
                    }
                  }
                  else if (f(i6, am[127]))
                  {
                    i7 = am[5];
                    "".length();
                    if ("   ".length() == "  ".length()) {
                      return (0xEA ^ 0xBA) & (0x60 ^ 0x30 ^ 0xFFFFFFFF);
                    }
                  }
                  else if (f(i6, am[94]))
                  {
                    i7 = am[1];
                  }
                  i10 = i10 | 0x80000000 | am['¤'] | i7 << am[45] & am['¡'];
                  "".length();
                  if (((0xDC ^ 0x99 ^ 0x9F ^ 0x98) & (0xE2 ^ 0xAA ^ 0xBC ^ 0xB6 ^ -" ".length())) < 0) {
                    return (0xDF ^ 0xBA ^ 0x2B ^ 0x19) & ('¿' + '' - 141 + 56 ^ 30 + 89 - 111 + 161 ^ -" ".length());
                  }
                }
                else if ((b(localObject4)) && (f(i6, ((fb)localObject4).f)))
                {
                  i7 = fn.fm;
                  i10 = i10 | 0x80000000 | am['¥'] | i7 << am[45] & am['¡'] | am['¦'];
                  "".length();
                  if ("   ".length() == 0) {
                    return (0xED ^ 0xB3) & (0x59 ^ 0x7 ^ 0xFFFFFFFF);
                  }
                }
                else
                {
                  switch (i6)
                  {
                  case 80: 
                    i10 = i10 | 0x80000000 | am['§'] | am[119];
                    "".length();
                    if ("   ".length() < 0) {
                      return (0xD9 ^ 0x85) & (0xFC ^ 0xA0 ^ 0xFFFFFFFF);
                    }
                    break;
                  case 91: 
                    i10 = i10 | 0x80000000 | am['£'] | am[119];
                    "".length();
                    if (((0x79 ^ 0x3A) & (0x68 ^ 0x2B ^ 0xFFFFFFFF)) > 0) {
                      return (0x4C ^ 0xE) & (0xF7 ^ 0xB5 ^ 0xFFFFFFFF);
                    }
                    break;
                  case 94: 
                    i10 = i10 | 0x80000000 | am['£'] | am[123];
                    "".length();
                    if ((32 + 75 - -25 + 27 ^ 5 + 62 - 7 + 95) <= -" ".length()) {
                      return (0x18 ^ 0x17 ^ 0x9 ^ 0x2F) & (0x6A ^ 0x44 ^ 0xA3 ^ 0xA4 ^ -" ".length());
                    }
                    break;
                  case 98: 
                    i7 = fn.fm + am[1];
                    i10 = i10 | 0x80000000 | am['¥'] | i7 << am[45] & am['¡'];
                    "".length();
                    if (((0x7F ^ 0x3F) & (0x4D ^ 0xD ^ 0xFFFFFFFF)) != 0) {
                      return (0x85 ^ 0xB9) & (0x40 ^ 0x7C ^ 0xFFFFFFFF);
                    }
                    break;
                  case 104: 
                    i7 = fn.fm + am[1];
                    i10 = i10 | 0x80000000 | am['¥'] | i7 << am[45] & am['¡'] | am[119];
                    "".length();
                    if (-"  ".length() > 0) {
                      return (0x59 ^ 0x19) & (0xD ^ 0x4D ^ 0xFFFFFFFF);
                    }
                    break;
                  case 105: 
                    i10 = i10 | 0x80000000 | am['£'] | am['¦'];
                    "".length();
                    if ("  ".length() < " ".length()) {
                      return (0xDC ^ 0x9F) & (0xF0 ^ 0xB3 ^ 0xFFFFFFFF);
                    }
                    break;
                  case 113: 
                    i7 = fn.fm + am[6];
                    i10 = i10 | 0x80000000 | am['¥'] | i7 << am[45] & am['¡'];
                    "".length();
                    if (null != null) {
                      return (2 + '' - 68 + 131 ^ 71 + 78 - 74 + 70) & ('' + 46 - 21 + 20 ^ 115 + 10 - -3 + 21 ^ -" ".length());
                    }
                    break;
                  case 114: 
                    i10 = i10 | 0x80000000 | am['£'] | am[124];
                    "".length();
                    if (null != null) {
                      return (0x25 ^ 0x60 ^ 0x2E ^ 0x7E) & (0x5B ^ 0x44 ^ 0x55 ^ 0x5F ^ -" ".length());
                    }
                    break;
                  case 125: 
                    i10 = i10 | 0x80000000 | am['£'] | am['¨'];
                    "".length();
                    if (((0xB4 ^ 0x8F ^ 0xB6 ^ 0x8A) & (0x22 ^ 0x1B ^ 0xFF ^ 0xC1 ^ -" ".length())) > (40 + 84 - 107 + 161 ^ '¢' + '' - 272 + 147)) {
                      return (0xC3 ^ 0x96 ^ 0xCA ^ 0xB1) & (" ".length() ^ 0xB0 ^ 0x9F ^ -" ".length());
                    }
                    break;
                  case 139: 
                    i10 = i10 | 0x80000000 | am['¢'] | am['£'];
                    "".length();
                    if ("  ".length() <= ((0x20 ^ 0x77) & (0x23 ^ 0x74 ^ 0xFFFFFFFF))) {
                      return (0x41 ^ 0x70) & (0x11 ^ 0x20 ^ 0xFFFFFFFF);
                    }
                    break;
                  case 157: 
                    i10 = i10 | 0x80000000 | am['£'] | am['©'];
                  }
                }
              }
              localci.addElement(new Integer(i10));
              i6 = ak[i6];
              "".length();
              if ("  ".length() == "   ".length()) {
                return (0x5A ^ 0x2B ^ 0x72 ^ 0x23) & (0x70 ^ 0x6B ^ 0x86 ^ 0xBD ^ -" ".length());
              }
            }
            localObject3 = new ci();
            i2 = localci.size() - am[5];
            while (s(i2))
            {
              ((ci)localObject3).addElement(localci.elementAt(i2));
              i2--;
              "".length();
              if (((0xE ^ 0x44) & (0xD8 ^ 0x92 ^ 0xFFFFFFFF)) != 0) {
                return (0x89 ^ 0xC6) & (0x35 ^ 0x7A ^ 0xFFFFFFFF);
              }
            }
            localObject1 = localObject3;
            "".length();
            if ("   ".length() != 0) {
              break;
            }
            return (0x57 ^ 0x59) & (0x61 ^ 0x6F ^ 0xFFFFFFFF);
          }
          int i3 = am[126];
          i9 = am[126];
          i2 = am[2];
          while (h(i2, m.length))
          {
            if ((q(at[i2])) && (l(bd[i2], am[126])) && ((!k(bd[i2], i3)) || (f(i3, am[126]))))
            {
              i3 = bd[i2];
              i9 = (short)i2;
            }
            i2++;
            "".length();
            if (null != null) {
              return (87 + 10 - -10 + 108 ^ 59 + '±' - 51 + 12) & (67 + 38 - 52 + 105 ^ 125 + 9 - 0 + 6 ^ -" ".length());
            }
          }
          if (f(i9, am[126]))
          {
            localObject1 = null;
            "".length();
            if ("  ".length() == "  ".length()) {
              break;
            }
            return (0x19 ^ 0x4) & (0xAC ^ 0xB1 ^ 0xFFFFFFFF);
          }
          at[i9] = am[2];
          int i4 = i(i9);
          Object localObject3 = m[i9];
          i2 = am[2];
          while (h(i2, localObject3.length))
          {
            i10 = localObject3[i2];
            if (q(at[i10]))
            {
              if (q(dt.g().aa))
              {
                i6 = dt.g().cj;
                if (((!l(i10, am[5])) || (!l(i10, am[127])) || (f(i10, am[94]))) && (h(i6, am[8])))
                {
                  i6 = am[2];
                  "".length();
                  if (((0x71 ^ 0x20) & (0x56 ^ 0x7 ^ 0xFFFFFFFF)) <= 0) {
                    break label3312;
                  }
                  return (0x88 ^ 0xA2) & (0x18 ^ 0x32 ^ 0xFFFFFFFF);
                }
                if (((!l(i10, am[10])) || (!l(i10, am[53])) || (f(i10, am['']))) && (h(i6, am[52])))
                {
                  i6 = am[2];
                  "".length();
                  if ("  ".length() >= -" ".length()) {
                    break label3312;
                  }
                  return (0x45 ^ 0xB) & (0x8E ^ 0xC0 ^ 0xFFFFFFFF);
                }
                if ((f(i10, am[48])) && (h(i6, am['ª'])))
                {
                  i6 = am[2];
                  "".length();
                  if ("  ".length() > " ".length()) {
                    break label3312;
                  }
                  return (0x56 ^ 0x42) & (0x2F ^ 0x3B ^ 0xFFFFFFFF);
                }
                if ((f(i10, am[15])) && (h(i6, am[59])))
                {
                  i6 = am[2];
                  "".length();
                  if (null == null) {
                    break label3312;
                  }
                  return (0x58 ^ 0x9 ^ 0x48 ^ 0x51) & (0x14 ^ 0x65 ^ 0x66 ^ 0x5F ^ -" ".length());
                }
                if ((f(i10, am[52])) && (h(i6, am[48])))
                {
                  i6 = am[2];
                  "".length();
                  if (null == null) {
                    break label3312;
                  }
                  return (0x19 ^ 0x5B) & (0x40 ^ 0x2 ^ 0xFFFFFFFF);
                }
                if ((f(i10, am[28])) && (h(i6, am[4])))
                {
                  i6 = am[2];
                  "".length();
                  if ("  ".length() != ((0x7D ^ 0x57) & (0x5C ^ 0x76 ^ 0xFFFFFFFF))) {
                    break label3312;
                  }
                  return (0x6B ^ 0x36) & (0x56 ^ 0xB ^ 0xFFFFFFFF);
                }
              }
              i6 = am[5];
              if ((q(i6)) && ((!q(i4)) || (!q(i(i10))) || (k(dt.g().cj, am[9]))) && ((!l(bd[i10], am[126])) || (i(bd[i10], bd[i9] + am[5]))))
              {
                bd[i9] += am[5];
                ak[i10] = i9;
              }
            }
            i2++;
            "".length();
            if ((0x56 ^ 0xD ^ 0xF8 ^ 0xA7) < 0) {
              return (0x7D ^ 0x63 ^ 0x1A ^ 0x35) & (0xA5 ^ 0xB2 ^ 0x95 ^ 0xB3 ^ -" ".length());
            }
          }
          if ((q(i4)) && (b(localObject4)) && (q(at[localObject4.f])) && ((!l(bd[localObject4.f], am[126])) || (i(bd[localObject4.f], bd[i9] + am[5]))))
          {
            bd[localObject4.f] = (bd[i9] + am[5]);
            ak[localObject4.f] = i9;
          }
          if ((q(dt.k)) && ((!l(bd[am['']], am[126])) || (i(bd[am['']], bd[i9] + am[5]))))
          {
            bd[am['']] = (bd[i9] + am[5]);
            ak[am['']] = i9;
            if (q(i4))
            {
              if (q(fn.df))
              {
                "".length();
                if (null == null) {
                  break label3762;
                }
                return (0x40 ^ 0xA ^ 0x9B ^ 0x84) & (0x23 ^ 0x4B ^ 0x29 ^ 0x14 ^ -" ".length());
              }
              i10 = (short)am[114];
              if ((!l(bd[i10], am[126])) || (i(bd[i10], bd[i9] + am[5])))
              {
                bd[i9] += am[5];
                ak[i10] = i9;
              }
            }
          }
        } while ((!q(dt.fk)) || ((l(bd[am[103]], am[126])) && (!i(bd[am[103]], bd[i9] + am[5]))));
        bd[am[103]] = (bd[i9] + am[5]);
        ak[am[103]] = i9;
        "".length();
      } while ("   ".length() != ((0x7 ^ 0x52) & (0xE9 ^ 0xBC ^ 0xFFFFFFFF)));
      return (0x10 ^ 0x6) & (0x7E ^ 0x68 ^ 0xFFFFFFFF);
    }
    Object localObject1 = null;
    Object localObject4 = localObject1;
    if (a(localObject1))
    {
      ae.a("Không thể chuyển map!", am[18], ax.l);
      ds.x = am[5];
      return am[2];
    }
    w = am[5];
    try
    {
      i6 = o;
      int i8 = am[5];
      while ((h(i8, ((Vector)localObject4).size())) && (q(w)) && (f(i6, o)))
      {
        int i5 = ((Integer)((ci)localObject4).elementAt(i8 - am[5])).intValue();
        i6 = ((Integer)((ci)localObject4).elementAt(i8)).intValue() & am[''];
        if (p(i5))
        {
          i9 = i5 >> am[108] & am[76];
          i2 = i5 >> am[45] & am[4];
          i5 = i5 >> am[51] & am[4];
          fn.c(i9, i2, i5);
          "".length();
          if (-" ".length() >= "  ".length()) {
            return (0x75 ^ 0x2F) & (0x30 ^ 0x6A ^ 0xFFFFFFFF);
          }
        }
        else
        {
          Object localObject2;
          if (((!k(i5, am[85])) || (i(i5, am[103]))) && (f(i6, am[103])))
          {
            if (r(dt.g().g))
            {
              ae.a("Hiếu chiến quá cao!", am[18], ax.l);
              return am[2];
            }
            if ((!b(localObject2 = dt.g(am['«']))) || (l(((ao)localObject2).j.f, am['«'])))
            {
              if ((q(dt.doa)) && (k(dt.g().ga, am[10])))
              {
                dl.ae().b(am[14], am['ª'], am[1]);
                cn.a();
                return am[2];
              }
              ae.a("Không đủ cổ lệnh!", am[18], ax.l);
              return am[2];
            }
            System.out.println("Dung co lenh");
            dl.ae().ad(((ao)localObject2).n);
            "".length();
            if (-" ".length() >= 0) {
              return (79 + 57 - -73 + 15 ^ '' + 37 - 22 + 2) & (108 + '' - 133 + 74 ^ 2 + 99 - 58 + 90 ^ -" ".length());
            }
          }
          else if (((!k(localObject2, am['¬'])) || (i(localObject2, am['­']))) && (f(i6, am[''])))
          {
            if (r(dt.g().g))
            {
              ae.a("Hiếu chiến quá cao!", am[18], ax.l);
              return am[2];
            }
            if ((!b(localObject2 = dt.g(am['®']))) || (l(((ao)localObject2).j.f, am['®'])))
            {
              if ((q(dt.bh)) && (k(dt.g().ga, am[10])))
              {
                dl.ae().b(am[14], am[30], am[1]);
                cn.a();
                return am[2];
              }
              ae.a("Không đủ cổ lệnh!", am[18], ax.l);
              return am[2];
            }
            System.out.println("Dung co lenh");
            dl.ae().ad(((ao)localObject2).n);
            "".length();
            if ((('' + 72 - 189 + 121 ^ 124 + 63 - 103 + 44) & (0xA1 ^ 0x87 ^ 0x87 ^ 0xA7 ^ -" ".length())) >= "   ".length()) {
              return (0x68 ^ 0x27 ^ 0xEE ^ 0xB3) & (109 + 62 - 58 + 71 ^ 97 + '' - 109 + 41 ^ -" ".length());
            }
          }
          else if ((q(localObject2)) && (l(localObject2, am[''])) && (l(localObject2, am[36])))
          {
            i2 = am[126];
            i9 = am[2];
            while (h(i9, m[localObject2].length)) {
              if (f(m[localObject2][i9], i6))
              {
                i2 = i9;
                "".length();
                if (((83 + 99 - 134 + 121 ^ 122 + 15 - 99 + 90) & ('£' + 114 - 133 + 20 ^ 37 + 47 - -46 + 11 ^ -" ".length())) != 0) {
                  return (0x38 ^ 0x67 ^ 0xA8 ^ 0x97) & (2 + 21 - -50 + 130 ^ 68 + 50 - 72 + 125 ^ -" ".length());
                }
              }
              else
              {
                i9++;
                "".length();
                if (((36 + 58 - 71 + 184 ^ 66 + 7 - 34 + 108) & (0xAA ^ 0x99 ^ 0xF1 ^ 0x9E ^ -" ".length())) > 0) {
                  return ((0x4F ^ 0x5E) & (0x89 ^ 0x98 ^ 0xFFFFFFFF) ^ 0x86 ^ 0x94) & (0x67 ^ 0x5C ^ 0x1B ^ 0x32 ^ -" ".length());
                }
              }
            }
            if (f(i2, am[126]))
            {
              ae.a("Không thể chuyển map!", am[18], ax.l);
              ds.x = am[5];
              return am[2];
            }
            b(i2);
            "".length();
            if ("   ".length() < 0) {
              return (0x6D ^ 0x8 ^ 0x95 ^ 0x93) & (0x40 ^ 0x4 ^ 0x9 ^ 0x2E ^ -" ".length());
            }
          }
          else if ((b(localObject2 = (fc)fn.al.elementAt(am[2]))) && (l(((dt)localObject2).ee, am[4])))
          {
            "".length();
            dt.g().bw = ((fc)localObject2);
            dl.ae().r(((fc)localObject2).go.a);
            dl.ae().c(((fc)localObject2).go.a, am[2], am[2]);
            dl.ae().l(((fc)localObject2).go.a, am[2]);
          }
        }
        if (l(o, i6)) {
          d();
        }
        Thread.sleep(100L);
        "".length();
        if ((0x7F ^ 0x50 ^ 0xAD ^ 0x86) <= "  ".length()) {
          return (75 + 102 - 51 + 78 ^ 11 + 90 - 60 + 134) & (0x74 ^ 0x12 ^ 0xBE ^ 0xBB ^ -" ".length());
        }
      }
      "".length();
      if (-" ".length() < -" ".length()) {
        return (0x5C ^ 0xB) & (0xC4 ^ 0x93 ^ 0xFFFFFFFF);
      }
    }
    catch (Exception localException2)
    {
      Exception localException1;
      (localException1 = localException2).printStackTrace();
      return am[2];
    }
    w = am[2];
    if (f(o, paramInt)) {
      return am[5];
    }
    return am[2];
  }
  
  public static boolean a(int paramInt1, int paramInt2, int[] paramArrayOfInt)
  {
    paramInt2 = k(paramInt2);
    if (q(a(paramInt1, paramInt2, am[1])))
    {
      paramArrayOfInt[am[2]] = paramInt1;
      paramArrayOfInt[am[5]] = paramInt2;
      return am[5];
    }
    int i1 = am[2];
    while (h(i1, am[7]))
    {
      int i2 = paramInt2 + i1 * am[108];
      int i3 = am[2];
      while (h(i3, am[7]))
      {
        int i4 = paramInt1 - am[''] + i3 * am[108];
        if ((h(i2, h)) && (i(i4, am[108])) && (h(i4, ab - am[108])) && (q(a(i4, i2, am[1]))))
        {
          paramArrayOfInt[am[2]] = i4;
          paramArrayOfInt[am[5]] = i2;
          return am[5];
        }
        i3++;
        "".length();
        if ("  ".length() != "  ".length()) {
          return (0x4D ^ 0x57 ^ 0x1B ^ 0x25) & (72 + 34 - -52 + 8 ^ 81 + 48 - 4 + 5 ^ -" ".length());
        }
      }
      i1++;
      "".length();
      if (null != null) {
        return "  ".length() & ("  ".length() ^ 0xFFFFFFFF);
      }
    }
    return am[2];
  }
  
  public static final void c(int paramInt1, int paramInt2)
  {
    int[] arrayOfInt = p;
    paramInt1 = paramInt2 / u * ae + paramInt1 / u;
    arrayOfInt[paramInt1] |= am[''];
  }
  
  public static boolean f(int paramInt)
  {
    if ((!l(paramInt, am[32])) || (!l(paramInt, am[33])) || (!l(paramInt, am[34])) || (!l(paramInt, am[35])) || (!l(paramInt, am[109])) || (!l(paramInt, am[111])) || (!l(paramInt, am[38])) || (!l(paramInt, am[115])) || (!l(paramInt, am[98])) || (!l(paramInt, am[99])) || (!l(paramInt, am[69])) || (!l(paramInt, am[70])) || (!l(paramInt, am[80])) || (!l(paramInt, am[81])) || (!l(paramInt, am[40])) || (!l(paramInt, am[74])) || (!l(paramInt, am[75])) || (!l(paramInt, am[76])) || (!l(paramInt, am[55])) || (!l(paramInt, am[''])) || (!l(paramInt, am[''])) || (f(paramInt, am['']))) {
      return am[5];
    }
    return am[2];
  }
  
  public static void g()
  {
    int i1 = am[5];
    while (h(i1, aj.length))
    {
      aj[i1] = aw.c("/t/" + i1 + ".png");
      az[i1] = aw.c("/t/mini_" + i1 + ".png");
      i1++;
      "".length();
      if (-" ".length() > " ".length()) {}
    }
  }
  
  private static boolean q(int paramInt)
  {
    return paramInt != 0;
  }
  
  public static void g(int paramInt)
  {
    h = ad * u;
    ab = ae * u;
    try
    {
      int i1 = am[2];
      while (h(i1, ae * ad))
      {
        int[] arrayOfInt;
        if ((b(r)) && (b(r.get(String.valueOf(i1))))) {
          (arrayOfInt = p)[i1] |= am[1];
        }
        if (f(paramInt, am[3]))
        {
          if ((!l(af[i1], am[5])) || (!l(af[i1], am[1])) || (!l(af[i1], am[6])) || (!l(af[i1], am[3])) || (!l(af[i1], am[7])) || (!l(af[i1], am[8])) || (!l(af[i1], am[9])) || (!l(af[i1], am[10])) || (!l(af[i1], am[11])) || (!l(af[i1], am[12])) || (!l(af[i1], am[13])) || (!l(af[i1], am[14])) || (!l(af[i1], am[15])) || (!l(af[i1], am[16])) || (!l(af[i1], am[17])) || (f(af[i1], am[18]))) {
            (arrayOfInt = p)[i1] |= am[1];
          }
          if ((!l(af[i1], am[9])) || (f(af[i1], am[19]))) {
            (arrayOfInt = p)[i1] |= am[3];
          }
          if ((!l(af[i1], am[10])) || (f(af[i1], am[0]))) {
            (arrayOfInt = p)[i1] |= am[20];
          }
          if ((!l(af[i1], am[13])) || (f(af[i1], am[14]))) {
            (arrayOfInt = p)[i1] |= am[21];
          }
          if ((!l(af[i1], am[22])) || (f(af[i1], am[23])))
          {
            (arrayOfInt = p)[i1] |= am[24];
            if (f(af[i1], am[25])) {
              (arrayOfInt = p)[i1] |= am[26];
            }
          }
        }
        if (f(paramInt, am[5]))
        {
          if (f(af[i1], am[27])) {
            av = af[i1] - am[5];
          }
          if ((!l(af[i1], am[5])) || (!l(af[i1], am[1])) || (!l(af[i1], am[6])) || (!l(af[i1], am[3])) || (!l(af[i1], am[7])) || (!l(af[i1], am[8])) || (!l(af[i1], am[28])) || (!l(af[i1], am[29])) || (!l(af[i1], am[30])) || (!l(af[i1], am[31])) || (!l(af[i1], am[32])) || (!l(af[i1], am[33])) || (!l(af[i1], am[34])) || (!l(af[i1], am[35])) || (!l(af[i1], am[36])) || (!l(af[i1], am[37])) || (!l(af[i1], am[38])) || (!l(af[i1], am[39])) || (!l(af[i1], am[40])) || (!l(af[i1], am[41])) || (!l(af[i1], am[42])) || (!l(af[i1], am[43])) || (f(af[i1], am[44]))) {
            (arrayOfInt = p)[i1] |= am[1];
          }
          if ((!l(af[i1], am[1])) || (!l(af[i1], am[6])) || (!l(af[i1], am[3])) || (!l(af[i1], am[7])) || (!l(af[i1], am[8])) || (!l(af[i1], am[45])) || (!l(af[i1], am[46])) || (!l(af[i1], am[27])) || (!l(af[i1], am[47])) || (!l(af[i1], am[29])) || (!l(af[i1], am[30])) || (!l(af[i1], am[48])) || (!l(af[i1], am[49])) || (f(af[i1], am[44]))) {
            (arrayOfInt = p)[i1] |= am[26];
          }
          if ((!l(af[i1], am[20])) || (!l(af[i1], am[9])) || (!l(af[i1], am[10])) || (!l(af[i1], am[0])) || (!l(af[i1], am[13])) || (!l(af[i1], am[14])) || (f(af[i1], am[50]))) {
            (arrayOfInt = p)[i1] |= am[51];
          }
          if (f(af[i1], am[52])) {
            (arrayOfInt = p)[i1] |= am[53];
          }
          if (f(af[i1], am[54])) {
            (arrayOfInt = p)[i1] |= am[55];
          }
          if ((!l(af[i1], am[30])) || (!l(af[i1], am[48])) || (f(af[i1], am[44]))) {
            (arrayOfInt = p)[i1] |= am[3];
          }
          if ((!l(af[i1], am[29])) || (!l(af[i1], am[49])) || (f(af[i1], am[44]))) {
            (arrayOfInt = p)[i1] |= am[20];
          }
          if (f(af[i1], am[56]))
          {
            (arrayOfInt = p)[i1] |= am[24];
            if (f(p[(i1 - ae)] & am[26], am[26])) {
              (arrayOfInt = p)[i1] |= am[26];
            }
          }
          if (f(af[i1], am[57])) {
            (arrayOfInt = p)[i1] |= am[58];
          }
          if (f(af[i1], am[28])) {
            (arrayOfInt = p)[i1] |= am[21];
          }
          if ((!l(af[i1], am[53])) || (!l(af[i1], am[59])) || (f(af[i1], am[60]))) {
            (arrayOfInt = p)[i1] |= am[61];
          }
        }
        if (f(paramInt, am[1]))
        {
          if ((!l(af[i1], am[27])) || (!l(af[i1], am[62])) || (f(af[i1], am[63]))) {
            av = af[i1] - am[5];
          }
          if ((!l(af[i1], am[5])) || (!l(af[i1], am[1])) || (!l(af[i1], am[6])) || (!l(af[i1], am[3])) || (!l(af[i1], am[7])) || (!l(af[i1], am[8])) || (!l(af[i1], am[28])) || (!l(af[i1], am[29])) || (!l(af[i1], am[30])) || (!l(af[i1], am[31])) || (!l(af[i1], am[44])) || (!l(af[i1], am[36])) || (!l(af[i1], am[22])) || (!l(af[i1], am[23])) || (!l(af[i1], am[25])) || (!l(af[i1], am[11])) || (!l(af[i1], am[64])) || (!l(af[i1], am[65])) || (!l(af[i1], am[39])) || (!l(af[i1], am[66])) || (!l(af[i1], am[67])) || (!l(af[i1], am[68])) || (!l(af[i1], am[62])) || (!l(af[i1], am[69])) || (!l(af[i1], am[70])) || (!l(af[i1], am[71])) || (!l(af[i1], am[72])) || (!l(af[i1], am[73])) || (!l(af[i1], am[40])) || (!l(af[i1], am[41])) || (!l(af[i1], am[74])) || (!l(af[i1], am[75])) || (!l(af[i1], am[76])) || (!l(af[i1], am[77])) || (f(af[i1], am[78]))) {
            (arrayOfInt = p)[i1] |= am[1];
          }
          if ((!l(af[i1], am[5])) || (!l(af[i1], am[6])) || (!l(af[i1], am[3])) || (!l(af[i1], am[7])) || (!l(af[i1], am[8])) || (!l(af[i1], am[45])) || (!l(af[i1], am[46])) || (!l(af[i1], am[27])) || (!l(af[i1], am[47])) || (!l(af[i1], am[29])) || (!l(af[i1], am[30])) || (!l(af[i1], am[48])) || (!l(af[i1], am[49])) || (!l(af[i1], am[79])) || (!l(af[i1], am[70])) || (!l(af[i1], am[63])) || (!l(af[i1], am[72])) || (!l(af[i1], am[73])) || (!l(af[i1], am[80])) || (!l(af[i1], am[81])) || (!l(af[i1], am[40])) || (!l(af[i1], am[76])) || (!l(af[i1], am[77])) || (f(af[i1], am[78]))) {
            (arrayOfInt = p)[i1] |= am[26];
          }
          if ((!l(af[i1], am[20])) || (!l(af[i1], am[9])) || (!l(af[i1], am[10])) || (!l(af[i1], am[0])) || (!l(af[i1], am[13])) || (!l(af[i1], am[14])) || (!l(af[i1], am[50])) || (f(af[i1], am[82]))) {
            (arrayOfInt = p)[i1] |= am[51];
          }
          if (f(af[i1], am[52])) {
            (arrayOfInt = p)[i1] |= am[53];
          }
          if (f(af[i1], am[54])) {
            (arrayOfInt = p)[i1] |= am[55];
          }
          if ((!l(af[i1], am[44])) || (!l(af[i1], am[30])) || (!l(af[i1], am[48])) || (!l(af[i1], am[76])) || (!l(af[i1], am[78])) || (f(af[i1], am[83]))) {
            (arrayOfInt = p)[i1] |= am[3];
          }
          if ((!l(af[i1], am[44])) || (!l(af[i1], am[29])) || (!l(af[i1], am[49])) || (!l(af[i1], am[76])) || (!l(af[i1], am[77])) || (f(af[i1], am[84]))) {
            (arrayOfInt = p)[i1] |= am[20];
          }
          if (f(af[i1], am[56]))
          {
            (arrayOfInt = p)[i1] |= am[24];
            if (f(p[(i1 - ae)] & am[26], am[26])) {
              (arrayOfInt = p)[i1] |= am[26];
            }
          }
          if (f(af[i1], am[85]))
          {
            (arrayOfInt = p)[i1] |= am[24];
            if (f(p[(i1 - ae)] & am[26], am[26])) {
              (arrayOfInt = p)[i1] |= am[26];
            }
          }
          if (f(af[i1], am[57])) {
            (arrayOfInt = p)[i1] |= am[58];
          }
          if (f(af[i1], am[28])) {
            (arrayOfInt = p)[i1] |= am[21];
          }
          if ((!l(af[i1], am[53])) || (!l(af[i1], am[59])) || (f(af[i1], am[60]))) {
            (arrayOfInt = p)[i1] |= am[61];
          }
          if ((!l(af[i1], am[44])) || (f(af[i1], am[76]))) {
            (arrayOfInt = p)[i1] |= am[86];
          }
        }
        if (f(paramInt, am[6]))
        {
          if ((!l(af[i1], am[0])) || (!l(af[i1], am[87])) || (!l(af[i1], am[88])) || (!l(af[i1], am[40])) || (f(af[i1], am[55]))) {
            av = af[i1] - am[5];
          }
          if ((!l(af[i1], am[70])) || (f(af[i1], am[71]))) {
            av = af[i1];
          }
          if ((!l(af[i1], am[5])) || (!l(af[i1], am[1])) || (!l(af[i1], am[6])) || (!l(af[i1], am[3])) || (!l(af[i1], am[7])) || (!l(af[i1], am[8])) || (!l(af[i1], am[28])) || (!l(af[i1], am[19])) || (!l(af[i1], am[14])) || (!l(af[i1], am[52])) || (!l(af[i1], am[15])) || (!l(af[i1], am[87])) || (!l(af[i1], am[89])) || (!l(af[i1], am[90])) || (!l(af[i1], am[91])) || (!l(af[i1], am[92])) || (!l(af[i1], am[93])) || (!l(af[i1], am[94])) || (!l(af[i1], am[65])) || (!l(af[i1], am[95])) || (!l(af[i1], am[96])) || (!l(af[i1], am[97])) || (!l(af[i1], am[32])) || (!l(af[i1], am[35])) || (!l(af[i1], am[38])) || (!l(af[i1], am[39])) || (!l(af[i1], am[98])) || (!l(af[i1], am[99])) || (!l(af[i1], am[63])) || (!l(af[i1], am[73])) || (!l(af[i1], am[41])) || (!l(af[i1], am[42])) || (!l(af[i1], am[100])) || (!l(af[i1], am[74])) || (!l(af[i1], am[75])) || (!l(af[i1], am[77])) || (!l(af[i1], am[78])) || (!l(af[i1], am[83])) || (!l(af[i1], am[101])) || (!l(af[i1], am[102])) || (!l(af[i1], am[103])) || (!l(af[i1], am[104])) || (f(af[i1], am[105]))) {
            (arrayOfInt = p)[i1] |= am[1];
          }
          if ((!l(af[i1], am[106])) || (!l(af[i1], am[40])) || (!l(af[i1], am[107])) || (!l(af[i1], am[16])) || (!l(af[i1], am[0])) || (!l(af[i1], am[4])) || (!l(af[i1], am[51])) || (!l(af[i1], am[17])) || (!l(af[i1], am[10])) || (f(af[i1], am[9]))) {
            (arrayOfInt = p)[i1] |= am[26];
          }
          if (f(af[i1], am[47])) {
            (arrayOfInt = p)[i1] |= am[53];
          }
          if (f(af[i1], am[108])) {
            (arrayOfInt = p)[i1] |= am[55];
          }
          if ((!l(af[i1], am[8])) || (!l(af[i1], am[4])) || (!l(af[i1], am[87])) || (!l(af[i1], am[109])) || (!l(af[i1], am[38])) || (!l(af[i1], am[98])) || (!l(af[i1], am[63])) || (!l(af[i1], am[107])) || (!l(af[i1], am[74])) || (!l(af[i1], am[103])) || (f(af[i1], am[110]))) {
            (arrayOfInt = p)[i1] |= am[3];
          }
          if ((!l(af[i1], am[28])) || (!l(af[i1], am[51])) || (!l(af[i1], am[87])) || (!l(af[i1], am[111])) || (!l(af[i1], am[39])) || (!l(af[i1], am[99])) || (!l(af[i1], am[63])) || (!l(af[i1], am[106])) || (!l(af[i1], am[75])) || (!l(af[i1], am[104])) || (f(af[i1], am[112]))) {
            (arrayOfInt = p)[i1] |= am[20];
          }
          if (f(af[i1], am[113]))
          {
            (arrayOfInt = p)[i1] |= am[24];
            if (f(p[(i1 - ae)] & am[26], am[26])) {
              (arrayOfInt = p)[i1] |= am[26];
            }
          }
          if (f(af[i1], am[60])) {
            (arrayOfInt = p)[i1] |= am[58];
          }
          if (f(af[i1], am[52])) {
            (arrayOfInt = p)[i1] |= am[21];
          }
          if ((!l(af[i1], am[59])) || (!l(af[i1], am[62])) || (!l(af[i1], am[114])) || (!l(af[i1], am[115])) || (!l(af[i1], am[116])) || (f(af[i1], am[59]))) {
            (arrayOfInt = p)[i1] |= am[61];
          }
          if ((!l(af[i1], am[87])) || (!l(af[i1], am[63])) || (f(af[i1], am[92]))) {
            (arrayOfInt = p)[i1] |= am[86];
          }
          if ((!l(af[i1], am[64])) || (!l(af[i1], am[71])) || (f(af[i1], am[117]))) {
            (arrayOfInt = p)[i1] |= am[118];
          }
          if (f(af[i1], am[73])) {
            (arrayOfInt = p)[i1] |= am[119];
          }
          if (f(af[i1], am[105])) {
            (arrayOfInt = p)[i1] |= am[120];
          }
          if ((!l(af[i1], am[121])) || (f(af[i1], am[122]))) {
            (arrayOfInt = p)[i1] |= am[123];
          }
          if (f(af[i1], am[71])) {
            (arrayOfInt = p)[i1] |= am[124];
          }
          if (f(af[i1], am[117])) {
            (arrayOfInt = p)[i1] |= am[125];
          }
        }
        i1++;
        "".length();
        if (((0xF2 ^ 0xB6) & (0x4 ^ 0x40 ^ 0xFFFFFFFF)) != 0) {
          return;
        }
      }
      z = Image.createImage(ae * v * cf.c, ad * v * cf.c);
      cf localcf;
      (localcf = new cf(z.getGraphics())).a(am[2]);
      localcf.b(am[2], am[2], ae * v, ad * v);
      paramInt = am[2];
      while (h(paramInt, ae))
      {
        int i2 = am[2];
        while (h(i2, ad))
        {
          int i3;
          if (l(i3 = af[(i2 * ae + paramInt)] - am[5], am[126])) {
            localcf.a(ai, am[2], i3 * v, v, v, am[2], paramInt * v, i2 * v, am[2]);
          }
          i2++;
          "".length();
          if (-" ".length() >= 0) {
            return;
          }
        }
        paramInt++;
        "".length();
        if ("   ".length() <= 0) {
          return;
        }
      }
      if (t(aw.ag))
      {
        if ((!q(o)) || (!i(o, am[3])) || ((k(o, am[51])) && (!i(o, am[54]))) || ((k(o, am[108])) && (!i(o, am[127]))) || (!l(o, am[27])) || (!l(o, am[59])) || (!l(o, am[60])) || (!l(o, am[48])) || (!l(o, am[''])) || (!l(o, am[''])) || (!l(o, am[''])) || (!l(o, am[92])) || ((k(o, am[''])) && (!i(o, am['']))) || (f(o, am['']))) {
          bg.e.addElement(new t(am[5], am[10]));
        }
        if (((k(o, am[49])) && (!i(o, am[16]))) || ((k(o, am[''])) && (!i(o, am['']))) || (!l(o, am[''])) || ((k(o, am[''])) && (g(o, am[90]))))
        {
          bg.e.addElement(new t(am[6], bc.b(am[''], am[''])));
          return;
        }
      }
      return;
    }
    catch (Exception localException)
    {
      System.out.println("Error Load Map");
      localException.printStackTrace();
      bv localbv = bv.d;
      dm.a = am[2];
      System.gc();
      localbv.g();
    }
  }
  
  /* Error */
  public static final int d(int paramInt1, int paramInt2)
  {
    // Byte code:
    //   0: getstatic 186	et:p	[I
    //   3: iload_1
    //   4: getstatic 190	et:u	B
    //   7: idiv
    //   8: getstatic 148	et:ae	I
    //   11: imul
    //   12: iload_0
    //   13: getstatic 190	et:u	B
    //   16: idiv
    //   17: iadd
    //   18: iaload
    //   19: ireturn
    //   20: ldc 24
    //   22: invokevirtual 291	java/lang/String:length	()I
    //   25: pop2
    //   26: getstatic 155	et:am	[I
    //   29: sipush 151
    //   32: iaload
    //   33: ireturn
    // Local variable table:
    //   start	length	slot	name	signature
    //   0	34	0	paramInt1	int
    //   0	34	1	paramInt2	int
    //   20	1	2	localException	Exception
    // Exception table:
    //   from	to	target	type
    //   0	19	20	java/lang/Exception
  }
  
  public static final void b(cf paramcf)
  {
    if (i(aw.b, am['']))
    {
      bc.a(paramcf);
      paramcf.a(ac + am[5], i + am[1]);
      paramcf.a(am[2]);
      paramcf.b(am[''], am[''], l + am[1], q);
      paramcf.c(am[''], am[''], l + am[3], q + am[3]);
      int i1 = am[2];
      while (h(i1, am[1]))
      {
        paramcf.a(aw[i1]);
        paramcf.e(i1 - am[1], i1 - am[1], l + am[1] - (i1 << am[5]), q - (i1 << am[5]));
        i1++;
        "".length();
        if ("   ".length() == 0) {
          return;
        }
      }
      paramcf.c(am[2], am[2], l - am[1], q - am[6]);
      if ((!g(cf.a(z), l)) || (i(cf.b(z), q))) {
        paramcf.a(-bb, -au);
      }
      paramcf.a(z, am[2], am[2], am[2]);
      int i2 = am[2];
      Object localObject;
      while (h(i2, r.r.size()))
      {
        i1 = (localObject = (e)r.r.elementAt(i2)).u / am[0];
        i3 = ((e)localObject).l / am[0];
        if (h(i1, bc)) {
          i1 = bc;
        }
        if (h(i3, ah)) {
          i3 = ah;
        }
        if (i(i1, bc + l)) {
          i1 = bc + l;
        }
        if (i(i3, ah + q)) {
          i3 = ah + q;
        }
        if (h(aw.ap % am[10], am[20]))
        {
          paramcf.a(am['']);
          paramcf.b(i1 - am[1], i3 - am[1], am[7], am[7]);
          if (f(((e)localObject).t, am[5]))
          {
            "".length();
            if ("   ".length() != (0xAA ^ 0xAE)) {}
          }
          else if (f(((e)localObject).t, am[1]))
          {
            "".length();
            if ((0xF6 ^ 0x90 ^ 0x7B ^ 0x19) >= 0) {
              break label593;
            }
          }
          label593:
          am[''].a(am['']);
          paramcf.b(i1 - am[5], i3 - am[5], am[6], am[6]);
        }
        i2++;
        "".length();
        if (((0xED ^ 0xB7) & (0xCE ^ 0x94 ^ 0xFFFFFFFF)) != 0) {
          return;
        }
      }
      i1 = dt.g().eg / am[0];
      int i3 = dt.g().ey / am[0];
      paramcf.a(am['']);
      paramcf.b(i1 - am[1], i3 - am[1], am[7], am[7]);
      paramcf.a(am['']);
      paramcf.b(i1 - am[5], i3 - am[5], am[6], am[6]);
      if (q(dn.l))
      {
        i2 = am[2];
        while (h(i2, dn.aj.size()))
        {
          i1 = ((Integer)dn.aj.elementAt(i2)).intValue() / am[0];
          i3 = ((Integer)dn.o.elementAt(i2)).intValue() / am[0];
          if (f(dn.m, i2))
          {
            paramcf.a(am['']);
            paramcf.b(i1 - am[1], i3 - am[1], am[7], am[7]);
          }
          paramcf.a(am['']);
          paramcf.b(i1 - am[5], i3 - am[5], am[6], am[6]);
          "".length();
          if ((0xC6 ^ 0xBE ^ 0x52 ^ 0x2E) < " ".length()) {
            return;
          }
          i2 = am[2];
          if (!h(i2, fn.ax.size())) {
            break label1235;
          }
          if ((!b((localObject = (bk)fn.ax.elementAt(i2)).f)) || (!a(((bk)localObject).f, dt.g()))) {
            break label1216;
          }
          i1 = ;;;
        }
      }
      label1216:
      do
      {
        if (h(i1, bc)) {
          i1 = bc;
        }
        if (h(i3, ah)) {
          i3 = ah;
        }
        if (i(i1, bc + l)) {
          i1 = bc + l;
        }
        if (i(i3, ah + q)) {
          i3 = ah + q;
        }
        if (h(aw.ap % am[10], am[20]))
        {
          paramcf.a(am['']);
          paramcf.b(i1 - am[1], i3 - am[1], am[7], am[7]);
          paramcf.a(am['']);
          paramcf.b(i1 - am[5], i3 - am[5], am[6], am[6]);
        }
        i2++;
        "".length();
      } while (-" ".length() <= 0);
      return;
      label1235:
      bc.a(paramcf);
      if (q(aw.s))
      {
        paramcf.a(fn.be, ac - am[5], i, am[2]);
        if (q(aq.c))
        {
          ax.l.a(paramcf, "Map : " + o, ac - am[5], i, am[2], ax.q);
          ax.l.a(paramcf, "Khu : " + b, ac - am[5], i = i + am[0], am[2], ax.q);
          ax.l.a(paramcf, "XY: " + dt.g().eg + "-" + dt.g().ey, ac - am[5], i = i + am[0], am[2], ax.q);
        }
      }
    }
  }
  
  private static boolean r(int paramInt)
  {
    return paramInt > 0;
  }
  
  private static boolean k(int paramInt1, int paramInt2)
  {
    return paramInt1 >= paramInt2;
  }
  
  public static int e(int paramInt1, int paramInt2)
  {
    if (q(d(paramInt1, paramInt2 - am[51]) & am['¯']))
    {
      paramInt2 = k(paramInt2);
      int i1 = am[108];
      int i2;
      while (h(i1, am['°']))
      {
        i2 = d(paramInt1, paramInt2 - i1);
        if ((r(paramInt2 - i1)) && (t(i2 & am['¯']))) {
          return paramInt2 - i1 + am[108];
        }
        i1 += 24;
        "".length();
        if ("  ".length() <= " ".length()) {
          return (57 + 29 - -15 + 147 ^ 11 + '' - 18 + 20) & (0xE1 ^ 0xBC ^ "   ".length() ^ -" ".length());
        }
      }
      i1 = am[108];
      while (h(i1, am[43]))
      {
        i2 = d(paramInt1, paramInt2 + i1);
        if ((h(paramInt2 + i1, h)) && (t(i2 & am['¯']))) {
          return paramInt2 + i1;
        }
        i1 += 24;
        "".length();
        if (" ".length() == 0) {
          return (0x5A ^ 0x7B) & (0x90 ^ 0xB1 ^ 0xFFFFFFFF);
        }
      }
    }
    return paramInt2;
  }
  
  private static boolean a(Object paramObject)
  {
    return paramObject == null;
  }
  
  public static void h(int paramInt)
  {
    aw.m();
    new Thread(new l(paramInt)).start();
  }
  
  /* Error */
  public static void a(int paramInt, InputStream paramInputStream)
  {
    // Byte code:
    //   0: getstatic 154	et:al	[[B
    //   3: arraylength
    //   4: iload_0
    //   5: invokestatic 255	et:g	(II)Z
    //   8: ifeq +40 -> 48
    //   11: iload_0
    //   12: getstatic 155	et:am	[I
    //   15: bipush 10
    //   17: iaload
    //   18: iadd
    //   19: anewarray 46	[B
    //   22: astore_2
    //   23: getstatic 154	et:al	[[B
    //   26: getstatic 155	et:am	[I
    //   29: iconst_2
    //   30: iaload
    //   31: aload_2
    //   32: getstatic 155	et:am	[I
    //   35: iconst_2
    //   36: iaload
    //   37: getstatic 154	et:al	[[B
    //   40: arraylength
    //   41: invokestatic 297	java/lang/System:arraycopy	(Ljava/lang/Object;ILjava/lang/Object;II)V
    //   44: aload_2
    //   45: putstatic 154	et:al	[[B
    //   48: getstatic 154	et:al	[[B
    //   51: iload_0
    //   52: aload_1
    //   53: invokevirtual 279	java/io/InputStream:available	()I
    //   56: newarray <illegal type>
    //   58: aastore
    //   59: aload_1
    //   60: getstatic 154	et:al	[[B
    //   63: iload_0
    //   64: aaload
    //   65: invokevirtual 281	java/io/InputStream:read	([B)I
    //   68: ldc 24
    //   70: invokevirtual 291	java/lang/String:length	()I
    //   73: pop2
    //   74: return
    //   75: ldc 24
    //   77: invokevirtual 291	java/lang/String:length	()I
    //   80: pop2
    //   81: return
    // Local variable table:
    //   start	length	slot	name	signature
    //   0	82	0	paramInt	int
    //   0	82	1	paramInputStream	InputStream
    //   22	23	2	arrayOfByte	byte[][]
    //   75	1	3	localException	Exception
    // Exception table:
    //   from	to	target	type
    //   0	74	75	java/lang/Exception
  }
  
  public static boolean i(int paramInt)
  {
    if ((!l(paramInt, am[5])) || (!l(paramInt, am[127])) || (f(paramInt, am[94]))) {
      return am[5];
    }
    return am[2];
  }
  
  private static boolean l(int paramInt1, int paramInt2)
  {
    return paramInt1 != paramInt2;
  }
  
  public static boolean j(int paramInt)
  {
    if ((!l(paramInt, am[10])) || (!l(paramInt, am[52])) || (!l(paramInt, am[27])) || (!l(paramInt, am[53])) || (!l(paramInt, am[48])) || (!l(paramInt, am[15])) || (!l(paramInt, am[''])) || (!l(paramInt, am[103])) || (f(paramInt, am['']))) {
      return am[5];
    }
    return am[2];
  }
  
  public static final void c(cf paramcf)
  {
    int i1 = fn.ec;
    while (h(i1, fn.ea))
    {
      int i2 = fn.o;
      while (h(i2, fn.dr))
      {
        int i3 = af[(i2 * ae + i1)] - am[5];
        if (l(j(i1, i2) & am[61], am[61]))
        {
          if ((f(d, am[3])) && (f(j(i1, i2) & am[24], am[24])))
          {
            i3 = i2 - am[5];
            if (f(i3 = af[(i3 * ae + i1)] - am[5], am[4]))
            {
              paramcf.a(bg, am[2], am[52] * u, am[108], am[108], am[2], i1 * u, i2 * u, am[2]);
              "".length();
              if ("  ".length() > 0) {
                break label2745;
              }
              return;
            }
            if (f(i3, am[7]))
            {
              paramcf.a(bg, am[2], am[28] * u, am[108], am[108], am[2], i1 * u, i2 * u, am[2]);
              "".length();
              if (null == null) {
                break label2745;
              }
              return;
            }
            if ((!l(i3, am[54])) || (!l(i3, am[27])) || (f(i3, am[4])))
            {
              paramcf.a(bg, am[2], am[52] * u, am[108], am[108], am[2], i1 * u, i2 * u, am[2]);
              "".length();
              if (-" ".length() <= 0) {
                break label2745;
              }
              return;
            }
            if ((!l(i3, am[16])) || (!l(i3, am[''])) || (f(i3, am[87])))
            {
              paramcf.a(bg, am[2], am[''] * u, am[108], am[108], am[2], i1 * u, i2 * u, am[2]);
              "".length();
              if (-" ".length() <= 0) {
                break label2745;
              }
              return;
            }
            if ((!l(i3, am[108])) || (!l(i3, am[47])) || (!l(i3, am[45])) || (!l(i3, am[46])) || (!l(i3, am[56])) || (!l(i3, am[0])) || (!l(i3, am[13]))) {
              break label2745;
            }
            if (l(i3, am[126]))
            {
              paramcf.a(bg, am[2], i3 * u, am[108], am[108], am[2], i1 * u, i2 * u, am[2]);
              "".length();
              if ("  ".length() <= "   ".length()) {}
            }
            else
            {
              if (!l(i3, am[126])) {
                break label2745;
              }
            }
          }
          if (f(d, am[5]))
          {
            if (f(j(i1, i2) & am[53], am[53]))
            {
              paramcf.a(as, am[2], am[108] * (aw.ap % am[3]), am[108], am[108], am[2], i1 * u, i2 * u, am[2]);
              "".length();
              if (" ".length() <= " ".length()) {
                break label2745;
              }
              return;
            }
            if ((!l(j(i1, i2) & am[24], am[24])) || (f(j(i1, i2) & am[58], am[58])))
            {
              if (f(j(i1, i2 - am[5]) & am[53], am[53]))
              {
                paramcf.a(as, am[2], am[108] * (aw.ap % am[3]), am[108], am[108], am[2], i1 * u, i2 * u, am[2]);
                "".length();
                if (-" ".length() < ((0x50 ^ 0x61) & (0x85 ^ 0xB4 ^ 0xFFFFFFFF) ^ 0x3A ^ 0x3E)) {
                  break label2745;
                }
                return;
              }
              if (f(j(i1, i2 - am[5]) & am[26], am[26]))
              {
                paramcf.a(bg, am[2], am[''], am[108], am[108], am[2], i1 * u, i2 * u, am[2]);
                "".length();
                if (null == null) {
                  break label2745;
                }
                return;
              }
            }
          }
          if (f(d, am[1]))
          {
            if (f(j(i1, i2) & am[53], am[53]))
            {
              paramcf.a(as, am[2], am[108] * (aw.ap % am[20] >> am[5]), am[108], am[108], am[2], i1 * u, i2 * u, am[2]);
              "".length();
              if (-" ".length() < " ".length()) {
                break label2745;
              }
              return;
            }
            if (f(i3, am[52]))
            {
              paramcf.a(ax, am[2], am[108] * (aw.ap % am[20] >> am[5]), am[108], am[108], am[2], i1 * u, i2 * u, am[2]);
              "".length();
              if (-" ".length() < 0) {
                break label2745;
              }
              return;
            }
            if (f(i3, am[101]))
            {
              paramcf.a(bg, am[2], am[84] * u, am[108], am[108], am[2], i1 * u, i2 * u, am[2]);
              "".length();
              if ((81 + 99 - 106 + 81 ^ 86 + 108 - 152 + 117) > 0) {
                break label2745;
              }
              return;
            }
            if ((!l(j(i1, i2) & am[24], am[24])) || (f(j(i1, i2) & am[58], am[58])))
            {
              if (f(j(i1, i2 - am[5]) & am[53], am[53]))
              {
                paramcf.a(as, am[2], am[108] * (aw.ap % am[3]), am[108], am[108], am[2], i1 * u, i2 * u, am[2]);
                "".length();
                if (((0x65 ^ 0x62) & (0x81 ^ 0x86 ^ 0xFFFFFFFF)) == ((0x1E ^ 0x15) & (0x82 ^ 0x89 ^ 0xFFFFFFFF))) {
                  break label2745;
                }
                return;
              }
              if (f(j(i1, i2 - am[5]) & am[26], am[26]))
              {
                if (f(i3 = m(i1, i2 - am[5]), am[79]))
                {
                  i3 = am[31];
                  "".length();
                  if ((0x7C ^ 0x79) != 0) {}
                }
                else if ((l(i3, am[56])) && (l(i3, am[57])))
                {
                  if (h(i3, am[121]))
                  {
                    i3 = am[46];
                    "".length();
                    if (" ".length() >= 0) {}
                  }
                  else
                  {
                    i3 = am[71];
                    "".length();
                    if (-"   ".length() <= 0) {}
                  }
                }
                else if (f(i3 = m(i1, i2 - am[1]), am[79]))
                {
                  i3 = am[31];
                  "".length();
                  if (null == null) {}
                }
                else if (h(i3, am[121]))
                {
                  i3 = am[46];
                }
                paramcf.a(bg, am[2], i3 * am[108], am[108], am[108], am[2], i1 * u, i2 * u, am[2]);
                "".length();
                if ("  ".length() > 0) {
                  break label2745;
                }
                return;
              }
            }
          }
          if (f(d, am[6]))
          {
            if (f(j(i1, i2) & am[53], am[53]))
            {
              paramcf.a(as, am[2], am[108] * (aw.ap % am[20] >> am[5]), am[108], am[108], am[2], i1 * u, i2 * u, am[2]);
              "".length();
              if (null == null) {
                break label2745;
              }
              return;
            }
            if (f(i3, am[47]))
            {
              paramcf.a(ax, am[2], am[108] * (aw.ap % am[20] >> am[5]), am[108], am[108], am[2], i1 * u, i2 * u, am[2]);
              "".length();
              if (-"  ".length() < 0) {
                break label2745;
              }
              return;
            }
            if ((!l(j(i1, i2) & am[24], am[24])) || (f(j(i1, i2) & am[58], am[58])))
            {
              if (f(j(i1, i2 - am[5]) & am[53], am[53]))
              {
                paramcf.a(as, am[2], am[108] * (aw.ap % am[3]), am[108], am[108], am[2], i1 * u, i2 * u, am[2]);
                "".length();
                if (null == null) {
                  break label2745;
                }
                return;
              }
              if (f(j(i1, i2 - am[5]) & am[26], am[26]))
              {
                if (f(i3 = m(i1, i2 - am[5]), am[113])) {
                  i3 = m(i1, i2 - am[1]);
                }
                if (f(i3, am[17])) {
                  i3 = am[16];
                }
                i3--;
                paramcf.a(bg, am[2], i3 * am[108], am[108], am[108], am[2], i1 * u, i2 * u, am[2]);
                "".length();
                if (null == null) {
                  break label2745;
                }
                return;
              }
            }
          }
          if (f(j(i1, i2) & am[51], am[51]))
          {
            ap = i1 * u - fn.ad - fn.u;
            ao = (u - am[1]) * ap / u + fn.u;
            paramcf.a(bg, am[2], i3 * u, am[108], am[108], am[2], ao + fn.ad, i2 * u, am[2]);
            "".length();
            if (-" ".length() < " ".length()) {}
          }
          else if (f(j(i1, i2) & am[''], am['']))
          {
            if (l(i3, am[126]))
            {
              paramcf.a(bg, am[2], i3 * u, am[108], am[5], am[2], i1 * u, i2 * u, am[2]);
              paramcf.a(bg, am[2], i3 * u, am[108], am[108], am[2], i1 * u, i2 * u + am[5], am[2]);
              "".length();
              if (-" ".length() <= 0) {}
            }
          }
          else if (l(i3, am[126]))
          {
            paramcf.a(bg, am[2], i3 * u, am[108], am[108], am[2], i1 * u, i2 * u, am[2]);
          }
        }
        label2745:
        i2++;
        "".length();
        if ((25 + '£' - 88 + 89 ^ '¤' + 72 - 189 + 138) <= "   ".length()) {
          return;
        }
      }
      i1++;
      "".length();
      if (-"   ".length() >= 0) {}
    }
  }
  
  public static final int k(int paramInt)
  {
    return paramInt / u * u;
  }
  
  public static void l(int paramInt)
  {
    aw.m();
    new Thread(new eh(paramInt)).start();
  }
  
  public static int m(int paramInt)
  {
    if (q(f(paramInt))) {
      switch (paramInt)
      {
      case 91: 
        return am[33];
      case 92: 
        return am[34];
      case 93: 
      case 97: 
      case 98: 
      case 99: 
      case 100: 
      case 101: 
      case 102: 
      case 103: 
      case 104: 
      case 109: 
      case 110: 
      case 111: 
      case 112: 
      case 113: 
      case 116: 
      case 117: 
      case 118: 
      case 119: 
      case 120: 
      case 121: 
      case 122: 
      case 123: 
      case 124: 
      case 128: 
      case 129: 
      case 130: 
      case 131: 
      case 132: 
      case 133: 
      case 134: 
      case 135: 
      case 136: 
      case 137: 
      case 138: 
      case 139: 
      case 140: 
      case 141: 
      case 142: 
      case 143: 
      case 144: 
      case 145: 
      case 146: 
      case 147: 
      case 148: 
      case 149: 
      case 150: 
      case 151: 
      case 152: 
      case 153: 
      case 154: 
      case 155: 
      case 156: 
      default: 
        "".length();
        if ("   ".length() == 0) {
          return (0xFA ^ 0xB6) & (0x26 ^ 0x6A ^ 0xFFFFFFFF);
        }
        break;
      case 94: 
        return am[109];
      case 95: 
        return am[111];
      case 96: 
        return am[38];
      case 105: 
        return am[98];
      case 106: 
        return am[99];
      case 107: 
        return am[69];
      case 108: 
        return am[70];
      case 114: 
        return am[81];
      case 115: 
        return am[40];
      case 125: 
        return am[75];
      case 126: 
        return am[76];
      case 127: 
        return am[55];
      case 157: 
        return am[''];
      case 158: 
        return am[''];
      case 159: 
        return am[''];
      }
    }
    return am[126];
  }
  
  private static boolean s(int paramInt)
  {
    return paramInt >= 0;
  }
  
  public static boolean n(int paramInt)
  {
    if ((k(paramInt, am[85])) && (g(paramInt, am[103]))) {
      return am[5];
    }
    return am[2];
  }
  
  public static void h()
  {
    if ((t(aw.ap % am[''])) && (q(o)) && (i(o, am[3])) && ((!k(o, am[51])) || (i(o, am[54]))) && ((!k(o, am[108])) || (i(o, am[127]))) && (l(o, am[27])) && (l(o, am[59])) && (l(o, am[60])) && (l(o, am[48])) && (l(o, am[''])) && (l(o, am[''])) && (l(o, am[''])) && (l(o, am[92])) && ((!k(o, am[''])) || (i(o, am['']))) && (l(o, am[''])) && ((!k(o, am[49])) || (i(o, am[16]))) && ((!k(o, am[''])) || (i(o, am['']))) && (l(o, am[''])) && ((!k(o, am[''])) || (i(o, am[90]))) && (l(o, am[''])) && (l(o, am[57])) && (l(o, am[18])) && (l(o, am[87])) && (l(o, am[''])) && (f(o, am[24]))) {
      "".length();
    }
  }
  
  /* Error */
  private static int m(int paramInt1, int paramInt2)
  {
    // Byte code:
    //   0: getstatic 149	et:af	[C
    //   3: iload_1
    //   4: getstatic 148	et:ae	I
    //   7: imul
    //   8: iload_0
    //   9: iadd
    //   10: caload
    //   11: ireturn
    //   12: ldc 24
    //   14: invokevirtual 291	java/lang/String:length	()I
    //   17: pop2
    //   18: getstatic 155	et:am	[I
    //   21: sipush 151
    //   24: iaload
    //   25: ireturn
    // Local variable table:
    //   start	length	slot	name	signature
    //   0	26	0	paramInt1	int
    //   0	26	1	paramInt2	int
    //   12	1	2	localException	Exception
    // Exception table:
    //   from	to	target	type
    //   0	11	12	java/lang/Exception
  }
  
  private static boolean t(int paramInt)
  {
    return paramInt == 0;
  }
  
  public static void i()
  {
    bg = null;
    System.gc();
    bg = aj[d];
    ai = az[d];
  }
  
  public static boolean o(int paramInt)
  {
    if ((!l(paramInt, am[10])) || (!l(paramInt, am[52])) || (!l(paramInt, am[27])) || (!l(paramInt, am[53])) || (!l(paramInt, am[48])) || (!l(paramInt, am[15])) || (!l(paramInt, am[''])) || (!l(paramInt, am[103])) || (!l(paramInt, am[5])) || (!l(paramInt, am[127])) || (f(paramInt, am[94]))) {
      return am[5];
    }
    return am[2];
  }
  
  private static boolean b(Object paramObject)
  {
    return paramObject != null;
  }
  
  public static void j()
  {
    if ((!h(ae * v, l)) || (k(ad * v, q)))
    {
      if (l(au, be))
      {
        ah = be - au << am[1];
        ay += ah;
        au += (ay >> am[3]);
        ay &= am[4];
      }
      if (l(bb, an))
      {
        bc = an - bb << am[1];
        bf += bc;
        bb += (bf >> am[3]);
        bf &= am[4];
      }
    }
  }
  
  public static void k()
  {
    if (q(a))
    {
      a = am[2];
      "".length();
      synchronized (ba)
      {
        ba.notifyAll();
        return;
      }
    }
  }
  
  public static void l() {}
}


/* Location:              C:\Users\Admin\OneDrive\Documents\NSOv2_test.jar!\et.class
 * Java compiler version: 1 (45.3)
 * JD-Core Version:       0.7.1
 */