public final class fd
{
  private static int[] a;
  
  private static boolean a(int paramInt)
  {
    return paramInt != 0;
  }
  
  private static void c()
  {
    a = new int[7];
    a[0] = (103 + '¨' - 98 + 19 ^ 73 + 74 - 143 + 193);
    a[1] = ((122 + 8 - 6 + 103 ^ 19 + '' - 41 + 51) & (0x16 ^ 0x41 ^ 0x2D ^ 0x25 ^ -" ".length()));
    a[2] = (0xB ^ 0x38);
    a[3] = (0x3C ^ 0x19 ^ 0x41 ^ 0x4C);
    a[4] = (-" ".length());
    a[5] = " ".length();
    a[6] = (0xA9 ^ 0xAD);
  }
  
  private static boolean a(int paramInt1, int paramInt2)
  {
    return paramInt1 < paramInt2;
  }
  
  private static boolean b(int paramInt)
  {
    return paramInt <= 0;
  }
  
  private static boolean c(int paramInt)
  {
    return paramInt >= 0;
  }
  
  private static boolean b(int paramInt1, int paramInt2)
  {
    return paramInt1 != paramInt2;
  }
  
  /* Error */
  public static void a(bj parambj)
  {
    // Byte code:
    //   0: aload_0
    //   1: dup
    //   2: astore_3
    //   3: getfield 26	bj:a	Ljava/io/DataInputStream;
    //   6: invokevirtual 51	java/io/DataInputStream:readByte	()B
    //   9: lookupswitch	default:+659->668, 0:+27->36, 1:+392->401
    //   36: aload_0
    //   37: dup
    //   38: astore_3
    //   39: getfield 26	bj:a	Ljava/io/DataInputStream;
    //   42: invokevirtual 52	java/io/DataInputStream:readInt	()I
    //   45: istore_1
    //   46: invokestatic 39	dt:g	()Ldt;
    //   49: getfield 31	dt:fy	I
    //   52: iload_1
    //   53: invokestatic 46	fd:b	(II)Z
    //   56: ifeq +23 -> 79
    //   59: iload_1
    //   60: invokestatic 49	fn:d	(I)Ldt;
    //   63: ldc 1
    //   65: invokevirtual 57	java/lang/String:length	()I
    //   68: pop
    //   69: ldc 3
    //   71: invokevirtual 57	java/lang/String:length	()I
    //   74: ineg
    //   75: iflt +7 -> 82
    //   78: return
    //   79: invokestatic 39	dt:g	()Ldt;
    //   82: dup
    //   83: astore_1
    //   84: invokestatic 44	fd:a	(Ljava/lang/Object;)Z
    //   87: ifeq +26 -> 113
    //   90: ldc 1
    //   92: invokevirtual 57	java/lang/String:length	()I
    //   95: pop
    //   96: sipush 224
    //   99: sipush 170
    //   102: ixor
    //   103: bipush 78
    //   105: iconst_0
    //   106: ixor
    //   107: ixor
    //   108: ineg
    //   109: ifle +566 -> 675
    //   112: return
    //   113: aload_1
    //   114: getstatic 33	fd:a	[I
    //   117: iconst_0
    //   118: iaload
    //   119: anewarray 5	ao
    //   122: putfield 30	dt:fb	[Lao;
    //   125: getstatic 33	fd:a	[I
    //   128: iconst_1
    //   129: iaload
    //   130: istore_2
    //   131: iload_2
    //   132: aload_1
    //   133: getfield 30	dt:fb	[Lao;
    //   136: arraylength
    //   137: invokestatic 43	fd:a	(II)Z
    //   140: ifeq +253 -> 393
    //   143: aload_0
    //   144: dup
    //   145: astore_3
    //   146: getfield 26	bj:a	Ljava/io/DataInputStream;
    //   149: invokevirtual 54	java/io/DataInputStream:readShort	()S
    //   152: dup
    //   153: istore_3
    //   154: invokestatic 48	fd:c	(I)Z
    //   157: ifeq +212 -> 369
    //   160: aload_1
    //   161: getfield 30	dt:fb	[Lao;
    //   164: iload_2
    //   165: new 5	ao
    //   168: dup
    //   169: invokespecial 34	ao:<init>	()V
    //   172: aastore
    //   173: aload_1
    //   174: getfield 30	dt:fb	[Lao;
    //   177: iload_2
    //   178: aaload
    //   179: iload_2
    //   180: putfield 24	ao:n	I
    //   183: aload_1
    //   184: getfield 30	dt:fb	[Lao;
    //   187: iload_2
    //   188: aaload
    //   189: getstatic 33	fd:a	[I
    //   192: iconst_2
    //   193: iaload
    //   194: putfield 23	ao:m	I
    //   197: aload_1
    //   198: getfield 30	dt:fb	[Lao;
    //   201: iload_2
    //   202: aaload
    //   203: iload_3
    //   204: invokestatic 35	bw:a	(S)Lat;
    //   207: putfield 21	ao:j	Lat;
    //   210: aload_1
    //   211: getfield 30	dt:fb	[Lao;
    //   214: iload_2
    //   215: aaload
    //   216: aload_0
    //   217: dup
    //   218: astore_3
    //   219: getfield 26	bj:a	Ljava/io/DataInputStream;
    //   222: invokevirtual 51	java/io/DataInputStream:readByte	()B
    //   225: putfield 25	ao:r	I
    //   228: aload_1
    //   229: getfield 30	dt:fb	[Lao;
    //   232: iload_2
    //   233: aaload
    //   234: aload_0
    //   235: dup
    //   236: astore_3
    //   237: getfield 26	bj:a	Ljava/io/DataInputStream;
    //   240: invokevirtual 53	java/io/DataInputStream:readLong	()J
    //   243: putfield 22	ao:k	J
    //   246: aload_1
    //   247: getfield 30	dt:fb	[Lao;
    //   250: iload_2
    //   251: aaload
    //   252: aload_0
    //   253: dup
    //   254: astore_3
    //   255: getfield 26	bj:a	Ljava/io/DataInputStream;
    //   258: invokevirtual 51	java/io/DataInputStream:readByte	()B
    //   261: putfield 19	ao:c	I
    //   264: aload_0
    //   265: dup
    //   266: astore_3
    //   267: getfield 26	bj:a	Ljava/io/DataInputStream;
    //   270: invokevirtual 51	java/io/DataInputStream:readByte	()B
    //   273: istore 4
    //   275: aload_1
    //   276: getfield 30	dt:fb	[Lao;
    //   279: iload_2
    //   280: aaload
    //   281: new 8	ci
    //   284: dup
    //   285: invokespecial 36	ci:<init>	()V
    //   288: putfield 20	ao:h	Lci;
    //   291: getstatic 33	fd:a	[I
    //   294: iconst_1
    //   295: iaload
    //   296: istore 5
    //   298: iload 5
    //   300: iload 4
    //   302: invokestatic 43	fd:a	(II)Z
    //   305: ifeq +64 -> 369
    //   308: aload_1
    //   309: getfield 30	dt:fb	[Lao;
    //   312: iload_2
    //   313: aaload
    //   314: getfield 20	ao:h	Lci;
    //   317: new 14	h
    //   320: dup
    //   321: aload_0
    //   322: dup
    //   323: astore_3
    //   324: getfield 26	bj:a	Ljava/io/DataInputStream;
    //   327: invokevirtual 55	java/io/DataInputStream:readUnsignedByte	()I
    //   330: aload_0
    //   331: dup
    //   332: astore_3
    //   333: getfield 26	bj:a	Ljava/io/DataInputStream;
    //   336: invokevirtual 52	java/io/DataInputStream:readInt	()I
    //   339: invokespecial 50	h:<init>	(II)V
    //   342: invokevirtual 37	ci:addElement	(Ljava/lang/Object;)V
    //   345: iinc 5 1
    //   348: ldc 1
    //   350: invokevirtual 57	java/lang/String:length	()I
    //   353: pop
    //   354: ldc 2
    //   356: invokevirtual 57	java/lang/String:length	()I
    //   359: ineg
    //   360: ldc 2
    //   362: invokevirtual 57	java/lang/String:length	()I
    //   365: if_icmplt -67 -> 298
    //   368: return
    //   369: iinc 2 1
    //   372: ldc 1
    //   374: invokevirtual 57	java/lang/String:length	()I
    //   377: pop
    //   378: ldc 2
    //   380: invokevirtual 57	java/lang/String:length	()I
    //   383: ineg
    //   384: bipush 102
    //   386: bipush 98
    //   388: ixor
    //   389: if_icmpne -258 -> 131
    //   392: return
    //   393: return
    //   394: ldc 1
    //   396: invokevirtual 57	java/lang/String:length	()I
    //   399: pop2
    //   400: return
    //   401: aload_0
    //   402: dup
    //   403: astore_3
    //   404: getfield 26	bj:a	Ljava/io/DataInputStream;
    //   407: invokevirtual 52	java/io/DataInputStream:readInt	()I
    //   410: istore_1
    //   411: invokestatic 39	dt:g	()Ldt;
    //   414: getfield 31	dt:fy	I
    //   417: iload_1
    //   418: invokestatic 46	fd:b	(II)Z
    //   421: ifeq +27 -> 448
    //   424: iload_1
    //   425: invokestatic 49	fn:d	(I)Ldt;
    //   428: ldc 1
    //   430: invokevirtual 57	java/lang/String:length	()I
    //   433: pop
    //   434: ldc 3
    //   436: invokevirtual 57	java/lang/String:length	()I
    //   439: ldc 4
    //   441: invokevirtual 57	java/lang/String:length	()I
    //   444: if_icmple +7 -> 451
    //   447: return
    //   448: invokestatic 39	dt:g	()Ldt;
    //   451: dup
    //   452: astore_1
    //   453: invokestatic 44	fd:a	(Ljava/lang/Object;)Z
    //   456: ifeq +4 -> 460
    //   459: return
    //   460: aload_0
    //   461: dup
    //   462: astore_3
    //   463: getfield 26	bj:a	Ljava/io/DataInputStream;
    //   466: invokevirtual 54	java/io/DataInputStream:readShort	()S
    //   469: istore_2
    //   470: aload_0
    //   471: dup
    //   472: astore_3
    //   473: getfield 26	bj:a	Ljava/io/DataInputStream;
    //   476: invokevirtual 51	java/io/DataInputStream:readByte	()B
    //   479: istore_3
    //   480: iload_2
    //   481: invokestatic 45	fd:b	(I)Z
    //   484: ifeq +9 -> 493
    //   487: aload_1
    //   488: aconst_null
    //   489: putfield 27	dt:aw	Le;
    //   492: return
    //   493: aload_1
    //   494: getfield 28	dt:eg	I
    //   497: i2s
    //   498: istore 4
    //   500: aload_1
    //   501: getfield 29	dt:ey	I
    //   504: getstatic 33	fd:a	[I
    //   507: iconst_3
    //   508: iaload
    //   509: isub
    //   510: i2s
    //   511: istore 5
    //   513: aload_1
    //   514: new 11	e
    //   517: dup
    //   518: getstatic 33	fd:a	[I
    //   521: iconst_4
    //   522: iaload
    //   523: getstatic 33	fd:a	[I
    //   526: iconst_1
    //   527: iaload
    //   528: getstatic 33	fd:a	[I
    //   531: iconst_1
    //   532: iaload
    //   533: getstatic 33	fd:a	[I
    //   536: iconst_1
    //   537: iaload
    //   538: getstatic 33	fd:a	[I
    //   541: iconst_1
    //   542: iaload
    //   543: getstatic 33	fd:a	[I
    //   546: iconst_1
    //   547: iaload
    //   548: iload_2
    //   549: getstatic 33	fd:a	[I
    //   552: iconst_5
    //   553: iaload
    //   554: getstatic 33	fd:a	[I
    //   557: iconst_1
    //   558: iaload
    //   559: getstatic 33	fd:a	[I
    //   562: iconst_1
    //   563: iaload
    //   564: getstatic 33	fd:a	[I
    //   567: iconst_1
    //   568: iaload
    //   569: iload 4
    //   571: iload 5
    //   573: getstatic 33	fd:a	[I
    //   576: bipush 6
    //   578: iaload
    //   579: getstatic 33	fd:a	[I
    //   582: iconst_1
    //   583: iaload
    //   584: iload_3
    //   585: invokestatic 42	fd:a	(I)Z
    //   588: ifeq +24 -> 612
    //   591: getstatic 33	fd:a	[I
    //   594: iconst_5
    //   595: iaload
    //   596: ldc 1
    //   598: invokevirtual 57	java/lang/String:length	()I
    //   601: pop
    //   602: ldc 4
    //   604: invokevirtual 57	java/lang/String:length	()I
    //   607: ineg
    //   608: ifle +9 -> 617
    //   611: return
    //   612: getstatic 33	fd:a	[I
    //   615: iconst_1
    //   616: iaload
    //   617: getstatic 33	fd:a	[I
    //   620: iconst_1
    //   621: iaload
    //   622: invokespecial 40	e:<init>	(SZZZZZIIIIISSBBZZ)V
    //   625: putfield 27	dt:aw	Le;
    //   628: aload_1
    //   629: getfield 27	dt:aw	Le;
    //   632: getstatic 33	fd:a	[I
    //   635: iconst_0
    //   636: iaload
    //   637: putfield 32	e:j	I
    //   640: ldc 1
    //   642: invokevirtual 57	java/lang/String:length	()I
    //   645: pop
    //   646: ldc 4
    //   648: invokevirtual 57	java/lang/String:length	()I
    //   651: sipush 195
    //   654: sipush 199
    //   657: ixor
    //   658: if_icmple +17 -> 675
    //   661: return
    //   662: ldc 1
    //   664: invokevirtual 57	java/lang/String:length	()I
    //   667: pop2
    //   668: return
    //   669: ldc 1
    //   671: invokevirtual 57	java/lang/String:length	()I
    //   674: pop2
    //   675: return
    // Local variable table:
    //   start	length	slot	name	signature
    //   0	676	0	parambj	bj
    //   45	15	1	i	int
    //   83	226	1	localdt1	dt
    //   410	15	1	j	int
    //   452	177	1	localdt2	dt
    //   130	419	2	k	int
    //   2	144	3	localbj1	bj
    //   153	51	3	s	short
    //   218	255	3	localbj2	bj
    //   479	106	3	m	int
    //   273	297	4	n	int
    //   296	276	5	i1	int
    //   394	1	12	localException1	Exception
    //   662	1	13	localException2	Exception
    //   669	1	14	localException3	Exception
    // Exception table:
    //   from	to	target	type
    //   36	90	394	java/lang/Exception
    //   113	393	394	java/lang/Exception
    //   401	459	662	java/lang/Exception
    //   460	492	662	java/lang/Exception
    //   493	640	662	java/lang/Exception
    //   0	393	669	java/lang/Exception
    //   401	459	669	java/lang/Exception
    //   460	492	669	java/lang/Exception
    //   493	668	669	java/lang/Exception
  }
  
  public static void a() {}
  
  static
  {
    cs.a(109);
    a();
  }
  
  private static boolean a(Object paramObject)
  {
    return paramObject == null;
  }
  
  public static void b() {}
}


/* Location:              C:\Users\Admin\OneDrive\Documents\NSOv2_test.jar!\fd.class
 * Java compiler version: 1 (45.3)
 * JD-Core Version:       0.7.1
 */