import java.util.Vector;

public abstract class r
{
  private static boolean v;
  public boolean a;
  public long b;
  public int c;
  public int d;
  public static ci e;
  public int f;
  protected long g = 0L;
  public boolean h;
  public r i;
  private int w;
  public static boolean j;
  public long k;
  public static ci l;
  private static long x;
  public static fy m;
  protected boolean n = ab[0];
  public int o;
  public static boolean p;
  protected long q = 0L;
  private static ci y;
  private int z;
  private static ci aa;
  public static ci r;
  private static int[] ab;
  public static int s;
  public int t;
  private static long ac;
  protected long u = 0L;
  
  private static boolean a(Object paramObject)
  {
    return paramObject != null;
  }
  
  /* Error */
  protected static void a(dt paramdt)
  {
    // Byte code:
    //   0: aload_0
    //   1: invokestatic 300	r:a	(Ljava/lang/Object;)Z
    //   4: ifeq +49 -> 53
    //   7: invokestatic 256	dt:g	()Ldt;
    //   10: astore_1
    //   11: aload_0
    //   12: getfield 122	dt:eg	I
    //   15: aload_0
    //   16: getfield 122	dt:eg	I
    //   19: aload_0
    //   20: getfield 126	dt:ey	I
    //   23: invokestatic 263	et:a	(II)I
    //   26: invokestatic 252	dt:b	(II)Z
    //   29: ldc 1
    //   31: invokevirtual 280	java/lang/String:length	()I
    //   34: pop2
    //   35: aload_1
    //   36: aload_0
    //   37: putfield 112	dt:cs	Ldt;
    //   40: ldc2_w 52
    //   43: invokestatic 285	java/lang/Thread:sleep	(J)V
    //   46: return
    //   47: ldc 1
    //   49: invokevirtual 280	java/lang/String:length	()I
    //   52: pop2
    //   53: return
    // Local variable table:
    //   start	length	slot	name	signature
    //   0	54	0	paramdt	dt
    //   10	26	1	localdt	dt
    //   47	1	2	localInterruptedException	InterruptedException
    // Exception table:
    //   from	to	target	type
    //   40	46	47	java/lang/InterruptedException
  }
  
  /* Error */
  protected static void a(int paramInt)
  {
    // Byte code:
    //   0: getstatic 161	et:b	B
    //   3: iload_0
    //   4: invokestatic 314	r:d	(II)Z
    //   7: ifeq +334 -> 341
    //   10: getstatic 190	r:ab	[I
    //   13: bipush 16
    //   15: iaload
    //   16: invokestatic 272	fn:g	(I)Lfc;
    //   19: astore_1
    //   20: getstatic 190	r:ab	[I
    //   23: bipush 8
    //   25: iaload
    //   26: istore_2
    //   27: aload_1
    //   28: invokestatic 300	r:a	(Ljava/lang/Object;)Z
    //   31: ifeq +138 -> 169
    //   34: aload_1
    //   35: getfield 120	dt:ee	I
    //   38: getstatic 190	r:ab	[I
    //   41: bipush 19
    //   43: iaload
    //   44: invokestatic 314	r:d	(II)Z
    //   47: ifeq +122 -> 169
    //   50: aload_1
    //   51: getfield 122	dt:eg	I
    //   54: invokestatic 256	dt:g	()Ldt;
    //   57: getfield 122	dt:eg	I
    //   60: isub
    //   61: invokestatic 276	java/lang/Math:abs	(I)I
    //   64: getstatic 190	r:ab	[I
    //   67: bipush 20
    //   69: iaload
    //   70: invokestatic 330	r:j	(II)Z
    //   73: ifeq +29 -> 102
    //   76: aload_1
    //   77: getfield 126	dt:ey	I
    //   80: invokestatic 256	dt:g	()Ldt;
    //   83: getfield 126	dt:ey	I
    //   86: isub
    //   87: invokestatic 276	java/lang/Math:abs	(I)I
    //   90: getstatic 190	r:ab	[I
    //   93: bipush 20
    //   95: iaload
    //   96: invokestatic 329	r:i	(II)Z
    //   99: ifeq +196 -> 295
    //   102: aload_1
    //   103: getfield 122	dt:eg	I
    //   106: aload_1
    //   107: getfield 126	dt:ey	I
    //   110: invokestatic 252	dt:b	(II)Z
    //   113: ldc 1
    //   115: invokevirtual 280	java/lang/String:length	()I
    //   118: pop2
    //   119: lconst_0
    //   120: invokestatic 285	java/lang/Thread:sleep	(J)V
    //   123: ldc 1
    //   125: invokevirtual 280	java/lang/String:length	()I
    //   128: pop
    //   129: ldc 4
    //   131: invokevirtual 280	java/lang/String:length	()I
    //   134: ldc 3
    //   136: invokevirtual 280	java/lang/String:length	()I
    //   139: if_icmpne +156 -> 295
    //   142: return
    //   143: ldc 1
    //   145: invokevirtual 280	java/lang/String:length	()I
    //   148: pop2
    //   149: ldc 1
    //   151: invokevirtual 280	java/lang/String:length	()I
    //   154: pop
    //   155: ldc 2
    //   157: invokevirtual 280	java/lang/String:length	()I
    //   160: ldc 4
    //   162: invokevirtual 280	java/lang/String:length	()I
    //   165: if_icmplt +130 -> 295
    //   168: return
    //   169: getstatic 163	et:o	S
    //   172: getstatic 190	r:ab	[I
    //   175: bipush 21
    //   177: iaload
    //   178: invokestatic 314	r:d	(II)Z
    //   181: ifeq +79 -> 260
    //   184: getstatic 163	et:o	S
    //   187: getstatic 190	r:ab	[I
    //   190: bipush 22
    //   192: iaload
    //   193: invokestatic 314	r:d	(II)Z
    //   196: ifeq +64 -> 260
    //   199: getstatic 163	et:o	S
    //   202: getstatic 190	r:ab	[I
    //   205: bipush 23
    //   207: iaload
    //   208: invokestatic 314	r:d	(II)Z
    //   211: ifeq +49 -> 260
    //   214: getstatic 163	et:o	S
    //   217: getstatic 190	r:ab	[I
    //   220: bipush 24
    //   222: iaload
    //   223: invokestatic 314	r:d	(II)Z
    //   226: ifeq +34 -> 260
    //   229: getstatic 163	et:o	S
    //   232: getstatic 190	r:ab	[I
    //   235: bipush 25
    //   237: iaload
    //   238: invokestatic 314	r:d	(II)Z
    //   241: ifeq +19 -> 260
    //   244: getstatic 163	et:o	S
    //   247: getstatic 190	r:ab	[I
    //   250: bipush 26
    //   252: iaload
    //   253: invokestatic 314	r:d	(II)Z
    //   256: ifeq +4 -> 260
    //   259: return
    //   260: getstatic 190	r:ab	[I
    //   263: bipush 14
    //   265: iaload
    //   266: invokestatic 253	dt:d	(I)I
    //   269: dup
    //   270: istore_2
    //   271: invokestatic 325	r:h	(I)Z
    //   274: ifeq +21 -> 295
    //   277: getstatic 190	r:ab	[I
    //   280: bipush 15
    //   282: iaload
    //   283: invokestatic 253	dt:d	(I)I
    //   286: dup
    //   287: istore_2
    //   288: invokestatic 325	r:h	(I)Z
    //   291: ifeq +4 -> 295
    //   294: return
    //   295: invokestatic 284	java/lang/System:currentTimeMillis	()J
    //   298: getstatic 213	r:x	J
    //   301: lsub
    //   302: lconst_0
    //   303: invokestatic 321	r:f	(JJ)I
    //   306: invokestatic 325	r:h	(I)Z
    //   309: ifeq +4 -> 313
    //   312: return
    //   313: invokestatic 237	dl:ae	()Ldl;
    //   316: iload_0
    //   317: iload_2
    //   318: invokevirtual 239	dl:b	(II)V
    //   321: invokestatic 264	et:d	()V
    //   324: invokestatic 284	java/lang/System:currentTimeMillis	()J
    //   327: putstatic 213	r:x	J
    //   330: lconst_0
    //   331: invokestatic 285	java/lang/Thread:sleep	(J)V
    //   334: return
    //   335: ldc 1
    //   337: invokevirtual 280	java/lang/String:length	()I
    //   340: pop2
    //   341: return
    // Local variable table:
    //   start	length	slot	name	signature
    //   0	342	0	paramInt	int
    //   19	88	1	localfc	fc
    //   26	292	2	i1	int
    //   143	1	3	localInterruptedException1	InterruptedException
    //   335	1	4	localInterruptedException2	InterruptedException
    // Exception table:
    //   from	to	target	type
    //   119	123	143	java/lang/InterruptedException
    //   330	334	335	java/lang/InterruptedException
  }
  
  public static void a(e parame)
  {
    "".length();
  }
  
  protected static dt b(dt paramdt)
  {
    dt localdt1 = paramdt;
    int i1 = paramdt.ey;
    int i2 = paramdt.eg;
    paramdt = null;
    dt localdt2 = dt.g();
    int i3 = i2 - localdt2.i() - ab[2];
    int i4 = i2 + localdt2.i() + ab[2];
    if ((i(localdt2.bs.b)) && (d(localdt2.bs.b, ab[3])) && (d(localdt2.bs.b, ab[1])) && (d(localdt2.bs.b, ab[11])))
    {
      "".length();
      if ("  ".length() != (0x50 ^ 0x54)) {
        break label160;
      }
      return null;
    }
    label160:
    int i5 = ab[0] - ab[54];
    if ((i(localdt2.bs.b)) && (d(localdt2.bs.b, ab[3])) && (d(localdt2.bs.b, ab[1])) && (d(localdt2.bs.b, ab[11])))
    {
      "".length();
      if ((0x81 ^ 0x85) != " ".length()) {
        break label276;
      }
      return null;
    }
    label276:
    int i6 = ab[0] + ab[54];
    int i7 = ab[8];
    int i8 = ab[0];
    while (g(i8, fn.ep.size()))
    {
      dt localdt3 = (dt)fn.ep.elementAt(i8);
      int i9 = Math.abs(i2 - localdt3.eg);
      int i10 = Math.abs(i1 - localdt3.ey);
      if (i(i9, i10))
      {
        "".length();
        if (-" ".length() <= 0) {
          break label376;
        }
        return null;
      }
      label376:
      i9 = i10;
      if ((j(i3, localdt3.eg)) && (j(localdt3.eg, i4)) && (j(i5, localdt3.ey)) && (j(localdt3.ey, i6)) && (f(c(localdt3))) && (i(a(localdt2, localdt3))) && (f(dn.f(localdt3.ci))) && ((!d(i7, ab[8])) || (g(i9, i7))))
      {
        paramdt = localdt3;
        i7 = i9;
      }
      i8++;
      "".length();
      if (-(0x21 ^ 0x3A ^ 0x17 ^ 0x9) >= 0) {
        return null;
      }
    }
    localdt1.cs = paramdt;
    return paramdt;
  }
  
  /* Error */
  public static void a(long paramLong)
  {
    // Byte code:
    //   0: lload_0
    //   1: invokestatic 285	java/lang/Thread:sleep	(J)V
    //   4: return
    //   5: ldc 1
    //   7: invokevirtual 280	java/lang/String:length	()I
    //   10: pop2
    //   11: return
    // Local variable table:
    //   start	length	slot	name	signature
    //   0	12	0	paramLong	long
    //   5	1	1	localInterruptedException	InterruptedException
    // Exception table:
    //   from	to	target	type
    //   0	4	5	java/lang/InterruptedException
  }
  
  protected static boolean a(dt paramdt1, dt paramdt2)
  {
    if ((d(paramdt2.ee, ab[10])) && (d(paramdt2.ee, ab[11])) && (d(paramdt2.ee, ab[19])) && ((!d(paramdt2.fm, ab[1])) || (!d(paramdt1.fm, ab[1])) || ((h(paramdt2.fm, ab[3])) && (!d(paramdt1.fm, ab[3]))) || ((h(paramdt2.fm, ab[11])) && (!d(paramdt1.fm, ab[9]))) || ((h(paramdt2.fm, ab[9])) && (!d(paramdt1.fm, ab[11]))) || ((d(paramdt1.eh)) && (!d(paramdt1.eh, paramdt2.fy))) || ((d(paramdt1.ai)) && (!d(paramdt1.ai, paramdt2.fy))) || ((d(paramdt2.eh)) && (h(paramdt2.eh, paramdt1.fy))))) {
      return ab[3];
    }
    return ab[0];
  }
  
  private static boolean c(int paramInt1, int paramInt2)
  {
    if ((!d(paramInt2)) || ((f(paramInt1)) && (!e(paramInt2 & ab[3]))) || ((h(paramInt1, ab[3])) && (!e(paramInt2 & ab[6]))) || ((h(paramInt1, ab[6])) && (!e(paramInt2 & ab[9]))) || ((h(paramInt1, ab[1])) && (g(paramInt2 & ab[28])))) {
      return ab[3];
    }
    return ab[0];
  }
  
  private static boolean d(int paramInt)
  {
    return paramInt >= 0;
  }
  
  public static void b(e parame)
  {
    if ((!f(parame.s)) || ((i(parame.j)) && (d(parame.t, ab[1])) && (d(parame.h, parame.f().j))))
    {
      if ((f(parame.s)) && (f(parame.t))) {
        if (h(parame.h, ab[2] * parame.f().j))
        {
          parame.t = ab[3];
          "".length();
          if (" ".length() != 0) {}
        }
        else
        {
          if ((d(parame.h, ab[4] * parame.f().j)) && (d(parame.v, ab[5]))) {
            return;
          }
          parame.t = ab[6];
        }
      }
      if (f(r.contains(parame))) {
        r.addElement(parame);
      }
    }
  }
  
  private static boolean d(int paramInt1, int paramInt2)
  {
    return paramInt1 != paramInt2;
  }
  
  protected final void e()
  {
    if (d(et.o, ab[20]))
    {
      a(ab[20], ab[73], ab[8], ab[8]);
      return;
    }
    dt localdt;
    if (a((localdt = dt.g()).m))
    {
      int i1 = ab[0];
      while (g(i1, localdt.az.size()))
      {
        fy localfy;
        if ((a(localfy = (fy)localdt.az.elementAt(i1))) && (f(localfy.c())) && (f(localfy.a.e, ab[62])) && (j(localfy.a.e, ab[63])))
        {
          dl.ae().l(localfy.a.e);
          dl.ae().v();
          cn.h();
          "".length();
          if (null == null) {
            break;
          }
        }
        else
        {
          i1++;
          "".length();
          if (" ".length() <= -" ".length()) {
            return;
          }
        }
      }
      fn.b(ab[74]);
      dl.ae().l(ab[74], ab[1]);
      cn.h();
      return;
    }
  }
  
  private static int a(long paramLong1, long paramLong2)
  {
    return paramLong1 < paramLong2;
  }
  
  /* Error */
  protected e a(dt paramdt1, int paramInt1, int paramInt2, dt paramdt2, boolean paramBoolean)
  {
    // Byte code:
    //   0: getstatic 96	dn:l	Z
    //   3: invokestatic 328	r:i	(I)Z
    //   6: ifeq +34 -> 40
    //   9: getstatic 88	dn:aj	Lci;
    //   12: invokevirtual 288	java/util/Vector:size	()I
    //   15: invokestatic 323	r:g	(I)Z
    //   18: ifeq +22 -> 40
    //   21: aload_0
    //   22: iload_3
    //   23: iload 5
    //   25: invokevirtual 293	r:a	(IZ)V
    //   28: aload_1
    //   29: getfield 122	dt:eg	I
    //   32: aload_1
    //   33: getfield 126	dt:ey	I
    //   36: invokestatic 290	r:a	(II)Le;
    //   39: areturn
    //   40: iload_3
    //   41: istore 6
    //   43: iload_2
    //   44: istore 7
    //   46: aload_1
    //   47: getfield 126	dt:ey	I
    //   50: istore_3
    //   51: aload_1
    //   52: getfield 122	dt:eg	I
    //   55: istore_2
    //   56: aload_0
    //   57: astore_1
    //   58: getstatic 190	r:ab	[I
    //   61: bipush 8
    //   63: iaload
    //   64: istore 8
    //   66: getstatic 190	r:ab	[I
    //   69: bipush 8
    //   71: iaload
    //   72: istore 9
    //   74: getstatic 190	r:ab	[I
    //   77: bipush 8
    //   79: iaload
    //   80: istore 10
    //   82: aconst_null
    //   83: astore 11
    //   85: getstatic 172	fn:bv	Lci;
    //   88: astore 12
    //   90: getstatic 190	r:ab	[I
    //   93: iconst_0
    //   94: iaload
    //   95: istore 13
    //   97: iload 13
    //   99: aload 12
    //   101: invokevirtual 288	java/util/Vector:size	()I
    //   104: invokestatic 320	r:f	(II)Z
    //   107: ifeq +18 -> 125
    //   110: aload 11
    //   112: astore_1
    //   113: ldc 1
    //   115: invokevirtual 280	java/lang/String:length	()I
    //   118: pop
    //   119: aconst_null
    //   120: ifnull +890 -> 1010
    //   123: aconst_null
    //   124: areturn
    //   125: aload 12
    //   127: iload 13
    //   129: invokevirtual 221	ci:elementAt	(I)Ljava/lang/Object;
    //   132: checkcast 27	e
    //   135: dup
    //   136: astore 14
    //   138: invokestatic 300	r:a	(Ljava/lang/Object;)Z
    //   141: ifeq +842 -> 983
    //   144: aload 14
    //   146: getfield 149	e:x	I
    //   149: invokestatic 323	r:g	(I)Z
    //   152: ifeq +831 -> 983
    //   155: aload 14
    //   157: getfield 140	e:j	I
    //   160: invokestatic 328	r:i	(I)Z
    //   163: ifeq +820 -> 983
    //   166: aload 14
    //   168: getfield 140	e:j	I
    //   171: getstatic 190	r:ab	[I
    //   174: iconst_3
    //   175: iaload
    //   176: invokestatic 314	r:d	(II)Z
    //   179: ifeq +804 -> 983
    //   182: aload 14
    //   184: iload 7
    //   186: invokestatic 299	r:a	(Le;I)Z
    //   189: invokestatic 328	r:i	(I)Z
    //   192: ifeq +791 -> 983
    //   195: aload 14
    //   197: getfield 146	e:t	S
    //   200: iload 6
    //   202: invokestatic 308	r:c	(II)Z
    //   205: invokestatic 328	r:i	(I)Z
    //   208: ifeq +775 -> 983
    //   211: aload 4
    //   213: invokestatic 300	r:a	(Ljava/lang/Object;)Z
    //   216: ifeq +55 -> 271
    //   219: aload 4
    //   221: getfield 131	dt:fy	I
    //   224: invokestatic 256	dt:g	()Ldt;
    //   227: getfield 131	dt:fy	I
    //   230: invokestatic 314	r:d	(II)Z
    //   233: ifeq +38 -> 271
    //   236: aload 14
    //   238: getfield 143	e:n	I
    //   241: aload 14
    //   243: getfield 137	e:d	I
    //   246: aload 4
    //   248: getfield 122	dt:eg	I
    //   251: aload 4
    //   253: getfield 126	dt:ey	I
    //   256: invokestatic 218	bc:a	(IIII)I
    //   259: getstatic 190	r:ab	[I
    //   262: bipush 56
    //   264: iaload
    //   265: invokestatic 330	r:j	(II)Z
    //   268: ifeq +715 -> 983
    //   271: aload_1
    //   272: iload 6
    //   274: aload 14
    //   276: getfield 147	e:u	I
    //   279: aload 14
    //   281: getfield 141	e:l	I
    //   284: invokespecial 291	r:a	(III)Z
    //   287: invokestatic 319	r:f	(I)Z
    //   290: ifeq +693 -> 983
    //   293: aload_1
    //   294: aload 14
    //   296: getfield 147	e:u	I
    //   299: aload 14
    //   301: getfield 141	e:l	I
    //   304: invokespecial 317	r:e	(II)Z
    //   307: invokestatic 319	r:f	(I)Z
    //   310: ifeq +673 -> 983
    //   313: aload_1
    //   314: getfield 198	r:h	Z
    //   317: invokestatic 328	r:i	(I)Z
    //   320: ifeq +237 -> 557
    //   323: aload_1
    //   324: getfield 194	r:d	I
    //   327: getstatic 190	r:ab	[I
    //   330: bipush 57
    //   332: iaload
    //   333: invokestatic 314	r:d	(II)Z
    //   336: ifeq +164 -> 500
    //   339: aload_1
    //   340: getfield 194	r:d	I
    //   343: getstatic 190	r:ab	[I
    //   346: bipush 58
    //   348: iaload
    //   349: invokestatic 314	r:d	(II)Z
    //   352: ifeq +148 -> 500
    //   355: aload_1
    //   356: getfield 194	r:d	I
    //   359: getstatic 190	r:ab	[I
    //   362: bipush 59
    //   364: iaload
    //   365: invokestatic 314	r:d	(II)Z
    //   368: ifeq +132 -> 500
    //   371: iload 8
    //   373: getstatic 190	r:ab	[I
    //   376: bipush 8
    //   378: iaload
    //   379: invokestatic 314	r:d	(II)Z
    //   382: ifeq +55 -> 437
    //   385: aload 14
    //   387: getfield 146	e:t	S
    //   390: iload 10
    //   392: invokestatic 320	r:f	(II)Z
    //   395: ifeq +42 -> 437
    //   398: aload 14
    //   400: getfield 137	e:d	I
    //   403: iload 8
    //   405: invokestatic 320	r:f	(II)Z
    //   408: ifeq +29 -> 437
    //   411: aload 14
    //   413: getfield 137	e:d	I
    //   416: iload 8
    //   418: invokestatic 326	r:h	(II)Z
    //   421: ifeq +562 -> 983
    //   424: aload 14
    //   426: getfield 143	e:n	I
    //   429: iload 9
    //   431: invokestatic 324	r:g	(II)Z
    //   434: ifeq +549 -> 983
    //   437: aload 14
    //   439: getfield 146	e:t	S
    //   442: istore 10
    //   444: aload 14
    //   446: getfield 137	e:d	I
    //   449: istore 8
    //   451: aload 14
    //   453: getfield 143	e:n	I
    //   456: istore 9
    //   458: aload 14
    //   460: astore 11
    //   462: ldc 1
    //   464: invokevirtual 280	java/lang/String:length	()I
    //   467: pop
    //   468: bipush 61
    //   470: sipush 131
    //   473: iadd
    //   474: bipush 121
    //   476: isub
    //   477: bipush 87
    //   479: iadd
    //   480: sipush 131
    //   483: bipush 93
    //   485: iadd
    //   486: sipush 183
    //   489: isub
    //   490: bipush 113
    //   492: iadd
    //   493: ixor
    //   494: ineg
    //   495: ifle +488 -> 983
    //   498: aconst_null
    //   499: areturn
    //   500: aload 14
    //   502: getfield 145	e:s	Z
    //   505: invokestatic 328	r:i	(I)Z
    //   508: ifeq +475 -> 983
    //   511: aload 14
    //   513: astore_1
    //   514: ldc 1
    //   516: invokevirtual 280	java/lang/String:length	()I
    //   519: pop
    //   520: bipush 97
    //   522: bipush 70
    //   524: ixor
    //   525: ldc 3
    //   527: invokevirtual 280	java/lang/String:length	()I
    //   530: ixor
    //   531: bipush 81
    //   533: bipush 37
    //   535: ixor
    //   536: sipush 209
    //   539: sipush 128
    //   542: ixor
    //   543: ixor
    //   544: ldc 2
    //   546: invokevirtual 280	java/lang/String:length	()I
    //   549: ineg
    //   550: ixor
    //   551: iand
    //   552: ifeq +458 -> 1010
    //   555: aconst_null
    //   556: areturn
    //   557: getstatic 93	dn:c	I
    //   560: getstatic 190	r:ab	[I
    //   563: bipush 8
    //   565: iaload
    //   566: invokestatic 314	r:d	(II)Z
    //   569: ifeq +31 -> 600
    //   572: getstatic 86	dn:ag	I
    //   575: getstatic 100	dn:x	I
    //   578: aload 14
    //   580: getfield 143	e:n	I
    //   583: aload 14
    //   585: getfield 137	e:d	I
    //   588: invokestatic 218	bc:a	(IIII)I
    //   591: getstatic 93	dn:c	I
    //   594: invokestatic 330	r:j	(II)Z
    //   597: ifeq +386 -> 983
    //   600: aload 12
    //   602: astore 15
    //   604: aload 14
    //   606: astore 16
    //   608: getstatic 190	r:ab	[I
    //   611: iconst_0
    //   612: iaload
    //   613: istore 17
    //   615: getstatic 190	r:ab	[I
    //   618: iconst_0
    //   619: iaload
    //   620: istore 18
    //   622: iload 18
    //   624: aload 15
    //   626: invokevirtual 288	java/util/Vector:size	()I
    //   629: invokestatic 324	r:g	(II)Z
    //   632: ifeq +167 -> 799
    //   635: aload 15
    //   637: iload 18
    //   639: invokevirtual 221	ci:elementAt	(I)Ljava/lang/Object;
    //   642: checkcast 27	e
    //   645: dup
    //   646: astore 19
    //   648: invokestatic 300	r:a	(Ljava/lang/Object;)Z
    //   651: ifeq +124 -> 775
    //   654: aload 19
    //   656: getfield 149	e:x	I
    //   659: invokestatic 323	r:g	(I)Z
    //   662: ifeq +113 -> 775
    //   665: aload 19
    //   667: getfield 140	e:j	I
    //   670: invokestatic 328	r:i	(I)Z
    //   673: ifeq +102 -> 775
    //   676: aload 19
    //   678: getfield 140	e:j	I
    //   681: getstatic 190	r:ab	[I
    //   684: iconst_3
    //   685: iaload
    //   686: invokestatic 314	r:d	(II)Z
    //   689: ifeq +86 -> 775
    //   692: aload 16
    //   694: iload 7
    //   696: invokestatic 299	r:a	(Le;I)Z
    //   699: invokestatic 328	r:i	(I)Z
    //   702: ifeq +73 -> 775
    //   705: aload 16
    //   707: getfield 146	e:t	S
    //   710: iload 6
    //   712: invokestatic 308	r:c	(II)Z
    //   715: invokestatic 328	r:i	(I)Z
    //   718: ifeq +57 -> 775
    //   721: aload 19
    //   723: getfield 147	e:u	I
    //   726: aload 16
    //   728: getfield 147	e:u	I
    //   731: isub
    //   732: invokestatic 217	bc:a	(I)I
    //   735: getstatic 190	r:ab	[I
    //   738: iconst_4
    //   739: iaload
    //   740: invokestatic 330	r:j	(II)Z
    //   743: ifeq +32 -> 775
    //   746: aload 19
    //   748: getfield 141	e:l	I
    //   751: aload 16
    //   753: getfield 141	e:l	I
    //   756: isub
    //   757: invokestatic 217	bc:a	(I)I
    //   760: getstatic 190	r:ab	[I
    //   763: bipush 60
    //   765: iaload
    //   766: invokestatic 330	r:j	(II)Z
    //   769: ifeq +6 -> 775
    //   772: iinc 17 1
    //   775: iinc 18 1
    //   778: ldc 1
    //   780: invokevirtual 280	java/lang/String:length	()I
    //   783: pop
    //   784: ldc 4
    //   786: invokevirtual 280	java/lang/String:length	()I
    //   789: ldc 4
    //   791: invokevirtual 280	java/lang/String:length	()I
    //   794: if_icmple -172 -> 622
    //   797: aconst_null
    //   798: areturn
    //   799: iload 17
    //   801: getstatic 203	r:m	Lfy;
    //   804: getfield 185	fy:i	I
    //   807: invokestatic 329	r:i	(II)Z
    //   810: ifeq +11 -> 821
    //   813: getstatic 203	r:m	Lfy;
    //   816: getfield 185	fy:i	I
    //   819: istore 17
    //   821: aload 16
    //   823: getfield 146	e:t	S
    //   826: getstatic 190	r:ab	[I
    //   829: bipush 9
    //   831: iaload
    //   832: ishl
    //   833: iload 17
    //   835: getstatic 190	r:ab	[I
    //   838: bipush 19
    //   840: iaload
    //   841: iand
    //   842: ior
    //   843: istore 17
    //   845: aload 4
    //   847: invokestatic 300	r:a	(Ljava/lang/Object;)Z
    //   850: ifeq +74 -> 924
    //   853: aload 4
    //   855: getfield 131	dt:fy	I
    //   858: invokestatic 256	dt:g	()Ldt;
    //   861: getfield 131	dt:fy	I
    //   864: invokestatic 314	r:d	(II)Z
    //   867: ifeq +57 -> 924
    //   870: aload 4
    //   872: getfield 122	dt:eg	I
    //   875: aload 4
    //   877: getfield 126	dt:ey	I
    //   880: aload 14
    //   882: getfield 143	e:n	I
    //   885: aload 14
    //   887: getfield 137	e:d	I
    //   890: invokestatic 218	bc:a	(IIII)I
    //   893: ldc 1
    //   895: invokevirtual 280	java/lang/String:length	()I
    //   898: pop
    //   899: bipush 24
    //   901: bipush 57
    //   903: ixor
    //   904: sipush 187
    //   907: sipush 154
    //   910: ixor
    //   911: iconst_m1
    //   912: ixor
    //   913: iand
    //   914: ldc 3
    //   916: invokevirtual 280	java/lang/String:length	()I
    //   919: if_icmple +20 -> 939
    //   922: aconst_null
    //   923: areturn
    //   924: iload_2
    //   925: iload_3
    //   926: aload 14
    //   928: getfield 143	e:n	I
    //   931: aload 14
    //   933: getfield 137	e:d	I
    //   936: invokestatic 218	bc:a	(IIII)I
    //   939: istore 18
    //   941: iload 17
    //   943: iload 10
    //   945: invokestatic 330	r:j	(II)Z
    //   948: ifeq +23 -> 971
    //   951: iload 17
    //   953: iload 10
    //   955: invokestatic 326	r:h	(II)Z
    //   958: ifeq +25 -> 983
    //   961: iload 18
    //   963: iload 8
    //   965: invokestatic 324	r:g	(II)Z
    //   968: ifeq +15 -> 983
    //   971: iload 17
    //   973: istore 10
    //   975: iload 18
    //   977: istore 8
    //   979: aload 14
    //   981: astore 11
    //   983: iinc 13 1
    //   986: ldc 1
    //   988: invokevirtual 280	java/lang/String:length	()I
    //   991: pop
    //   992: sipush 211
    //   995: sipush 136
    //   998: ixor
    //   999: bipush 113
    //   1001: bipush 46
    //   1003: ixor
    //   1004: ixor
    //   1005: ifgt -908 -> 97
    //   1008: aconst_null
    //   1009: areturn
    //   1010: aload_1
    //   1011: invokestatic 300	r:a	(Ljava/lang/Object;)Z
    //   1014: ifeq +10 -> 1024
    //   1017: aload_0
    //   1018: aload_1
    //   1019: invokevirtual 311	r:c	(Le;)V
    //   1022: aload_1
    //   1023: areturn
    //   1024: invokestatic 284	java/lang/System:currentTimeMillis	()J
    //   1027: aload_0
    //   1028: getfield 210	r:u	J
    //   1031: lsub
    //   1032: ldc2_w 56
    //   1035: invokestatic 294	r:a	(JJ)I
    //   1038: invokestatic 323	r:g	(I)Z
    //   1041: ifeq +140 -> 1181
    //   1044: aload_0
    //   1045: invokevirtual 322	r:g	()Z
    //   1048: invokestatic 319	r:f	(I)Z
    //   1051: ifeq +130 -> 1181
    //   1054: aload_0
    //   1055: getfield 198	r:h	Z
    //   1058: invokestatic 328	r:i	(I)Z
    //   1061: ifeq +99 -> 1160
    //   1064: getstatic 163	et:o	S
    //   1067: invokestatic 267	et:m	(I)I
    //   1070: dup
    //   1071: istore 14
    //   1073: invokestatic 313	r:d	(I)Z
    //   1076: ifeq +9 -> 1085
    //   1079: aload_0
    //   1080: iload 14
    //   1082: putfield 194	r:d	I
    //   1085: aload_0
    //   1086: aload_0
    //   1087: getstatic 190	r:ab	[I
    //   1090: bipush 8
    //   1092: iaload
    //   1093: dup_x1
    //   1094: putfield 205	r:o	I
    //   1097: putfield 209	r:t	I
    //   1100: ldc2_w 50
    //   1103: invokestatic 285	java/lang/Thread:sleep	(J)V
    //   1106: ldc 1
    //   1108: invokevirtual 280	java/lang/String:length	()I
    //   1111: pop
    //   1112: bipush 18
    //   1114: bipush 110
    //   1116: ixor
    //   1117: bipush 118
    //   1119: bipush 14
    //   1121: ixor
    //   1122: ixor
    //   1123: ldc 3
    //   1125: invokevirtual 280	java/lang/String:length	()I
    //   1128: if_icmpge +53 -> 1181
    //   1131: aconst_null
    //   1132: areturn
    //   1133: ldc 1
    //   1135: invokevirtual 280	java/lang/String:length	()I
    //   1138: pop2
    //   1139: ldc 1
    //   1141: invokevirtual 280	java/lang/String:length	()I
    //   1144: pop
    //   1145: ldc 2
    //   1147: invokevirtual 280	java/lang/String:length	()I
    //   1150: ldc 2
    //   1152: invokevirtual 280	java/lang/String:length	()I
    //   1155: if_icmpeq +26 -> 1181
    //   1158: aconst_null
    //   1159: areturn
    //   1160: iload 5
    //   1162: invokestatic 328	r:i	(I)Z
    //   1165: ifeq +16 -> 1181
    //   1168: getstatic 104	dt:ax	Z
    //   1171: invokestatic 328	r:i	(I)Z
    //   1174: ifeq +7 -> 1181
    //   1177: aload_0
    //   1178: invokespecial 312	r:d	()V
    //   1181: aconst_null
    //   1182: areturn
    // Local variable table:
    //   start	length	slot	name	signature
    //   0	1183	0	this	r
    //   0	1183	1	paramdt1	dt
    //   0	1183	2	paramInt1	int
    //   0	1183	3	paramInt2	int
    //   0	1183	4	paramdt2	dt
    //   0	1183	5	paramBoolean	boolean
    //   41	670	6	i1	int
    //   44	651	7	i2	int
    //   64	914	8	i3	int
    //   72	385	9	i4	int
    //   80	894	10	i5	int
    //   83	899	11	localObject	Object
    //   88	513	12	localci1	ci
    //   95	889	13	i6	int
    //   136	844	14	locale1	e
    //   1071	10	14	i7	int
    //   602	34	15	localci2	ci
    //   606	216	16	locale2	e
    //   613	359	17	i8	int
    //   620	356	18	i9	int
    //   646	101	19	locale3	e
    //   1133	1	21	localInterruptedException	InterruptedException
    // Exception table:
    //   from	to	target	type
    //   1100	1106	1133	java/lang/InterruptedException
  }
  
  public static void f()
  {
    y.removeAllElements();
  }
  
  protected static e a(int paramInt1, int paramInt2)
  {
    Object localObject = null;
    dt localdt = dt.g();
    int i2 = paramInt1 - localdt.i() - ab[2];
    int i3 = paramInt1 + localdt.i() + ab[2];
    if ((i(localdt.bs.b)) && (d(localdt.bs.b, ab[3])) && (d(localdt.bs.b, ab[1])) && (d(localdt.bs.b, ab[11])))
    {
      "".length();
      if (" ".length() > 0) {
        break label135;
      }
      return null;
    }
    label135:
    int i4 = ab[0] - ab[54];
    int i1;
    if (i(i1 = paramInt2 + localdt.ab(), paramInt2 + ab[55])) {
      i1 = paramInt2 + ab[55];
    }
    int i5 = ab[8];
    int i6 = ab[0];
    while (g(i6, fn.bv.size()))
    {
      e locale = (e)fn.bv.elementAt(i6);
      int i7 = Math.abs(paramInt1 - locale.u);
      int i8 = Math.abs(paramInt2 - locale.l);
      if (i(i7, i8))
      {
        "".length();
        if (-"  ".length() <= 0) {
          break label266;
        }
        return null;
      }
      label266:
      i7 = i8;
      if ((j(i2, locale.u)) && (j(locale.u, i3)) && (j(i4, locale.l)) && (j(locale.l, i1)) && (i(locale.j)) && (d(locale.j, ab[3])) && ((!d(i5, ab[8])) || (g(i7, i5))))
      {
        localObject = locale;
        i5 = i7;
      }
      i6++;
      "".length();
      if (-"  ".length() > 0) {
        return null;
      }
    }
    return (e)localObject;
  }
  
  private static int b(long paramLong1, long paramLong2)
  {
    return paramLong1 < paramLong2;
  }
  
  private static boolean e(int paramInt)
  {
    return paramInt <= 0;
  }
  
  protected boolean g()
  {
    if ((f(this instanceof bm)) && (f(dn.f)))
    {
      dt localdt = dt.g();
      if (h(dn.j))
      {
        "".length();
        if (((0x22 ^ 0x5) & (0x5D ^ 0x7A ^ 0xFFFFFFFF)) != -" ".length()) {
          break label84;
        }
        return (0xF7 ^ 0x96) & (0x45 ^ 0x24 ^ 0xFFFFFFFF);
      }
      label84:
      int i1 = dn.j;
      int i2 = ab[0];
      while (g(i2, fn.ch.size()))
      {
        es locales;
        if ((f((locales = (es)fn.ch.elementAt(i2)).e)) && (((h(localdt.bs.b, ab[3])) && (!d(locales.k.f, ab[71]))) || (((!d(locales.k.b, ab[72])) || ((i(dn.a(locales.k))) && ((!j(dt.f(), ab[6])) || ((i(locales.k.c)) && (i(dt.n(locales.k.f))))))) && ((!d(i1)) || (g(bc.a(localdt.eg, localdt.ey, locales.f, locales.i), i1))) && (f(e(locales.d, locales.j)))))) {
          return ab[3];
        }
        i2++;
        "".length();
        if (" ".length() >= "   ".length()) {
          return ('µ' + 117 - 112 + 16 ^ '' + 113 - 251 + 146) & (0x15 ^ 0x42 ^ 0x81 ^ 0x88 ^ -" ".length());
        }
      }
      return ab[0];
    }
    return ab[0];
  }
  
  private static int c(long paramLong1, long paramLong2)
  {
    return paramLong1 < paramLong2;
  }
  
  private boolean e(int paramInt1, int paramInt2)
  {
    if ((i(dt.ex)) && (f(this instanceof bm)))
    {
      int i1 = ab[0];
      while (g(i1, y.size()))
      {
        dt localdt;
        if ((f(c(localdt = (dt)y.elementAt(i1)))) && (j(bc.a(paramInt1 - localdt.eg), ab[7])) && (j(bc.a(paramInt2 - localdt.ey), ab[7]))) {
          return ab[3];
        }
        i1++;
        "".length();
        if (-" ".length() > (('Â' + 78 - 197 + 160 ^ '¿' + 98 - 143 + 48) & (0x9E ^ 0xB3 ^ 0x24 ^ 0x20 ^ -" ".length()))) {
          return (0xED ^ 0x97 ^ 0xC7 ^ 0x89) & (63 + 47 - -33 + 42 ^ 85 + 74 - 58 + 40 ^ -" ".length());
        }
      }
      return ab[0];
    }
    return ab[0];
  }
  
  public static void h()
  {
    r.removeAllElements();
  }
  
  private static int d(long paramLong1, long paramLong2)
  {
    return paramLong1 < paramLong2;
  }
  
  private static boolean f(int paramInt1, int paramInt2)
  {
    return paramInt1 >= paramInt2;
  }
  
  protected static boolean i()
  {
    dt localdt;
    if ((i((localdt = dt.g()).aa)) && (g(localdt.ef, localdt.cw)))
    {
      int i1 = ab[0];
      while (g(i1, localdt.be.size()))
      {
        bt localbt;
        if ((a(localbt = (bt)localdt.be.elementAt(i1))) && (h(localbt.a.a, ab[74]))) {
          return ab[3];
        }
        i1++;
        "".length();
        if (null != null) {
          return (0xC6 ^ 0xB8 ^ 0x50 ^ 0x8) & (0x56 ^ 0x27 ^ 0x1E ^ 0x49 ^ -" ".length());
        }
      }
    }
    return ab[0];
  }
  
  /* Error */
  protected final void a(int paramInt1, int paramInt2, int paramInt3, int paramInt4)
  {
    // Byte code:
    //   0: iload_1
    //   1: getstatic 190	r:ab	[I
    //   4: bipush 12
    //   6: iaload
    //   7: invokestatic 320	r:f	(II)Z
    //   10: ifeq +16 -> 26
    //   13: iload_1
    //   14: getstatic 190	r:ab	[I
    //   17: bipush 13
    //   19: iaload
    //   20: invokestatic 329	r:i	(II)Z
    //   23: ifeq +37 -> 60
    //   26: getstatic 163	et:o	S
    //   29: getstatic 190	r:ab	[I
    //   32: bipush 12
    //   34: iaload
    //   35: invokestatic 320	r:f	(II)Z
    //   38: ifeq +22 -> 60
    //   41: getstatic 163	et:o	S
    //   44: getstatic 190	r:ab	[I
    //   47: bipush 13
    //   49: iaload
    //   50: invokestatic 330	r:j	(II)Z
    //   53: ifeq +7 -> 60
    //   56: invokestatic 333	r:n	()V
    //   59: return
    //   60: getstatic 163	et:o	S
    //   63: iload_1
    //   64: invokestatic 314	r:d	(II)Z
    //   67: ifeq +151 -> 218
    //   70: iload_1
    //   71: invokestatic 266	et:e	(I)Z
    //   74: invokestatic 319	r:f	(I)Z
    //   77: ifeq +37 -> 114
    //   80: iload_1
    //   81: invokestatic 268	et:n	(I)Z
    //   84: invokestatic 319	r:f	(I)Z
    //   87: ifeq +13 -> 100
    //   90: iload_1
    //   91: invokestatic 265	et:d	(I)Z
    //   94: invokestatic 328	r:i	(I)Z
    //   97: ifeq +16 -> 113
    //   100: ldc2_w 56
    //   103: invokestatic 285	java/lang/Thread:sleep	(J)V
    //   106: return
    //   107: ldc 1
    //   109: invokevirtual 280	java/lang/String:length	()I
    //   112: pop2
    //   113: return
    //   114: iload_2
    //   115: getstatic 190	r:ab	[I
    //   118: bipush 8
    //   120: iaload
    //   121: invokestatic 320	r:f	(II)Z
    //   124: ifeq +65 -> 189
    //   127: getstatic 161	et:b	B
    //   130: iload_2
    //   131: invokestatic 314	r:d	(II)Z
    //   134: ifeq +55 -> 189
    //   137: ldc2_w 56
    //   140: invokestatic 285	java/lang/Thread:sleep	(J)V
    //   143: ldc 1
    //   145: invokevirtual 280	java/lang/String:length	()I
    //   148: pop
    //   149: ldc 2
    //   151: invokevirtual 280	java/lang/String:length	()I
    //   154: ldc 4
    //   156: invokevirtual 280	java/lang/String:length	()I
    //   159: if_icmple +59 -> 218
    //   162: return
    //   163: ldc 1
    //   165: invokevirtual 280	java/lang/String:length	()I
    //   168: pop2
    //   169: ldc 1
    //   171: invokevirtual 280	java/lang/String:length	()I
    //   174: pop
    //   175: ldc 3
    //   177: invokevirtual 280	java/lang/String:length	()I
    //   180: ldc 2
    //   182: invokevirtual 280	java/lang/String:length	()I
    //   185: if_icmpne +33 -> 218
    //   188: return
    //   189: ldc2_w 56
    //   192: invokestatic 285	java/lang/Thread:sleep	(J)V
    //   195: ldc 1
    //   197: invokevirtual 280	java/lang/String:length	()I
    //   200: pop
    //   201: sipush 140
    //   204: sipush 136
    //   207: ixor
    //   208: ifgt +10 -> 218
    //   211: return
    //   212: ldc 1
    //   214: invokevirtual 280	java/lang/String:length	()I
    //   217: pop2
    //   218: iload_2
    //   219: getstatic 190	r:ab	[I
    //   222: bipush 8
    //   224: iaload
    //   225: invokestatic 326	r:h	(II)Z
    //   228: ifeq +78 -> 306
    //   231: getstatic 99	dn:q	Z
    //   234: invokestatic 328	r:i	(I)Z
    //   237: ifeq +41 -> 278
    //   240: getstatic 89	dn:al	[I
    //   243: astore_1
    //   244: getstatic 190	r:ab	[I
    //   247: iconst_0
    //   248: iaload
    //   249: putstatic 85	dn:af	I
    //   252: aload_0
    //   253: aload_1
    //   254: getstatic 190	r:ab	[I
    //   257: iconst_0
    //   258: iaload
    //   259: iaload
    //   260: dup_x1
    //   261: putfield 196	r:f	I
    //   264: invokestatic 289	r:a	(I)V
    //   267: ldc 1
    //   269: invokevirtual 280	java/lang/String:length	()I
    //   272: pop
    //   273: aconst_null
    //   274: ifnull +43 -> 317
    //   277: return
    //   278: aload_0
    //   279: iload_2
    //   280: invokevirtual 303	r:b	(I)V
    //   283: ldc 1
    //   285: invokevirtual 280	java/lang/String:length	()I
    //   288: pop
    //   289: bipush 110
    //   291: bipush 101
    //   293: ixor
    //   294: bipush 119
    //   296: bipush 124
    //   298: ixor
    //   299: iconst_m1
    //   300: ixor
    //   301: iand
    //   302: ifge +15 -> 317
    //   305: return
    //   306: iload_2
    //   307: invokestatic 313	r:d	(I)Z
    //   310: ifeq +7 -> 317
    //   313: iload_2
    //   314: invokestatic 289	r:a	(I)V
    //   317: getstatic 161	et:b	B
    //   320: aload_0
    //   321: getfield 196	r:f	I
    //   324: invokestatic 326	r:h	(II)Z
    //   327: ifeq +88 -> 415
    //   330: iload_3
    //   331: invokestatic 323	r:g	(I)Z
    //   334: ifeq +81 -> 415
    //   337: iload 4
    //   339: invokestatic 323	r:g	(I)Z
    //   342: ifeq +73 -> 415
    //   345: invokestatic 256	dt:g	()Ldt;
    //   348: getfield 122	dt:eg	I
    //   351: iload_3
    //   352: invokestatic 314	r:d	(II)Z
    //   355: ifeq +60 -> 415
    //   358: invokestatic 256	dt:g	()Ldt;
    //   361: getfield 126	dt:ey	I
    //   364: iload 4
    //   366: invokestatic 314	r:d	(II)Z
    //   369: ifeq +46 -> 415
    //   372: aload_0
    //   373: instanceof 46
    //   376: invokestatic 319	r:f	(I)Z
    //   379: ifeq +13 -> 392
    //   382: aload_0
    //   383: instanceof 17
    //   386: invokestatic 328	r:i	(I)Z
    //   389: ifeq +16 -> 405
    //   392: iload_3
    //   393: iload 4
    //   395: invokestatic 252	dt:b	(II)Z
    //   398: ldc 1
    //   400: invokevirtual 280	java/lang/String:length	()I
    //   403: pop2
    //   404: return
    //   405: aload_0
    //   406: iload_3
    //   407: iload 4
    //   409: invokestatic 290	r:a	(II)Le;
    //   412: invokevirtual 311	r:c	(Le;)V
    //   415: return
    // Local variable table:
    //   start	length	slot	name	signature
    //   0	416	0	this	r
    //   0	416	1	paramInt1	int
    //   0	416	2	paramInt2	int
    //   0	416	3	paramInt3	int
    //   0	416	4	paramInt4	int
    //   107	1	5	localInterruptedException1	InterruptedException
    //   163	1	6	localInterruptedException2	InterruptedException
    //   212	1	7	localInterruptedException3	InterruptedException
    // Exception table:
    //   from	to	target	type
    //   100	106	107	java/lang/InterruptedException
    //   137	143	163	java/lang/InterruptedException
    //   189	195	212	java/lang/InterruptedException
  }
  
  protected final boolean j()
  {
    if ((i(this.a)) && (g(fn.ax.size())) && (d(((bk)fn.ax.firstElement()).g, dt.g().fy))) {
      return ab[3];
    }
    return ab[0];
  }
  
  /* Error */
  protected final void b(int paramInt1, int paramInt2)
  {
    // Byte code:
    //   0: invokestatic 249	dn:g	()V
    //   3: invokestatic 256	dt:g	()Ldt;
    //   6: astore_3
    //   7: invokestatic 327	r:i	()Z
    //   10: invokestatic 319	r:f	(I)Z
    //   13: ifeq +4768 -> 4781
    //   16: aload_0
    //   17: getfield 188	r:a	Z
    //   20: invokestatic 328	r:i	(I)Z
    //   23: ifeq +42 -> 65
    //   26: getstatic 171	fn:ax	Lci;
    //   29: invokevirtual 288	java/util/Vector:size	()I
    //   32: invokestatic 323	r:g	(I)Z
    //   35: ifeq +30 -> 65
    //   38: getstatic 171	fn:ax	Lci;
    //   41: invokevirtual 287	java/util/Vector:firstElement	()Ljava/lang/Object;
    //   44: checkcast 14	bk
    //   47: getfield 77	bk:f	Ldt;
    //   50: ldc 1
    //   52: invokevirtual 280	java/lang/String:length	()I
    //   55: pop
    //   56: ldc 2
    //   58: invokevirtual 280	java/lang/String:length	()I
    //   61: ifge +5 -> 66
    //   64: return
    //   65: aconst_null
    //   66: astore 4
    //   68: aload_0
    //   69: getfield 188	r:a	Z
    //   72: invokestatic 328	r:i	(I)Z
    //   75: ifeq +37 -> 112
    //   78: getstatic 92	dn:as	Ljava/lang/String;
    //   81: invokestatic 300	r:a	(Ljava/lang/Object;)Z
    //   84: ifeq +28 -> 112
    //   87: aload_3
    //   88: getfield 111	dt:ci	Ljava/lang/String;
    //   91: getstatic 92	dn:as	Ljava/lang/String;
    //   94: invokevirtual 279	java/lang/String:equals	(Ljava/lang/Object;)Z
    //   97: invokestatic 328	r:i	(I)Z
    //   100: ifeq +32 -> 132
    //   103: invokestatic 228	cn:l	()Z
    //   106: invokestatic 328	r:i	(I)Z
    //   109: ifeq +23 -> 132
    //   112: getstatic 190	r:ab	[I
    //   115: iconst_3
    //   116: iaload
    //   117: ldc 1
    //   119: invokevirtual 280	java/lang/String:length	()I
    //   122: pop
    //   123: ldc 4
    //   125: invokevirtual 280	java/lang/String:length	()I
    //   128: ifne +9 -> 137
    //   131: return
    //   132: getstatic 190	r:ab	[I
    //   135: iconst_0
    //   136: iaload
    //   137: istore 5
    //   139: aload_3
    //   140: getfield 102	dt:ab	Le;
    //   143: astore 6
    //   145: aload_3
    //   146: getfield 112	dt:cs	Ldt;
    //   149: astore 7
    //   151: getstatic 90	dn:am	Z
    //   154: invokestatic 328	r:i	(I)Z
    //   157: ifeq +72 -> 229
    //   160: aload 7
    //   162: invokestatic 300	r:a	(Ljava/lang/Object;)Z
    //   165: ifeq +43 -> 208
    //   168: aload 7
    //   170: getfield 111	dt:ci	Ljava/lang/String;
    //   173: invokestatic 248	dn:f	(Ljava/lang/String;)Z
    //   176: invokestatic 319	r:f	(I)Z
    //   179: ifeq +29 -> 208
    //   182: aload 7
    //   184: getfield 111	dt:ci	Ljava/lang/String;
    //   187: invokestatic 261	dv:a	(Ljava/lang/String;)Z
    //   190: invokestatic 319	r:f	(I)Z
    //   193: ifeq +36 -> 229
    //   196: aload_3
    //   197: aload 7
    //   199: invokestatic 298	r:a	(Ldt;Ldt;)Z
    //   202: invokestatic 319	r:f	(I)Z
    //   205: ifeq +24 -> 229
    //   208: aload_0
    //   209: aload_3
    //   210: iload_2
    //   211: invokevirtual 296	r:a	(Ldt;I)Ldt;
    //   214: dup
    //   215: astore 7
    //   217: invokestatic 306	r:b	(Ljava/lang/Object;)Z
    //   220: ifeq +9 -> 229
    //   223: aload_3
    //   224: invokestatic 305	r:b	(Ldt;)Ldt;
    //   227: astore 7
    //   229: aload 7
    //   231: invokestatic 300	r:a	(Ljava/lang/Object;)Z
    //   234: ifeq +44 -> 278
    //   237: aload 7
    //   239: getfield 111	dt:ci	Ljava/lang/String;
    //   242: invokestatic 261	dv:a	(Ljava/lang/String;)Z
    //   245: invokestatic 328	r:i	(I)Z
    //   248: ifeq +30 -> 278
    //   251: getstatic 190	r:ab	[I
    //   254: iconst_3
    //   255: iaload
    //   256: ldc 1
    //   258: invokevirtual 280	java/lang/String:length	()I
    //   261: pop
    //   262: iconst_2
    //   263: bipush 9
    //   265: ixor
    //   266: sipush 187
    //   269: sipush 180
    //   272: ixor
    //   273: ixor
    //   274: ifne +9 -> 283
    //   277: return
    //   278: getstatic 190	r:ab	[I
    //   281: iconst_0
    //   282: iaload
    //   283: istore 8
    //   285: aload 7
    //   287: invokestatic 306	r:b	(Ljava/lang/Object;)Z
    //   290: ifeq +33 -> 323
    //   293: aload_0
    //   294: getfield 204	r:n	Z
    //   297: invokestatic 328	r:i	(I)Z
    //   300: ifeq +23 -> 323
    //   303: invokestatic 237	dl:ae	()Ldl;
    //   306: getstatic 190	r:ab	[I
    //   309: iconst_0
    //   310: iaload
    //   311: invokevirtual 246	dl:x	(I)V
    //   314: aload_0
    //   315: getstatic 190	r:ab	[I
    //   318: iconst_0
    //   319: iaload
    //   320: putfield 204	r:n	Z
    //   323: getstatic 90	dn:am	Z
    //   326: invokestatic 328	r:i	(I)Z
    //   329: ifeq +95 -> 424
    //   332: aload_3
    //   333: getfield 132	dt:g	B
    //   336: getstatic 190	r:ab	[I
    //   339: bipush 11
    //   341: iaload
    //   342: invokestatic 320	r:f	(II)Z
    //   345: ifeq +79 -> 424
    //   348: invokestatic 284	java/lang/System:currentTimeMillis	()J
    //   351: aload_0
    //   352: getfield 197	r:g	J
    //   355: lsub
    //   356: ldc2_w 68
    //   359: invokestatic 309	r:c	(JJ)I
    //   362: invokestatic 323	r:g	(I)Z
    //   365: ifeq +59 -> 424
    //   368: getstatic 190	r:ab	[I
    //   371: bipush 61
    //   373: iaload
    //   374: invokestatic 257	dt:g	(I)Lao;
    //   377: dup
    //   378: astore 9
    //   380: invokestatic 300	r:a	(Ljava/lang/Object;)Z
    //   383: ifeq +34 -> 417
    //   386: aload 9
    //   388: getfield 71	ao:j	Lat;
    //   391: getfield 76	at:f	S
    //   394: getstatic 190	r:ab	[I
    //   397: bipush 61
    //   399: iaload
    //   400: invokestatic 326	r:h	(II)Z
    //   403: ifeq +14 -> 417
    //   406: invokestatic 237	dl:ae	()Ldl;
    //   409: aload 9
    //   411: getfield 72	ao:n	I
    //   414: invokevirtual 236	dl:ad	(I)V
    //   417: aload_0
    //   418: invokestatic 284	java/lang/System:currentTimeMillis	()J
    //   421: putfield 197	r:g	J
    //   424: getstatic 96	dn:l	Z
    //   427: invokestatic 328	r:i	(I)Z
    //   430: ifeq +32 -> 462
    //   433: getstatic 88	dn:aj	Lci;
    //   436: invokevirtual 288	java/util/Vector:size	()I
    //   439: invokestatic 323	r:g	(I)Z
    //   442: ifeq +20 -> 462
    //   445: getstatic 97	dn:m	I
    //   448: invokestatic 325	r:h	(I)Z
    //   451: ifeq +11 -> 462
    //   454: aload_0
    //   455: iload_2
    //   456: iload 5
    //   458: invokevirtual 293	r:a	(IZ)V
    //   461: return
    //   462: getstatic 190	r:ab	[I
    //   465: iconst_0
    //   466: iaload
    //   467: istore 9
    //   469: aload_0
    //   470: iload_2
    //   471: aload_3
    //   472: getfield 122	dt:eg	I
    //   475: aload_3
    //   476: getfield 126	dt:ey	I
    //   479: invokespecial 291	r:a	(III)Z
    //   482: invokestatic 319	r:f	(I)Z
    //   485: ifeq +50 -> 535
    //   488: aload_0
    //   489: aload_3
    //   490: getfield 122	dt:eg	I
    //   493: aload_3
    //   494: getfield 126	dt:ey	I
    //   497: invokespecial 317	r:e	(II)Z
    //   500: invokestatic 319	r:f	(I)Z
    //   503: ifeq +32 -> 535
    //   506: aload 6
    //   508: invokestatic 300	r:a	(Ljava/lang/Object;)Z
    //   511: ifeq +151 -> 662
    //   514: aload_0
    //   515: iload_2
    //   516: aload 6
    //   518: getfield 147	e:u	I
    //   521: aload 6
    //   523: getfield 141	e:l	I
    //   526: invokespecial 291	r:a	(III)Z
    //   529: invokestatic 328	r:i	(I)Z
    //   532: ifeq +130 -> 662
    //   535: ldc2_w 62
    //   538: invokestatic 285	java/lang/Thread:sleep	(J)V
    //   541: ldc 1
    //   543: invokevirtual 280	java/lang/String:length	()I
    //   546: pop
    //   547: bipush 15
    //   549: bipush 11
    //   551: ixor
    //   552: ldc 2
    //   554: invokevirtual 280	java/lang/String:length	()I
    //   557: if_icmpgt +10 -> 567
    //   560: return
    //   561: ldc 1
    //   563: invokevirtual 280	java/lang/String:length	()I
    //   566: pop2
    //   567: ldc 6
    //   569: invokestatic 270	fn:a	(Ljava/lang/String;)V
    //   572: getstatic 104	dt:ax	Z
    //   575: invokestatic 328	r:i	(I)Z
    //   578: ifeq +58 -> 636
    //   581: iload 5
    //   583: invokestatic 328	r:i	(I)Z
    //   586: ifeq +50 -> 636
    //   589: aload_0
    //   590: invokespecial 312	r:d	()V
    //   593: getstatic 190	r:ab	[I
    //   596: iconst_3
    //   597: iaload
    //   598: istore 9
    //   600: ldc 1
    //   602: invokevirtual 280	java/lang/String:length	()I
    //   605: pop
    //   606: bipush 97
    //   608: bipush 66
    //   610: ixor
    //   611: bipush 72
    //   613: bipush 107
    //   615: ixor
    //   616: iconst_m1
    //   617: ixor
    //   618: iand
    //   619: bipush 49
    //   621: bipush 33
    //   623: ixor
    //   624: bipush 44
    //   626: bipush 60
    //   628: ixor
    //   629: iconst_m1
    //   630: ixor
    //   631: iand
    //   632: if_icmple +11 -> 643
    //   635: return
    //   636: getstatic 190	r:ab	[I
    //   639: iconst_0
    //   640: iaload
    //   641: istore 9
    //   643: iload 9
    //   645: invokestatic 328	r:i	(I)Z
    //   648: ifeq +4 -> 652
    //   651: return
    //   652: getstatic 190	r:ab	[I
    //   655: iconst_3
    //   656: iaload
    //   657: istore 9
    //   659: aconst_null
    //   660: astore 6
    //   662: aload 6
    //   664: invokestatic 300	r:a	(Ljava/lang/Object;)Z
    //   667: ifeq +61 -> 728
    //   670: aload 6
    //   672: getfield 140	e:j	I
    //   675: invokestatic 328	r:i	(I)Z
    //   678: ifeq +50 -> 728
    //   681: aload 6
    //   683: iload_1
    //   684: invokestatic 299	r:a	(Le;I)Z
    //   687: invokestatic 328	r:i	(I)Z
    //   690: ifeq +38 -> 728
    //   693: aload 6
    //   695: getfield 146	e:t	S
    //   698: iload_2
    //   699: invokestatic 308	r:c	(II)Z
    //   702: invokestatic 328	r:i	(I)Z
    //   705: ifeq +23 -> 728
    //   708: invokestatic 284	java/lang/System:currentTimeMillis	()J
    //   711: aload_0
    //   712: getfield 210	r:u	J
    //   715: lsub
    //   716: ldc2_w 68
    //   719: invokestatic 309	r:c	(JJ)I
    //   722: invokestatic 323	r:g	(I)Z
    //   725: ifeq +16 -> 741
    //   728: aload_0
    //   729: aload_3
    //   730: iload_1
    //   731: iload_2
    //   732: aload 4
    //   734: iload 5
    //   736: invokevirtual 297	r:a	(Ldt;IILdt;Z)Le;
    //   739: astore 6
    //   741: aload 6
    //   743: invokestatic 306	r:b	(Ljava/lang/Object;)Z
    //   746: ifeq +48 -> 794
    //   749: iload 9
    //   751: invokestatic 328	r:i	(I)Z
    //   754: ifeq +40 -> 794
    //   757: aload_0
    //   758: getfield 212	r:w	I
    //   761: invokestatic 323	r:g	(I)Z
    //   764: ifeq +30 -> 794
    //   767: aload_0
    //   768: getfield 215	r:z	I
    //   771: invokestatic 323	r:g	(I)Z
    //   774: ifeq +20 -> 794
    //   777: aload_0
    //   778: getfield 212	r:w	I
    //   781: aload_0
    //   782: getfield 215	r:z	I
    //   785: invokestatic 252	dt:b	(II)Z
    //   788: ldc 1
    //   790: invokevirtual 280	java/lang/String:length	()I
    //   793: pop2
    //   794: getstatic 134	dt:gj	Z
    //   797: invokestatic 328	r:i	(I)Z
    //   800: ifeq +473 -> 1273
    //   803: getstatic 171	fn:ax	Lci;
    //   806: invokevirtual 288	java/util/Vector:size	()I
    //   809: invokestatic 323	r:g	(I)Z
    //   812: ifeq +461 -> 1273
    //   815: aload_3
    //   816: getfield 109	dt:bs	Lfl;
    //   819: getfield 170	fl:b	I
    //   822: getstatic 190	r:ab	[I
    //   825: bipush 18
    //   827: iaload
    //   828: invokestatic 326	r:h	(II)Z
    //   831: ifeq +442 -> 1273
    //   834: aload_3
    //   835: getfield 121	dt:ef	I
    //   838: invokestatic 323	r:g	(I)Z
    //   841: ifeq +432 -> 1273
    //   844: getstatic 190	r:ab	[I
    //   847: iconst_0
    //   848: iaload
    //   849: istore 10
    //   851: iload 10
    //   853: aload_3
    //   854: getfield 105	dt:az	Lci;
    //   857: invokevirtual 288	java/util/Vector:size	()I
    //   860: invokestatic 324	r:g	(II)Z
    //   863: ifeq +410 -> 1273
    //   866: aload_3
    //   867: getfield 105	dt:az	Lci;
    //   870: iload 10
    //   872: invokevirtual 221	ci:elementAt	(I)Ljava/lang/Object;
    //   875: checkcast 36	fy
    //   878: dup
    //   879: astore 9
    //   881: invokestatic 300	r:a	(Ljava/lang/Object;)Z
    //   884: ifeq +356 -> 1240
    //   887: aload 9
    //   889: getfield 181	fy:a	Lev;
    //   892: getfield 164	ev:b	I
    //   895: getstatic 190	r:ab	[I
    //   898: bipush 9
    //   900: iaload
    //   901: invokestatic 326	r:h	(II)Z
    //   904: ifeq +336 -> 1240
    //   907: aload 9
    //   909: invokevirtual 274	fy:c	()Z
    //   912: invokestatic 319	r:f	(I)Z
    //   915: ifeq +358 -> 1273
    //   918: getstatic 190	r:ab	[I
    //   921: iconst_0
    //   922: iaload
    //   923: istore 4
    //   925: iload 4
    //   927: getstatic 171	fn:ax	Lci;
    //   930: invokevirtual 288	java/util/Vector:size	()I
    //   933: invokestatic 324	r:g	(II)Z
    //   936: ifeq +337 -> 1273
    //   939: getstatic 171	fn:ax	Lci;
    //   942: iload 4
    //   944: invokevirtual 221	ci:elementAt	(I)Ljava/lang/Object;
    //   947: checkcast 14	bk
    //   950: dup
    //   951: astore 11
    //   953: getfield 78	bk:g	I
    //   956: aload_3
    //   957: getfield 131	dt:fy	I
    //   960: invokestatic 314	r:d	(II)Z
    //   963: ifeq +208 -> 1171
    //   966: aload 11
    //   968: getfield 77	bk:f	Ldt;
    //   971: invokestatic 300	r:a	(Ljava/lang/Object;)Z
    //   974: ifeq +197 -> 1171
    //   977: aload 11
    //   979: getfield 77	bk:f	Ldt;
    //   982: getfield 121	dt:ef	I
    //   985: invokestatic 316	r:e	(I)Z
    //   988: ifeq +183 -> 1171
    //   991: aload 11
    //   993: getfield 77	bk:f	Ldt;
    //   996: astore 5
    //   998: aload_3
    //   999: getfield 122	dt:eg	I
    //   1002: aload 5
    //   1004: getfield 122	dt:eg	I
    //   1007: isub
    //   1008: invokestatic 276	java/lang/Math:abs	(I)I
    //   1011: getstatic 190	r:ab	[I
    //   1014: bipush 60
    //   1016: iaload
    //   1017: invokestatic 330	r:j	(II)Z
    //   1020: ifeq +28 -> 1048
    //   1023: aload_3
    //   1024: getfield 126	dt:ey	I
    //   1027: aload 5
    //   1029: getfield 126	dt:ey	I
    //   1032: isub
    //   1033: invokestatic 276	java/lang/Math:abs	(I)I
    //   1036: getstatic 190	r:ab	[I
    //   1039: bipush 60
    //   1041: iaload
    //   1042: invokestatic 329	r:i	(II)Z
    //   1045: ifeq +22 -> 1067
    //   1048: aload 5
    //   1050: getfield 122	dt:eg	I
    //   1053: aload 5
    //   1055: getfield 126	dt:ey	I
    //   1058: invokestatic 252	dt:b	(II)Z
    //   1061: ldc 1
    //   1063: invokevirtual 280	java/lang/String:length	()I
    //   1066: pop2
    //   1067: ldc2_w 62
    //   1070: invokestatic 285	java/lang/Thread:sleep	(J)V
    //   1073: ldc 1
    //   1075: invokevirtual 280	java/lang/String:length	()I
    //   1078: pop
    //   1079: bipush 40
    //   1081: iconst_0
    //   1082: ixor
    //   1083: bipush 66
    //   1085: bipush 106
    //   1087: ixor
    //   1088: iconst_m1
    //   1089: ixor
    //   1090: iand
    //   1091: ldc 2
    //   1093: invokevirtual 280	java/lang/String:length	()I
    //   1096: ineg
    //   1097: if_icmpge +10 -> 1107
    //   1100: return
    //   1101: ldc 1
    //   1103: invokevirtual 280	java/lang/String:length	()I
    //   1106: pop2
    //   1107: invokestatic 237	dl:ae	()Ldl;
    //   1110: aload 11
    //   1112: getfield 78	bk:g	I
    //   1115: invokevirtual 238	dl:ao	(I)V
    //   1118: aload 9
    //   1120: invokestatic 284	java/lang/System:currentTimeMillis	()J
    //   1123: putfield 183	fy:e	J
    //   1126: aload 9
    //   1128: getstatic 190	r:ab	[I
    //   1131: iconst_3
    //   1132: iaload
    //   1133: putfield 186	fy:k	Z
    //   1136: aload_3
    //   1137: getstatic 174	fn:dc	[Lad;
    //   1140: aload 9
    //   1142: getfield 181	fy:a	Lev;
    //   1145: getfield 165	ev:e	B
    //   1148: aaload
    //   1149: getstatic 190	r:ab	[I
    //   1152: iconst_0
    //   1153: iaload
    //   1154: invokevirtual 250	dt:a	(Lad;I)V
    //   1157: ldc2_w 56
    //   1160: invokestatic 285	java/lang/Thread:sleep	(J)V
    //   1163: return
    //   1164: ldc 1
    //   1166: invokevirtual 280	java/lang/String:length	()I
    //   1169: pop2
    //   1170: return
    //   1171: iinc 4 1
    //   1174: ldc 1
    //   1176: invokevirtual 280	java/lang/String:length	()I
    //   1179: pop
    //   1180: ldc 3
    //   1182: invokevirtual 280	java/lang/String:length	()I
    //   1185: sipush 170
    //   1188: sipush 174
    //   1191: ixor
    //   1192: sipush 130
    //   1195: sipush 197
    //   1198: ixor
    //   1199: ixor
    //   1200: sipush 130
    //   1203: bipush 37
    //   1205: iadd
    //   1206: sipush 128
    //   1209: isub
    //   1210: sipush 164
    //   1213: iadd
    //   1214: bipush 122
    //   1216: bipush 73
    //   1218: iadd
    //   1219: sipush 191
    //   1222: isub
    //   1223: sipush 132
    //   1226: iadd
    //   1227: ixor
    //   1228: ldc 2
    //   1230: invokevirtual 280	java/lang/String:length	()I
    //   1233: ineg
    //   1234: ixor
    //   1235: iand
    //   1236: if_icmpgt -311 -> 925
    //   1239: return
    //   1240: iinc 10 1
    //   1243: ldc 1
    //   1245: invokevirtual 280	java/lang/String:length	()I
    //   1248: pop
    //   1249: sipush 132
    //   1252: sipush 193
    //   1255: ixor
    //   1256: bipush 35
    //   1258: bipush 102
    //   1260: ixor
    //   1261: iconst_m1
    //   1262: ixor
    //   1263: iand
    //   1264: ldc 4
    //   1266: invokevirtual 280	java/lang/String:length	()I
    //   1269: if_icmple -418 -> 851
    //   1272: return
    //   1273: getstatic 129	dt:fl	Z
    //   1276: invokestatic 328	r:i	(I)Z
    //   1279: ifeq +359 -> 1638
    //   1282: aload_0
    //   1283: getfield 198	r:h	Z
    //   1286: invokestatic 319	r:f	(I)Z
    //   1289: ifeq +349 -> 1638
    //   1292: aload 6
    //   1294: invokestatic 300	r:a	(Ljava/lang/Object;)Z
    //   1297: ifeq +28 -> 1325
    //   1300: aload 6
    //   1302: getfield 146	e:t	S
    //   1305: invokestatic 319	r:f	(I)Z
    //   1308: ifeq +330 -> 1638
    //   1311: iload_2
    //   1312: getstatic 190	r:ab	[I
    //   1315: bipush 18
    //   1317: iaload
    //   1318: iand
    //   1319: invokestatic 328	r:i	(I)Z
    //   1322: ifeq +316 -> 1638
    //   1325: iload_2
    //   1326: getstatic 190	r:ab	[I
    //   1329: bipush 6
    //   1331: iaload
    //   1332: iand
    //   1333: invokestatic 328	r:i	(I)Z
    //   1336: ifeq +30 -> 1366
    //   1339: getstatic 190	r:ab	[I
    //   1342: iconst_3
    //   1343: iaload
    //   1344: ldc 1
    //   1346: invokevirtual 280	java/lang/String:length	()I
    //   1349: pop
    //   1350: ldc 2
    //   1352: invokevirtual 280	java/lang/String:length	()I
    //   1355: ineg
    //   1356: ldc 2
    //   1358: invokevirtual 280	java/lang/String:length	()I
    //   1361: ineg
    //   1362: if_icmpeq +9 -> 1371
    //   1365: return
    //   1366: getstatic 190	r:ab	[I
    //   1369: iconst_0
    //   1370: iaload
    //   1371: istore 9
    //   1373: iload_2
    //   1374: getstatic 190	r:ab	[I
    //   1377: bipush 9
    //   1379: iaload
    //   1380: iand
    //   1381: invokestatic 328	r:i	(I)Z
    //   1384: ifeq +35 -> 1419
    //   1387: getstatic 190	r:ab	[I
    //   1390: iconst_3
    //   1391: iaload
    //   1392: ldc 1
    //   1394: invokevirtual 280	java/lang/String:length	()I
    //   1397: pop
    //   1398: bipush 124
    //   1400: bipush 51
    //   1402: ixor
    //   1403: bipush 123
    //   1405: bipush 48
    //   1407: ixor
    //   1408: ixor
    //   1409: ldc 2
    //   1411: invokevirtual 280	java/lang/String:length	()I
    //   1414: ineg
    //   1415: if_icmpgt +9 -> 1424
    //   1418: return
    //   1419: getstatic 190	r:ab	[I
    //   1422: iconst_0
    //   1423: iaload
    //   1424: istore 5
    //   1426: getstatic 190	r:ab	[I
    //   1429: iconst_0
    //   1430: iaload
    //   1431: istore 4
    //   1433: iload 4
    //   1435: getstatic 208	r:r	Lci;
    //   1438: invokevirtual 288	java/util/Vector:size	()I
    //   1441: invokestatic 324	r:g	(II)Z
    //   1444: ifeq +194 -> 1638
    //   1447: getstatic 208	r:r	Lci;
    //   1450: iload 4
    //   1452: invokevirtual 221	ci:elementAt	(I)Ljava/lang/Object;
    //   1455: checkcast 27	e
    //   1458: dup
    //   1459: astore 10
    //   1461: getfield 149	e:x	I
    //   1464: invokestatic 323	r:g	(I)Z
    //   1467: ifeq +157 -> 1624
    //   1470: aload 10
    //   1472: getfield 140	e:j	I
    //   1475: invokestatic 328	r:i	(I)Z
    //   1478: ifeq +146 -> 1624
    //   1481: aload 10
    //   1483: getfield 140	e:j	I
    //   1486: getstatic 190	r:ab	[I
    //   1489: iconst_3
    //   1490: iaload
    //   1491: invokestatic 314	r:d	(II)Z
    //   1494: ifeq +130 -> 1624
    //   1497: aload_0
    //   1498: iload_2
    //   1499: aload 10
    //   1501: getfield 147	e:u	I
    //   1504: aload 10
    //   1506: getfield 141	e:l	I
    //   1509: invokespecial 291	r:a	(III)Z
    //   1512: invokestatic 319	r:f	(I)Z
    //   1515: ifeq +109 -> 1624
    //   1518: aload_0
    //   1519: aload 10
    //   1521: getfield 147	e:u	I
    //   1524: aload 10
    //   1526: getfield 141	e:l	I
    //   1529: invokespecial 317	r:e	(II)Z
    //   1532: invokestatic 319	r:f	(I)Z
    //   1535: ifeq +89 -> 1624
    //   1538: aload 10
    //   1540: iload_1
    //   1541: invokestatic 299	r:a	(Le;I)Z
    //   1544: invokestatic 328	r:i	(I)Z
    //   1547: ifeq +77 -> 1624
    //   1550: iload 9
    //   1552: invokestatic 328	r:i	(I)Z
    //   1555: ifeq +19 -> 1574
    //   1558: aload 10
    //   1560: getfield 146	e:t	S
    //   1563: getstatic 190	r:ab	[I
    //   1566: iconst_3
    //   1567: iaload
    //   1568: invokestatic 314	r:d	(II)Z
    //   1571: ifeq +28 -> 1599
    //   1574: iload 5
    //   1576: invokestatic 328	r:i	(I)Z
    //   1579: ifeq +45 -> 1624
    //   1582: aload 10
    //   1584: getfield 146	e:t	S
    //   1587: getstatic 190	r:ab	[I
    //   1590: bipush 6
    //   1592: iaload
    //   1593: invokestatic 326	r:h	(II)Z
    //   1596: ifeq +28 -> 1624
    //   1599: aload 10
    //   1601: astore 6
    //   1603: aload_0
    //   1604: aload 10
    //   1606: invokevirtual 311	r:c	(Le;)V
    //   1609: ldc 1
    //   1611: invokevirtual 280	java/lang/String:length	()I
    //   1614: pop
    //   1615: bipush 33
    //   1617: bipush 37
    //   1619: ixor
    //   1620: ifgt +18 -> 1638
    //   1623: return
    //   1624: iinc 4 1
    //   1627: ldc 1
    //   1629: invokevirtual 280	java/lang/String:length	()I
    //   1632: pop
    //   1633: aconst_null
    //   1634: ifnull -201 -> 1433
    //   1637: return
    //   1638: getstatic 203	r:m	Lfy;
    //   1641: invokestatic 300	r:a	(Ljava/lang/Object;)Z
    //   1644: ifeq +3137 -> 4781
    //   1647: getstatic 203	r:m	Lfy;
    //   1650: dup
    //   1651: astore 10
    //   1653: invokevirtual 274	fy:c	()Z
    //   1656: invokestatic 328	r:i	(I)Z
    //   1659: ifeq +991 -> 2650
    //   1662: getstatic 119	dt:ec	Z
    //   1665: invokestatic 319	r:f	(I)Z
    //   1668: ifeq +13 -> 1681
    //   1671: aload_0
    //   1672: instanceof 19
    //   1675: invokestatic 328	r:i	(I)Z
    //   1678: ifeq +972 -> 2650
    //   1681: getstatic 190	r:ab	[I
    //   1684: iconst_0
    //   1685: iaload
    //   1686: istore 11
    //   1688: iload 11
    //   1690: aload_3
    //   1691: getfield 105	dt:az	Lci;
    //   1694: invokevirtual 288	java/util/Vector:size	()I
    //   1697: invokestatic 324	r:g	(II)Z
    //   1700: ifeq +950 -> 2650
    //   1703: aload_3
    //   1704: getfield 105	dt:az	Lci;
    //   1707: iload 11
    //   1709: invokevirtual 221	ci:elementAt	(I)Ljava/lang/Object;
    //   1712: checkcast 36	fy
    //   1715: dup
    //   1716: astore 5
    //   1718: invokestatic 300	r:a	(Ljava/lang/Object;)Z
    //   1721: ifeq +805 -> 2526
    //   1724: invokestatic 284	java/lang/System:currentTimeMillis	()J
    //   1727: aload 5
    //   1729: getfield 183	fy:e	J
    //   1732: lsub
    //   1733: aload 5
    //   1735: getfield 187	fy:l	I
    //   1738: i2l
    //   1739: ldc2_w 60
    //   1742: lsub
    //   1743: invokestatic 309	r:c	(JJ)I
    //   1746: invokestatic 313	r:d	(I)Z
    //   1749: ifeq +777 -> 2526
    //   1752: aload 5
    //   1754: getfield 181	fy:a	Lev;
    //   1757: getfield 164	ev:b	I
    //   1760: getstatic 190	r:ab	[I
    //   1763: bipush 6
    //   1765: iaload
    //   1766: invokestatic 326	r:h	(II)Z
    //   1769: ifeq +353 -> 2122
    //   1772: aload_3
    //   1773: getfield 136	dt:m	Ldt;
    //   1776: invokestatic 306	r:b	(Ljava/lang/Object;)Z
    //   1779: ifeq +12 -> 1791
    //   1782: getstatic 118	dt:eb	Z
    //   1785: invokestatic 319	r:f	(I)Z
    //   1788: ifeq +43 -> 1831
    //   1791: aload 5
    //   1793: getfield 181	fy:a	Lev;
    //   1796: getfield 165	ev:e	B
    //   1799: getstatic 190	r:ab	[I
    //   1802: bipush 62
    //   1804: iaload
    //   1805: invokestatic 320	r:f	(II)Z
    //   1808: ifeq +23 -> 1831
    //   1811: aload 5
    //   1813: getfield 181	fy:a	Lev;
    //   1816: getfield 165	ev:e	B
    //   1819: getstatic 190	r:ab	[I
    //   1822: bipush 63
    //   1824: iaload
    //   1825: invokestatic 329	r:i	(II)Z
    //   1828: ifeq +698 -> 2526
    //   1831: getstatic 115	dt:df	Z
    //   1834: invokestatic 319	r:f	(I)Z
    //   1837: ifeq +23 -> 1860
    //   1840: aload 5
    //   1842: getfield 181	fy:a	Lev;
    //   1845: getfield 165	ev:e	B
    //   1848: getstatic 190	r:ab	[I
    //   1851: bipush 64
    //   1853: iaload
    //   1854: invokestatic 314	r:d	(II)Z
    //   1857: ifeq +669 -> 2526
    //   1860: aload 5
    //   1862: getfield 181	fy:a	Lev;
    //   1865: getfield 165	ev:e	B
    //   1868: getstatic 190	r:ab	[I
    //   1871: bipush 19
    //   1873: iaload
    //   1874: invokestatic 326	r:h	(II)Z
    //   1877: ifeq +46 -> 1923
    //   1880: getstatic 128	dt:ff	Z
    //   1883: invokestatic 328	r:i	(I)Z
    //   1886: ifeq +37 -> 1923
    //   1889: aload_3
    //   1890: getfield 121	dt:ef	I
    //   1893: aload_3
    //   1894: getfield 113	dt:cw	I
    //   1897: getstatic 114	dt:d	I
    //   1900: imul
    //   1901: getstatic 190	r:ab	[I
    //   1904: iconst_4
    //   1905: iaload
    //   1906: idiv
    //   1907: invokestatic 324	r:g	(II)Z
    //   1910: ifeq +616 -> 2526
    //   1913: aload_3
    //   1914: getfield 101	dt:aa	Z
    //   1917: invokestatic 328	r:i	(I)Z
    //   1920: ifeq +606 -> 2526
    //   1923: aload 5
    //   1925: getfield 181	fy:a	Lev;
    //   1928: getfield 165	ev:e	B
    //   1931: getstatic 190	r:ab	[I
    //   1934: bipush 18
    //   1936: iaload
    //   1937: invokestatic 326	r:h	(II)Z
    //   1940: ifeq +13 -> 1953
    //   1943: aload_3
    //   1944: getfield 101	dt:aa	Z
    //   1947: invokestatic 328	r:i	(I)Z
    //   1950: ifeq +576 -> 2526
    //   1953: invokestatic 284	java/lang/System:currentTimeMillis	()J
    //   1956: ldc2_w 64
    //   1959: ldiv
    //   1960: l2i
    //   1961: istore 9
    //   1963: getstatic 190	r:ab	[I
    //   1966: iconst_0
    //   1967: iaload
    //   1968: istore 4
    //   1970: iload 4
    //   1972: aload_3
    //   1973: getfield 107	dt:be	Lci;
    //   1976: invokevirtual 288	java/util/Vector:size	()I
    //   1979: invokestatic 324	r:g	(II)Z
    //   1982: ifeq +632 -> 2614
    //   1985: aload_3
    //   1986: getfield 107	dt:be	Lci;
    //   1989: iload 4
    //   1991: invokevirtual 221	ci:elementAt	(I)Ljava/lang/Object;
    //   1994: checkcast 16	bt
    //   1997: dup
    //   1998: astore 12
    //   2000: invokestatic 300	r:a	(Ljava/lang/Object;)Z
    //   2003: ifeq +91 -> 2094
    //   2006: aload 12
    //   2008: getfield 79	bt:a	Lfx;
    //   2011: getfield 180	fx:c	I
    //   2014: aload 5
    //   2016: getfield 181	fy:a	Lev;
    //   2019: getfield 166	ev:g	I
    //   2022: invokestatic 314	r:d	(II)Z
    //   2025: ifeq +43 -> 2068
    //   2028: aload 5
    //   2030: getfield 181	fy:a	Lev;
    //   2033: getfield 165	ev:e	B
    //   2036: getstatic 190	r:ab	[I
    //   2039: bipush 65
    //   2041: iaload
    //   2042: invokestatic 326	r:h	(II)Z
    //   2045: ifeq +49 -> 2094
    //   2048: aload 12
    //   2050: getfield 79	bt:a	Lfx;
    //   2053: getfield 179	fx:a	B
    //   2056: getstatic 190	r:ab	[I
    //   2059: bipush 66
    //   2061: iaload
    //   2062: invokestatic 326	r:h	(II)Z
    //   2065: ifeq +29 -> 2094
    //   2068: aload 12
    //   2070: getfield 80	bt:b	I
    //   2073: iload 9
    //   2075: aload 12
    //   2077: getfield 81	bt:d	I
    //   2080: isub
    //   2081: isub
    //   2082: getstatic 190	r:ab	[I
    //   2085: bipush 6
    //   2087: iaload
    //   2088: invokestatic 324	r:g	(II)Z
    //   2091: ifeq +435 -> 2526
    //   2094: iinc 4 1
    //   2097: ldc 1
    //   2099: invokevirtual 280	java/lang/String:length	()I
    //   2102: pop
    //   2103: sipush 209
    //   2106: sipush 139
    //   2109: ixor
    //   2110: bipush 37
    //   2112: bipush 127
    //   2114: ixor
    //   2115: iconst_m1
    //   2116: ixor
    //   2117: iand
    //   2118: ifge -148 -> 1970
    //   2121: return
    //   2122: aload 5
    //   2124: getfield 181	fy:a	Lev;
    //   2127: getfield 164	ev:b	I
    //   2130: getstatic 190	r:ab	[I
    //   2133: iconst_1
    //   2134: iaload
    //   2135: invokestatic 326	r:h	(II)Z
    //   2138: ifeq +113 -> 2251
    //   2141: aload 6
    //   2143: invokestatic 300	r:a	(Ljava/lang/Object;)Z
    //   2146: ifeq +105 -> 2251
    //   2149: aload 6
    //   2151: getfield 146	e:t	S
    //   2154: invokestatic 319	r:f	(I)Z
    //   2157: ifeq +94 -> 2251
    //   2160: aload 6
    //   2162: getfield 149	e:x	I
    //   2165: aload 6
    //   2167: getfield 139	e:h	I
    //   2170: getstatic 190	r:ab	[I
    //   2173: bipush 6
    //   2175: iaload
    //   2176: idiv
    //   2177: invokestatic 329	r:i	(II)Z
    //   2180: ifeq +71 -> 2251
    //   2183: aload 5
    //   2185: getfield 181	fy:a	Lev;
    //   2188: getfield 165	ev:e	B
    //   2191: getstatic 190	r:ab	[I
    //   2194: bipush 9
    //   2196: iaload
    //   2197: invokestatic 326	r:h	(II)Z
    //   2200: ifeq +414 -> 2614
    //   2203: getstatic 128	dt:ff	Z
    //   2206: invokestatic 328	r:i	(I)Z
    //   2209: ifeq +317 -> 2526
    //   2212: aload_3
    //   2213: getfield 121	dt:ef	I
    //   2216: aload_3
    //   2217: getfield 113	dt:cw	I
    //   2220: getstatic 114	dt:d	I
    //   2223: imul
    //   2224: getstatic 190	r:ab	[I
    //   2227: iconst_4
    //   2228: iaload
    //   2229: idiv
    //   2230: invokestatic 324	r:g	(II)Z
    //   2233: ifeq +293 -> 2526
    //   2236: ldc 1
    //   2238: invokevirtual 280	java/lang/String:length	()I
    //   2241: pop
    //   2242: ldc 2
    //   2244: invokevirtual 280	java/lang/String:length	()I
    //   2247: ifge +367 -> 2614
    //   2250: return
    //   2251: aload 5
    //   2253: getfield 181	fy:a	Lev;
    //   2256: getfield 165	ev:e	B
    //   2259: getstatic 190	r:ab	[I
    //   2262: bipush 66
    //   2264: iaload
    //   2265: invokestatic 314	r:d	(II)Z
    //   2268: ifeq +83 -> 2351
    //   2271: aload 5
    //   2273: getfield 181	fy:a	Lev;
    //   2276: getfield 165	ev:e	B
    //   2279: getstatic 190	r:ab	[I
    //   2282: bipush 67
    //   2284: iaload
    //   2285: invokestatic 314	r:d	(II)Z
    //   2288: ifeq +63 -> 2351
    //   2291: aload 5
    //   2293: getfield 181	fy:a	Lev;
    //   2296: getfield 165	ev:e	B
    //   2299: getstatic 190	r:ab	[I
    //   2302: bipush 68
    //   2304: iaload
    //   2305: invokestatic 314	r:d	(II)Z
    //   2308: ifeq +43 -> 2351
    //   2311: aload 5
    //   2313: getfield 181	fy:a	Lev;
    //   2316: getfield 165	ev:e	B
    //   2319: getstatic 190	r:ab	[I
    //   2322: bipush 69
    //   2324: iaload
    //   2325: invokestatic 314	r:d	(II)Z
    //   2328: ifeq +23 -> 2351
    //   2331: aload 5
    //   2333: getfield 181	fy:a	Lev;
    //   2336: getfield 165	ev:e	B
    //   2339: getstatic 190	r:ab	[I
    //   2342: bipush 70
    //   2344: iaload
    //   2345: invokestatic 326	r:h	(II)Z
    //   2348: ifeq +178 -> 2526
    //   2351: aload 6
    //   2353: invokestatic 300	r:a	(Ljava/lang/Object;)Z
    //   2356: ifeq +170 -> 2526
    //   2359: aload 6
    //   2361: getfield 146	e:t	S
    //   2364: invokestatic 319	r:f	(I)Z
    //   2367: ifeq +26 -> 2393
    //   2370: aload 6
    //   2372: getfield 149	e:x	I
    //   2375: aload 6
    //   2377: getfield 139	e:h	I
    //   2380: getstatic 190	r:ab	[I
    //   2383: bipush 6
    //   2385: iaload
    //   2386: idiv
    //   2387: invokestatic 320	r:f	(II)Z
    //   2390: ifeq +136 -> 2526
    //   2393: aload 5
    //   2395: getfield 181	fy:a	Lev;
    //   2398: getfield 165	ev:e	B
    //   2401: getstatic 190	r:ab	[I
    //   2404: bipush 66
    //   2406: iaload
    //   2407: invokestatic 314	r:d	(II)Z
    //   2410: ifeq +23 -> 2433
    //   2413: aload 5
    //   2415: getfield 181	fy:a	Lev;
    //   2418: getfield 165	ev:e	B
    //   2421: getstatic 190	r:ab	[I
    //   2424: bipush 67
    //   2426: iaload
    //   2427: invokestatic 326	r:h	(II)Z
    //   2430: ifeq +14 -> 2444
    //   2433: aload 6
    //   2435: getfield 142	e:m	Z
    //   2438: invokestatic 319	r:f	(I)Z
    //   2441: ifeq +85 -> 2526
    //   2444: aload 5
    //   2446: getfield 181	fy:a	Lev;
    //   2449: getfield 165	ev:e	B
    //   2452: getstatic 190	r:ab	[I
    //   2455: bipush 68
    //   2457: iaload
    //   2458: invokestatic 314	r:d	(II)Z
    //   2461: ifeq +23 -> 2484
    //   2464: aload 5
    //   2466: getfield 181	fy:a	Lev;
    //   2469: getfield 165	ev:e	B
    //   2472: getstatic 190	r:ab	[I
    //   2475: bipush 69
    //   2477: iaload
    //   2478: invokestatic 326	r:h	(II)Z
    //   2481: ifeq +14 -> 2495
    //   2484: aload 6
    //   2486: getfield 144	e:q	Z
    //   2489: invokestatic 328	r:i	(I)Z
    //   2492: ifeq +34 -> 2526
    //   2495: aload 5
    //   2497: getfield 181	fy:a	Lev;
    //   2500: getfield 165	ev:e	B
    //   2503: getstatic 190	r:ab	[I
    //   2506: bipush 70
    //   2508: iaload
    //   2509: invokestatic 326	r:h	(II)Z
    //   2512: ifeq +102 -> 2614
    //   2515: aload 6
    //   2517: getfield 138	e:g	Z
    //   2520: invokestatic 319	r:f	(I)Z
    //   2523: ifeq +91 -> 2614
    //   2526: iinc 11 1
    //   2529: ldc 1
    //   2531: invokevirtual 280	java/lang/String:length	()I
    //   2534: pop
    //   2535: bipush 42
    //   2537: bipush 16
    //   2539: iadd
    //   2540: bipush -4
    //   2542: isub
    //   2543: bipush 116
    //   2545: iadd
    //   2546: bipush 105
    //   2548: bipush 38
    //   2550: iadd
    //   2551: bipush 101
    //   2553: isub
    //   2554: bipush 125
    //   2556: iadd
    //   2557: ixor
    //   2558: bipush 118
    //   2560: bipush 22
    //   2562: ixor
    //   2563: sipush 202
    //   2566: sipush 191
    //   2569: ixor
    //   2570: ixor
    //   2571: ldc 2
    //   2573: invokevirtual 280	java/lang/String:length	()I
    //   2576: ineg
    //   2577: ixor
    //   2578: iand
    //   2579: sipush 137
    //   2582: sipush 177
    //   2585: ixor
    //   2586: bipush 113
    //   2588: iconst_3
    //   2589: ixor
    //   2590: ixor
    //   2591: bipush 18
    //   2593: bipush 10
    //   2595: ixor
    //   2596: bipush 15
    //   2598: bipush 93
    //   2600: ixor
    //   2601: ixor
    //   2602: ldc 2
    //   2604: invokevirtual 280	java/lang/String:length	()I
    //   2607: ineg
    //   2608: ixor
    //   2609: iand
    //   2610: if_icmpeq -922 -> 1688
    //   2613: return
    //   2614: aload 5
    //   2616: astore 10
    //   2618: ldc2_w 56
    //   2621: invokestatic 285	java/lang/Thread:sleep	(J)V
    //   2624: ldc 1
    //   2626: invokevirtual 280	java/lang/String:length	()I
    //   2629: pop
    //   2630: bipush 55
    //   2632: bipush 51
    //   2634: ixor
    //   2635: ldc 3
    //   2637: invokevirtual 280	java/lang/String:length	()I
    //   2640: if_icmpgt +10 -> 2650
    //   2643: return
    //   2644: ldc 1
    //   2646: invokevirtual 280	java/lang/String:length	()I
    //   2649: pop2
    //   2650: aload 10
    //   2652: getfield 181	fy:a	Lev;
    //   2655: getfield 164	ev:b	I
    //   2658: getstatic 190	r:ab	[I
    //   2661: bipush 6
    //   2663: iaload
    //   2664: invokestatic 326	r:h	(II)Z
    //   2667: ifeq +138 -> 2805
    //   2670: invokestatic 284	java/lang/System:currentTimeMillis	()J
    //   2673: aload 10
    //   2675: getfield 183	fy:e	J
    //   2678: lsub
    //   2679: aload 10
    //   2681: getfield 187	fy:l	I
    //   2684: i2l
    //   2685: invokestatic 309	r:c	(JJ)I
    //   2688: invokestatic 313	r:d	(I)Z
    //   2691: ifeq +81 -> 2772
    //   2694: aload 10
    //   2696: invokestatic 284	java/lang/System:currentTimeMillis	()J
    //   2699: putfield 183	fy:e	J
    //   2702: invokestatic 237	dl:ae	()Ldl;
    //   2705: aload 10
    //   2707: getfield 181	fy:a	Lev;
    //   2710: getfield 165	ev:e	B
    //   2713: invokevirtual 242	dl:l	(I)V
    //   2716: invokestatic 237	dl:ae	()Ldl;
    //   2719: invokevirtual 245	dl:v	()V
    //   2722: getstatic 84	dn:ae	Z
    //   2725: invokestatic 319	r:f	(I)Z
    //   2728: ifeq +2046 -> 4774
    //   2731: aload_3
    //   2732: getstatic 174	fn:dc	[Lad;
    //   2735: aload 10
    //   2737: getfield 181	fy:a	Lev;
    //   2740: getfield 165	ev:e	B
    //   2743: aaload
    //   2744: getstatic 190	r:ab	[I
    //   2747: iconst_0
    //   2748: iaload
    //   2749: invokevirtual 250	dt:a	(Lad;I)V
    //   2752: ldc 1
    //   2754: invokevirtual 280	java/lang/String:length	()I
    //   2757: pop
    //   2758: ldc 4
    //   2760: invokevirtual 280	java/lang/String:length	()I
    //   2763: ldc 3
    //   2765: invokevirtual 280	java/lang/String:length	()I
    //   2768: if_icmpge +2006 -> 4774
    //   2771: return
    //   2772: aload 10
    //   2774: getstatic 190	r:ab	[I
    //   2777: iconst_3
    //   2778: iaload
    //   2779: putfield 186	fy:k	Z
    //   2782: ldc 1
    //   2784: invokevirtual 280	java/lang/String:length	()I
    //   2787: pop
    //   2788: sipush 220
    //   2791: sipush 149
    //   2794: ixor
    //   2795: bipush 35
    //   2797: bipush 110
    //   2799: ixor
    //   2800: ixor
    //   2801: ifge +1973 -> 4774
    //   2804: return
    //   2805: getstatic 90	dn:am	Z
    //   2808: invokestatic 328	r:i	(I)Z
    //   2811: ifeq +42 -> 2853
    //   2814: aload 7
    //   2816: invokestatic 300	r:a	(Ljava/lang/Object;)Z
    //   2819: ifeq +34 -> 2853
    //   2822: aload 7
    //   2824: invokestatic 310	r:c	(Ldt;)Z
    //   2827: invokestatic 319	r:f	(I)Z
    //   2830: ifeq +23 -> 2853
    //   2833: iload 8
    //   2835: invokestatic 319	r:f	(I)Z
    //   2838: ifeq +981 -> 3819
    //   2841: aload_3
    //   2842: aload 7
    //   2844: invokestatic 298	r:a	(Ldt;Ldt;)Z
    //   2847: invokestatic 319	r:f	(I)Z
    //   2850: ifeq +969 -> 3819
    //   2853: aload 6
    //   2855: invokestatic 300	r:a	(Ljava/lang/Object;)Z
    //   2858: ifeq +43 -> 2901
    //   2861: iload_1
    //   2862: getstatic 190	r:ab	[I
    //   2865: bipush 8
    //   2867: iaload
    //   2868: invokestatic 314	r:d	(II)Z
    //   2871: ifeq +15 -> 2886
    //   2874: aload 6
    //   2876: getfield 148	e:v	I
    //   2879: iload_1
    //   2880: invokestatic 326	r:h	(II)Z
    //   2883: ifeq +18 -> 2901
    //   2886: aload 6
    //   2888: getfield 146	e:t	S
    //   2891: iload_2
    //   2892: invokestatic 308	r:c	(II)Z
    //   2895: invokestatic 319	r:f	(I)Z
    //   2898: ifeq +4 -> 2902
    //   2901: return
    //   2902: aload 10
    //   2904: getfield 181	fy:a	Lev;
    //   2907: getfield 164	ev:b	I
    //   2910: getstatic 190	r:ab	[I
    //   2913: iconst_3
    //   2914: iaload
    //   2915: invokestatic 314	r:d	(II)Z
    //   2918: ifeq +22 -> 2940
    //   2921: aload 10
    //   2923: getfield 181	fy:a	Lev;
    //   2926: getfield 164	ev:b	I
    //   2929: getstatic 190	r:ab	[I
    //   2932: iconst_1
    //   2933: iaload
    //   2934: invokestatic 326	r:h	(II)Z
    //   2937: ifeq +71 -> 3008
    //   2940: aload_3
    //   2941: getfield 122	dt:eg	I
    //   2944: aload 6
    //   2946: getfield 143	e:n	I
    //   2949: isub
    //   2950: invokestatic 217	bc:a	(I)I
    //   2953: aload 10
    //   2955: getfield 182	fy:c	I
    //   2958: getstatic 190	r:ab	[I
    //   2961: bipush 55
    //   2963: iaload
    //   2964: iadd
    //   2965: invokestatic 330	r:j	(II)Z
    //   2968: ifeq +34 -> 3002
    //   2971: aload_3
    //   2972: getfield 126	dt:ey	I
    //   2975: aload 6
    //   2977: getfield 137	e:d	I
    //   2980: isub
    //   2981: invokestatic 217	bc:a	(I)I
    //   2984: aload 10
    //   2986: getfield 184	fy:g	I
    //   2989: getstatic 190	r:ab	[I
    //   2992: bipush 55
    //   2994: iaload
    //   2995: iadd
    //   2996: invokestatic 329	r:i	(II)Z
    //   2999: ifeq +9 -> 3008
    //   3002: aload_3
    //   3003: aconst_null
    //   3004: putfield 102	dt:ab	Le;
    //   3007: return
    //   3008: aload 10
    //   3010: getfield 182	fy:c	I
    //   3013: istore 11
    //   3015: aload 10
    //   3017: getfield 184	fy:g	I
    //   3020: istore 4
    //   3022: getstatic 195	r:e	Lci;
    //   3025: invokevirtual 222	ci:removeAllElements	()V
    //   3028: getstatic 202	r:l	Lci;
    //   3031: invokevirtual 222	ci:removeAllElements	()V
    //   3034: getstatic 195	r:e	Lci;
    //   3037: aload 6
    //   3039: invokevirtual 220	ci:addElement	(Ljava/lang/Object;)V
    //   3042: getstatic 190	r:ab	[I
    //   3045: iconst_0
    //   3046: iaload
    //   3047: istore 9
    //   3049: iload 9
    //   3051: getstatic 172	fn:bv	Lci;
    //   3054: invokevirtual 288	java/util/Vector:size	()I
    //   3057: invokestatic 324	r:g	(II)Z
    //   3060: ifeq +240 -> 3300
    //   3063: getstatic 195	r:e	Lci;
    //   3066: invokevirtual 288	java/util/Vector:size	()I
    //   3069: getstatic 202	r:l	Lci;
    //   3072: invokevirtual 288	java/util/Vector:size	()I
    //   3075: iadd
    //   3076: aload 10
    //   3078: getfield 185	fy:i	I
    //   3081: invokestatic 324	r:g	(II)Z
    //   3084: ifeq +216 -> 3300
    //   3087: getstatic 172	fn:bv	Lci;
    //   3090: iload 9
    //   3092: invokevirtual 221	ci:elementAt	(I)Ljava/lang/Object;
    //   3095: checkcast 27	e
    //   3098: dup
    //   3099: astore 5
    //   3101: getfield 140	e:j	I
    //   3104: invokestatic 328	r:i	(I)Z
    //   3107: ifeq +170 -> 3277
    //   3110: aload 5
    //   3112: getfield 140	e:j	I
    //   3115: getstatic 190	r:ab	[I
    //   3118: iconst_3
    //   3119: iaload
    //   3120: invokestatic 314	r:d	(II)Z
    //   3123: ifeq +154 -> 3277
    //   3126: aload 5
    //   3128: aload 6
    //   3130: invokevirtual 278	java/lang/Object:equals	(Ljava/lang/Object;)Z
    //   3133: invokestatic 319	r:f	(I)Z
    //   3136: ifeq +141 -> 3277
    //   3139: aload 6
    //   3141: getfield 143	e:n	I
    //   3144: getstatic 190	r:ab	[I
    //   3147: iconst_4
    //   3148: iaload
    //   3149: isub
    //   3150: aload 5
    //   3152: getfield 143	e:n	I
    //   3155: invokestatic 330	r:j	(II)Z
    //   3158: ifeq +119 -> 3277
    //   3161: aload 5
    //   3163: getfield 143	e:n	I
    //   3166: aload 6
    //   3168: getfield 143	e:n	I
    //   3171: getstatic 190	r:ab	[I
    //   3174: iconst_4
    //   3175: iaload
    //   3176: iadd
    //   3177: invokestatic 330	r:j	(II)Z
    //   3180: ifeq +97 -> 3277
    //   3183: aload 6
    //   3185: getfield 137	e:d	I
    //   3188: getstatic 190	r:ab	[I
    //   3191: bipush 60
    //   3193: iaload
    //   3194: isub
    //   3195: aload 5
    //   3197: getfield 137	e:d	I
    //   3200: invokestatic 330	r:j	(II)Z
    //   3203: ifeq +74 -> 3277
    //   3206: aload 5
    //   3208: getfield 137	e:d	I
    //   3211: aload 6
    //   3213: getfield 137	e:d	I
    //   3216: getstatic 190	r:ab	[I
    //   3219: bipush 60
    //   3221: iaload
    //   3222: iadd
    //   3223: invokestatic 330	r:j	(II)Z
    //   3226: ifeq +51 -> 3277
    //   3229: aload 5
    //   3231: getfield 146	e:t	S
    //   3234: iload_2
    //   3235: invokestatic 308	r:c	(II)Z
    //   3238: invokestatic 328	r:i	(I)Z
    //   3241: ifeq +36 -> 3277
    //   3244: iload_1
    //   3245: getstatic 190	r:ab	[I
    //   3248: bipush 8
    //   3250: iaload
    //   3251: invokestatic 314	r:d	(II)Z
    //   3254: ifeq +15 -> 3269
    //   3257: aload 5
    //   3259: getfield 148	e:v	I
    //   3262: iload_1
    //   3263: invokestatic 326	r:h	(II)Z
    //   3266: ifeq +11 -> 3277
    //   3269: getstatic 195	r:e	Lci;
    //   3272: aload 5
    //   3274: invokevirtual 220	ci:addElement	(Ljava/lang/Object;)V
    //   3277: iinc 9 1
    //   3280: ldc 1
    //   3282: invokevirtual 280	java/lang/String:length	()I
    //   3285: pop
    //   3286: ldc 4
    //   3288: invokevirtual 280	java/lang/String:length	()I
    //   3291: ldc 2
    //   3293: invokevirtual 280	java/lang/String:length	()I
    //   3296: if_icmpgt -247 -> 3049
    //   3299: return
    //   3300: getstatic 190	r:ab	[I
    //   3303: iconst_0
    //   3304: iaload
    //   3305: istore 9
    //   3307: iload 9
    //   3309: getstatic 176	fn:ep	Lci;
    //   3312: invokevirtual 288	java/util/Vector:size	()I
    //   3315: invokestatic 324	r:g	(II)Z
    //   3318: ifeq +350 -> 3668
    //   3321: getstatic 195	r:e	Lci;
    //   3324: invokevirtual 288	java/util/Vector:size	()I
    //   3327: getstatic 202	r:l	Lci;
    //   3330: invokevirtual 288	java/util/Vector:size	()I
    //   3333: iadd
    //   3334: aload 10
    //   3336: getfield 185	fy:i	I
    //   3339: invokestatic 324	r:g	(II)Z
    //   3342: ifeq +326 -> 3668
    //   3345: getstatic 176	fn:ep	Lci;
    //   3348: iload 9
    //   3350: invokevirtual 221	ci:elementAt	(I)Ljava/lang/Object;
    //   3353: checkcast 25	dt
    //   3356: dup
    //   3357: astore 5
    //   3359: getfield 121	dt:ef	I
    //   3362: invokestatic 323	r:g	(I)Z
    //   3365: ifeq +279 -> 3644
    //   3368: aload 5
    //   3370: getfield 120	dt:ee	I
    //   3373: getstatic 190	r:ab	[I
    //   3376: bipush 10
    //   3378: iaload
    //   3379: invokestatic 314	r:d	(II)Z
    //   3382: ifeq +262 -> 3644
    //   3385: aload 5
    //   3387: getfield 120	dt:ee	I
    //   3390: getstatic 190	r:ab	[I
    //   3393: bipush 11
    //   3395: iaload
    //   3396: invokestatic 314	r:d	(II)Z
    //   3399: ifeq +245 -> 3644
    //   3402: aload 5
    //   3404: getfield 120	dt:ee	I
    //   3407: getstatic 190	r:ab	[I
    //   3410: bipush 19
    //   3412: iaload
    //   3413: invokestatic 314	r:d	(II)Z
    //   3416: ifeq +228 -> 3644
    //   3419: aload 5
    //   3421: getfield 130	dt:fm	B
    //   3424: getstatic 190	r:ab	[I
    //   3427: iconst_1
    //   3428: iaload
    //   3429: invokestatic 314	r:d	(II)Z
    //   3432: ifeq +114 -> 3546
    //   3435: aload_3
    //   3436: getfield 130	dt:fm	B
    //   3439: getstatic 190	r:ab	[I
    //   3442: iconst_1
    //   3443: iaload
    //   3444: invokestatic 314	r:d	(II)Z
    //   3447: ifeq +99 -> 3546
    //   3450: aload 5
    //   3452: getfield 130	dt:fm	B
    //   3455: getstatic 190	r:ab	[I
    //   3458: iconst_3
    //   3459: iaload
    //   3460: invokestatic 326	r:h	(II)Z
    //   3463: ifeq +18 -> 3481
    //   3466: aload_3
    //   3467: getfield 130	dt:fm	B
    //   3470: getstatic 190	r:ab	[I
    //   3473: iconst_3
    //   3474: iaload
    //   3475: invokestatic 314	r:d	(II)Z
    //   3478: ifeq +68 -> 3546
    //   3481: aload_3
    //   3482: getfield 123	dt:eh	I
    //   3485: invokestatic 313	r:d	(I)Z
    //   3488: ifeq +18 -> 3506
    //   3491: aload_3
    //   3492: getfield 123	dt:eh	I
    //   3495: aload 5
    //   3497: getfield 131	dt:fy	I
    //   3500: invokestatic 314	r:d	(II)Z
    //   3503: ifeq +43 -> 3546
    //   3506: aload_3
    //   3507: getfield 103	dt:ai	I
    //   3510: invokestatic 313	r:d	(I)Z
    //   3513: ifeq +18 -> 3531
    //   3516: aload_3
    //   3517: getfield 103	dt:ai	I
    //   3520: aload 5
    //   3522: getfield 131	dt:fy	I
    //   3525: invokestatic 314	r:d	(II)Z
    //   3528: ifeq +18 -> 3546
    //   3531: aload 5
    //   3533: getfield 123	dt:eh	I
    //   3536: aload_3
    //   3537: getfield 131	dt:fy	I
    //   3540: invokestatic 326	r:h	(II)Z
    //   3543: ifeq +101 -> 3644
    //   3546: aload 5
    //   3548: getfield 111	dt:ci	Ljava/lang/String;
    //   3551: invokestatic 248	dn:f	(Ljava/lang/String;)Z
    //   3554: invokestatic 319	r:f	(I)Z
    //   3557: ifeq +87 -> 3644
    //   3560: aload 6
    //   3562: getfield 147	e:u	I
    //   3565: iload 11
    //   3567: isub
    //   3568: aload 5
    //   3570: getfield 122	dt:eg	I
    //   3573: invokestatic 330	r:j	(II)Z
    //   3576: ifeq +68 -> 3644
    //   3579: aload 5
    //   3581: getfield 122	dt:eg	I
    //   3584: aload 6
    //   3586: getfield 147	e:u	I
    //   3589: iload 11
    //   3591: iadd
    //   3592: invokestatic 330	r:j	(II)Z
    //   3595: ifeq +49 -> 3644
    //   3598: aload 6
    //   3600: getfield 141	e:l	I
    //   3603: iload 4
    //   3605: isub
    //   3606: aload 5
    //   3608: getfield 126	dt:ey	I
    //   3611: invokestatic 330	r:j	(II)Z
    //   3614: ifeq +30 -> 3644
    //   3617: aload 5
    //   3619: getfield 126	dt:ey	I
    //   3622: aload 6
    //   3624: getfield 141	e:l	I
    //   3627: iload 4
    //   3629: iadd
    //   3630: invokestatic 330	r:j	(II)Z
    //   3633: ifeq +11 -> 3644
    //   3636: getstatic 202	r:l	Lci;
    //   3639: aload 5
    //   3641: invokevirtual 220	ci:addElement	(Ljava/lang/Object;)V
    //   3644: iinc 9 1
    //   3647: ldc 1
    //   3649: invokevirtual 280	java/lang/String:length	()I
    //   3652: pop
    //   3653: ldc 2
    //   3655: invokevirtual 280	java/lang/String:length	()I
    //   3658: ineg
    //   3659: ldc 3
    //   3661: invokevirtual 280	java/lang/String:length	()I
    //   3664: if_icmpne -357 -> 3307
    //   3667: return
    //   3668: invokestatic 284	java/lang/System:currentTimeMillis	()J
    //   3671: aload 10
    //   3673: getfield 183	fy:e	J
    //   3676: lsub
    //   3677: aload 10
    //   3679: getfield 187	fy:l	I
    //   3682: i2l
    //   3683: invokestatic 309	r:c	(JJ)I
    //   3686: invokestatic 313	r:d	(I)Z
    //   3689: ifeq +83 -> 3772
    //   3692: aload 10
    //   3694: invokestatic 284	java/lang/System:currentTimeMillis	()J
    //   3697: putfield 183	fy:e	J
    //   3700: invokestatic 237	dl:ae	()Ldl;
    //   3703: aload 10
    //   3705: getfield 181	fy:a	Lev;
    //   3708: getfield 165	ev:e	B
    //   3711: invokevirtual 242	dl:l	(I)V
    //   3714: invokestatic 237	dl:ae	()Ldl;
    //   3717: getstatic 195	r:e	Lci;
    //   3720: getstatic 202	r:l	Lci;
    //   3723: getstatic 190	r:ab	[I
    //   3726: iconst_3
    //   3727: iaload
    //   3728: invokevirtual 233	dl:a	(Lci;Lci;I)V
    //   3731: getstatic 84	dn:ae	Z
    //   3734: invokestatic 319	r:f	(I)Z
    //   3737: ifeq +1037 -> 4774
    //   3740: aload_3
    //   3741: getstatic 174	fn:dc	[Lad;
    //   3744: aload 10
    //   3746: getfield 181	fy:a	Lev;
    //   3749: getfield 165	ev:e	B
    //   3752: aaload
    //   3753: getstatic 190	r:ab	[I
    //   3756: iconst_0
    //   3757: iaload
    //   3758: invokevirtual 250	dt:a	(Lad;I)V
    //   3761: ldc 1
    //   3763: invokevirtual 280	java/lang/String:length	()I
    //   3766: pop
    //   3767: aconst_null
    //   3768: ifnull +1006 -> 4774
    //   3771: return
    //   3772: aload 10
    //   3774: getstatic 190	r:ab	[I
    //   3777: iconst_3
    //   3778: iaload
    //   3779: putfield 186	fy:k	Z
    //   3782: ldc 1
    //   3784: invokevirtual 280	java/lang/String:length	()I
    //   3787: pop
    //   3788: bipush 113
    //   3790: bipush 121
    //   3792: ixor
    //   3793: bipush 20
    //   3795: bipush 28
    //   3797: ixor
    //   3798: iconst_m1
    //   3799: ixor
    //   3800: iand
    //   3801: sipush 217
    //   3804: sipush 144
    //   3807: ixor
    //   3808: iconst_0
    //   3809: bipush 73
    //   3811: ixor
    //   3812: iconst_m1
    //   3813: ixor
    //   3814: iand
    //   3815: if_icmple +959 -> 4774
    //   3818: return
    //   3819: iload 8
    //   3821: invokestatic 328	r:i	(I)Z
    //   3824: ifeq +186 -> 4010
    //   3827: aload 10
    //   3829: getfield 181	fy:a	Lev;
    //   3832: getfield 164	ev:b	I
    //   3835: getstatic 190	r:ab	[I
    //   3838: iconst_3
    //   3839: iaload
    //   3840: invokestatic 314	r:d	(II)Z
    //   3843: ifeq +22 -> 3865
    //   3846: aload 10
    //   3848: getfield 181	fy:a	Lev;
    //   3851: getfield 164	ev:b	I
    //   3854: getstatic 190	r:ab	[I
    //   3857: iconst_1
    //   3858: iaload
    //   3859: invokestatic 326	r:h	(II)Z
    //   3862: ifeq +97 -> 3959
    //   3865: aload_3
    //   3866: getfield 122	dt:eg	I
    //   3869: aload 7
    //   3871: getfield 122	dt:eg	I
    //   3874: isub
    //   3875: invokestatic 217	bc:a	(I)I
    //   3878: aload 10
    //   3880: getfield 182	fy:c	I
    //   3883: getstatic 190	r:ab	[I
    //   3886: bipush 55
    //   3888: iaload
    //   3889: iadd
    //   3890: invokestatic 330	r:j	(II)Z
    //   3893: ifeq +34 -> 3927
    //   3896: aload_3
    //   3897: getfield 126	dt:ey	I
    //   3900: aload 7
    //   3902: getfield 126	dt:ey	I
    //   3905: isub
    //   3906: invokestatic 217	bc:a	(I)I
    //   3909: aload 10
    //   3911: getfield 184	fy:g	I
    //   3914: getstatic 190	r:ab	[I
    //   3917: bipush 55
    //   3919: iaload
    //   3920: iadd
    //   3921: invokestatic 329	r:i	(II)Z
    //   3924: ifeq +35 -> 3959
    //   3927: invokestatic 284	java/lang/System:currentTimeMillis	()J
    //   3930: aload_0
    //   3931: getfield 207	r:q	J
    //   3934: lsub
    //   3935: ldc2_w 66
    //   3938: invokestatic 309	r:c	(JJ)I
    //   3941: invokestatic 323	r:g	(I)Z
    //   3944: ifeq +15 -> 3959
    //   3947: aload 7
    //   3949: invokestatic 295	r:a	(Ldt;)V
    //   3952: aload_0
    //   3953: invokestatic 284	java/lang/System:currentTimeMillis	()J
    //   3956: putfield 207	r:q	J
    //   3959: aload 7
    //   3961: getfield 123	dt:eh	I
    //   3964: aload_3
    //   3965: getfield 131	dt:fy	I
    //   3968: invokestatic 314	r:d	(II)Z
    //   3971: ifeq +39 -> 4010
    //   3974: aload 7
    //   3976: getfield 130	dt:fm	B
    //   3979: getstatic 190	r:ab	[I
    //   3982: iconst_1
    //   3983: iaload
    //   3984: invokestatic 314	r:d	(II)Z
    //   3987: ifeq +23 -> 4010
    //   3990: aload_0
    //   3991: getstatic 190	r:ab	[I
    //   3994: iconst_3
    //   3995: iaload
    //   3996: putfield 204	r:n	Z
    //   3999: invokestatic 237	dl:ae	()Ldl;
    //   4002: getstatic 190	r:ab	[I
    //   4005: iconst_1
    //   4006: iaload
    //   4007: invokevirtual 246	dl:x	(I)V
    //   4010: aload 10
    //   4012: getfield 182	fy:c	I
    //   4015: istore 11
    //   4017: aload 10
    //   4019: getfield 184	fy:g	I
    //   4022: istore 4
    //   4024: getstatic 195	r:e	Lci;
    //   4027: invokevirtual 222	ci:removeAllElements	()V
    //   4030: getstatic 202	r:l	Lci;
    //   4033: invokevirtual 222	ci:removeAllElements	()V
    //   4036: getstatic 202	r:l	Lci;
    //   4039: aload 7
    //   4041: invokevirtual 220	ci:addElement	(Ljava/lang/Object;)V
    //   4044: getstatic 190	r:ab	[I
    //   4047: iconst_0
    //   4048: iaload
    //   4049: istore 9
    //   4051: iload 9
    //   4053: getstatic 176	fn:ep	Lci;
    //   4056: invokevirtual 288	java/util/Vector:size	()I
    //   4059: invokestatic 324	r:g	(II)Z
    //   4062: ifeq +365 -> 4427
    //   4065: getstatic 195	r:e	Lci;
    //   4068: invokevirtual 288	java/util/Vector:size	()I
    //   4071: getstatic 202	r:l	Lci;
    //   4074: invokevirtual 288	java/util/Vector:size	()I
    //   4077: iadd
    //   4078: aload 10
    //   4080: getfield 185	fy:i	I
    //   4083: invokestatic 324	r:g	(II)Z
    //   4086: ifeq +341 -> 4427
    //   4089: getstatic 176	fn:ep	Lci;
    //   4092: iload 9
    //   4094: invokevirtual 221	ci:elementAt	(I)Ljava/lang/Object;
    //   4097: checkcast 25	dt
    //   4100: dup
    //   4101: astore 5
    //   4103: getfield 121	dt:ef	I
    //   4106: invokestatic 323	r:g	(I)Z
    //   4109: ifeq +292 -> 4401
    //   4112: aload 5
    //   4114: getfield 120	dt:ee	I
    //   4117: getstatic 190	r:ab	[I
    //   4120: bipush 10
    //   4122: iaload
    //   4123: invokestatic 314	r:d	(II)Z
    //   4126: ifeq +275 -> 4401
    //   4129: aload 5
    //   4131: getfield 120	dt:ee	I
    //   4134: getstatic 190	r:ab	[I
    //   4137: bipush 11
    //   4139: iaload
    //   4140: invokestatic 314	r:d	(II)Z
    //   4143: ifeq +258 -> 4401
    //   4146: aload 5
    //   4148: getfield 120	dt:ee	I
    //   4151: getstatic 190	r:ab	[I
    //   4154: bipush 19
    //   4156: iaload
    //   4157: invokestatic 314	r:d	(II)Z
    //   4160: ifeq +241 -> 4401
    //   4163: aload 5
    //   4165: aload 7
    //   4167: invokevirtual 278	java/lang/Object:equals	(Ljava/lang/Object;)Z
    //   4170: invokestatic 319	r:f	(I)Z
    //   4173: ifeq +228 -> 4401
    //   4176: aload 5
    //   4178: getfield 130	dt:fm	B
    //   4181: getstatic 190	r:ab	[I
    //   4184: iconst_1
    //   4185: iaload
    //   4186: invokestatic 314	r:d	(II)Z
    //   4189: ifeq +114 -> 4303
    //   4192: aload_3
    //   4193: getfield 130	dt:fm	B
    //   4196: getstatic 190	r:ab	[I
    //   4199: iconst_1
    //   4200: iaload
    //   4201: invokestatic 314	r:d	(II)Z
    //   4204: ifeq +99 -> 4303
    //   4207: aload 5
    //   4209: getfield 130	dt:fm	B
    //   4212: getstatic 190	r:ab	[I
    //   4215: iconst_3
    //   4216: iaload
    //   4217: invokestatic 326	r:h	(II)Z
    //   4220: ifeq +18 -> 4238
    //   4223: aload_3
    //   4224: getfield 130	dt:fm	B
    //   4227: getstatic 190	r:ab	[I
    //   4230: iconst_3
    //   4231: iaload
    //   4232: invokestatic 314	r:d	(II)Z
    //   4235: ifeq +68 -> 4303
    //   4238: aload_3
    //   4239: getfield 123	dt:eh	I
    //   4242: invokestatic 313	r:d	(I)Z
    //   4245: ifeq +18 -> 4263
    //   4248: aload_3
    //   4249: getfield 123	dt:eh	I
    //   4252: aload 5
    //   4254: getfield 131	dt:fy	I
    //   4257: invokestatic 314	r:d	(II)Z
    //   4260: ifeq +43 -> 4303
    //   4263: aload_3
    //   4264: getfield 103	dt:ai	I
    //   4267: invokestatic 313	r:d	(I)Z
    //   4270: ifeq +18 -> 4288
    //   4273: aload_3
    //   4274: getfield 103	dt:ai	I
    //   4277: aload 5
    //   4279: getfield 131	dt:fy	I
    //   4282: invokestatic 314	r:d	(II)Z
    //   4285: ifeq +18 -> 4303
    //   4288: aload 5
    //   4290: getfield 123	dt:eh	I
    //   4293: aload_3
    //   4294: getfield 131	dt:fy	I
    //   4297: invokestatic 326	r:h	(II)Z
    //   4300: ifeq +101 -> 4401
    //   4303: aload 5
    //   4305: getfield 111	dt:ci	Ljava/lang/String;
    //   4308: invokestatic 248	dn:f	(Ljava/lang/String;)Z
    //   4311: invokestatic 319	r:f	(I)Z
    //   4314: ifeq +87 -> 4401
    //   4317: aload 7
    //   4319: getfield 122	dt:eg	I
    //   4322: iload 11
    //   4324: isub
    //   4325: aload 5
    //   4327: getfield 122	dt:eg	I
    //   4330: invokestatic 330	r:j	(II)Z
    //   4333: ifeq +68 -> 4401
    //   4336: aload 5
    //   4338: getfield 122	dt:eg	I
    //   4341: aload 7
    //   4343: getfield 122	dt:eg	I
    //   4346: iload 11
    //   4348: iadd
    //   4349: invokestatic 330	r:j	(II)Z
    //   4352: ifeq +49 -> 4401
    //   4355: aload 7
    //   4357: getfield 126	dt:ey	I
    //   4360: iload 4
    //   4362: isub
    //   4363: aload 5
    //   4365: getfield 126	dt:ey	I
    //   4368: invokestatic 330	r:j	(II)Z
    //   4371: ifeq +30 -> 4401
    //   4374: aload 5
    //   4376: getfield 126	dt:ey	I
    //   4379: aload 7
    //   4381: getfield 126	dt:ey	I
    //   4384: iload 4
    //   4386: iadd
    //   4387: invokestatic 330	r:j	(II)Z
    //   4390: ifeq +11 -> 4401
    //   4393: getstatic 202	r:l	Lci;
    //   4396: aload 5
    //   4398: invokevirtual 220	ci:addElement	(Ljava/lang/Object;)V
    //   4401: iinc 9 1
    //   4404: ldc 1
    //   4406: invokevirtual 280	java/lang/String:length	()I
    //   4409: pop
    //   4410: sipush 182
    //   4413: sipush 178
    //   4416: ixor
    //   4417: ldc 2
    //   4419: invokevirtual 280	java/lang/String:length	()I
    //   4422: ineg
    //   4423: if_icmpge -372 -> 4051
    //   4426: return
    //   4427: getstatic 190	r:ab	[I
    //   4430: iconst_0
    //   4431: iaload
    //   4432: istore 9
    //   4434: iload 9
    //   4436: getstatic 172	fn:bv	Lci;
    //   4439: invokevirtual 288	java/util/Vector:size	()I
    //   4442: invokestatic 324	r:g	(II)Z
    //   4445: ifeq +214 -> 4659
    //   4448: getstatic 195	r:e	Lci;
    //   4451: invokevirtual 288	java/util/Vector:size	()I
    //   4454: getstatic 202	r:l	Lci;
    //   4457: invokevirtual 288	java/util/Vector:size	()I
    //   4460: iadd
    //   4461: aload 10
    //   4463: getfield 185	fy:i	I
    //   4466: invokestatic 324	r:g	(II)Z
    //   4469: ifeq +190 -> 4659
    //   4472: getstatic 172	fn:bv	Lci;
    //   4475: iload 9
    //   4477: invokevirtual 221	ci:elementAt	(I)Ljava/lang/Object;
    //   4480: checkcast 27	e
    //   4483: dup
    //   4484: astore 5
    //   4486: getfield 140	e:j	I
    //   4489: invokestatic 328	r:i	(I)Z
    //   4492: ifeq +143 -> 4635
    //   4495: aload 5
    //   4497: getfield 140	e:j	I
    //   4500: getstatic 190	r:ab	[I
    //   4503: iconst_3
    //   4504: iaload
    //   4505: invokestatic 314	r:d	(II)Z
    //   4508: ifeq +127 -> 4635
    //   4511: aload 7
    //   4513: getfield 122	dt:eg	I
    //   4516: iload 11
    //   4518: isub
    //   4519: aload 5
    //   4521: getfield 147	e:u	I
    //   4524: invokestatic 330	r:j	(II)Z
    //   4527: ifeq +108 -> 4635
    //   4530: aload 5
    //   4532: getfield 147	e:u	I
    //   4535: aload 7
    //   4537: getfield 122	dt:eg	I
    //   4540: iload 11
    //   4542: iadd
    //   4543: invokestatic 330	r:j	(II)Z
    //   4546: ifeq +89 -> 4635
    //   4549: aload 7
    //   4551: getfield 126	dt:ey	I
    //   4554: iload 4
    //   4556: isub
    //   4557: aload 5
    //   4559: getfield 141	e:l	I
    //   4562: invokestatic 330	r:j	(II)Z
    //   4565: ifeq +70 -> 4635
    //   4568: aload 5
    //   4570: getfield 141	e:l	I
    //   4573: aload 7
    //   4575: getfield 126	dt:ey	I
    //   4578: iload 4
    //   4580: iadd
    //   4581: invokestatic 330	r:j	(II)Z
    //   4584: ifeq +51 -> 4635
    //   4587: aload 5
    //   4589: getfield 146	e:t	S
    //   4592: iload_2
    //   4593: invokestatic 308	r:c	(II)Z
    //   4596: invokestatic 328	r:i	(I)Z
    //   4599: ifeq +36 -> 4635
    //   4602: iload_1
    //   4603: getstatic 190	r:ab	[I
    //   4606: bipush 8
    //   4608: iaload
    //   4609: invokestatic 314	r:d	(II)Z
    //   4612: ifeq +15 -> 4627
    //   4615: aload 5
    //   4617: getfield 148	e:v	I
    //   4620: iload_1
    //   4621: invokestatic 326	r:h	(II)Z
    //   4624: ifeq +11 -> 4635
    //   4627: getstatic 195	r:e	Lci;
    //   4630: aload 5
    //   4632: invokevirtual 220	ci:addElement	(Ljava/lang/Object;)V
    //   4635: iinc 9 1
    //   4638: ldc 1
    //   4640: invokevirtual 280	java/lang/String:length	()I
    //   4643: pop
    //   4644: ldc 3
    //   4646: invokevirtual 280	java/lang/String:length	()I
    //   4649: ldc 2
    //   4651: invokevirtual 280	java/lang/String:length	()I
    //   4654: ineg
    //   4655: if_icmpgt -221 -> 4434
    //   4658: return
    //   4659: invokestatic 284	java/lang/System:currentTimeMillis	()J
    //   4662: aload 10
    //   4664: getfield 183	fy:e	J
    //   4667: lsub
    //   4668: aload 10
    //   4670: getfield 187	fy:l	I
    //   4673: i2l
    //   4674: invokestatic 309	r:c	(JJ)I
    //   4677: invokestatic 313	r:d	(I)Z
    //   4680: ifeq +84 -> 4764
    //   4683: aload 10
    //   4685: invokestatic 284	java/lang/System:currentTimeMillis	()J
    //   4688: putfield 183	fy:e	J
    //   4691: invokestatic 237	dl:ae	()Ldl;
    //   4694: aload 10
    //   4696: getfield 181	fy:a	Lev;
    //   4699: getfield 165	ev:e	B
    //   4702: invokevirtual 242	dl:l	(I)V
    //   4705: invokestatic 237	dl:ae	()Ldl;
    //   4708: getstatic 195	r:e	Lci;
    //   4711: getstatic 202	r:l	Lci;
    //   4714: getstatic 190	r:ab	[I
    //   4717: bipush 6
    //   4719: iaload
    //   4720: invokevirtual 233	dl:a	(Lci;Lci;I)V
    //   4723: getstatic 84	dn:ae	Z
    //   4726: invokestatic 319	r:f	(I)Z
    //   4729: ifeq +45 -> 4774
    //   4732: aload_3
    //   4733: getstatic 174	fn:dc	[Lad;
    //   4736: aload 10
    //   4738: getfield 181	fy:a	Lev;
    //   4741: getfield 165	ev:e	B
    //   4744: aaload
    //   4745: getstatic 190	r:ab	[I
    //   4748: iconst_0
    //   4749: iaload
    //   4750: invokevirtual 250	dt:a	(Lad;I)V
    //   4753: ldc 1
    //   4755: invokevirtual 280	java/lang/String:length	()I
    //   4758: pop
    //   4759: aconst_null
    //   4760: ifnull +14 -> 4774
    //   4763: return
    //   4764: aload 10
    //   4766: getstatic 190	r:ab	[I
    //   4769: iconst_3
    //   4770: iaload
    //   4771: putfield 186	fy:k	Z
    //   4774: aload_0
    //   4775: invokestatic 284	java/lang/System:currentTimeMillis	()J
    //   4778: putfield 210	r:u	J
    //   4781: return
    // Local variable table:
    //   start	length	slot	name	signature
    //   0	4782	0	this	r
    //   0	4782	1	paramInt1	int
    //   0	4782	2	paramInt2	int
    //   6	4727	3	localdt1	dt
    //   66	667	4	localdt2	dt
    //   923	3658	4	i1	int
    //   137	598	5	i2	int
    //   996	58	5	localdt3	dt
    //   1424	151	5	i3	int
    //   1716	2915	5	localObject1	Object
    //   143	3480	6	localObject2	Object
    //   149	4425	7	localdt4	dt
    //   283	3537	8	i4	int
    //   378	32	9	localao	ao
    //   467	283	9	i5	int
    //   879	262	9	localfy	fy
    //   1371	3265	9	i6	int
    //   849	392	10	i7	int
    //   1459	3306	10	localObject3	Object
    //   951	160	11	localbk	bk
    //   1686	2857	11	i8	int
    //   1998	78	12	localbt	bt
    //   561	1	22	localInterruptedException1	InterruptedException
    //   1101	1	23	localInterruptedException2	InterruptedException
    //   1164	1	24	localInterruptedException3	InterruptedException
    //   2644	1	25	localInterruptedException4	InterruptedException
    // Exception table:
    //   from	to	target	type
    //   535	541	561	java/lang/InterruptedException
    //   1067	1073	1101	java/lang/InterruptedException
    //   1157	1163	1164	java/lang/InterruptedException
    //   2618	2624	2644	java/lang/InterruptedException
  }
  
  private static void c()
  {
    ab = new int[75];
    ab[0] = ((0xEC ^ 0xBB) & (0xD7 ^ 0x80 ^ 0xFFFFFFFF));
    ab[1] = "   ".length();
    ab[2] = (0x3 ^ 0x8 ^ " ".length());
    ab[3] = " ".length();
    ab[4] = (0x58 ^ 0x10 ^ 0x79 ^ 0x55);
    ab[5] = (0xCA ^ 0x93);
    ab[6] = "  ".length();
    ab[7] = (0xCF7F & 0x31AC);
    ab[8] = (-" ".length());
    ab[9] = (0xA5 ^ 0xAC ^ 0xA9 ^ 0xA4);
    ab[10] = (92 + '' - 145 + 64 ^ 71 + 74 - 125 + 131);
    ab[11] = (0x87 ^ 0x89 ^ 0x3A ^ 0x31);
    ab[12] = (118 + '' - 134 + 27);
    ab[13] = ((0x16 ^ 0x62) + (0x58 ^ 0x17) - (0x92 ^ 0xA3) + "  ".length());
    ab[14] = (0x7 ^ 0x22);
    ab[15] = (0x13 ^ 0x30);
    ab[16] = (0x43 ^ 0x4E);
    ab[17] = (-(0xFE7B & 0x538D) & 0xFFFFFF9F & 0x53F8);
    ab[18] = (0x80 ^ 0x86);
    ab[19] = (0x50 ^ 0x5F);
    ab[20] = (0x21 ^ 0x42 ^ 0x70 ^ 0x5);
    ab[21] = (0x48 ^ 0x5C ^ 0x63 ^ 0x14);
    ab[22] = ('' + 53 - 63 + 119 ^ 14 + 51 - -79 + 12);
    ab[23] = (49 + 108 - 24 + 1);
    ab[24] = (((0x3F ^ 0x3A) & (0x47 ^ 0x42 ^ 0xFFFFFFFF)) + (0x16 ^ 0x1B) - -(0x93 ^ 0x9F) + (0xDA ^ 0xB4));
    ab[25] = ((0x96 ^ 0x86) + (0x51 ^ 0x7F) - -(0xD5 ^ 0x9F) + ((0xE ^ 0x21) & (0x65 ^ 0x4A ^ 0xFFFFFFFF)));
    ab[26] = ((0x11 ^ 0x4F) + (0xF4 ^ 0xB7) - (0xDE ^ 0x9E) + (0x8C ^ 0xA4));
    ab[27] = ((0x4F ^ 0x17) + (0x5E ^ 0xF) - (121 + 42 - 99 + 90) + ('®' + 13 - 49 + 49));
    ab[28] = (0x41 ^ 0x49);
    ab[29] = (0xADDF & 0x57B4);
    ab[30] = (0xB7F7 & 0x4A18);
    ab[31] = (0xFFFFFFFC & 0x5AF);
    ab[32] = (-(0xDDEE & 0x77D7) & 0xF7EF & 0x5FFD);
    ab[33] = (0x85CD & 0x7F36);
    ab[34] = (-(0xDAC4 & 0x6D3F) & 0xEFBF & 0x5D5F);
    ab[35] = (-(0xF41B & 0x7BF7) & 0xFFFFFFBE & 0x777F);
    ab[36] = (-(0xAD6A & 0x7FDD) & 0xFFFFFFCF & 0x2FFF);
    ab[37] = (-(0xADBB & 0x5AEF) & 0x9FFF & 0x6FBE);
    ab[38] = (0xBFBD & 0x42E2);
    ab[39] = (-(0xD5D5 & 0x7E3E) & 0xD7FF & 0x7F7F);
    ab[40] = (0xCBB5 & 0x37CE);
    ab[41] = (-(0xD7C7 & 0x6E7F) & 0xFFFFFFDF & 0x47FE);
    ab[42] = (0xA5B6 & 0x5BF9);
    ab[43] = (0xAFBF & 0x537C);
    ab[44] = (-(0xCC1B & 0x3FE7) & 0xEFFE & 0x1F57);
    ab[45] = (-(0xFA37 & 0x67CD) & 0xE3EC & 0x7F7F);
    ab[46] = (-(0xEAD3 & 0x7F2F) & 0xFFFFFFA6 & 0x6BDB);
    ab[47] = (-(0xFFFFFFA7 & 0x1C79) & 0xFFFFFFBC & 0x1FFF);
    ab[48] = (0xFE7A & 0x3F5);
    ab[49] = (0x96FF & 0x6BDC);
    ab[50] = (-(0xFBE7 & 0x7C9E) & 0xFEFF & 0x7BDD);
    ab[51] = (0xC6F6 & 0x3BFD);
    ab[52] = (-(0xF55F & 0x6FBB) & 0xFF5A & 0x67FF);
    ab[53] = ((0x29 ^ 0x4B) + ('' + '' - 152 + 58) - (0x9F3B & 0x61E7) + ('' + 126 - 227 + 143));
    ab[54] = (0x86 ^ 0xAE);
    ab[55] = (0x52 ^ 0x4C);
    ab[56] = (-(0xFEF5 & 0x6D1B) & 0xFFFFFFF9 & 0x6FFE);
    ab[57] = ((0x78 ^ 0x4) + (0xF5 ^ 0xAF) - (69 + '' - 100 + 32) + (0x41 ^ 0x20));
    ab[58] = (81 + 104 - 46 + 19);
    ab[59] = ((0xA2 ^ 0xC7) + (0x35 ^ 0x54) - (0xC7 ^ 0x86) + (0x11 ^ 0xB));
    ab[60] = (0xD4 ^ 0xBA ^ 0x14 ^ 0x48);
    ab[61] = (-(0xFB6F & 0x5CF5) & 0xD9FD & 0x7F67);
    ab[62] = (0xFB ^ 0x87 ^ 0xB2 ^ 0x8D);
    ab[63] = (0x19 ^ 0x51);
    ab[64] = (0x88 ^ 0x97);
    ab[65] = (0x12 ^ 0x28);
    ab[66] = (0xC0 ^ 0xC7);
    ab[67] = (0x83 ^ 0x93);
    ab[68] = (43 + 40 - 44 + 113 ^ 69 + 50 - 34 + 44);
    ab[69] = (0x1 ^ 0x23);
    ab[70] = (0x13 ^ 0x38);
    ab[71] = (23 + 50 - -107 + 17 + (72 + 45 - -5 + 5) - ('' + 'À' - 235 + 122) + (0x4A ^ 0x30));
    ab[72] = (0x23 ^ 0x30);
    ab[73] = (-"  ".length());
    ab[74] = (0x60 ^ 0x6C);
  }
  
  private static boolean g(int paramInt1, int paramInt2)
  {
    return paramInt1 < paramInt2;
  }
  
  protected static boolean k()
  {
    return c(dt.g());
  }
  
  public static void l()
  {
    c();
    r = new ci();
    y = new ci();
    v = ab[0];
    ac = -1L;
    e = new ci();
    l = new ci();
    aa = new ci();
    x = 0L;
  }
  
  static
  {
    cs.a(170);
    l();
  }
  
  private static boolean f(int paramInt)
  {
    return paramInt == 0;
  }
  
  private static boolean g(int paramInt)
  {
    return paramInt > 0;
  }
  
  public abstract void b();
  
  /* Error */
  protected final void a(int paramInt, boolean paramBoolean)
  {
    // Byte code:
    //   0: getstatic 97	dn:m	I
    //   3: invokestatic 313	r:d	(I)Z
    //   6: ifeq +18 -> 24
    //   9: getstatic 97	dn:m	I
    //   12: getstatic 88	dn:aj	Lci;
    //   15: invokevirtual 288	java/util/Vector:size	()I
    //   18: invokestatic 320	r:f	(II)Z
    //   21: ifeq +11 -> 32
    //   24: getstatic 190	r:ab	[I
    //   27: iconst_0
    //   28: iaload
    //   29: putstatic 97	dn:m	I
    //   32: getstatic 88	dn:aj	Lci;
    //   35: getstatic 97	dn:m	I
    //   38: invokevirtual 221	ci:elementAt	(I)Ljava/lang/Object;
    //   41: checkcast 37	java/lang/Integer
    //   44: invokevirtual 275	java/lang/Integer:intValue	()I
    //   47: istore_3
    //   48: getstatic 98	dn:o	Lci;
    //   51: getstatic 97	dn:m	I
    //   54: invokevirtual 221	ci:elementAt	(I)Ljava/lang/Object;
    //   57: checkcast 37	java/lang/Integer
    //   60: invokevirtual 275	java/lang/Integer:intValue	()I
    //   63: istore 4
    //   65: iload_3
    //   66: iload 4
    //   68: invokestatic 290	r:a	(II)Le;
    //   71: astore 5
    //   73: aload_0
    //   74: iload_1
    //   75: iload_3
    //   76: iload 4
    //   78: invokespecial 291	r:a	(III)Z
    //   81: invokestatic 319	r:f	(I)Z
    //   84: ifeq +110 -> 194
    //   87: aload_0
    //   88: iload_3
    //   89: iload 4
    //   91: invokespecial 317	r:e	(II)Z
    //   94: invokestatic 319	r:f	(I)Z
    //   97: ifeq +97 -> 194
    //   100: aload 5
    //   102: invokestatic 300	r:a	(Ljava/lang/Object;)Z
    //   105: ifeq +89 -> 194
    //   108: aload_0
    //   109: iload_1
    //   110: aload 5
    //   112: getfield 147	e:u	I
    //   115: aload 5
    //   117: getfield 141	e:l	I
    //   120: invokespecial 291	r:a	(III)Z
    //   123: invokestatic 319	r:f	(I)Z
    //   126: ifeq +68 -> 194
    //   129: aload_0
    //   130: invokestatic 256	dt:g	()Ldt;
    //   133: getfield 122	dt:eg	I
    //   136: putfield 212	r:w	I
    //   139: aload_0
    //   140: invokestatic 256	dt:g	()Ldt;
    //   143: getfield 126	dt:ey	I
    //   146: putfield 215	r:z	I
    //   149: iload_3
    //   150: iload 4
    //   152: invokestatic 252	dt:b	(II)Z
    //   155: ldc 1
    //   157: invokevirtual 280	java/lang/String:length	()I
    //   160: pop2
    //   161: invokestatic 256	dt:g	()Ldt;
    //   164: aload 5
    //   166: putfield 102	dt:ab	Le;
    //   169: invokestatic 237	dl:ae	()Ldl;
    //   172: aload 5
    //   174: getfield 150	e:y	S
    //   177: invokevirtual 234	dl:a	(S)V
    //   180: ldc2_w 52
    //   183: invokestatic 285	java/lang/Thread:sleep	(J)V
    //   186: return
    //   187: ldc 1
    //   189: invokevirtual 280	java/lang/String:length	()I
    //   192: pop2
    //   193: return
    //   194: getstatic 97	dn:m	I
    //   197: getstatic 190	r:ab	[I
    //   200: iconst_3
    //   201: iaload
    //   202: iadd
    //   203: dup
    //   204: putstatic 97	dn:m	I
    //   207: getstatic 88	dn:aj	Lci;
    //   210: invokevirtual 288	java/util/Vector:size	()I
    //   213: invokestatic 326	r:h	(II)Z
    //   216: ifeq +31 -> 247
    //   219: getstatic 190	r:ab	[I
    //   222: iconst_0
    //   223: iaload
    //   224: putstatic 97	dn:m	I
    //   227: getstatic 104	dt:ax	Z
    //   230: invokestatic 328	r:i	(I)Z
    //   233: ifeq +14 -> 247
    //   236: iload_2
    //   237: invokestatic 328	r:i	(I)Z
    //   240: ifeq +7 -> 247
    //   243: aload_0
    //   244: invokespecial 312	r:d	()V
    //   247: ldc 1
    //   249: invokevirtual 280	java/lang/String:length	()I
    //   252: pop
    //   253: sipush 242
    //   256: sipush 167
    //   259: ixor
    //   260: bipush 41
    //   262: bipush 124
    //   264: ixor
    //   265: iconst_m1
    //   266: ixor
    //   267: iand
    //   268: ifeq -236 -> 32
    //   271: return
    // Local variable table:
    //   start	length	slot	name	signature
    //   0	272	0	this	r
    //   0	272	1	paramInt	int
    //   0	272	2	paramBoolean	boolean
    //   47	103	3	i1	int
    //   63	88	4	i2	int
    //   71	102	5	locale	e
    //   187	1	6	localInterruptedException	InterruptedException
    // Exception table:
    //   from	to	target	type
    //   180	186	187	java/lang/InterruptedException
  }
  
  private static boolean a(Object paramObject1, Object paramObject2)
  {
    return paramObject1 != paramObject2;
  }
  
  protected static boolean c(dt paramdt)
  {
    if ((!g(paramdt.ef)) || (!d(paramdt.ee, ab[10])) || (h(paramdt.ee, ab[11]))) {
      return ab[3];
    }
    return ab[0];
  }
  
  private static boolean h(int paramInt)
  {
    return paramInt < 0;
  }
  
  /* Error */
  protected final void b(int paramInt)
  {
    // Byte code:
    //   0: aload_0
    //   1: getfield 188	r:a	Z
    //   4: invokestatic 328	r:i	(I)Z
    //   7: ifeq +30 -> 37
    //   10: getstatic 92	dn:as	Ljava/lang/String;
    //   13: invokestatic 300	r:a	(Ljava/lang/Object;)Z
    //   16: ifeq +21 -> 37
    //   19: invokestatic 256	dt:g	()Ldt;
    //   22: getfield 111	dt:ci	Ljava/lang/String;
    //   25: getstatic 92	dn:as	Ljava/lang/String;
    //   28: invokevirtual 279	java/lang/String:equals	(Ljava/lang/Object;)Z
    //   31: invokestatic 328	r:i	(I)Z
    //   34: ifeq +670 -> 704
    //   37: invokestatic 273	fn:j	()Lfn;
    //   40: astore_2
    //   41: getstatic 190	r:ab	[I
    //   44: bipush 16
    //   46: iaload
    //   47: invokestatic 272	fn:g	(I)Lfc;
    //   50: astore_3
    //   51: getstatic 190	r:ab	[I
    //   54: bipush 8
    //   56: iaload
    //   57: istore 4
    //   59: aload_3
    //   60: invokestatic 300	r:a	(Ljava/lang/Object;)Z
    //   63: ifeq +134 -> 197
    //   66: aload_3
    //   67: getfield 120	dt:ee	I
    //   70: getstatic 190	r:ab	[I
    //   73: bipush 19
    //   75: iaload
    //   76: invokestatic 314	r:d	(II)Z
    //   79: ifeq +118 -> 197
    //   82: aload_3
    //   83: getfield 122	dt:eg	I
    //   86: invokestatic 256	dt:g	()Ldt;
    //   89: getfield 122	dt:eg	I
    //   92: isub
    //   93: invokestatic 276	java/lang/Math:abs	(I)I
    //   96: getstatic 190	r:ab	[I
    //   99: bipush 20
    //   101: iaload
    //   102: invokestatic 330	r:j	(II)Z
    //   105: ifeq +29 -> 134
    //   108: aload_3
    //   109: getfield 126	dt:ey	I
    //   112: invokestatic 256	dt:g	()Ldt;
    //   115: getfield 126	dt:ey	I
    //   118: isub
    //   119: invokestatic 276	java/lang/Math:abs	(I)I
    //   122: getstatic 190	r:ab	[I
    //   125: bipush 20
    //   127: iaload
    //   128: invokestatic 329	r:i	(II)Z
    //   131: ifeq +220 -> 351
    //   134: aload_3
    //   135: getfield 122	dt:eg	I
    //   138: aload_3
    //   139: getfield 126	dt:ey	I
    //   142: invokestatic 252	dt:b	(II)Z
    //   145: ldc 1
    //   147: invokevirtual 280	java/lang/String:length	()I
    //   150: pop2
    //   151: lconst_0
    //   152: invokestatic 285	java/lang/Thread:sleep	(J)V
    //   155: ldc 1
    //   157: invokevirtual 280	java/lang/String:length	()I
    //   160: pop
    //   161: ldc 2
    //   163: invokevirtual 280	java/lang/String:length	()I
    //   166: ineg
    //   167: ifle +184 -> 351
    //   170: return
    //   171: ldc 1
    //   173: invokevirtual 280	java/lang/String:length	()I
    //   176: pop2
    //   177: ldc 1
    //   179: invokevirtual 280	java/lang/String:length	()I
    //   182: pop
    //   183: ldc 2
    //   185: invokevirtual 280	java/lang/String:length	()I
    //   188: ldc 2
    //   190: invokevirtual 280	java/lang/String:length	()I
    //   193: if_icmpeq +158 -> 351
    //   196: return
    //   197: getstatic 163	et:o	S
    //   200: getstatic 190	r:ab	[I
    //   203: bipush 21
    //   205: iaload
    //   206: invokestatic 314	r:d	(II)Z
    //   209: ifeq +92 -> 301
    //   212: getstatic 163	et:o	S
    //   215: getstatic 190	r:ab	[I
    //   218: bipush 22
    //   220: iaload
    //   221: invokestatic 314	r:d	(II)Z
    //   224: ifeq +77 -> 301
    //   227: getstatic 163	et:o	S
    //   230: getstatic 190	r:ab	[I
    //   233: bipush 23
    //   235: iaload
    //   236: invokestatic 314	r:d	(II)Z
    //   239: ifeq +62 -> 301
    //   242: getstatic 163	et:o	S
    //   245: getstatic 190	r:ab	[I
    //   248: bipush 24
    //   250: iaload
    //   251: invokestatic 314	r:d	(II)Z
    //   254: ifeq +47 -> 301
    //   257: getstatic 163	et:o	S
    //   260: getstatic 190	r:ab	[I
    //   263: bipush 25
    //   265: iaload
    //   266: invokestatic 314	r:d	(II)Z
    //   269: ifeq +32 -> 301
    //   272: getstatic 163	et:o	S
    //   275: getstatic 190	r:ab	[I
    //   278: bipush 26
    //   280: iaload
    //   281: invokestatic 314	r:d	(II)Z
    //   284: ifeq +17 -> 301
    //   287: aload_0
    //   288: getstatic 161	et:b	B
    //   291: putfield 196	r:f	I
    //   294: invokestatic 284	java/lang/System:currentTimeMillis	()J
    //   297: putstatic 213	r:x	J
    //   300: return
    //   301: getstatic 190	r:ab	[I
    //   304: bipush 14
    //   306: iaload
    //   307: invokestatic 253	dt:d	(I)I
    //   310: dup
    //   311: istore 4
    //   313: invokestatic 325	r:h	(I)Z
    //   316: ifeq +35 -> 351
    //   319: getstatic 190	r:ab	[I
    //   322: bipush 15
    //   324: iaload
    //   325: invokestatic 253	dt:d	(I)I
    //   328: dup
    //   329: istore 4
    //   331: invokestatic 325	r:h	(I)Z
    //   334: ifeq +17 -> 351
    //   337: aload_0
    //   338: getstatic 161	et:b	B
    //   341: putfield 196	r:f	I
    //   344: invokestatic 284	java/lang/System:currentTimeMillis	()J
    //   347: putstatic 213	r:x	J
    //   350: return
    //   351: invokestatic 284	java/lang/System:currentTimeMillis	()J
    //   354: getstatic 213	r:x	J
    //   357: lsub
    //   358: lconst_0
    //   359: invokestatic 318	r:e	(JJ)I
    //   362: invokestatic 325	r:h	(I)Z
    //   365: ifeq +4 -> 369
    //   368: return
    //   369: invokestatic 237	dl:ae	()Ldl;
    //   372: invokevirtual 232	dl:a	()V
    //   375: invokestatic 227	cn:k	()V
    //   378: getstatic 190	r:ab	[I
    //   381: bipush 8
    //   383: iaload
    //   384: istore_3
    //   385: iload_1
    //   386: invokestatic 325	r:h	(I)Z
    //   389: ifeq +35 -> 424
    //   392: aload_2
    //   393: getfield 175	fn:dk	[I
    //   396: arraylength
    //   397: getstatic 190	r:ab	[I
    //   400: iconst_3
    //   401: iaload
    //   402: isub
    //   403: istore_1
    //   404: ldc 1
    //   406: invokevirtual 280	java/lang/String:length	()I
    //   409: pop
    //   410: ldc 4
    //   412: invokevirtual 280	java/lang/String:length	()I
    //   415: ldc 3
    //   417: invokevirtual 280	java/lang/String:length	()I
    //   420: if_icmpge +22 -> 442
    //   423: return
    //   424: iload_1
    //   425: aload_2
    //   426: getfield 175	fn:dk	[I
    //   429: arraylength
    //   430: invokestatic 320	r:f	(II)Z
    //   433: ifeq +9 -> 442
    //   436: getstatic 190	r:ab	[I
    //   439: iconst_0
    //   440: iaload
    //   441: istore_1
    //   442: aload_0
    //   443: instanceof 15
    //   446: invokestatic 328	r:i	(I)Z
    //   449: ifeq +42 -> 491
    //   452: iload_1
    //   453: getstatic 190	r:ab	[I
    //   456: bipush 11
    //   458: iaload
    //   459: idiv
    //   460: getstatic 190	r:ab	[I
    //   463: iconst_3
    //   464: iaload
    //   465: iadd
    //   466: getstatic 190	r:ab	[I
    //   469: bipush 11
    //   471: iaload
    //   472: imul
    //   473: aload_2
    //   474: getfield 175	fn:dk	[I
    //   477: arraylength
    //   478: irem
    //   479: istore_3
    //   480: ldc 1
    //   482: invokevirtual 280	java/lang/String:length	()I
    //   485: pop
    //   486: aconst_null
    //   487: ifnull +151 -> 638
    //   490: return
    //   491: getstatic 106	dt:bb	Z
    //   494: invokestatic 319	r:f	(I)Z
    //   497: ifeq +37 -> 534
    //   500: iload_1
    //   501: getstatic 190	r:ab	[I
    //   504: iconst_3
    //   505: iaload
    //   506: iadd
    //   507: aload_2
    //   508: getfield 175	fn:dk	[I
    //   511: arraylength
    //   512: irem
    //   513: istore_3
    //   514: ldc 1
    //   516: invokevirtual 280	java/lang/String:length	()I
    //   519: pop
    //   520: ldc 2
    //   522: invokevirtual 280	java/lang/String:length	()I
    //   525: ldc 4
    //   527: invokevirtual 280	java/lang/String:length	()I
    //   530: if_icmplt +108 -> 638
    //   533: return
    //   534: getstatic 190	r:ab	[I
    //   537: bipush 8
    //   539: iaload
    //   540: istore 5
    //   542: iload_1
    //   543: getstatic 190	r:ab	[I
    //   546: iconst_3
    //   547: iaload
    //   548: iadd
    //   549: aload_2
    //   550: getfield 175	fn:dk	[I
    //   553: arraylength
    //   554: irem
    //   555: istore 6
    //   557: iload 6
    //   559: iload_1
    //   560: invokestatic 314	r:d	(II)Z
    //   563: ifeq +75 -> 638
    //   566: iload 5
    //   568: getstatic 190	r:ab	[I
    //   571: bipush 8
    //   573: iaload
    //   574: invokestatic 314	r:d	(II)Z
    //   577: ifeq +18 -> 595
    //   580: aload_2
    //   581: getfield 175	fn:dk	[I
    //   584: iload 6
    //   586: iaload
    //   587: iload 5
    //   589: invokestatic 324	r:g	(II)Z
    //   592: ifeq +15 -> 607
    //   595: iload 6
    //   597: istore_3
    //   598: aload_2
    //   599: getfield 175	fn:dk	[I
    //   602: iload 6
    //   604: iaload
    //   605: istore 5
    //   607: iload 6
    //   609: getstatic 190	r:ab	[I
    //   612: iconst_3
    //   613: iaload
    //   614: iadd
    //   615: aload_2
    //   616: getfield 175	fn:dk	[I
    //   619: arraylength
    //   620: irem
    //   621: istore 6
    //   623: ldc 1
    //   625: invokevirtual 280	java/lang/String:length	()I
    //   628: pop
    //   629: ldc 3
    //   631: invokevirtual 280	java/lang/String:length	()I
    //   634: ifne -77 -> 557
    //   637: return
    //   638: invokestatic 237	dl:ae	()Ldl;
    //   641: iload_3
    //   642: iload 4
    //   644: invokevirtual 239	dl:b	(II)V
    //   647: aload_0
    //   648: iload_3
    //   649: putfield 196	r:f	I
    //   652: invokestatic 264	et:d	()V
    //   655: aload_0
    //   656: invokespecial 334	r:p	()Z
    //   659: invokestatic 328	r:i	(I)Z
    //   662: ifeq +25 -> 687
    //   665: invokestatic 237	dl:ae	()Ldl;
    //   668: new 42	java/lang/StringBuffer
    //   671: dup
    //   672: ldc 7
    //   674: invokespecial 281	java/lang/StringBuffer:<init>	(Ljava/lang/String;)V
    //   677: iload_3
    //   678: invokevirtual 282	java/lang/StringBuffer:append	(I)Ljava/lang/StringBuffer;
    //   681: invokevirtual 283	java/lang/StringBuffer:toString	()Ljava/lang/String;
    //   684: invokevirtual 244	dl:n	(Ljava/lang/String;)V
    //   687: invokestatic 284	java/lang/System:currentTimeMillis	()J
    //   690: putstatic 213	r:x	J
    //   693: lconst_0
    //   694: invokestatic 285	java/lang/Thread:sleep	(J)V
    //   697: return
    //   698: ldc 1
    //   700: invokevirtual 280	java/lang/String:length	()I
    //   703: pop2
    //   704: return
    // Local variable table:
    //   start	length	slot	name	signature
    //   0	705	0	this	r
    //   0	705	1	paramInt	int
    //   40	576	2	localfn	fn
    //   50	89	3	localfc	fc
    //   384	294	3	i1	int
    //   57	586	4	i2	int
    //   540	66	5	i3	int
    //   555	67	6	i4	int
    //   171	1	8	localInterruptedException1	InterruptedException
    //   698	1	9	localInterruptedException2	InterruptedException
    // Exception table:
    //   from	to	target	type
    //   151	155	171	java/lang/InterruptedException
    //   693	697	698	java/lang/InterruptedException
  }
  
  public static void d(dt paramdt)
  {
    if (a(paramdt, dt.g())) {
      if (i(y.contains(paramdt)))
      {
        if ((d(paramdt.fm, ab[1])) && (d(paramdt.eh, dt.g().fy))) {
          "".length();
        }
      }
      else if ((!d(paramdt.fm, ab[1])) || (h(paramdt.eh, dt.g().fy)))
      {
        y.addElement(paramdt);
        if ((i(cn.b)) && (j(bc.a(dt.g().eg - paramdt.eg), ab[7])) && (j(bc.a(dt.g().ey - paramdt.ey), ab[7]))) {
          cn.ab();
        }
      }
    }
  }
  
  private static boolean i(int paramInt)
  {
    return paramInt != 0;
  }
  
  public void a()
  {
    this.d = ab[8];
    this.f = ab[8];
    this.h = ab[0];
    this.i = null;
    this.c = dt.g().ev;
    this.k = dt.g().dz;
    this.b = System.currentTimeMillis();
    this.a = ab[0];
    dn.m = ab[8];
    dn.af = ab[0];
    p = dt.g().aa;
    m = dt.g().bg;
    if ((a(fn.ez[ab[3]])) && (i(aq.l))) {
      "".length();
    }
    if ((a(fn.ez[ab[6]])) && (i(aq.l))) {
      "".length();
    }
    if ((a(fn.ez[ab[1]])) && (i(aq.l))) {
      "".length();
    }
    if ((a(fn.ez[ab[9]])) && (i(aq.l))) {
      "".length();
    }
    if (i(aq.l))
    {
      "".length();
      if (null == null) {
        break label274;
      }
    }
    label274:
    m = dt.g().bg;
    m();
  }
  
  private static int e(long paramLong1, long paramLong2)
  {
    return paramLong1 < paramLong2;
  }
  
  public void m()
  {
    j = ab[0];
    dn.ao = System.currentTimeMillis();
  }
  
  private void d()
  {
    if (i(dn.q))
    {
      a(this.f = dn.al[(dn.af = (dn.af + ab[3]) % dn.al.length)]);
      if (i(p())) {
        dl.ae().n("khu " + this.f);
      }
    }
    else
    {
      b(et.b);
    }
  }
  
  private static boolean h(int paramInt1, int paramInt2)
  {
    return paramInt1 == paramInt2;
  }
  
  private static int f(long paramLong1, long paramLong2)
  {
    return paramLong1 < paramLong2;
  }
  
  /* Error */
  protected final void c(int paramInt)
  {
    // Byte code:
    //   0: getstatic 94	dn:f	Z
    //   3: invokestatic 319	r:f	(I)Z
    //   6: ifeq +754 -> 760
    //   9: invokestatic 256	dt:g	()Ldt;
    //   12: astore_2
    //   13: invokestatic 327	r:i	()Z
    //   16: invokestatic 319	r:f	(I)Z
    //   19: ifeq +741 -> 760
    //   22: getstatic 189	r:aa	Lci;
    //   25: invokevirtual 222	ci:removeAllElements	()V
    //   28: aload_0
    //   29: getstatic 106	dt:bb	Z
    //   32: getstatic 135	dt:h	Z
    //   35: getstatic 116	dt:dj	Z
    //   38: invokevirtual 302	r:a	(ZZZ)I
    //   41: istore_3
    //   42: getstatic 190	r:ab	[I
    //   45: iconst_0
    //   46: iaload
    //   47: istore 4
    //   49: iload 4
    //   51: getstatic 173	fn:ch	Lci;
    //   54: invokevirtual 288	java/util/Vector:size	()I
    //   57: invokestatic 324	r:g	(II)Z
    //   60: ifeq +293 -> 353
    //   63: getstatic 173	fn:ch	Lci;
    //   66: iload 4
    //   68: invokevirtual 221	ci:elementAt	(I)Ljava/lang/Object;
    //   71: checkcast 29	es
    //   74: dup
    //   75: astore 5
    //   77: getfield 154	es:e	Z
    //   80: invokestatic 319	r:f	(I)Z
    //   83: ifeq +224 -> 307
    //   86: aload_2
    //   87: getfield 109	dt:bs	Lfl;
    //   90: getfield 170	fl:b	I
    //   93: getstatic 190	r:ab	[I
    //   96: iconst_3
    //   97: iaload
    //   98: invokestatic 326	r:h	(II)Z
    //   101: ifeq +23 -> 124
    //   104: aload 5
    //   106: getfield 159	es:k	Lat;
    //   109: getfield 76	at:f	S
    //   112: getstatic 190	r:ab	[I
    //   115: bipush 71
    //   117: iaload
    //   118: invokestatic 314	r:d	(II)Z
    //   121: ifeq +98 -> 219
    //   124: aload 5
    //   126: getfield 159	es:k	Lat;
    //   129: invokestatic 247	dn:a	(Lat;)Z
    //   132: invokestatic 319	r:f	(I)Z
    //   135: ifeq +18 -> 153
    //   138: aload 5
    //   140: getfield 159	es:k	Lat;
    //   143: getfield 76	at:f	S
    //   146: iload_1
    //   147: invokestatic 326	r:h	(II)Z
    //   150: ifeq +157 -> 307
    //   153: invokestatic 255	dt:f	()I
    //   156: getstatic 190	r:ab	[I
    //   159: bipush 6
    //   161: iaload
    //   162: invokestatic 330	r:j	(II)Z
    //   165: ifeq +54 -> 219
    //   168: aload 5
    //   170: getfield 159	es:k	Lat;
    //   173: getfield 74	at:b	B
    //   176: getstatic 190	r:ab	[I
    //   179: bipush 72
    //   181: iaload
    //   182: invokestatic 314	r:d	(II)Z
    //   185: ifeq +34 -> 219
    //   188: aload 5
    //   190: getfield 159	es:k	Lat;
    //   193: getfield 75	at:c	Z
    //   196: invokestatic 328	r:i	(I)Z
    //   199: ifeq +108 -> 307
    //   202: aload 5
    //   204: getfield 159	es:k	Lat;
    //   207: getfield 76	at:f	S
    //   210: invokestatic 260	dt:n	(I)Z
    //   213: invokestatic 328	r:i	(I)Z
    //   216: ifeq +91 -> 307
    //   219: aload_0
    //   220: iload_3
    //   221: aload 5
    //   223: getfield 155	es:f	I
    //   226: aload 5
    //   228: getfield 157	es:i	I
    //   231: invokespecial 291	r:a	(III)Z
    //   234: invokestatic 319	r:f	(I)Z
    //   237: ifeq +70 -> 307
    //   240: aload_0
    //   241: aload 5
    //   243: getfield 155	es:f	I
    //   246: aload 5
    //   248: getfield 157	es:i	I
    //   251: invokespecial 317	r:e	(II)Z
    //   254: invokestatic 319	r:f	(I)Z
    //   257: ifeq +50 -> 307
    //   260: getstatic 95	dn:j	I
    //   263: invokestatic 313	r:d	(I)Z
    //   266: ifeq +33 -> 299
    //   269: aload_2
    //   270: getfield 122	dt:eg	I
    //   273: aload_2
    //   274: getfield 126	dt:ey	I
    //   277: aload 5
    //   279: getfield 155	es:f	I
    //   282: aload 5
    //   284: getfield 157	es:i	I
    //   287: invokestatic 218	bc:a	(IIII)I
    //   290: getstatic 95	dn:j	I
    //   293: invokestatic 324	r:g	(II)Z
    //   296: ifeq +11 -> 307
    //   299: getstatic 189	r:aa	Lci;
    //   302: aload 5
    //   304: invokevirtual 220	ci:addElement	(Ljava/lang/Object;)V
    //   307: iinc 4 1
    //   310: ldc 1
    //   312: invokevirtual 280	java/lang/String:length	()I
    //   315: pop
    //   316: bipush 64
    //   318: bipush 9
    //   320: ixor
    //   321: sipush 219
    //   324: sipush 195
    //   327: ixor
    //   328: ixor
    //   329: sipush 180
    //   332: sipush 150
    //   335: ixor
    //   336: iconst_4
    //   337: bipush 119
    //   339: ixor
    //   340: ixor
    //   341: ldc 2
    //   343: invokevirtual 280	java/lang/String:length	()I
    //   346: ineg
    //   347: ixor
    //   348: iand
    //   349: ifeq -300 -> 49
    //   352: return
    //   353: getstatic 189	r:aa	Lci;
    //   356: invokevirtual 288	java/util/Vector:size	()I
    //   359: invokestatic 323	r:g	(I)Z
    //   362: ifeq +398 -> 760
    //   365: aload_2
    //   366: getfield 122	dt:eg	I
    //   369: istore 4
    //   371: aload_2
    //   372: getfield 126	dt:ey	I
    //   375: istore 5
    //   377: aload_2
    //   378: getfield 102	dt:ab	Le;
    //   381: astore_1
    //   382: getstatic 190	r:ab	[I
    //   385: iconst_0
    //   386: iaload
    //   387: istore_3
    //   388: iload_3
    //   389: getstatic 189	r:aa	Lci;
    //   392: invokevirtual 288	java/util/Vector:size	()I
    //   395: invokestatic 324	r:g	(II)Z
    //   398: ifeq +265 -> 663
    //   401: lconst_1
    //   402: invokestatic 285	java/lang/Thread:sleep	(J)V
    //   405: ldc 1
    //   407: invokevirtual 280	java/lang/String:length	()I
    //   410: pop
    //   411: ldc 2
    //   413: invokevirtual 280	java/lang/String:length	()I
    //   416: ineg
    //   417: bipush 42
    //   419: bipush 122
    //   421: ixor
    //   422: sipush 149
    //   425: sipush 197
    //   428: ixor
    //   429: iconst_m1
    //   430: ixor
    //   431: iand
    //   432: if_icmple +10 -> 442
    //   435: return
    //   436: ldc 1
    //   438: invokevirtual 280	java/lang/String:length	()I
    //   441: pop2
    //   442: getstatic 189	r:aa	Lci;
    //   445: iload_3
    //   446: invokevirtual 221	ci:elementAt	(I)Ljava/lang/Object;
    //   449: checkcast 29	es
    //   452: dup
    //   453: astore 6
    //   455: getfield 155	es:f	I
    //   458: aload 6
    //   460: getfield 155	es:f	I
    //   463: aload 6
    //   465: getfield 157	es:i	I
    //   468: invokestatic 263	et:a	(II)I
    //   471: invokestatic 252	dt:b	(II)Z
    //   474: ldc 1
    //   476: invokevirtual 280	java/lang/String:length	()I
    //   479: pop2
    //   480: aload_2
    //   481: aload 6
    //   483: putfield 110	dt:bt	Les;
    //   486: getstatic 190	r:ab	[I
    //   489: iconst_0
    //   490: iaload
    //   491: istore 7
    //   493: iload 7
    //   495: getstatic 190	r:ab	[I
    //   498: bipush 9
    //   500: iaload
    //   501: invokestatic 324	r:g	(II)Z
    //   504: ifeq +110 -> 614
    //   507: aload 6
    //   509: getfield 156	es:g	B
    //   512: getstatic 190	r:ab	[I
    //   515: bipush 6
    //   517: iaload
    //   518: invokestatic 314	r:d	(II)Z
    //   521: ifeq +93 -> 614
    //   524: aload 6
    //   526: getfield 154	es:e	Z
    //   529: invokestatic 319	r:f	(I)Z
    //   532: ifeq +82 -> 614
    //   535: invokestatic 237	dl:ae	()Ldl;
    //   538: aload 6
    //   540: getfield 152	es:a	I
    //   543: invokevirtual 241	dl:g	(I)V
    //   546: invokestatic 224	cn:aa	()Z
    //   549: invokestatic 319	r:f	(I)Z
    //   552: ifeq +62 -> 614
    //   555: aload_0
    //   556: aload_2
    //   557: getfield 122	dt:eg	I
    //   560: aload_2
    //   561: getfield 126	dt:ey	I
    //   564: invokespecial 317	r:e	(II)Z
    //   567: invokestatic 319	r:f	(I)Z
    //   570: ifeq +93 -> 663
    //   573: aload_2
    //   574: getfield 121	dt:ef	I
    //   577: invokestatic 323	r:g	(I)Z
    //   580: ifeq +83 -> 663
    //   583: iinc 7 1
    //   586: ldc 1
    //   588: invokevirtual 280	java/lang/String:length	()I
    //   591: pop
    //   592: bipush 96
    //   594: bipush 104
    //   596: ixor
    //   597: bipush 56
    //   599: bipush 48
    //   601: ixor
    //   602: iconst_m1
    //   603: ixor
    //   604: iand
    //   605: ldc 2
    //   607: invokevirtual 280	java/lang/String:length	()I
    //   610: if_icmple -117 -> 493
    //   613: return
    //   614: aload 6
    //   616: getstatic 190	r:ab	[I
    //   619: iconst_3
    //   620: iaload
    //   621: putfield 154	es:e	Z
    //   624: aload 6
    //   626: invokestatic 284	java/lang/System:currentTimeMillis	()J
    //   629: putfield 160	es:l	J
    //   632: iinc 3 1
    //   635: ldc 1
    //   637: invokevirtual 280	java/lang/String:length	()I
    //   640: pop
    //   641: ldc 2
    //   643: invokevirtual 280	java/lang/String:length	()I
    //   646: bipush 38
    //   648: bipush 78
    //   650: ixor
    //   651: sipush 217
    //   654: sipush 181
    //   657: ixor
    //   658: ixor
    //   659: if_icmpne -271 -> 388
    //   662: return
    //   663: ldc2_w 62
    //   666: invokestatic 285	java/lang/Thread:sleep	(J)V
    //   669: ldc 1
    //   671: invokevirtual 280	java/lang/String:length	()I
    //   674: pop
    //   675: sipush 172
    //   678: sipush 150
    //   681: ixor
    //   682: bipush 23
    //   684: bipush 121
    //   686: ixor
    //   687: ixor
    //   688: bipush 14
    //   690: bipush 46
    //   692: ixor
    //   693: sipush 238
    //   696: sipush 154
    //   699: ixor
    //   700: ixor
    //   701: ldc 2
    //   703: invokevirtual 280	java/lang/String:length	()I
    //   706: ineg
    //   707: ixor
    //   708: iand
    //   709: sipush 134
    //   712: bipush 46
    //   714: iadd
    //   715: bipush 30
    //   717: isub
    //   718: iconst_2
    //   719: iadd
    //   720: bipush 92
    //   722: bipush 116
    //   724: iadd
    //   725: bipush 74
    //   727: isub
    //   728: bipush 22
    //   730: iadd
    //   731: ixor
    //   732: if_icmplt +10 -> 742
    //   735: return
    //   736: ldc 1
    //   738: invokevirtual 280	java/lang/String:length	()I
    //   741: pop2
    //   742: iload 4
    //   744: iload 5
    //   746: invokestatic 252	dt:b	(II)Z
    //   749: ldc 1
    //   751: invokevirtual 280	java/lang/String:length	()I
    //   754: pop2
    //   755: aload_2
    //   756: aload_1
    //   757: putfield 102	dt:ab	Le;
    //   760: return
    // Local variable table:
    //   start	length	slot	name	signature
    //   0	761	0	this	r
    //   0	761	1	paramInt	int
    //   12	744	2	localdt	dt
    //   41	405	3	i1	int
    //   47	696	4	i2	int
    //   75	228	5	locales1	es
    //   375	370	5	i3	int
    //   453	172	6	locales2	es
    //   491	3	7	i4	int
    //   436	1	9	localInterruptedException1	InterruptedException
    //   736	1	10	localInterruptedException2	InterruptedException
    // Exception table:
    //   from	to	target	type
    //   401	405	436	java/lang/InterruptedException
    //   663	669	736	java/lang/InterruptedException
  }
  
  /* Error */
  protected static void a(boolean paramBoolean)
  {
    // Byte code:
    //   0: invokestatic 256	dt:g	()Ldt;
    //   3: astore_1
    //   4: iload_0
    //   5: invokestatic 328	r:i	(I)Z
    //   8: ifeq +195 -> 203
    //   11: getstatic 211	r:v	Z
    //   14: invokestatic 328	r:i	(I)Z
    //   17: ifeq +42 -> 59
    //   20: invokestatic 284	java/lang/System:currentTimeMillis	()J
    //   23: getstatic 191	r:ac	J
    //   26: lsub
    //   27: ldc2_w 58
    //   30: invokestatic 315	r:d	(JJ)I
    //   33: invokestatic 325	r:h	(I)Z
    //   36: ifeq +4 -> 40
    //   39: return
    //   40: getstatic 190	r:ab	[I
    //   43: iconst_0
    //   44: iaload
    //   45: putstatic 211	r:v	Z
    //   48: ldc 1
    //   50: invokevirtual 280	java/lang/String:length	()I
    //   53: pop
    //   54: aconst_null
    //   55: ifnull +148 -> 203
    //   58: return
    //   59: getstatic 134	dt:gj	Z
    //   62: invokestatic 328	r:i	(I)Z
    //   65: ifeq +138 -> 203
    //   68: getstatic 171	fn:ax	Lci;
    //   71: invokevirtual 288	java/util/Vector:size	()I
    //   74: invokestatic 323	r:g	(I)Z
    //   77: ifeq +126 -> 203
    //   80: getstatic 190	r:ab	[I
    //   83: iconst_0
    //   84: iaload
    //   85: istore_0
    //   86: iload_0
    //   87: getstatic 171	fn:ax	Lci;
    //   90: invokevirtual 288	java/util/Vector:size	()I
    //   93: invokestatic 324	r:g	(II)Z
    //   96: ifeq +107 -> 203
    //   99: getstatic 171	fn:ax	Lci;
    //   102: iload_0
    //   103: invokevirtual 221	ci:elementAt	(I)Ljava/lang/Object;
    //   106: checkcast 14	bk
    //   109: dup
    //   110: astore_2
    //   111: getfield 78	bk:g	I
    //   114: aload_1
    //   115: getfield 131	dt:fy	I
    //   118: invokestatic 314	r:d	(II)Z
    //   121: ifeq +68 -> 189
    //   124: aload_2
    //   125: getfield 77	bk:f	Ldt;
    //   128: invokestatic 300	r:a	(Ljava/lang/Object;)Z
    //   131: ifeq +58 -> 189
    //   134: aload_2
    //   135: getfield 77	bk:f	Ldt;
    //   138: getfield 121	dt:ef	I
    //   141: invokestatic 323	r:g	(I)Z
    //   144: ifeq +45 -> 189
    //   147: aload_2
    //   148: getfield 77	bk:f	Ldt;
    //   151: getfield 109	dt:bs	Lfl;
    //   154: getfield 170	fl:b	I
    //   157: getstatic 190	r:ab	[I
    //   160: bipush 18
    //   162: iaload
    //   163: invokestatic 326	r:h	(II)Z
    //   166: ifeq +23 -> 189
    //   169: ldc 5
    //   171: invokestatic 270	fn:a	(Ljava/lang/String;)V
    //   174: invokestatic 284	java/lang/System:currentTimeMillis	()J
    //   177: putstatic 191	r:ac	J
    //   180: getstatic 190	r:ab	[I
    //   183: iconst_3
    //   184: iaload
    //   185: putstatic 211	r:v	Z
    //   188: return
    //   189: iinc 0 1
    //   192: ldc 1
    //   194: invokevirtual 280	java/lang/String:length	()I
    //   197: pop
    //   198: aconst_null
    //   199: ifnull -113 -> 86
    //   202: return
    //   203: ldc2_w 54
    //   206: invokestatic 285	java/lang/Thread:sleep	(J)V
    //   209: ldc 1
    //   211: invokevirtual 280	java/lang/String:length	()I
    //   214: pop
    //   215: bipush 29
    //   217: bipush 127
    //   219: iadd
    //   220: bipush 36
    //   222: isub
    //   223: bipush 9
    //   225: iadd
    //   226: bipush 90
    //   228: bipush 78
    //   230: iadd
    //   231: sipush 141
    //   234: isub
    //   235: bipush 106
    //   237: iadd
    //   238: ixor
    //   239: ldc 2
    //   241: invokevirtual 280	java/lang/String:length	()I
    //   244: ineg
    //   245: if_icmpge +10 -> 255
    //   248: return
    //   249: ldc 1
    //   251: invokevirtual 280	java/lang/String:length	()I
    //   254: pop2
    //   255: getstatic 208	r:r	Lci;
    //   258: invokevirtual 222	ci:removeAllElements	()V
    //   261: getstatic 190	r:ab	[I
    //   264: iconst_0
    //   265: iaload
    //   266: putstatic 200	r:j	Z
    //   269: getstatic 190	r:ab	[I
    //   272: iconst_3
    //   273: iaload
    //   274: putstatic 82	cn:a	Z
    //   277: getstatic 87	dn:ai	Z
    //   280: invokestatic 328	r:i	(I)Z
    //   283: ifeq +43 -> 326
    //   286: invokestatic 256	dt:g	()Ldt;
    //   289: getfield 133	dt:ga	I
    //   292: invokestatic 323	r:g	(I)Z
    //   295: ifeq +31 -> 326
    //   298: invokestatic 237	dl:ae	()Ldl;
    //   301: invokevirtual 235	dl:ab	()V
    //   304: ldc 1
    //   306: invokevirtual 280	java/lang/String:length	()I
    //   309: pop
    //   310: ldc 2
    //   312: invokevirtual 280	java/lang/String:length	()I
    //   315: ineg
    //   316: ldc 2
    //   318: invokevirtual 280	java/lang/String:length	()I
    //   321: ineg
    //   322: if_icmpeq +13 -> 335
    //   325: return
    //   326: invokestatic 237	dl:ae	()Ldl;
    //   329: invokevirtual 240	dl:f	()V
    //   332: invokestatic 264	et:d	()V
    //   335: getstatic 190	r:ab	[I
    //   338: iconst_0
    //   339: iaload
    //   340: putstatic 82	cn:a	Z
    //   343: ldc2_w 54
    //   346: invokestatic 285	java/lang/Thread:sleep	(J)V
    //   349: return
    //   350: ldc 1
    //   352: invokevirtual 280	java/lang/String:length	()I
    //   355: pop2
    //   356: return
    // Local variable table:
    //   start	length	slot	name	signature
    //   0	357	0	paramBoolean	boolean
    //   3	112	1	localdt	dt
    //   110	38	2	localbk	bk
    //   249	1	3	localInterruptedException1	InterruptedException
    //   350	1	4	localInterruptedException2	InterruptedException
    // Exception table:
    //   from	to	target	type
    //   203	209	249	java/lang/InterruptedException
    //   343	349	350	java/lang/InterruptedException
  }
  
  private static boolean a(e parame, int paramInt)
  {
    if (((!h(parame.v, ab[27])) || (d(parame.j, ab[28]))) && ((!d(paramInt)) || (h(parame.v, paramInt)))) {
      return ab[3];
    }
    return ab[0];
  }
  
  private boolean p()
  {
    if ((i(this.a)) && (g(fn.ax.size())) && (h(((bk)fn.ax.firstElement()).g, dt.g().fy))) {
      return ab[3];
    }
    return ab[0];
  }
  
  private static boolean i(int paramInt1, int paramInt2)
  {
    return paramInt1 > paramInt2;
  }
  
  /* Error */
  protected final void c(e parame)
  {
    // Byte code:
    //   0: aload_1
    //   1: invokestatic 300	r:a	(Ljava/lang/Object;)Z
    //   4: ifeq +779 -> 783
    //   7: aload_1
    //   8: getfield 143	e:n	I
    //   11: istore_2
    //   12: aload_1
    //   13: getfield 137	e:d	I
    //   16: istore_3
    //   17: invokestatic 256	dt:g	()Ldt;
    //   20: astore 4
    //   22: getstatic 163	et:o	S
    //   25: getstatic 190	r:ab	[I
    //   28: bipush 15
    //   30: iaload
    //   31: invokestatic 326	r:h	(II)Z
    //   34: ifeq +312 -> 346
    //   37: aload_1
    //   38: getfield 143	e:n	I
    //   41: getstatic 190	r:ab	[I
    //   44: bipush 29
    //   46: iaload
    //   47: invokestatic 326	r:h	(II)Z
    //   50: ifeq +109 -> 159
    //   53: aload_1
    //   54: getfield 137	e:d	I
    //   57: getstatic 190	r:ab	[I
    //   60: bipush 30
    //   62: iaload
    //   63: invokestatic 326	r:h	(II)Z
    //   66: ifeq +93 -> 159
    //   69: getstatic 190	r:ab	[I
    //   72: bipush 31
    //   74: iaload
    //   75: istore_2
    //   76: getstatic 190	r:ab	[I
    //   79: bipush 32
    //   81: iaload
    //   82: istore_3
    //   83: ldc 1
    //   85: invokevirtual 280	java/lang/String:length	()I
    //   88: pop
    //   89: sipush 143
    //   92: sipush 158
    //   95: iadd
    //   96: sipush 280
    //   99: isub
    //   100: sipush 224
    //   103: iadd
    //   104: bipush 54
    //   106: bipush 37
    //   108: iadd
    //   109: bipush -86
    //   111: isub
    //   112: bipush 21
    //   114: iadd
    //   115: ixor
    //   116: bipush 88
    //   118: sipush 132
    //   121: iadd
    //   122: bipush 41
    //   124: isub
    //   125: bipush 63
    //   127: iadd
    //   128: sipush 191
    //   131: bipush 126
    //   133: iadd
    //   134: sipush 225
    //   137: isub
    //   138: bipush 101
    //   140: iadd
    //   141: ixor
    //   142: ldc 2
    //   144: invokevirtual 280	java/lang/String:length	()I
    //   147: ineg
    //   148: ixor
    //   149: iand
    //   150: ldc 2
    //   152: invokevirtual 280	java/lang/String:length	()I
    //   155: if_icmple +557 -> 712
    //   158: return
    //   159: aload_1
    //   160: getfield 143	e:n	I
    //   163: getstatic 190	r:ab	[I
    //   166: bipush 33
    //   168: iaload
    //   169: invokestatic 326	r:h	(II)Z
    //   172: ifeq +103 -> 275
    //   175: aload_1
    //   176: getfield 137	e:d	I
    //   179: getstatic 190	r:ab	[I
    //   182: bipush 30
    //   184: iaload
    //   185: invokestatic 326	r:h	(II)Z
    //   188: ifeq +87 -> 275
    //   191: getstatic 190	r:ab	[I
    //   194: bipush 34
    //   196: iaload
    //   197: istore_2
    //   198: getstatic 190	r:ab	[I
    //   201: bipush 32
    //   203: iaload
    //   204: istore_3
    //   205: ldc 1
    //   207: invokevirtual 280	java/lang/String:length	()I
    //   210: pop
    //   211: sipush 186
    //   214: sipush 139
    //   217: iadd
    //   218: sipush 234
    //   221: isub
    //   222: bipush 110
    //   224: iadd
    //   225: bipush 17
    //   227: bipush 82
    //   229: iadd
    //   230: bipush 17
    //   232: isub
    //   233: bipush 70
    //   235: iadd
    //   236: ixor
    //   237: sipush 177
    //   240: bipush 68
    //   242: iadd
    //   243: sipush 176
    //   246: isub
    //   247: sipush 157
    //   250: iadd
    //   251: bipush 45
    //   253: bipush 50
    //   255: iadd
    //   256: bipush -2
    //   258: isub
    //   259: bipush 82
    //   261: iadd
    //   262: ixor
    //   263: ldc 2
    //   265: invokevirtual 280	java/lang/String:length	()I
    //   268: ineg
    //   269: ixor
    //   270: iand
    //   271: ifge +441 -> 712
    //   274: return
    //   275: aload_1
    //   276: getfield 143	e:n	I
    //   279: getstatic 190	r:ab	[I
    //   282: bipush 35
    //   284: iaload
    //   285: invokestatic 326	r:h	(II)Z
    //   288: ifeq +424 -> 712
    //   291: aload_1
    //   292: getfield 137	e:d	I
    //   295: getstatic 190	r:ab	[I
    //   298: bipush 36
    //   300: iaload
    //   301: invokestatic 326	r:h	(II)Z
    //   304: ifeq +408 -> 712
    //   307: getstatic 190	r:ab	[I
    //   310: bipush 37
    //   312: iaload
    //   313: istore_2
    //   314: getstatic 190	r:ab	[I
    //   317: bipush 38
    //   319: iaload
    //   320: istore_3
    //   321: ldc 1
    //   323: invokevirtual 280	java/lang/String:length	()I
    //   326: pop
    //   327: bipush 36
    //   329: bipush 99
    //   331: ixor
    //   332: sipush 241
    //   335: sipush 182
    //   338: ixor
    //   339: iconst_m1
    //   340: ixor
    //   341: iand
    //   342: ifle +370 -> 712
    //   345: return
    //   346: getstatic 163	et:o	S
    //   349: getstatic 190	r:ab	[I
    //   352: bipush 14
    //   354: iaload
    //   355: invokestatic 326	r:h	(II)Z
    //   358: ifeq +354 -> 712
    //   361: aload_1
    //   362: getfield 143	e:n	I
    //   365: getstatic 190	r:ab	[I
    //   368: bipush 39
    //   370: iaload
    //   371: invokestatic 314	r:d	(II)Z
    //   374: ifeq +19 -> 393
    //   377: aload_1
    //   378: getfield 143	e:n	I
    //   381: getstatic 190	r:ab	[I
    //   384: bipush 40
    //   386: iaload
    //   387: invokestatic 326	r:h	(II)Z
    //   390: ifeq +85 -> 475
    //   393: aload_1
    //   394: getfield 137	e:d	I
    //   397: getstatic 190	r:ab	[I
    //   400: bipush 41
    //   402: iaload
    //   403: invokestatic 326	r:h	(II)Z
    //   406: ifeq +69 -> 475
    //   409: getstatic 190	r:ab	[I
    //   412: bipush 40
    //   414: iaload
    //   415: istore_2
    //   416: getstatic 190	r:ab	[I
    //   419: bipush 42
    //   421: iaload
    //   422: istore_3
    //   423: ldc 1
    //   425: invokevirtual 280	java/lang/String:length	()I
    //   428: pop
    //   429: bipush 35
    //   431: bipush 21
    //   433: ixor
    //   434: bipush 39
    //   436: bipush 6
    //   438: ixor
    //   439: ixor
    //   440: bipush 48
    //   442: bipush 20
    //   444: iadd
    //   445: bipush -74
    //   447: isub
    //   448: bipush 7
    //   450: iadd
    //   451: bipush 100
    //   453: bipush 33
    //   455: iadd
    //   456: bipush 26
    //   458: isub
    //   459: bipush 23
    //   461: iadd
    //   462: ixor
    //   463: ldc 2
    //   465: invokevirtual 280	java/lang/String:length	()I
    //   468: ineg
    //   469: ixor
    //   470: iand
    //   471: ifeq +241 -> 712
    //   474: return
    //   475: aload_1
    //   476: getfield 143	e:n	I
    //   479: getstatic 190	r:ab	[I
    //   482: bipush 43
    //   484: iaload
    //   485: invokestatic 314	r:d	(II)Z
    //   488: ifeq +19 -> 507
    //   491: aload_1
    //   492: getfield 143	e:n	I
    //   495: getstatic 190	r:ab	[I
    //   498: bipush 44
    //   500: iaload
    //   501: invokestatic 326	r:h	(II)Z
    //   504: ifeq +48 -> 552
    //   507: aload_1
    //   508: getfield 137	e:d	I
    //   511: getstatic 190	r:ab	[I
    //   514: bipush 45
    //   516: iaload
    //   517: invokestatic 326	r:h	(II)Z
    //   520: ifeq +32 -> 552
    //   523: getstatic 190	r:ab	[I
    //   526: bipush 44
    //   528: iaload
    //   529: istore_2
    //   530: getstatic 190	r:ab	[I
    //   533: bipush 46
    //   535: iaload
    //   536: istore_3
    //   537: ldc 1
    //   539: invokevirtual 280	java/lang/String:length	()I
    //   542: pop
    //   543: bipush 119
    //   545: bipush 114
    //   547: ixor
    //   548: ifgt +164 -> 712
    //   551: return
    //   552: aload_1
    //   553: getfield 143	e:n	I
    //   556: getstatic 190	r:ab	[I
    //   559: bipush 47
    //   561: iaload
    //   562: invokestatic 314	r:d	(II)Z
    //   565: ifeq +19 -> 584
    //   568: aload_1
    //   569: getfield 143	e:n	I
    //   572: getstatic 190	r:ab	[I
    //   575: bipush 39
    //   577: iaload
    //   578: invokestatic 326	r:h	(II)Z
    //   581: ifeq +53 -> 634
    //   584: aload_1
    //   585: getfield 137	e:d	I
    //   588: getstatic 190	r:ab	[I
    //   591: bipush 48
    //   593: iaload
    //   594: invokestatic 326	r:h	(II)Z
    //   597: ifeq +37 -> 634
    //   600: getstatic 190	r:ab	[I
    //   603: bipush 47
    //   605: iaload
    //   606: istore_2
    //   607: getstatic 190	r:ab	[I
    //   610: bipush 36
    //   612: iaload
    //   613: istore_3
    //   614: ldc 1
    //   616: invokevirtual 280	java/lang/String:length	()I
    //   619: pop
    //   620: ldc 3
    //   622: invokevirtual 280	java/lang/String:length	()I
    //   625: ldc 3
    //   627: invokevirtual 280	java/lang/String:length	()I
    //   630: if_icmpge +82 -> 712
    //   633: return
    //   634: aload_1
    //   635: getfield 143	e:n	I
    //   638: getstatic 190	r:ab	[I
    //   641: bipush 49
    //   643: iaload
    //   644: invokestatic 326	r:h	(II)Z
    //   647: ifeq +19 -> 666
    //   650: aload_1
    //   651: getfield 137	e:d	I
    //   654: getstatic 190	r:ab	[I
    //   657: bipush 50
    //   659: iaload
    //   660: invokestatic 314	r:d	(II)Z
    //   663: ifeq +35 -> 698
    //   666: aload_1
    //   667: getfield 143	e:n	I
    //   670: getstatic 190	r:ab	[I
    //   673: bipush 51
    //   675: iaload
    //   676: invokestatic 326	r:h	(II)Z
    //   679: ifeq +33 -> 712
    //   682: aload_1
    //   683: getfield 137	e:d	I
    //   686: getstatic 190	r:ab	[I
    //   689: bipush 52
    //   691: iaload
    //   692: invokestatic 326	r:h	(II)Z
    //   695: ifeq +17 -> 712
    //   698: getstatic 190	r:ab	[I
    //   701: bipush 51
    //   703: iaload
    //   704: istore_2
    //   705: getstatic 190	r:ab	[I
    //   708: bipush 50
    //   710: iaload
    //   711: istore_3
    //   712: iload_2
    //   713: iload_3
    //   714: invokestatic 254	dt:e	(II)Z
    //   717: invokestatic 328	r:i	(I)Z
    //   720: ifeq +57 -> 777
    //   723: aload_0
    //   724: aload_0
    //   725: getfield 209	r:t	I
    //   728: putfield 212	r:w	I
    //   731: aload_0
    //   732: aload_0
    //   733: getfield 205	r:o	I
    //   736: putfield 215	r:z	I
    //   739: aload_0
    //   740: aload 4
    //   742: getfield 122	dt:eg	I
    //   745: putfield 209	r:t	I
    //   748: aload_0
    //   749: aload 4
    //   751: getfield 126	dt:ey	I
    //   754: putfield 205	r:o	I
    //   757: aload 4
    //   759: aload_1
    //   760: putfield 102	dt:ab	Le;
    //   763: ldc2_w 50
    //   766: invokestatic 285	java/lang/Thread:sleep	(J)V
    //   769: return
    //   770: ldc 1
    //   772: invokevirtual 280	java/lang/String:length	()I
    //   775: pop2
    //   776: return
    //   777: aload 4
    //   779: aconst_null
    //   780: putfield 102	dt:ab	Le;
    //   783: return
    // Local variable table:
    //   start	length	slot	name	signature
    //   0	784	0	this	r
    //   0	784	1	parame	e
    //   11	702	2	i1	int
    //   16	698	3	i2	int
    //   20	758	4	localdt	dt
    //   770	1	5	localInterruptedException	InterruptedException
    // Exception table:
    //   from	to	target	type
    //   763	769	770	java/lang/InterruptedException
  }
  
  private static boolean j(int paramInt1, int paramInt2)
  {
    return paramInt1 <= paramInt2;
  }
  
  public final int a(boolean paramBoolean1, boolean paramBoolean2, boolean paramBoolean3)
  {
    if (i(this.h)) {
      return ab[8];
    }
    int i1 = ab[0];
    if (i(paramBoolean1)) {
      i1 = ab[3];
    }
    if (i(paramBoolean2)) {
      i1 |= ab[6];
    }
    if (i(paramBoolean3)) {
      i1 |= ab[9];
    }
    return i1;
  }
  
  private static boolean b(Object paramObject)
  {
    return paramObject == null;
  }
  
  private boolean a(int paramInt1, int paramInt2, int paramInt3)
  {
    if (f(paramInt1, ab[9])) {
      return ab[0];
    }
    int i1 = ab[0];
    while (g(i1, r.size()))
    {
      e locale;
      if ((i((locale = (e)r.elementAt(i1)).t)) && (g(locale.x)) && (i(locale.j)))
      {
        if (h(locale.t, ab[1]))
        {
          if ((!f(this instanceof bm)) || (i(this instanceof o)))
          {
            i2 = ab[0];
            "".length();
            if (((0x6A ^ 0x77 ^ 0xD ^ 0x1F) & (56 + '' - 81 + 28 ^ 100 + '' - 175 + 82 ^ -" ".length())) < "   ".length()) {
              break label396;
            }
            return (10 + 88 - -19 + 19 ^ 23 + 109 - 67 + 132) & (37 + 37 - 65 + 236 ^ 31 + 93 - 110 + 170 ^ -" ".length());
          }
        }
        else if (((!i(locale.s)) || (h(paramInt1 & ab[18], ab[18]))) && ((!h(locale.t, ab[3])) || (i(paramInt1 & ab[6]))) && ((!h(locale.t, ab[6])) || (i(paramInt1 & ab[9]))))
        {
          i2 = ab[0];
          "".length();
          if (((0x6D ^ 0x74) & (0x28 ^ 0x31 ^ 0xFFFFFFFF)) <= (0xAA ^ 0xAE)) {
            break label396;
          }
          return (0xD9 ^ 0x9C) & (0x19 ^ 0x5C ^ 0xFFFFFFFF);
        }
        int i2 = ab[3];
        label396:
        if ((i(i2)) && (j(bc.a(paramInt2 - locale.n), ab[53])) && (j(bc.a(paramInt3 - locale.d), ab[4]))) {
          return ab[3];
        }
        "".length();
        if (" ".length() != " ".length()) {
          return (0xAE ^ 0xC3 ^ 0x1D ^ 0x6E) & (76 + 95 - 68 + 28 ^ 46 + '' - 121 + 83 ^ -" ".length());
        }
      }
      else
      {
        "".length();
      }
      i1++;
      "".length();
      if (-(0x4F ^ 0x4B) > 0) {
        return (0x2E ^ 0x3E) & (0x95 ^ 0x85 ^ 0xFFFFFFFF);
      }
    }
    return ab[0];
  }
  
  public static void a(ad paramad)
  {
    if ((!e(e.size())) || (g(l.size())))
    {
      fe[] arrayOffe = new fe[e.size() + l.size()];
      int i1 = ab[0];
      while (g(i1, e.size()))
      {
        arrayOffe[i1] = new fe();
        arrayOffe[i1].b = fn.fg[(paramad.a - ab[3])];
        arrayOffe[i1].a = ((e)e.elementAt(i1));
        i1++;
        "".length();
        if (-" ".length() > 0) {
          return;
        }
      }
      i1 = ab[0];
      while (g(i1, l.size()))
      {
        arrayOffe[(i1 + e.size())] = new fe();
        arrayOffe[(i1 + e.size())].b = fn.fg[(paramad.a - ab[3])];
        arrayOffe[(i1 + e.size())].c = ((dt)l.elementAt(i1));
        i1++;
        "".length();
        if ((76 + 80 - 115 + 124 ^ 118 + 79 - 132 + 96) != (0xC0 ^ 0xB9 ^ 0x51 ^ 0x2C)) {
          return;
        }
      }
      if (i(arrayOffe.length, ab[3]))
      {
        paramad = new d();
        if (a(arrayOffe[ab[0]].a))
        {
          paramad = new d(arrayOffe[ab[0]].a.u, arrayOffe[ab[0]].a.l);
          "".length();
          if ((0x14 ^ 0x11) != 0) {}
        }
        else if (a(arrayOffe[ab[0]].c))
        {
          paramad = new d(arrayOffe[ab[0]].c.eg, arrayOffe[ab[0]].c.ey);
        }
        ci localci = new ci();
        int i2 = ab[3];
        while (g(i2, arrayOffe.length))
        {
          if (a(arrayOffe[i2].a))
          {
            localci.addElement(new d(arrayOffe[i2].a.u, arrayOffe[i2].a.l));
            "".length();
            if ("   ".length() != 0) {}
          }
          else if (a(arrayOffe[i2].c))
          {
            localci.addElement(new d(arrayOffe[i2].c.eg, arrayOffe[i2].c.ey));
          }
          if (j(i2, ab[11]))
          {
            i2++;
            "".length();
            if ("  ".length() != "  ".length()) {
              return;
            }
          }
        }
        al.a(localci, paramad, dt.g().h());
      }
      dt.g().fa = arrayOffe;
    }
  }
  
  protected final dt a(dt paramdt, int paramInt)
  {
    int i1 = ab[0];
    while (g(i1, fn.ep.size()))
    {
      dt localdt;
      if ((a(localdt = (dt)fn.ep.elementAt(i1))) && (f(c(localdt))) && (f(a(paramInt, localdt.eg, localdt.ey))) && (f(e(localdt.eg, localdt.ey))) && (f(dn.f(localdt.ci))) && (i(dv.a(localdt.ci))) && ((!d(localdt.fm, ab[3])) || (!d(localdt.eh, paramdt.fy)) || (g(paramdt.g, ab[19])))) {
        return localdt;
      }
      i1++;
      "".length();
      if ("  ".length() <= 0) {
        return null;
      }
    }
    return null;
  }
  
  /* Error */
  public static void n()
  {
    // Byte code:
    //   0: invokestatic 256	dt:g	()Ldt;
    //   3: astore_0
    //   4: getstatic 190	r:ab	[I
    //   7: bipush 14
    //   9: iaload
    //   10: invokestatic 260	dt:n	(I)Z
    //   13: invokestatic 319	r:f	(I)Z
    //   16: ifeq +175 -> 191
    //   19: getstatic 190	r:ab	[I
    //   22: bipush 15
    //   24: iaload
    //   25: invokestatic 260	dt:n	(I)Z
    //   28: invokestatic 319	r:f	(I)Z
    //   31: ifeq +160 -> 191
    //   34: getstatic 190	r:ab	[I
    //   37: bipush 16
    //   39: iaload
    //   40: invokestatic 272	fn:g	(I)Lfc;
    //   43: dup
    //   44: astore_1
    //   45: invokestatic 300	r:a	(Ljava/lang/Object;)Z
    //   48: ifeq +117 -> 165
    //   51: aload_1
    //   52: getfield 122	dt:eg	I
    //   55: aload_0
    //   56: getfield 122	dt:eg	I
    //   59: isub
    //   60: invokestatic 276	java/lang/Math:abs	(I)I
    //   63: getstatic 190	r:ab	[I
    //   66: bipush 17
    //   68: iaload
    //   69: invokestatic 330	r:j	(II)Z
    //   72: ifeq +93 -> 165
    //   75: aload_1
    //   76: getfield 126	dt:ey	I
    //   79: aload_0
    //   80: getfield 126	dt:ey	I
    //   83: isub
    //   84: invokestatic 276	java/lang/Math:abs	(I)I
    //   87: getstatic 190	r:ab	[I
    //   90: bipush 17
    //   92: iaload
    //   93: invokestatic 330	r:j	(II)Z
    //   96: ifeq +69 -> 165
    //   99: aload_1
    //   100: getfield 122	dt:eg	I
    //   103: getstatic 190	r:ab	[I
    //   106: bipush 17
    //   108: iaload
    //   109: invokestatic 329	r:i	(II)Z
    //   112: ifeq +29 -> 141
    //   115: aload_1
    //   116: getfield 122	dt:eg	I
    //   119: getstatic 190	r:ab	[I
    //   122: bipush 17
    //   124: iaload
    //   125: isub
    //   126: ldc 1
    //   128: invokevirtual 280	java/lang/String:length	()I
    //   131: pop
    //   132: ldc 4
    //   134: invokevirtual 280	java/lang/String:length	()I
    //   137: ifgt +15 -> 152
    //   140: return
    //   141: aload_1
    //   142: getfield 122	dt:eg	I
    //   145: getstatic 190	r:ab	[I
    //   148: bipush 17
    //   150: iaload
    //   151: iadd
    //   152: aload_1
    //   153: getfield 126	dt:ey	I
    //   156: invokestatic 252	dt:b	(II)Z
    //   159: ldc 1
    //   161: invokevirtual 280	java/lang/String:length	()I
    //   164: pop2
    //   165: invokestatic 237	dl:ae	()Ldl;
    //   168: invokevirtual 232	dl:a	()V
    //   171: ldc 1
    //   173: invokevirtual 280	java/lang/String:length	()I
    //   176: pop
    //   177: ldc 4
    //   179: invokevirtual 280	java/lang/String:length	()I
    //   182: ldc 3
    //   184: invokevirtual 280	java/lang/String:length	()I
    //   187: if_icmpgt +20 -> 207
    //   190: return
    //   191: aload_0
    //   192: getfield 122	dt:eg	I
    //   195: getstatic 162	et:h	I
    //   198: invokestatic 252	dt:b	(II)Z
    //   201: ldc 1
    //   203: invokevirtual 280	java/lang/String:length	()I
    //   206: pop2
    //   207: invokestatic 284	java/lang/System:currentTimeMillis	()J
    //   210: lstore_1
    //   211: aload_0
    //   212: getfield 121	dt:ef	I
    //   215: invokestatic 323	r:g	(I)Z
    //   218: ifeq +60 -> 278
    //   221: invokestatic 284	java/lang/System:currentTimeMillis	()J
    //   224: lload_1
    //   225: lsub
    //   226: lconst_0
    //   227: invokestatic 304	r:b	(JJ)I
    //   230: invokestatic 325	r:h	(I)Z
    //   233: ifeq +45 -> 278
    //   236: lconst_0
    //   237: invokestatic 285	java/lang/Thread:sleep	(J)V
    //   240: ldc 1
    //   242: invokevirtual 280	java/lang/String:length	()I
    //   245: pop
    //   246: ldc 2
    //   248: invokevirtual 280	java/lang/String:length	()I
    //   251: ineg
    //   252: ldc 2
    //   254: invokevirtual 280	java/lang/String:length	()I
    //   257: if_icmplt -46 -> 211
    //   260: return
    //   261: ldc 1
    //   263: invokevirtual 280	java/lang/String:length	()I
    //   266: pop2
    //   267: ldc 1
    //   269: invokevirtual 280	java/lang/String:length	()I
    //   272: pop
    //   273: aconst_null
    //   274: ifnull -63 -> 211
    //   277: return
    //   278: return
    // Local variable table:
    //   start	length	slot	name	signature
    //   3	209	0	localdt	dt
    //   44	109	1	localfc	fc
    //   210	15	1	l1	long
    //   261	1	3	localInterruptedException	InterruptedException
    // Exception table:
    //   from	to	target	type
    //   236	240	261	java/lang/InterruptedException
  }
  
  public String toString()
  {
    return "";
  }
  
  public static void o() {}
}


/* Location:              C:\Users\Admin\OneDrive\Documents\NSOv2_test.jar!\r.class
 * Java compiler version: 1 (45.3)
 * JD-Core Version:       0.7.1
 */