import java.io.PrintStream;

public final class s
  extends r
{
  private static String v;
  private static at w;
  private static at x;
  private static int y;
  private static int z;
  private static int aa;
  private static int ab;
  private static boolean ac;
  private static ao ad;
  private static boolean ae;
  private static boolean af;
  private static int ag;
  private static ao ah;
  private static String ai;
  private static int aj;
  private static int[] ak;
  private static int al;
  private static int am;
  private static boolean an;
  private long ao;
  
  private static boolean c(int paramInt1, int paramInt2)
  {
    return paramInt1 > paramInt2;
  }
  
  public static void c()
  {
    s();
    ab = ak[1];
    ag = ak[1];
    al = ak[0];
    aa = ak[5];
    am = ak[5];
    z = ak[5];
    aj = ak[5];
    af = ak[1];
    an = ak[1];
    ae = ak[1];
    ac = ak[1];
    v = "Hoàn thành nhiệm vụ. Hãy gặp Ameji để trả nhiệm vụ";
    ai = "Con đã hoàn thành đủ số nhiệm vụ cho ngày hôm nay rồi";
  }
  
  static
  {
    cs.a(134);
    c();
  }
  
  /* Error */
  private boolean p()
  {
    // Byte code:
    //   0: getstatic 229	s:ah	Lao;
    //   3: invokestatic 326	s:b	(Ljava/lang/Object;)Z
    //   6: ifeq +1589 -> 1595
    //   9: getstatic 238	s:w	Lat;
    //   12: getfield 146	at:f	S
    //   15: invokestatic 284	dt:g	(I)Lao;
    //   18: dup
    //   19: putstatic 229	s:ah	Lao;
    //   22: invokestatic 326	s:b	(Ljava/lang/Object;)Z
    //   25: ifeq +1523 -> 1548
    //   28: getstatic 238	s:w	Lat;
    //   31: getfield 146	at:f	S
    //   34: invokestatic 277	dt:a	(I)Lao;
    //   37: dup
    //   38: putstatic 229	s:ah	Lao;
    //   41: invokestatic 326	s:b	(Ljava/lang/Object;)Z
    //   44: ifeq +1400 -> 1444
    //   47: aload_0
    //   48: astore_1
    //   49: getstatic 238	s:w	Lat;
    //   52: getfield 147	at:i	B
    //   55: getstatic 232	s:ak	[I
    //   58: bipush 25
    //   60: iaload
    //   61: invokestatic 330	s:d	(II)Z
    //   64: ifeq +10 -> 74
    //   67: getstatic 232	s:ak	[I
    //   70: bipush 6
    //   72: iaload
    //   73: ireturn
    //   74: getstatic 185	et:o	S
    //   77: invokestatic 286	et:i	(I)Z
    //   80: invokestatic 341	s:j	(I)Z
    //   83: ifeq +53 -> 136
    //   86: aload_1
    //   87: getstatic 159	cz:l	I
    //   90: getstatic 232	s:ak	[I
    //   93: iconst_0
    //   94: iaload
    //   95: getstatic 232	s:ak	[I
    //   98: iconst_5
    //   99: iaload
    //   100: getstatic 232	s:ak	[I
    //   103: iconst_5
    //   104: iaload
    //   105: invokevirtual 315	r:a	(IIII)V
    //   108: ldc 1
    //   110: invokevirtual 300	java/lang/String:length	()I
    //   113: pop
    //   114: aconst_null
    //   115: ifnull +1323 -> 1438
    //   118: sipush 202
    //   121: sipush 143
    //   124: ixor
    //   125: sipush 205
    //   128: sipush 136
    //   131: ixor
    //   132: iconst_m1
    //   133: ixor
    //   134: iand
    //   135: ireturn
    //   136: getstatic 217	java/lang/System:out	Ljava/io/PrintStream;
    //   139: new 124	java/lang/StringBuffer
    //   142: dup
    //   143: ldc 43
    //   145: invokespecial 306	java/lang/StringBuffer:<init>	(Ljava/lang/String;)V
    //   148: getstatic 238	s:w	Lat;
    //   151: getfield 144	at:a	Ljava/lang/String;
    //   154: invokevirtual 308	java/lang/StringBuffer:append	(Ljava/lang/String;)Ljava/lang/StringBuffer;
    //   157: invokevirtual 309	java/lang/StringBuffer:toString	()Ljava/lang/String;
    //   160: invokevirtual 293	java/io/PrintStream:println	(Ljava/lang/String;)V
    //   163: getstatic 238	s:w	Lat;
    //   166: getfield 145	at:b	B
    //   169: invokestatic 283	dt:g	()Ldt;
    //   172: getfield 175	dt:el	I
    //   175: invokestatic 338	s:h	(II)[Lao;
    //   178: astore_1
    //   179: getstatic 238	s:w	Lat;
    //   182: getfield 145	at:b	B
    //   185: getstatic 232	s:ak	[I
    //   188: bipush 6
    //   190: iaload
    //   191: invokestatic 340	s:i	(II)Z
    //   194: ifeq +99 -> 293
    //   197: getstatic 232	s:ak	[I
    //   200: iconst_1
    //   201: iaload
    //   202: getstatic 232	s:ak	[I
    //   205: iconst_1
    //   206: iaload
    //   207: getstatic 232	s:ak	[I
    //   210: iconst_1
    //   211: iaload
    //   212: invokestatic 290	fn:b	(III)V
    //   215: ldc 1
    //   217: invokevirtual 300	java/lang/String:length	()I
    //   220: pop
    //   221: ldc 5
    //   223: invokevirtual 300	java/lang/String:length	()I
    //   226: ineg
    //   227: ifle +852 -> 1079
    //   230: sipush 224
    //   233: bipush 43
    //   235: iadd
    //   236: sipush 264
    //   239: isub
    //   240: sipush 233
    //   243: iadd
    //   244: bipush 48
    //   246: sipush 171
    //   249: iadd
    //   250: sipush 161
    //   253: isub
    //   254: bipush 120
    //   256: iadd
    //   257: ixor
    //   258: bipush 62
    //   260: sipush 223
    //   263: iadd
    //   264: bipush 110
    //   266: isub
    //   267: bipush 58
    //   269: iadd
    //   270: bipush 91
    //   272: sipush 169
    //   275: iadd
    //   276: sipush 190
    //   279: isub
    //   280: bipush 113
    //   282: iadd
    //   283: ixor
    //   284: ldc 3
    //   286: invokevirtual 300	java/lang/String:length	()I
    //   289: ineg
    //   290: ixor
    //   291: iand
    //   292: ireturn
    //   293: getstatic 238	s:w	Lat;
    //   296: getfield 145	at:b	B
    //   299: getstatic 232	s:ak	[I
    //   302: bipush 18
    //   304: iaload
    //   305: invokestatic 340	s:i	(II)Z
    //   308: ifeq +53 -> 361
    //   311: getstatic 232	s:ak	[I
    //   314: bipush 6
    //   316: iaload
    //   317: getstatic 232	s:ak	[I
    //   320: iconst_1
    //   321: iaload
    //   322: getstatic 232	s:ak	[I
    //   325: iconst_4
    //   326: iaload
    //   327: invokestatic 290	fn:b	(III)V
    //   330: ldc 1
    //   332: invokevirtual 300	java/lang/String:length	()I
    //   335: pop
    //   336: bipush 84
    //   338: bipush 80
    //   340: ixor
    //   341: ineg
    //   342: iflt +737 -> 1079
    //   345: bipush 22
    //   347: bipush 10
    //   349: ixor
    //   350: sipush 171
    //   353: sipush 183
    //   356: ixor
    //   357: iconst_m1
    //   358: ixor
    //   359: iand
    //   360: ireturn
    //   361: getstatic 238	s:w	Lat;
    //   364: getfield 145	at:b	B
    //   367: getstatic 232	s:ak	[I
    //   370: bipush 9
    //   372: iaload
    //   373: invokestatic 340	s:i	(II)Z
    //   376: ifeq +83 -> 459
    //   379: getstatic 232	s:ak	[I
    //   382: bipush 6
    //   384: iaload
    //   385: getstatic 232	s:ak	[I
    //   388: iconst_1
    //   389: iaload
    //   390: getstatic 232	s:ak	[I
    //   393: iconst_3
    //   394: iaload
    //   395: invokestatic 290	fn:b	(III)V
    //   398: ldc 1
    //   400: invokevirtual 300	java/lang/String:length	()I
    //   403: pop
    //   404: aconst_null
    //   405: ifnull +674 -> 1079
    //   408: bipush 19
    //   410: bipush 68
    //   412: ixor
    //   413: sipush 197
    //   416: sipush 160
    //   419: ixor
    //   420: ixor
    //   421: sipush 166
    //   424: bipush 9
    //   426: iadd
    //   427: sipush 140
    //   430: isub
    //   431: sipush 206
    //   434: iadd
    //   435: sipush 173
    //   438: bipush 26
    //   440: iadd
    //   441: sipush 140
    //   444: isub
    //   445: sipush 136
    //   448: iadd
    //   449: ixor
    //   450: ldc 3
    //   452: invokevirtual 300	java/lang/String:length	()I
    //   455: ineg
    //   456: ixor
    //   457: iand
    //   458: ireturn
    //   459: getstatic 238	s:w	Lat;
    //   462: getfield 145	at:b	B
    //   465: getstatic 232	s:ak	[I
    //   468: iconst_4
    //   469: iaload
    //   470: invokestatic 340	s:i	(II)Z
    //   473: ifeq +51 -> 524
    //   476: getstatic 232	s:ak	[I
    //   479: bipush 6
    //   481: iaload
    //   482: getstatic 232	s:ak	[I
    //   485: iconst_1
    //   486: iaload
    //   487: getstatic 232	s:ak	[I
    //   490: bipush 8
    //   492: iaload
    //   493: invokestatic 290	fn:b	(III)V
    //   496: ldc 1
    //   498: invokevirtual 300	java/lang/String:length	()I
    //   501: pop
    //   502: ldc 4
    //   504: invokevirtual 300	java/lang/String:length	()I
    //   507: ifge +572 -> 1079
    //   510: bipush 117
    //   512: bipush 84
    //   514: ixor
    //   515: bipush 29
    //   517: bipush 60
    //   519: ixor
    //   520: iconst_m1
    //   521: ixor
    //   522: iand
    //   523: ireturn
    //   524: getstatic 238	s:w	Lat;
    //   527: getfield 145	at:b	B
    //   530: getstatic 232	s:ak	[I
    //   533: bipush 8
    //   535: iaload
    //   536: invokestatic 340	s:i	(II)Z
    //   539: ifeq +94 -> 633
    //   542: getstatic 232	s:ak	[I
    //   545: bipush 6
    //   547: iaload
    //   548: getstatic 232	s:ak	[I
    //   551: iconst_1
    //   552: iaload
    //   553: getstatic 232	s:ak	[I
    //   556: bipush 6
    //   558: iaload
    //   559: invokestatic 290	fn:b	(III)V
    //   562: ldc 1
    //   564: invokevirtual 300	java/lang/String:length	()I
    //   567: pop
    //   568: ldc 3
    //   570: invokevirtual 300	java/lang/String:length	()I
    //   573: bipush 117
    //   575: bipush 61
    //   577: ixor
    //   578: iconst_2
    //   579: bipush 78
    //   581: ixor
    //   582: ixor
    //   583: if_icmplt +496 -> 1079
    //   586: bipush 65
    //   588: bipush 93
    //   590: ixor
    //   591: bipush 27
    //   593: bipush 67
    //   595: ixor
    //   596: ixor
    //   597: sipush 187
    //   600: sipush 171
    //   603: iadd
    //   604: sipush 300
    //   607: isub
    //   608: sipush 159
    //   611: iadd
    //   612: bipush 104
    //   614: bipush 72
    //   616: iadd
    //   617: bipush 81
    //   619: isub
    //   620: bipush 62
    //   622: iadd
    //   623: ixor
    //   624: ldc 3
    //   626: invokevirtual 300	java/lang/String:length	()I
    //   629: ineg
    //   630: ixor
    //   631: iand
    //   632: ireturn
    //   633: getstatic 238	s:w	Lat;
    //   636: getfield 145	at:b	B
    //   639: invokestatic 341	s:j	(I)Z
    //   642: ifeq +59 -> 701
    //   645: getstatic 232	s:ak	[I
    //   648: bipush 6
    //   650: iaload
    //   651: getstatic 232	s:ak	[I
    //   654: iconst_1
    //   655: iaload
    //   656: getstatic 232	s:ak	[I
    //   659: iconst_1
    //   660: iaload
    //   661: invokestatic 290	fn:b	(III)V
    //   664: ldc 1
    //   666: invokevirtual 300	java/lang/String:length	()I
    //   669: pop
    //   670: sipush 144
    //   673: sipush 148
    //   676: ixor
    //   677: bipush 96
    //   679: bipush 100
    //   681: ixor
    //   682: if_icmpge +397 -> 1079
    //   685: bipush 66
    //   687: bipush 85
    //   689: ixor
    //   690: sipush 147
    //   693: sipush 132
    //   696: ixor
    //   697: iconst_m1
    //   698: ixor
    //   699: iand
    //   700: ireturn
    //   701: getstatic 238	s:w	Lat;
    //   704: getfield 145	at:b	B
    //   707: getstatic 232	s:ak	[I
    //   710: bipush 17
    //   712: iaload
    //   713: invokestatic 340	s:i	(II)Z
    //   716: ifeq +95 -> 811
    //   719: getstatic 232	s:ak	[I
    //   722: bipush 8
    //   724: iaload
    //   725: getstatic 232	s:ak	[I
    //   728: iconst_1
    //   729: iaload
    //   730: getstatic 232	s:ak	[I
    //   733: iconst_3
    //   734: iaload
    //   735: invokestatic 290	fn:b	(III)V
    //   738: ldc 1
    //   740: invokevirtual 300	java/lang/String:length	()I
    //   743: pop
    //   744: ldc 4
    //   746: invokevirtual 300	java/lang/String:length	()I
    //   749: ifge +330 -> 1079
    //   752: bipush 61
    //   754: bipush 117
    //   756: iadd
    //   757: sipush 169
    //   760: isub
    //   761: sipush 166
    //   764: iadd
    //   765: bipush 38
    //   767: bipush 26
    //   769: iadd
    //   770: bipush 23
    //   772: isub
    //   773: bipush 124
    //   775: iadd
    //   776: ixor
    //   777: sipush 175
    //   780: bipush 107
    //   782: iadd
    //   783: bipush 122
    //   785: isub
    //   786: bipush 43
    //   788: iadd
    //   789: sipush 180
    //   792: bipush 56
    //   794: iadd
    //   795: bipush 118
    //   797: isub
    //   798: bipush 75
    //   800: iadd
    //   801: ixor
    //   802: ldc 3
    //   804: invokevirtual 300	java/lang/String:length	()I
    //   807: ineg
    //   808: ixor
    //   809: iand
    //   810: ireturn
    //   811: getstatic 238	s:w	Lat;
    //   814: getfield 145	at:b	B
    //   817: getstatic 232	s:ak	[I
    //   820: bipush 10
    //   822: iaload
    //   823: invokestatic 340	s:i	(II)Z
    //   826: ifeq +104 -> 930
    //   829: getstatic 232	s:ak	[I
    //   832: bipush 8
    //   834: iaload
    //   835: getstatic 232	s:ak	[I
    //   838: iconst_1
    //   839: iaload
    //   840: getstatic 232	s:ak	[I
    //   843: bipush 8
    //   845: iaload
    //   846: invokestatic 290	fn:b	(III)V
    //   849: ldc 1
    //   851: invokevirtual 300	java/lang/String:length	()I
    //   854: pop
    //   855: bipush 96
    //   857: bipush 51
    //   859: ixor
    //   860: bipush 58
    //   862: bipush 109
    //   864: ixor
    //   865: ixor
    //   866: ineg
    //   867: ifle +212 -> 1079
    //   870: sipush 207
    //   873: sipush 190
    //   876: iadd
    //   877: sipush 232
    //   880: isub
    //   881: bipush 84
    //   883: iadd
    //   884: sipush 146
    //   887: bipush 18
    //   889: iadd
    //   890: bipush 22
    //   892: isub
    //   893: bipush 32
    //   895: iadd
    //   896: ixor
    //   897: bipush 55
    //   899: bipush 106
    //   901: iadd
    //   902: bipush 109
    //   904: isub
    //   905: sipush 163
    //   908: iadd
    //   909: bipush 105
    //   911: bipush 115
    //   913: iadd
    //   914: bipush 114
    //   916: isub
    //   917: bipush 22
    //   919: iadd
    //   920: ixor
    //   921: ldc 3
    //   923: invokevirtual 300	java/lang/String:length	()I
    //   926: ineg
    //   927: ixor
    //   928: iand
    //   929: ireturn
    //   930: getstatic 238	s:w	Lat;
    //   933: getfield 145	at:b	B
    //   936: getstatic 232	s:ak	[I
    //   939: iconst_2
    //   940: iaload
    //   941: invokestatic 340	s:i	(II)Z
    //   944: ifeq +99 -> 1043
    //   947: getstatic 232	s:ak	[I
    //   950: bipush 8
    //   952: iaload
    //   953: getstatic 232	s:ak	[I
    //   956: iconst_1
    //   957: iaload
    //   958: getstatic 232	s:ak	[I
    //   961: bipush 6
    //   963: iaload
    //   964: invokestatic 290	fn:b	(III)V
    //   967: ldc 1
    //   969: invokevirtual 300	java/lang/String:length	()I
    //   972: pop
    //   973: ldc 3
    //   975: invokevirtual 300	java/lang/String:length	()I
    //   978: ineg
    //   979: iflt +100 -> 1079
    //   982: bipush 52
    //   984: sipush 128
    //   987: iadd
    //   988: sipush 138
    //   991: isub
    //   992: bipush 96
    //   994: iadd
    //   995: bipush 82
    //   997: sipush 150
    //   1000: iadd
    //   1001: bipush 86
    //   1003: isub
    //   1004: bipush 42
    //   1006: iadd
    //   1007: ixor
    //   1008: sipush 238
    //   1011: sipush 206
    //   1014: iadd
    //   1015: sipush 269
    //   1018: isub
    //   1019: bipush 68
    //   1021: iadd
    //   1022: bipush 118
    //   1024: bipush 6
    //   1026: iadd
    //   1027: bipush 16
    //   1029: isub
    //   1030: bipush 89
    //   1032: iadd
    //   1033: ixor
    //   1034: ldc 3
    //   1036: invokevirtual 300	java/lang/String:length	()I
    //   1039: ineg
    //   1040: ixor
    //   1041: iand
    //   1042: ireturn
    //   1043: getstatic 238	s:w	Lat;
    //   1046: getfield 145	at:b	B
    //   1049: getstatic 232	s:ak	[I
    //   1052: iconst_3
    //   1053: iaload
    //   1054: invokestatic 340	s:i	(II)Z
    //   1057: ifeq +22 -> 1079
    //   1060: getstatic 232	s:ak	[I
    //   1063: bipush 8
    //   1065: iaload
    //   1066: getstatic 232	s:ak	[I
    //   1069: iconst_1
    //   1070: iaload
    //   1071: getstatic 232	s:ak	[I
    //   1074: iconst_1
    //   1075: iaload
    //   1076: invokestatic 290	fn:b	(III)V
    //   1079: aload_1
    //   1080: invokestatic 326	s:b	(Ljava/lang/Object;)Z
    //   1083: ifeq +28 -> 1111
    //   1086: invokestatic 255	cn:n	()Z
    //   1089: ldc 1
    //   1091: invokevirtual 300	java/lang/String:length	()I
    //   1094: pop2
    //   1095: getstatic 238	s:w	Lat;
    //   1098: getfield 145	at:b	B
    //   1101: invokestatic 283	dt:g	()Ldt;
    //   1104: getfield 175	dt:el	I
    //   1107: invokestatic 338	s:h	(II)[Lao;
    //   1110: astore_1
    //   1111: aload_1
    //   1112: invokestatic 325	s:a	(Ljava/lang/Object;)Z
    //   1115: ifeq +296 -> 1411
    //   1118: aconst_null
    //   1119: astore_2
    //   1120: getstatic 232	s:ak	[I
    //   1123: iconst_1
    //   1124: iaload
    //   1125: istore_3
    //   1126: iload_3
    //   1127: aload_1
    //   1128: arraylength
    //   1129: invokestatic 336	s:g	(II)Z
    //   1132: ifeq +156 -> 1288
    //   1135: aload_1
    //   1136: iload_3
    //   1137: aaload
    //   1138: getfield 140	ao:j	Lat;
    //   1141: getfield 146	at:f	S
    //   1144: getstatic 238	s:w	Lat;
    //   1147: getfield 146	at:f	S
    //   1150: invokestatic 340	s:i	(II)Z
    //   1153: ifeq +40 -> 1193
    //   1156: aload_1
    //   1157: iload_3
    //   1158: aaload
    //   1159: astore_2
    //   1160: ldc 1
    //   1162: invokevirtual 300	java/lang/String:length	()I
    //   1165: pop
    //   1166: ldc 3
    //   1168: invokevirtual 300	java/lang/String:length	()I
    //   1171: bipush 77
    //   1173: bipush 73
    //   1175: ixor
    //   1176: if_icmplt +112 -> 1288
    //   1179: bipush 102
    //   1181: bipush 74
    //   1183: ixor
    //   1184: bipush 89
    //   1186: bipush 117
    //   1188: ixor
    //   1189: iconst_m1
    //   1190: ixor
    //   1191: iand
    //   1192: ireturn
    //   1193: iinc 3 1
    //   1196: ldc 1
    //   1198: invokevirtual 300	java/lang/String:length	()I
    //   1201: pop
    //   1202: sipush 185
    //   1205: sipush 172
    //   1208: iadd
    //   1209: sipush 322
    //   1212: isub
    //   1213: sipush 218
    //   1216: iadd
    //   1217: bipush 30
    //   1219: bipush 25
    //   1221: iadd
    //   1222: bipush 12
    //   1224: isub
    //   1225: bipush 124
    //   1227: iadd
    //   1228: ixor
    //   1229: bipush 45
    //   1231: bipush 16
    //   1233: ixor
    //   1234: sipush 237
    //   1237: sipush 138
    //   1240: ixor
    //   1241: ixor
    //   1242: ldc 3
    //   1244: invokevirtual 300	java/lang/String:length	()I
    //   1247: ineg
    //   1248: ixor
    //   1249: iand
    //   1250: ldc 3
    //   1252: invokevirtual 300	java/lang/String:length	()I
    //   1255: if_icmple -129 -> 1126
    //   1258: bipush 41
    //   1260: bipush 34
    //   1262: ixor
    //   1263: bipush 40
    //   1265: bipush 99
    //   1267: ixor
    //   1268: ixor
    //   1269: iconst_3
    //   1270: bipush 111
    //   1272: ixor
    //   1273: bipush 50
    //   1275: bipush 30
    //   1277: ixor
    //   1278: ixor
    //   1279: ldc 3
    //   1281: invokevirtual 300	java/lang/String:length	()I
    //   1284: ineg
    //   1285: ixor
    //   1286: iand
    //   1287: ireturn
    //   1288: aload_2
    //   1289: invokestatic 325	s:a	(Ljava/lang/Object;)Z
    //   1292: ifeq +26 -> 1318
    //   1295: invokestatic 264	dl:ae	()Ldl;
    //   1298: aload_2
    //   1299: getfield 141	ao:m	I
    //   1302: aload_2
    //   1303: getfield 142	ao:n	I
    //   1306: getstatic 232	s:ak	[I
    //   1309: bipush 6
    //   1311: iaload
    //   1312: invokevirtual 266	dl:b	(III)V
    //   1315: invokestatic 252	cn:a	()V
    //   1318: ldc 1
    //   1320: invokevirtual 300	java/lang/String:length	()I
    //   1323: pop
    //   1324: bipush 53
    //   1326: bipush 59
    //   1328: ixor
    //   1329: bipush 54
    //   1331: bipush 14
    //   1333: ixor
    //   1334: ixor
    //   1335: bipush 62
    //   1337: bipush 44
    //   1339: iadd
    //   1340: bipush -33
    //   1342: isub
    //   1343: bipush 20
    //   1345: iadd
    //   1346: sipush 143
    //   1349: bipush 106
    //   1351: iadd
    //   1352: sipush 165
    //   1355: isub
    //   1356: bipush 85
    //   1358: iadd
    //   1359: ixor
    //   1360: ldc 3
    //   1362: invokevirtual 300	java/lang/String:length	()I
    //   1365: ineg
    //   1366: ixor
    //   1367: iand
    //   1368: ifeq +70 -> 1438
    //   1371: bipush 84
    //   1373: iconst_5
    //   1374: ixor
    //   1375: bipush 96
    //   1377: bipush 122
    //   1379: ixor
    //   1380: ixor
    //   1381: bipush 64
    //   1383: bipush 21
    //   1385: iadd
    //   1386: bipush -39
    //   1388: isub
    //   1389: bipush 74
    //   1391: iadd
    //   1392: iconst_5
    //   1393: bipush 125
    //   1395: iadd
    //   1396: bipush -6
    //   1398: isub
    //   1399: iconst_5
    //   1400: iadd
    //   1401: ixor
    //   1402: ldc 3
    //   1404: invokevirtual 300	java/lang/String:length	()I
    //   1407: ineg
    //   1408: ixor
    //   1409: iand
    //   1410: ireturn
    //   1411: getstatic 217	java/lang/System:out	Ljava/io/PrintStream;
    //   1414: new 124	java/lang/StringBuffer
    //   1417: dup
    //   1418: ldc 45
    //   1420: invokespecial 306	java/lang/StringBuffer:<init>	(Ljava/lang/String;)V
    //   1423: getstatic 238	s:w	Lat;
    //   1426: getfield 145	at:b	B
    //   1429: invokevirtual 307	java/lang/StringBuffer:append	(I)Ljava/lang/StringBuffer;
    //   1432: invokevirtual 309	java/lang/StringBuffer:toString	()Ljava/lang/String;
    //   1435: invokevirtual 293	java/io/PrintStream:println	(Ljava/lang/String;)V
    //   1438: getstatic 232	s:ak	[I
    //   1441: iconst_1
    //   1442: iaload
    //   1443: ireturn
    //   1444: getstatic 217	java/lang/System:out	Ljava/io/PrintStream;
    //   1447: new 124	java/lang/StringBuffer
    //   1450: dup
    //   1451: ldc 70
    //   1453: invokespecial 306	java/lang/StringBuffer:<init>	(Ljava/lang/String;)V
    //   1456: getstatic 229	s:ah	Lao;
    //   1459: getfield 141	ao:m	I
    //   1462: invokevirtual 307	java/lang/StringBuffer:append	(I)Ljava/lang/StringBuffer;
    //   1465: ldc 18
    //   1467: invokevirtual 308	java/lang/StringBuffer:append	(Ljava/lang/String;)Ljava/lang/StringBuffer;
    //   1470: getstatic 229	s:ah	Lao;
    //   1473: getfield 142	ao:n	I
    //   1476: invokevirtual 307	java/lang/StringBuffer:append	(I)Ljava/lang/StringBuffer;
    //   1479: invokevirtual 309	java/lang/StringBuffer:toString	()Ljava/lang/String;
    //   1482: invokevirtual 293	java/io/PrintStream:println	(Ljava/lang/String;)V
    //   1485: getstatic 232	s:ak	[I
    //   1488: bipush 6
    //   1490: iaload
    //   1491: putstatic 227	s:af	Z
    //   1494: ldc 1
    //   1496: invokevirtual 300	java/lang/String:length	()I
    //   1499: pop
    //   1500: aconst_null
    //   1501: ifnull +88 -> 1589
    //   1504: bipush 83
    //   1506: bipush 72
    //   1508: iadd
    //   1509: bipush -32
    //   1511: isub
    //   1512: bipush 29
    //   1514: iadd
    //   1515: sipush 171
    //   1518: bipush 27
    //   1520: iadd
    //   1521: bipush 11
    //   1523: isub
    //   1524: bipush 7
    //   1526: iadd
    //   1527: ixor
    //   1528: bipush 13
    //   1530: bipush 65
    //   1532: ixor
    //   1533: bipush 92
    //   1535: bipush 10
    //   1537: ixor
    //   1538: ixor
    //   1539: ldc 3
    //   1541: invokevirtual 300	java/lang/String:length	()I
    //   1544: ineg
    //   1545: ixor
    //   1546: iand
    //   1547: ireturn
    //   1548: getstatic 217	java/lang/System:out	Ljava/io/PrintStream;
    //   1551: new 124	java/lang/StringBuffer
    //   1554: dup
    //   1555: ldc 69
    //   1557: invokespecial 306	java/lang/StringBuffer:<init>	(Ljava/lang/String;)V
    //   1560: getstatic 229	s:ah	Lao;
    //   1563: getfield 141	ao:m	I
    //   1566: invokevirtual 307	java/lang/StringBuffer:append	(I)Ljava/lang/StringBuffer;
    //   1569: ldc 18
    //   1571: invokevirtual 308	java/lang/StringBuffer:append	(Ljava/lang/String;)Ljava/lang/StringBuffer;
    //   1574: getstatic 229	s:ah	Lao;
    //   1577: getfield 142	ao:n	I
    //   1580: invokevirtual 307	java/lang/StringBuffer:append	(I)Ljava/lang/StringBuffer;
    //   1583: invokevirtual 309	java/lang/StringBuffer:toString	()Ljava/lang/String;
    //   1586: invokevirtual 293	java/io/PrintStream:println	(Ljava/lang/String;)V
    //   1589: getstatic 232	s:ak	[I
    //   1592: iconst_1
    //   1593: iaload
    //   1594: ireturn
    //   1595: getstatic 229	s:ah	Lao;
    //   1598: getfield 141	ao:m	I
    //   1601: getstatic 232	s:ak	[I
    //   1604: iconst_4
    //   1605: iaload
    //   1606: invokestatic 340	s:i	(II)Z
    //   1609: ifeq +122 -> 1731
    //   1612: getstatic 232	s:ak	[I
    //   1615: iconst_2
    //   1616: iaload
    //   1617: getstatic 232	s:ak	[I
    //   1620: iconst_1
    //   1621: iaload
    //   1622: getstatic 232	s:ak	[I
    //   1625: iconst_1
    //   1626: iaload
    //   1627: invokestatic 290	fn:b	(III)V
    //   1630: invokestatic 282	dt:f	()I
    //   1633: invokestatic 339	s:i	(I)Z
    //   1636: ifeq +203 -> 1839
    //   1639: invokestatic 264	dl:ae	()Ldl;
    //   1642: getstatic 229	s:ah	Lao;
    //   1645: getfield 142	ao:n	I
    //   1648: invokevirtual 259	dl:a	(I)V
    //   1651: ldc2_w 132
    //   1654: invokestatic 311	java/lang/Thread:sleep	(J)V
    //   1657: ldc 1
    //   1659: invokevirtual 300	java/lang/String:length	()I
    //   1662: pop
    //   1663: ldc 5
    //   1665: invokevirtual 300	java/lang/String:length	()I
    //   1668: ldc 3
    //   1670: invokevirtual 300	java/lang/String:length	()I
    //   1673: ineg
    //   1674: if_icmpgt +165 -> 1839
    //   1677: bipush 70
    //   1679: bipush 23
    //   1681: ixor
    //   1682: bipush 78
    //   1684: bipush 31
    //   1686: ixor
    //   1687: iconst_m1
    //   1688: ixor
    //   1689: iand
    //   1690: ireturn
    //   1691: ldc 1
    //   1693: invokevirtual 300	java/lang/String:length	()I
    //   1696: pop2
    //   1697: ldc 1
    //   1699: invokevirtual 300	java/lang/String:length	()I
    //   1702: pop
    //   1703: ldc 4
    //   1705: invokevirtual 300	java/lang/String:length	()I
    //   1708: ldc 3
    //   1710: invokevirtual 300	java/lang/String:length	()I
    //   1713: ineg
    //   1714: if_icmpne +125 -> 1839
    //   1717: bipush 19
    //   1719: bipush 70
    //   1721: ixor
    //   1722: bipush 22
    //   1724: bipush 67
    //   1726: ixor
    //   1727: iconst_m1
    //   1728: ixor
    //   1729: iand
    //   1730: ireturn
    //   1731: getstatic 225	s:ad	Lao;
    //   1734: invokestatic 326	s:b	(Ljava/lang/Object;)Z
    //   1737: ifeq +19 -> 1756
    //   1740: invokestatic 283	dt:g	()Ldt;
    //   1743: getfield 183	dt:s	[Lao;
    //   1746: getstatic 238	s:w	Lat;
    //   1749: getfield 145	at:b	B
    //   1752: aaload
    //   1753: putstatic 225	s:ad	Lao;
    //   1756: getstatic 225	s:ad	Lao;
    //   1759: invokestatic 325	s:a	(Ljava/lang/Object;)Z
    //   1762: ifeq +44 -> 1806
    //   1765: getstatic 217	java/lang/System:out	Ljava/io/PrintStream;
    //   1768: new 124	java/lang/StringBuffer
    //   1771: dup
    //   1772: ldc 68
    //   1774: invokespecial 306	java/lang/StringBuffer:<init>	(Ljava/lang/String;)V
    //   1777: getstatic 225	s:ad	Lao;
    //   1780: getfield 141	ao:m	I
    //   1783: invokevirtual 307	java/lang/StringBuffer:append	(I)Ljava/lang/StringBuffer;
    //   1786: ldc 18
    //   1788: invokevirtual 308	java/lang/StringBuffer:append	(Ljava/lang/String;)Ljava/lang/StringBuffer;
    //   1791: getstatic 225	s:ad	Lao;
    //   1794: getfield 142	ao:n	I
    //   1797: invokevirtual 307	java/lang/StringBuffer:append	(I)Ljava/lang/StringBuffer;
    //   1800: invokevirtual 309	java/lang/StringBuffer:toString	()Ljava/lang/String;
    //   1803: invokevirtual 293	java/io/PrintStream:println	(Ljava/lang/String;)V
    //   1806: getstatic 229	s:ah	Lao;
    //   1809: getfield 143	ao:r	I
    //   1812: invokestatic 337	s:h	(I)Z
    //   1815: ifeq +24 -> 1839
    //   1818: invokestatic 264	dl:ae	()Ldl;
    //   1821: getstatic 229	s:ah	Lao;
    //   1824: getfield 142	ao:n	I
    //   1827: invokevirtual 263	dl:ad	(I)V
    //   1830: invokestatic 253	cn:ae	()Z
    //   1833: ldc 1
    //   1835: invokevirtual 300	java/lang/String:length	()I
    //   1838: pop2
    //   1839: getstatic 232	s:ak	[I
    //   1842: iconst_1
    //   1843: iaload
    //   1844: ireturn
    // Local variable table:
    //   start	length	slot	name	signature
    //   0	1845	0	this	s
    //   48	1109	1	localObject1	Object
    //   1119	184	2	localObject2	Object
    //   1125	69	3	i	int
    //   1691	1	4	localInterruptedException	InterruptedException
    // Exception table:
    //   from	to	target	type
    //   1651	1657	1691	java/lang/InterruptedException
  }
  
  public final void a()
  {
    super.a();
    al = ak[0];
    aa = ak[1];
    am = ak[1];
    ad = null;
    ah = null;
    an = ak[1];
    ae = ak[1];
    ac = ak[1];
  }
  
  private static boolean a(Object paramObject)
  {
    return paramObject != null;
  }
  
  /* Error */
  public static boolean a(String paramString)
  {
    // Byte code:
    //   0: aload_0
    //   1: getstatic 230	s:ai	Ljava/lang/String;
    //   4: invokevirtual 297	java/lang/String:equals	(Ljava/lang/Object;)Z
    //   7: invokestatic 329	s:d	(I)Z
    //   10: ifeq +19 -> 29
    //   13: getstatic 232	s:ak	[I
    //   16: bipush 6
    //   18: iaload
    //   19: putstatic 224	s:ac	Z
    //   22: getstatic 232	s:ak	[I
    //   25: bipush 6
    //   27: iaload
    //   28: ireturn
    //   29: aload_0
    //   30: getstatic 237	s:v	Ljava/lang/String;
    //   33: invokevirtual 301	java/lang/String:startsWith	(Ljava/lang/String;)Z
    //   36: invokestatic 329	s:d	(I)Z
    //   39: ifeq +517 -> 556
    //   42: getstatic 233	s:al	I
    //   45: getstatic 232	s:ak	[I
    //   48: iconst_4
    //   49: iaload
    //   50: invokestatic 330	s:d	(II)Z
    //   53: ifeq +497 -> 550
    //   56: getstatic 233	s:al	I
    //   59: getstatic 232	s:ak	[I
    //   62: bipush 9
    //   64: iaload
    //   65: invokestatic 334	s:f	(II)Z
    //   68: ifeq +482 -> 550
    //   71: getstatic 233	s:al	I
    //   74: getstatic 232	s:ak	[I
    //   77: iconst_4
    //   78: iaload
    //   79: invokestatic 340	s:i	(II)Z
    //   82: ifeq +424 -> 506
    //   85: invokestatic 264	dl:ae	()Ldl;
    //   88: invokestatic 283	dt:g	()Ldt;
    //   91: getfield 169	dt:ci	Ljava/lang/String;
    //   94: invokevirtual 270	dl:r	(Ljava/lang/String;)V
    //   97: invokestatic 253	cn:ae	()Z
    //   100: ldc 1
    //   102: invokevirtual 300	java/lang/String:length	()I
    //   105: pop2
    //   106: getstatic 232	s:ak	[I
    //   109: iconst_1
    //   110: iaload
    //   111: istore_1
    //   112: iload_1
    //   113: invokestatic 283	dt:g	()Ldt;
    //   116: getfield 184	dt:w	[Lao;
    //   119: arraylength
    //   120: invokestatic 336	s:g	(II)Z
    //   123: ifeq +286 -> 409
    //   126: invokestatic 283	dt:g	()Ldt;
    //   129: getfield 184	dt:w	[Lao;
    //   132: iload_1
    //   133: aaload
    //   134: dup
    //   135: astore_2
    //   136: invokestatic 325	s:a	(Ljava/lang/Object;)Z
    //   139: ifeq +217 -> 356
    //   142: aload_2
    //   143: getfield 143	ao:r	I
    //   146: getstatic 232	s:ak	[I
    //   149: bipush 18
    //   151: iaload
    //   152: invokestatic 340	s:i	(II)Z
    //   155: ifeq +201 -> 356
    //   158: invokestatic 283	dt:g	()Ldt;
    //   161: getfield 184	dt:w	[Lao;
    //   164: iload_1
    //   165: aaload
    //   166: getfield 140	ao:j	Lat;
    //   169: getfield 146	at:f	S
    //   172: getstatic 232	s:ak	[I
    //   175: bipush 19
    //   177: iaload
    //   178: invokestatic 334	s:f	(II)Z
    //   181: ifeq +29 -> 210
    //   184: invokestatic 283	dt:g	()Ldt;
    //   187: getfield 184	dt:w	[Lao;
    //   190: iload_1
    //   191: aaload
    //   192: getfield 140	ao:j	Lat;
    //   195: getfield 146	at:f	S
    //   198: getstatic 232	s:ak	[I
    //   201: bipush 20
    //   203: iaload
    //   204: invokestatic 340	s:i	(II)Z
    //   207: ifeq +149 -> 356
    //   210: invokestatic 264	dl:ae	()Ldl;
    //   213: aload_2
    //   214: invokevirtual 260	dl:a	(Lao;)V
    //   217: invokestatic 253	cn:ae	()Z
    //   220: ldc 1
    //   222: invokevirtual 300	java/lang/String:length	()I
    //   225: pop2
    //   226: invokestatic 264	dl:ae	()Ldl;
    //   229: invokestatic 283	dt:g	()Ldt;
    //   232: getfield 169	dt:ci	Ljava/lang/String;
    //   235: invokevirtual 270	dl:r	(Ljava/lang/String;)V
    //   238: invokestatic 253	cn:ae	()Z
    //   241: ldc 1
    //   243: invokevirtual 300	java/lang/String:length	()I
    //   246: pop2
    //   247: ldc 1
    //   249: invokevirtual 300	java/lang/String:length	()I
    //   252: pop
    //   253: sipush 177
    //   256: sipush 167
    //   259: ixor
    //   260: bipush 78
    //   262: bipush 94
    //   264: ixor
    //   265: ixor
    //   266: bipush 61
    //   268: bipush 107
    //   270: ixor
    //   271: sipush 247
    //   274: sipush 167
    //   277: ixor
    //   278: ixor
    //   279: ldc 3
    //   281: invokevirtual 300	java/lang/String:length	()I
    //   284: ineg
    //   285: ixor
    //   286: iand
    //   287: ldc 3
    //   289: invokevirtual 300	java/lang/String:length	()I
    //   292: ineg
    //   293: if_icmpgt +116 -> 409
    //   296: bipush 118
    //   298: sipush 159
    //   301: iadd
    //   302: sipush 149
    //   305: isub
    //   306: bipush 35
    //   308: iadd
    //   309: bipush 91
    //   311: bipush 90
    //   313: iadd
    //   314: bipush 20
    //   316: isub
    //   317: bipush 21
    //   319: iadd
    //   320: ixor
    //   321: bipush 13
    //   323: bipush 28
    //   325: iadd
    //   326: bipush 36
    //   328: isub
    //   329: sipush 134
    //   332: iadd
    //   333: bipush 117
    //   335: sipush 141
    //   338: iadd
    //   339: sipush 149
    //   342: isub
    //   343: bipush 49
    //   345: iadd
    //   346: ixor
    //   347: ldc 3
    //   349: invokevirtual 300	java/lang/String:length	()I
    //   352: ineg
    //   353: ixor
    //   354: iand
    //   355: ireturn
    //   356: iinc 1 1
    //   359: ldc 1
    //   361: invokevirtual 300	java/lang/String:length	()I
    //   364: pop
    //   365: bipush 22
    //   367: bipush 38
    //   369: ixor
    //   370: sipush 170
    //   373: sipush 154
    //   376: ixor
    //   377: iconst_m1
    //   378: ixor
    //   379: iand
    //   380: iconst_5
    //   381: bipush 71
    //   383: ixor
    //   384: bipush 28
    //   386: bipush 94
    //   388: ixor
    //   389: iconst_m1
    //   390: ixor
    //   391: iand
    //   392: if_icmpge -280 -> 112
    //   395: bipush 19
    //   397: bipush 84
    //   399: ixor
    //   400: bipush 90
    //   402: bipush 29
    //   404: ixor
    //   405: iconst_m1
    //   406: ixor
    //   407: iand
    //   408: ireturn
    //   409: getstatic 232	s:ak	[I
    //   412: bipush 6
    //   414: iaload
    //   415: putstatic 235	s:an	Z
    //   418: ldc 1
    //   420: invokevirtual 300	java/lang/String:length	()I
    //   423: pop
    //   424: sipush 196
    //   427: sipush 180
    //   430: ixor
    //   431: sipush 142
    //   434: sipush 193
    //   437: ixor
    //   438: ixor
    //   439: bipush 61
    //   441: bipush 91
    //   443: iadd
    //   444: bipush 86
    //   446: isub
    //   447: bipush 120
    //   449: iadd
    //   450: iconst_4
    //   451: sipush 131
    //   454: iadd
    //   455: bipush 47
    //   457: isub
    //   458: bipush 45
    //   460: iadd
    //   461: ixor
    //   462: ldc 3
    //   464: invokevirtual 300	java/lang/String:length	()I
    //   467: ineg
    //   468: ixor
    //   469: iand
    //   470: ifle +86 -> 556
    //   473: bipush 54
    //   475: bipush 42
    //   477: ixor
    //   478: bipush 75
    //   480: bipush 76
    //   482: ixor
    //   483: ixor
    //   484: sipush 158
    //   487: sipush 139
    //   490: ixor
    //   491: bipush 104
    //   493: bipush 102
    //   495: ixor
    //   496: ixor
    //   497: ldc 3
    //   499: invokevirtual 300	java/lang/String:length	()I
    //   502: ineg
    //   503: ixor
    //   504: iand
    //   505: ireturn
    //   506: getstatic 232	s:ak	[I
    //   509: bipush 6
    //   511: iaload
    //   512: putstatic 235	s:an	Z
    //   515: ldc 1
    //   517: invokevirtual 300	java/lang/String:length	()I
    //   520: pop
    //   521: ldc 4
    //   523: invokevirtual 300	java/lang/String:length	()I
    //   526: ldc 4
    //   528: invokevirtual 300	java/lang/String:length	()I
    //   531: if_icmpeq +25 -> 556
    //   534: bipush 110
    //   536: bipush 118
    //   538: ixor
    //   539: sipush 183
    //   542: sipush 175
    //   545: ixor
    //   546: iconst_m1
    //   547: ixor
    //   548: iand
    //   549: ireturn
    //   550: getstatic 231	s:aj	I
    //   553: putstatic 241	s:z	I
    //   556: aload_0
    //   557: ldc 97
    //   559: invokevirtual 301	java/lang/String:startsWith	(Ljava/lang/String;)Z
    //   562: ldc 1
    //   564: invokevirtual 300	java/lang/String:length	()I
    //   567: pop2
    //   568: aload_0
    //   569: ldc 71
    //   571: invokevirtual 299	java/lang/String:indexOf	(Ljava/lang/String;)I
    //   574: getstatic 232	s:ak	[I
    //   577: iconst_5
    //   578: iaload
    //   579: invokestatic 334	s:f	(II)Z
    //   582: ifeq +118 -> 700
    //   585: getstatic 233	s:al	I
    //   588: getstatic 232	s:ak	[I
    //   591: bipush 9
    //   593: iaload
    //   594: invokestatic 340	s:i	(II)Z
    //   597: ifeq +103 -> 700
    //   600: aload_0
    //   601: aload_0
    //   602: ldc 72
    //   604: invokevirtual 299	java/lang/String:indexOf	(Ljava/lang/String;)I
    //   607: getstatic 232	s:ak	[I
    //   610: iconst_4
    //   611: iaload
    //   612: iadd
    //   613: aload_0
    //   614: getstatic 232	s:ak	[I
    //   617: bipush 13
    //   619: iaload
    //   620: invokevirtual 298	java/lang/String:indexOf	(I)I
    //   623: invokevirtual 303	java/lang/String:substring	(II)Ljava/lang/String;
    //   626: astore_0
    //   627: new 124	java/lang/StringBuffer
    //   630: dup
    //   631: ldc 94
    //   633: invokespecial 306	java/lang/StringBuffer:<init>	(Ljava/lang/String;)V
    //   636: aload_0
    //   637: invokevirtual 308	java/lang/StringBuffer:append	(Ljava/lang/String;)Ljava/lang/StringBuffer;
    //   640: ldc 13
    //   642: invokevirtual 308	java/lang/StringBuffer:append	(Ljava/lang/String;)Ljava/lang/StringBuffer;
    //   645: getstatic 231	s:aj	I
    //   648: invokevirtual 307	java/lang/StringBuffer:append	(I)Ljava/lang/StringBuffer;
    //   651: invokevirtual 309	java/lang/StringBuffer:toString	()Ljava/lang/String;
    //   654: invokestatic 288	fn:a	(Ljava/lang/String;)V
    //   657: aload_0
    //   658: invokestatic 295	java/lang/Integer:parseInt	(Ljava/lang/String;)I
    //   661: putstatic 241	s:z	I
    //   664: ldc 1
    //   666: invokevirtual 300	java/lang/String:length	()I
    //   669: pop
    //   670: sipush 187
    //   673: sipush 190
    //   676: ixor
    //   677: ifne +23 -> 700
    //   680: bipush 46
    //   682: bipush 36
    //   684: ixor
    //   685: bipush 80
    //   687: bipush 90
    //   689: ixor
    //   690: iconst_m1
    //   691: ixor
    //   692: iand
    //   693: ireturn
    //   694: ldc 1
    //   696: invokevirtual 300	java/lang/String:length	()I
    //   699: pop2
    //   700: aload_0
    //   701: ldc 54
    //   703: invokevirtual 299	java/lang/String:indexOf	(Ljava/lang/String;)I
    //   706: getstatic 232	s:ak	[I
    //   709: iconst_5
    //   710: iaload
    //   711: invokestatic 334	s:f	(II)Z
    //   714: ifeq +148 -> 862
    //   717: getstatic 233	s:al	I
    //   720: getstatic 232	s:ak	[I
    //   723: bipush 10
    //   725: iaload
    //   726: invokestatic 340	s:i	(II)Z
    //   729: ifeq +133 -> 862
    //   732: aload_0
    //   733: aload_0
    //   734: ldc 54
    //   736: invokevirtual 299	java/lang/String:indexOf	(Ljava/lang/String;)I
    //   739: getstatic 232	s:ak	[I
    //   742: bipush 10
    //   744: iaload
    //   745: iadd
    //   746: aload_0
    //   747: getstatic 232	s:ak	[I
    //   750: bipush 13
    //   752: iaload
    //   753: invokevirtual 298	java/lang/String:indexOf	(I)I
    //   756: invokevirtual 303	java/lang/String:substring	(II)Ljava/lang/String;
    //   759: astore_0
    //   760: new 124	java/lang/StringBuffer
    //   763: dup
    //   764: ldc 53
    //   766: invokespecial 306	java/lang/StringBuffer:<init>	(Ljava/lang/String;)V
    //   769: aload_0
    //   770: invokevirtual 308	java/lang/StringBuffer:append	(Ljava/lang/String;)Ljava/lang/StringBuffer;
    //   773: ldc 13
    //   775: invokevirtual 308	java/lang/StringBuffer:append	(Ljava/lang/String;)Ljava/lang/StringBuffer;
    //   778: getstatic 231	s:aj	I
    //   781: invokevirtual 307	java/lang/StringBuffer:append	(I)Ljava/lang/StringBuffer;
    //   784: invokevirtual 309	java/lang/StringBuffer:toString	()Ljava/lang/String;
    //   787: invokestatic 288	fn:a	(Ljava/lang/String;)V
    //   790: aload_0
    //   791: invokestatic 295	java/lang/Integer:parseInt	(Ljava/lang/String;)I
    //   794: putstatic 241	s:z	I
    //   797: ldc 1
    //   799: invokevirtual 300	java/lang/String:length	()I
    //   802: pop
    //   803: ldc 5
    //   805: invokevirtual 300	java/lang/String:length	()I
    //   808: sipush 131
    //   811: sipush 135
    //   814: ixor
    //   815: if_icmple +23 -> 838
    //   818: bipush 8
    //   820: bipush 31
    //   822: ixor
    //   823: bipush 45
    //   825: bipush 58
    //   827: ixor
    //   828: iconst_m1
    //   829: ixor
    //   830: iand
    //   831: ireturn
    //   832: ldc 1
    //   834: invokevirtual 300	java/lang/String:length	()I
    //   837: pop2
    //   838: getstatic 241	s:z	I
    //   841: getstatic 231	s:aj	I
    //   844: invokestatic 336	s:g	(II)Z
    //   847: ifeq +15 -> 862
    //   850: getstatic 148	au:g	Lau;
    //   853: invokevirtual 247	au:f	()V
    //   856: invokestatic 258	cu:e	()Lcu;
    //   859: invokevirtual 257	cu:c	()V
    //   862: aload_0
    //   863: ldc 49
    //   865: invokevirtual 299	java/lang/String:indexOf	(Ljava/lang/String;)I
    //   868: getstatic 232	s:ak	[I
    //   871: iconst_5
    //   872: iaload
    //   873: invokestatic 334	s:f	(II)Z
    //   876: ifeq +150 -> 1026
    //   879: getstatic 233	s:al	I
    //   882: getstatic 232	s:ak	[I
    //   885: iconst_2
    //   886: iaload
    //   887: invokestatic 340	s:i	(II)Z
    //   890: ifeq +136 -> 1026
    //   893: aload_0
    //   894: aload_0
    //   895: ldc 49
    //   897: invokevirtual 299	java/lang/String:indexOf	(Ljava/lang/String;)I
    //   900: getstatic 232	s:ak	[I
    //   903: bipush 12
    //   905: iaload
    //   906: iadd
    //   907: aload_0
    //   908: getstatic 232	s:ak	[I
    //   911: bipush 13
    //   913: iaload
    //   914: invokevirtual 298	java/lang/String:indexOf	(I)I
    //   917: invokevirtual 303	java/lang/String:substring	(II)Ljava/lang/String;
    //   920: astore_0
    //   921: new 124	java/lang/StringBuffer
    //   924: dup
    //   925: ldc 48
    //   927: invokespecial 306	java/lang/StringBuffer:<init>	(Ljava/lang/String;)V
    //   930: aload_0
    //   931: invokevirtual 308	java/lang/StringBuffer:append	(Ljava/lang/String;)Ljava/lang/StringBuffer;
    //   934: ldc 13
    //   936: invokevirtual 308	java/lang/StringBuffer:append	(Ljava/lang/String;)Ljava/lang/StringBuffer;
    //   939: getstatic 231	s:aj	I
    //   942: invokevirtual 307	java/lang/StringBuffer:append	(I)Ljava/lang/StringBuffer;
    //   945: ldc 23
    //   947: invokevirtual 308	java/lang/StringBuffer:append	(Ljava/lang/String;)Ljava/lang/StringBuffer;
    //   950: invokevirtual 309	java/lang/StringBuffer:toString	()Ljava/lang/String;
    //   953: invokestatic 288	fn:a	(Ljava/lang/String;)V
    //   956: aload_0
    //   957: invokestatic 295	java/lang/Integer:parseInt	(Ljava/lang/String;)I
    //   960: putstatic 241	s:z	I
    //   963: ldc 1
    //   965: invokevirtual 300	java/lang/String:length	()I
    //   968: pop
    //   969: ldc 4
    //   971: invokevirtual 300	java/lang/String:length	()I
    //   974: ldc 3
    //   976: invokevirtual 300	java/lang/String:length	()I
    //   979: if_icmpgt +23 -> 1002
    //   982: bipush 54
    //   984: bipush 125
    //   986: ixor
    //   987: bipush 28
    //   989: bipush 87
    //   991: ixor
    //   992: iconst_m1
    //   993: ixor
    //   994: iand
    //   995: ireturn
    //   996: ldc 1
    //   998: invokevirtual 300	java/lang/String:length	()I
    //   1001: pop2
    //   1002: getstatic 241	s:z	I
    //   1005: getstatic 231	s:aj	I
    //   1008: invokestatic 336	s:g	(II)Z
    //   1011: ifeq +15 -> 1026
    //   1014: getstatic 148	au:g	Lau;
    //   1017: invokevirtual 247	au:f	()V
    //   1020: invokestatic 258	cu:e	()Lcu;
    //   1023: invokevirtual 257	cu:c	()V
    //   1026: aload_0
    //   1027: ldc 87
    //   1029: invokevirtual 299	java/lang/String:indexOf	(Ljava/lang/String;)I
    //   1032: getstatic 232	s:ak	[I
    //   1035: iconst_5
    //   1036: iaload
    //   1037: invokestatic 334	s:f	(II)Z
    //   1040: ifeq +105 -> 1145
    //   1043: getstatic 233	s:al	I
    //   1046: getstatic 232	s:ak	[I
    //   1049: iconst_4
    //   1050: iaload
    //   1051: invokestatic 336	s:g	(II)Z
    //   1054: ifeq +91 -> 1145
    //   1057: getstatic 217	java/lang/System:out	Ljava/io/PrintStream;
    //   1060: ldc 27
    //   1062: invokevirtual 293	java/io/PrintStream:println	(Ljava/lang/String;)V
    //   1065: aload_0
    //   1066: aload_0
    //   1067: ldc 86
    //   1069: invokevirtual 299	java/lang/String:indexOf	(Ljava/lang/String;)I
    //   1072: getstatic 232	s:ak	[I
    //   1075: bipush 11
    //   1077: iaload
    //   1078: iadd
    //   1079: aload_0
    //   1080: getstatic 232	s:ak	[I
    //   1083: bipush 13
    //   1085: iaload
    //   1086: invokevirtual 298	java/lang/String:indexOf	(I)I
    //   1089: invokevirtual 303	java/lang/String:substring	(II)Ljava/lang/String;
    //   1092: astore_0
    //   1093: aload_0
    //   1094: invokestatic 295	java/lang/Integer:parseInt	(Ljava/lang/String;)I
    //   1097: putstatic 223	s:ab	I
    //   1100: ldc 1
    //   1102: invokevirtual 300	java/lang/String:length	()I
    //   1105: pop
    //   1106: sipush 192
    //   1109: sipush 196
    //   1112: ixor
    //   1113: sipush 193
    //   1116: sipush 197
    //   1119: ixor
    //   1120: if_icmpeq +25 -> 1145
    //   1123: bipush 51
    //   1125: bipush 9
    //   1127: ixor
    //   1128: sipush 151
    //   1131: sipush 173
    //   1134: ixor
    //   1135: iconst_m1
    //   1136: ixor
    //   1137: iand
    //   1138: ireturn
    //   1139: ldc 1
    //   1141: invokevirtual 300	java/lang/String:length	()I
    //   1144: pop2
    //   1145: getstatic 232	s:ak	[I
    //   1148: bipush 6
    //   1150: iaload
    //   1151: ireturn
    // Local variable table:
    //   start	length	slot	name	signature
    //   0	1152	0	paramString	String
    //   111	246	1	i	int
    //   135	79	2	localao	ao
    //   694	1	3	localNumberFormatException1	NumberFormatException
    //   832	1	4	localNumberFormatException2	NumberFormatException
    //   996	1	5	localNumberFormatException3	NumberFormatException
    //   1139	1	6	localNumberFormatException4	NumberFormatException
    // Exception table:
    //   from	to	target	type
    //   657	664	694	java/lang/NumberFormatException
    //   790	797	832	java/lang/NumberFormatException
    //   956	963	996	java/lang/NumberFormatException
    //   1093	1100	1139	java/lang/NumberFormatException
  }
  
  private static boolean d(int paramInt)
  {
    return paramInt != 0;
  }
  
  private static int a(long paramLong1, long paramLong2)
  {
    return paramLong1 < paramLong2;
  }
  
  private static boolean d(int paramInt1, int paramInt2)
  {
    return paramInt1 >= paramInt2;
  }
  
  private boolean q()
  {
    if (j(et.i(et.o)))
    {
      a(cz.l, ak[0], ak[5], ak[5]);
      return ak[1];
    }
    System.out.println("Buy Item Up" + x.a);
    ao[] arrayOfao = h(x.b, dt.g().el);
    if (i(x.b, ak[18])) {
      fn.b(ak[6], ak[1], ak[4]);
    }
    if (b(arrayOfao))
    {
      "".length();
      arrayOfao = h(x.b, dt.g().el);
    }
    if (a(arrayOfao))
    {
      ao localao = null;
      int i = ak[1];
      while (g(i, arrayOfao.length)) {
        if (i(arrayOfao[i].j.f, x.f))
        {
          localao = arrayOfao[i];
          "".length();
          if (-" ".length() >= "  ".length()) {
            return (0x62 ^ 0x25 ^ 0x36 ^ 0x10) & (0x56 ^ 0x14 ^ 0x66 ^ 0x45 ^ -" ".length());
          }
        }
        else
        {
          i++;
          "".length();
          if (" ".length() == 0) {
            return (0x21 ^ 0x65 ^ 0x4B ^ 0x3B) & (0x1F ^ 0x45 ^ 0xDA ^ 0xB4 ^ -" ".length()) & ((0x4B ^ 0x39 ^ 0x5 ^ 0x59) & (0x6D ^ 0x1E ^ 0x8 ^ 0x55 ^ -" ".length()) ^ -" ".length());
          }
        }
      }
      if (a(localao))
      {
        dl.ae().b(localao.m, localao.n, ak[6]);
        cn.a();
      }
      "".length();
      if ("  ".length() < "  ".length()) {
        return (0x28 ^ 0x48) & (0xCA ^ 0xAA ^ 0xFFFFFFFF);
      }
    }
    else
    {
      System.out.println("BuyER: " + x.b);
    }
    return ak[1];
  }
  
  private static boolean e(int paramInt1, int paramInt2)
  {
    return paramInt1 <= paramInt2;
  }
  
  private static boolean e(int paramInt)
  {
    return paramInt <= 0;
  }
  
  /* Error */
  public static void b(String paramString)
  {
    // Byte code:
    //   0: getstatic 217	java/lang/System:out	Ljava/io/PrintStream;
    //   3: ldc 84
    //   5: aload_0
    //   6: invokestatic 305	java/lang/String:valueOf	(Ljava/lang/Object;)Ljava/lang/String;
    //   9: invokevirtual 296	java/lang/String:concat	(Ljava/lang/String;)Ljava/lang/String;
    //   12: invokevirtual 293	java/io/PrintStream:println	(Ljava/lang/String;)V
    //   15: getstatic 233	s:al	I
    //   18: invokestatic 337	s:h	(I)Z
    //   21: ifeq +101 -> 122
    //   24: getstatic 217	java/lang/System:out	Ljava/io/PrintStream;
    //   27: ldc 39
    //   29: invokevirtual 293	java/io/PrintStream:println	(Ljava/lang/String;)V
    //   32: aload_0
    //   33: ldc 29
    //   35: invokevirtual 301	java/lang/String:startsWith	(Ljava/lang/String;)Z
    //   38: invokestatic 341	s:j	(I)Z
    //   41: ifeq +15 -> 56
    //   44: aload_0
    //   45: ldc 98
    //   47: invokevirtual 301	java/lang/String:startsWith	(Ljava/lang/String;)Z
    //   50: invokestatic 329	s:d	(I)Z
    //   53: ifeq +34 -> 87
    //   56: getstatic 217	java/lang/System:out	Ljava/io/PrintStream;
    //   59: ldc 40
    //   61: invokevirtual 293	java/io/PrintStream:println	(Ljava/lang/String;)V
    //   64: aconst_null
    //   65: putstatic 238	s:w	Lat;
    //   68: getstatic 232	s:ak	[I
    //   71: iconst_1
    //   72: iaload
    //   73: putstatic 235	s:an	Z
    //   76: getstatic 232	s:ak	[I
    //   79: iconst_5
    //   80: iaload
    //   81: putstatic 233	s:al	I
    //   84: invokestatic 254	cn:e	()V
    //   87: aload_0
    //   88: ldc 91
    //   90: invokevirtual 301	java/lang/String:startsWith	(Ljava/lang/String;)Z
    //   93: invokestatic 329	s:d	(I)Z
    //   96: ifeq +3987 -> 4083
    //   99: getstatic 233	s:al	I
    //   102: getstatic 232	s:ak	[I
    //   105: iconst_2
    //   106: iaload
    //   107: invokestatic 340	s:i	(II)Z
    //   110: ifeq +3973 -> 4083
    //   113: getstatic 232	s:ak	[I
    //   116: iconst_0
    //   117: iaload
    //   118: putstatic 233	s:al	I
    //   121: return
    //   122: aload_0
    //   123: ldc 91
    //   125: invokevirtual 301	java/lang/String:startsWith	(Ljava/lang/String;)Z
    //   128: invokestatic 329	s:d	(I)Z
    //   131: ifeq +15 -> 146
    //   134: getstatic 232	s:ak	[I
    //   137: iconst_0
    //   138: iaload
    //   139: putstatic 233	s:al	I
    //   142: invokestatic 254	cn:e	()V
    //   145: return
    //   146: getstatic 233	s:al	I
    //   149: getstatic 232	s:ak	[I
    //   152: iconst_0
    //   153: iaload
    //   154: invokestatic 340	s:i	(II)Z
    //   157: ifeq +47 -> 204
    //   160: getstatic 217	java/lang/System:out	Ljava/io/PrintStream;
    //   163: ldc 41
    //   165: invokevirtual 293	java/io/PrintStream:println	(Ljava/lang/String;)V
    //   168: aload_0
    //   169: ldc 31
    //   171: invokevirtual 301	java/lang/String:startsWith	(Ljava/lang/String;)Z
    //   174: invokestatic 329	s:d	(I)Z
    //   177: ifeq +27 -> 204
    //   180: getstatic 217	java/lang/System:out	Ljava/io/PrintStream;
    //   183: ldc 42
    //   185: invokevirtual 293	java/io/PrintStream:println	(Ljava/lang/String;)V
    //   188: aconst_null
    //   189: putstatic 238	s:w	Lat;
    //   192: getstatic 232	s:ak	[I
    //   195: iconst_5
    //   196: iaload
    //   197: putstatic 233	s:al	I
    //   200: invokestatic 254	cn:e	()V
    //   203: return
    //   204: getstatic 217	java/lang/System:out	Ljava/io/PrintStream;
    //   207: ldc 46
    //   209: invokevirtual 293	java/io/PrintStream:println	(Ljava/lang/String;)V
    //   212: getstatic 232	s:ak	[I
    //   215: iconst_1
    //   216: iaload
    //   217: putstatic 235	s:an	Z
    //   220: aload_0
    //   221: ldc 2
    //   223: invokestatic 272	dn:a	(Ljava/lang/String;Ljava/lang/String;)[Ljava/lang/String;
    //   226: astore_0
    //   227: getstatic 217	java/lang/System:out	Ljava/io/PrintStream;
    //   230: new 124	java/lang/StringBuffer
    //   233: dup
    //   234: ldc 79
    //   236: invokespecial 306	java/lang/StringBuffer:<init>	(Ljava/lang/String;)V
    //   239: aload_0
    //   240: getstatic 232	s:ak	[I
    //   243: iconst_1
    //   244: iaload
    //   245: aaload
    //   246: invokevirtual 308	java/lang/StringBuffer:append	(Ljava/lang/String;)Ljava/lang/StringBuffer;
    //   249: invokevirtual 309	java/lang/StringBuffer:toString	()Ljava/lang/String;
    //   252: invokevirtual 293	java/io/PrintStream:println	(Ljava/lang/String;)V
    //   255: aload_0
    //   256: getstatic 232	s:ak	[I
    //   259: iconst_1
    //   260: iaload
    //   261: aaload
    //   262: ldc 88
    //   264: invokevirtual 297	java/lang/String:equals	(Ljava/lang/Object;)Z
    //   267: invokestatic 329	s:d	(I)Z
    //   270: ifeq +155 -> 425
    //   273: getstatic 232	s:ak	[I
    //   276: bipush 6
    //   278: iaload
    //   279: putstatic 167	dt:bb	Z
    //   282: getstatic 232	s:ak	[I
    //   285: iconst_1
    //   286: iaload
    //   287: putstatic 182	dt:h	Z
    //   290: getstatic 232	s:ak	[I
    //   293: iconst_1
    //   294: iaload
    //   295: putstatic 171	dt:dj	Z
    //   298: getstatic 232	s:ak	[I
    //   301: iconst_1
    //   302: iaload
    //   303: istore_1
    //   304: iload_1
    //   305: invokestatic 283	dt:g	()Ldt;
    //   308: getfield 184	dt:w	[Lao;
    //   311: arraylength
    //   312: invokestatic 336	s:g	(II)Z
    //   315: ifeq +86 -> 401
    //   318: invokestatic 283	dt:g	()Ldt;
    //   321: getfield 184	dt:w	[Lao;
    //   324: iload_1
    //   325: aaload
    //   326: dup
    //   327: astore_2
    //   328: invokestatic 325	s:a	(Ljava/lang/Object;)Z
    //   331: ifeq +56 -> 387
    //   334: aload_2
    //   335: getfield 140	ao:j	Lat;
    //   338: getfield 145	at:b	B
    //   341: getstatic 232	s:ak	[I
    //   344: bipush 7
    //   346: iaload
    //   347: invokestatic 340	s:i	(II)Z
    //   350: ifeq +37 -> 387
    //   353: aload_2
    //   354: getfield 140	ao:j	Lat;
    //   357: getfield 146	at:f	S
    //   360: getstatic 232	s:ak	[I
    //   363: iconst_3
    //   364: iaload
    //   365: invokestatic 332	s:e	(II)Z
    //   368: ifeq +19 -> 387
    //   371: invokestatic 264	dl:ae	()Ldl;
    //   374: aload_2
    //   375: getfield 142	ao:n	I
    //   378: getstatic 232	s:ak	[I
    //   381: bipush 6
    //   383: iaload
    //   384: invokevirtual 267	dl:g	(II)V
    //   387: iinc 1 1
    //   390: ldc 1
    //   392: invokevirtual 300	java/lang/String:length	()I
    //   395: pop
    //   396: aconst_null
    //   397: ifnull -93 -> 304
    //   400: return
    //   401: getstatic 232	s:ak	[I
    //   404: bipush 6
    //   406: iaload
    //   407: putstatic 233	s:al	I
    //   410: ldc 1
    //   412: invokevirtual 300	java/lang/String:length	()I
    //   415: pop
    //   416: ldc 5
    //   418: invokevirtual 300	java/lang/String:length	()I
    //   421: ifgt +1269 -> 1690
    //   424: return
    //   425: aload_0
    //   426: getstatic 232	s:ak	[I
    //   429: iconst_1
    //   430: iaload
    //   431: aaload
    //   432: ldc 90
    //   434: invokevirtual 297	java/lang/String:equals	(Ljava/lang/Object;)Z
    //   437: invokestatic 329	s:d	(I)Z
    //   440: ifeq +228 -> 668
    //   443: getstatic 158	cz:k	Z
    //   446: invokestatic 341	s:j	(I)Z
    //   449: ifeq +219 -> 668
    //   452: getstatic 232	s:ak	[I
    //   455: bipush 6
    //   457: iaload
    //   458: putstatic 167	dt:bb	Z
    //   461: getstatic 232	s:ak	[I
    //   464: bipush 6
    //   466: iaload
    //   467: putstatic 182	dt:h	Z
    //   470: getstatic 232	s:ak	[I
    //   473: iconst_1
    //   474: iaload
    //   475: putstatic 171	dt:dj	Z
    //   478: getstatic 232	s:ak	[I
    //   481: iconst_1
    //   482: iaload
    //   483: istore_1
    //   484: iload_1
    //   485: invokestatic 283	dt:g	()Ldt;
    //   488: getfield 184	dt:w	[Lao;
    //   491: arraylength
    //   492: invokestatic 336	s:g	(II)Z
    //   495: ifeq +142 -> 637
    //   498: invokestatic 283	dt:g	()Ldt;
    //   501: getfield 184	dt:w	[Lao;
    //   504: iload_1
    //   505: aaload
    //   506: dup
    //   507: astore_2
    //   508: invokestatic 325	s:a	(Ljava/lang/Object;)Z
    //   511: ifeq +56 -> 567
    //   514: aload_2
    //   515: getfield 140	ao:j	Lat;
    //   518: getfield 145	at:b	B
    //   521: getstatic 232	s:ak	[I
    //   524: bipush 7
    //   526: iaload
    //   527: invokestatic 340	s:i	(II)Z
    //   530: ifeq +37 -> 567
    //   533: aload_2
    //   534: getfield 140	ao:j	Lat;
    //   537: getfield 146	at:f	S
    //   540: getstatic 232	s:ak	[I
    //   543: iconst_3
    //   544: iaload
    //   545: invokestatic 332	s:e	(II)Z
    //   548: ifeq +19 -> 567
    //   551: invokestatic 264	dl:ae	()Ldl;
    //   554: aload_2
    //   555: getfield 142	ao:n	I
    //   558: getstatic 232	s:ak	[I
    //   561: bipush 6
    //   563: iaload
    //   564: invokevirtual 267	dl:g	(II)V
    //   567: iinc 1 1
    //   570: ldc 1
    //   572: invokevirtual 300	java/lang/String:length	()I
    //   575: pop
    //   576: bipush 51
    //   578: bipush 68
    //   580: iadd
    //   581: bipush 53
    //   583: isub
    //   584: bipush 80
    //   586: iadd
    //   587: sipush 165
    //   590: sipush 134
    //   593: iadd
    //   594: sipush 160
    //   597: isub
    //   598: bipush 29
    //   600: iadd
    //   601: ixor
    //   602: bipush 73
    //   604: bipush 83
    //   606: iadd
    //   607: bipush 90
    //   609: isub
    //   610: bipush 71
    //   612: iadd
    //   613: bipush 51
    //   615: bipush 65
    //   617: iadd
    //   618: bipush -28
    //   620: isub
    //   621: bipush 35
    //   623: iadd
    //   624: ixor
    //   625: ldc 3
    //   627: invokevirtual 300	java/lang/String:length	()I
    //   630: ineg
    //   631: ixor
    //   632: iand
    //   633: ifeq -149 -> 484
    //   636: return
    //   637: getstatic 232	s:ak	[I
    //   640: bipush 8
    //   642: iaload
    //   643: putstatic 233	s:al	I
    //   646: ldc 1
    //   648: invokevirtual 300	java/lang/String:length	()I
    //   651: pop
    //   652: sipush 144
    //   655: sipush 148
    //   658: ixor
    //   659: bipush 95
    //   661: bipush 91
    //   663: ixor
    //   664: if_icmple +1026 -> 1690
    //   667: return
    //   668: aload_0
    //   669: getstatic 232	s:ak	[I
    //   672: iconst_1
    //   673: iaload
    //   674: aaload
    //   675: ldc 89
    //   677: invokevirtual 297	java/lang/String:equals	(Ljava/lang/Object;)Z
    //   680: invokestatic 329	s:d	(I)Z
    //   683: ifeq +170 -> 853
    //   686: getstatic 162	cz:o	Z
    //   689: invokestatic 341	s:j	(I)Z
    //   692: ifeq +161 -> 853
    //   695: getstatic 232	s:ak	[I
    //   698: bipush 6
    //   700: iaload
    //   701: putstatic 167	dt:bb	Z
    //   704: getstatic 232	s:ak	[I
    //   707: iconst_1
    //   708: iaload
    //   709: putstatic 182	dt:h	Z
    //   712: getstatic 232	s:ak	[I
    //   715: bipush 6
    //   717: iaload
    //   718: putstatic 171	dt:dj	Z
    //   721: getstatic 232	s:ak	[I
    //   724: iconst_1
    //   725: iaload
    //   726: istore_1
    //   727: iload_1
    //   728: invokestatic 283	dt:g	()Ldt;
    //   731: getfield 184	dt:w	[Lao;
    //   734: arraylength
    //   735: invokestatic 336	s:g	(II)Z
    //   738: ifeq +86 -> 824
    //   741: invokestatic 283	dt:g	()Ldt;
    //   744: getfield 184	dt:w	[Lao;
    //   747: iload_1
    //   748: aaload
    //   749: dup
    //   750: astore_2
    //   751: invokestatic 325	s:a	(Ljava/lang/Object;)Z
    //   754: ifeq +56 -> 810
    //   757: aload_2
    //   758: getfield 140	ao:j	Lat;
    //   761: getfield 145	at:b	B
    //   764: getstatic 232	s:ak	[I
    //   767: bipush 7
    //   769: iaload
    //   770: invokestatic 340	s:i	(II)Z
    //   773: ifeq +37 -> 810
    //   776: aload_2
    //   777: getfield 140	ao:j	Lat;
    //   780: getfield 146	at:f	S
    //   783: getstatic 232	s:ak	[I
    //   786: iconst_3
    //   787: iaload
    //   788: invokestatic 332	s:e	(II)Z
    //   791: ifeq +19 -> 810
    //   794: invokestatic 264	dl:ae	()Ldl;
    //   797: aload_2
    //   798: getfield 142	ao:n	I
    //   801: getstatic 232	s:ak	[I
    //   804: bipush 6
    //   806: iaload
    //   807: invokevirtual 267	dl:g	(II)V
    //   810: iinc 1 1
    //   813: ldc 1
    //   815: invokevirtual 300	java/lang/String:length	()I
    //   818: pop
    //   819: aconst_null
    //   820: ifnull -93 -> 727
    //   823: return
    //   824: getstatic 232	s:ak	[I
    //   827: iconst_3
    //   828: iaload
    //   829: putstatic 233	s:al	I
    //   832: ldc 1
    //   834: invokevirtual 300	java/lang/String:length	()I
    //   837: pop
    //   838: ldc 5
    //   840: invokevirtual 300	java/lang/String:length	()I
    //   843: ldc 3
    //   845: invokevirtual 300	java/lang/String:length	()I
    //   848: ineg
    //   849: if_icmpgt +841 -> 1690
    //   852: return
    //   853: aload_0
    //   854: getstatic 232	s:ak	[I
    //   857: iconst_1
    //   858: iaload
    //   859: aaload
    //   860: ldc 81
    //   862: invokevirtual 297	java/lang/String:equals	(Ljava/lang/Object;)Z
    //   865: invokestatic 329	s:d	(I)Z
    //   868: ifeq +162 -> 1030
    //   871: getstatic 161	cz:n	Z
    //   874: invokestatic 341	s:j	(I)Z
    //   877: ifeq +153 -> 1030
    //   880: getstatic 232	s:ak	[I
    //   883: iconst_1
    //   884: iaload
    //   885: istore_1
    //   886: iload_1
    //   887: invokestatic 283	dt:g	()Ldt;
    //   890: getfield 184	dt:w	[Lao;
    //   893: arraylength
    //   894: invokestatic 336	s:g	(II)Z
    //   897: ifeq +100 -> 997
    //   900: invokestatic 283	dt:g	()Ldt;
    //   903: getfield 184	dt:w	[Lao;
    //   906: iload_1
    //   907: aaload
    //   908: dup
    //   909: astore_2
    //   910: invokestatic 325	s:a	(Ljava/lang/Object;)Z
    //   913: ifeq +56 -> 969
    //   916: aload_2
    //   917: getfield 140	ao:j	Lat;
    //   920: getfield 145	at:b	B
    //   923: getstatic 232	s:ak	[I
    //   926: bipush 7
    //   928: iaload
    //   929: invokestatic 340	s:i	(II)Z
    //   932: ifeq +37 -> 969
    //   935: aload_2
    //   936: getfield 140	ao:j	Lat;
    //   939: getfield 146	at:f	S
    //   942: getstatic 232	s:ak	[I
    //   945: iconst_3
    //   946: iaload
    //   947: invokestatic 332	s:e	(II)Z
    //   950: ifeq +19 -> 969
    //   953: invokestatic 264	dl:ae	()Ldl;
    //   956: aload_2
    //   957: getfield 142	ao:n	I
    //   960: getstatic 232	s:ak	[I
    //   963: bipush 6
    //   965: iaload
    //   966: invokevirtual 267	dl:g	(II)V
    //   969: iinc 1 1
    //   972: ldc 1
    //   974: invokevirtual 300	java/lang/String:length	()I
    //   977: pop
    //   978: sipush 132
    //   981: sipush 148
    //   984: ixor
    //   985: bipush 82
    //   987: bipush 66
    //   989: ixor
    //   990: iconst_m1
    //   991: ixor
    //   992: iand
    //   993: ifeq -107 -> 886
    //   996: return
    //   997: getstatic 232	s:ak	[I
    //   1000: iconst_4
    //   1001: iaload
    //   1002: putstatic 233	s:al	I
    //   1005: ldc 1
    //   1007: invokevirtual 300	java/lang/String:length	()I
    //   1010: pop
    //   1011: bipush 61
    //   1013: bipush 50
    //   1015: ixor
    //   1016: sipush 148
    //   1019: sipush 155
    //   1022: ixor
    //   1023: iconst_m1
    //   1024: ixor
    //   1025: iand
    //   1026: ifeq +664 -> 1690
    //   1029: return
    //   1030: aload_0
    //   1031: getstatic 232	s:ak	[I
    //   1034: iconst_1
    //   1035: iaload
    //   1036: aaload
    //   1037: ldc 50
    //   1039: invokevirtual 297	java/lang/String:equals	(Ljava/lang/Object;)Z
    //   1042: invokestatic 329	s:d	(I)Z
    //   1045: ifeq +205 -> 1250
    //   1048: getstatic 156	cz:i	Z
    //   1051: invokestatic 341	s:j	(I)Z
    //   1054: ifeq +196 -> 1250
    //   1057: getstatic 152	cz:d	Ljava/lang/String;
    //   1060: ldc 28
    //   1062: invokestatic 272	dn:a	(Ljava/lang/String;Ljava/lang/String;)[Ljava/lang/String;
    //   1065: astore_1
    //   1066: getstatic 232	s:ak	[I
    //   1069: iconst_1
    //   1070: iaload
    //   1071: istore_2
    //   1072: iload_2
    //   1073: aload_1
    //   1074: arraylength
    //   1075: invokestatic 336	s:g	(II)Z
    //   1078: ifeq +30 -> 1108
    //   1081: aload_1
    //   1082: iload_2
    //   1083: aaload
    //   1084: ldc 96
    //   1086: invokestatic 273	dn:d	(Ljava/lang/String;Ljava/lang/String;)V
    //   1089: iinc 2 1
    //   1092: ldc 1
    //   1094: invokevirtual 300	java/lang/String:length	()I
    //   1097: pop
    //   1098: ldc 3
    //   1100: invokevirtual 300	java/lang/String:length	()I
    //   1103: ineg
    //   1104: iflt -32 -> 1072
    //   1107: return
    //   1108: getstatic 232	s:ak	[I
    //   1111: iconst_1
    //   1112: iaload
    //   1113: istore_2
    //   1114: iload_2
    //   1115: invokestatic 283	dt:g	()Ldt;
    //   1118: getfield 184	dt:w	[Lao;
    //   1121: arraylength
    //   1122: invokestatic 336	s:g	(II)Z
    //   1125: ifeq +97 -> 1222
    //   1128: invokestatic 283	dt:g	()Ldt;
    //   1131: getfield 184	dt:w	[Lao;
    //   1134: iload_2
    //   1135: aaload
    //   1136: dup
    //   1137: astore_3
    //   1138: invokestatic 325	s:a	(Ljava/lang/Object;)Z
    //   1141: ifeq +56 -> 1197
    //   1144: aload_3
    //   1145: getfield 140	ao:j	Lat;
    //   1148: getfield 145	at:b	B
    //   1151: getstatic 232	s:ak	[I
    //   1154: bipush 7
    //   1156: iaload
    //   1157: invokestatic 340	s:i	(II)Z
    //   1160: ifeq +37 -> 1197
    //   1163: aload_3
    //   1164: getfield 140	ao:j	Lat;
    //   1167: getfield 146	at:f	S
    //   1170: getstatic 232	s:ak	[I
    //   1173: iconst_3
    //   1174: iaload
    //   1175: invokestatic 332	s:e	(II)Z
    //   1178: ifeq +19 -> 1197
    //   1181: invokestatic 264	dl:ae	()Ldl;
    //   1184: aload_3
    //   1185: getfield 142	ao:n	I
    //   1188: getstatic 232	s:ak	[I
    //   1191: bipush 6
    //   1193: iaload
    //   1194: invokevirtual 267	dl:g	(II)V
    //   1197: iinc 2 1
    //   1200: ldc 1
    //   1202: invokevirtual 300	java/lang/String:length	()I
    //   1205: pop
    //   1206: bipush 34
    //   1208: bipush 116
    //   1210: ixor
    //   1211: bipush 64
    //   1213: bipush 18
    //   1215: ixor
    //   1216: ixor
    //   1217: ineg
    //   1218: iflt -104 -> 1114
    //   1221: return
    //   1222: getstatic 232	s:ak	[I
    //   1225: iconst_2
    //   1226: iaload
    //   1227: putstatic 233	s:al	I
    //   1230: ldc 1
    //   1232: invokevirtual 300	java/lang/String:length	()I
    //   1235: pop
    //   1236: ldc 5
    //   1238: invokevirtual 300	java/lang/String:length	()I
    //   1241: ldc 4
    //   1243: invokevirtual 300	java/lang/String:length	()I
    //   1246: if_icmpgt +444 -> 1690
    //   1249: return
    //   1250: aload_0
    //   1251: getstatic 232	s:ak	[I
    //   1254: iconst_1
    //   1255: iaload
    //   1256: aaload
    //   1257: ldc 82
    //   1259: invokevirtual 297	java/lang/String:equals	(Ljava/lang/Object;)Z
    //   1262: invokestatic 329	s:d	(I)Z
    //   1265: ifeq +171 -> 1436
    //   1268: getstatic 154	cz:g	Z
    //   1271: invokestatic 341	s:j	(I)Z
    //   1274: ifeq +162 -> 1436
    //   1277: getstatic 232	s:ak	[I
    //   1280: bipush 6
    //   1282: iaload
    //   1283: putstatic 167	dt:bb	Z
    //   1286: getstatic 232	s:ak	[I
    //   1289: bipush 6
    //   1291: iaload
    //   1292: putstatic 182	dt:h	Z
    //   1295: getstatic 232	s:ak	[I
    //   1298: bipush 6
    //   1300: iaload
    //   1301: putstatic 171	dt:dj	Z
    //   1304: getstatic 232	s:ak	[I
    //   1307: iconst_1
    //   1308: iaload
    //   1309: istore_1
    //   1310: iload_1
    //   1311: invokestatic 283	dt:g	()Ldt;
    //   1314: getfield 184	dt:w	[Lao;
    //   1317: arraylength
    //   1318: invokestatic 336	s:g	(II)Z
    //   1321: ifeq +86 -> 1407
    //   1324: invokestatic 283	dt:g	()Ldt;
    //   1327: getfield 184	dt:w	[Lao;
    //   1330: iload_1
    //   1331: aaload
    //   1332: dup
    //   1333: astore_2
    //   1334: invokestatic 325	s:a	(Ljava/lang/Object;)Z
    //   1337: ifeq +56 -> 1393
    //   1340: aload_2
    //   1341: getfield 140	ao:j	Lat;
    //   1344: getfield 145	at:b	B
    //   1347: getstatic 232	s:ak	[I
    //   1350: bipush 7
    //   1352: iaload
    //   1353: invokestatic 340	s:i	(II)Z
    //   1356: ifeq +37 -> 1393
    //   1359: aload_2
    //   1360: getfield 140	ao:j	Lat;
    //   1363: getfield 146	at:f	S
    //   1366: getstatic 232	s:ak	[I
    //   1369: iconst_3
    //   1370: iaload
    //   1371: invokestatic 332	s:e	(II)Z
    //   1374: ifeq +19 -> 1393
    //   1377: invokestatic 264	dl:ae	()Ldl;
    //   1380: aload_2
    //   1381: getfield 142	ao:n	I
    //   1384: getstatic 232	s:ak	[I
    //   1387: bipush 6
    //   1389: iaload
    //   1390: invokevirtual 267	dl:g	(II)V
    //   1393: iinc 1 1
    //   1396: ldc 1
    //   1398: invokevirtual 300	java/lang/String:length	()I
    //   1401: pop
    //   1402: aconst_null
    //   1403: ifnull -93 -> 1310
    //   1406: return
    //   1407: getstatic 232	s:ak	[I
    //   1410: bipush 9
    //   1412: iaload
    //   1413: putstatic 233	s:al	I
    //   1416: ldc 1
    //   1418: invokevirtual 300	java/lang/String:length	()I
    //   1421: pop
    //   1422: ldc 3
    //   1424: invokevirtual 300	java/lang/String:length	()I
    //   1427: ldc 5
    //   1429: invokevirtual 300	java/lang/String:length	()I
    //   1432: if_icmple +258 -> 1690
    //   1435: return
    //   1436: aload_0
    //   1437: getstatic 232	s:ak	[I
    //   1440: iconst_1
    //   1441: iaload
    //   1442: aaload
    //   1443: ldc 55
    //   1445: invokevirtual 297	java/lang/String:equals	(Ljava/lang/Object;)Z
    //   1448: invokestatic 329	s:d	(I)Z
    //   1451: ifeq +231 -> 1682
    //   1454: getstatic 155	cz:h	Z
    //   1457: invokestatic 341	s:j	(I)Z
    //   1460: ifeq +222 -> 1682
    //   1463: getstatic 152	cz:d	Ljava/lang/String;
    //   1466: ldc 28
    //   1468: invokestatic 272	dn:a	(Ljava/lang/String;Ljava/lang/String;)[Ljava/lang/String;
    //   1471: astore_1
    //   1472: getstatic 232	s:ak	[I
    //   1475: iconst_1
    //   1476: iaload
    //   1477: istore_2
    //   1478: iload_2
    //   1479: aload_1
    //   1480: arraylength
    //   1481: invokestatic 336	s:g	(II)Z
    //   1484: ifeq +25 -> 1509
    //   1487: aload_1
    //   1488: iload_2
    //   1489: aaload
    //   1490: ldc 95
    //   1492: invokestatic 273	dn:d	(Ljava/lang/String;Ljava/lang/String;)V
    //   1495: iinc 2 1
    //   1498: ldc 1
    //   1500: invokevirtual 300	java/lang/String:length	()I
    //   1503: pop
    //   1504: aconst_null
    //   1505: ifnull -27 -> 1478
    //   1508: return
    //   1509: getstatic 232	s:ak	[I
    //   1512: iconst_1
    //   1513: iaload
    //   1514: istore_2
    //   1515: iload_2
    //   1516: invokestatic 283	dt:g	()Ldt;
    //   1519: getfield 184	dt:w	[Lao;
    //   1522: arraylength
    //   1523: invokestatic 336	s:g	(II)Z
    //   1526: ifeq +127 -> 1653
    //   1529: invokestatic 283	dt:g	()Ldt;
    //   1532: getfield 184	dt:w	[Lao;
    //   1535: iload_2
    //   1536: aaload
    //   1537: dup
    //   1538: astore_3
    //   1539: invokestatic 325	s:a	(Ljava/lang/Object;)Z
    //   1542: ifeq +56 -> 1598
    //   1545: aload_3
    //   1546: getfield 140	ao:j	Lat;
    //   1549: getfield 145	at:b	B
    //   1552: getstatic 232	s:ak	[I
    //   1555: bipush 7
    //   1557: iaload
    //   1558: invokestatic 340	s:i	(II)Z
    //   1561: ifeq +37 -> 1598
    //   1564: aload_3
    //   1565: getfield 140	ao:j	Lat;
    //   1568: getfield 146	at:f	S
    //   1571: getstatic 232	s:ak	[I
    //   1574: iconst_3
    //   1575: iaload
    //   1576: invokestatic 332	s:e	(II)Z
    //   1579: ifeq +19 -> 1598
    //   1582: invokestatic 264	dl:ae	()Ldl;
    //   1585: aload_3
    //   1586: getfield 142	ao:n	I
    //   1589: getstatic 232	s:ak	[I
    //   1592: bipush 6
    //   1594: iaload
    //   1595: invokevirtual 267	dl:g	(II)V
    //   1598: iinc 2 1
    //   1601: ldc 1
    //   1603: invokevirtual 300	java/lang/String:length	()I
    //   1606: pop
    //   1607: bipush 49
    //   1609: bipush 104
    //   1611: ixor
    //   1612: sipush 218
    //   1615: sipush 178
    //   1618: ixor
    //   1619: ixor
    //   1620: sipush 237
    //   1623: sipush 174
    //   1626: ixor
    //   1627: sipush 206
    //   1630: sipush 188
    //   1633: ixor
    //   1634: ixor
    //   1635: ldc 3
    //   1637: invokevirtual 300	java/lang/String:length	()I
    //   1640: ineg
    //   1641: ixor
    //   1642: iand
    //   1643: ldc 3
    //   1645: invokevirtual 300	java/lang/String:length	()I
    //   1648: ineg
    //   1649: if_icmpne -134 -> 1515
    //   1652: return
    //   1653: getstatic 232	s:ak	[I
    //   1656: bipush 10
    //   1658: iaload
    //   1659: putstatic 233	s:al	I
    //   1662: ldc 1
    //   1664: invokevirtual 300	java/lang/String:length	()I
    //   1667: pop
    //   1668: bipush 54
    //   1670: bipush 50
    //   1672: ixor
    //   1673: ldc 3
    //   1675: invokevirtual 300	java/lang/String:length	()I
    //   1678: if_icmpge +12 -> 1690
    //   1681: return
    //   1682: getstatic 232	s:ak	[I
    //   1685: iconst_1
    //   1686: iaload
    //   1687: putstatic 233	s:al	I
    //   1690: getstatic 233	s:al	I
    //   1693: invokestatic 329	s:d	(I)Z
    //   1696: ifeq +2384 -> 4080
    //   1699: getstatic 233	s:al	I
    //   1702: getstatic 232	s:ak	[I
    //   1705: iconst_4
    //   1706: iaload
    //   1707: invokestatic 336	s:g	(II)Z
    //   1710: ifeq +454 -> 2164
    //   1713: aload_0
    //   1714: getstatic 232	s:ak	[I
    //   1717: bipush 6
    //   1719: iaload
    //   1720: aaload
    //   1721: ldc 36
    //   1723: invokevirtual 301	java/lang/String:startsWith	(Ljava/lang/String;)Z
    //   1726: invokestatic 329	s:d	(I)Z
    //   1729: ifeq +400 -> 2129
    //   1732: aload_0
    //   1733: getstatic 232	s:ak	[I
    //   1736: bipush 8
    //   1738: iaload
    //   1739: aaload
    //   1740: ldc 37
    //   1742: invokevirtual 301	java/lang/String:startsWith	(Ljava/lang/String;)Z
    //   1745: invokestatic 329	s:d	(I)Z
    //   1748: ifeq +381 -> 2129
    //   1751: getstatic 232	s:ak	[I
    //   1754: iconst_1
    //   1755: iaload
    //   1756: putstatic 168	dt:bc	Z
    //   1759: aload_0
    //   1760: getstatic 232	s:ak	[I
    //   1763: bipush 6
    //   1765: iaload
    //   1766: aaload
    //   1767: getstatic 232	s:ak	[I
    //   1770: bipush 11
    //   1772: iaload
    //   1773: aload_0
    //   1774: getstatic 232	s:ak	[I
    //   1777: bipush 6
    //   1779: iaload
    //   1780: aaload
    //   1781: invokevirtual 300	java/lang/String:length	()I
    //   1784: invokevirtual 303	java/lang/String:substring	(II)Ljava/lang/String;
    //   1787: astore_1
    //   1788: aload_0
    //   1789: getstatic 232	s:ak	[I
    //   1792: bipush 8
    //   1794: iaload
    //   1795: aaload
    //   1796: getstatic 232	s:ak	[I
    //   1799: bipush 12
    //   1801: iaload
    //   1802: invokevirtual 302	java/lang/String:substring	(I)Ljava/lang/String;
    //   1805: invokevirtual 304	java/lang/String:trim	()Ljava/lang/String;
    //   1808: dup
    //   1809: astore_2
    //   1810: getstatic 232	s:ak	[I
    //   1813: bipush 13
    //   1815: iaload
    //   1816: invokevirtual 298	java/lang/String:indexOf	(I)I
    //   1819: istore 4
    //   1821: aload_2
    //   1822: getstatic 232	s:ak	[I
    //   1825: iconst_1
    //   1826: iaload
    //   1827: iload 4
    //   1829: invokevirtual 303	java/lang/String:substring	(II)Ljava/lang/String;
    //   1832: astore_3
    //   1833: aload_2
    //   1834: iload 4
    //   1836: getstatic 232	s:ak	[I
    //   1839: bipush 6
    //   1841: iaload
    //   1842: iadd
    //   1843: aload_2
    //   1844: getstatic 232	s:ak	[I
    //   1847: bipush 14
    //   1849: iaload
    //   1850: invokevirtual 298	java/lang/String:indexOf	(I)I
    //   1853: invokevirtual 303	java/lang/String:substring	(II)Ljava/lang/String;
    //   1856: astore_2
    //   1857: aload_3
    //   1858: invokestatic 295	java/lang/Integer:parseInt	(Ljava/lang/String;)I
    //   1861: dup
    //   1862: putstatic 241	s:z	I
    //   1865: putstatic 223	s:ab	I
    //   1868: aload_2
    //   1869: invokestatic 295	java/lang/Integer:parseInt	(Ljava/lang/String;)I
    //   1872: dup
    //   1873: putstatic 231	s:aj	I
    //   1876: putstatic 228	s:ag	I
    //   1879: getstatic 217	java/lang/System:out	Ljava/io/PrintStream;
    //   1882: new 124	java/lang/StringBuffer
    //   1885: dup
    //   1886: ldc 83
    //   1888: invokespecial 306	java/lang/StringBuffer:<init>	(Ljava/lang/String;)V
    //   1891: aload_1
    //   1892: invokevirtual 308	java/lang/StringBuffer:append	(Ljava/lang/String;)Ljava/lang/StringBuffer;
    //   1895: ldc 17
    //   1897: invokevirtual 308	java/lang/StringBuffer:append	(Ljava/lang/String;)Ljava/lang/StringBuffer;
    //   1900: invokestatic 283	dt:g	()Ldt;
    //   1903: getfield 175	dt:el	I
    //   1906: invokevirtual 307	java/lang/StringBuffer:append	(I)Ljava/lang/StringBuffer;
    //   1909: invokevirtual 309	java/lang/StringBuffer:toString	()Ljava/lang/String;
    //   1912: invokevirtual 293	java/io/PrintStream:println	(Ljava/lang/String;)V
    //   1915: aload_1
    //   1916: invokestatic 283	dt:g	()Ldt;
    //   1919: getfield 175	dt:el	I
    //   1922: i2b
    //   1923: invokestatic 248	bw:a	(Ljava/lang/String;B)Lat;
    //   1926: dup
    //   1927: putstatic 238	s:w	Lat;
    //   1930: invokestatic 326	s:b	(Ljava/lang/Object;)Z
    //   1933: ifeq +11 -> 1944
    //   1936: new 119	java/lang/Exception
    //   1939: dup
    //   1940: invokespecial 294	java/lang/Exception:<init>	()V
    //   1943: athrow
    //   1944: getstatic 217	java/lang/System:out	Ljava/io/PrintStream;
    //   1947: new 124	java/lang/StringBuffer
    //   1950: dup
    //   1951: ldc 57
    //   1953: invokespecial 306	java/lang/StringBuffer:<init>	(Ljava/lang/String;)V
    //   1956: getstatic 238	s:w	Lat;
    //   1959: getfield 146	at:f	S
    //   1962: invokevirtual 307	java/lang/StringBuffer:append	(I)Ljava/lang/StringBuffer;
    //   1965: ldc 24
    //   1967: invokevirtual 308	java/lang/StringBuffer:append	(Ljava/lang/String;)Ljava/lang/StringBuffer;
    //   1970: getstatic 238	s:w	Lat;
    //   1973: getfield 145	at:b	B
    //   1976: invokevirtual 307	java/lang/StringBuffer:append	(I)Ljava/lang/StringBuffer;
    //   1979: ldc 21
    //   1981: invokevirtual 308	java/lang/StringBuffer:append	(Ljava/lang/String;)Ljava/lang/StringBuffer;
    //   1984: getstatic 238	s:w	Lat;
    //   1987: getfield 144	at:a	Ljava/lang/String;
    //   1990: invokevirtual 308	java/lang/StringBuffer:append	(Ljava/lang/String;)Ljava/lang/StringBuffer;
    //   1993: ldc 20
    //   1995: invokevirtual 308	java/lang/StringBuffer:append	(Ljava/lang/String;)Ljava/lang/StringBuffer;
    //   1998: aload_3
    //   1999: invokevirtual 308	java/lang/StringBuffer:append	(Ljava/lang/String;)Ljava/lang/StringBuffer;
    //   2002: ldc 19
    //   2004: invokevirtual 308	java/lang/StringBuffer:append	(Ljava/lang/String;)Ljava/lang/StringBuffer;
    //   2007: aload_2
    //   2008: invokevirtual 308	java/lang/StringBuffer:append	(Ljava/lang/String;)Ljava/lang/StringBuffer;
    //   2011: invokevirtual 309	java/lang/StringBuffer:toString	()Ljava/lang/String;
    //   2014: invokevirtual 293	java/io/PrintStream:println	(Ljava/lang/String;)V
    //   2017: aload_0
    //   2018: arraylength
    //   2019: getstatic 232	s:ak	[I
    //   2022: iconst_4
    //   2023: iaload
    //   2024: invokestatic 330	s:d	(II)Z
    //   2027: ifeq +30 -> 2057
    //   2030: aload_0
    //   2031: getstatic 232	s:ak	[I
    //   2034: iconst_3
    //   2035: iaload
    //   2036: aaload
    //   2037: ldc 33
    //   2039: invokevirtual 297	java/lang/String:equals	(Ljava/lang/Object;)Z
    //   2042: invokestatic 329	s:d	(I)Z
    //   2045: ifeq +12 -> 2057
    //   2048: getstatic 232	s:ak	[I
    //   2051: bipush 6
    //   2053: iaload
    //   2054: putstatic 235	s:an	Z
    //   2057: ldc 1
    //   2059: invokevirtual 300	java/lang/String:length	()I
    //   2062: pop
    //   2063: bipush 54
    //   2065: sipush 128
    //   2068: iadd
    //   2069: bipush 67
    //   2071: isub
    //   2072: bipush 44
    //   2074: iadd
    //   2075: bipush 26
    //   2077: bipush 75
    //   2079: iadd
    //   2080: bipush -33
    //   2082: isub
    //   2083: bipush 21
    //   2085: iadd
    //   2086: ixor
    //   2087: ldc 5
    //   2089: invokevirtual 300	java/lang/String:length	()I
    //   2092: if_icmpgt +1953 -> 4045
    //   2095: return
    //   2096: ldc 1
    //   2098: invokevirtual 300	java/lang/String:length	()I
    //   2101: pop2
    //   2102: ldc 56
    //   2104: invokestatic 288	fn:a	(Ljava/lang/String;)V
    //   2107: getstatic 232	s:ak	[I
    //   2110: bipush 6
    //   2112: iaload
    //   2113: putstatic 226	s:ae	Z
    //   2116: ldc 1
    //   2118: invokevirtual 300	java/lang/String:length	()I
    //   2121: pop
    //   2122: iconst_5
    //   2123: iconst_0
    //   2124: ixor
    //   2125: ifgt +1920 -> 4045
    //   2128: return
    //   2129: ldc 56
    //   2131: invokestatic 288	fn:a	(Ljava/lang/String;)V
    //   2134: getstatic 232	s:ak	[I
    //   2137: bipush 6
    //   2139: iaload
    //   2140: putstatic 226	s:ae	Z
    //   2143: ldc 1
    //   2145: invokevirtual 300	java/lang/String:length	()I
    //   2148: pop
    //   2149: ldc 3
    //   2151: invokevirtual 300	java/lang/String:length	()I
    //   2154: ineg
    //   2155: ldc 3
    //   2157: invokevirtual 300	java/lang/String:length	()I
    //   2160: if_icmplt +1885 -> 4045
    //   2163: return
    //   2164: getstatic 233	s:al	I
    //   2167: getstatic 232	s:ak	[I
    //   2170: iconst_4
    //   2171: iaload
    //   2172: invokestatic 340	s:i	(II)Z
    //   2175: ifeq +537 -> 2712
    //   2178: aload_0
    //   2179: getstatic 232	s:ak	[I
    //   2182: bipush 6
    //   2184: iaload
    //   2185: aaload
    //   2186: ldc 36
    //   2188: invokevirtual 301	java/lang/String:startsWith	(Ljava/lang/String;)Z
    //   2191: invokestatic 329	s:d	(I)Z
    //   2194: ifeq +480 -> 2674
    //   2197: aload_0
    //   2198: getstatic 232	s:ak	[I
    //   2201: bipush 8
    //   2203: iaload
    //   2204: aaload
    //   2205: ldc 35
    //   2207: invokevirtual 301	java/lang/String:startsWith	(Ljava/lang/String;)Z
    //   2210: invokestatic 329	s:d	(I)Z
    //   2213: ifeq +461 -> 2674
    //   2216: getstatic 232	s:ak	[I
    //   2219: bipush 6
    //   2221: iaload
    //   2222: putstatic 168	dt:bc	Z
    //   2225: getstatic 232	s:ak	[I
    //   2228: iconst_4
    //   2229: iaload
    //   2230: putstatic 176	dt:er	I
    //   2233: aload_0
    //   2234: getstatic 232	s:ak	[I
    //   2237: bipush 6
    //   2239: iaload
    //   2240: aaload
    //   2241: getstatic 232	s:ak	[I
    //   2244: bipush 11
    //   2246: iaload
    //   2247: aload_0
    //   2248: getstatic 232	s:ak	[I
    //   2251: bipush 6
    //   2253: iaload
    //   2254: aaload
    //   2255: invokevirtual 300	java/lang/String:length	()I
    //   2258: invokevirtual 303	java/lang/String:substring	(II)Ljava/lang/String;
    //   2261: astore_1
    //   2262: aload_0
    //   2263: getstatic 232	s:ak	[I
    //   2266: bipush 8
    //   2268: iaload
    //   2269: aaload
    //   2270: getstatic 232	s:ak	[I
    //   2273: bipush 15
    //   2275: iaload
    //   2276: invokevirtual 302	java/lang/String:substring	(I)Ljava/lang/String;
    //   2279: invokevirtual 304	java/lang/String:trim	()Ljava/lang/String;
    //   2282: dup
    //   2283: astore_2
    //   2284: getstatic 232	s:ak	[I
    //   2287: bipush 13
    //   2289: iaload
    //   2290: invokevirtual 298	java/lang/String:indexOf	(I)I
    //   2293: istore 4
    //   2295: aload_2
    //   2296: getstatic 232	s:ak	[I
    //   2299: iconst_1
    //   2300: iaload
    //   2301: iload 4
    //   2303: invokevirtual 303	java/lang/String:substring	(II)Ljava/lang/String;
    //   2306: astore_3
    //   2307: aload_2
    //   2308: iload 4
    //   2310: getstatic 232	s:ak	[I
    //   2313: bipush 6
    //   2315: iaload
    //   2316: iadd
    //   2317: aload_2
    //   2318: getstatic 232	s:ak	[I
    //   2321: bipush 14
    //   2323: iaload
    //   2324: invokevirtual 298	java/lang/String:indexOf	(I)I
    //   2327: invokevirtual 303	java/lang/String:substring	(II)Ljava/lang/String;
    //   2330: astore_2
    //   2331: aload_3
    //   2332: invokestatic 295	java/lang/Integer:parseInt	(Ljava/lang/String;)I
    //   2335: dup
    //   2336: putstatic 241	s:z	I
    //   2339: putstatic 223	s:ab	I
    //   2342: aload_2
    //   2343: invokestatic 295	java/lang/Integer:parseInt	(Ljava/lang/String;)I
    //   2346: dup
    //   2347: putstatic 231	s:aj	I
    //   2350: putstatic 228	s:ag	I
    //   2353: getstatic 217	java/lang/System:out	Ljava/io/PrintStream;
    //   2356: new 124	java/lang/StringBuffer
    //   2359: dup
    //   2360: ldc 83
    //   2362: invokespecial 306	java/lang/StringBuffer:<init>	(Ljava/lang/String;)V
    //   2365: aload_1
    //   2366: invokevirtual 308	java/lang/StringBuffer:append	(Ljava/lang/String;)Ljava/lang/StringBuffer;
    //   2369: ldc 17
    //   2371: invokevirtual 308	java/lang/StringBuffer:append	(Ljava/lang/String;)Ljava/lang/StringBuffer;
    //   2374: invokestatic 283	dt:g	()Ldt;
    //   2377: getfield 175	dt:el	I
    //   2380: invokevirtual 307	java/lang/StringBuffer:append	(I)Ljava/lang/StringBuffer;
    //   2383: invokevirtual 309	java/lang/StringBuffer:toString	()Ljava/lang/String;
    //   2386: invokevirtual 293	java/io/PrintStream:println	(Ljava/lang/String;)V
    //   2389: aload_1
    //   2390: invokestatic 283	dt:g	()Ldt;
    //   2393: getfield 175	dt:el	I
    //   2396: i2b
    //   2397: invokestatic 248	bw:a	(Ljava/lang/String;B)Lat;
    //   2400: dup
    //   2401: putstatic 238	s:w	Lat;
    //   2404: invokestatic 326	s:b	(Ljava/lang/Object;)Z
    //   2407: ifeq +11 -> 2418
    //   2410: new 119	java/lang/Exception
    //   2413: dup
    //   2414: invokespecial 294	java/lang/Exception:<init>	()V
    //   2417: athrow
    //   2418: ldc 58
    //   2420: invokestatic 283	dt:g	()Ldt;
    //   2423: getfield 175	dt:el	I
    //   2426: i2b
    //   2427: invokestatic 248	bw:a	(Ljava/lang/String;B)Lat;
    //   2430: dup
    //   2431: putstatic 239	s:x	Lat;
    //   2434: invokestatic 326	s:b	(Ljava/lang/Object;)Z
    //   2437: ifeq +11 -> 2448
    //   2440: new 119	java/lang/Exception
    //   2443: dup
    //   2444: invokespecial 294	java/lang/Exception:<init>	()V
    //   2447: athrow
    //   2448: getstatic 217	java/lang/System:out	Ljava/io/PrintStream;
    //   2451: new 124	java/lang/StringBuffer
    //   2454: dup
    //   2455: ldc 57
    //   2457: invokespecial 306	java/lang/StringBuffer:<init>	(Ljava/lang/String;)V
    //   2460: getstatic 238	s:w	Lat;
    //   2463: getfield 146	at:f	S
    //   2466: invokevirtual 307	java/lang/StringBuffer:append	(I)Ljava/lang/StringBuffer;
    //   2469: ldc 24
    //   2471: invokevirtual 308	java/lang/StringBuffer:append	(Ljava/lang/String;)Ljava/lang/StringBuffer;
    //   2474: getstatic 238	s:w	Lat;
    //   2477: getfield 145	at:b	B
    //   2480: invokevirtual 307	java/lang/StringBuffer:append	(I)Ljava/lang/StringBuffer;
    //   2483: ldc 21
    //   2485: invokevirtual 308	java/lang/StringBuffer:append	(Ljava/lang/String;)Ljava/lang/StringBuffer;
    //   2488: getstatic 238	s:w	Lat;
    //   2491: getfield 144	at:a	Ljava/lang/String;
    //   2494: invokevirtual 308	java/lang/StringBuffer:append	(Ljava/lang/String;)Ljava/lang/StringBuffer;
    //   2497: ldc 20
    //   2499: invokevirtual 308	java/lang/StringBuffer:append	(Ljava/lang/String;)Ljava/lang/StringBuffer;
    //   2502: aload_3
    //   2503: invokevirtual 308	java/lang/StringBuffer:append	(Ljava/lang/String;)Ljava/lang/StringBuffer;
    //   2506: ldc 19
    //   2508: invokevirtual 308	java/lang/StringBuffer:append	(Ljava/lang/String;)Ljava/lang/StringBuffer;
    //   2511: aload_2
    //   2512: invokevirtual 308	java/lang/StringBuffer:append	(Ljava/lang/String;)Ljava/lang/StringBuffer;
    //   2515: invokevirtual 309	java/lang/StringBuffer:toString	()Ljava/lang/String;
    //   2518: invokevirtual 293	java/io/PrintStream:println	(Ljava/lang/String;)V
    //   2521: aload_0
    //   2522: arraylength
    //   2523: getstatic 232	s:ak	[I
    //   2526: iconst_4
    //   2527: iaload
    //   2528: invokestatic 330	s:d	(II)Z
    //   2531: ifeq +30 -> 2561
    //   2534: aload_0
    //   2535: getstatic 232	s:ak	[I
    //   2538: iconst_3
    //   2539: iaload
    //   2540: aaload
    //   2541: ldc 33
    //   2543: invokevirtual 297	java/lang/String:equals	(Ljava/lang/Object;)Z
    //   2546: invokestatic 329	s:d	(I)Z
    //   2549: ifeq +12 -> 2561
    //   2552: getstatic 232	s:ak	[I
    //   2555: bipush 6
    //   2557: iaload
    //   2558: putstatic 235	s:an	Z
    //   2561: ldc 1
    //   2563: invokevirtual 300	java/lang/String:length	()I
    //   2566: pop
    //   2567: sipush 171
    //   2570: sipush 156
    //   2573: ixor
    //   2574: bipush 106
    //   2576: bipush 65
    //   2578: ixor
    //   2579: ixor
    //   2580: bipush 94
    //   2582: bipush 54
    //   2584: iadd
    //   2585: bipush 23
    //   2587: isub
    //   2588: bipush 51
    //   2590: iadd
    //   2591: bipush 119
    //   2593: bipush 75
    //   2595: iadd
    //   2596: bipush 27
    //   2598: isub
    //   2599: iconst_5
    //   2600: iadd
    //   2601: ixor
    //   2602: ldc 3
    //   2604: invokevirtual 300	java/lang/String:length	()I
    //   2607: ineg
    //   2608: ixor
    //   2609: iand
    //   2610: ldc 3
    //   2612: invokevirtual 300	java/lang/String:length	()I
    //   2615: ineg
    //   2616: if_icmpne +1429 -> 4045
    //   2619: return
    //   2620: ldc 1
    //   2622: invokevirtual 300	java/lang/String:length	()I
    //   2625: pop2
    //   2626: ldc 56
    //   2628: invokestatic 288	fn:a	(Ljava/lang/String;)V
    //   2631: getstatic 232	s:ak	[I
    //   2634: bipush 6
    //   2636: iaload
    //   2637: putstatic 226	s:ae	Z
    //   2640: ldc 1
    //   2642: invokevirtual 300	java/lang/String:length	()I
    //   2645: pop
    //   2646: bipush 7
    //   2648: bipush 69
    //   2650: iadd
    //   2651: bipush -58
    //   2653: isub
    //   2654: bipush 41
    //   2656: iadd
    //   2657: bipush 100
    //   2659: bipush 115
    //   2661: iadd
    //   2662: bipush 84
    //   2664: isub
    //   2665: bipush 40
    //   2667: iadd
    //   2668: ixor
    //   2669: ineg
    //   2670: ifle +1375 -> 4045
    //   2673: return
    //   2674: ldc 56
    //   2676: invokestatic 288	fn:a	(Ljava/lang/String;)V
    //   2679: getstatic 232	s:ak	[I
    //   2682: bipush 6
    //   2684: iaload
    //   2685: putstatic 226	s:ae	Z
    //   2688: ldc 1
    //   2690: invokevirtual 300	java/lang/String:length	()I
    //   2693: pop
    //   2694: bipush 108
    //   2696: bipush 68
    //   2698: ixor
    //   2699: sipush 179
    //   2702: sipush 159
    //   2705: ixor
    //   2706: ixor
    //   2707: ineg
    //   2708: iflt +1337 -> 4045
    //   2711: return
    //   2712: getstatic 233	s:al	I
    //   2715: getstatic 232	s:ak	[I
    //   2718: iconst_2
    //   2719: iaload
    //   2720: invokestatic 340	s:i	(II)Z
    //   2723: ifeq +440 -> 3163
    //   2726: getstatic 232	s:ak	[I
    //   2729: iconst_1
    //   2730: iaload
    //   2731: putstatic 168	dt:bc	Z
    //   2734: aload_0
    //   2735: getstatic 232	s:ak	[I
    //   2738: bipush 6
    //   2740: iaload
    //   2741: aaload
    //   2742: ldc 36
    //   2744: invokevirtual 301	java/lang/String:startsWith	(Ljava/lang/String;)Z
    //   2747: invokestatic 329	s:d	(I)Z
    //   2750: ifeq +379 -> 3129
    //   2753: aload_0
    //   2754: getstatic 232	s:ak	[I
    //   2757: bipush 8
    //   2759: iaload
    //   2760: aaload
    //   2761: ldc 30
    //   2763: invokevirtual 301	java/lang/String:startsWith	(Ljava/lang/String;)Z
    //   2766: invokestatic 329	s:d	(I)Z
    //   2769: ifeq +360 -> 3129
    //   2772: aload_0
    //   2773: getstatic 232	s:ak	[I
    //   2776: bipush 6
    //   2778: iaload
    //   2779: aaload
    //   2780: getstatic 232	s:ak	[I
    //   2783: bipush 11
    //   2785: iaload
    //   2786: aload_0
    //   2787: getstatic 232	s:ak	[I
    //   2790: bipush 6
    //   2792: iaload
    //   2793: aaload
    //   2794: invokevirtual 300	java/lang/String:length	()I
    //   2797: invokevirtual 303	java/lang/String:substring	(II)Ljava/lang/String;
    //   2800: astore_1
    //   2801: aload_0
    //   2802: getstatic 232	s:ak	[I
    //   2805: bipush 8
    //   2807: iaload
    //   2808: aaload
    //   2809: getstatic 232	s:ak	[I
    //   2812: bipush 16
    //   2814: iaload
    //   2815: invokevirtual 302	java/lang/String:substring	(I)Ljava/lang/String;
    //   2818: invokevirtual 304	java/lang/String:trim	()Ljava/lang/String;
    //   2821: dup
    //   2822: astore_2
    //   2823: getstatic 232	s:ak	[I
    //   2826: bipush 13
    //   2828: iaload
    //   2829: invokevirtual 298	java/lang/String:indexOf	(I)I
    //   2832: istore 4
    //   2834: aload_2
    //   2835: getstatic 232	s:ak	[I
    //   2838: iconst_1
    //   2839: iaload
    //   2840: iload 4
    //   2842: invokevirtual 303	java/lang/String:substring	(II)Ljava/lang/String;
    //   2845: astore_3
    //   2846: aload_2
    //   2847: iload 4
    //   2849: getstatic 232	s:ak	[I
    //   2852: bipush 6
    //   2854: iaload
    //   2855: iadd
    //   2856: aload_2
    //   2857: getstatic 232	s:ak	[I
    //   2860: bipush 14
    //   2862: iaload
    //   2863: invokevirtual 298	java/lang/String:indexOf	(I)I
    //   2866: invokevirtual 303	java/lang/String:substring	(II)Ljava/lang/String;
    //   2869: astore_2
    //   2870: aload_3
    //   2871: invokestatic 295	java/lang/Integer:parseInt	(Ljava/lang/String;)I
    //   2874: putstatic 241	s:z	I
    //   2877: aload_2
    //   2878: invokestatic 295	java/lang/Integer:parseInt	(Ljava/lang/String;)I
    //   2881: putstatic 231	s:aj	I
    //   2884: getstatic 217	java/lang/System:out	Ljava/io/PrintStream;
    //   2887: new 124	java/lang/StringBuffer
    //   2890: dup
    //   2891: ldc 83
    //   2893: invokespecial 306	java/lang/StringBuffer:<init>	(Ljava/lang/String;)V
    //   2896: aload_1
    //   2897: invokevirtual 308	java/lang/StringBuffer:append	(Ljava/lang/String;)Ljava/lang/StringBuffer;
    //   2900: ldc 17
    //   2902: invokevirtual 308	java/lang/StringBuffer:append	(Ljava/lang/String;)Ljava/lang/StringBuffer;
    //   2905: invokestatic 283	dt:g	()Ldt;
    //   2908: getfield 175	dt:el	I
    //   2911: invokevirtual 307	java/lang/StringBuffer:append	(I)Ljava/lang/StringBuffer;
    //   2914: invokevirtual 309	java/lang/StringBuffer:toString	()Ljava/lang/String;
    //   2917: invokevirtual 293	java/io/PrintStream:println	(Ljava/lang/String;)V
    //   2920: aload_1
    //   2921: invokestatic 283	dt:g	()Ldt;
    //   2924: getfield 175	dt:el	I
    //   2927: i2b
    //   2928: invokestatic 248	bw:a	(Ljava/lang/String;B)Lat;
    //   2931: dup
    //   2932: putstatic 238	s:w	Lat;
    //   2935: invokestatic 326	s:b	(Ljava/lang/Object;)Z
    //   2938: ifeq +11 -> 2949
    //   2941: new 119	java/lang/Exception
    //   2944: dup
    //   2945: invokespecial 294	java/lang/Exception:<init>	()V
    //   2948: athrow
    //   2949: getstatic 217	java/lang/System:out	Ljava/io/PrintStream;
    //   2952: new 124	java/lang/StringBuffer
    //   2955: dup
    //   2956: ldc 57
    //   2958: invokespecial 306	java/lang/StringBuffer:<init>	(Ljava/lang/String;)V
    //   2961: getstatic 238	s:w	Lat;
    //   2964: getfield 146	at:f	S
    //   2967: invokevirtual 307	java/lang/StringBuffer:append	(I)Ljava/lang/StringBuffer;
    //   2970: ldc 24
    //   2972: invokevirtual 308	java/lang/StringBuffer:append	(Ljava/lang/String;)Ljava/lang/StringBuffer;
    //   2975: getstatic 238	s:w	Lat;
    //   2978: getfield 145	at:b	B
    //   2981: invokevirtual 307	java/lang/StringBuffer:append	(I)Ljava/lang/StringBuffer;
    //   2984: ldc 21
    //   2986: invokevirtual 308	java/lang/StringBuffer:append	(Ljava/lang/String;)Ljava/lang/StringBuffer;
    //   2989: getstatic 238	s:w	Lat;
    //   2992: getfield 144	at:a	Ljava/lang/String;
    //   2995: invokevirtual 308	java/lang/StringBuffer:append	(Ljava/lang/String;)Ljava/lang/StringBuffer;
    //   2998: ldc 20
    //   3000: invokevirtual 308	java/lang/StringBuffer:append	(Ljava/lang/String;)Ljava/lang/StringBuffer;
    //   3003: aload_3
    //   3004: invokevirtual 308	java/lang/StringBuffer:append	(Ljava/lang/String;)Ljava/lang/StringBuffer;
    //   3007: ldc 19
    //   3009: invokevirtual 308	java/lang/StringBuffer:append	(Ljava/lang/String;)Ljava/lang/StringBuffer;
    //   3012: aload_2
    //   3013: invokevirtual 308	java/lang/StringBuffer:append	(Ljava/lang/String;)Ljava/lang/StringBuffer;
    //   3016: invokevirtual 309	java/lang/StringBuffer:toString	()Ljava/lang/String;
    //   3019: invokevirtual 293	java/io/PrintStream:println	(Ljava/lang/String;)V
    //   3022: aload_0
    //   3023: arraylength
    //   3024: getstatic 232	s:ak	[I
    //   3027: iconst_4
    //   3028: iaload
    //   3029: invokestatic 330	s:d	(II)Z
    //   3032: ifeq +52 -> 3084
    //   3035: aload_0
    //   3036: getstatic 232	s:ak	[I
    //   3039: iconst_3
    //   3040: iaload
    //   3041: aaload
    //   3042: ldc 33
    //   3044: invokevirtual 297	java/lang/String:equals	(Ljava/lang/Object;)Z
    //   3047: invokestatic 329	s:d	(I)Z
    //   3050: ifeq +34 -> 3084
    //   3053: getstatic 232	s:ak	[I
    //   3056: bipush 6
    //   3058: iaload
    //   3059: putstatic 235	s:an	Z
    //   3062: ldc 1
    //   3064: invokevirtual 300	java/lang/String:length	()I
    //   3067: pop
    //   3068: ldc 3
    //   3070: invokevirtual 300	java/lang/String:length	()I
    //   3073: ineg
    //   3074: ldc 3
    //   3076: invokevirtual 300	java/lang/String:length	()I
    //   3079: ineg
    //   3080: if_icmpeq +965 -> 4045
    //   3083: return
    //   3084: getstatic 165	dn:z	Lah;
    //   3087: invokevirtual 243	ah:c	()V
    //   3090: ldc 1
    //   3092: invokevirtual 300	java/lang/String:length	()I
    //   3095: pop
    //   3096: bipush 40
    //   3098: bipush 125
    //   3100: iadd
    //   3101: bipush 66
    //   3103: isub
    //   3104: bipush 92
    //   3106: iadd
    //   3107: bipush 97
    //   3109: bipush 19
    //   3111: iadd
    //   3112: bipush -54
    //   3114: isub
    //   3115: bipush 17
    //   3117: iadd
    //   3118: ixor
    //   3119: ifge +926 -> 4045
    //   3122: return
    //   3123: ldc 1
    //   3125: invokevirtual 300	java/lang/String:length	()I
    //   3128: pop2
    //   3129: ldc 56
    //   3131: invokestatic 288	fn:a	(Ljava/lang/String;)V
    //   3134: getstatic 232	s:ak	[I
    //   3137: bipush 6
    //   3139: iaload
    //   3140: putstatic 226	s:ae	Z
    //   3143: ldc 1
    //   3145: invokevirtual 300	java/lang/String:length	()I
    //   3148: pop
    //   3149: ldc 4
    //   3151: invokevirtual 300	java/lang/String:length	()I
    //   3154: ldc 3
    //   3156: invokevirtual 300	java/lang/String:length	()I
    //   3159: if_icmpge +886 -> 4045
    //   3162: return
    //   3163: getstatic 233	s:al	I
    //   3166: getstatic 232	s:ak	[I
    //   3169: bipush 9
    //   3171: iaload
    //   3172: invokestatic 340	s:i	(II)Z
    //   3175: ifeq +453 -> 3628
    //   3178: aload_0
    //   3179: getstatic 232	s:ak	[I
    //   3182: bipush 6
    //   3184: iaload
    //   3185: aaload
    //   3186: ldc 36
    //   3188: invokevirtual 301	java/lang/String:startsWith	(Ljava/lang/String;)Z
    //   3191: invokestatic 329	s:d	(I)Z
    //   3194: ifeq +405 -> 3599
    //   3197: aload_0
    //   3198: getstatic 232	s:ak	[I
    //   3201: bipush 8
    //   3203: iaload
    //   3204: aaload
    //   3205: ldc 34
    //   3207: invokevirtual 301	java/lang/String:startsWith	(Ljava/lang/String;)Z
    //   3210: invokestatic 329	s:d	(I)Z
    //   3213: ifeq +386 -> 3599
    //   3216: getstatic 232	s:ak	[I
    //   3219: iconst_1
    //   3220: iaload
    //   3221: putstatic 168	dt:bc	Z
    //   3224: aload_0
    //   3225: getstatic 232	s:ak	[I
    //   3228: bipush 6
    //   3230: iaload
    //   3231: aaload
    //   3232: getstatic 232	s:ak	[I
    //   3235: bipush 11
    //   3237: iaload
    //   3238: aload_0
    //   3239: getstatic 232	s:ak	[I
    //   3242: bipush 6
    //   3244: iaload
    //   3245: aaload
    //   3246: invokevirtual 300	java/lang/String:length	()I
    //   3249: invokevirtual 303	java/lang/String:substring	(II)Ljava/lang/String;
    //   3252: astore_1
    //   3253: aload_0
    //   3254: getstatic 232	s:ak	[I
    //   3257: bipush 8
    //   3259: iaload
    //   3260: aaload
    //   3261: getstatic 232	s:ak	[I
    //   3264: bipush 9
    //   3266: iaload
    //   3267: invokevirtual 302	java/lang/String:substring	(I)Ljava/lang/String;
    //   3270: invokevirtual 304	java/lang/String:trim	()Ljava/lang/String;
    //   3273: dup
    //   3274: astore_2
    //   3275: getstatic 232	s:ak	[I
    //   3278: bipush 13
    //   3280: iaload
    //   3281: invokevirtual 298	java/lang/String:indexOf	(I)I
    //   3284: istore 4
    //   3286: aload_2
    //   3287: getstatic 232	s:ak	[I
    //   3290: iconst_1
    //   3291: iaload
    //   3292: iload 4
    //   3294: invokevirtual 303	java/lang/String:substring	(II)Ljava/lang/String;
    //   3297: astore_3
    //   3298: aload_2
    //   3299: iload 4
    //   3301: getstatic 232	s:ak	[I
    //   3304: bipush 6
    //   3306: iaload
    //   3307: iadd
    //   3308: aload_2
    //   3309: getstatic 232	s:ak	[I
    //   3312: bipush 14
    //   3314: iaload
    //   3315: invokevirtual 298	java/lang/String:indexOf	(I)I
    //   3318: invokevirtual 303	java/lang/String:substring	(II)Ljava/lang/String;
    //   3321: astore_2
    //   3322: aload_3
    //   3323: invokestatic 295	java/lang/Integer:parseInt	(Ljava/lang/String;)I
    //   3326: dup
    //   3327: putstatic 241	s:z	I
    //   3330: putstatic 223	s:ab	I
    //   3333: aload_2
    //   3334: invokestatic 295	java/lang/Integer:parseInt	(Ljava/lang/String;)I
    //   3337: dup
    //   3338: putstatic 231	s:aj	I
    //   3341: putstatic 228	s:ag	I
    //   3344: getstatic 217	java/lang/System:out	Ljava/io/PrintStream;
    //   3347: new 124	java/lang/StringBuffer
    //   3350: dup
    //   3351: ldc 83
    //   3353: invokespecial 306	java/lang/StringBuffer:<init>	(Ljava/lang/String;)V
    //   3356: aload_1
    //   3357: invokevirtual 308	java/lang/StringBuffer:append	(Ljava/lang/String;)Ljava/lang/StringBuffer;
    //   3360: ldc 17
    //   3362: invokevirtual 308	java/lang/StringBuffer:append	(Ljava/lang/String;)Ljava/lang/StringBuffer;
    //   3365: invokestatic 283	dt:g	()Ldt;
    //   3368: getfield 175	dt:el	I
    //   3371: invokevirtual 307	java/lang/StringBuffer:append	(I)Ljava/lang/StringBuffer;
    //   3374: invokevirtual 309	java/lang/StringBuffer:toString	()Ljava/lang/String;
    //   3377: invokevirtual 293	java/io/PrintStream:println	(Ljava/lang/String;)V
    //   3380: aload_1
    //   3381: invokestatic 283	dt:g	()Ldt;
    //   3384: getfield 175	dt:el	I
    //   3387: i2b
    //   3388: invokestatic 248	bw:a	(Ljava/lang/String;B)Lat;
    //   3391: dup
    //   3392: putstatic 238	s:w	Lat;
    //   3395: invokestatic 326	s:b	(Ljava/lang/Object;)Z
    //   3398: ifeq +11 -> 3409
    //   3401: new 119	java/lang/Exception
    //   3404: dup
    //   3405: invokespecial 294	java/lang/Exception:<init>	()V
    //   3408: athrow
    //   3409: getstatic 217	java/lang/System:out	Ljava/io/PrintStream;
    //   3412: new 124	java/lang/StringBuffer
    //   3415: dup
    //   3416: ldc 99
    //   3418: invokespecial 306	java/lang/StringBuffer:<init>	(Ljava/lang/String;)V
    //   3421: getstatic 223	s:ab	I
    //   3424: invokevirtual 307	java/lang/StringBuffer:append	(I)Ljava/lang/StringBuffer;
    //   3427: ldc 15
    //   3429: invokevirtual 308	java/lang/StringBuffer:append	(Ljava/lang/String;)Ljava/lang/StringBuffer;
    //   3432: getstatic 228	s:ag	I
    //   3435: invokevirtual 307	java/lang/StringBuffer:append	(I)Ljava/lang/StringBuffer;
    //   3438: ldc 57
    //   3440: invokevirtual 308	java/lang/StringBuffer:append	(Ljava/lang/String;)Ljava/lang/StringBuffer;
    //   3443: getstatic 238	s:w	Lat;
    //   3446: getfield 146	at:f	S
    //   3449: invokevirtual 307	java/lang/StringBuffer:append	(I)Ljava/lang/StringBuffer;
    //   3452: ldc 24
    //   3454: invokevirtual 308	java/lang/StringBuffer:append	(Ljava/lang/String;)Ljava/lang/StringBuffer;
    //   3457: getstatic 238	s:w	Lat;
    //   3460: getfield 145	at:b	B
    //   3463: invokevirtual 307	java/lang/StringBuffer:append	(I)Ljava/lang/StringBuffer;
    //   3466: ldc 21
    //   3468: invokevirtual 308	java/lang/StringBuffer:append	(Ljava/lang/String;)Ljava/lang/StringBuffer;
    //   3471: getstatic 238	s:w	Lat;
    //   3474: getfield 144	at:a	Ljava/lang/String;
    //   3477: invokevirtual 308	java/lang/StringBuffer:append	(Ljava/lang/String;)Ljava/lang/StringBuffer;
    //   3480: ldc 20
    //   3482: invokevirtual 308	java/lang/StringBuffer:append	(Ljava/lang/String;)Ljava/lang/StringBuffer;
    //   3485: aload_3
    //   3486: invokevirtual 308	java/lang/StringBuffer:append	(Ljava/lang/String;)Ljava/lang/StringBuffer;
    //   3489: ldc 19
    //   3491: invokevirtual 308	java/lang/StringBuffer:append	(Ljava/lang/String;)Ljava/lang/StringBuffer;
    //   3494: aload_2
    //   3495: invokevirtual 308	java/lang/StringBuffer:append	(Ljava/lang/String;)Ljava/lang/StringBuffer;
    //   3498: invokevirtual 309	java/lang/StringBuffer:toString	()Ljava/lang/String;
    //   3501: invokevirtual 293	java/io/PrintStream:println	(Ljava/lang/String;)V
    //   3504: aload_0
    //   3505: arraylength
    //   3506: getstatic 232	s:ak	[I
    //   3509: iconst_4
    //   3510: iaload
    //   3511: invokestatic 330	s:d	(II)Z
    //   3514: ifeq +30 -> 3544
    //   3517: aload_0
    //   3518: getstatic 232	s:ak	[I
    //   3521: iconst_3
    //   3522: iaload
    //   3523: aaload
    //   3524: ldc 33
    //   3526: invokevirtual 297	java/lang/String:equals	(Ljava/lang/Object;)Z
    //   3529: invokestatic 329	s:d	(I)Z
    //   3532: ifeq +12 -> 3544
    //   3535: getstatic 232	s:ak	[I
    //   3538: bipush 6
    //   3540: iaload
    //   3541: putstatic 235	s:an	Z
    //   3544: ldc 1
    //   3546: invokevirtual 300	java/lang/String:length	()I
    //   3549: pop
    //   3550: ldc 4
    //   3552: invokevirtual 300	java/lang/String:length	()I
    //   3555: bipush 31
    //   3557: bipush 27
    //   3559: ixor
    //   3560: if_icmpne +485 -> 4045
    //   3563: return
    //   3564: ldc 1
    //   3566: invokevirtual 300	java/lang/String:length	()I
    //   3569: pop2
    //   3570: ldc 56
    //   3572: invokestatic 288	fn:a	(Ljava/lang/String;)V
    //   3575: getstatic 232	s:ak	[I
    //   3578: bipush 6
    //   3580: iaload
    //   3581: putstatic 226	s:ae	Z
    //   3584: ldc 1
    //   3586: invokevirtual 300	java/lang/String:length	()I
    //   3589: pop
    //   3590: bipush 54
    //   3592: bipush 50
    //   3594: ixor
    //   3595: ifge +450 -> 4045
    //   3598: return
    //   3599: ldc 56
    //   3601: invokestatic 288	fn:a	(Ljava/lang/String;)V
    //   3604: getstatic 232	s:ak	[I
    //   3607: bipush 6
    //   3609: iaload
    //   3610: putstatic 226	s:ae	Z
    //   3613: ldc 1
    //   3615: invokevirtual 300	java/lang/String:length	()I
    //   3618: pop
    //   3619: ldc 3
    //   3621: invokevirtual 300	java/lang/String:length	()I
    //   3624: ifne +421 -> 4045
    //   3627: return
    //   3628: getstatic 233	s:al	I
    //   3631: getstatic 232	s:ak	[I
    //   3634: bipush 10
    //   3636: iaload
    //   3637: invokestatic 340	s:i	(II)Z
    //   3640: ifeq +405 -> 4045
    //   3643: aload_0
    //   3644: getstatic 232	s:ak	[I
    //   3647: bipush 6
    //   3649: iaload
    //   3650: aaload
    //   3651: ldc 36
    //   3653: invokevirtual 301	java/lang/String:startsWith	(Ljava/lang/String;)Z
    //   3656: invokestatic 329	s:d	(I)Z
    //   3659: ifeq +372 -> 4031
    //   3662: aload_0
    //   3663: getstatic 232	s:ak	[I
    //   3666: bipush 8
    //   3668: iaload
    //   3669: aaload
    //   3670: ldc 32
    //   3672: invokevirtual 301	java/lang/String:startsWith	(Ljava/lang/String;)Z
    //   3675: invokestatic 329	s:d	(I)Z
    //   3678: ifeq +353 -> 4031
    //   3681: getstatic 232	s:ak	[I
    //   3684: iconst_1
    //   3685: iaload
    //   3686: putstatic 168	dt:bc	Z
    //   3689: aload_0
    //   3690: getstatic 232	s:ak	[I
    //   3693: bipush 6
    //   3695: iaload
    //   3696: aaload
    //   3697: getstatic 232	s:ak	[I
    //   3700: bipush 11
    //   3702: iaload
    //   3703: aload_0
    //   3704: getstatic 232	s:ak	[I
    //   3707: bipush 6
    //   3709: iaload
    //   3710: aaload
    //   3711: invokevirtual 300	java/lang/String:length	()I
    //   3714: invokevirtual 303	java/lang/String:substring	(II)Ljava/lang/String;
    //   3717: astore_1
    //   3718: aload_0
    //   3719: getstatic 232	s:ak	[I
    //   3722: bipush 8
    //   3724: iaload
    //   3725: aaload
    //   3726: getstatic 232	s:ak	[I
    //   3729: bipush 17
    //   3731: iaload
    //   3732: invokevirtual 302	java/lang/String:substring	(I)Ljava/lang/String;
    //   3735: invokevirtual 304	java/lang/String:trim	()Ljava/lang/String;
    //   3738: dup
    //   3739: astore_2
    //   3740: getstatic 232	s:ak	[I
    //   3743: bipush 13
    //   3745: iaload
    //   3746: invokevirtual 298	java/lang/String:indexOf	(I)I
    //   3749: istore 4
    //   3751: aload_2
    //   3752: getstatic 232	s:ak	[I
    //   3755: iconst_1
    //   3756: iaload
    //   3757: iload 4
    //   3759: invokevirtual 303	java/lang/String:substring	(II)Ljava/lang/String;
    //   3762: astore_3
    //   3763: aload_2
    //   3764: iload 4
    //   3766: getstatic 232	s:ak	[I
    //   3769: bipush 6
    //   3771: iaload
    //   3772: iadd
    //   3773: aload_2
    //   3774: getstatic 232	s:ak	[I
    //   3777: bipush 14
    //   3779: iaload
    //   3780: invokevirtual 298	java/lang/String:indexOf	(I)I
    //   3783: invokevirtual 303	java/lang/String:substring	(II)Ljava/lang/String;
    //   3786: astore_2
    //   3787: aload_3
    //   3788: invokestatic 295	java/lang/Integer:parseInt	(Ljava/lang/String;)I
    //   3791: dup
    //   3792: putstatic 241	s:z	I
    //   3795: putstatic 223	s:ab	I
    //   3798: aload_2
    //   3799: invokestatic 295	java/lang/Integer:parseInt	(Ljava/lang/String;)I
    //   3802: dup
    //   3803: putstatic 231	s:aj	I
    //   3806: putstatic 228	s:ag	I
    //   3809: getstatic 217	java/lang/System:out	Ljava/io/PrintStream;
    //   3812: new 124	java/lang/StringBuffer
    //   3815: dup
    //   3816: ldc 83
    //   3818: invokespecial 306	java/lang/StringBuffer:<init>	(Ljava/lang/String;)V
    //   3821: aload_1
    //   3822: invokevirtual 308	java/lang/StringBuffer:append	(Ljava/lang/String;)Ljava/lang/StringBuffer;
    //   3825: ldc 17
    //   3827: invokevirtual 308	java/lang/StringBuffer:append	(Ljava/lang/String;)Ljava/lang/StringBuffer;
    //   3830: invokestatic 283	dt:g	()Ldt;
    //   3833: getfield 175	dt:el	I
    //   3836: invokevirtual 307	java/lang/StringBuffer:append	(I)Ljava/lang/StringBuffer;
    //   3839: invokevirtual 309	java/lang/StringBuffer:toString	()Ljava/lang/String;
    //   3842: invokevirtual 293	java/io/PrintStream:println	(Ljava/lang/String;)V
    //   3845: aload_1
    //   3846: invokestatic 283	dt:g	()Ldt;
    //   3849: getfield 175	dt:el	I
    //   3852: i2b
    //   3853: invokestatic 248	bw:a	(Ljava/lang/String;B)Lat;
    //   3856: dup
    //   3857: putstatic 238	s:w	Lat;
    //   3860: invokestatic 326	s:b	(Ljava/lang/Object;)Z
    //   3863: ifeq +11 -> 3874
    //   3866: new 119	java/lang/Exception
    //   3869: dup
    //   3870: invokespecial 294	java/lang/Exception:<init>	()V
    //   3873: athrow
    //   3874: getstatic 217	java/lang/System:out	Ljava/io/PrintStream;
    //   3877: new 124	java/lang/StringBuffer
    //   3880: dup
    //   3881: ldc 57
    //   3883: invokespecial 306	java/lang/StringBuffer:<init>	(Ljava/lang/String;)V
    //   3886: getstatic 238	s:w	Lat;
    //   3889: getfield 146	at:f	S
    //   3892: invokevirtual 307	java/lang/StringBuffer:append	(I)Ljava/lang/StringBuffer;
    //   3895: ldc 24
    //   3897: invokevirtual 308	java/lang/StringBuffer:append	(Ljava/lang/String;)Ljava/lang/StringBuffer;
    //   3900: getstatic 238	s:w	Lat;
    //   3903: getfield 145	at:b	B
    //   3906: invokevirtual 307	java/lang/StringBuffer:append	(I)Ljava/lang/StringBuffer;
    //   3909: ldc 21
    //   3911: invokevirtual 308	java/lang/StringBuffer:append	(Ljava/lang/String;)Ljava/lang/StringBuffer;
    //   3914: getstatic 238	s:w	Lat;
    //   3917: getfield 144	at:a	Ljava/lang/String;
    //   3920: invokevirtual 308	java/lang/StringBuffer:append	(Ljava/lang/String;)Ljava/lang/StringBuffer;
    //   3923: ldc 20
    //   3925: invokevirtual 308	java/lang/StringBuffer:append	(Ljava/lang/String;)Ljava/lang/StringBuffer;
    //   3928: aload_3
    //   3929: invokevirtual 308	java/lang/StringBuffer:append	(Ljava/lang/String;)Ljava/lang/StringBuffer;
    //   3932: ldc 19
    //   3934: invokevirtual 308	java/lang/StringBuffer:append	(Ljava/lang/String;)Ljava/lang/StringBuffer;
    //   3937: aload_2
    //   3938: invokevirtual 308	java/lang/StringBuffer:append	(Ljava/lang/String;)Ljava/lang/StringBuffer;
    //   3941: invokevirtual 309	java/lang/StringBuffer:toString	()Ljava/lang/String;
    //   3944: invokevirtual 293	java/io/PrintStream:println	(Ljava/lang/String;)V
    //   3947: aload_0
    //   3948: arraylength
    //   3949: getstatic 232	s:ak	[I
    //   3952: iconst_4
    //   3953: iaload
    //   3954: invokestatic 330	s:d	(II)Z
    //   3957: ifeq +30 -> 3987
    //   3960: aload_0
    //   3961: getstatic 232	s:ak	[I
    //   3964: iconst_3
    //   3965: iaload
    //   3966: aaload
    //   3967: ldc 33
    //   3969: invokevirtual 297	java/lang/String:equals	(Ljava/lang/Object;)Z
    //   3972: invokestatic 329	s:d	(I)Z
    //   3975: ifeq +12 -> 3987
    //   3978: getstatic 232	s:ak	[I
    //   3981: bipush 6
    //   3983: iaload
    //   3984: putstatic 235	s:an	Z
    //   3987: ldc 1
    //   3989: invokevirtual 300	java/lang/String:length	()I
    //   3992: pop
    //   3993: ldc 3
    //   3995: invokevirtual 300	java/lang/String:length	()I
    //   3998: ineg
    //   3999: iconst_3
    //   4000: bipush 74
    //   4002: iadd
    //   4003: bipush -2
    //   4005: isub
    //   4006: bipush 54
    //   4008: iadd
    //   4009: bipush 45
    //   4011: bipush 56
    //   4013: iadd
    //   4014: bipush -2
    //   4016: isub
    //   4017: bipush 26
    //   4019: iadd
    //   4020: ixor
    //   4021: if_icmplt +24 -> 4045
    //   4024: return
    //   4025: ldc 1
    //   4027: invokevirtual 300	java/lang/String:length	()I
    //   4030: pop2
    //   4031: ldc 56
    //   4033: invokestatic 288	fn:a	(Ljava/lang/String;)V
    //   4036: getstatic 232	s:ak	[I
    //   4039: bipush 6
    //   4041: iaload
    //   4042: putstatic 226	s:ae	Z
    //   4045: getstatic 238	s:w	Lat;
    //   4048: invokestatic 325	s:a	(Ljava/lang/Object;)Z
    //   4051: ifeq +29 -> 4080
    //   4054: getstatic 238	s:w	Lat;
    //   4057: getfield 147	at:i	B
    //   4060: invokestatic 283	dt:g	()Ldt;
    //   4063: getfield 166	dt:ap	I
    //   4066: invokestatic 328	s:c	(II)Z
    //   4069: ifeq +11 -> 4080
    //   4072: getstatic 232	s:ak	[I
    //   4075: iconst_1
    //   4076: iaload
    //   4077: putstatic 233	s:al	I
    //   4080: invokestatic 254	cn:e	()V
    //   4083: return
    // Local variable table:
    //   start	length	slot	name	signature
    //   0	4084	0	paramString	String
    //   303	667	1	i	int
    //   1065	17	1	arrayOfString	String[]
    //   1309	85	1	j	int
    //   1471	2375	1	localObject1	Object
    //   327	630	2	localao1	ao
    //   1071	127	2	k	int
    //   1333	48	2	localao2	ao
    //   1477	122	2	m	int
    //   1809	2129	2	str	String
    //   1137	2792	3	localObject2	Object
    //   1819	1954	4	n	int
    //   2096	1	12	localException1	Exception
    //   2620	1	13	localException2	Exception
    //   3123	1	14	localException3	Exception
    //   3564	1	15	localException4	Exception
    //   4025	1	16	localException5	Exception
    // Exception table:
    //   from	to	target	type
    //   1857	2057	2096	java/lang/Exception
    //   2331	2561	2620	java/lang/Exception
    //   2870	3090	3123	java/lang/Exception
    //   3322	3544	3564	java/lang/Exception
    //   3787	3987	4025	java/lang/Exception
  }
  
  /* Error */
  public final void b()
  {
    // Byte code:
    //   0: invokestatic 320	r:k	()Z
    //   3: invokestatic 329	s:d	(I)Z
    //   6: ifeq +12 -> 18
    //   9: getstatic 232	s:ak	[I
    //   12: iconst_1
    //   13: iaload
    //   14: invokestatic 316	r:a	(Z)V
    //   17: return
    //   18: getstatic 224	s:ac	Z
    //   21: invokestatic 329	s:d	(I)Z
    //   24: ifeq +67 -> 91
    //   27: ldc 93
    //   29: invokestatic 288	fn:a	(Ljava/lang/String;)V
    //   32: aload_0
    //   33: getfield 219	r:i	Lr;
    //   36: invokestatic 325	s:a	(Ljava/lang/Object;)Z
    //   39: ifeq +48 -> 87
    //   42: aload_0
    //   43: getfield 219	r:i	Lr;
    //   46: instanceof 129
    //   49: invokestatic 341	s:j	(I)Z
    //   52: ifeq +35 -> 87
    //   55: ldc2_w 138
    //   58: invokestatic 311	java/lang/Thread:sleep	(J)V
    //   61: ldc 1
    //   63: invokevirtual 300	java/lang/String:length	()I
    //   66: pop
    //   67: bipush 82
    //   69: bipush 86
    //   71: ixor
    //   72: ineg
    //   73: ifle +10 -> 83
    //   76: return
    //   77: ldc 1
    //   79: invokevirtual 300	java/lang/String:length	()I
    //   82: pop2
    //   83: invokestatic 274	dn:o	()V
    //   86: return
    //   87: invokestatic 275	dn:r	()V
    //   90: return
    //   91: getstatic 233	s:al	I
    //   94: invokestatic 339	s:i	(I)Z
    //   97: ifeq +1820 -> 1917
    //   100: getstatic 235	s:an	Z
    //   103: invokestatic 341	s:j	(I)Z
    //   106: ifeq +1811 -> 1917
    //   109: getstatic 226	s:ae	Z
    //   112: invokestatic 341	s:j	(I)Z
    //   115: ifeq +1802 -> 1917
    //   118: getstatic 233	s:al	I
    //   121: getstatic 232	s:ak	[I
    //   124: iconst_4
    //   125: iaload
    //   126: invokestatic 336	s:g	(II)Z
    //   129: ifeq +405 -> 534
    //   132: invokestatic 283	dt:g	()Ldt;
    //   135: getfield 183	dt:s	[Lao;
    //   138: getstatic 238	s:w	Lat;
    //   141: getfield 145	at:b	B
    //   144: aaload
    //   145: invokestatic 325	s:a	(Ljava/lang/Object;)Z
    //   148: ifeq +342 -> 490
    //   151: invokestatic 283	dt:g	()Ldt;
    //   154: getfield 183	dt:s	[Lao;
    //   157: getstatic 238	s:w	Lat;
    //   160: getfield 145	at:b	B
    //   163: aaload
    //   164: getfield 140	ao:j	Lat;
    //   167: getfield 146	at:f	S
    //   170: getstatic 238	s:w	Lat;
    //   173: getfield 146	at:f	S
    //   176: invokestatic 340	s:i	(II)Z
    //   179: ifeq +311 -> 490
    //   182: getstatic 149	cz:a	I
    //   185: invokestatic 339	s:i	(I)Z
    //   188: ifeq +28 -> 216
    //   191: getstatic 149	cz:a	I
    //   194: dup
    //   195: istore_1
    //   196: ldc 1
    //   198: invokevirtual 300	java/lang/String:length	()I
    //   201: pop
    //   202: ldc 5
    //   204: invokevirtual 300	java/lang/String:length	()I
    //   207: bipush 25
    //   209: bipush 29
    //   211: ixor
    //   212: if_icmple +96 -> 308
    //   215: return
    //   216: getstatic 232	s:ak	[I
    //   219: iconst_1
    //   220: iaload
    //   221: invokestatic 285	dt:k	(I)Lfb;
    //   224: dup
    //   225: astore_1
    //   226: invokestatic 325	s:a	(Ljava/lang/Object;)Z
    //   229: ifeq +72 -> 301
    //   232: aload_1
    //   233: getfield 187	fb:f	I
    //   236: dup
    //   237: istore_1
    //   238: ldc 1
    //   240: invokevirtual 300	java/lang/String:length	()I
    //   243: pop
    //   244: ldc 5
    //   246: invokevirtual 300	java/lang/String:length	()I
    //   249: sipush 203
    //   252: sipush 175
    //   255: ixor
    //   256: sipush 204
    //   259: sipush 143
    //   262: ixor
    //   263: ixor
    //   264: bipush 114
    //   266: sipush 147
    //   269: iadd
    //   270: sipush 139
    //   273: isub
    //   274: bipush 39
    //   276: iadd
    //   277: bipush 91
    //   279: bipush 30
    //   281: iadd
    //   282: bipush 50
    //   284: isub
    //   285: bipush 63
    //   287: iadd
    //   288: ixor
    //   289: ldc 3
    //   291: invokevirtual 300	java/lang/String:length	()I
    //   294: ineg
    //   295: ixor
    //   296: iand
    //   297: if_icmpne +11 -> 308
    //   300: return
    //   301: getstatic 232	s:ak	[I
    //   304: iconst_5
    //   305: iaload
    //   306: dup
    //   307: istore_1
    //   308: istore_2
    //   309: iload_1
    //   310: i2s
    //   311: istore_1
    //   312: iload_2
    //   313: invokestatic 331	s:e	(I)Z
    //   316: ifeq +18 -> 334
    //   319: ldc 51
    //   321: invokestatic 288	fn:a	(Ljava/lang/String;)V
    //   324: getstatic 232	s:ak	[I
    //   327: bipush 6
    //   329: iaload
    //   330: putstatic 226	s:ae	Z
    //   333: return
    //   334: getstatic 185	et:o	S
    //   337: iload_1
    //   338: invokestatic 334	s:f	(II)Z
    //   341: ifeq +22 -> 363
    //   344: aload_0
    //   345: iload_1
    //   346: getstatic 157	cz:j	I
    //   349: getstatic 232	s:ak	[I
    //   352: iconst_5
    //   353: iaload
    //   354: getstatic 232	s:ak	[I
    //   357: iconst_5
    //   358: iaload
    //   359: invokevirtual 315	r:a	(IIII)V
    //   362: return
    //   363: getstatic 241	s:z	I
    //   366: getstatic 231	s:aj	I
    //   369: invokestatic 336	s:g	(II)Z
    //   372: ifeq +105 -> 477
    //   375: aload_0
    //   376: getstatic 232	s:ak	[I
    //   379: iconst_5
    //   380: iaload
    //   381: getstatic 233	s:al	I
    //   384: getstatic 232	s:ak	[I
    //   387: bipush 8
    //   389: iaload
    //   390: invokestatic 340	s:i	(II)Z
    //   393: ifeq +19 -> 412
    //   396: getstatic 232	s:ak	[I
    //   399: iconst_3
    //   400: iaload
    //   401: ldc 1
    //   403: invokevirtual 300	java/lang/String:length	()I
    //   406: pop
    //   407: aconst_null
    //   408: ifnull +56 -> 464
    //   411: return
    //   412: getstatic 233	s:al	I
    //   415: getstatic 232	s:ak	[I
    //   418: iconst_3
    //   419: iaload
    //   420: invokestatic 340	s:i	(II)Z
    //   423: ifeq +35 -> 458
    //   426: getstatic 232	s:ak	[I
    //   429: iconst_2
    //   430: iaload
    //   431: ldc 1
    //   433: invokevirtual 300	java/lang/String:length	()I
    //   436: pop
    //   437: bipush 66
    //   439: bipush 70
    //   441: ixor
    //   442: bipush 18
    //   444: iconst_0
    //   445: ixor
    //   446: bipush 29
    //   448: bipush 15
    //   450: ixor
    //   451: iconst_m1
    //   452: ixor
    //   453: iand
    //   454: if_icmpne +10 -> 464
    //   457: return
    //   458: getstatic 232	s:ak	[I
    //   461: bipush 6
    //   463: iaload
    //   464: invokevirtual 318	r:b	(II)V
    //   467: aload_0
    //   468: getstatic 232	s:ak	[I
    //   471: iconst_5
    //   472: iaload
    //   473: invokevirtual 319	r:c	(I)V
    //   476: return
    //   477: getstatic 232	s:ak	[I
    //   480: bipush 6
    //   482: iaload
    //   483: putstatic 235	s:an	Z
    //   486: invokestatic 322	r:n	()V
    //   489: return
    //   490: aload_0
    //   491: invokespecial 342	s:p	()Z
    //   494: invokestatic 329	s:d	(I)Z
    //   497: ifeq +2295 -> 2792
    //   500: new 124	java/lang/StringBuffer
    //   503: dup
    //   504: ldc 85
    //   506: invokespecial 306	java/lang/StringBuffer:<init>	(Ljava/lang/String;)V
    //   509: getstatic 238	s:w	Lat;
    //   512: getfield 144	at:a	Ljava/lang/String;
    //   515: invokevirtual 308	java/lang/StringBuffer:append	(Ljava/lang/String;)Ljava/lang/StringBuffer;
    //   518: invokevirtual 309	java/lang/StringBuffer:toString	()Ljava/lang/String;
    //   521: invokestatic 288	fn:a	(Ljava/lang/String;)V
    //   524: getstatic 232	s:ak	[I
    //   527: bipush 6
    //   529: iaload
    //   530: putstatic 226	s:ae	Z
    //   533: return
    //   534: getstatic 233	s:al	I
    //   537: getstatic 232	s:ak	[I
    //   540: iconst_4
    //   541: iaload
    //   542: invokestatic 340	s:i	(II)Z
    //   545: ifeq +266 -> 811
    //   548: invokestatic 283	dt:g	()Ldt;
    //   551: getfield 183	dt:s	[Lao;
    //   554: getstatic 238	s:w	Lat;
    //   557: getfield 145	at:b	B
    //   560: aaload
    //   561: invokestatic 325	s:a	(Ljava/lang/Object;)Z
    //   564: ifeq +204 -> 768
    //   567: invokestatic 283	dt:g	()Ldt;
    //   570: getfield 183	dt:s	[Lao;
    //   573: getstatic 238	s:w	Lat;
    //   576: getfield 145	at:b	B
    //   579: aaload
    //   580: getfield 140	ao:j	Lat;
    //   583: getfield 146	at:f	S
    //   586: getstatic 238	s:w	Lat;
    //   589: getfield 146	at:f	S
    //   592: invokestatic 340	s:i	(II)Z
    //   595: ifeq +173 -> 768
    //   598: getstatic 239	s:x	Lat;
    //   601: getfield 146	at:f	S
    //   604: invokestatic 280	dt:d	(I)I
    //   607: dup
    //   608: istore_1
    //   609: invokestatic 333	s:f	(I)Z
    //   612: ifeq +51 -> 663
    //   615: aload_0
    //   616: invokespecial 343	s:q	()Z
    //   619: ldc 1
    //   621: invokevirtual 300	java/lang/String:length	()I
    //   624: pop2
    //   625: ldc 1
    //   627: invokevirtual 300	java/lang/String:length	()I
    //   630: pop
    //   631: sipush 219
    //   634: sipush 187
    //   637: ixor
    //   638: bipush 32
    //   640: bipush 68
    //   642: ixor
    //   643: ixor
    //   644: sipush 200
    //   647: sipush 192
    //   650: ixor
    //   651: sipush 171
    //   654: sipush 167
    //   657: ixor
    //   658: ixor
    //   659: if_icmple +152 -> 811
    //   662: return
    //   663: getstatic 241	s:z	I
    //   666: getstatic 231	s:aj	I
    //   669: invokestatic 336	s:g	(II)Z
    //   672: ifeq +139 -> 811
    //   675: invokestatic 283	dt:g	()Ldt;
    //   678: getfield 184	dt:w	[Lao;
    //   681: iload_1
    //   682: aaload
    //   683: dup
    //   684: astore_2
    //   685: getfield 143	ao:r	I
    //   688: getstatic 232	s:ak	[I
    //   691: bipush 18
    //   693: iaload
    //   694: invokestatic 340	s:i	(II)Z
    //   697: ifeq +40 -> 737
    //   700: invokestatic 264	dl:ae	()Ldl;
    //   703: aload_2
    //   704: invokevirtual 260	dl:a	(Lao;)V
    //   707: invokestatic 253	cn:ae	()Z
    //   710: ldc 1
    //   712: invokevirtual 300	java/lang/String:length	()I
    //   715: pop2
    //   716: invokestatic 264	dl:ae	()Ldl;
    //   719: invokestatic 283	dt:g	()Ldt;
    //   722: getfield 169	dt:ci	Ljava/lang/String;
    //   725: invokevirtual 270	dl:r	(Ljava/lang/String;)V
    //   728: invokestatic 253	cn:ae	()Z
    //   731: ldc 1
    //   733: invokevirtual 300	java/lang/String:length	()I
    //   736: pop2
    //   737: aload_0
    //   738: aload_2
    //   739: getstatic 232	s:ak	[I
    //   742: bipush 18
    //   744: iaload
    //   745: invokespecial 324	s:a	(Lao;I)V
    //   748: ldc 1
    //   750: invokevirtual 300	java/lang/String:length	()I
    //   753: pop
    //   754: ldc 3
    //   756: invokevirtual 300	java/lang/String:length	()I
    //   759: ldc 4
    //   761: invokevirtual 300	java/lang/String:length	()I
    //   764: if_icmpne +47 -> 811
    //   767: return
    //   768: aload_0
    //   769: invokespecial 342	s:p	()Z
    //   772: invokestatic 329	s:d	(I)Z
    //   775: ifeq +36 -> 811
    //   778: new 124	java/lang/StringBuffer
    //   781: dup
    //   782: ldc 85
    //   784: invokespecial 306	java/lang/StringBuffer:<init>	(Ljava/lang/String;)V
    //   787: getstatic 238	s:w	Lat;
    //   790: getfield 144	at:a	Ljava/lang/String;
    //   793: invokevirtual 308	java/lang/StringBuffer:append	(Ljava/lang/String;)Ljava/lang/StringBuffer;
    //   796: invokevirtual 309	java/lang/StringBuffer:toString	()Ljava/lang/String;
    //   799: invokestatic 288	fn:a	(Ljava/lang/String;)V
    //   802: getstatic 232	s:ak	[I
    //   805: bipush 6
    //   807: iaload
    //   808: putstatic 226	s:ae	Z
    //   811: getstatic 233	s:al	I
    //   814: getstatic 232	s:ak	[I
    //   817: iconst_2
    //   818: iaload
    //   819: invokestatic 340	s:i	(II)Z
    //   822: ifeq +217 -> 1039
    //   825: getstatic 152	cz:d	Ljava/lang/String;
    //   828: ldc 28
    //   830: invokestatic 272	dn:a	(Ljava/lang/String;Ljava/lang/String;)[Ljava/lang/String;
    //   833: astore_3
    //   834: getstatic 232	s:ak	[I
    //   837: iconst_1
    //   838: iaload
    //   839: istore_1
    //   840: iload_1
    //   841: aload_3
    //   842: arraylength
    //   843: invokestatic 336	s:g	(II)Z
    //   846: ifeq +193 -> 1039
    //   849: aload_3
    //   850: iload_1
    //   851: aaload
    //   852: invokestatic 325	s:a	(Ljava/lang/Object;)Z
    //   855: ifeq +15 -> 870
    //   858: aload_3
    //   859: iload_1
    //   860: aaload
    //   861: invokevirtual 300	java/lang/String:length	()I
    //   864: invokestatic 341	s:j	(I)Z
    //   867: ifeq +18 -> 885
    //   870: ldc 64
    //   872: invokestatic 288	fn:a	(Ljava/lang/String;)V
    //   875: getstatic 232	s:ak	[I
    //   878: bipush 6
    //   880: iaload
    //   881: putstatic 226	s:ae	Z
    //   884: return
    //   885: invokestatic 283	dt:g	()Ldt;
    //   888: getfield 183	dt:s	[Lao;
    //   891: getstatic 238	s:w	Lat;
    //   894: getfield 145	at:b	B
    //   897: aaload
    //   898: invokestatic 325	s:a	(Ljava/lang/Object;)Z
    //   901: ifeq +72 -> 973
    //   904: invokestatic 283	dt:g	()Ldt;
    //   907: getfield 183	dt:s	[Lao;
    //   910: getstatic 238	s:w	Lat;
    //   913: getfield 145	at:b	B
    //   916: aaload
    //   917: getfield 140	ao:j	Lat;
    //   920: getfield 146	at:f	S
    //   923: getstatic 238	s:w	Lat;
    //   926: getfield 146	at:f	S
    //   929: invokestatic 340	s:i	(II)Z
    //   932: ifeq +41 -> 973
    //   935: getstatic 241	s:z	I
    //   938: getstatic 231	s:aj	I
    //   941: invokestatic 336	s:g	(II)Z
    //   944: ifeq +72 -> 1016
    //   947: getstatic 165	dn:z	Lah;
    //   950: invokevirtual 242	ah:b	()V
    //   953: ldc 1
    //   955: invokevirtual 300	java/lang/String:length	()I
    //   958: pop
    //   959: ldc 3
    //   961: invokevirtual 300	java/lang/String:length	()I
    //   964: ldc 5
    //   966: invokevirtual 300	java/lang/String:length	()I
    //   969: if_icmplt +47 -> 1016
    //   972: return
    //   973: aload_0
    //   974: invokespecial 342	s:p	()Z
    //   977: invokestatic 329	s:d	(I)Z
    //   980: ifeq +36 -> 1016
    //   983: new 124	java/lang/StringBuffer
    //   986: dup
    //   987: ldc 85
    //   989: invokespecial 306	java/lang/StringBuffer:<init>	(Ljava/lang/String;)V
    //   992: getstatic 238	s:w	Lat;
    //   995: getfield 144	at:a	Ljava/lang/String;
    //   998: invokevirtual 308	java/lang/StringBuffer:append	(Ljava/lang/String;)Ljava/lang/StringBuffer;
    //   1001: invokevirtual 309	java/lang/StringBuffer:toString	()Ljava/lang/String;
    //   1004: invokestatic 288	fn:a	(Ljava/lang/String;)V
    //   1007: getstatic 232	s:ak	[I
    //   1010: bipush 6
    //   1012: iaload
    //   1013: putstatic 226	s:ae	Z
    //   1016: iinc 1 1
    //   1019: ldc 1
    //   1021: invokevirtual 300	java/lang/String:length	()I
    //   1024: pop
    //   1025: ldc 4
    //   1027: invokevirtual 300	java/lang/String:length	()I
    //   1030: ldc 4
    //   1032: invokevirtual 300	java/lang/String:length	()I
    //   1035: if_icmpge -195 -> 840
    //   1038: return
    //   1039: getstatic 233	s:al	I
    //   1042: getstatic 232	s:ak	[I
    //   1045: bipush 9
    //   1047: iaload
    //   1048: invokestatic 340	s:i	(II)Z
    //   1051: ifeq +300 -> 1351
    //   1054: invokestatic 283	dt:g	()Ldt;
    //   1057: getfield 183	dt:s	[Lao;
    //   1060: getstatic 238	s:w	Lat;
    //   1063: getfield 145	at:b	B
    //   1066: aaload
    //   1067: invokestatic 325	s:a	(Ljava/lang/Object;)Z
    //   1070: ifeq +238 -> 1308
    //   1073: invokestatic 283	dt:g	()Ldt;
    //   1076: getfield 183	dt:s	[Lao;
    //   1079: getstatic 238	s:w	Lat;
    //   1082: getfield 145	at:b	B
    //   1085: aaload
    //   1086: getfield 140	ao:j	Lat;
    //   1089: getfield 146	at:f	S
    //   1092: getstatic 238	s:w	Lat;
    //   1095: getfield 146	at:f	S
    //   1098: invokestatic 340	s:i	(II)Z
    //   1101: ifeq +207 -> 1308
    //   1104: getstatic 149	cz:a	I
    //   1107: invokestatic 339	s:i	(I)Z
    //   1110: ifeq +23 -> 1133
    //   1113: getstatic 149	cz:a	I
    //   1116: dup
    //   1117: istore_1
    //   1118: ldc 1
    //   1120: invokevirtual 300	java/lang/String:length	()I
    //   1123: pop
    //   1124: ldc 5
    //   1126: invokevirtual 300	java/lang/String:length	()I
    //   1129: ifge +53 -> 1182
    //   1132: return
    //   1133: getstatic 232	s:ak	[I
    //   1136: iconst_1
    //   1137: iaload
    //   1138: invokestatic 285	dt:k	(I)Lfb;
    //   1141: dup
    //   1142: astore_1
    //   1143: invokestatic 325	s:a	(Ljava/lang/Object;)Z
    //   1146: ifeq +29 -> 1175
    //   1149: aload_1
    //   1150: getfield 187	fb:f	I
    //   1153: dup
    //   1154: istore_1
    //   1155: ldc 1
    //   1157: invokevirtual 300	java/lang/String:length	()I
    //   1160: pop
    //   1161: ldc 3
    //   1163: invokevirtual 300	java/lang/String:length	()I
    //   1166: ldc 5
    //   1168: invokevirtual 300	java/lang/String:length	()I
    //   1171: if_icmplt +11 -> 1182
    //   1174: return
    //   1175: getstatic 232	s:ak	[I
    //   1178: iconst_5
    //   1179: iaload
    //   1180: dup
    //   1181: istore_1
    //   1182: istore_2
    //   1183: iload_1
    //   1184: i2s
    //   1185: istore_1
    //   1186: iload_2
    //   1187: invokestatic 331	s:e	(I)Z
    //   1190: ifeq +18 -> 1208
    //   1193: ldc 51
    //   1195: invokestatic 288	fn:a	(Ljava/lang/String;)V
    //   1198: getstatic 232	s:ak	[I
    //   1201: bipush 6
    //   1203: iaload
    //   1204: putstatic 226	s:ae	Z
    //   1207: return
    //   1208: getstatic 185	et:o	S
    //   1211: iload_1
    //   1212: invokestatic 334	s:f	(II)Z
    //   1215: ifeq +22 -> 1237
    //   1218: aload_0
    //   1219: iload_1
    //   1220: getstatic 157	cz:j	I
    //   1223: getstatic 232	s:ak	[I
    //   1226: iconst_5
    //   1227: iaload
    //   1228: getstatic 232	s:ak	[I
    //   1231: iconst_5
    //   1232: iaload
    //   1233: invokevirtual 315	r:a	(IIII)V
    //   1236: return
    //   1237: getstatic 241	s:z	I
    //   1240: getstatic 231	s:aj	I
    //   1243: invokestatic 336	s:g	(II)Z
    //   1246: ifeq +35 -> 1281
    //   1249: aload_0
    //   1250: getstatic 232	s:ak	[I
    //   1253: iconst_5
    //   1254: iaload
    //   1255: aload_0
    //   1256: getstatic 167	dt:bb	Z
    //   1259: getstatic 182	dt:h	Z
    //   1262: getstatic 171	dt:dj	Z
    //   1265: invokevirtual 317	r:a	(ZZZ)I
    //   1268: invokevirtual 318	r:b	(II)V
    //   1271: aload_0
    //   1272: getstatic 232	s:ak	[I
    //   1275: iconst_5
    //   1276: iaload
    //   1277: invokevirtual 319	r:c	(I)V
    //   1280: return
    //   1281: getstatic 232	s:ak	[I
    //   1284: bipush 6
    //   1286: iaload
    //   1287: putstatic 235	s:an	Z
    //   1290: invokestatic 322	r:n	()V
    //   1293: ldc 1
    //   1295: invokevirtual 300	java/lang/String:length	()I
    //   1298: pop
    //   1299: ldc 5
    //   1301: invokevirtual 300	java/lang/String:length	()I
    //   1304: ifgt +47 -> 1351
    //   1307: return
    //   1308: aload_0
    //   1309: invokespecial 342	s:p	()Z
    //   1312: invokestatic 329	s:d	(I)Z
    //   1315: ifeq +36 -> 1351
    //   1318: new 124	java/lang/StringBuffer
    //   1321: dup
    //   1322: ldc 85
    //   1324: invokespecial 306	java/lang/StringBuffer:<init>	(Ljava/lang/String;)V
    //   1327: getstatic 238	s:w	Lat;
    //   1330: getfield 144	at:a	Ljava/lang/String;
    //   1333: invokevirtual 308	java/lang/StringBuffer:append	(Ljava/lang/String;)Ljava/lang/StringBuffer;
    //   1336: invokevirtual 309	java/lang/StringBuffer:toString	()Ljava/lang/String;
    //   1339: invokestatic 288	fn:a	(Ljava/lang/String;)V
    //   1342: getstatic 232	s:ak	[I
    //   1345: bipush 6
    //   1347: iaload
    //   1348: putstatic 226	s:ae	Z
    //   1351: getstatic 233	s:al	I
    //   1354: getstatic 232	s:ak	[I
    //   1357: bipush 10
    //   1359: iaload
    //   1360: invokestatic 340	s:i	(II)Z
    //   1363: ifeq +1429 -> 2792
    //   1366: invokestatic 283	dt:g	()Ldt;
    //   1369: getfield 183	dt:s	[Lao;
    //   1372: getstatic 238	s:w	Lat;
    //   1375: getfield 145	at:b	B
    //   1378: aaload
    //   1379: invokestatic 325	s:a	(Ljava/lang/Object;)Z
    //   1382: ifeq +491 -> 1873
    //   1385: invokestatic 283	dt:g	()Ldt;
    //   1388: getfield 183	dt:s	[Lao;
    //   1391: getstatic 238	s:w	Lat;
    //   1394: getfield 145	at:b	B
    //   1397: aaload
    //   1398: getfield 140	ao:j	Lat;
    //   1401: getfield 146	at:f	S
    //   1404: getstatic 238	s:w	Lat;
    //   1407: getfield 146	at:f	S
    //   1410: invokestatic 340	s:i	(II)Z
    //   1413: ifeq +460 -> 1873
    //   1416: getstatic 185	et:o	S
    //   1419: getstatic 150	cz:b	I
    //   1422: invokestatic 334	s:f	(II)Z
    //   1425: ifeq +24 -> 1449
    //   1428: aload_0
    //   1429: getstatic 150	cz:b	I
    //   1432: getstatic 153	cz:e	I
    //   1435: getstatic 232	s:ak	[I
    //   1438: iconst_5
    //   1439: iaload
    //   1440: getstatic 232	s:ak	[I
    //   1443: iconst_5
    //   1444: iaload
    //   1445: invokevirtual 315	r:a	(IIII)V
    //   1448: return
    //   1449: getstatic 241	s:z	I
    //   1452: getstatic 231	s:aj	I
    //   1455: invokestatic 336	s:g	(II)Z
    //   1458: ifeq +402 -> 1860
    //   1461: getstatic 232	s:ak	[I
    //   1464: iconst_1
    //   1465: iaload
    //   1466: istore_1
    //   1467: iload_1
    //   1468: getstatic 203	fn:ep	Lci;
    //   1471: invokevirtual 312	java/util/Vector:size	()I
    //   1474: invokestatic 336	s:g	(II)Z
    //   1477: ifeq +382 -> 1859
    //   1480: getstatic 203	fn:ep	Lci;
    //   1483: iload_1
    //   1484: invokevirtual 250	ci:elementAt	(I)Ljava/lang/Object;
    //   1487: checkcast 112	dt
    //   1490: astore_3
    //   1491: invokestatic 283	dt:g	()Ldt;
    //   1494: getfield 166	dt:ap	I
    //   1497: getstatic 232	s:ak	[I
    //   1500: bipush 11
    //   1502: iaload
    //   1503: isub
    //   1504: aload_3
    //   1505: getfield 166	dt:ap	I
    //   1508: invokestatic 332	s:e	(II)Z
    //   1511: ifeq +307 -> 1818
    //   1514: aload_3
    //   1515: getfield 166	dt:ap	I
    //   1518: invokestatic 283	dt:g	()Ldt;
    //   1521: getfield 166	dt:ap	I
    //   1524: getstatic 232	s:ak	[I
    //   1527: bipush 11
    //   1529: iaload
    //   1530: iadd
    //   1531: invokestatic 332	s:e	(II)Z
    //   1534: ifeq +284 -> 1818
    //   1537: aload_3
    //   1538: getfield 173	dt:ef	I
    //   1541: invokestatic 339	s:i	(I)Z
    //   1544: ifeq +274 -> 1818
    //   1547: invokestatic 310	java/lang/System:currentTimeMillis	()J
    //   1550: aload_0
    //   1551: getfield 236	s:ao	J
    //   1554: lsub
    //   1555: ldc2_w 136
    //   1558: invokestatic 323	s:a	(JJ)I
    //   1561: invokestatic 337	s:h	(I)Z
    //   1564: ifeq +27 -> 1591
    //   1567: aload_3
    //   1568: getfield 174	dt:eg	I
    //   1571: aload_3
    //   1572: getfield 178	dt:ey	I
    //   1575: invokestatic 279	dt:b	(II)Z
    //   1578: ldc 1
    //   1580: invokevirtual 300	java/lang/String:length	()I
    //   1583: pop2
    //   1584: aload_0
    //   1585: invokestatic 310	java/lang/System:currentTimeMillis	()J
    //   1588: putfield 236	s:ao	J
    //   1591: invokestatic 283	dt:g	()Ldt;
    //   1594: getfield 179	dt:fm	B
    //   1597: getstatic 232	s:ak	[I
    //   1600: iconst_3
    //   1601: iaload
    //   1602: invokestatic 334	s:f	(II)Z
    //   1605: ifeq +14 -> 1619
    //   1608: invokestatic 264	dl:ae	()Ldl;
    //   1611: getstatic 232	s:ak	[I
    //   1614: iconst_3
    //   1615: iaload
    //   1616: invokevirtual 271	dl:x	(I)V
    //   1619: invokestatic 283	dt:g	()Ldt;
    //   1622: getfield 180	dt:g	B
    //   1625: getstatic 232	s:ak	[I
    //   1628: iconst_2
    //   1629: iaload
    //   1630: invokestatic 330	s:d	(II)Z
    //   1633: ifeq +49 -> 1682
    //   1636: getstatic 232	s:ak	[I
    //   1639: bipush 26
    //   1641: iaload
    //   1642: invokestatic 284	dt:g	(I)Lao;
    //   1645: dup
    //   1646: astore_2
    //   1647: invokestatic 325	s:a	(Ljava/lang/Object;)Z
    //   1650: ifeq +32 -> 1682
    //   1653: aload_2
    //   1654: getfield 140	ao:j	Lat;
    //   1657: getfield 146	at:f	S
    //   1660: getstatic 232	s:ak	[I
    //   1663: bipush 26
    //   1665: iaload
    //   1666: invokestatic 340	s:i	(II)Z
    //   1669: ifeq +13 -> 1682
    //   1672: invokestatic 264	dl:ae	()Ldl;
    //   1675: aload_2
    //   1676: getfield 142	ao:n	I
    //   1679: invokevirtual 263	dl:ad	(I)V
    //   1682: getstatic 218	r:e	Lci;
    //   1685: invokevirtual 251	ci:removeAllElements	()V
    //   1688: getstatic 220	r:l	Lci;
    //   1691: invokevirtual 251	ci:removeAllElements	()V
    //   1694: getstatic 220	r:l	Lci;
    //   1697: aload_3
    //   1698: invokevirtual 249	ci:addElement	(Ljava/lang/Object;)V
    //   1701: invokestatic 264	dl:ae	()Ldl;
    //   1704: getstatic 221	r:m	Lfy;
    //   1707: getfield 213	fy:a	Lev;
    //   1710: getfield 186	ev:e	B
    //   1713: invokevirtual 268	dl:l	(I)V
    //   1716: invokestatic 264	dl:ae	()Ldl;
    //   1719: getstatic 218	r:e	Lci;
    //   1722: getstatic 220	r:l	Lci;
    //   1725: getstatic 232	s:ak	[I
    //   1728: bipush 8
    //   1730: iaload
    //   1731: invokevirtual 262	dl:a	(Lci;Lci;I)V
    //   1734: invokestatic 310	java/lang/System:currentTimeMillis	()J
    //   1737: getstatic 221	r:m	Lfy;
    //   1740: getfield 214	fy:e	J
    //   1743: lsub
    //   1744: getstatic 221	r:m	Lfy;
    //   1747: getfield 216	fy:l	I
    //   1750: i2l
    //   1751: ldc2_w 130
    //   1754: ladd
    //   1755: invokestatic 323	s:a	(JJ)I
    //   1758: invokestatic 337	s:h	(I)Z
    //   1761: ifeq +57 -> 1818
    //   1764: getstatic 221	r:m	Lfy;
    //   1767: invokestatic 310	java/lang/System:currentTimeMillis	()J
    //   1770: putfield 214	fy:e	J
    //   1773: getstatic 221	r:m	Lfy;
    //   1776: getstatic 232	s:ak	[I
    //   1779: bipush 6
    //   1781: iaload
    //   1782: putfield 215	fy:k	Z
    //   1785: getstatic 163	dn:ae	Z
    //   1788: invokestatic 341	s:j	(I)Z
    //   1791: ifeq +27 -> 1818
    //   1794: invokestatic 283	dt:g	()Ldt;
    //   1797: getstatic 195	fn:dc	[Lad;
    //   1800: getstatic 221	r:m	Lfy;
    //   1803: getfield 213	fy:a	Lev;
    //   1806: getfield 186	ev:e	B
    //   1809: aaload
    //   1810: getstatic 232	s:ak	[I
    //   1813: iconst_1
    //   1814: iaload
    //   1815: invokevirtual 278	dt:a	(Lad;I)V
    //   1818: iinc 1 1
    //   1821: ldc 1
    //   1823: invokevirtual 300	java/lang/String:length	()I
    //   1826: pop
    //   1827: sipush 165
    //   1830: sipush 132
    //   1833: ixor
    //   1834: bipush 121
    //   1836: bipush 88
    //   1838: ixor
    //   1839: iconst_m1
    //   1840: ixor
    //   1841: iand
    //   1842: bipush 124
    //   1844: bipush 89
    //   1846: ixor
    //   1847: bipush 112
    //   1849: bipush 85
    //   1851: ixor
    //   1852: iconst_m1
    //   1853: ixor
    //   1854: iand
    //   1855: if_icmpge -388 -> 1467
    //   1858: return
    //   1859: return
    //   1860: getstatic 232	s:ak	[I
    //   1863: bipush 6
    //   1865: iaload
    //   1866: putstatic 235	s:an	Z
    //   1869: invokestatic 322	r:n	()V
    //   1872: return
    //   1873: aload_0
    //   1874: invokespecial 342	s:p	()Z
    //   1877: invokestatic 329	s:d	(I)Z
    //   1880: ifeq +912 -> 2792
    //   1883: new 124	java/lang/StringBuffer
    //   1886: dup
    //   1887: ldc 85
    //   1889: invokespecial 306	java/lang/StringBuffer:<init>	(Ljava/lang/String;)V
    //   1892: getstatic 238	s:w	Lat;
    //   1895: getfield 144	at:a	Ljava/lang/String;
    //   1898: invokevirtual 308	java/lang/StringBuffer:append	(Ljava/lang/String;)Ljava/lang/StringBuffer;
    //   1901: invokevirtual 309	java/lang/StringBuffer:toString	()Ljava/lang/String;
    //   1904: invokestatic 288	fn:a	(Ljava/lang/String;)V
    //   1907: getstatic 232	s:ak	[I
    //   1910: bipush 6
    //   1912: iaload
    //   1913: putstatic 226	s:ae	Z
    //   1916: return
    //   1917: getstatic 185	et:o	S
    //   1920: invokestatic 286	et:i	(I)Z
    //   1923: invokestatic 341	s:j	(I)Z
    //   1926: ifeq +26 -> 1952
    //   1929: aload_0
    //   1930: getstatic 159	cz:l	I
    //   1933: getstatic 232	s:ak	[I
    //   1936: iconst_0
    //   1937: iaload
    //   1938: getstatic 232	s:ak	[I
    //   1941: iconst_5
    //   1942: iaload
    //   1943: getstatic 232	s:ak	[I
    //   1946: iconst_5
    //   1947: iaload
    //   1948: invokevirtual 315	r:a	(IIII)V
    //   1951: return
    //   1952: getstatic 233	s:al	I
    //   1955: getstatic 232	s:ak	[I
    //   1958: iconst_0
    //   1959: iaload
    //   1960: invokestatic 340	s:i	(II)Z
    //   1963: ifeq +79 -> 2042
    //   1966: getstatic 217	java/lang/System:out	Ljava/io/PrintStream;
    //   1969: ldc 67
    //   1971: invokevirtual 293	java/io/PrintStream:println	(Ljava/lang/String;)V
    //   1974: new 124	java/lang/StringBuffer
    //   1977: dup
    //   1978: ldc 92
    //   1980: invokespecial 306	java/lang/StringBuffer:<init>	(Ljava/lang/String;)V
    //   1983: getstatic 222	s:aa	I
    //   1986: getstatic 232	s:ak	[I
    //   1989: bipush 6
    //   1991: iaload
    //   1992: iadd
    //   1993: invokevirtual 307	java/lang/StringBuffer:append	(I)Ljava/lang/StringBuffer;
    //   1996: invokevirtual 309	java/lang/StringBuffer:toString	()Ljava/lang/String;
    //   1999: invokestatic 288	fn:a	(Ljava/lang/String;)V
    //   2002: getstatic 232	s:ak	[I
    //   2005: bipush 8
    //   2007: iaload
    //   2008: invokestatic 289	fn:b	(I)V
    //   2011: getstatic 232	s:ak	[I
    //   2014: bipush 8
    //   2016: iaload
    //   2017: getstatic 232	s:ak	[I
    //   2020: bipush 6
    //   2022: iaload
    //   2023: getstatic 232	s:ak	[I
    //   2026: bipush 9
    //   2028: iaload
    //   2029: invokestatic 290	fn:b	(III)V
    //   2032: invokestatic 255	cn:n	()Z
    //   2035: ldc 1
    //   2037: invokevirtual 300	java/lang/String:length	()I
    //   2040: pop2
    //   2041: return
    //   2042: getstatic 233	s:al	I
    //   2045: getstatic 232	s:ak	[I
    //   2048: iconst_5
    //   2049: iaload
    //   2050: invokestatic 340	s:i	(II)Z
    //   2053: ifeq +81 -> 2134
    //   2056: getstatic 217	java/lang/System:out	Ljava/io/PrintStream;
    //   2059: ldc 78
    //   2061: invokevirtual 293	java/io/PrintStream:println	(Ljava/lang/String;)V
    //   2064: new 124	java/lang/StringBuffer
    //   2067: dup
    //   2068: ldc 80
    //   2070: invokespecial 306	java/lang/StringBuffer:<init>	(Ljava/lang/String;)V
    //   2073: getstatic 222	s:aa	I
    //   2076: getstatic 232	s:ak	[I
    //   2079: bipush 6
    //   2081: iaload
    //   2082: iadd
    //   2083: invokevirtual 307	java/lang/StringBuffer:append	(I)Ljava/lang/StringBuffer;
    //   2086: invokevirtual 309	java/lang/StringBuffer:toString	()Ljava/lang/String;
    //   2089: invokestatic 288	fn:a	(Ljava/lang/String;)V
    //   2092: getstatic 232	s:ak	[I
    //   2095: bipush 8
    //   2097: iaload
    //   2098: invokestatic 289	fn:b	(I)V
    //   2101: getstatic 232	s:ak	[I
    //   2104: bipush 8
    //   2106: iaload
    //   2107: getstatic 232	s:ak	[I
    //   2110: bipush 6
    //   2112: iaload
    //   2113: getstatic 232	s:ak	[I
    //   2116: iconst_1
    //   2117: iaload
    //   2118: invokestatic 290	fn:b	(III)V
    //   2121: invokestatic 344	s:r	()V
    //   2124: invokestatic 255	cn:n	()Z
    //   2127: ldc 1
    //   2129: invokevirtual 300	java/lang/String:length	()I
    //   2132: pop2
    //   2133: return
    //   2134: getstatic 233	s:al	I
    //   2137: invokestatic 341	s:j	(I)Z
    //   2140: ifeq +111 -> 2251
    //   2143: getstatic 217	java/lang/System:out	Ljava/io/PrintStream;
    //   2146: ldc 62
    //   2148: invokevirtual 293	java/io/PrintStream:println	(Ljava/lang/String;)V
    //   2151: new 124	java/lang/StringBuffer
    //   2154: dup
    //   2155: ldc 66
    //   2157: invokespecial 306	java/lang/StringBuffer:<init>	(Ljava/lang/String;)V
    //   2160: getstatic 222	s:aa	I
    //   2163: getstatic 232	s:ak	[I
    //   2166: bipush 6
    //   2168: iaload
    //   2169: iadd
    //   2170: invokevirtual 307	java/lang/StringBuffer:append	(I)Ljava/lang/StringBuffer;
    //   2173: invokevirtual 309	java/lang/StringBuffer:toString	()Ljava/lang/String;
    //   2176: invokestatic 288	fn:a	(Ljava/lang/String;)V
    //   2179: getstatic 232	s:ak	[I
    //   2182: bipush 8
    //   2184: iaload
    //   2185: getstatic 232	s:ak	[I
    //   2188: bipush 6
    //   2190: iaload
    //   2191: getstatic 232	s:ak	[I
    //   2194: bipush 8
    //   2196: iaload
    //   2197: invokestatic 290	fn:b	(III)V
    //   2200: getstatic 232	s:ak	[I
    //   2203: bipush 8
    //   2205: iaload
    //   2206: invokestatic 289	fn:b	(I)V
    //   2209: invokestatic 264	dl:ae	()Ldl;
    //   2212: getstatic 232	s:ak	[I
    //   2215: iconst_4
    //   2216: iaload
    //   2217: invokevirtual 269	dl:q	(I)V
    //   2220: invokestatic 255	cn:n	()Z
    //   2223: ldc 1
    //   2225: invokevirtual 300	java/lang/String:length	()I
    //   2228: pop2
    //   2229: getstatic 222	s:aa	I
    //   2232: getstatic 232	s:ak	[I
    //   2235: bipush 6
    //   2237: iaload
    //   2238: iadd
    //   2239: putstatic 222	s:aa	I
    //   2242: getstatic 232	s:ak	[I
    //   2245: iconst_5
    //   2246: iaload
    //   2247: putstatic 233	s:al	I
    //   2250: return
    //   2251: getstatic 226	s:ae	Z
    //   2254: invokestatic 341	s:j	(I)Z
    //   2257: ifeq +12 -> 2269
    //   2260: getstatic 235	s:an	Z
    //   2263: invokestatic 329	s:d	(I)Z
    //   2266: ifeq +526 -> 2792
    //   2269: getstatic 225	s:ad	Lao;
    //   2272: invokestatic 325	s:a	(Ljava/lang/Object;)Z
    //   2275: ifeq +156 -> 2431
    //   2278: getstatic 225	s:ad	Lao;
    //   2281: getfield 141	ao:m	I
    //   2284: getstatic 232	s:ak	[I
    //   2287: iconst_2
    //   2288: iaload
    //   2289: invokestatic 334	s:f	(II)Z
    //   2292: ifeq +73 -> 2365
    //   2295: getstatic 217	java/lang/System:out	Ljava/io/PrintStream;
    //   2298: new 124	java/lang/StringBuffer
    //   2301: dup
    //   2302: ldc 76
    //   2304: invokespecial 306	java/lang/StringBuffer:<init>	(Ljava/lang/String;)V
    //   2307: getstatic 225	s:ad	Lao;
    //   2310: getfield 140	ao:j	Lat;
    //   2313: getfield 144	at:a	Ljava/lang/String;
    //   2316: invokevirtual 308	java/lang/StringBuffer:append	(Ljava/lang/String;)Ljava/lang/StringBuffer;
    //   2319: ldc 18
    //   2321: invokevirtual 308	java/lang/StringBuffer:append	(Ljava/lang/String;)Ljava/lang/StringBuffer;
    //   2324: getstatic 225	s:ad	Lao;
    //   2327: getfield 142	ao:n	I
    //   2330: invokevirtual 307	java/lang/StringBuffer:append	(I)Ljava/lang/StringBuffer;
    //   2333: invokevirtual 309	java/lang/StringBuffer:toString	()Ljava/lang/String;
    //   2336: invokevirtual 293	java/io/PrintStream:println	(Ljava/lang/String;)V
    //   2339: invokestatic 264	dl:ae	()Ldl;
    //   2342: getstatic 225	s:ad	Lao;
    //   2345: getfield 142	ao:n	I
    //   2348: invokevirtual 263	dl:ad	(I)V
    //   2351: invokestatic 253	cn:ae	()Z
    //   2354: ldc 1
    //   2356: invokevirtual 300	java/lang/String:length	()I
    //   2359: pop2
    //   2360: aconst_null
    //   2361: putstatic 225	s:ad	Lao;
    //   2364: return
    //   2365: invokestatic 283	dt:g	()Ldt;
    //   2368: getfield 183	dt:s	[Lao;
    //   2371: getstatic 225	s:ad	Lao;
    //   2374: getfield 140	ao:j	Lat;
    //   2377: getfield 145	at:b	B
    //   2380: aaload
    //   2381: getfield 143	ao:r	I
    //   2384: getstatic 232	s:ak	[I
    //   2387: bipush 12
    //   2389: iaload
    //   2390: invokestatic 336	s:g	(II)Z
    //   2393: ifeq +33 -> 2426
    //   2396: getstatic 217	java/lang/System:out	Ljava/io/PrintStream;
    //   2399: new 124	java/lang/StringBuffer
    //   2402: dup
    //   2403: ldc 73
    //   2405: invokespecial 306	java/lang/StringBuffer:<init>	(Ljava/lang/String;)V
    //   2408: getstatic 225	s:ad	Lao;
    //   2411: getfield 140	ao:j	Lat;
    //   2414: getfield 145	at:b	B
    //   2417: invokevirtual 307	java/lang/StringBuffer:append	(I)Ljava/lang/StringBuffer;
    //   2420: invokevirtual 309	java/lang/StringBuffer:toString	()Ljava/lang/String;
    //   2423: invokevirtual 293	java/io/PrintStream:println	(Ljava/lang/String;)V
    //   2426: aconst_null
    //   2427: putstatic 225	s:ad	Lao;
    //   2430: return
    //   2431: getstatic 229	s:ah	Lao;
    //   2434: invokestatic 325	s:a	(Ljava/lang/Object;)Z
    //   2437: ifeq +132 -> 2569
    //   2440: getstatic 227	s:af	Z
    //   2443: invokestatic 341	s:j	(I)Z
    //   2446: ifeq +8 -> 2454
    //   2449: aconst_null
    //   2450: putstatic 229	s:ah	Lao;
    //   2453: return
    //   2454: getstatic 229	s:ah	Lao;
    //   2457: getfield 141	ao:m	I
    //   2460: getstatic 232	s:ak	[I
    //   2463: iconst_3
    //   2464: iaload
    //   2465: invokestatic 340	s:i	(II)Z
    //   2468: ifeq +96 -> 2564
    //   2471: getstatic 217	java/lang/System:out	Ljava/io/PrintStream;
    //   2474: new 124	java/lang/StringBuffer
    //   2477: dup
    //   2478: ldc 47
    //   2480: invokespecial 306	java/lang/StringBuffer:<init>	(Ljava/lang/String;)V
    //   2483: getstatic 229	s:ah	Lao;
    //   2486: getfield 140	ao:j	Lat;
    //   2489: getfield 144	at:a	Ljava/lang/String;
    //   2492: invokevirtual 308	java/lang/StringBuffer:append	(Ljava/lang/String;)Ljava/lang/StringBuffer;
    //   2495: ldc 25
    //   2497: invokevirtual 308	java/lang/StringBuffer:append	(Ljava/lang/String;)Ljava/lang/StringBuffer;
    //   2500: invokevirtual 309	java/lang/StringBuffer:toString	()Ljava/lang/String;
    //   2503: invokevirtual 293	java/io/PrintStream:println	(Ljava/lang/String;)V
    //   2506: getstatic 232	s:ak	[I
    //   2509: iconst_2
    //   2510: iaload
    //   2511: getstatic 232	s:ak	[I
    //   2514: iconst_1
    //   2515: iaload
    //   2516: getstatic 232	s:ak	[I
    //   2519: iconst_1
    //   2520: iaload
    //   2521: invokestatic 290	fn:b	(III)V
    //   2524: invokestatic 281	dt:e	()I
    //   2527: invokestatic 339	s:i	(I)Z
    //   2530: ifeq +29 -> 2559
    //   2533: invokestatic 264	dl:ae	()Ldl;
    //   2536: getstatic 229	s:ah	Lao;
    //   2539: getfield 141	ao:m	I
    //   2542: invokevirtual 265	dl:ae	(I)V
    //   2545: ldc2_w 134
    //   2548: invokestatic 311	java/lang/Thread:sleep	(J)V
    //   2551: return
    //   2552: ldc 1
    //   2554: invokevirtual 300	java/lang/String:length	()I
    //   2557: pop2
    //   2558: return
    //   2559: aconst_null
    //   2560: putstatic 229	s:ah	Lao;
    //   2563: return
    //   2564: aconst_null
    //   2565: putstatic 229	s:ah	Lao;
    //   2568: return
    //   2569: getstatic 235	s:an	Z
    //   2572: invokestatic 329	s:d	(I)Z
    //   2575: ifeq +164 -> 2739
    //   2578: invokestatic 282	dt:f	()I
    //   2581: invokestatic 331	s:e	(I)Z
    //   2584: ifeq +9 -> 2593
    //   2587: ldc 63
    //   2589: invokestatic 288	fn:a	(Ljava/lang/String;)V
    //   2592: return
    //   2593: getstatic 217	java/lang/System:out	Ljava/io/PrintStream;
    //   2596: ldc 59
    //   2598: invokevirtual 293	java/io/PrintStream:println	(Ljava/lang/String;)V
    //   2601: invokestatic 283	dt:g	()Ldt;
    //   2604: getfield 179	dt:fm	B
    //   2607: getstatic 232	s:ak	[I
    //   2610: iconst_3
    //   2611: iaload
    //   2612: invokestatic 340	s:i	(II)Z
    //   2615: ifeq +14 -> 2629
    //   2618: invokestatic 264	dl:ae	()Ldl;
    //   2621: getstatic 232	s:ak	[I
    //   2624: iconst_1
    //   2625: iaload
    //   2626: invokevirtual 271	dl:x	(I)V
    //   2629: new 124	java/lang/StringBuffer
    //   2632: dup
    //   2633: ldc 60
    //   2635: invokespecial 306	java/lang/StringBuffer:<init>	(Ljava/lang/String;)V
    //   2638: getstatic 222	s:aa	I
    //   2641: getstatic 232	s:ak	[I
    //   2644: bipush 6
    //   2646: iaload
    //   2647: iadd
    //   2648: invokevirtual 307	java/lang/StringBuffer:append	(I)Ljava/lang/StringBuffer;
    //   2651: invokevirtual 309	java/lang/StringBuffer:toString	()Ljava/lang/String;
    //   2654: invokestatic 288	fn:a	(Ljava/lang/String;)V
    //   2657: getstatic 232	s:ak	[I
    //   2660: bipush 8
    //   2662: iaload
    //   2663: invokestatic 289	fn:b	(I)V
    //   2666: getstatic 232	s:ak	[I
    //   2669: bipush 8
    //   2671: iaload
    //   2672: getstatic 232	s:ak	[I
    //   2675: bipush 6
    //   2677: iaload
    //   2678: getstatic 232	s:ak	[I
    //   2681: bipush 6
    //   2683: iaload
    //   2684: invokestatic 290	fn:b	(III)V
    //   2687: invokestatic 344	s:r	()V
    //   2690: invokestatic 255	cn:n	()Z
    //   2693: ldc 1
    //   2695: invokevirtual 300	java/lang/String:length	()I
    //   2698: pop2
    //   2699: getstatic 222	s:aa	I
    //   2702: getstatic 232	s:ak	[I
    //   2705: bipush 6
    //   2707: iaload
    //   2708: iadd
    //   2709: putstatic 222	s:aa	I
    //   2712: getstatic 234	s:am	I
    //   2715: getstatic 232	s:ak	[I
    //   2718: bipush 6
    //   2720: iaload
    //   2721: iadd
    //   2722: putstatic 234	s:am	I
    //   2725: getstatic 240	s:y	I
    //   2728: getstatic 232	s:ak	[I
    //   2731: bipush 6
    //   2733: iaload
    //   2734: iadd
    //   2735: putstatic 240	s:y	I
    //   2738: return
    //   2739: aload_0
    //   2740: getfield 219	r:i	Lr;
    //   2743: invokestatic 325	s:a	(Ljava/lang/Object;)Z
    //   2746: ifeq +46 -> 2792
    //   2749: aload_0
    //   2750: getfield 219	r:i	Lr;
    //   2753: instanceof 129
    //   2756: invokestatic 341	s:j	(I)Z
    //   2759: ifeq +33 -> 2792
    //   2762: ldc2_w 138
    //   2765: invokestatic 311	java/lang/Thread:sleep	(J)V
    //   2768: ldc 1
    //   2770: invokevirtual 300	java/lang/String:length	()I
    //   2773: pop
    //   2774: ldc 4
    //   2776: invokevirtual 300	java/lang/String:length	()I
    //   2779: ifge +10 -> 2789
    //   2782: return
    //   2783: ldc 1
    //   2785: invokevirtual 300	java/lang/String:length	()I
    //   2788: pop2
    //   2789: invokestatic 274	dn:o	()V
    //   2792: return
    // Local variable table:
    //   start	length	slot	name	signature
    //   0	2793	0	this	s
    //   195	1	1	i	int
    //   225	8	1	localfb1	fb
    //   237	881	1	j	int
    //   1142	8	1	localfb2	fb
    //   1154	665	1	k	int
    //   308	5	2	m	int
    //   684	55	2	localao1	ao
    //   1182	5	2	n	int
    //   1646	30	2	localao2	ao
    //   833	865	3	localObject	Object
    //   77	1	11	localInterruptedException1	InterruptedException
    //   2552	1	12	localInterruptedException2	InterruptedException
    //   2783	1	13	localInterruptedException3	InterruptedException
    // Exception table:
    //   from	to	target	type
    //   55	61	77	java/lang/InterruptedException
    //   2545	2551	2552	java/lang/InterruptedException
    //   2762	2768	2783	java/lang/InterruptedException
  }
  
  private static void r()
  {
    int i = ak[1];
    while (g(i, dt.g().w.length))
    {
      ao localao;
      if ((a(localao = dt.g().w[i])) && (g(localao.j.b, ak[11])) && (d(localao.r, ak[12]))) {
        dl.ae().ad(localao.n);
      }
      i++;
      "".length();
      if (-" ".length() > (0xA7 ^ 0xA3)) {}
    }
  }
  
  private static void s()
  {
    ak = new int[28];
    ak[0] = (-"  ".length());
    ak[1] = ((69 + '' - 144 + 117 ^ 44 + 1 - 44 + 184) & ('¯' + 26 - 35 + 24 ^ '' + 6 - 87 + 111 ^ -" ".length()));
    ak[2] = (20 + 50 - -25 + 37 ^ 26 + 108 - 27 + 22);
    ak[3] = "   ".length();
    ak[4] = (0x5C ^ 0x58);
    ak[5] = (-" ".length());
    ak[6] = " ".length();
    ak[7] = (0x71 ^ 0x66 ^ 0x96 ^ 0x9B);
    ak[8] = "  ".length();
    ak[9] = (0xE ^ 0x8);
    ak[10] = (0xD7 ^ 0xB4 ^ 0x1B ^ 0x7F);
    ak[11] = (0xB5 ^ 0xBF);
    ak[12] = (58 + 95 - 54 + 60 ^ 97 + 6 - 85 + 129);
    ak[13] = (0x7 ^ 0x28);
    ak[14] = (0x70 ^ 0x50);
    ak[15] = (0x41 ^ 0x4A);
    ak[16] = (0xA0 ^ 0x8E ^ 0x6F ^ 0x4F);
    ak[17] = (66 + 115 - 121 + 130 ^ 124 + '' - 247 + 148);
    ak[18] = (54 + 87 - 69 + 81 ^ 80 + 99 - 135 + 101);
    ak[19] = ('¦' + 'î' - 263 + 107 ^ 43 + 8 - -73 + 10);
    ak[20] = ((0x48 ^ 0x25) + " ".length() - (0x9 ^ 0x61) + (0xF ^ 0x76));
    ak[21] = (0x2C ^ 0x16 ^ 0x67 ^ 0x4B);
    ak[22] = (0x61 ^ 0x39 ^ 0x49 ^ 0x3B);
    ak[23] = (0x26 ^ 0x1B ^ 0x8D ^ 0xA2);
    ak[24] = (86 + 64 - 119 + 211);
    ak[25] = (99 + 55 - 121 + 95 ^ 94 + 94 - 185 + 175);
    ak[26] = (0xA33F & 0x5DC1);
    ak[27] = (0x52 ^ 0x4E);
  }
  
  public final String toString()
  {
    if (i(al, ak[6])) {
      return " - Đánh quái thường: " + ab + "/" + ag + " | Đã làm : " + y + " NV";
    }
    if (i(al, ak[8])) {
      return " - Đánh tinh anh: " + ab + "/" + ag + " | Đã làm : " + y + " NV";
    }
    if (i(al, ak[3])) {
      return " - Đánh thủ lĩnh: " + ab + "/" + ag + " | Đã làm : " + y + " NV";
    }
    if (i(al, ak[4])) {
      return " - Nâng cấp: " + ab + "/" + ag + " | Đã làm : " + y + " NV";
    }
    if (i(al, ak[2])) {
      return " - Lôi đài | Đã làm : " + y + " NV";
    }
    if (i(al, ak[9])) {
      return " - Kiếm: " + ag + " Yên | Đã làm : " + y + " NV";
    }
    if (i(al, ak[10])) {
      return " - Cừ sát: " + z + "/" + ag + " người | Đã làm : " + y + " NV";
    }
    return "NVDV ";
  }
  
  private static boolean b(Object paramObject)
  {
    return paramObject == null;
  }
  
  /* Error */
  private void a(ao paramao, int paramInt)
  {
    // Byte code:
    //   0: getstatic 232	s:ak	[I
    //   3: iconst_1
    //   4: iaload
    //   5: istore_2
    //   6: getstatic 232	s:ak	[I
    //   9: iconst_1
    //   10: iaload
    //   11: istore_3
    //   12: aload_1
    //   13: invokevirtual 244	ao:b	()Z
    //   16: invokestatic 329	s:d	(I)Z
    //   19: ifeq +49 -> 68
    //   22: getstatic 207	fn:fn	[I
    //   25: aload_1
    //   26: getfield 143	ao:r	I
    //   29: iaload
    //   30: getstatic 232	s:ak	[I
    //   33: iconst_3
    //   34: iaload
    //   35: idiv
    //   36: istore_2
    //   37: getstatic 197	fn:dl	[I
    //   40: aload_1
    //   41: getfield 143	ao:r	I
    //   44: iaload
    //   45: istore_3
    //   46: ldc 1
    //   48: invokevirtual 300	java/lang/String:length	()I
    //   51: pop
    //   52: ldc 3
    //   54: invokevirtual 300	java/lang/String:length	()I
    //   57: ineg
    //   58: ldc 3
    //   60: invokevirtual 300	java/lang/String:length	()I
    //   63: ineg
    //   64: if_icmpeq +92 -> 156
    //   67: return
    //   68: aload_1
    //   69: invokevirtual 245	ao:i	()Z
    //   72: invokestatic 329	s:d	(I)Z
    //   75: ifeq +47 -> 122
    //   78: getstatic 201	fn:em	[I
    //   81: aload_1
    //   82: getfield 143	ao:r	I
    //   85: iaload
    //   86: getstatic 232	s:ak	[I
    //   89: iconst_3
    //   90: iaload
    //   91: idiv
    //   92: istore_2
    //   93: getstatic 202	fn:eo	[I
    //   96: aload_1
    //   97: getfield 143	ao:r	I
    //   100: iaload
    //   101: istore_3
    //   102: ldc 1
    //   104: invokevirtual 300	java/lang/String:length	()I
    //   107: pop
    //   108: bipush 53
    //   110: bipush 49
    //   112: ixor
    //   113: ldc 4
    //   115: invokevirtual 300	java/lang/String:length	()I
    //   118: if_icmpgt +38 -> 156
    //   121: return
    //   122: aload_1
    //   123: invokevirtual 246	ao:m	()Z
    //   126: invokestatic 329	s:d	(I)Z
    //   129: ifeq +27 -> 156
    //   132: getstatic 211	fn:fz	[I
    //   135: aload_1
    //   136: getfield 143	ao:r	I
    //   139: iaload
    //   140: getstatic 232	s:ak	[I
    //   143: iconst_3
    //   144: iaload
    //   145: idiv
    //   146: istore_2
    //   147: getstatic 199	fn:eb	[I
    //   150: aload_1
    //   151: getfield 143	ao:r	I
    //   154: iaload
    //   155: istore_3
    //   156: iload_2
    //   157: getstatic 232	s:ak	[I
    //   160: bipush 6
    //   162: iaload
    //   163: ishl
    //   164: invokestatic 276	dt:a	()I
    //   167: invokestatic 332	s:e	(II)Z
    //   170: ifeq +756 -> 926
    //   173: iload_3
    //   174: getstatic 232	s:ak	[I
    //   177: bipush 6
    //   179: iaload
    //   180: ishl
    //   181: invokestatic 283	dt:g	()Ldt;
    //   184: getfield 177	dt:ev	I
    //   187: invokestatic 332	s:e	(II)Z
    //   190: ifeq +736 -> 926
    //   193: aload_1
    //   194: getfield 143	ao:r	I
    //   197: getstatic 232	s:ak	[I
    //   200: bipush 18
    //   202: iaload
    //   203: invokestatic 336	s:g	(II)Z
    //   206: ifeq +720 -> 926
    //   209: getstatic 185	et:o	S
    //   212: getstatic 232	s:ak	[I
    //   215: bipush 21
    //   217: iaload
    //   218: invokestatic 334	s:f	(II)Z
    //   221: ifeq +62 -> 283
    //   224: getstatic 185	et:o	S
    //   227: invokestatic 287	et:o	(I)Z
    //   230: invokestatic 341	s:j	(I)Z
    //   233: ifeq +24 -> 257
    //   236: invokestatic 283	dt:g	()Ldt;
    //   239: getfield 170	dt:cj	I
    //   242: getstatic 232	s:ak	[I
    //   245: bipush 22
    //   247: iaload
    //   248: invokestatic 336	s:g	(II)Z
    //   251: ifeq +6 -> 257
    //   254: invokestatic 322	r:n	()V
    //   257: aload_0
    //   258: getstatic 232	s:ak	[I
    //   261: bipush 21
    //   263: iaload
    //   264: getstatic 232	s:ak	[I
    //   267: iconst_0
    //   268: iaload
    //   269: getstatic 232	s:ak	[I
    //   272: iconst_5
    //   273: iaload
    //   274: getstatic 232	s:ak	[I
    //   277: iconst_5
    //   278: iaload
    //   279: invokevirtual 315	r:a	(IIII)V
    //   282: return
    //   283: aload_1
    //   284: getfield 143	ao:r	I
    //   287: istore_3
    //   288: getstatic 232	s:ak	[I
    //   291: bipush 9
    //   293: iaload
    //   294: invokestatic 289	fn:b	(I)V
    //   297: invokestatic 292	fn:j	()Lfn;
    //   300: getstatic 232	s:ak	[I
    //   303: bipush 11
    //   305: iaload
    //   306: invokevirtual 291	fn:h	(I)V
    //   309: aload_1
    //   310: putstatic 208	fn:fr	Lao;
    //   313: getstatic 232	s:ak	[I
    //   316: iconst_1
    //   317: iaload
    //   318: istore 5
    //   320: iload 5
    //   322: invokestatic 331	s:e	(I)Z
    //   325: ifeq +596 -> 921
    //   328: aload_1
    //   329: getfield 143	ao:r	I
    //   332: iload_3
    //   333: invokestatic 340	s:i	(II)Z
    //   336: ifeq +585 -> 921
    //   339: getstatic 232	s:ak	[I
    //   342: bipush 23
    //   344: iaload
    //   345: anewarray 101	ao
    //   348: putstatic 196	fn:dh	[Lao;
    //   351: getstatic 232	s:ak	[I
    //   354: iconst_1
    //   355: iaload
    //   356: istore 4
    //   358: getstatic 232	s:ak	[I
    //   361: iconst_1
    //   362: iaload
    //   363: istore 6
    //   365: getstatic 232	s:ak	[I
    //   368: iconst_1
    //   369: iaload
    //   370: istore 7
    //   372: iload 7
    //   374: invokestatic 283	dt:g	()Ldt;
    //   377: getfield 184	dt:w	[Lao;
    //   380: arraylength
    //   381: invokestatic 336	s:g	(II)Z
    //   384: ifeq +436 -> 820
    //   387: iload 6
    //   389: iload_2
    //   390: invokestatic 336	s:g	(II)Z
    //   393: ifeq +427 -> 820
    //   396: invokestatic 283	dt:g	()Ldt;
    //   399: getfield 184	dt:w	[Lao;
    //   402: iload 7
    //   404: aaload
    //   405: astore 8
    //   407: aload_1
    //   408: getfield 143	ao:r	I
    //   411: getstatic 232	s:ak	[I
    //   414: bipush 9
    //   416: iaload
    //   417: invokestatic 340	s:i	(II)Z
    //   420: ifeq +145 -> 565
    //   423: getstatic 151	cz:c	Z
    //   426: invokestatic 329	s:d	(I)Z
    //   429: ifeq +136 -> 565
    //   432: getstatic 232	s:ak	[I
    //   435: bipush 24
    //   437: iaload
    //   438: invokestatic 280	dt:d	(I)I
    //   441: invokestatic 333	s:f	(I)Z
    //   444: ifeq +102 -> 546
    //   447: invokestatic 283	dt:g	()Ldt;
    //   450: getfield 181	dt:ga	I
    //   453: getstatic 232	s:ak	[I
    //   456: bipush 11
    //   458: iaload
    //   459: invokestatic 330	s:d	(II)Z
    //   462: ifeq +68 -> 530
    //   465: invokestatic 264	dl:ae	()Ldl;
    //   468: getstatic 232	s:ak	[I
    //   471: bipush 16
    //   473: iaload
    //   474: getstatic 232	s:ak	[I
    //   477: bipush 21
    //   479: iaload
    //   480: getstatic 232	s:ak	[I
    //   483: bipush 6
    //   485: iaload
    //   486: invokevirtual 266	dl:b	(III)V
    //   489: invokestatic 252	cn:a	()V
    //   492: ldc 1
    //   494: invokevirtual 300	java/lang/String:length	()I
    //   497: pop
    //   498: ldc 3
    //   500: invokevirtual 300	java/lang/String:length	()I
    //   503: ldc 3
    //   505: invokevirtual 300	java/lang/String:length	()I
    //   508: iconst_m1
    //   509: ixor
    //   510: iand
    //   511: bipush 110
    //   513: bipush 69
    //   515: ixor
    //   516: sipush 183
    //   519: sipush 156
    //   522: ixor
    //   523: iconst_m1
    //   524: ixor
    //   525: iand
    //   526: if_icmpeq +39 -> 565
    //   529: return
    //   530: ldc 65
    //   532: invokestatic 288	fn:a	(Ljava/lang/String;)V
    //   535: ldc 1
    //   537: invokevirtual 300	java/lang/String:length	()I
    //   540: pop
    //   541: aconst_null
    //   542: ifnull +23 -> 565
    //   545: return
    //   546: getstatic 196	fn:dh	[Lao;
    //   549: getstatic 232	s:ak	[I
    //   552: bipush 8
    //   554: iaload
    //   555: getstatic 232	s:ak	[I
    //   558: bipush 24
    //   560: iaload
    //   561: invokestatic 335	s:g	(I)Lao;
    //   564: aastore
    //   565: aload_1
    //   566: getfield 143	ao:r	I
    //   569: getstatic 232	s:ak	[I
    //   572: bipush 10
    //   574: iaload
    //   575: invokestatic 340	s:i	(II)Z
    //   578: ifeq +132 -> 710
    //   581: getstatic 160	cz:m	Z
    //   584: invokestatic 329	s:d	(I)Z
    //   587: ifeq +123 -> 710
    //   590: getstatic 232	s:ak	[I
    //   593: bipush 24
    //   595: iaload
    //   596: invokestatic 280	dt:d	(I)I
    //   599: invokestatic 333	s:f	(I)Z
    //   602: ifeq +89 -> 691
    //   605: invokestatic 283	dt:g	()Ldt;
    //   608: getfield 181	dt:ga	I
    //   611: getstatic 232	s:ak	[I
    //   614: bipush 11
    //   616: iaload
    //   617: invokestatic 330	s:d	(II)Z
    //   620: ifeq +51 -> 671
    //   623: invokestatic 264	dl:ae	()Ldl;
    //   626: getstatic 232	s:ak	[I
    //   629: bipush 16
    //   631: iaload
    //   632: getstatic 232	s:ak	[I
    //   635: bipush 21
    //   637: iaload
    //   638: getstatic 232	s:ak	[I
    //   641: bipush 6
    //   643: iaload
    //   644: invokevirtual 266	dl:b	(III)V
    //   647: invokestatic 252	cn:a	()V
    //   650: ldc 1
    //   652: invokevirtual 300	java/lang/String:length	()I
    //   655: pop
    //   656: bipush 96
    //   658: bipush 62
    //   660: ixor
    //   661: bipush 53
    //   663: bipush 111
    //   665: ixor
    //   666: ixor
    //   667: ifge +43 -> 710
    //   670: return
    //   671: ldc 65
    //   673: invokestatic 288	fn:a	(Ljava/lang/String;)V
    //   676: ldc 1
    //   678: invokevirtual 300	java/lang/String:length	()I
    //   681: pop
    //   682: bipush 92
    //   684: bipush 88
    //   686: ixor
    //   687: ifgt +23 -> 710
    //   690: return
    //   691: getstatic 196	fn:dh	[Lao;
    //   694: getstatic 232	s:ak	[I
    //   697: bipush 9
    //   699: iaload
    //   700: getstatic 232	s:ak	[I
    //   703: bipush 24
    //   705: iaload
    //   706: invokestatic 335	s:g	(I)Lao;
    //   709: aastore
    //   710: aload 8
    //   712: invokestatic 325	s:a	(Ljava/lang/Object;)Z
    //   715: ifeq +81 -> 796
    //   718: aload 8
    //   720: getfield 140	ao:j	Lat;
    //   723: getfield 145	at:b	B
    //   726: getstatic 232	s:ak	[I
    //   729: bipush 7
    //   731: iaload
    //   732: invokestatic 340	s:i	(II)Z
    //   735: ifeq +61 -> 796
    //   738: aload 8
    //   740: getfield 140	ao:j	Lat;
    //   743: getfield 146	at:f	S
    //   746: getstatic 232	s:ak	[I
    //   749: bipush 9
    //   751: iaload
    //   752: invokestatic 332	s:e	(II)Z
    //   755: ifeq +41 -> 796
    //   758: invokestatic 283	dt:g	()Ldt;
    //   761: getfield 184	dt:w	[Lao;
    //   764: iload 7
    //   766: aconst_null
    //   767: aastore
    //   768: getstatic 196	fn:dh	[Lao;
    //   771: iload 4
    //   773: iinc 4 1
    //   776: aload 8
    //   778: aastore
    //   779: iload 6
    //   781: getstatic 207	fn:fn	[I
    //   784: aload 8
    //   786: getfield 140	ao:j	Lat;
    //   789: getfield 146	at:f	S
    //   792: iaload
    //   793: iadd
    //   794: istore 6
    //   796: iinc 7 1
    //   799: ldc 1
    //   801: invokevirtual 300	java/lang/String:length	()I
    //   804: pop
    //   805: ldc 4
    //   807: invokevirtual 300	java/lang/String:length	()I
    //   810: ldc 3
    //   812: invokevirtual 300	java/lang/String:length	()I
    //   815: ineg
    //   816: if_icmpge -444 -> 372
    //   819: return
    //   820: ldc2_w 136
    //   823: invokestatic 311	java/lang/Thread:sleep	(J)V
    //   826: ldc 1
    //   828: invokevirtual 300	java/lang/String:length	()I
    //   831: pop
    //   832: bipush 61
    //   834: bipush 57
    //   836: ixor
    //   837: bipush 62
    //   839: bipush 58
    //   841: ixor
    //   842: if_icmpeq +10 -> 852
    //   845: return
    //   846: ldc 1
    //   848: invokevirtual 300	java/lang/String:length	()I
    //   851: pop2
    //   852: invokestatic 264	dl:ae	()Ldl;
    //   855: aload_1
    //   856: getstatic 196	fn:dh	[Lao;
    //   859: invokevirtual 261	dl:a	(Lao;[Lao;)V
    //   862: invokestatic 264	dl:ae	()Ldl;
    //   865: invokestatic 283	dt:g	()Ldt;
    //   868: getfield 169	dt:ci	Ljava/lang/String;
    //   871: invokevirtual 270	dl:r	(Ljava/lang/String;)V
    //   874: invokestatic 253	cn:ae	()Z
    //   877: ldc 1
    //   879: invokevirtual 300	java/lang/String:length	()I
    //   882: pop2
    //   883: getstatic 196	fn:dh	[Lao;
    //   886: getstatic 232	s:ak	[I
    //   889: iconst_1
    //   890: iaload
    //   891: aaload
    //   892: invokestatic 326	s:b	(Ljava/lang/Object;)Z
    //   895: ifeq -75 -> 820
    //   898: iinc 5 1
    //   901: ldc 1
    //   903: invokevirtual 300	java/lang/String:length	()I
    //   906: pop
    //   907: ldc 4
    //   909: invokevirtual 300	java/lang/String:length	()I
    //   912: bipush 64
    //   914: bipush 68
    //   916: ixor
    //   917: if_icmplt -597 -> 320
    //   920: return
    //   921: aconst_null
    //   922: putstatic 208	fn:fr	Lao;
    //   925: return
    //   926: getstatic 149	cz:a	I
    //   929: invokestatic 339	s:i	(I)Z
    //   932: ifeq +28 -> 960
    //   935: getstatic 149	cz:a	I
    //   938: dup
    //   939: istore_3
    //   940: ldc 1
    //   942: invokevirtual 300	java/lang/String:length	()I
    //   945: pop
    //   946: ldc 3
    //   948: invokevirtual 300	java/lang/String:length	()I
    //   951: ldc 3
    //   953: invokevirtual 300	java/lang/String:length	()I
    //   956: if_icmple +55 -> 1011
    //   959: return
    //   960: getstatic 232	s:ak	[I
    //   963: iconst_1
    //   964: iaload
    //   965: invokestatic 285	dt:k	(I)Lfb;
    //   968: dup
    //   969: astore 5
    //   971: invokestatic 325	s:a	(Ljava/lang/Object;)Z
    //   974: ifeq +30 -> 1004
    //   977: aload 5
    //   979: getfield 187	fb:f	I
    //   982: dup
    //   983: istore_3
    //   984: ldc 1
    //   986: invokevirtual 300	java/lang/String:length	()I
    //   989: pop
    //   990: ldc 4
    //   992: invokevirtual 300	java/lang/String:length	()I
    //   995: ldc 3
    //   997: invokevirtual 300	java/lang/String:length	()I
    //   1000: if_icmpgt +11 -> 1011
    //   1003: return
    //   1004: getstatic 232	s:ak	[I
    //   1007: iconst_5
    //   1008: iaload
    //   1009: dup
    //   1010: istore_3
    //   1011: istore 4
    //   1013: iload_3
    //   1014: i2s
    //   1015: istore 6
    //   1017: iload 4
    //   1019: invokestatic 331	s:e	(I)Z
    //   1022: ifeq +18 -> 1040
    //   1025: ldc 51
    //   1027: invokestatic 288	fn:a	(Ljava/lang/String;)V
    //   1030: getstatic 232	s:ak	[I
    //   1033: bipush 6
    //   1035: iaload
    //   1036: putstatic 226	s:ae	Z
    //   1039: return
    //   1040: getstatic 185	et:o	S
    //   1043: iload 6
    //   1045: invokestatic 340	s:i	(II)Z
    //   1048: ifeq +68 -> 1116
    //   1051: getstatic 232	s:ak	[I
    //   1054: iconst_2
    //   1055: iaload
    //   1056: putstatic 176	dt:er	I
    //   1059: getstatic 232	s:ak	[I
    //   1062: iconst_1
    //   1063: iaload
    //   1064: putstatic 164	dn:f	Z
    //   1067: getstatic 232	s:ak	[I
    //   1070: iconst_1
    //   1071: iaload
    //   1072: putstatic 167	dt:bb	Z
    //   1075: getstatic 232	s:ak	[I
    //   1078: iconst_1
    //   1079: iaload
    //   1080: putstatic 182	dt:h	Z
    //   1083: getstatic 232	s:ak	[I
    //   1086: iconst_1
    //   1087: iaload
    //   1088: putstatic 171	dt:dj	Z
    //   1091: aload_0
    //   1092: getstatic 232	s:ak	[I
    //   1095: iconst_0
    //   1096: iaload
    //   1097: invokevirtual 319	r:c	(I)V
    //   1100: aload_0
    //   1101: getstatic 232	s:ak	[I
    //   1104: iconst_5
    //   1105: iaload
    //   1106: getstatic 232	s:ak	[I
    //   1109: bipush 6
    //   1111: iaload
    //   1112: invokevirtual 318	r:b	(II)V
    //   1115: return
    //   1116: aload_0
    //   1117: iload 6
    //   1119: getstatic 157	cz:j	I
    //   1122: getstatic 232	s:ak	[I
    //   1125: iconst_5
    //   1126: iaload
    //   1127: getstatic 232	s:ak	[I
    //   1130: iconst_5
    //   1131: iaload
    //   1132: invokevirtual 315	r:a	(IIII)V
    //   1135: getstatic 232	s:ak	[I
    //   1138: bipush 6
    //   1140: iaload
    //   1141: putstatic 168	dt:bc	Z
    //   1144: return
    // Local variable table:
    //   start	length	slot	name	signature
    //   0	1145	0	this	s
    //   0	1145	1	paramao	ao
    //   0	1145	2	paramInt	int
    //   11	1003	3	i	int
    //   356	662	4	j	int
    //   318	3	5	k	int
    //   969	9	5	localfb	fb
    //   363	755	6	m	int
    //   370	427	7	n	int
    //   405	380	8	localao	ao
    //   846	1	10	localInterruptedException	InterruptedException
    // Exception table:
    //   from	to	target	type
    //   820	826	846	java/lang/InterruptedException
  }
  
  private static boolean f(int paramInt1, int paramInt2)
  {
    return paramInt1 != paramInt2;
  }
  
  private static boolean f(int paramInt)
  {
    return paramInt < 0;
  }
  
  public final void m()
  {
    super.m();
    if (a(ah)) {
      if (i(ah.m, ak[2]))
      {
        ah = dt.g().s[ah.j.b];
        "".length();
        if (((0x80 ^ 0x93 ^ 0x5A ^ 0x44) & (0xBA ^ 0x80 ^ 0x2 ^ 0x35 ^ -" ".length())) >= ("  ".length() & ("  ".length() ^ -" ".length()))) {}
      }
      else if (i(ah.m, ak[3]))
      {
        ah = dt.g().w[ah.n];
        "".length();
        if (" ".length() >= 0) {}
      }
      else if (i(ah.m, ak[4]))
      {
        ah = dt.g().ea[ah.n];
        "".length();
        if (-" ".length() < " ".length()) {}
      }
      else
      {
        System.out.println("Loi reset itemNV");
      }
    }
    if (a(ad))
    {
      if (i(ad.m, ak[2]))
      {
        ad = dt.g().s[ad.j.b];
        return;
      }
      if (i(ad.m, ak[3]))
      {
        ad = dt.g().w[ad.n];
        return;
      }
      System.out.println("Loi reset itemBody");
    }
  }
  
  private static boolean g(int paramInt1, int paramInt2)
  {
    return paramInt1 < paramInt2;
  }
  
  private static ao g(int paramInt)
  {
    paramInt = ak[1];
    while (g(paramInt, dt.g().w.length))
    {
      ao localao;
      if ((a(localao = dt.g().w[paramInt])) && (i(localao.j.b, ak[27])) && (i(localao.j.f, ak[24]))) {
        return localao;
      }
      paramInt++;
      "".length();
      if ((0x1A ^ 0x1E) <= ((0x57 ^ 0x40) & (0x65 ^ 0x72 ^ 0xFFFFFFFF))) {
        return null;
      }
    }
    return null;
  }
  
  private static ao[] h(int paramInt1, int paramInt2)
  {
    switch (paramInt1)
    {
    case 0: 
      if (i(paramInt2, ak[6])) {
        return fn.af;
      }
      return fn.ar;
    case 1: 
      return fn.fy;
    case 2: 
      if (i(paramInt2, ak[6])) {
        return fn.an;
      }
      return fn.cx;
    case 3: 
      return fn.cz;
    case 4: 
      if (i(paramInt2, ak[6])) {
        return fn.fc;
      }
      return fn.dt;
    case 5: 
      return fn.at;
    case 6: 
      if (i(paramInt2, ak[6])) {
        return fn.fk;
      }
      return fn.el;
    case 7: 
      return fn.fa;
    case 8: 
      if (i(paramInt2, ak[6])) {
        return fn.fu;
      }
      return fn.ap;
    case 9: 
      return fn.n;
    }
    return null;
  }
  
  private static boolean h(int paramInt)
  {
    return paramInt >= 0;
  }
  
  private static boolean i(int paramInt1, int paramInt2)
  {
    return paramInt1 == paramInt2;
  }
  
  private static boolean i(int paramInt)
  {
    return paramInt > 0;
  }
  
  private static boolean j(int paramInt)
  {
    return paramInt == 0;
  }
  
  public static void d() {}
}


/* Location:              C:\Users\Admin\OneDrive\Documents\NSOv2_test.jar!\s.class
 * Java compiler version: 1 (45.3)
 * JD-Core Version:       0.7.1
 */