public final class v
  implements Runnable
{
  private static int[] a;
  private final int b;
  private final int c;
  private final int d;
  
  public static void a() {}
  
  static
  {
    cs.a(35);
    a();
  }
  
  private static boolean a(int paramInt1, int paramInt2)
  {
    return paramInt1 < paramInt2;
  }
  
  public v(int paramInt1, int paramInt2, int paramInt3)
  {
    this.d = paramInt1;
    this.c = paramInt2;
    this.b = paramInt3;
  }
  
  /* Error */
  public final void run()
  {
    // Byte code:
    //   0: getstatic 13	v:a	[I
    //   3: iconst_0
    //   4: iaload
    //   5: invokestatic 21	fn:b	(I)V
    //   8: invokestatic 18	dl:ae	()Ldl;
    //   11: getstatic 13	v:a	[I
    //   14: iconst_0
    //   15: iaload
    //   16: invokevirtual 20	dl:s	(I)V
    //   19: getstatic 13	v:a	[I
    //   22: iconst_1
    //   23: iaload
    //   24: istore_1
    //   25: iload_1
    //   26: aload_0
    //   27: getfield 16	v:d	I
    //   30: invokestatic 26	v:a	(II)Z
    //   33: ifeq +59 -> 92
    //   36: invokestatic 18	dl:ae	()Ldl;
    //   39: getstatic 13	v:a	[I
    //   42: iconst_0
    //   43: iaload
    //   44: aload_0
    //   45: getfield 15	v:c	I
    //   48: aload_0
    //   49: getfield 14	v:b	I
    //   52: invokevirtual 19	dl:c	(III)V
    //   55: ldc2_w 11
    //   58: invokestatic 24	java/lang/Thread:sleep	(J)V
    //   61: ldc 1
    //   63: invokevirtual 23	java/lang/String:length	()I
    //   66: pop
    //   67: aconst_null
    //   68: ifnull +10 -> 78
    //   71: return
    //   72: ldc 1
    //   74: invokevirtual 23	java/lang/String:length	()I
    //   77: pop2
    //   78: iinc 1 1
    //   81: ldc 1
    //   83: invokevirtual 23	java/lang/String:length	()I
    //   86: pop
    //   87: aconst_null
    //   88: ifnull -63 -> 25
    //   91: return
    //   92: return
    // Local variable table:
    //   start	length	slot	name	signature
    //   0	93	0	this	v
    //   24	55	1	i	int
    //   72	1	2	localInterruptedException	InterruptedException
    // Exception table:
    //   from	to	target	type
    //   55	61	72	java/lang/InterruptedException
  }
  
  private static void c()
  {
    a = new int[2];
    a[0] = (0x4E ^ 0x6F);
    a[1] = ((0x48 ^ 0x54) & (0x34 ^ 0x28 ^ 0xFFFFFFFF));
  }
  
  public static void b() {}
}


/* Location:              C:\Users\Admin\OneDrive\Documents\NSOv2_test.jar!\v.class
 * Java compiler version: 1 (45.3)
 * JD-Core Version:       0.7.1
 */