import java.util.Vector;

public final class x
  extends r
{
  private boolean w;
  public static boolean v;
  private String x;
  private long y;
  private boolean z;
  private int aa;
  private ci ab;
  private boolean ac;
  private static int[] ad;
  private ci ae;
  private int af;
  
  /* Error */
  public final void a(String paramString1, String paramString2)
  {
    // Byte code:
    //   0: aload_2
    //   1: ldc 2
    //   3: invokestatic 141	dn:a	(Ljava/lang/String;Ljava/lang/String;)[Ljava/lang/String;
    //   6: astore_2
    //   7: aload_0
    //   8: getfield 113	x:w	Z
    //   11: invokestatic 187	x:g	(I)Z
    //   14: ifeq +19 -> 33
    //   17: getstatic 103	fn:x	Z
    //   20: invokestatic 179	x:d	(I)Z
    //   23: ifeq +1431 -> 1454
    //   26: aload_1
    //   27: ldc 30
    //   29: invokestatic 142	dn:d	(Ljava/lang/String;Ljava/lang/String;)V
    //   32: return
    //   33: aload_2
    //   34: getstatic 109	x:ad	[I
    //   37: iconst_1
    //   38: iaload
    //   39: aaload
    //   40: invokevirtual 155	java/lang/String:toLowerCase	()Ljava/lang/String;
    //   43: ldc 32
    //   45: invokevirtual 153	java/lang/String:equals	(Ljava/lang/Object;)Z
    //   48: invokestatic 187	x:g	(I)Z
    //   51: ifeq +615 -> 666
    //   54: new 40	ci
    //   57: dup
    //   58: invokespecial 123	ci:<init>	()V
    //   61: astore_3
    //   62: new 40	ci
    //   65: dup
    //   66: invokespecial 123	ci:<init>	()V
    //   69: astore 4
    //   71: getstatic 109	x:ad	[I
    //   74: iconst_1
    //   75: iaload
    //   76: istore 5
    //   78: getstatic 109	x:ad	[I
    //   81: iconst_0
    //   82: iaload
    //   83: istore 6
    //   85: aload_2
    //   86: arraylength
    //   87: getstatic 109	x:ad	[I
    //   90: iconst_0
    //   91: iaload
    //   92: isub
    //   93: istore 7
    //   95: iload 6
    //   97: iload 7
    //   99: invokestatic 185	x:f	(II)Z
    //   102: ifeq +512 -> 614
    //   105: aload_2
    //   106: iload 6
    //   108: aaload
    //   109: astore 8
    //   111: aload_2
    //   112: iload 6
    //   114: getstatic 109	x:ad	[I
    //   117: iconst_0
    //   118: iaload
    //   119: iadd
    //   120: aaload
    //   121: astore 9
    //   123: aload 8
    //   125: invokestatic 118	aj:a	(Ljava/lang/String;)Ldf;
    //   128: dup
    //   129: astore 10
    //   131: invokestatic 173	x:a	(Ljava/lang/Object;)Z
    //   134: ifeq +427 -> 561
    //   137: aload 10
    //   139: getfield 81	df:b	I
    //   142: invokestatic 181	x:e	(I)Z
    //   145: ifeq +416 -> 561
    //   148: aload 10
    //   150: getfield 81	df:b	I
    //   153: invokestatic 181	x:e	(I)Z
    //   156: ifeq +71 -> 227
    //   159: aload 10
    //   161: getfield 85	df:i	Lat;
    //   164: getfield 79	at:f	S
    //   167: invokestatic 143	dt:b	(I)I
    //   170: aload 10
    //   172: getfield 83	df:g	I
    //   175: invokestatic 185	x:f	(II)Z
    //   178: ifeq +49 -> 227
    //   181: aload_1
    //   182: new 53	java/lang/StringBuffer
    //   185: dup
    //   186: ldc 14
    //   188: invokespecial 156	java/lang/StringBuffer:<init>	(Ljava/lang/String;)V
    //   191: aload 8
    //   193: invokevirtual 158	java/lang/StringBuffer:append	(Ljava/lang/String;)Ljava/lang/StringBuffer;
    //   196: ldc 6
    //   198: invokevirtual 158	java/lang/StringBuffer:append	(Ljava/lang/String;)Ljava/lang/StringBuffer;
    //   201: invokevirtual 159	java/lang/StringBuffer:toString	()Ljava/lang/String;
    //   204: invokestatic 142	dn:d	(Ljava/lang/String;Ljava/lang/String;)V
    //   207: ldc 1
    //   209: invokevirtual 154	java/lang/String:length	()I
    //   212: pop
    //   213: ldc 4
    //   215: invokevirtual 154	java/lang/String:length	()I
    //   218: ldc 3
    //   220: invokevirtual 154	java/lang/String:length	()I
    //   223: if_icmpge +364 -> 587
    //   226: return
    //   227: aload 9
    //   229: invokestatic 152	java/lang/Integer:parseInt	(Ljava/lang/String;)I
    //   232: istore 11
    //   234: ldc 1
    //   236: invokevirtual 154	java/lang/String:length	()I
    //   239: pop
    //   240: ldc 2
    //   242: invokevirtual 154	java/lang/String:length	()I
    //   245: ineg
    //   246: ldc 2
    //   248: invokevirtual 154	java/lang/String:length	()I
    //   251: if_icmplt +63 -> 314
    //   254: return
    //   255: ldc 1
    //   257: invokevirtual 154	java/lang/String:length	()I
    //   260: pop2
    //   261: aload_1
    //   262: new 53	java/lang/StringBuffer
    //   265: dup
    //   266: ldc 14
    //   268: invokespecial 156	java/lang/StringBuffer:<init>	(Ljava/lang/String;)V
    //   271: aload 8
    //   273: invokevirtual 158	java/lang/StringBuffer:append	(Ljava/lang/String;)Ljava/lang/StringBuffer;
    //   276: ldc 10
    //   278: invokevirtual 158	java/lang/StringBuffer:append	(Ljava/lang/String;)Ljava/lang/StringBuffer;
    //   281: invokevirtual 159	java/lang/StringBuffer:toString	()Ljava/lang/String;
    //   284: invokestatic 142	dn:d	(Ljava/lang/String;Ljava/lang/String;)V
    //   287: ldc 1
    //   289: invokevirtual 154	java/lang/String:length	()I
    //   292: pop
    //   293: bipush 127
    //   295: bipush 24
    //   297: ixor
    //   298: bipush 126
    //   300: bipush 29
    //   302: ixor
    //   303: ixor
    //   304: ldc 2
    //   306: invokevirtual 154	java/lang/String:length	()I
    //   309: ineg
    //   310: if_icmpgt +277 -> 587
    //   313: return
    //   314: aload 10
    //   316: invokevirtual 129	df:c	()I
    //   319: iload 11
    //   321: invokestatic 182	x:e	(II)Z
    //   324: ifeq +50 -> 374
    //   327: aload_1
    //   328: new 53	java/lang/StringBuffer
    //   331: dup
    //   332: ldc 14
    //   334: invokespecial 156	java/lang/StringBuffer:<init>	(Ljava/lang/String;)V
    //   337: aload 8
    //   339: invokevirtual 158	java/lang/StringBuffer:append	(Ljava/lang/String;)Ljava/lang/StringBuffer;
    //   342: ldc 9
    //   344: invokevirtual 158	java/lang/StringBuffer:append	(Ljava/lang/String;)Ljava/lang/StringBuffer;
    //   347: invokevirtual 159	java/lang/StringBuffer:toString	()Ljava/lang/String;
    //   350: invokestatic 142	dn:d	(Ljava/lang/String;Ljava/lang/String;)V
    //   353: ldc 1
    //   355: invokevirtual 154	java/lang/String:length	()I
    //   358: pop
    //   359: ldc 2
    //   361: invokevirtual 154	java/lang/String:length	()I
    //   364: ineg
    //   365: ldc 3
    //   367: invokevirtual 154	java/lang/String:length	()I
    //   370: if_icmplt +217 -> 587
    //   373: return
    //   374: aload 10
    //   376: getfield 85	df:i	Lat;
    //   379: getfield 78	at:c	Z
    //   382: invokestatic 187	x:g	(I)Z
    //   385: ifeq +28 -> 413
    //   388: getstatic 109	x:ad	[I
    //   391: iconst_0
    //   392: iaload
    //   393: ldc 1
    //   395: invokevirtual 154	java/lang/String:length	()I
    //   398: pop
    //   399: ldc 3
    //   401: invokevirtual 154	java/lang/String:length	()I
    //   404: ldc 3
    //   406: invokevirtual 154	java/lang/String:length	()I
    //   409: if_icmple +6 -> 415
    //   412: return
    //   413: iload 11
    //   415: istore 12
    //   417: iload 5
    //   419: iload 12
    //   421: iadd
    //   422: getstatic 109	x:ad	[I
    //   425: iconst_2
    //   426: iaload
    //   427: invokestatic 177	x:c	(II)Z
    //   430: ifeq +44 -> 474
    //   433: aload_1
    //   434: new 53	java/lang/StringBuffer
    //   437: dup
    //   438: ldc 14
    //   440: invokespecial 156	java/lang/StringBuffer:<init>	(Ljava/lang/String;)V
    //   443: aload 8
    //   445: invokevirtual 158	java/lang/StringBuffer:append	(Ljava/lang/String;)Ljava/lang/StringBuffer;
    //   448: ldc 11
    //   450: invokevirtual 158	java/lang/StringBuffer:append	(Ljava/lang/String;)Ljava/lang/StringBuffer;
    //   453: invokevirtual 159	java/lang/StringBuffer:toString	()Ljava/lang/String;
    //   456: invokestatic 142	dn:d	(Ljava/lang/String;Ljava/lang/String;)V
    //   459: ldc 1
    //   461: invokevirtual 154	java/lang/String:length	()I
    //   464: pop
    //   465: bipush 93
    //   467: bipush 88
    //   469: ixor
    //   470: ifgt +144 -> 614
    //   473: return
    //   474: iload 5
    //   476: iload 12
    //   478: iadd
    //   479: istore 5
    //   481: aload_3
    //   482: aload 10
    //   484: invokevirtual 124	ci:addElement	(Ljava/lang/Object;)V
    //   487: aload 4
    //   489: new 50	java/lang/Integer
    //   492: dup
    //   493: iload 11
    //   495: invokespecial 150	java/lang/Integer:<init>	(I)V
    //   498: invokevirtual 124	ci:addElement	(Ljava/lang/Object;)V
    //   501: ldc 1
    //   503: invokevirtual 154	java/lang/String:length	()I
    //   506: pop
    //   507: sipush 147
    //   510: sipush 192
    //   513: ixor
    //   514: ldc 4
    //   516: invokevirtual 154	java/lang/String:length	()I
    //   519: ixor
    //   520: bipush 29
    //   522: sipush 169
    //   525: iadd
    //   526: bipush 66
    //   528: isub
    //   529: bipush 99
    //   531: iadd
    //   532: bipush 20
    //   534: bipush 88
    //   536: iadd
    //   537: bipush 47
    //   539: isub
    //   540: bipush 122
    //   542: iadd
    //   543: ixor
    //   544: ldc 2
    //   546: invokevirtual 154	java/lang/String:length	()I
    //   549: ineg
    //   550: ixor
    //   551: iand
    //   552: ldc 4
    //   554: invokevirtual 154	java/lang/String:length	()I
    //   557: if_icmple +30 -> 587
    //   560: return
    //   561: aload_1
    //   562: new 53	java/lang/StringBuffer
    //   565: dup
    //   566: ldc 14
    //   568: invokespecial 156	java/lang/StringBuffer:<init>	(Ljava/lang/String;)V
    //   571: aload 8
    //   573: invokevirtual 158	java/lang/StringBuffer:append	(Ljava/lang/String;)Ljava/lang/StringBuffer;
    //   576: ldc 8
    //   578: invokevirtual 158	java/lang/StringBuffer:append	(Ljava/lang/String;)Ljava/lang/StringBuffer;
    //   581: invokevirtual 159	java/lang/StringBuffer:toString	()Ljava/lang/String;
    //   584: invokestatic 142	dn:d	(Ljava/lang/String;Ljava/lang/String;)V
    //   587: iinc 6 2
    //   590: ldc 1
    //   592: invokevirtual 154	java/lang/String:length	()I
    //   595: pop
    //   596: sipush 152
    //   599: sipush 156
    //   602: ixor
    //   603: sipush 134
    //   606: sipush 130
    //   609: ixor
    //   610: if_icmpge -515 -> 95
    //   613: return
    //   614: aload_3
    //   615: invokevirtual 166	java/util/Vector:size	()I
    //   618: invokestatic 179	x:d	(I)Z
    //   621: ifeq +10 -> 631
    //   624: aload_1
    //   625: ldc 19
    //   627: invokestatic 142	dn:d	(Ljava/lang/String;Ljava/lang/String;)V
    //   630: return
    //   631: aload_0
    //   632: aload_1
    //   633: putfield 114	x:x	Ljava/lang/String;
    //   636: aload_0
    //   637: getstatic 109	x:ad	[I
    //   640: iconst_1
    //   641: iaload
    //   642: putfield 116	x:z	Z
    //   645: aload_0
    //   646: aload_3
    //   647: putfield 107	x:ab	Lci;
    //   650: aload_0
    //   651: aload 4
    //   653: putfield 110	x:ae	Lci;
    //   656: aload_0
    //   657: getstatic 109	x:ad	[I
    //   660: iconst_0
    //   661: iaload
    //   662: putfield 113	x:w	Z
    //   665: return
    //   666: aload_2
    //   667: getstatic 109	x:ad	[I
    //   670: iconst_1
    //   671: iaload
    //   672: aaload
    //   673: invokevirtual 155	java/lang/String:toLowerCase	()Ljava/lang/String;
    //   676: ldc 34
    //   678: invokevirtual 153	java/lang/String:equals	(Ljava/lang/Object;)Z
    //   681: invokestatic 179	x:d	(I)Z
    //   684: ifeq +171 -> 855
    //   687: aload_2
    //   688: getstatic 109	x:ad	[I
    //   691: iconst_1
    //   692: iaload
    //   693: aaload
    //   694: invokevirtual 155	java/lang/String:toLowerCase	()Ljava/lang/String;
    //   697: ldc 33
    //   699: invokevirtual 153	java/lang/String:equals	(Ljava/lang/Object;)Z
    //   702: invokestatic 187	x:g	(I)Z
    //   705: ifeq +37 -> 742
    //   708: aload_0
    //   709: aload_1
    //   710: putfield 114	x:x	Ljava/lang/String;
    //   713: aload_0
    //   714: getstatic 109	x:ad	[I
    //   717: iconst_1
    //   718: iaload
    //   719: putfield 116	x:z	Z
    //   722: aload_0
    //   723: aconst_null
    //   724: putfield 107	x:ab	Lci;
    //   727: aload_0
    //   728: aconst_null
    //   729: putfield 110	x:ae	Lci;
    //   732: aload_0
    //   733: getstatic 109	x:ad	[I
    //   736: iconst_0
    //   737: iaload
    //   738: putfield 113	x:w	Z
    //   741: return
    //   742: aload_2
    //   743: getstatic 109	x:ad	[I
    //   746: iconst_1
    //   747: iaload
    //   748: aaload
    //   749: invokevirtual 155	java/lang/String:toLowerCase	()Ljava/lang/String;
    //   752: ldc 35
    //   754: invokevirtual 153	java/lang/String:equals	(Ljava/lang/Object;)Z
    //   757: invokestatic 187	x:g	(I)Z
    //   760: ifeq +62 -> 822
    //   763: invokestatic 122	aj:d	()Z
    //   766: invokestatic 187	x:g	(I)Z
    //   769: ifeq +46 -> 815
    //   772: aload_0
    //   773: aload_1
    //   774: putfield 114	x:x	Ljava/lang/String;
    //   777: aload_0
    //   778: getstatic 109	x:ad	[I
    //   781: iconst_0
    //   782: iaload
    //   783: putfield 116	x:z	Z
    //   786: aload_0
    //   787: getstatic 109	x:ad	[I
    //   790: iconst_1
    //   791: iaload
    //   792: putfield 108	x:ac	Z
    //   795: aload_0
    //   796: aconst_null
    //   797: putfield 107	x:ab	Lci;
    //   800: aload_0
    //   801: aconst_null
    //   802: putfield 110	x:ae	Lci;
    //   805: aload_0
    //   806: getstatic 109	x:ad	[I
    //   809: iconst_0
    //   810: iaload
    //   811: putfield 113	x:w	Z
    //   814: return
    //   815: aload_1
    //   816: ldc 21
    //   818: invokestatic 142	dn:d	(Ljava/lang/String;Ljava/lang/String;)V
    //   821: return
    //   822: aload_1
    //   823: ldc 16
    //   825: invokestatic 142	dn:d	(Ljava/lang/String;Ljava/lang/String;)V
    //   828: aload_1
    //   829: ldc 18
    //   831: invokestatic 142	dn:d	(Ljava/lang/String;Ljava/lang/String;)V
    //   834: aload_1
    //   835: invokestatic 121	aj:c	(Ljava/lang/String;)V
    //   838: aload_1
    //   839: ldc 15
    //   841: invokestatic 142	dn:d	(Ljava/lang/String;Ljava/lang/String;)V
    //   844: aload_1
    //   845: invokestatic 120	aj:b	(Ljava/lang/String;)V
    //   848: aload_1
    //   849: ldc 15
    //   851: invokestatic 142	dn:d	(Ljava/lang/String;Ljava/lang/String;)V
    //   854: return
    //   855: new 40	ci
    //   858: dup
    //   859: invokespecial 123	ci:<init>	()V
    //   862: astore_3
    //   863: new 40	ci
    //   866: dup
    //   867: invokespecial 123	ci:<init>	()V
    //   870: astore 4
    //   872: getstatic 109	x:ad	[I
    //   875: iconst_1
    //   876: iaload
    //   877: istore 5
    //   879: getstatic 109	x:ad	[I
    //   882: iconst_0
    //   883: iaload
    //   884: istore 6
    //   886: aload_2
    //   887: arraylength
    //   888: getstatic 109	x:ad	[I
    //   891: iconst_0
    //   892: iaload
    //   893: isub
    //   894: istore 7
    //   896: iload 6
    //   898: iload 7
    //   900: invokestatic 185	x:f	(II)Z
    //   903: ifeq +500 -> 1403
    //   906: aload_2
    //   907: iload 6
    //   909: aaload
    //   910: astore 8
    //   912: aload_2
    //   913: iload 6
    //   915: getstatic 109	x:ad	[I
    //   918: iconst_0
    //   919: iaload
    //   920: iadd
    //   921: aaload
    //   922: dup
    //   923: astore 9
    //   925: invokestatic 118	aj:a	(Ljava/lang/String;)Ldf;
    //   928: dup
    //   929: astore 10
    //   931: invokestatic 173	x:a	(Ljava/lang/Object;)Z
    //   934: ifeq +401 -> 1335
    //   937: aload 10
    //   939: getfield 81	df:b	I
    //   942: invokestatic 181	x:e	(I)Z
    //   945: ifeq +390 -> 1335
    //   948: aload 10
    //   950: getfield 81	df:b	I
    //   953: invokestatic 181	x:e	(I)Z
    //   956: ifeq +72 -> 1028
    //   959: aload 10
    //   961: getfield 85	df:i	Lat;
    //   964: getfield 79	at:f	S
    //   967: invokestatic 143	dt:b	(I)I
    //   970: aload 10
    //   972: getfield 83	df:g	I
    //   975: invokestatic 185	x:f	(II)Z
    //   978: ifeq +50 -> 1028
    //   981: aload_1
    //   982: new 53	java/lang/StringBuffer
    //   985: dup
    //   986: ldc 14
    //   988: invokespecial 156	java/lang/StringBuffer:<init>	(Ljava/lang/String;)V
    //   991: aload 9
    //   993: invokevirtual 158	java/lang/StringBuffer:append	(Ljava/lang/String;)Ljava/lang/StringBuffer;
    //   996: ldc 6
    //   998: invokevirtual 158	java/lang/StringBuffer:append	(Ljava/lang/String;)Ljava/lang/StringBuffer;
    //   1001: invokevirtual 159	java/lang/StringBuffer:toString	()Ljava/lang/String;
    //   1004: invokestatic 142	dn:d	(Ljava/lang/String;Ljava/lang/String;)V
    //   1007: ldc 1
    //   1009: invokevirtual 154	java/lang/String:length	()I
    //   1012: pop
    //   1013: bipush 108
    //   1015: bipush 104
    //   1017: ixor
    //   1018: ldc 2
    //   1020: invokevirtual 154	java/lang/String:length	()I
    //   1023: ineg
    //   1024: if_icmpge +337 -> 1361
    //   1027: return
    //   1028: aload 8
    //   1030: invokestatic 152	java/lang/Integer:parseInt	(Ljava/lang/String;)I
    //   1033: istore 11
    //   1035: ldc 1
    //   1037: invokevirtual 154	java/lang/String:length	()I
    //   1040: pop
    //   1041: ldc 3
    //   1043: invokevirtual 154	java/lang/String:length	()I
    //   1046: ifge +52 -> 1098
    //   1049: return
    //   1050: ldc 1
    //   1052: invokevirtual 154	java/lang/String:length	()I
    //   1055: pop2
    //   1056: aload_1
    //   1057: new 53	java/lang/StringBuffer
    //   1060: dup
    //   1061: ldc 14
    //   1063: invokespecial 156	java/lang/StringBuffer:<init>	(Ljava/lang/String;)V
    //   1066: aload 9
    //   1068: invokevirtual 158	java/lang/StringBuffer:append	(Ljava/lang/String;)Ljava/lang/StringBuffer;
    //   1071: ldc 10
    //   1073: invokevirtual 158	java/lang/StringBuffer:append	(Ljava/lang/String;)Ljava/lang/StringBuffer;
    //   1076: invokevirtual 159	java/lang/StringBuffer:toString	()Ljava/lang/String;
    //   1079: invokestatic 142	dn:d	(Ljava/lang/String;Ljava/lang/String;)V
    //   1082: ldc 1
    //   1084: invokevirtual 154	java/lang/String:length	()I
    //   1087: pop
    //   1088: ldc 2
    //   1090: invokevirtual 154	java/lang/String:length	()I
    //   1093: ineg
    //   1094: iflt +267 -> 1361
    //   1097: return
    //   1098: aload 10
    //   1100: invokevirtual 129	df:c	()I
    //   1103: iload 11
    //   1105: invokestatic 182	x:e	(II)Z
    //   1108: ifeq +47 -> 1155
    //   1111: aload_1
    //   1112: new 53	java/lang/StringBuffer
    //   1115: dup
    //   1116: ldc 14
    //   1118: invokespecial 156	java/lang/StringBuffer:<init>	(Ljava/lang/String;)V
    //   1121: aload 9
    //   1123: invokevirtual 158	java/lang/StringBuffer:append	(Ljava/lang/String;)Ljava/lang/StringBuffer;
    //   1126: ldc 9
    //   1128: invokevirtual 158	java/lang/StringBuffer:append	(Ljava/lang/String;)Ljava/lang/StringBuffer;
    //   1131: invokevirtual 159	java/lang/StringBuffer:toString	()Ljava/lang/String;
    //   1134: invokestatic 142	dn:d	(Ljava/lang/String;Ljava/lang/String;)V
    //   1137: ldc 1
    //   1139: invokevirtual 154	java/lang/String:length	()I
    //   1142: pop
    //   1143: sipush 180
    //   1146: sipush 176
    //   1149: ixor
    //   1150: ineg
    //   1151: ifle +210 -> 1361
    //   1154: return
    //   1155: aload 10
    //   1157: getfield 85	df:i	Lat;
    //   1160: getfield 78	at:c	Z
    //   1163: invokestatic 187	x:g	(I)Z
    //   1166: ifeq +29 -> 1195
    //   1169: getstatic 109	x:ad	[I
    //   1172: iconst_0
    //   1173: iaload
    //   1174: ldc 1
    //   1176: invokevirtual 154	java/lang/String:length	()I
    //   1179: pop
    //   1180: ldc 2
    //   1182: invokevirtual 154	java/lang/String:length	()I
    //   1185: ineg
    //   1186: ldc 4
    //   1188: invokevirtual 154	java/lang/String:length	()I
    //   1191: if_icmplt +6 -> 1197
    //   1194: return
    //   1195: iload 11
    //   1197: istore 12
    //   1199: iload 5
    //   1201: iload 12
    //   1203: iadd
    //   1204: getstatic 109	x:ad	[I
    //   1207: iconst_2
    //   1208: iaload
    //   1209: invokestatic 177	x:c	(II)Z
    //   1212: ifeq +60 -> 1272
    //   1215: aload_1
    //   1216: new 53	java/lang/StringBuffer
    //   1219: dup
    //   1220: ldc 14
    //   1222: invokespecial 156	java/lang/StringBuffer:<init>	(Ljava/lang/String;)V
    //   1225: aload 9
    //   1227: invokevirtual 158	java/lang/StringBuffer:append	(Ljava/lang/String;)Ljava/lang/StringBuffer;
    //   1230: ldc 11
    //   1232: invokevirtual 158	java/lang/StringBuffer:append	(Ljava/lang/String;)Ljava/lang/StringBuffer;
    //   1235: invokevirtual 159	java/lang/StringBuffer:toString	()Ljava/lang/String;
    //   1238: invokestatic 142	dn:d	(Ljava/lang/String;Ljava/lang/String;)V
    //   1241: ldc 1
    //   1243: invokevirtual 154	java/lang/String:length	()I
    //   1246: pop
    //   1247: ldc 2
    //   1249: invokevirtual 154	java/lang/String:length	()I
    //   1252: ineg
    //   1253: bipush 60
    //   1255: bipush 58
    //   1257: ixor
    //   1258: sipush 166
    //   1261: sipush 160
    //   1264: ixor
    //   1265: iconst_m1
    //   1266: ixor
    //   1267: iand
    //   1268: if_icmplt +135 -> 1403
    //   1271: return
    //   1272: iload 5
    //   1274: iload 12
    //   1276: iadd
    //   1277: istore 5
    //   1279: aload_3
    //   1280: aload 10
    //   1282: invokevirtual 124	ci:addElement	(Ljava/lang/Object;)V
    //   1285: aload 4
    //   1287: new 50	java/lang/Integer
    //   1290: dup
    //   1291: iload 11
    //   1293: invokespecial 150	java/lang/Integer:<init>	(I)V
    //   1296: invokevirtual 124	ci:addElement	(Ljava/lang/Object;)V
    //   1299: ldc 1
    //   1301: invokevirtual 154	java/lang/String:length	()I
    //   1304: pop
    //   1305: bipush 49
    //   1307: bipush 124
    //   1309: ixor
    //   1310: bipush 82
    //   1312: bipush 31
    //   1314: ixor
    //   1315: iconst_m1
    //   1316: ixor
    //   1317: iand
    //   1318: bipush 102
    //   1320: bipush 66
    //   1322: ixor
    //   1323: bipush 93
    //   1325: bipush 121
    //   1327: ixor
    //   1328: iconst_m1
    //   1329: ixor
    //   1330: iand
    //   1331: if_icmple +30 -> 1361
    //   1334: return
    //   1335: aload_1
    //   1336: new 53	java/lang/StringBuffer
    //   1339: dup
    //   1340: ldc 14
    //   1342: invokespecial 156	java/lang/StringBuffer:<init>	(Ljava/lang/String;)V
    //   1345: aload 9
    //   1347: invokevirtual 158	java/lang/StringBuffer:append	(Ljava/lang/String;)Ljava/lang/StringBuffer;
    //   1350: ldc 8
    //   1352: invokevirtual 158	java/lang/StringBuffer:append	(Ljava/lang/String;)Ljava/lang/StringBuffer;
    //   1355: invokevirtual 159	java/lang/StringBuffer:toString	()Ljava/lang/String;
    //   1358: invokestatic 142	dn:d	(Ljava/lang/String;Ljava/lang/String;)V
    //   1361: iinc 6 2
    //   1364: ldc 1
    //   1366: invokevirtual 154	java/lang/String:length	()I
    //   1369: pop
    //   1370: bipush 20
    //   1372: bipush 110
    //   1374: iadd
    //   1375: bipush 7
    //   1377: isub
    //   1378: bipush 51
    //   1380: iadd
    //   1381: bipush 47
    //   1383: bipush 100
    //   1385: iadd
    //   1386: bipush 112
    //   1388: isub
    //   1389: sipush 135
    //   1392: iadd
    //   1393: ixor
    //   1394: ldc 2
    //   1396: invokevirtual 154	java/lang/String:length	()I
    //   1399: if_icmpgt -503 -> 896
    //   1402: return
    //   1403: aload_3
    //   1404: invokevirtual 166	java/util/Vector:size	()I
    //   1407: invokestatic 179	x:d	(I)Z
    //   1410: ifeq +10 -> 1420
    //   1413: aload_1
    //   1414: ldc 19
    //   1416: invokestatic 142	dn:d	(Ljava/lang/String;Ljava/lang/String;)V
    //   1419: return
    //   1420: aload_0
    //   1421: aload_1
    //   1422: putfield 114	x:x	Ljava/lang/String;
    //   1425: aload_0
    //   1426: getstatic 109	x:ad	[I
    //   1429: iconst_1
    //   1430: iaload
    //   1431: putfield 116	x:z	Z
    //   1434: aload_0
    //   1435: aload_3
    //   1436: putfield 107	x:ab	Lci;
    //   1439: aload_0
    //   1440: aload 4
    //   1442: putfield 110	x:ae	Lci;
    //   1445: aload_0
    //   1446: getstatic 109	x:ad	[I
    //   1449: iconst_0
    //   1450: iaload
    //   1451: putfield 113	x:w	Z
    //   1454: return
    // Local variable table:
    //   start	length	slot	name	signature
    //   0	1455	0	this	x
    //   0	1455	1	paramString1	String
    //   0	1455	2	paramString2	String
    //   61	1375	3	localci1	ci
    //   69	1372	4	localci2	ci
    //   76	1202	5	i	int
    //   83	1279	6	j	int
    //   93	806	7	k	int
    //   109	920	8	str1	String
    //   121	1225	9	str2	String
    //   129	1152	10	localdf	df
    //   232	1060	11	m	int
    //   415	862	12	n	int
    //   255	1	13	localException1	Exception
    //   1050	1	14	localException2	Exception
    // Exception table:
    //   from	to	target	type
    //   227	234	255	java/lang/Exception
    //   1028	1035	1050	java/lang/Exception
  }
  
  private static int a(long paramLong1, long paramLong2)
  {
    return paramLong1 < paramLong2;
  }
  
  private static void p()
  {
    ad = new int[6];
    ad[0] = " ".length();
    ad[1] = ((0x64 ^ 0xF ^ 0x3 ^ 0x6E) & (110 + 104 - 154 + 97 ^ 4 + 49 - -62 + 40 ^ -" ".length()));
    ad[2] = (0x9F ^ 0xBA ^ 0x89 ^ 0xA0);
    ad[3] = (-" ".length());
    ad[4] = (0xCBED & 0x37FA);
    ad[5] = "  ".length();
  }
  
  private static boolean c(int paramInt1, int paramInt2)
  {
    return paramInt1 > paramInt2;
  }
  
  public final String toString()
  {
    return "Auto Sell";
  }
  
  public final void b()
  {
    if (g(r.k()))
    {
      r.a(ad[0]);
      return;
    }
    if ((d(this.d, et.o)) && (d(this.f, et.b)))
    {
      if (d(this.w))
      {
        if ((!d(dt.g().eg, this.af)) || (g(dt.g().ey, this.aa))) {
          try
          {
            "".length();
            Thread.sleep(500L);
            "".length();
            if (" ".length() <= 0) {
              return;
            }
          }
          catch (InterruptedException localInterruptedException2)
          {
            (localObject2 = localInterruptedException2).printStackTrace();
          }
        }
        if ((h(a(System.currentTimeMillis() - this.y, 5000L))) && (d((localObject1 = aj.a()).equals(""))))
        {
          dl.ae().q((String)localObject1);
          this.y = System.currentTimeMillis();
        }
        return;
      }
      Object localObject1 = this.x;
      int i = ad[1];
      while (e(i, fn.ep.size()))
      {
        if (g((localObject2 = (dt)fn.ep.elementAt(i)).ci.equals(localObject1)))
        {
          localObject1 = localObject2;
          "".length();
          if (null == null) {
            break label263;
          }
          return;
        }
        i++;
        "".length();
        if (-"   ".length() > 0) {
          return;
        }
      }
      localObject1 = null;
      label263:
      Object localObject2 = localObject1;
      if (b(localObject1))
      {
        if (a(this.x)) {
          dn.d(this.x, "<Hãy đến " + et.ag[et.o] + " khu " + et.b + " để giao dịch>");
        }
        this.w = ad[1];
        "".length();
        if ("   ".length() >= 0) {}
      }
      else
      {
        try
        {
          if (g(this.z))
          {
            f((dt)localObject2);
            "".length();
            if (((0x1F ^ 0x22) & (0xBC ^ 0x81 ^ 0xFFFFFFFF) & ((0x5D ^ 0x7C) & (0x22 ^ 0x3 ^ 0xFFFFFFFF) ^ 0xFFFFFFFF)) != (0x9F ^ 0x9B)) {}
          }
          else
          {
            e((dt)localObject2);
          }
          Thread.sleep(500L);
          this.w = ad[1];
          "".length();
          if ((0xA3 ^ 0xA7) >= 0) {
            return;
          }
          return;
        }
        catch (InterruptedException localInterruptedException3)
        {
          InterruptedException localInterruptedException1;
          (localInterruptedException1 = localInterruptedException3).printStackTrace();
          return;
        }
      }
    }
    else
    {
      a(this.d, this.f, ad[3], ad[3]);
    }
  }
  
  public final void a()
  {
    super.a();
    this.d = et.o;
    this.f = et.b;
    this.af = dt.g().eg;
    this.aa = dt.g().ey;
    this.y = 0L;
    this.w = ad[1];
    aj.a = ad[3];
  }
  
  private static boolean d(int paramInt)
  {
    return paramInt == 0;
  }
  
  private static boolean d(int paramInt1, int paramInt2)
  {
    return paramInt1 == paramInt2;
  }
  
  private static boolean e(int paramInt)
  {
    return paramInt > 0;
  }
  
  private static boolean f(int paramInt)
  {
    return paramInt < 0;
  }
  
  private static boolean g(int paramInt)
  {
    return paramInt != 0;
  }
  
  private static boolean a(Object paramObject)
  {
    return paramObject != null;
  }
  
  private static boolean e(int paramInt1, int paramInt2)
  {
    return paramInt1 < paramInt2;
  }
  
  private static int b(long paramLong1, long paramLong2)
  {
    return paramLong1 < paramLong2;
  }
  
  private static int c(long paramLong1, long paramLong2)
  {
    return paramLong1 < paramLong2;
  }
  
  private static boolean b(Object paramObject)
  {
    return paramObject == null;
  }
  
  private void e(dt paramdt)
  {
    ao[] arrayOfao = new ao[ad[2]];
    int i = ad[1];
    int j = ad[1];
    int k = ad[1];
    int m;
    Object localObject1;
    int n;
    if (a(this.ab))
    {
      m = ad[1];
      while (e(m, this.ab.size()))
      {
        localObject1 = (df)this.ab.elementAt(m);
        n = ((Integer)this.ae.elementAt(m)).intValue();
        Object localObject2;
        if (g(((df)localObject1).i.c))
        {
          if (b(localObject2 = dt.g(((df)localObject1).i.f)))
          {
            dn.d(this.x, "<Xin lỗi, có lỗi chọn item>");
            return;
          }
          dl.ae().j(((ao)localObject2).n, n);
          "".length();
          if (b(localObject2 = dt.d(((df)localObject1).i.f, n)))
          {
            dn.d(this.x, "<Xin lỗi, có lỗi chọn item>");
            return;
          }
          arrayOfao[(i++)] = localObject2;
          k = ad[0];
          "".length();
          if (-" ".length() <= 0) {}
        }
        else
        {
          localObject2 = dt.g();
          int i2 = ad[1];
          if (e(n))
          {
            while (e(i2, ((dt)localObject2).w.length))
            {
              if ((a(paramdt = localObject2.w[i2])) && (d(paramdt.j.f, ((df)localObject1).i.f))) {
                arrayOfao[(i++)] = paramdt;
              }
              i2++;
              "".length();
              if (-" ".length() > 0) {
                return;
              }
            }
            dn.d(this.x, "<Xin lỗi, có lỗi chọn item>");
            return;
          }
        }
        j += n * ((df)localObject1).j * ad[4] / ((df)localObject1).b;
        "".length();
        if ("  ".length() == 0) {
          return;
        }
      }
      if (d(j)) {
        j = ad[0];
      }
    }
    v = ad[1];
    if (d(dt.e(paramdt.eg, paramdt.ey)))
    {
      dn.d(;;
      if (g(k))
      {
        dl.ae().y();
        "".length();
      }
    }
    else
    {
      dl.ae().aq(paramdt.fy);
      if (d(cn.g()))
      {
        if (g(fn.x)) {
          try
          {
            dl.ae().aa();
            Thread.sleep(1000L);
            "".length();
            if ("   ".length() == 0) {
              return;
            }
          }
          catch (InterruptedException localInterruptedException2)
          {
            (localObject1 = localInterruptedException2).printStackTrace();
          }
        }
        if (g(k))
        {
          dl.ae().y();
          "".length();
        }
        dn.d(this.x, "<Hãy đồng ý giao dịch>");
        return;
      }
      fn.j().fq = ad[1];
      fn.cr = new ao[ad[2]];
      m = ad[1];
      while (e(m, ad[2]))
      {
        fn.cr[m] = arrayOfao[m];
        if ((a(arrayOfao[m])) && (h(arrayOfao[m].n)) && (e(arrayOfao[m].n, dt.g().w.length)))
        {
          int i1 = arrayOfao[m].n;
          dt.g().w[i1] = null;
        }
        m++;
        "".length();
        if (-" ".length() >= "  ".length()) {
          return;
        }
      }
      dl.ae().a(ad[1], (ao[])arrayOfao);
      fn.j().ee = ad[0];
      long l = System.currentTimeMillis();
      InterruptedException localInterruptedException1;
      while (g(fn.j().ao, ad[0]))
      {
        try
        {
          if ((!d(v)) || (h(c(System.currentTimeMillis() - l, 20000L))))
          {
            if (g(fn.x)) {
              try
              {
                dl.ae().aa();
                Thread.sleep(1000L);
                "".length();
                if (" ".length() <= -" ".length()) {
                  return;
                }
              }
              catch (InterruptedException localInterruptedException3)
              {
                (localInterruptedException1 = localInterruptedException3).printStackTrace();
              }
            }
            if (g(k))
            {
              dl.ae().y();
              "".length();
            }
            dn.d(this.x, "<Hãy giao dịch lại>");
            return;
          }
          Thread.sleep(200L);
          "".length();
          if (null == null) {
            continue;
          }
          return;
        }
        catch (InterruptedException localInterruptedException4)
        {
          (localInterruptedException1 = localInterruptedException4).printStackTrace();
          "".length();
        }
        if (-" ".length() >= 0) {
          return;
        }
      }
      l = System.currentTimeMillis();
      if (e(fn.j().bi, j))
      {
        if (g(fn.x)) {
          try
          {
            dl.ae().aa();
            Thread.sleep(1000L);
            "".length();
            if (-" ".length() != -" ".length()) {
              return;
            }
          }
          catch (InterruptedException localInterruptedException5)
          {
            (localInterruptedException1 = localInterruptedException5).printStackTrace();
          }
        }
        if (g(k))
        {
          dl.ae().y();
          "".length();
        }
        dn.d(this.x, "<Không đủ xu>");
        return;
      }
      n = ad[1];
      while (e(n, fn.cv.length))
      {
        if ((a(fn.cv[n])) && (b(aj.a(fn.cv[n].j.f))))
        {
          if (g(fn.x)) {
            try
            {
              dl.ae().aa();
              Thread.sleep(1000L);
              "".length();
              if (-" ".length() > 0) {
                return;
              }
            }
            catch (InterruptedException localInterruptedException6)
            {
              (localInterruptedException1 = localInterruptedException6).printStackTrace();
            }
          }
          if (g(k))
          {
            dl.ae().y();
            "".length();
          }
          dn.d(this.x, "<Chỉ GD xu>");
          return;
        }
        n++;
        "".length();
        if (" ".length() == 0) {
          return;
        }
      }
      while (f(c(System.currentTimeMillis() - l, 6000L)))
      {
        try
        {
          if (g(v))
          {
            if (g(k))
            {
              dl.ae().y();
              "".length();
            }
            dn.d(this.x, "<Hãy giao dịch lại>");
            return;
          }
          Thread.sleep(200L);
          "".length();
          if ((0x78 ^ 0x7D) > 0) {
            continue;
          }
          return;
        }
        catch (InterruptedException localInterruptedException7)
        {
          (localInterruptedException1 = localInterruptedException7).printStackTrace();
          "".length();
        }
        if (-"  ".length() > 0) {
          return;
        }
      }
      dl.ae().o();
      fn.j().ee = ad[5];
      while (e(fn.j().ao, ad[5]))
      {
        try
        {
          if ((!d(v)) || (h(c(System.currentTimeMillis() - l, 20000L))))
          {
            if (g(fn.x))
            {
              dl.ae().aa();
              Thread.sleep(1000L);
            }
            if (g(k))
            {
              dl.ae().y();
              "".length();
            }
            dn.d(this.x, "<Hãy giao dịch lại>");
            return;
          }
          Thread.sleep(200L);
          "".length();
          if (((0xC4 ^ 0x81) & (0xC6 ^ 0x83 ^ 0xFFFFFFFF)) == 0) {
            continue;
          }
          return;
        }
        catch (InterruptedException localInterruptedException8)
        {
          (localInterruptedException1 = localInterruptedException8).printStackTrace();
          "".length();
        }
        if (" ".length() <= 0) {}
      }
    }
  }
  
  public final void a(String paramString, int paramInt)
  {
    if (g(aj.d()))
    {
      dl.ae().al(paramInt);
      this.x = paramString;
      this.z = ad[0];
      this.ac = ad[0];
      this.ab = null;
      this.ae = null;
      this.w = ad[0];
      return;
    }
    dl.ae().p();
    dn.d(paramString, "<Hiện mk ko mua vp nào>");
  }
  
  private static boolean h(int paramInt)
  {
    return paramInt >= 0;
  }
  
  public static void c() {}
  
  static
  {
    cs.a(138);
    c();
  }
  
  private static boolean f(int paramInt1, int paramInt2)
  {
    return paramInt1 <= paramInt2;
  }
  
  private void f(dt paramdt)
  {
    ao[] arrayOfao = new ao[ad[2]];
    v = ad[1];
    if (d(this.ac))
    {
      if (d(dt.e(paramdt.eg, paramdt.ey)))
      {
        dn.d(this.x, "<Hãy đứng ở nơi dễ GD>");
        return;
      }
      dl.ae().aq(paramdt.fy);
      if (d(cn.g()))
      {
        if (g(fn.x)) {
          try
          {
            dl.ae().aa();
            Thread.sleep(1000L);
            "".length();
            if (null != null) {
              return;
            }
          }
          catch (InterruptedException localInterruptedException1)
          {
            (paramdt = localInterruptedException1).printStackTrace();
          }
        }
        dn.d(this.x, "<Hãy đồng ý giao dịch>");
      }
    }
    else
    {
      l1 = System.currentTimeMillis();
      while ((!g(fn.x)) || (h(b(System.currentTimeMillis() - l1, 10000L))))
      {
        try
        {
          Thread.sleep(1000L);
          "".length();
          if (-"  ".length() < 0) {
            continue;
          }
          return;
        }
        catch (InterruptedException localInterruptedException2)
        {
          (paramdt = localInterruptedException2).printStackTrace();
          "".length();
        }
        if (null != null) {
          return;
        }
      }
    }
    long l1 = System.currentTimeMillis();
    while (g(fn.j().ao, ad[0]))
    {
      try
      {
        if ((!d(v)) || (h(b(System.currentTimeMillis() - l1, 20000L))))
        {
          if (g(fn.x))
          {
            dl.ae().aa();
            Thread.sleep(1000L);
          }
          dn.d(this.x, "<Hãy giao dịch lại>");
          return;
        }
        Thread.sleep(200L);
        "".length();
        if ((0x16 ^ 0x72 ^ 0xD9 ^ 0xB9) >= 0) {
          continue;
        }
        return;
      }
      catch (InterruptedException localInterruptedException3)
      {
        (paramdt = localInterruptedException3).printStackTrace();
        "".length();
      }
      if ((0x6F ^ 0x6B) < "  ".length()) {
        return;
      }
    }
    paramdt = new ci();
    ci localci = new ci();
    int i = ad[1];
    df localdf;
    label540:
    int j;
    while (e(i, fn.cv.length))
    {
      if (a(fn.cv[i]))
      {
        if ((!a(localdf = aj.a(fn.cv[i].j.f))) || (d(localdf.e())))
        {
          if (g(fn.x)) {
            try
            {
              dl.ae().aa();
              Thread.sleep(1000L);
              "".length();
              if ((0xB9 ^ 0xB5 ^ 0x73 ^ 0x7B) <= "   ".length()) {
                return;
              }
            }
            catch (InterruptedException localInterruptedException4)
            {
              (paramdt = localInterruptedException4).printStackTrace();
            }
          }
          dn.d(this.x, "<Item " + i + ": bạn đã GD vp mk ko mua>");
          return;
        }
        if (g(fn.cv[i].j.c))
        {
          "".length();
          if ((0xA5 ^ 0x8E ^ 0x1 ^ 0x2E) != 0) {
            break label540;
          }
        }
        k = ad[0];
        if (g(paramdt.contains(localdf)))
        {
          j = paramdt.indexOf(localdf);
          k += ((Integer)localci.elementAt(j)).intValue();
          localci.setElementAt(new Integer(k), j);
          "".length();
          if (((0xA ^ 0x55 ^ 0x45 ^ 0x5E) & (0x7 ^ 0x56 ^ 0x7B ^ 0x6E ^ -" ".length())) == 0) {}
        }
        else
        {
          paramdt.addElement(localdf);
          localci.addElement(new Integer(k));
        }
      }
      i++;
      "".length();
      if (null != null) {
        return;
      }
    }
    if (d(paramdt.size()))
    {
      if (g(fn.x)) {
        try
        {
          dl.ae().aa();
          Thread.sleep(1000L);
          "".length();
          if (-" ".length() >= ((0x9E ^ 0xBB ^ 0x82 ^ 0xBF) & (0x73 ^ 0x5D ^ 0x1 ^ 0x37 ^ -" ".length()))) {
            return;
          }
        }
        catch (InterruptedException localInterruptedException5)
        {
          (paramdt = localInterruptedException5).printStackTrace();
        }
      }
      dn.d(this.x, "<Giao dịch trống>");
      return;
    }
    i = ad[1];
    int k = ad[1];
    while (e(k, paramdt.size()))
    {
      localdf = (df)paramdt.elementAt(k);
      j = ((Integer)localci.elementAt(k)).intValue();
      if (c(dt.b(localdf.i.f) + j, localdf.d))
      {
        if (g(fn.x)) {
          try
          {
            dl.ae().aa();
            Thread.sleep(1000L);
            "".length();
            if (" ".length() >= "   ".length()) {
              return;
            }
          }
          catch (InterruptedException localInterruptedException6)
          {
            (paramdt = localInterruptedException6).printStackTrace();
          }
        }
        dn.d(this.x, "<" + localdf.i.a + " bạn đá bán quá số mk cần mua>");
        return;
      }
      i += j * localdf.a * ad[4] / localdf.h;
      "".length();
      if (-" ".length() > " ".length()) {
        return;
      }
    }
    if (c(i, dt.g().a))
    {
      if (g(fn.x)) {
        dl.ae().aa();
      }
      dn.d(this.x, "<Hiện mk ko đủ xu, xin bạn quay lại sau>");
      return;
    }
    fn.j().fq = i;
    fn.cr = arrayOfao;
    dl.ae().a(i, arrayOfao);
    fn.j().ee = ad[0];
    long l2 = System.currentTimeMillis();
    while (f(b(System.currentTimeMillis() - l2, 5000L)))
    {
      try
      {
        if (g(v))
        {
          dn.d(this.x, "<Hãy giao dịch lại>");
          return;
        }
        Thread.sleep(200L);
        "".length();
        if (-(0x8D ^ 0x92 ^ 0x64 ^ 0x7E) < 0) {
          continue;
        }
        return;
      }
      catch (InterruptedException localInterruptedException7)
      {
        (paramdt = localInterruptedException7).printStackTrace();
        "".length();
      }
      if (" ".length() >= "  ".length()) {
        return;
      }
    }
    dl.ae().o();
    fn.j().ee = ad[5];
    while (e(fn.j().fq, ad[5]))
    {
      try
      {
        if ((!d(v)) || (h(b(System.currentTimeMillis() - l2, 20000L))))
        {
          if (g(fn.x))
          {
            dl.ae().aa();
            Thread.sleep(1000L);
          }
          dn.d(this.x, "<Hãy giao dịch lại>");
          return;
        }
        Thread.sleep(200L);
        "".length();
        if (((0x4D ^ 0x7C) & (0xB3 ^ 0x82 ^ 0xFFFFFFFF)) == 0) {
          continue;
        }
        return;
      }
      catch (InterruptedException localInterruptedException8)
      {
        (paramdt = localInterruptedException8).printStackTrace();
        "".length();
      }
      if ("   ".length() < "   ".length()) {}
    }
  }
  
  private static boolean g(int paramInt1, int paramInt2)
  {
    return paramInt1 != paramInt2;
  }
  
  public static void d() {}
}


/* Location:              C:\Users\Admin\OneDrive\Documents\NSOv2_test.jar!\x.class
 * Java compiler version: 1 (45.3)
 * JD-Core Version:       0.7.1
 */